Workbook

Sheet Mode d'emploi
B1: CorpusImmo · www.corpus.immo · Estimer, comparer, décider. Sur les ventes réelles.
B2: Mode d'emploi
B3: À quoi sert ce classeur, dans quel ordre le remplir, et comment lire ce qu'il répond.
B6: À QUOI SERT CE CLASSEUR
B7: Vous devez donner un prix à un logement, et le défendre. Ce classeur répond à la question que se pose tout professionnel avant de remettre un avis de valeur : combien vaut ce bien, au vu des ventes réellement signées autour de lui, et avec quelle marge d'incertitude ?
B8: Il calcule le prix au m² de chaque vente comparable, puis lui applique une grille d'ajustements : des corrections chiffrées qui rapprochent la vente du bien à évaluer (état, étage, extérieur, étiquette DPE, stationnement, écoulement du temps). Il pondère ensuite chaque comparable par sa ressemblance avec le bien, puis produit une valeur centrale et une fourchette dont la largeur est mesurée sur la dispersion du panel, c'est-à-dire sur l'écart qui sépare encore les ventes retenues une fois corrigées.
B9: Le classeur est livré rempli d'un exemple : un appartement de 75 m² et six ventes comparables. Pour votre dossier, remplacez les cellules violettes de l'onglet Avis de valeur. Celles du Référentiel sont vos coefficients : elles se recalent une fois par marché, jamais par dossier. L'étape 0 de la marche à suivre dit exactement lesquelles se vident, et lesquelles ne se vident jamais.
B10: Vous êtes | C10: Ce que le classeur vous donne
B11: Agent immobilier | C11: Une valeur et une fourchette défendables devant un vendeur, avec le détail des corrections appliquées à chaque vente comparable.
B12: Expert débutant | C12: La formalisation d'une pondération : ce qui se corrige, dans quel sens, de combien, et ce que vaut le panel une fois les corrections faites.
B13: Notaire | C13: Un avis de valeur documenté à partir de ventes signées, avec la mention écrite qu'exige une estimation allégée, c'est-à-dire une évaluation qui n'est pas une expertise au sens de la charte de l'expertise.
B14: Banquier, courtier | C14: Un ordre de grandeur du prix au m² du secteur et la dispersion des références, pour juger un prix d'acquisition présenté au dossier.
B15: Investisseur, marchand de biens | C15: Le prix au m² retenu et le plus bas des comparables ajustés, pour situer une offre.
B17: LE PRINCIPE, EN UNE LIGNE
B18: Prix au m² des ventes comparables, corrigé des différences, pondéré par la ressemblance, multiplié par la surface du bien, avec une fourchette aussi large que la dispersion des ventes retenues
B20: LES ONGLETS, DANS L'ORDRE OÙ ON LES REMPLIT
B21: Onglet | C21: Ce que vous y faites | D21: Ce que vous y lisez
B22: Mode d'emploi | C22: Rien à saisir. Vous lisez ce guide. | D22: La marche à suivre et l'exemple guidé.
B23: Avis de valeur | C23: Vous décrivez le bien, puis vous saisissez une ligne par vente comparable. | D23: Le statut de chaque ligne, le prix au m² retenu, la dispersion du panel, la valeur centrale et la fourchette.
B24: Référentiel | C24: Une fois par marché, vous recalez les coefficients sur votre secteur et vous datez votre vérification. | D24: Chaque coefficient avec sa source, sa fréquence de mise à jour et son ordre de grandeur.
B25: Méthode | C25: Rien à saisir. | D25: Les conventions de calcul et ce qu'elles coûtent, ce que le modèle ne fait pas, les sources.
B27: LE CODE COULEUR, ET COMMENT DÉVERROUILLER UNE CELLULE
B28: Cellule | C28: Ce que c'est | D28: Ce que vous faites
B29: Fond violet clair, texte violet sombre | C29: Saisie utilisateur | D29: Vous la remplissez. Jamais de formule dedans.
B30: Fond blanc | C30: Calcul | D30: Vous la lisez. Elle est verrouillée.
B31: Fond presque blanc, texte violet sombre en gras | C31: Résultat, chiffre clé | D31: Vous la lisez. C'est un chiffre à retenir.
B32: Bandeau violet | C32: Titre de section ou en-tête de tableau | D32: Repère de navigation.
B33: Texte gris, à droite | C33: Commentaire d'aide | D33: Une phrase par ligne. Les ordres de grandeur y renvoient au Référentiel.
B34: Texte sans fond, dans le Référentiel | C34: Libellé de liste ou de statut | D34: Vous le lisez. Il est verrouillé, parce que les formules testent son texte : pour le modifier, ôtez d'abord la protection de la feuille.
B35: Cellule violette qui affiche un % | C35: Coefficient | D35: Tapez le nombre tel qu'il se lit (6 pour 6 %), puis vérifiez l'affichage.
B36: Vert OK / rouge À CORRIGER | C36: Contrôle de cohérence | D36: Rouge : la ligne juste au-dessus nomme ce qui manque. Les deux se lisent en Avis de valeur!C19 pour le bien et en Avis de valeur!C38 pour les comparables.
B37: Vert OK / rouge À VÉRIFIER | C37: Contrôle de cohérence des prix | D37: Rouge (Avis de valeur!C42) : un prix saisi s'écarte fortement du panel. Rien n'est bloqué, mais Avis de valeur!C41 nomme la ligne à revoir. Vide : aucune ligne exploitable, le contrôle est sans objet.
B38: Vert OK / rouge À JUSTIFIER | C38: Contrôle de dispersion | D38: Rouge (Avis de valeur!C53) : la dispersion de votre panel dépasse le seuil du Référentiel, ou l'échantillon est trop petit pour la mesurer. La fourchette reste juste, mais elle est large. Resserrez la sélection, ou écrivez au dossier pourquoi ces ventes sont les seules disponibles.
B39: Les onglets sont protégés sans mot de passe pour éviter d'écraser une formule par erreur. En usage normal vous n'en avez jamais besoin : toutes les cellules violettes sont déjà libres. Pour modifier une cellule blanche ou un texte de source : onglet Révision, puis « Ôter la protection de la feuille ». Aucun mot de passe n'est demandé.
B41: LA MARCHE À SUIVRE, ÉTAPE PAR ÉTAPE
B42: Étape | C42: Où (onglet et plage) | D42: Ce que vous faites | E42: Pourquoi
B43: 0. L'exemple livré | C43: Avis de valeur!C8:C17 et Avis de valeur!B23:K30 | D43: Le classeur arrive rempli d'un exemple : un appartement et six ventes. Effacez les cellules violettes du bien (Avis de valeur!C8:C17) et celles du tableau des comparables (Avis de valeur!B23:K30, soit les 6 lignes de l'exemple et les 2 lignes libres) avant de saisir votre dossier, ou gardez l'exemple pour vous repérer et travaillez à côté. Ne videz jamais les cellules du Référentiel : ce sont vos coefficients, pas des données de dossier. Vérifiez surtout les saisies d'option qui n'ont pas de raison d'être dans votre cas : extérieur (Avis de valeur!C13), stationnement (Avis de valeur!C15), ascenseur (Avis de valeur!C16), et la date de l'avis (Avis de valeur!C17), qui reste souvent celle de l'exemple. Pour supprimer une ligne de comparable, videz la ligne entière de la colonne B à la colonne K : tant qu'une seule cellule violette y reste remplie, la ligne compte comme renseignée et bloque le calcul. | E43: Une valeur de l'exemple oubliée est l'erreur la plus probable d'un premier usage. Pendant que vous effacez, puis pendant que vous saisissez, les contrôles restent rouges et la valeur centrale affiche successivement Bien incomplet, Trop peu de comparables, puis Lignes à compléter : c'est normal, le classeur ne conclut qu'une fois la saisie complète, et il préfère nommer ce qui manque plutôt qu'afficher un chiffre qu'il ne tient pas. Une date d'avis restée au 16/08/2026 fera rejeter toutes vos ventes plus récentes, qui passeront à compléter, et le classeur refusera de conclure.
B44: 1. Le bien | C44: Avis de valeur!C8:C17 | D44: Adresse, type de bien, surface habitable au sens de la loi Boutin, état choisi dans la liste, étage, extérieur, étiquette DPE choisie dans la liste, stationnement, ascenseur, date de l'avis. Vérifiez que le contrôle en Avis de valeur!C19 affiche OK. | E44: Sans les caractéristiques du bien, aucun comparable ne peut être corrigé : le classeur met alors toutes les lignes à compléter plutôt que de calculer sans ajustement. L'ascenseur (Avis de valeur!C16) ne se saisit que pour le bien et vaut pour tous les comparables : sans ascenseur, un étage élevé devient une décote au lieu d'une prime. Un comparable situé dans un immeuble sans ascenseur alors que le bien en a un ne se corrige pas, il s'écarte. Le type de bien (Avis de valeur!C9) choisit la colonne de la grille de valeur verte : les écarts de prix entre étiquettes DPE sont environ deux fois plus forts sur une maison que sur un appartement.
B45: 2. Les ventes comparables | C45: Avis de valeur!B23:K30 | D45: Une ligne par vente, 8 au maximum. Adresse, date de vente en vraie date, prix net vendeur, surface habitable, puis les mêmes caractéristiques que pour le bien, puis la similarité de 0 à 100. Le prix net vendeur est le prix porté à l'acte, hors droits de mutation et hors honoraires d'agence : c'est celui que donne la base DVF. | E45: La similarité est le seul endroit où votre jugement entre. C'est assumé : aucun algorithme ne sait qu'une des deux ventes s'est faite entre voisins. Si vous avez plus de 8 ventes, gardez les 8 plus ressemblantes : ce n'est pas le nombre qui fait la qualité du panel. Et graduez, 8 lignes toutes à 100 valent moins que 5 lignes notées honnêtement.
B46: 3. Le statut de chaque ligne | C46: Avis de valeur!P23:P30 | D46: Rien à saisir. Lisez la colonne Statut ligne par ligne, puis les compteurs Avis de valeur!C35 et Avis de valeur!C36. Une ligne « À compléter » bloque tout : le classeur refuse de produire une valeur tant qu'elle est là, et Avis de valeur!C37 vous nomme la ligne et le champ en cause. Une ligne « Écarté » ne bloque rien : le calcul continue sans elle, mais votre panel a perdu une vente. | E46: C'est le garde-fou principal. Une ligne à compléter se corrige : complétez le champ nommé et le statut repasse à Retenu. Une ligne écartée se remplace : un ajustement au-delà du plafond veut dire que la vente n'est pas comparable, ou qu'une saisie est fausse, une étiquette DPE de travers suffit. Une vente trop ancienne se remplace par une plus récente. Si les comparables retenus tombent sous le minimum, cherchez d'autres ventes : ne relevez le plafond du Référentiel que si vous êtes prêt à le justifier au dossier.
B47: 4. Le panel | C47: Avis de valeur!C33:C43 | D47: Rien à saisir. Vérifiez que Avis de valeur!C34 atteint le minimum du Référentiel, que le contrôle en Avis de valeur!C38 affiche OK, et que le poids du comparable dominant (Avis de valeur!C43) reste sous le plafond de Référentiel!C34. Avis de valeur!C35 et Avis de valeur!C36 vous disent d'un coup d'œil combien de lignes sont à compléter et combien sont écartées ; Avis de valeur!C37 nomme la première à compléter. Regardez enfin Avis de valeur!C42 : il compare les prix au m² saisis entre eux et nomme celui qui s'écarte du panel. | E47: Le nombre de lignes saisies ne veut rien dire. Seuls comptent les comparables réellement retenus. Le contrôle des prix, lui, ne bloque rien : il attrape une saisie manifestement fausse, un prix tapé en milliers ou la surface d'un autre bien.
B48: 5. La dispersion | C48: Avis de valeur!C46:C53 | D48: Rien à saisir. Regardez l'écart entre le plus bas (Avis de valeur!C47) et le plus haut (Avis de valeur!C48) des prix au m² ajustés, puis le coefficient de variation (Avis de valeur!C50), c'est-à-dire l'écart moyen des comparables au prix retenu exprimé en pourcentage de ce prix, et le contrôle d'homogénéité qui en découle (Avis de valeur!C53). Avis de valeur!C52 dit en une phrase sur quoi la largeur de votre fourchette est fondée. | E48: C'est ce qu'un expert regarde en premier pour juger la qualité d'un panel, et ce qui justifie la largeur de la fourchette. C'est le coefficient de variation qui décide, et lui seul : l'écart entre le plus bas et le plus haut est une lecture d'ambiance, pas un critère.
B49: 6. La valeur et la fourchette | C49: Avis de valeur!C56:C59 | D49: Rien à saisir. Présentez la ligne Avis de valeur!C59, jamais la valeur centrale seule, et lisez Avis de valeur!C52 : elle dit en une phrase sur quoi la largeur de votre fourchette est fondée. Si elle vous paraît trop large, la réponse n'est pas de la resserrer à la main : resserrez le panel, voir la troisième situation de la section « Trois façons de s'en servir ». | E49: Un prix unique devient immédiatement le plancher de la négociation dans la tête du vendeur, et le plafond dans celle de l'acquéreur. Une fourchette large n'est pas un aveu de faiblesse : c'est la dispersion réelle des ventes du secteur, mesurée. Dites la comme telle, en lisant le plus bas et le plus haut des prix au m² corrigés (Avis de valeur!C47 et Avis de valeur!C48) : sur ces ventes, les prix au m² corrigés vont de tant à tant, je ne vais pas vous annoncer une précision que le marché ne porte pas, et voici ce qui vous place en haut plutôt qu'en bas. Un confrère qui annonce une fourchette deux fois plus étroite sur les mêmes ventes annonce une précision qu'il n'a pas mesurée. Si le vendeur veut une fourchette plus serrée, la réponse professionnelle est d'aller chercher des ventes plus proches de son bien, pas de resserrer l'affichage.
B50: 7. Les coefficients | C50: Référentiel!C9, Référentiel!C13:D19, Référentiel!C23:C27 et Référentiel!C31:C43 | D50: Une fois par marché, pas une fois par dossier : comparez chaque valeur violette à sa source (colonne D, colonne F pour la grille DPE) et mettez à jour la date en Référentiel!C56. Les mentions « Vérifié le » suivent automatiquement. | E50: Un coefficient national appliqué à un marché local est la première critique qu'on vous fera. Un référentiel visible se discute ; un coefficient caché dans une formule se subit.
B52: EXEMPLE GUIDÉ
B53: Le fichier est livré avec un appartement de 75 m² au 2e étage avec ascenseur, en état « Bon », avec un extérieur, sans stationnement, étiquette DPE D, à évaluer au 16/08/2026. Il est accompagné de 6 ventes comparables, de 275 000 € à 372 000 €, pour des surfaces de 65 à 81 m².
B54: Prenez la première ligne, le 12 rue des Lilas : vendu 318 000 € pour 72 m², soit 4 417 € par m². Il est au 3e étage quand le bien est au 2e, et il a un stationnement que le bien n'a pas : son prix est tiré vers le bas de 5,2 %, ce qui le ramène à 4 189 € par m² (Avis de valeur!N23). Sa similarité de 85 devient son poids (Avis de valeur!O23).
B55: Les 6 lignes affichent « Retenu » (Avis de valeur!C34 : 6 comparables retenus, aucune ligne à compléter). Le comparable le plus corrigé est le 15 rue Pasteur, en état « À rénover » et classé F : 21,5 % d'ajustement, sous le plafond de 25 % du Référentiel. Le poids du comparable dominant ressort à 19,57 % (Avis de valeur!C43), sous le plafond de 40 % du Référentiel. Les prix au m² saisis se tiennent : le plus éloigné s'écarte de 4 % de leur moyenne (Avis de valeur!C40), bien sous le seuil de 35 % du Référentiel qui déclencherait une vérification.
B56: Le prix au m² retenu est de 4 362 € (Avis de valeur!C46), moyenne des 6 prix ajustés pondérée par la similarité. Ces 6 prix vont de 3 815 € à 5 140 € par m². Leur dispersion, c'est-à-dire l'écart moyen de chacun au prix retenu, vaut 455 € par m² (Avis de valeur!C49) : c'est l'écart type pondéré. Rapportée au prix retenu, elle fait 10,44 % (Avis de valeur!C50), et ce pourcentage s'appelle le coefficient de variation. C'est lui qui devient la demi-fourchette (Avis de valeur!C51), c'est-à-dire ce qu'on retranche puis ce qu'on ajoute à la valeur centrale, puisqu'il dépasse le plancher de 3 % du Référentiel.
B57: Résultat : une valeur centrale de 327 139 € (Avis de valeur!C56) et une fourchette de 292 999 € à 361 279 € (Avis de valeur!C59), soit 68 281 € d'amplitude, près de 21 % de la valeur centrale. Comment la lire : le contrôle Avis de valeur!C53 affiche OK, parce que la dispersion mesurée, 10,44 %, reste sous le seuil de 12 % du Référentiel (millésime 2026). Le panel tient, mais il n'est pas serré : entre le plus bas et le plus haut des comparables ajustés il y a près de 35 %, ce qui explique une fourchette de cette largeur. Une demi-fourchette forfaitaire, deux fois plus étroite, annoncerait une précision que ces 6 ventes ne portent pas : elle ne tiendrait pas devant un contradicteur.
B58: Essayez : effacez la surface du 27 rue Victor Hugo (Avis de valeur!E25). Le statut de la ligne passe à « À compléter : surface manquante », le contrôle Avis de valeur!C38 passe au rouge et Avis de valeur!C37, juste au-dessus, nomme le comparable et le champ en cause. Avis de valeur!C34 tombe à 5, et la valeur centrale affiche « Lignes à compléter » au lieu d'un chiffre. C'est le piège le plus coûteux de la méthode par comparaison : un comparable compté à zéro au lieu d'être exclu tirerait le prix au m² retenu de 19 % vers le bas, à 3 529 € par m², sans un mot.
B60: LES CHIFFRES À REGARDER, ET CE QU'ILS VALENT
B61: Indicateur | C61: Où | D61: Repère métier | E61: Ce qu'il dit vraiment
B62: Comparables retenus | C62: Avis de valeur!C34 | D62: Au moins 5, la convention du Référentiel (Référentiel!C33, millésime 2026). | E62: Le nombre de lignes qui entrent réellement dans la moyenne. Une ligne saisie mais incomplète n'en fait pas partie.
B63: Statut de la ligne | C63: Avis de valeur!P23:P30 | D63: Retenu, Écarté ou À compléter : rien d'autre ne doit s'y lire. | E63: Le seul endroit qui dit pourquoi un comparable ne pèse rien. À compléter bloque le calcul, écarté ne le bloque pas.
B64: Poids du comparable dominant | C64: Avis de valeur!C43 | D64: Sous 40 % (Référentiel!C34, millésime 2026). | E64: Au-delà, une seule vente fait la valeur : élargissez la recherche.
B65: Ajustement par ligne | C65: Avis de valeur!M23:M30 | D65: Au-delà de 15 % (Référentiel!C31, millésime 2026), le comparable est éloigné ; au-delà de 25 % (Référentiel!C32), il est écarté. | E65: La somme des corrections appliquées à la ligne. Un panel dont toutes les lignes dépassent le premier seuil n'est pas un panel.
B66: Prix au m² retenu | C66: Avis de valeur!C46 | D66: À confronter au prix médian du quartier (base DVF, chiffres des notaires). | E66: Le cœur du calcul. S'il s'écarte du médian du quartier, c'est la sélection des comparables qu'il faut revoir, pas le coefficient.
B67: Coefficient de variation | C67: Avis de valeur!C50 | D67: Alerte au-delà de 12 % (Référentiel!C39, millésime 2026). C'est l'écart moyen des comparables au prix retenu, exprimé en pourcentage de ce prix. | E67: La dispersion du panel une fois les corrections faites. C'est lui qui fixe la largeur de la fourchette, et lui seul qui décide si le panel tient.
B68: Fourchette | C68: Avis de valeur!C59 | D68: Sa largeur se mesure sur vos comparables, elle ne se décide pas. Plus le panel est resserré, plus elle l'est. | E68: C'est ce qui se présente au vendeur. Jamais la valeur centrale seule.
B69: Message à la place de la valeur | C69: Avis de valeur!C56 | D69: Quatre messages possibles, dans l'ordre où ils se corrigent. | E69: Bien incomplet : Avis de valeur!C18 nomme le champ manquant. Lignes à compléter : Avis de valeur!C37 nomme la ligne. Trop peu de comparables : il en faut au moins le minimum du Référentiel (Référentiel!C33), retenus et non pas saisis. Un comparable domine : une seule vente pèse plus que le plafond de Référentiel!C34, ajoutez des ventes ou baissez sa similarité. Le classeur préfère nommer son refus plutôt qu'afficher un chiffre qu'il ne tient pas.
B71: LES DONNÉES À METTRE À JOUR, OÙ ET POURQUOI
B72: Deux familles de données. Les coefficients du Référentiel décrivent un marché : ils changent avec lui, à date fixe, et se rafraîchissent depuis la source indiquée en face de chacun. Les données de l'onglet Avis de valeur décrivent un dossier : elles changent à chaque avis de valeur. L'architecture du classeur ne bouge pas quand les données bougent.
B73: Les chiffres cités dans ce guide portent le millésime 2026 : relisez-les à chaque mise à jour du Référentiel, en particulier les seuils cités dans le tableau ci-dessus (nombre minimal de comparables, poids maximal, seuil de signalement et plafond d'ajustement, seuil de dispersion, écart de prix signalé) et les ordres de grandeur de l'exemple guidé, qui sont recalculés sur le jeu de données livré.
B74: Paramètre | C74: Onglet et cellule | D74: Ce qu'il pilote | E74: Source à consulter, fréquence
B75: Dérive du marché sur un an | C75: Référentiel!C9 | D75: La correction d'ancienneté de chaque vente comparable, c'est-à-dire ce que le marché a bougé entre la vente et votre avis | E75: Indice Notaires INSEE de votre secteur, publication trimestrielle
B76: Valeur verte par étiquette DPE | C76: Référentiel!C13:D19 | D76: L'ajustement d'étiquette, appartement et maison séparément. La valeur verte est l'écart de prix mesuré entre deux étiquettes | E76: Bilan annuel des notaires sur la valeur verte, publication de fin d'année
B77: Coefficients d'état, d'étage, d'extérieur et de stationnement, et repère du prix affiché | C77: Référentiel!C23:C27 | D77: Toute la grille d'ajustements, et l'ordre de grandeur de ce que gonfle un prix saisi honoraires comprises | E77: Études de marché locales et chiffres des notaires, à recaler chaque année et à chaque changement de secteur
B78: Garde-fous du modèle | C78: Référentiel!C31:C40 | D78: Les verrous, l'ancienneté maximale, la largeur de la fourchette et les deux seuils de signalement | E78: Conventions du modèle et usage professionnel : stables, à relire une fois par an
B79: Bornes de saisie | C79: Référentiel!C41:C43 | D79: Les listes déroulantes, les validations et les statuts de ligne | E79: Sans objet : bornes techniques
B80: Listes déroulantes et libellés de statut | C80: Référentiel!B47:D53 | D80: Les listes de l'état et du DPE, et les trois libellés que les formules testent | E80: Cellules verrouillées, sans fond : ôtez la protection de la feuille pour les modifier, et relisez d'abord l'onglet Méthode, qui dit ce que leur ordre porte
B81: Date de dernière vérification | C81: Référentiel!C56 | D81: Toutes les mentions « Vérifié le » du Référentiel et de Méthode, et le millésime du titre | E81: À chaque recalage : une seule cellule à changer
B82: Le bien et les ventes comparables | C82: Avis de valeur!C8:C17 et Avis de valeur!B23:K30 | D82: Tout le reste | E82: Données de dossier, propres à chaque avis de valeur
B84: TROIS FAÇONS DE S'EN SERVIR
B85: Votre situation | C85: Ce que vous faites
B86: Vous préparez un rendez-vous vendeur | C86: Saisissez le bien et 5 à 8 ventes récentes. Imprimez l'onglet Avis de valeur en paysage, ajusté à une page en largeur : le vendeur y voit les ventes retenues, la correction appliquée à chacune, le statut de chaque ligne et la fourchette. Sachez qu'il y lira aussi la similarité que vous avez donnée à chaque vente, y compris à celle qu'il vous a apportée. C'est le référentiel qui se discute, pas votre honnêteté.
B87: Un vendeur conteste votre prix | C87: Ajoutez sa vente de référence comme comparable. Soit elle est retenue et vous voyez son effet sur Avis de valeur!C46, soit son statut dit pourquoi elle ne tient pas : ajustement au-delà du plafond, vente trop ancienne, ou saisie incomplète.
B88: Vous doutez de la largeur de votre fourchette | C88: Regardez d'abord Avis de valeur!C50, le coefficient de variation : c'est lui qui décide, et son seuil vit dans le Référentiel (Référentiel!C39). Regardez ensuite Avis de valeur!C47 et Avis de valeur!C48 : plus l'écart entre le plus bas et le plus haut est grand, plus votre panel mélange des situations différentes, même quand le contrôle reste vert. Resserrez la sélection (même quartier, surfaces proches, ventes récentes) et relisez Avis de valeur!C50. La fourchette se resserre d'elle-même quand le panel est homogène.
B90: LES ERREURS QUI FAUSSENT TOUT
B91: Le piège | C91: Le dégât
B92: Oublier la surface d'un comparable (Avis de valeur!E23:E30) | C92: L'erreur la plus coûteuse de la méthode : sans surface, il n'y a pas de prix au m², et un comparable compté à zéro au lieu d'être exclu tirerait la valeur de 19 % vers le bas sur le jeu d'exemple. Le classeur l'exclut, le nomme et refuse de conclure tant qu'il n'est pas complété.
B93: Laisser la date de l'avis de l'exemple (Avis de valeur!C17) | C93: Elle pilote deux choses. La dérive de marché, dont l'effet reste petit tant que le Référentiel porte une dérive faible (millésime 2026). Et surtout l'ancienneté de chaque vente : une vente signée après cette date passe à compléter et bloque le calcul, une vente de plus de 24 mois par rapport à elle est écartée. Une date restée à celle de l'exemple vous fera donc rejeter vos ventes les plus récentes, qui sont vos meilleures références.
B94: Saisir un prix honoraires comprises ou droits compris | C94: Le prix au m² de cette seule ligne monte de l'ordre de 7 % (Référentiel!C27, millésime 2026), et le panel devient incohérent : les ventes tirées de la base DVF sont hors droits, celles relevées sur une annonce sont souvent honoraires comprises. Saisissez partout le prix net vendeur, celui porté à l'acte hors droits et hors honoraires. Un panel mélangé gonfle deux fois : la valeur, et la dispersion qui fixe la fourchette.
B95: Mélanger surface Carrez et surface habitable (Avis de valeur!C10 et Avis de valeur!E23:E30) | C95: Le prix au m² est le cœur du calcul : quelques mètres carrés d'écart de convention déplacent une ligne de plusieurs points. Employez la même règle sur le bien et sur tous les comparables, pondérez vos annexes avant de saisir, et notez au dossier la règle que vous avez retenue.
B96: Mettre 100 de similarité partout (Avis de valeur!K23:K30) | C96: La pondération ne joue plus, la moyenne devient arithmétique et le comparable le moins ressemblant pèse autant que le meilleur. Descendez à 50 ou 60 dès qu'une vente est moyennement comparable.
B97: Prendre la valeur centrale pour un prix | C97: C'est le milieu d'une fourchette, pas un prix de vente. Présentez la fourchette, et dites de quoi dépend le fait d'être en haut ou en bas : état, étage, vue, travaux votés.
B98: Recaler un coefficient dans une formule plutôt que dans le Référentiel | C98: Le classeur redevient une boîte noire et la mise à jour suivante l'écrase. Toutes les formules pointent vers le Référentiel, sans exception.
B100: Ce que le classeur ne fait pas, et sur quelles sources reposent ses chiffres : voir l'onglet Méthode.
B102: CorpusImmo, millésime 2026. Modèle d'aide à la décision : ne constitue ni un conseil en investissement, ni un conseil fiscal, ni une expertise au sens de la charte de l'expertise en évaluation immobilière. Vérifiez les paramètres avant tout engagement.

Sheet Avis de valeur
B1: CorpusImmo · www.corpus.immo · Estimer, comparer, décider. Sur les ventes réelles.
B2: Avis de valeur par comparaison
B3: Cinq ventes au minimum, des ajustements explicites, une fourchette large comme la dispersion des comparables.
B5: Cellules violettes : à remplir. Cellules blanches : calculées automatiquement.
B7: LE BIEN À ÉVALUER
B8: Adresse | C8: 22 rue de la République | D8: Pour votre dossier. N'entre dans aucun calcul.
B9: Type de bien | C9: Appartement | D9: Liste. Pilote la grille de valeur verte du DPE (Référentiel!C13 et suivantes) : les écarts mesurés sont deux fois plus forts sur une maison.
B10: Surface habitable | C10: 75 | D10: Surface habitable au sens de la loi Boutin, annexes pondérées à part. Toute la valeur en dépend.
B11: État | C11: Bon | D11: Liste de quatre crans. Un cran d'écart vaut le coefficient d'état du Référentiel.
B12: Étage | C12: 2 | D12: 0 pour un rez-de-chaussée, négatif en sous-sol. Bornes de saisie en Référentiel!C41 et Référentiel!C42.
B13: Extérieur (1 = oui, 0 = non) | C13: 1 | D13: Balcon, terrasse ou jardin. Un extérieur exceptionnel se traite dans la similarité.
B14: Étiquette DPE | C14: D | D14: Liste de A à G. La lettre, pas le rang : la grille de valeur verte n'est pas linéaire.
B15: Stationnement (1 = oui, 0 = non) | C15: 0 | D15: Place, box ou garage privatif compris dans la vente.
B16: Ascenseur (1 = oui, 0 = non) | C16: 1 | D16: Sans ascenseur, un étage élevé devient une décote : le sens de l'ajustement d'étage s'inverse.
B17: Date de l'avis | C17: 46250 | D17: Vraie date (jj/mm/aaaa). Elle pilote toute la dérive de marché : ne la laissez jamais vide.
B18: Saisies du bien | C18: =IF(OR(NOT(ISNUMBER($C$10)),$C$10<=0),Référentiel!$D$49&" : surface habitable",IF(ISNA(MATCH($C$9,Référentiel!$C$12:$D$12,0)),Référentiel!$D$49&" : type de bien",IF(ISNA(MATCH($C$11,Référentiel!$B$47:$B$50,0)),Référentiel!$D$49&" : état",IF(OR(NOT(ISNUMBER($C$12)),$C$12<Référentiel!$C$41,$C$12>Référentiel!$C$42),Référentiel!$D$49&" : étage",IF(OR(NOT(ISNUMBER($C$13)),$C$13<0,$C$13>1),Référentiel!$D$49&" : extérieur",IF(ISNA(MATCH($C$14,Référentiel!$C$47:$C$53,0)),Référentiel!$D$49&" : étiquette DPE",IF(OR(NOT(ISNUMBER($C$15)),$C$15<0,$C$15>1),Référentiel!$D$49&" : stationnement",IF(OR(NOT(ISNUMBER($C$16)),$C$16<0,$C$16>1),Référentiel!$D$49&" : ascenseur",IF(NOT(ISNUMBER($C$17)),Référentiel!$D$49&" : date de l'avis","Toutes les saisies du bien sont renseignées."))))))))) -> Toutes les saisies du bien sont renseignées. | M18: Nomme la première saisie manquante ou hors bornes. Tant qu'elle en signale une, aucun ajustement n'est calculé.
B19: Le bien est complet | C19: =IF(LEFT($C$18,LEN(Référentiel!$D$49))<>Référentiel!$D$49,"OK","À CORRIGER") -> OK | D19: À CORRIGER : la ligne au-dessus nomme le champ en cause. Les comparables ne peuvent pas être ajustés sans les caractéristiques du bien.
B21: LES VENTES COMPARABLES
B22: Adresse | C22: Date de vente | D22: Prix net vendeur | E22: Surface | F22: État | G22: Étage | H22: Extérieur (1/0) | I22: DPE | J22: Stationnement (1/0) | K22: Similarité (0 à 100) | L22: Prix €/m² | M22: Ajustement | N22: €/m² ajusté | O22: Poids retenu | P22: Statut de la ligne
B23: 12 rue des Lilas | C23: 46095 | D23: 318000 | E23: 72 | F23: Bon | G23: 3 | H23: 1 | I23: D | J23: 1 | K23: 85 | L23: =IF(AND(ISNUMBER(D23),D23>0,ISNUMBER(E23),E23>0),D23/E23,0) -> 4416.6667 | M23: =IF(OR($C$19<>"OK",NOT(ISNUMBER(C23)),ISNA(MATCH(F23,Référentiel!$B$47:$B$50,0)),NOT(ISNUMBER(G23)),NOT(ISNUMBER(H23)),ISNA(MATCH(I23,Référentiel!$C$47:$C$53,0)),NOT(ISNUMBER(J23))),0,(MATCH($C$11,Référentiel!$B$47:$B$50,0)-MATCH(F23,Référentiel!$B$47:$B$50,0))*Référentiel!$C$23+($C$12-G23)*Référentiel!$C$24*IF($C$16=0,-1,1)+($C$13-H23)*Référentiel!$C$25+(INDEX(Référentiel!$C$13:$D$19,MATCH($C$14,Référentiel!$C$47:$C$53,0),MATCH($C$9,Référentiel!$C$12:$D$12,0))-INDEX(Référentiel!$C$13:$D$19,MATCH(I23,Référentiel!$C$47:$C$53,0),MATCH($C$9,Référentiel!$C$12:$D$12,0)))+($C$15-J23)*Référentiel!$C$26+(($C$17-C23)/(365.25/12))*(Référentiel!$C$9/12)) -> -0.051575633 | N23: =IF(L23>0,L23*(1+M23),0) -> 4188.8743 | O23: =IF(P23=Référentiel!$D$47,K23,0) -> 85 | P23: =IF(COUNTA(B23:K23)=0,"",IF($C$19<>"OK",Référentiel!$D$49&" : le bien est incomplet",IF(OR(NOT(ISNUMBER(D23)),D23<=0),Référentiel!$D$49&" : prix net vendeur manquant",IF(OR(NOT(ISNUMBER(E23)),E23<=0),Référentiel!$D$49&" : surface manquante",IF(NOT(ISNUMBER(C23)),Référentiel!$D$49&" : date de vente non exploitable",IF(C23>$C$17,Référentiel!$D$49&" : vente postérieure à la date de l'avis",IF(ISNA(MATCH(F23,Référentiel!$B$47:$B$50,0)),Référentiel!$D$49&" : état hors liste",IF(OR(NOT(ISNUMBER(G23)),G23<Référentiel!$C$41,G23>Référentiel!$C$42),Référentiel!$D$49&" : étage hors bornes",IF(OR(NOT(ISNUMBER(H23)),H23<0,H23>1),Référentiel!$D$49&" : extérieur, saisir 1 ou 0",IF(ISNA(MATCH(I23,Référentiel!$C$47:$C$53,0)),Référentiel!$D$49&" : DPE hors liste",IF(OR(NOT(ISNUMBER(J23)),J23<0,J23>1),Référentiel!$D$49&" : stationnement, saisir 1 ou 0",IF(OR(NOT(ISNUMBER(K23)),K23<0,K23>Référentiel!$C$43),Référentiel!$D$49&" : similarité hors de 0 à "&TEXT(Référentiel!$C$43,"0"),IF(K23=0,Référentiel!$D$49&" : similarité nulle, le comparable ne pèserait rien",IF(($C$17-C23)/(365.25/12)>Référentiel!$C$35,Référentiel!$D$48&" : vente de "&TEXT(ROUND(($C$17-C23)/(365.25/12),0),"0")&" mois, au-delà du plafond",IF(ABS(M23)>Référentiel!$C$32,Référentiel!$D$48&" : ajustement de "&ROUND(M23*100,1)&" %"&", au-delà du plafond",Référentiel!$D$47))))))))))))))) -> Retenu
B24: 4 avenue du Parc | C24: 45993 | D24: 349000 | E24: 78 | F24: Refait | G24: 1 | H24: 1 | I24: C | J24: 1 | K24: 70 | L24: =IF(AND(ISNUMBER(D24),D24>0,ISNUMBER(E24),E24>0),D24/E24,0) -> 4474.359 | M24: =IF(OR($C$19<>"OK",NOT(ISNUMBER(C24)),ISNA(MATCH(F24,Référentiel!$B$47:$B$50,0)),NOT(ISNUMBER(G24)),NOT(ISNUMBER(H24)),ISNA(MATCH(I24,Référentiel!$C$47:$C$53,0)),NOT(ISNUMBER(J24))),0,(MATCH($C$11,Référentiel!$B$47:$B$50,0)-MATCH(F24,Référentiel!$B$47:$B$50,0))*Référentiel!$C$23+($C$12-G24)*Référentiel!$C$24*IF($C$16=0,-1,1)+($C$13-H24)*Référentiel!$C$25+(INDEX(Référentiel!$C$13:$D$19,MATCH($C$14,Référentiel!$C$47:$C$53,0),MATCH($C$9,Référentiel!$C$12:$D$12,0))-INDEX(Référentiel!$C$13:$D$19,MATCH(I24,Référentiel!$C$47:$C$53,0),MATCH($C$9,Référentiel!$C$12:$D$12,0)))+($C$15-J24)*Référentiel!$C$26+(($C$17-C24)/(365.25/12))*(Référentiel!$C$9/12)) -> -0.14729637 | N24: =IF(L24>0,L24*(1+M24),0) -> 3815.3021 | O24: =IF(P24=Référentiel!$D$47,K24,0) -> 70 | P24: =IF(COUNTA(B24:K24)=0,"",IF($C$19<>"OK",Référentiel!$D$49&" : le bien est incomplet",IF(OR(NOT(ISNUMBER(D24)),D24<=0),Référentiel!$D$49&" : prix net vendeur manquant",IF(OR(NOT(ISNUMBER(E24)),E24<=0),Référentiel!$D$49&" : surface manquante",IF(NOT(ISNUMBER(C24)),Référentiel!$D$49&" : date de vente non exploitable",IF(C24>$C$17,Référentiel!$D$49&" : vente postérieure à la date de l'avis",IF(ISNA(MATCH(F24,Référentiel!$B$47:$B$50,0)),Référentiel!$D$49&" : état hors liste",IF(OR(NOT(ISNUMBER(G24)),G24<Référentiel!$C$41,G24>Référentiel!$C$42),Référentiel!$D$49&" : étage hors bornes",IF(OR(NOT(ISNUMBER(H24)),H24<0,H24>1),Référentiel!$D$49&" : extérieur, saisir 1 ou 0",IF(ISNA(MATCH(I24,Référentiel!$C$47:$C$53,0)),Référentiel!$D$49&" : DPE hors liste",IF(OR(NOT(ISNUMBER(J24)),J24<0,J24>1),Référentiel!$D$49&" : stationnement, saisir 1 ou 0",IF(OR(NOT(ISNUMBER(K24)),K24<0,K24>Référentiel!$C$43),Référentiel!$D$49&" : similarité hors de 0 à "&TEXT(Référentiel!$C$43,"0"),IF(K24=0,Référentiel!$D$49&" : similarité nulle, le comparable ne pèserait rien",IF(($C$17-C24)/(365.25/12)>Référentiel!$C$35,Référentiel!$D$48&" : vente de "&TEXT(ROUND(($C$17-C24)/(365.25/12),0),"0")&" mois, au-delà du plafond",IF(ABS(M24)>Référentiel!$C$32,Référentiel!$D$48&" : ajustement de "&ROUND(M24*100,1)&" %"&", au-delà du plafond",Référentiel!$D$47))))))))))))))) -> Retenu
B25: 27 rue Victor Hugo | C25: 46043 | D25: 289000 | E25: 68 | F25: À rafraîchir | G25: 4 | H25: 0 | I25: E | J25: 0 | K25: 80 | L25: =IF(AND(ISNUMBER(D25),D25>0,ISNUMBER(E25),E25>0),D25/E25,0) -> 4250 | M25: =IF(OR($C$19<>"OK",NOT(ISNUMBER(C25)),ISNA(MATCH(F25,Référentiel!$B$47:$B$50,0)),NOT(ISNUMBER(G25)),NOT(ISNUMBER(H25)),ISNA(MATCH(I25,Référentiel!$C$47:$C$53,0)),NOT(ISNUMBER(J25))),0,(MATCH($C$11,Référentiel!$B$47:$B$50,0)-MATCH(F25,Référentiel!$B$47:$B$50,0))*Référentiel!$C$23+($C$12-G25)*Référentiel!$C$24*IF($C$16=0,-1,1)+($C$13-H25)*Référentiel!$C$25+(INDEX(Référentiel!$C$13:$D$19,MATCH($C$14,Référentiel!$C$47:$C$53,0),MATCH($C$9,Référentiel!$C$12:$D$12,0))-INDEX(Référentiel!$C$13:$D$19,MATCH(I25,Référentiel!$C$47:$C$53,0),MATCH($C$9,Référentiel!$C$12:$D$12,0)))+($C$15-J25)*Référentiel!$C$26+(($C$17-C25)/(365.25/12))*(Référentiel!$C$9/12)) -> 0.12656674 | N25: =IF(L25>0,L25*(1+M25),0) -> 4787.9086 | O25: =IF(P25=Référentiel!$D$47,K25,0) -> 80 | P25: =IF(COUNTA(B25:K25)=0,"",IF($C$19<>"OK",Référentiel!$D$49&" : le bien est incomplet",IF(OR(NOT(ISNUMBER(D25)),D25<=0),Référentiel!$D$49&" : prix net vendeur manquant",IF(OR(NOT(ISNUMBER(E25)),E25<=0),Référentiel!$D$49&" : surface manquante",IF(NOT(ISNUMBER(C25)),Référentiel!$D$49&" : date de vente non exploitable",IF(C25>$C$17,Référentiel!$D$49&" : vente postérieure à la date de l'avis",IF(ISNA(MATCH(F25,Référentiel!$B$47:$B$50,0)),Référentiel!$D$49&" : état hors liste",IF(OR(NOT(ISNUMBER(G25)),G25<Référentiel!$C$41,G25>Référentiel!$C$42),Référentiel!$D$49&" : étage hors bornes",IF(OR(NOT(ISNUMBER(H25)),H25<0,H25>1),Référentiel!$D$49&" : extérieur, saisir 1 ou 0",IF(ISNA(MATCH(I25,Référentiel!$C$47:$C$53,0)),Référentiel!$D$49&" : DPE hors liste",IF(OR(NOT(ISNUMBER(J25)),J25<0,J25>1),Référentiel!$D$49&" : stationnement, saisir 1 ou 0",IF(OR(NOT(ISNUMBER(K25)),K25<0,K25>Référentiel!$C$43),Référentiel!$D$49&" : similarité hors de 0 à "&TEXT(Référentiel!$C$43,"0"),IF(K25=0,Référentiel!$D$49&" : similarité nulle, le comparable ne pèserait rien",IF(($C$17-C25)/(365.25/12)>Référentiel!$C$35,Référentiel!$D$48&" : vente de "&TEXT(ROUND(($C$17-C25)/(365.25/12),0),"0")&" mois, au-delà du plafond",IF(ABS(M25)>Référentiel!$C$32,Référentiel!$D$48&" : ajustement de "&ROUND(M25*100,1)&" %"&", au-delà du plafond",Référentiel!$D$47))))))))))))))) -> Retenu
B26: 8 place Carnot | C26: 46151 | D26: 372000 | E26: 81 | F26: Bon | G26: 2 | H26: 1 | I26: C | J26: 1 | K26: 75 | L26: =IF(AND(ISNUMBER(D26),D26>0,ISNUMBER(E26),E26>0),D26/E26,0) -> 4592.5926 | M26: =IF(OR($C$19<>"OK",NOT(ISNUMBER(C26)),ISNA(MATCH(F26,Référentiel!$B$47:$B$50,0)),NOT(ISNUMBER(G26)),NOT(ISNUMBER(H26)),ISNA(MATCH(I26,Référentiel!$C$47:$C$53,0)),NOT(ISNUMBER(J26))),0,(MATCH($C$11,Référentiel!$B$47:$B$50,0)-MATCH(F26,Référentiel!$B$47:$B$50,0))*Référentiel!$C$23+($C$12-G26)*Référentiel!$C$24*IF($C$16=0,-1,1)+($C$13-H26)*Référentiel!$C$25+(INDEX(Référentiel!$C$13:$D$19,MATCH($C$14,Référentiel!$C$47:$C$53,0),MATCH($C$9,Référentiel!$C$12:$D$12,0))-INDEX(Référentiel!$C$13:$D$19,MATCH(I26,Référentiel!$C$47:$C$53,0),MATCH($C$9,Référentiel!$C$12:$D$12,0)))+($C$15-J26)*Référentiel!$C$26+(($C$17-C26)/(365.25/12))*(Référentiel!$C$9/12)) -> -0.099728953 | N26: =IF(L26>0,L26*(1+M26),0) -> 4134.5781 | O26: =IF(P26=Référentiel!$D$47,K26,0) -> 75 | P26: =IF(COUNTA(B26:K26)=0,"",IF($C$19<>"OK",Référentiel!$D$49&" : le bien est incomplet",IF(OR(NOT(ISNUMBER(D26)),D26<=0),Référentiel!$D$49&" : prix net vendeur manquant",IF(OR(NOT(ISNUMBER(E26)),E26<=0),Référentiel!$D$49&" : surface manquante",IF(NOT(ISNUMBER(C26)),Référentiel!$D$49&" : date de vente non exploitable",IF(C26>$C$17,Référentiel!$D$49&" : vente postérieure à la date de l'avis",IF(ISNA(MATCH(F26,Référentiel!$B$47:$B$50,0)),Référentiel!$D$49&" : état hors liste",IF(OR(NOT(ISNUMBER(G26)),G26<Référentiel!$C$41,G26>Référentiel!$C$42),Référentiel!$D$49&" : étage hors bornes",IF(OR(NOT(ISNUMBER(H26)),H26<0,H26>1),Référentiel!$D$49&" : extérieur, saisir 1 ou 0",IF(ISNA(MATCH(I26,Référentiel!$C$47:$C$53,0)),Référentiel!$D$49&" : DPE hors liste",IF(OR(NOT(ISNUMBER(J26)),J26<0,J26>1),Référentiel!$D$49&" : stationnement, saisir 1 ou 0",IF(OR(NOT(ISNUMBER(K26)),K26<0,K26>Référentiel!$C$43),Référentiel!$D$49&" : similarité hors de 0 à "&TEXT(Référentiel!$C$43,"0"),IF(K26=0,Référentiel!$D$49&" : similarité nulle, le comparable ne pèserait rien",IF(($C$17-C26)/(365.25/12)>Référentiel!$C$35,Référentiel!$D$48&" : vente de "&TEXT(ROUND(($C$17-C26)/(365.25/12),0),"0")&" mois, au-delà du plafond",IF(ABS(M26)>Référentiel!$C$32,Référentiel!$D$48&" : ajustement de "&ROUND(M26*100,1)&" %"&", au-delà du plafond",Référentiel!$D$47))))))))))))))) -> Retenu
B27: 15 rue Pasteur | C27: 45948 | D27: 275000 | E27: 65 | F27: À rénover | G27: 5 | H27: 0 | I27: F | J27: 0 | K27: 60 | L27: =IF(AND(ISNUMBER(D27),D27>0,ISNUMBER(E27),E27>0),D27/E27,0) -> 4230.7692 | M27: =IF(OR($C$19<>"OK",NOT(ISNUMBER(C27)),ISNA(MATCH(F27,Référentiel!$B$47:$B$50,0)),NOT(ISNUMBER(G27)),NOT(ISNUMBER(H27)),ISNA(MATCH(I27,Référentiel!$C$47:$C$53,0)),NOT(ISNUMBER(J27))),0,(MATCH($C$11,Référentiel!$B$47:$B$50,0)-MATCH(F27,Référentiel!$B$47:$B$50,0))*Référentiel!$C$23+($C$12-G27)*Référentiel!$C$24*IF($C$16=0,-1,1)+($C$13-H27)*Référentiel!$C$25+(INDEX(Référentiel!$C$13:$D$19,MATCH($C$14,Référentiel!$C$47:$C$53,0),MATCH($C$9,Référentiel!$C$12:$D$12,0))-INDEX(Référentiel!$C$13:$D$19,MATCH(I27,Référentiel!$C$47:$C$53,0),MATCH($C$9,Référentiel!$C$12:$D$12,0)))+($C$15-J27)*Référentiel!$C$26+(($C$17-C27)/(365.25/12))*(Référentiel!$C$9/12)) -> 0.21482683 | N27: =IF(L27>0,L27*(1+M27),0) -> 5139.652 | O27: =IF(P27=Référentiel!$D$47,K27,0) -> 60 | P27: =IF(COUNTA(B27:K27)=0,"",IF($C$19<>"OK",Référentiel!$D$49&" : le bien est incomplet",IF(OR(NOT(ISNUMBER(D27)),D27<=0),Référentiel!$D$49&" : prix net vendeur manquant",IF(OR(NOT(ISNUMBER(E27)),E27<=0),Référentiel!$D$49&" : surface manquante",IF(NOT(ISNUMBER(C27)),Référentiel!$D$49&" : date de vente non exploitable",IF(C27>$C$17,Référentiel!$D$49&" : vente postérieure à la date de l'avis",IF(ISNA(MATCH(F27,Référentiel!$B$47:$B$50,0)),Référentiel!$D$49&" : état hors liste",IF(OR(NOT(ISNUMBER(G27)),G27<Référentiel!$C$41,G27>Référentiel!$C$42),Référentiel!$D$49&" : étage hors bornes",IF(OR(NOT(ISNUMBER(H27)),H27<0,H27>1),Référentiel!$D$49&" : extérieur, saisir 1 ou 0",IF(ISNA(MATCH(I27,Référentiel!$C$47:$C$53,0)),Référentiel!$D$49&" : DPE hors liste",IF(OR(NOT(ISNUMBER(J27)),J27<0,J27>1),Référentiel!$D$49&" : stationnement, saisir 1 ou 0",IF(OR(NOT(ISNUMBER(K27)),K27<0,K27>Référentiel!$C$43),Référentiel!$D$49&" : similarité hors de 0 à "&TEXT(Référentiel!$C$43,"0"),IF(K27=0,Référentiel!$D$49&" : similarité nulle, le comparable ne pèserait rien",IF(($C$17-C27)/(365.25/12)>Référentiel!$C$35,Référentiel!$D$48&" : vente de "&TEXT(ROUND(($C$17-C27)/(365.25/12),0),"0")&" mois, au-delà du plafond",IF(ABS(M27)>Référentiel!$C$32,Référentiel!$D$48&" : ajustement de "&ROUND(M27*100,1)&" %"&", au-delà du plafond",Référentiel!$D$47))))))))))))))) -> Retenu
B28: 31 boulevard Gambetta | C28: 46080 | D28: 331000 | E28: 74 | F28: Bon | G28: 3 | H28: 1 | I28: D | J28: 1 | K28: 90 | L28: =IF(AND(ISNUMBER(D28),D28>0,ISNUMBER(E28),E28>0),D28/E28,0) -> 4472.973 | M28: =IF(OR($C$19<>"OK",NOT(ISNUMBER(C28)),ISNA(MATCH(F28,Référentiel!$B$47:$B$50,0)),NOT(ISNUMBER(G28)),NOT(ISNUMBER(H28)),ISNA(MATCH(I28,Référentiel!$C$47:$C$53,0)),NOT(ISNUMBER(J28))),0,(MATCH($C$11,Référentiel!$B$47:$B$50,0)-MATCH(F28,Référentiel!$B$47:$B$50,0))*Référentiel!$C$23+($C$12-G28)*Référentiel!$C$24*IF($C$16=0,-1,1)+($C$13-H28)*Référentiel!$C$25+(INDEX(Référentiel!$C$13:$D$19,MATCH($C$14,Référentiel!$C$47:$C$53,0),MATCH($C$9,Référentiel!$C$12:$D$12,0))-INDEX(Référentiel!$C$13:$D$19,MATCH(I28,Référentiel!$C$47:$C$53,0),MATCH($C$9,Référentiel!$C$12:$D$12,0)))+($C$15-J28)*Référentiel!$C$26+(($C$17-C28)/(365.25/12))*(Référentiel!$C$9/12)) -> -0.051534565 | N28: =IF(L28>0,L28*(1+M28),0) -> 4242.4603 | O28: =IF(P28=Référentiel!$D$47,K28,0) -> 90 | P28: =IF(COUNTA(B28:K28)=0,"",IF($C$19<>"OK",Référentiel!$D$49&" : le bien est incomplet",IF(OR(NOT(ISNUMBER(D28)),D28<=0),Référentiel!$D$49&" : prix net vendeur manquant",IF(OR(NOT(ISNUMBER(E28)),E28<=0),Référentiel!$D$49&" : surface manquante",IF(NOT(ISNUMBER(C28)),Référentiel!$D$49&" : date de vente non exploitable",IF(C28>$C$17,Référentiel!$D$49&" : vente postérieure à la date de l'avis",IF(ISNA(MATCH(F28,Référentiel!$B$47:$B$50,0)),Référentiel!$D$49&" : état hors liste",IF(OR(NOT(ISNUMBER(G28)),G28<Référentiel!$C$41,G28>Référentiel!$C$42),Référentiel!$D$49&" : étage hors bornes",IF(OR(NOT(ISNUMBER(H28)),H28<0,H28>1),Référentiel!$D$49&" : extérieur, saisir 1 ou 0",IF(ISNA(MATCH(I28,Référentiel!$C$47:$C$53,0)),Référentiel!$D$49&" : DPE hors liste",IF(OR(NOT(ISNUMBER(J28)),J28<0,J28>1),Référentiel!$D$49&" : stationnement, saisir 1 ou 0",IF(OR(NOT(ISNUMBER(K28)),K28<0,K28>Référentiel!$C$43),Référentiel!$D$49&" : similarité hors de 0 à "&TEXT(Référentiel!$C$43,"0"),IF(K28=0,Référentiel!$D$49&" : similarité nulle, le comparable ne pèserait rien",IF(($C$17-C28)/(365.25/12)>Référentiel!$C$35,Référentiel!$D$48&" : vente de "&TEXT(ROUND(($C$17-C28)/(365.25/12),0),"0")&" mois, au-delà du plafond",IF(ABS(M28)>Référentiel!$C$32,Référentiel!$D$48&" : ajustement de "&ROUND(M28*100,1)&" %"&", au-delà du plafond",Référentiel!$D$47))))))))))))))) -> Retenu
L29: =IF(AND(ISNUMBER(D29),D29>0,ISNUMBER(E29),E29>0),D29/E29,0) -> 0 | M29: =IF(OR($C$19<>"OK",NOT(ISNUMBER(C29)),ISNA(MATCH(F29,Référentiel!$B$47:$B$50,0)),NOT(ISNUMBER(G29)),NOT(ISNUMBER(H29)),ISNA(MATCH(I29,Référentiel!$C$47:$C$53,0)),NOT(ISNUMBER(J29))),0,(MATCH($C$11,Référentiel!$B$47:$B$50,0)-MATCH(F29,Référentiel!$B$47:$B$50,0))*Référentiel!$C$23+($C$12-G29)*Référentiel!$C$24*IF($C$16=0,-1,1)+($C$13-H29)*Référentiel!$C$25+(INDEX(Référentiel!$C$13:$D$19,MATCH($C$14,Référentiel!$C$47:$C$53,0),MATCH($C$9,Référentiel!$C$12:$D$12,0))-INDEX(Référentiel!$C$13:$D$19,MATCH(I29,Référentiel!$C$47:$C$53,0),MATCH($C$9,Référentiel!$C$12:$D$12,0)))+($C$15-J29)*Référentiel!$C$26+(($C$17-C29)/(365.25/12))*(Référentiel!$C$9/12)) -> 0 | N29: =IF(L29>0,L29*(1+M29),0) -> 0 | O29: =IF(P29=Référentiel!$D$47,K29,0) -> 0 | P29: =IF(COUNTA(B29:K29)=0,"",IF($C$19<>"OK",Référentiel!$D$49&" : le bien est incomplet",IF(OR(NOT(ISNUMBER(D29)),D29<=0),Référentiel!$D$49&" : prix net vendeur manquant",IF(OR(NOT(ISNUMBER(E29)),E29<=0),Référentiel!$D$49&" : surface manquante",IF(NOT(ISNUMBER(C29)),Référentiel!$D$49&" : date de vente non exploitable",IF(C29>$C$17,Référentiel!$D$49&" : vente postérieure à la date de l'avis",IF(ISNA(MATCH(F29,Référentiel!$B$47:$B$50,0)),Référentiel!$D$49&" : état hors liste",IF(OR(NOT(ISNUMBER(G29)),G29<Référentiel!$C$41,G29>Référentiel!$C$42),Référentiel!$D$49&" : étage hors bornes",IF(OR(NOT(ISNUMBER(H29)),H29<0,H29>1),Référentiel!$D$49&" : extérieur, saisir 1 ou 0",IF(ISNA(MATCH(I29,Référentiel!$C$47:$C$53,0)),Référentiel!$D$49&" : DPE hors liste",IF(OR(NOT(ISNUMBER(J29)),J29<0,J29>1),Référentiel!$D$49&" : stationnement, saisir 1 ou 0",IF(OR(NOT(ISNUMBER(K29)),K29<0,K29>Référentiel!$C$43),Référentiel!$D$49&" : similarité hors de 0 à "&TEXT(Référentiel!$C$43,"0"),IF(K29=0,Référentiel!$D$49&" : similarité nulle, le comparable ne pèserait rien",IF(($C$17-C29)/(365.25/12)>Référentiel!$C$35,Référentiel!$D$48&" : vente de "&TEXT(ROUND(($C$17-C29)/(365.25/12),0),"0")&" mois, au-delà du plafond",IF(ABS(M29)>Référentiel!$C$32,Référentiel!$D$48&" : ajustement de "&ROUND(M29*100,1)&" %"&", au-delà du plafond",Référentiel!$D$47)))))))))))))))
L30: =IF(AND(ISNUMBER(D30),D30>0,ISNUMBER(E30),E30>0),D30/E30,0) -> 0 | M30: =IF(OR($C$19<>"OK",NOT(ISNUMBER(C30)),ISNA(MATCH(F30,Référentiel!$B$47:$B$50,0)),NOT(ISNUMBER(G30)),NOT(ISNUMBER(H30)),ISNA(MATCH(I30,Référentiel!$C$47:$C$53,0)),NOT(ISNUMBER(J30))),0,(MATCH($C$11,Référentiel!$B$47:$B$50,0)-MATCH(F30,Référentiel!$B$47:$B$50,0))*Référentiel!$C$23+($C$12-G30)*Référentiel!$C$24*IF($C$16=0,-1,1)+($C$13-H30)*Référentiel!$C$25+(INDEX(Référentiel!$C$13:$D$19,MATCH($C$14,Référentiel!$C$47:$C$53,0),MATCH($C$9,Référentiel!$C$12:$D$12,0))-INDEX(Référentiel!$C$13:$D$19,MATCH(I30,Référentiel!$C$47:$C$53,0),MATCH($C$9,Référentiel!$C$12:$D$12,0)))+($C$15-J30)*Référentiel!$C$26+(($C$17-C30)/(365.25/12))*(Référentiel!$C$9/12)) -> 0 | N30: =IF(L30>0,L30*(1+M30),0) -> 0 | O30: =IF(P30=Référentiel!$D$47,K30,0) -> 0 | P30: =IF(COUNTA(B30:K30)=0,"",IF($C$19<>"OK",Référentiel!$D$49&" : le bien est incomplet",IF(OR(NOT(ISNUMBER(D30)),D30<=0),Référentiel!$D$49&" : prix net vendeur manquant",IF(OR(NOT(ISNUMBER(E30)),E30<=0),Référentiel!$D$49&" : surface manquante",IF(NOT(ISNUMBER(C30)),Référentiel!$D$49&" : date de vente non exploitable",IF(C30>$C$17,Référentiel!$D$49&" : vente postérieure à la date de l'avis",IF(ISNA(MATCH(F30,Référentiel!$B$47:$B$50,0)),Référentiel!$D$49&" : état hors liste",IF(OR(NOT(ISNUMBER(G30)),G30<Référentiel!$C$41,G30>Référentiel!$C$42),Référentiel!$D$49&" : étage hors bornes",IF(OR(NOT(ISNUMBER(H30)),H30<0,H30>1),Référentiel!$D$49&" : extérieur, saisir 1 ou 0",IF(ISNA(MATCH(I30,Référentiel!$C$47:$C$53,0)),Référentiel!$D$49&" : DPE hors liste",IF(OR(NOT(ISNUMBER(J30)),J30<0,J30>1),Référentiel!$D$49&" : stationnement, saisir 1 ou 0",IF(OR(NOT(ISNUMBER(K30)),K30<0,K30>Référentiel!$C$43),Référentiel!$D$49&" : similarité hors de 0 à "&TEXT(Référentiel!$C$43,"0"),IF(K30=0,Référentiel!$D$49&" : similarité nulle, le comparable ne pèserait rien",IF(($C$17-C30)/(365.25/12)>Référentiel!$C$35,Référentiel!$D$48&" : vente de "&TEXT(ROUND(($C$17-C30)/(365.25/12),0),"0")&" mois, au-delà du plafond",IF(ABS(M30)>Référentiel!$C$32,Référentiel!$D$48&" : ajustement de "&ROUND(M30*100,1)&" %"&", au-delà du plafond",Référentiel!$D$47)))))))))))))))
B32: LE PANEL DE COMPARABLES
B33: Comparables renseignés | C33: =SUMPRODUCT(--($P$23:$P$30<>"")) -> 6 | D33: Lignes du tableau où au moins une cellule violette est remplie.
B34: Comparables retenus | C34: =COUNTIF($P$23:$P$30,Référentiel!$D$47) -> 6 | D34: Ceux qui entrent réellement dans la moyenne, et eux seuls. Minimum exigé en Référentiel!C33.
B35: Dont lignes à compléter | C35: =COUNTIF($P$23:$P$30,Référentiel!$D$49&"*") -> 0 | D35: Une saisie manque ou sort de ses bornes. Ces lignes n'entrent pas dans la moyenne et la valeur n'est pas produite tant qu'elles sont là.
B36: Dont comparables écartés | C36: =COUNTIF($P$23:$P$30,Référentiel!$D$48&"*") -> 0 | D36: Ajustement au-delà du plafond, ou vente trop ancienne. La ligne est complète, mais le modèle refuse de s'en servir : son statut dit lequel des deux motifs s'applique.
B37: Première ligne à compléter | C37: =IF($C$35=0,"Aucune ligne à compléter.","Comparable "&TEXT(MATCH(Référentiel!$D$49&"*",$P$23:$P$30,0),"0")&IF(INDEX($B$23:$B$30,MATCH(Référentiel!$D$49&"*",$P$23:$P$30,0))=""," "," ("&INDEX($B$23:$B$30,MATCH(Référentiel!$D$49&"*",$P$23:$P$30,0))&") ")&": "&INDEX($P$23:$P$30,MATCH(Référentiel!$D$49&"*",$P$23:$P$30,0))&IF($C$35>1," Et "&TEXT($C$35-1,"0")&" autre(s) ligne(s) à compléter.","")) -> Aucune ligne à compléter. | M37: Nomme le comparable et le champ en cause. C'est le garde-fou de la saisie oubliée.
B38: Toutes les lignes renseignées sont exploitables | C38: =IF($C$35=0,"OK","À CORRIGER") -> OK | D38: À CORRIGER : complétez la ligne nommée juste au-dessus, puis relisez ce contrôle.
B39: Prix au m² moyen des lignes saisies | C39: =IF(COUNTIF($L$23:$L$30,">0")>0,SUMIF($L$23:$L$30,">0")/COUNTIF($L$23:$L$30,">0"),0) -> 4406.2267 | D39: Moyenne simple des prix au m² avant tout ajustement, sur les lignes exploitables. Sert au seul contrôle de cohérence ci-dessous : ce n'est pas le prix au m² retenu.
B40: Écart maximal au prix au m² moyen | C40: =IF($C$39>0,MAX(SUMPRODUCT(MAX(($L$23:$L$30>0)*($L$23:$L$30-$C$39))),SUMPRODUCT(MAX(($L$23:$L$30>0)*($C$39-$L$23:$L$30))))/$C$39,0) -> 0.04229602 | D40: Écart de la ligne la plus éloignée de cette moyenne. Seuil de signalement en Référentiel!C40.
B41: Cohérence des prix saisis | C41: =IF(OR($C$39<=0,$C$40<=Référentiel!$C$40),"Prix au m² cohérents entre eux.","Comparable "&TEXT(SUMPRODUCT(MAX(((($L$23:$L$30-$C$39)=MAX(SUMPRODUCT(MAX(($L$23:$L$30>0)*($L$23:$L$30-$C$39))),SUMPRODUCT(MAX(($L$23:$L$30>0)*($C$39-$L$23:$L$30)))))+(($C$39-$L$23:$L$30)=MAX(SUMPRODUCT(MAX(($L$23:$L$30>0)*($L$23:$L$30-$C$39))),SUMPRODUCT(MAX(($L$23:$L$30>0)*($C$39-$L$23:$L$30))))))*($L$23:$L$30>0)*ROW($L$23:$L$30)))-ROW($L$23)+1,"0")&IF(INDEX($B$23:$B$30,SUMPRODUCT(MAX(((($L$23:$L$30-$C$39)=MAX(SUMPRODUCT(MAX(($L$23:$L$30>0)*($L$23:$L$30-$C$39))),SUMPRODUCT(MAX(($L$23:$L$30>0)*($C$39-$L$23:$L$30)))))+(($C$39-$L$23:$L$30)=MAX(SUMPRODUCT(MAX(($L$23:$L$30>0)*($L$23:$L$30-$C$39))),SUMPRODUCT(MAX(($L$23:$L$30>0)*($C$39-$L$23:$L$30))))))*($L$23:$L$30>0)*ROW($L$23:$L$30)))-ROW($L$23)+1)=""," "," ("&INDEX($B$23:$B$30,SUMPRODUCT(MAX(((($L$23:$L$30-$C$39)=MAX(SUMPRODUCT(MAX(($L$23:$L$30>0)*($L$23:$L$30-$C$39))),SUMPRODUCT(MAX(($L$23:$L$30>0)*($C$39-$L$23:$L$30)))))+(($C$39-$L$23:$L$30)=MAX(SUMPRODUCT(MAX(($L$23:$L$30>0)*($L$23:$L$30-$C$39))),SUMPRODUCT(MAX(($L$23:$L$30>0)*($C$39-$L$23:$L$30))))))*($L$23:$L$30>0)*ROW($L$23:$L$30)))-ROW($L$23)+1)&") ")&": son prix au m² s'écarte de "&ROUND($C$40*100,0)&" %"&" de la moyenne du panel. Vérifiez qu'il s'agit bien d'un prix net vendeur, hors "&"honoraires d'agence et hors droits de mutation, comme les autres lignes.") -> Prix au m² cohérents entre eux. | M41: Nomme la ligne dont le prix au m² s'écarte le plus du panel, quand elle dépasse le seuil.
B42: Prix saisis cohérents entre eux | C42: =IF($C$39>0,IF($C$40<=Référentiel!$C$40,"OK","À VÉRIFIER"),"") -> OK | D42: À VÉRIFIER : une ligne s'écarte fortement du panel. Le plus souvent un prix tapé en milliers, une surface qui n'est pas celle du bien vendu, ou une vente qui n'appartient pas au même marché. Ce contrôle signale, il ne bloque rien.
B43: Poids du comparable dominant | C43: =IF(SUM($O$23:$O$30)>0,MAX($O$23:$O$30)/SUM($O$23:$O$30),0) -> 0.19565217 | D43: Part de la plus forte similarité dans le total des poids. Plafond en Référentiel!C34 : au-delà, une seule vente ferait la valeur.
B45: PRIX AU M² ET DISPERSION
B46: Prix au m² retenu | C46: =IF(SUM($O$23:$O$30)>0,SUMPRODUCT($N$23:$N$30,$O$23:$O$30)/SUM($O$23:$O$30),0) -> 4361.8523 | D46: Moyenne des prix au m² ajustés, pondérée par la similarité. À confronter au prix médian du quartier (base DVF, chiffres des notaires) avant de conclure.
B47: Le plus bas des prix au m² ajustés | C47: =IF($C$34>0,SUMPRODUCT(MIN(($O$23:$O$30>0)*$N$23:$N$30+($O$23:$O$30=0)*$C$48)),0) -> 3815.3021 | D47: Parmi les comparables retenus seulement.
B48: Le plus haut des prix au m² ajustés | C48: =IF($C$34>0,SUMPRODUCT(MAX(($O$23:$O$30>0)*$N$23:$N$30)),0) -> 5139.652 | D48: L'écart entre ce chiffre et le précédent est la première chose que regarde un contradicteur.
B49: Écart type pondéré des prix au m² ajustés | C49: =IF(AND($C$34>=Référentiel!$C$36,$C$46>0),SQRT(SUMPRODUCT($O$23:$O$30,($N$23:$N$30-$C$46)^2)/SUM($O$23:$O$30)*$C$34/($C$34-1)),0) -> 455.2038 | D49: Dispersion du panel une fois les ajustements faits, pondérée par la similarité et corrigée du biais de petit échantillon.
B50: Coefficient de variation | C50: =IF($C$46>0,$C$49/$C$46,0) -> 0.1043602 | D50: Écart type rapporté au prix au m² retenu. Seuil d'alerte en Référentiel!C39.
B51: Demi-fourchette retenue | C51: =IF($C$34<Référentiel!$C$36,Référentiel!$C$38,MAX(Référentiel!$C$37,$C$50)) -> 0.1043602 | D51: Ce qu'on retranche puis ce qu'on ajoute à la valeur centrale : la fourchette fait donc deux fois ce pourcentage. Le plus élevé du plancher (Référentiel!C37) et du coefficient de variation.
B52: Ce que vaut cette fourchette | C52: =IF($C$34<Référentiel!$C$36,"Échantillon trop faible pour mesurer une dispersion : demi-fourchette de repli de "&ROUND(Référentiel!$C$38*100,1)&" %"&", à justifier au dossier.","Demi-fourchette fondée sur l'écart type pondéré des comparables retenus, avec un plancher de "&ROUND(Référentiel!$C$37*100,1)&" %"&".") -> Demi-fourchette fondée sur l'écart type pondéré des comparables retenus, avec un plancher de 3 %. | M52: La phrase à montrer au vendeur : elle dit sur quoi la largeur de la fourchette est fondée, et signale un échantillon trop faible pour la mesurer.
B53: Dispersion sous le seuil | C53: =IF(AND($C$34>=Référentiel!$C$36,$C$50<=Référentiel!$C$39),"OK","À JUSTIFIER") -> OK | D53: À JUSTIFIER : la dispersion dépasse le seuil du Référentiel, ou l'échantillon est trop faible pour la mesurer. La fourchette reste juste, mais elle est large : dites pourquoi au dossier. Ce contrôle mesure la dispersion, il ne juge pas l'écart brut entre le plus bas et le plus haut.
B55: VALEUR ET FOURCHETTE
B56: Valeur centrale | C56: =IF($C$19<>"OK","Bien incomplet",IF($C$35>0,"Lignes à compléter",IF($C$34<Référentiel!$C$33,"Trop peu de comparables",IF($C$43>Référentiel!$C$34,"Un comparable domine",$C$46*$C$10)))) -> 327138.92 | D56: Prix au m² retenu multiplié par la surface habitable. Quand un verrou du modèle joue, elle affiche à la place l'un des quatre messages : Bien incomplet, Lignes à compléter, Trop peu de comparables, Un comparable domine. Le Mode d'emploi dit ce qui déclenche chacun et ce qui le lève.
B57: Bas de fourchette | C57: =IF(ISNUMBER($C$56),$C$56*(1-$C$51),$C$56) -> 292998.64 | D57: Valeur centrale moins la demi-fourchette.
B58: Haut de fourchette | C58: =IF(ISNUMBER($C$56),$C$56*(1+$C$51),$C$56) -> 361279.21 | D58: Valeur centrale plus la demi-fourchette.
B59: Fourchette à présenter | C59: =IF(ISNUMBER($C$56),IF(ROUND($C$57,0)>=1000000,TEXT(INT(ROUND($C$57,0)/1000000),"0")&" "&TEXT(INT(MOD(ROUND($C$57,0),1000000)/1000),"000")&" "&TEXT(MOD(ROUND($C$57,0),1000),"000"),IF(ROUND($C$57,0)>=1000,TEXT(INT(ROUND($C$57,0)/1000),"0")&" "&TEXT(MOD(ROUND($C$57,0),1000),"000"),TEXT(ROUND($C$57,0),"0")))&" €"&" à "&IF(ROUND($C$58,0)>=1000000,TEXT(INT(ROUND($C$58,0)/1000000),"0")&" "&TEXT(INT(MOD(ROUND($C$58,0),1000000)/1000),"000")&" "&TEXT(MOD(ROUND($C$58,0),1000),"000"),IF(ROUND($C$58,0)>=1000,TEXT(INT(ROUND($C$58,0)/1000),"0")&" "&TEXT(MOD(ROUND($C$58,0),1000),"000"),TEXT(ROUND($C$58,0),"0")))&" €",$C$56) -> 292 999 € à 361 279 € | M59: C'est cette ligne qui se présente au vendeur, jamais la valeur centrale seule.
B61: Cet avis de valeur n'est pas une expertise en évaluation immobilière : des investigations complètes auraient pu conduire à des conclusions sensiblement différentes.
B62: Présentez la fourchette, jamais la valeur centrale seule. Un prix unique devient le plancher de la négociation dans la tête du vendeur, et le plafond dans celle de l'acquéreur.
B63: La fourchette, elle, ouvre la discussion sur les caractéristiques du bien, c'est-à-dire sur votre expertise.
B65: CorpusImmo, millésime 2026. Modèle d'aide à la décision : ne constitue ni un conseil en investissement, ni un conseil fiscal, ni une expertise au sens de la charte de l'expertise en évaluation immobilière. Vérifiez les paramètres avant tout engagement.

Sheet Référentiel
B1: CorpusImmo · www.corpus.immo · Estimer, comparer, décider. Sur les ventes réelles.
B2: Référentiel
B3: Tous les coefficients, barèmes et garde-fous du classeur, avec leur source et leur date. Aucun n'est recopié dans une formule.
B5: Cellules violettes : à remplir. Cellules blanches : calculées automatiquement.
B7: =" BARÈME SOURCÉ, MILLÉSIME "&YEAR(Référentiel!$C$56) -> BARÈME SOURCÉ, MILLÉSIME 2026
B8: Paramètre | C8: Valeur | D8: Source (organisme, texte, date) | E8: Mise à jour | F8: Commentaire
B9: Dérive du marché, sur un an | C9: 0.001 | D9: ="INSEE, Informations rapides n° 130 du 28 mai 2026 (indice Notaires INSEE, 1er trimestre 2026) : plus 0,2 % sur le trimestre et plus 0,1 % sur un an, France entière, tous logements ; appartements plus "&"0,6 %, maisons moins 0,2 % ; Île-de-France plus 0,6 %, province 0 %. Vérifié le "&TEXT(DAY(Référentiel!$C$56),"00")&"/"&TEXT(MONTH(Référentiel!$C$56),"00")&"/"&YEAR(Référentiel!$C$56)&"." -> INSEE, Informations rapides n° 130 du 28 mai 2026 (indice Notaires INSEE, 1er trimestre 2026) : plus 0,2 % sur le trimestre et plus 0,1 % sur un an, France entière, tous logements ; appartements plus 0,6 %, maisons moins 0,2 % ; Île-de-France plus 0,6 %, province 0 %. Vérifié le 05/09/2026. | E9: Trimestrielle (indice Notaires INSEE) | F9: Ramenée au mois par le classeur, puis appliquée à l'ancienneté de chaque vente. Valeur par défaut prudente : la hausse France entière tous logements, plus basse que celle des seuls appartements. Recalez-la sur votre marché, négative en marché baissier.
B11: VALEUR VERTE : ÉCART DE PRIX PAR ÉTIQUETTE DPE, PAR RAPPORT À UNE ÉTIQUETTE D
B12: Étiquette DPE | C12: Appartement | D12: Maison | E12: Mise à jour | F12: Origine de la valeur
B13: A | C13: 0.16 | D13: 0.2 | E13: Annuelle | F13: ="Notaires de France, bilan immobilier de décembre 2025 portant sur les transactions 2024 (valeur verte, écart de prix par rapport à une étiquette D). Appartements : mesuré. Maisons : interpolé sur la m"&"ême forme, calée sur le G mesuré. Vérifié le "&TEXT(DAY(Référentiel!$C$56),"00")&"/"&TEXT(MONTH(Référentiel!$C$56),"00")&"/"&YEAR(Référentiel!$C$56)&"." -> Notaires de France, bilan immobilier de décembre 2025 portant sur les transactions 2024 (valeur verte, écart de prix par rapport à une étiquette D). Appartements : mesuré. Maisons : interpolé sur la même forme, calée sur le G mesuré. Vérifié le 05/09/2026.
B14: B | C14: 0.12 | D14: 0.15 | F14: Appartements : mesuré. Maisons : interpolé.
B15: C | C15: 0.06 | D15: 0.08 | F15: Appartements : mesuré. Maisons : interpolé.
B16: D | C16: 0 | D16: 0 | F16: Étiquette de référence de la grille : par construction, écart nul.
B17: E | C17: -0.04 | D17: -0.08 | F17: Interpolé entre le C et le G mesurés : aucune valeur publiée pour cette étiquette.
B18: F | C18: -0.08 | D18: -0.16 | F18: Interpolé entre le C et le G mesurés. La loi Climat et résilience du 22 août 2021 interdit la location des étiquettes G depuis le 1er janvier 2025 et celle des F au 1er janvier 2028 : l'écart se creuse à mesure que l'échéance approche.
B19: G | C19: -0.12 | D19: -0.25 | F19: Mesuré pour les deux : moins 12 % en appartement, moins 25 % en maison.
B20: Les en-têtes « Appartement » et « Maison » alimentent aussi la liste du type de bien.
B21: REPÈRES DE MARCHÉ, À RECALER SUR VOTRE SECTEUR
B22: Paramètre | C22: Valeur | D22: Source (organisme, texte, date) | E22: Mise à jour | F22: Commentaire
B23: Écart d'un cran d'état | C23: 0.06 | D23: ="Casavo, étude relayée par MySweetimmo le 7 avril 2025 (écarts mesurés sur les ventes 2024). Rénové contre non rénové : plus 9 % en France, plus 12,5 % à Paris, plus 13 % en Île-de-France, plus 5,8 % à"&" Nantes. Vérifié le "&TEXT(DAY(Référentiel!$C$56),"00")&"/"&TEXT(MONTH(Référentiel!$C$56),"00")&"/"&YEAR(Référentiel!$C$56)&"." -> Casavo, étude relayée par MySweetimmo le 7 avril 2025 (écarts mesurés sur les ventes 2024). Rénové contre non rénové : plus 9 % en France, plus 12,5 % à Paris, plus 13 % en Île-de-France, plus 5,8 % à Nantes. Vérifié le 05/09/2026. | E23: Annuelle | F23: Un cran sépare deux libellés voisins de la liste. Trois crans séparent « À rénover » de « Refait », donc trois fois ce coefficient, quelle que soit la valeur que vous y mettez.
B24: Écart d'un étage | C24: 0.012 | D24: ="MeilleursAgents, relevé cité par SeLoger le 3 juin 2017 : environ plus 4 % entre le 2e et le 4e étage en province, soit 2 % par étage ; du rez-de-chaussée au dernier étage, 15 % en province et 19 % à "&"Paris. Décote de rez-de-chaussée de 4 à 10 % selon Casavo 2025, non linéaire : elle se traite dans la similarité, pas par ce coefficient. Vérifié le "&TEXT(DAY(Référentiel!$C$56),"00")&"/"&TEXT(MONTH(Référentiel!$C$56),"00")&"/"&YEAR(Référentiel!$C$56)&"." -> MeilleursAgents, relevé cité par SeLoger le 3 juin 2017 : environ plus 4 % entre le 2e et le 4e étage en province, soit 2 % par étage ; du rez-de-chaussée au dernier étage, 15 % en province et 19 % à Paris. Décote de rez-de-chaussée de 4 à 10 % selon Casavo 2025, non linéaire : elle se traite dans la similarité, pas par ce coefficient. Vérifié le 05/09/2026. | E24: Annuelle | F24: Le sens s'inverse automatiquement quand le bien n'a pas d'ascenseur. Valeur par défaut plutôt basse : les relevés de province donnent jusqu'à 2 % par étage.
B25: Présence d'un extérieur | C25: 0.05 | D25: ="Casavo, étude relayée par MySweetimmo le 7 avril 2025 (écarts mesurés sur les ventes 2024). Plus 6,3 % en Île-de-France, plus 7,2 % à Lyon, plus 8,5 % à Nantes, plus 12,1 % en Provence-Alpes-Côte d'Az"&"ur. Vérifié le "&TEXT(DAY(Référentiel!$C$56),"00")&"/"&TEXT(MONTH(Référentiel!$C$56),"00")&"/"&YEAR(Référentiel!$C$56)&"." -> Casavo, étude relayée par MySweetimmo le 7 avril 2025 (écarts mesurés sur les ventes 2024). Plus 6,3 % en Île-de-France, plus 7,2 % à Lyon, plus 8,5 % à Nantes, plus 12,1 % en Provence-Alpes-Côte d'Azur. Vérifié le 05/09/2026. | E25: Annuelle | F25: Balcon, terrasse ou jardin, contre rien. Valeur par défaut en bas de fourchette : très local, à recaler.
B26: Présence d'un stationnement | C26: 0.04 | D26: ="Casavo, étude relayée par MySweetimmo le 7 avril 2025 (écarts mesurés sur les ventes 2024). Très variable selon la ville : de moins 18,2 % à Lyon à plus 18 % à Saint-Cloud, selon la tension sur le sta"&"tionnement de surface. Vérifié le "&TEXT(DAY(Référentiel!$C$56),"00")&"/"&TEXT(MONTH(Référentiel!$C$56),"00")&"/"&YEAR(Référentiel!$C$56)&"." -> Casavo, étude relayée par MySweetimmo le 7 avril 2025 (écarts mesurés sur les ventes 2024). Très variable selon la ville : de moins 18,2 % à Lyon à plus 18 % à Saint-Cloud, selon la tension sur le stationnement de surface. Vérifié le 05/09/2026. | E26: Annuelle | F26: Le coefficient le plus local de la grille. Nul en périphérie, décisif en centre-ville.
B27: Écart entre un prix affiché et le prix net vendeur | C27: 0.07 | D27: ="Droits de mutation à titre onéreux dans l'ancien : 6,32 % du prix dans 89 départements, 5,81 % dans 11, 5,09 % dans l'Indre (Notaires de France, 18/11/2025). Droit départemental porté de 4,50 % à 5 % "&"par la loi de finances pour 2025, article 116, pour les actes reçus du 1er avril 2025 au 31 mars 2028 (CGI art. 1594 D) ; taxe communale de 1,20 % (art. 1584) ; frais d'assiette de 2,37 % du droit dép"&"artemental (art. 1647 V), d'où 5 % × 1,0237 + 1,20 % = 6,32 %, et 4,50 % × 1,0237 + 1,20 % = 5,81 % dans les départements restés au taux de base et pour les primo-accédants achetant leur résidence pri"&"ncipale. Émoluments et débours du notaire en sus. Les honoraires d'agence d'une vente de particulier se situent dans le même ordre de grandeur, sans barème public. Vérifié le "&TEXT(DAY(Référentiel!$C$56),"00")&"/"&TEXT(MONTH(Référentiel!$C$56),"00")&"/"&YEAR(Référentiel!$C$56)&"." -> Droits de mutation à titre onéreux dans l'ancien : 6,32 % du prix dans 89 départements, 5,81 % dans 11, 5,09 % dans l'Indre (Notaires de France, 18/11/2025). Droit départemental porté de 4,50 % à 5 % par la loi de finances pour 2025, article 116, pour les actes reçus du 1er avril 2025 au 31 mars 2028 (CGI art. 1594 D) ; taxe communale de 1,20 % (art. 1584) ; frais d'assiette de 2,37 % du droit départemental (art. 1647 V), d'où 5 % × 1,0237 + 1,20 % = 6,32 %, et 4,50 % × 1,0237 + 1,20 % = 5,81 % dans les départements restés au taux de base et pour les primo-accédants achetant leur résidence principale. Émoluments et débours du notaire en sus. Les honoraires d'agence d'une vente de particulier se situent dans le même ordre de grandeur, sans barème public. Vérifié le 05/09/2026. | E27: Annuelle | F27: Ce que gonfle une ligne saisie honoraires comprises ou droits compris, au lieu du prix net vendeur attendu. Ce repère ne sert à aucun calcul : il chiffre l'erreur de saisie la plus coûteuse et la moins visible du classeur, celle qu'aucun contrôle ne peut détecter.
B29: CONVENTIONS ET GARDE-FOUS DU MODÈLE
B30: Paramètre | C30: Valeur | D30: Source (organisme, texte, date) | E30: Mise à jour | F30: Commentaire
B31: Ajustement au-delà duquel un comparable est signalé comme éloigné | C31: 0.15 | D31: ="Convention du modèle, pas un barème de marché. Seuil de vigilance, plus bas que le plafond d'exclusion. Vérifié le "&TEXT(DAY(Référentiel!$C$56),"00")&"/"&TEXT(MONTH(Référentiel!$C$56),"00")&"/"&YEAR(Référentiel!$C$56)&"." -> Convention du modèle, pas un barème de marché. Seuil de vigilance, plus bas que le plafond d'exclusion. Vérifié le 05/09/2026. | E31: Stable | F31: Au-delà, la vente reste retenue, mais elle ressemble déjà peu au bien. Un panel dont toutes les lignes dépassent ce seuil n'est pas un panel : cherchez d'autres ventes.
B32: Ajustement total maximal admis par comparable | C32: 0.25 | D32: ="Usage professionnel : un ajustement supérieur à 20 ou 25 % disqualifie la référence, et un panel résidentiel se construit sur au minimum cinq ventes homogènes et récentes (Real Group, méthode par comp"&"araison). Charte de l'expertise en évaluation immobilière, 6e édition de novembre 2025, § 2.1.4 et § 2.1.5. Vérifié le "&TEXT(DAY(Référentiel!$C$56),"00")&"/"&TEXT(MONTH(Référentiel!$C$56),"00")&"/"&YEAR(Référentiel!$C$56)&"." -> Usage professionnel : un ajustement supérieur à 20 ou 25 % disqualifie la référence, et un panel résidentiel se construit sur au minimum cinq ventes homogènes et récentes (Real Group, méthode par comparaison). Charte de l'expertise en évaluation immobilière, 6e édition de novembre 2025, § 2.1.4 et § 2.1.5. Vérifié le 05/09/2026. | E32: Stable | F32: Au-delà, le bien n'est pas comparable : la ligne est écartée et son statut le dit.
B33: Nombre minimal de comparables retenus | C33: 5 | D33: ="Usage professionnel : un ajustement supérieur à 20 ou 25 % disqualifie la référence, et un panel résidentiel se construit sur au minimum cinq ventes homogènes et récentes (Real Group, méthode par comp"&"araison). Charte de l'expertise en évaluation immobilière, 6e édition de novembre 2025, § 2.1.4 et § 2.1.5. Vérifié le "&TEXT(DAY(Référentiel!$C$56),"00")&"/"&TEXT(MONTH(Référentiel!$C$56),"00")&"/"&YEAR(Référentiel!$C$56)&"." -> Usage professionnel : un ajustement supérieur à 20 ou 25 % disqualifie la référence, et un panel résidentiel se construit sur au minimum cinq ventes homogènes et récentes (Real Group, méthode par comparaison). Charte de l'expertise en évaluation immobilière, 6e édition de novembre 2025, § 2.1.4 et § 2.1.5. Vérifié le 05/09/2026. | E33: Stable | F33: En dessous, aucune valeur n'est produite. Ce sont les comparables réellement retenus qui comptent, pas les lignes saisies.
B34: Poids maximal d'un comparable dans la moyenne | C34: 0.4 | D34: ="Convention du modèle, pas un barème de marché. Cohérent avec 5 comparables minimum : 20 % chacun à poids égaux. Vérifié le "&TEXT(DAY(Référentiel!$C$56),"00")&"/"&TEXT(MONTH(Référentiel!$C$56),"00")&"/"&YEAR(Référentiel!$C$56)&"." -> Convention du modèle, pas un barème de marché. Cohérent avec 5 comparables minimum : 20 % chacun à poids égaux. Vérifié le 05/09/2026. | E34: Stable | F34: Empêche qu'une seule vente fasse la valeur.
B35: Ancienneté maximale d'une vente comparable | C35: 24 | D35: ="Charte de l'expertise en évaluation immobilière, 6e édition, § 2.1.4 : l'expert apprécie l'antériorité des transactions et l'évolution du marché. Base DVF (data.gouv.fr), publication semestrielle avec"&" 3 à 4 mois de délai : la mise à jour du 7 avril 2026 couvre les ventes jusqu'au 31 décembre 2025. Vérifié le "&TEXT(DAY(Référentiel!$C$56),"00")&"/"&TEXT(MONTH(Référentiel!$C$56),"00")&"/"&YEAR(Référentiel!$C$56)&"." -> Charte de l'expertise en évaluation immobilière, 6e édition, § 2.1.4 : l'expert apprécie l'antériorité des transactions et l'évolution du marché. Base DVF (data.gouv.fr), publication semestrielle avec 3 à 4 mois de délai : la mise à jour du 7 avril 2026 couvre les ventes jusqu'au 31 décembre 2025. Vérifié le 05/09/2026. | E35: Stable | F35: Au-delà, la vente est écartée : une dérive linéaire appliquée sur une ancienneté pareille n'a plus de sens de marché. Resserrez à 12 mois sur un marché qui bouge vite.
B36: Nombre minimal de comparables pour mesurer une dispersion | C36: 3 | D36: ="Convention du modèle, pas un barème de marché. Vérifié le "&TEXT(DAY(Référentiel!$C$56),"00")&"/"&TEXT(MONTH(Référentiel!$C$56),"00")&"/"&YEAR(Référentiel!$C$56)&"." -> Convention du modèle, pas un barème de marché. Vérifié le 05/09/2026. | E36: Stable | F36: En dessous, l'écart type n'a pas de sens : le classeur le dit et bascule sur la demi-fourchette de repli, au lieu d'afficher une précision qu'il n'a pas.
B37: Demi-fourchette : plancher | C37: 0.03 | D37: ="Convention du modèle, pas un barème de marché. Vérifié le "&TEXT(DAY(Référentiel!$C$56),"00")&"/"&TEXT(MONTH(Référentiel!$C$56),"00")&"/"&YEAR(Référentiel!$C$56)&"." -> Convention du modèle, pas un barème de marché. Vérifié le 05/09/2026. | E37: Stable | F37: Des comparables presque identiques donneraient une fourchette quasi nulle : ce plancher évite d'afficher une fausse précision.
B38: Demi-fourchette de repli, échantillon trop faible | C38: 0.1 | D38: ="Convention du modèle, pas un barème de marché. Vérifié le "&TEXT(DAY(Référentiel!$C$56),"00")&"/"&TEXT(MONTH(Référentiel!$C$56),"00")&"/"&YEAR(Référentiel!$C$56)&"." -> Convention du modèle, pas un barème de marché. Vérifié le 05/09/2026. | E38: Stable | F38: Appliquée quand le nombre de comparables ne permet pas de mesurer la dispersion. Large à dessein : une fourchette étroite sur deux ventes ne se défend pas.
B39: Dispersion au-delà de laquelle le panel est jugé hétérogène | C39: 0.12 | D39: ="RICS, Comparable evidence in real estate valuation, 1re édition d'octobre 2019, norme professionnelle depuis avril 2023, § 7 : l'incertitude de l'évaluation doit être signalée (renvoi au Red Book, VPS"&" 3, 2.2 o). Charte de l'expertise, 6e édition, § 2.1.5 : la pertinence d'une référence diminue avec l'écart entre les caractéristiques des biens. Vérifié le "&TEXT(DAY(Référentiel!$C$56),"00")&"/"&TEXT(MONTH(Référentiel!$C$56),"00")&"/"&YEAR(Référentiel!$C$56)&"." -> RICS, Comparable evidence in real estate valuation, 1re édition d'octobre 2019, norme professionnelle depuis avril 2023, § 7 : l'incertitude de l'évaluation doit être signalée (renvoi au Red Book, VPS 3, 2.2 o). Charte de l'expertise, 6e édition, § 2.1.5 : la pertinence d'une référence diminue avec l'écart entre les caractéristiques des biens. Vérifié le 05/09/2026. | E39: Stable | F39: Coefficient de variation des prix au m² ajustés. Au-delà, le contrôle de dispersion passe au rouge : resserrez la sélection ou justifiez la largeur de la fourchette au dossier.
B40: Écart au prix au m² moyen au-delà duquel une ligne est signalée | C40: 0.35 | D40: ="Convention du modèle, pas un barème de marché. Seuil volontairement large : il attrape une saisie manifestement fausse, pas un écart de quelques points. Vérifié le "&TEXT(DAY(Référentiel!$C$56),"00")&"/"&TEXT(MONTH(Référentiel!$C$56),"00")&"/"&YEAR(Référentiel!$C$56)&"." -> Convention du modèle, pas un barème de marché. Seuil volontairement large : il attrape une saisie manifestement fausse, pas un écart de quelques points. Vérifié le 05/09/2026. | E40: Stable | F40: Contrôle de cohérence des prix saisis, avant tout ajustement. Il repère un prix tapé en milliers ou la surface d'un autre bien. Il ne détecte pas un prix honoraires comprises, qui n'ajoute que quelques points : contre celui-là, seule la consigne de saisie protège.
B41: Borne de saisie : étage le plus bas admis | C41: -2 | D41: ="Convention du modèle, pas un barème de marché. Vérifié le "&TEXT(DAY(Référentiel!$C$56),"00")&"/"&TEXT(MONTH(Référentiel!$C$56),"00")&"/"&YEAR(Référentiel!$C$56)&"." -> Convention du modèle, pas un barème de marché. Vérifié le 05/09/2026. | E41: Sans objet | F41: Deux niveaux de sous-sol. 0 pour un rez-de-chaussée.
B42: Borne de saisie : étage le plus haut admis | C42: 30 | D42: ="Convention du modèle, pas un barème de marché. Vérifié le "&TEXT(DAY(Référentiel!$C$56),"00")&"/"&TEXT(MONTH(Référentiel!$C$56),"00")&"/"&YEAR(Référentiel!$C$56)&"." -> Convention du modèle, pas un barème de marché. Vérifié le 05/09/2026. | E42: Sans objet
B43: Borne de saisie : similarité maximale | C43: 100 | D43: ="Convention du modèle, pas un barème de marché. Vérifié le "&TEXT(DAY(Référentiel!$C$56),"00")&"/"&TEXT(MONTH(Référentiel!$C$56),"00")&"/"&YEAR(Référentiel!$C$56)&"." -> Convention du modèle, pas un barème de marché. Vérifié le 05/09/2026. | E43: Sans objet | F43: La similarité se saisit de 0 à cette borne. Une similarité nulle vaut exclusion, et le statut de la ligne le dit.
B45: LISTES DÉROULANTES ET LIBELLÉS DE STATUT
B46: État (liste du bien et des comparables) | C46: Étiquette DPE (liste) | D46: Libellés de statut de ligne
B47: À rénover | C47: A | D47: Retenu | F47: L'ordre de la liste des états porte le calcul : un cran d'écart entre deux libellés voisins vaut le coefficient d'état ci-dessus.
B48: À rafraîchir | C48: B | D48: Écarté | F48: Les étiquettes DPE sont lues dans la grille de valeur verte : la lettre, jamais un rang.
B49: Bon | C49: C | D49: À compléter | F49: Les formules du tableau des comparables testent ces trois libellés : ne les modifiez pas sans relire l'onglet Méthode.
B50: Refait | C50: D
C51: E
C52: F
C53: G
B55: MILLÉSIME
B56: Dernière vérification du référentiel | C56: 46270 | D56: Aucun de ces coefficients n'est recopié dans une formule : toutes pointent ici. | E56: À chaque recalage | F56: Cette date s'affiche dans chaque libellé de source, ici et dans l'onglet Méthode : une seule cellule à changer.
B58: Ces valeurs sont volontairement isolées ici. Un modèle qui enfouit ses coefficients dans ses formules devient faux dès que le marché bouge, sans que personne ne s'en aperçoive.
B59: Un vendeur qui voit le référentiel discute le référentiel, pas votre honnêteté : c'est la raison d'être de cet onglet.
B61: CorpusImmo, millésime 2026. Modèle d'aide à la décision : ne constitue ni un conseil en investissement, ni un conseil fiscal, ni une expertise au sens de la charte de l'expertise en évaluation immobilière. Vérifiez les paramètres avant tout engagement.

Sheet Méthode
B1: CorpusImmo · www.corpus.immo · Estimer, comparer, décider. Sur les ventes réelles.
B2: Méthode de calcul
B3: Ce que le modèle fait, ce qu'il ne fait pas, et sur quelles sources reposent ses chiffres.
B5: CONVENTIONS RETENUES, ET CE QU'ELLES COÛTENT
B6: Sens des ajustements | C6: On corrige le comparable POUR LE RENDRE SEMBLABLE au bien évalué. Si le comparable est en meilleur état, son prix est tiré vers le bas ; s'il est moins bien situé dans l'immeuble, vers le haut. L'erreur classique est d'inverser le signe, ce qui double l'écart au lieu de l'annuler, d'où l'affichage explicite de l'ajustement en pourcentage signé.
B7: Étiquette DPE | C7: Le classeur ne raisonne plus par rang mais par étiquette, et lit l'écart de prix de chaque lettre dans la grille de valeur verte du Référentiel : l'ajustement vaut la prime de l'étiquette du bien moins celle du comparable. C'est ce qui permet de respecter la non-linéarité mesurée par les notaires, invisible dans un coefficient unique par lettre : entre A et D l'écart mesuré est de 16 points en appartement, entre D et G de 12 points, et de 25 points sur une maison. La grille dépend donc du type de bien saisi.
B8: Dérive du marché | C8: Une vente de dix mois ne vaut pas une vente d'un mois. La dérive se saisit sur un an dans le Référentiel, avec sa source, et le classeur la ramène au mois (division par 12) avant de l'appliquer à l'ancienneté de chaque vente. En marché baissier, elle est négative.
B9: Ancienneté d'une vente | C9: Nombre de jours entre la vente et la date de l'avis, divisé par 365,25 / 12, soit 30,44 jours par mois : la convention de l'année civile moyenne, bissextiles comprises. Au-delà de l'ancienneté maximale du Référentiel, aujourd'hui de 24 mois, la vente est écartée et son statut le dit : une dérive linéaire appliquée sur une durée pareille ne décrit plus un marché. La date de l'avis est aussi la borne haute : une vente postérieure à elle met la ligne à compléter et bloque la conclusion.
B10: Le prix saisi | C10: Le classeur attend, pour chaque vente, le prix net vendeur : le prix porté à l'acte, hors droits de mutation et hors honoraires d'agence. C'est celui que donne la base DVF. Un prix relevé sur une annonce est le plus souvent honoraires comprises, et un prix annoncé comme acte en main comprend les frais d'acquisition : les deux gonflent la ligne de l'ordre du repère inscrit dans le Référentiel. Ce que cela coûte : un panel qui mélange les deux conventions gonfle deux fois, la valeur et la dispersion qui fixe la fourchette. Le contrôle de cohérence des prix repère une ligne manifestement hors du panel, jamais un écart de quelques points : sur celui-là, seule la consigne de saisie protège.
B11: Pondération | C11: La similarité est saisie par vous, de 0 à 100. C'est le seul endroit où votre jugement entre, et c'est assumé : aucun algorithme ne sait qu'une des deux ventes s'est faite entre voisins.
B12: Ce qui exclut un comparable | C12: Trois familles de motifs, toutes nommées dans la colonne Statut de la ligne. Une saisie manquante ou hors bornes : la ligne est à compléter et le classeur refuse de conclure tant qu'elle est là. Un ajustement au-delà du plafond, ou une vente trop ancienne : la ligne est écartée, le calcul continue sans elle. Une similarité nulle : elle vaut exclusion, et c'est écrit plutôt que subi. Le compteur « Comparables retenus » ne compte que les lignes qui entrent réellement dans la moyenne.
B13: Les trois verrous | C13: Sous le nombre minimal de comparables retenus, aucune valeur n'est produite. Si un comparable pèse plus que le poids maximal du Référentiel, le modèle refuse également de conclure. Un comparable dont l'ajustement dépasse le plafond est écarté automatiquement. Les trois seuils vivent dans le Référentiel, et le classeur affiche le motif de son refus plutôt qu'un chiffre. Quatre messages peuvent ainsi remplacer la valeur centrale, dans l'ordre où ils se corrigent : Bien incomplet, Lignes à compléter, Trop peu de comparables, Un comparable domine.
B14: Ajustements additifs | C14: Les corrections s'additionnent puis s'appliquent en une fois au prix au m² : un total de -10 % signifie que le comparable est ramené à 90 % de son prix. Choix volontaire de lisibilité. Une composition multiplicative donnerait un résultat très proche sur des ajustements de cet ordre.
B15: Dispersion et fourchette | C15: La fourchette n'est pas une convention : elle est mesurée. Le classeur calcule l'écart type des prix au m² ajustés des comparables retenus, pondéré par la similarité, puis le corrige par la racine de n / (n - 1) parce qu'un écart type de population sous-estime la dispersion réelle quand l'échantillon est petit. Le coefficient de variation qui en découle devient la demi-fourchette, avec un plancher pour ne pas afficher une fausse précision sur des comparables presque identiques. Ce que cela coûte : la fourchette s'élargit quand le panel est hétérogène, et cela se voit. C'est le prix de l'honnêteté, et c'est ce qu'un contradicteur vous demandera de justifier.
B16: Échantillon trop faible | C16: En dessous du nombre minimal de comparables pour mesurer une dispersion, l'écart type n'a pas de sens statistique. Le classeur l'écrit et applique la demi-fourchette de repli du Référentiel, volontairement large. Une fourchette étroite calculée sur deux ventes ne se défend devant personne.
B17: Intégrité des dates | C17: Les dates de vente doivent être de vraies dates, pas du texte. Elles alimentent la dérive de marché et l'ancienneté. Une date non reconnue, une date vide ou une vente postérieure à la date de l'avis mettent la ligne à compléter, et le classeur refuse de conclure plutôt que d'appliquer une dérive nulle en silence.
... B22: Annexes | C22: Balcon, terrasse, cave et garage sont ramenés à un extérieur binaire. Les usages de pondération de surface existent mais ne sont ni normés ni stables d'un marché à l'autre : pondérez vos annexes avant de saisir la surface, et notez la règle que vous avez retenue.
B24: CE QUE CE MODÈLE NE FAIT PAS
B25: • Il ne remplace pas une visite. Aucune grille ne voit une vue, un vis-à-vis ou une nuisance.
B26: • Il ne traite pas les biens atypiques, pour lesquels la comparaison n'a pas de sens.
B27: • Il ne vaut rien sans comparables réels : des ventes inventées produisent une valeur inventée.
B28: • Il ne corrige pas les écarts de surface, alors que le prix au m² décroît avec la taille du bien.
B29: • Il n'intègre ni les charges de copropriété, ni les travaux votés, qui pèsent lourd sur un appartement.
B30: • Il suppose l'ascenseur des immeubles comparables identique à celui du bien évalué.
B31: • Il ne hiérarchise pas les sources : une vente signée, une offre et une annonce y pèsent pareil, alors que la norme professionnelle les classe. Plafonnez la similarité d'une simple annonce.
B32: • Ce n'est pas une expertise en évaluation immobilière : des investigations complètes auraient pu conduire à des conclusions sensiblement différentes.
B34: SOURCES (LUES DANS LE RÉFÉRENTIEL, COLONNE F POUR LA GRILLE DPE)
B35: Dérive du marché, sur un an | C35: =Référentiel!$D$9 -> INSEE, Informations rapides n° 130 du 28 mai 2026 (indice Notaires INSEE, 1er trimestre 2026) : plus 0,2 % sur le trimestre et plus 0,1 % sur un an, France entière, tous logements ; appartements plus 0,6 %, maisons moins 0,2 % ; Île-de-France plus 0,6 %, province 0 %. Vérifié le 05/09/2026.
B36: Écart d'un cran d'état | C36: =Référentiel!$D$23 -> Casavo, étude relayée par MySweetimmo le 7 avril 2025 (écarts mesurés sur les ventes 2024). Rénové contre non rénové : plus 9 % en France, plus 12,5 % à Paris, plus 13 % en Île-de-France, plus 5,8 % à Nantes. Vérifié le 05/09/2026.
B37: Écart d'un étage | C37: =Référentiel!$D$24 -> MeilleursAgents, relevé cité par SeLoger le 3 juin 2017 : environ plus 4 % entre le 2e et le 4e étage en province, soit 2 % par étage ; du rez-de-chaussée au dernier étage, 15 % en province et 19 % à Paris. Décote de rez-de-chaussée de 4 à 10 % selon Casavo 2025, non linéaire : elle se traite dans la similarité, pas par ce coefficient. Vérifié le 05/09/2026.
B38: Présence d'un extérieur | C38: =Référentiel!$D$25 -> Casavo, étude relayée par MySweetimmo le 7 avril 2025 (écarts mesurés sur les ventes 2024). Plus 6,3 % en Île-de-France, plus 7,2 % à Lyon, plus 8,5 % à Nantes, plus 12,1 % en Provence-Alpes-Côte d'Azur. Vérifié le 05/09/2026.
B39: Présence d'un stationnement | C39: =Référentiel!$D$26 -> Casavo, étude relayée par MySweetimmo le 7 avril 2025 (écarts mesurés sur les ventes 2024). Très variable selon la ville : de moins 18,2 % à Lyon à plus 18 % à Saint-Cloud, selon la tension sur le stationnement de surface. Vérifié le 05/09/2026.
B40: Écart entre un prix affiché et le prix net vendeur | C40: =Référentiel!$D$27 -> Droits de mutation à titre onéreux dans l'ancien : 6,32 % du prix dans 89 départements, 5,81 % dans 11, 5,09 % dans l'Indre (Notaires de France, 18/11/2025). Droit départemental porté de 4,50 % à 5 % par la loi de finances pour 2025, article 116, pour les actes reçus du 1er avril 2025 au 31 mars 2028 (CGI art. 1594 D) ; taxe communale de 1,20 % (art. 1584) ; frais d'assiette de 2,37 % du droit départemental (art. 1647 V), d'où 5 % × 1,0237 + 1,20 % = 6,32 %, et 4,50 % × 1,0237 + 1,20 % = 5,81 % dans les départements restés au taux de base et pour les primo-accédants achetant leur résidence principale. Émoluments et débours du notaire en sus. Les honoraires d'agence d'une vente de particulier se situent dans le même ordre de grandeur, sans barème public. Vérifié le 05/09/2026.
B41: Ajustement au-delà duquel un comparable est signalé comme éloigné | C41: =Référentiel!$D$31 -> Convention du modèle, pas un barème de marché. Seuil de vigilance, plus bas que le plafond d'exclusion. Vérifié le 05/09/2026.
B42: Ajustement total maximal admis par comparable | C42: =Référentiel!$D$32 -> Usage professionnel : un ajustement supérieur à 20 ou 25 % disqualifie la référence, et un panel résidentiel se construit sur au minimum cinq ventes homogènes et récentes (Real Group, méthode par comparaison). Charte de l'expertise en évaluation immobilière, 6e édition de novembre 2025, § 2.1.4 et § 2.1.5. Vérifié le 05/09/2026.
B43: Nombre minimal de comparables retenus | C43: =Référentiel!$D$33 -> Usage professionnel : un ajustement supérieur à 20 ou 25 % disqualifie la référence, et un panel résidentiel se construit sur au minimum cinq ventes homogènes et récentes (Real Group, méthode par comparaison). Charte de l'expertise en évaluation immobilière, 6e édition de novembre 2025, § 2.1.4 et § 2.1.5. Vérifié le 05/09/2026.
B44: Poids maximal d'un comparable dans la moyenne | C44: =Référentiel!$D$34 -> Convention du modèle, pas un barème de marché. Cohérent avec 5 comparables minimum : 20 % chacun à poids égaux. Vérifié le 05/09/2026.
B45: Ancienneté maximale d'une vente comparable | C45: =Référentiel!$D$35 -> Charte de l'expertise en évaluation immobilière, 6e édition, § 2.1.4 : l'expert apprécie l'antériorité des transactions et l'évolution du marché. Base DVF (data.gouv.fr), publication semestrielle avec 3 à 4 mois de délai : la mise à jour du 7 avril 2026 couvre les ventes jusqu'au 31 décembre 2025. Vérifié le 05/09/2026.
B46: Nombre minimal de comparables pour mesurer une dispersion | C46: =Référentiel!$D$36 -> Convention du modèle, pas un barème de marché. Vérifié le 05/09/2026.
B47: Demi-fourchette : plancher | C47: =Référentiel!$D$37 -> Convention du modèle, pas un barème de marché. Vérifié le 05/09/2026.
B48: Demi-fourchette de repli, échantillon trop faible | C48: =Référentiel!$D$38 -> Convention du modèle, pas un barème de marché. Vérifié le 05/09/2026.
B49: Dispersion au-delà de laquelle le panel est jugé hétérogène | C49: =Référentiel!$D$39 -> RICS, Comparable evidence in real estate valuation, 1re édition d'octobre 2019, norme professionnelle depuis avril 2023, § 7 : l'incertitude de l'évaluation doit être signalée (renvoi au Red Book, VPS 3, 2.2 o). Charte de l'expertise, 6e édition, § 2.1.5 : la pertinence d'une référence diminue avec l'écart entre les caractéristiques des biens. Vérifié le 05/09/2026.
B50: Écart au prix au m² moyen au-delà duquel une ligne est signalée | C50: =Référentiel!$D$40 -> Convention du modèle, pas un barème de marché. Seuil volontairement large : il attrape une saisie manifestement fausse, pas un écart de quelques points. Vérifié le 05/09/2026.
B51: Borne de saisie : étage le plus bas admis | C51: =Référentiel!$D$41 -> Convention du modèle, pas un barème de marché. Vérifié le 05/09/2026.
B52: Borne de saisie : étage le plus haut admis | C52: =Référentiel!$D$42 -> Convention du modèle, pas un barème de marché. Vérifié le 05/09/2026.
B53: Borne de saisie : similarité maximale | C53: =Référentiel!$D$43 -> Convention du modèle, pas un barème de marché. Vérifié le 05/09/2026.
B54: Valeur verte par étiquette DPE | C54: =Référentiel!$F$13 -> Notaires de France, bilan immobilier de décembre 2025 portant sur les transactions 2024 (valeur verte, écart de prix par rapport à une étiquette D). Appartements : mesuré. Maisons : interpolé sur la même forme, calée sur le G mesuré. Vérifié le 05/09/2026.
B55: Incertitude et fourchette | C55: RICS, Comparable evidence in real estate valuation, 1re édition d'octobre 2019, norme professionnelle depuis avril 2023, § 7 et § 4.6 (hiérarchie des preuves : transaction achevée, puis offre, puis indice) ; Red Book, VPS 3, 2.2 o.
B56: Mention obligatoire d'une estimation allégée | C56: Charte de l'expertise en évaluation immobilière, 6e édition de novembre 2025, page 32 : une estimation allégée est accompagnée d'une mention écrite précisant qu'il ne s'agit pas d'une expertise en évaluation immobilière et que des investigations complètes auraient pu conduire à des conclusions sensiblement différentes.
B58: CorpusImmo, millésime 2026. Modèle d'aide à la décision : ne constitue ni un conseil en investissement, ni un conseil fiscal, ni une expertise au sens de la charte de l'expertise en évaluation immobilière. Vérifiez les paramètres avant tout engagement.
