Workbook

Sheet Bilan
B1: CorpusImmo · www.corpus.immo · Estimer, comparer, décider. Sur les ventes réelles.
B2: Bilan promoteur
B3: Du prix de vente à la charge foncière admissible : la question posée dans le bon sens.
B5: Cellules violettes : à remplir. Cellules blanches : calculées automatiquement.
B7: LE PROGRAMME | E7: LA CASCADE
B8: Surface de plancher constructible | C8: 2400 | D8: Issue du PLU : emprise × hauteur × COS résiduel. | E8: Travaux (construction + VRD) | F8: =$C$8*$C$17+$C$18
B9: Surface habitable vendable | C9: 2040 | D9: Environ 85 % de la surface de plancher. | E9: Honoraires techniques | F9: =$F$8*$C$19/100
B10: Nombre de logements | C10: 32 | E10: Assurances et garanties | F10: =$F$8*$C$20/100
B11: Prix de vente moyen TTC | C11: 4200 | D11: Au m² habitable. Le paramètre le plus sensible. | E11: Aléas | F11: =$F$8*$C$25/100
B12: Parkings vendus | C12: 28 | E12: Taxes et raccordements | F12: =$C$21
B13: Prix de vente d'un parking | C13: 18000 | E13: Coût technique total | F13: =$F$8+$F$9+$F$10+$F$11+$C$21
B14: Chiffre d'affaires TTC | C14: =$C$9*$C$11+$C$12*$C$13 | E14: Commercialisation | F14: =$C$14*$C$22/100
E15: Frais financiers | F15: =$C$14*$C$23/100
B16: LES COÛTS | E16: Frais de structure | F16: =$C$14*$C$24/100
B17: Coût de construction | C17: 1950 | D17: Au m² de surface de plancher, tous corps d'état. | E17: Coûts hors foncier | F17: =$F$13+$F$14+$F$15+$F$16
B18: VRD, espaces verts et fondations spéciales | C18: 180000
B19: Honoraires techniques | C19: 12 | D19: Architecte, BET, contrôle, OPC, en % du coût de construction. | E19: LA MARGE VISÉE
B20: Assurances et garanties | C20: 2.5 | D20: Dommage-ouvrage, GFA, RC, en % du coût de construction. | E20: Marge cible sur chiffre d'affaires | F20: 8 | G20: 6 à 10 % en logement libre. En dessous de 6 %, aucun financeur ne suit.
B21: Taxes d'aménagement et raccordements | C21: 95000 | E21: Marge en valeur | F21: =$C$14*$F$20/100
B22: Frais de commercialisation | C22: 4.5 | D22: En % du chiffre d'affaires TTC. | E22: CHARGE FONCIÈRE ADMISSIBLE | F22: =$C$14-$F$17-$F$21 | G22: Le prix maximal du terrain, frais d'acquisition inclus.
B23: Frais financiers | C23: 3 | D23: En % du chiffre d'affaires. Portage sur 24 à 30 mois. | E23: Charge foncière au m² de plancher | F23: =IFERROR($F$22/$C$8,0)
B24: Frais de structure du promoteur | C24: 5 | D24: En % du chiffre d'affaires. | E24: Charge foncière en % du chiffre d'affaires | F24: =IFERROR($F$22/$C$14*100,0) | G24: 12 à 20 % en zone détendue, 25 à 35 % en zone tendue.
B25: Aléas et imprévus | C25: 3 | D25: En % du coût de construction. Jamais zéro.
E26: CONTRE-ÉPREUVE
E27: Prix du terrain réellement demandé | F27: 1250000
E28: Marge résultante en valeur | F28: =$C$14-$F$17-$F$27
E29: Marge résultante en % du CA | F29: =IFERROR($F$28/$C$14*100,0)
E30: Écart au prix admissible | F30: =$F$27-$F$22 | G30: Positif : le terrain est trop cher pour la marge visée.
B32: RÉSULTAT
B33: =$F$22 | E33: =$F$29
B36: Charge foncière admissible | E36: Marge au prix de terrain demandé
B39: CorpusImmo, millésime 2026. Modèle d'aide à la décision : ne constitue ni un conseil en investissement, ni un conseil fiscal. Vérifiez les paramètres avant tout engagement.

Sheet Sensibilité
B1: CorpusImmo · www.corpus.immo · Estimer, comparer, décider. Sur les ventes réelles.
B2: Sensibilité de la charge foncière
B3: Prix de vente en lignes, coût de construction en colonnes.
B5: Deux variables font basculer une opération de promotion : le prix auquel on vendra, et le prix auquel on construira. Tout le reste est du second ordre. Cette matrice montre ce que vaut le terrain dans vingt-cinq scénarios, à marge cible constante. Si la charge foncière devient négative dans un coin du tableau, l'opération y est structurellement perdante.
B9: Vente ╲ Construction | C9: =Bilan!$C$17+-150 | D9: =Bilan!$C$17+-75 | E9: =Bilan!$C$17+0 | F9: =Bilan!$C$17+75 | G9: =Bilan!$C$17+150
B10: =Bilan!$C$11+-200 | C10: =IFERROR((Bilan!$C$9*$B10+Bilan!$C$12*Bilan!$C$13)-((Bilan!$C$8*C$9+Bilan!$C$18)*(1+Bilan!$C$19/100+Bilan!$C$20/100+Bilan!$C$25/100)+Bilan!$C$21+(Bilan!$C$9*$B10+Bilan!$C$12*Bilan!$C$13)*(Bilan!$C$22+Bilan!$C$23+Bilan!$C$24)/100)-(Bilan!$C$9*$B10+Bilan!$C$12*Bilan!$C$13)*Bilan!$F$20/100,0) | D10: =IFERROR((Bilan!$C$9*$B10+Bilan!$C$12*Bilan!$C$13)-((Bilan!$C$8*D$9+Bilan!$C$18)*(1+Bilan!$C$19/100+Bilan!$C$20/100+Bilan!$C$25/100)+Bilan!$C$21+(Bilan!$C$9*$B10+Bilan!$C$12*Bilan!$C$13)*(Bilan!$C$22+Bilan!$C$23+Bilan!$C$24)/100)-(Bilan!$C$9*$B10+Bilan!$C$12*Bilan!$C$13)*Bilan!$F$20/100,0) | E10: =IFERROR((Bilan!$C$9*$B10+Bilan!$C$12*Bilan!$C$13)-((Bilan!$C$8*E$9+Bilan!$C$18)*(1+Bilan!$C$19/100+Bilan!$C$20/100+Bilan!$C$25/100)+Bilan!$C$21+(Bilan!$C$9*$B10+Bilan!$C$12*Bilan!$C$13)*(Bilan!$C$22+Bilan!$C$23+Bilan!$C$24)/100)-(Bilan!$C$9*$B10+Bilan!$C$12*Bilan!$C$13)*Bilan!$F$20/100,0) | F10: =IFERROR((Bilan!$C$9*$B10+Bilan!$C$12*Bilan!$C$13)-((Bilan!$C$8*F$9+Bilan!$C$18)*(1+Bilan!$C$19/100+Bilan!$C$20/100+Bilan!$C$25/100)+Bilan!$C$21+(Bilan!$C$9*$B10+Bilan!$C$12*Bilan!$C$13)*(Bilan!$C$22+Bilan!$C$23+Bilan!$C$24)/100)-(Bilan!$C$9*$B10+Bilan!$C$12*Bilan!$C$13)*Bilan!$F$20/100,0) | G10: =IFERROR((Bilan!$C$9*$B10+Bilan!$C$12*Bilan!$C$13)-((Bilan!$C$8*G$9+Bilan!$C$18)*(1+Bilan!$C$19/100+Bilan!$C$20/100+Bilan!$C$25/100)+Bilan!$C$21+(Bilan!$C$9*$B10+Bilan!$C$12*Bilan!$C$13)*(Bilan!$C$22+Bilan!$C$23+Bilan!$C$24)/100)-(Bilan!$C$9*$B10+Bilan!$C$12*Bilan!$C$13)*Bilan!$F$20/100,0)
B11: =Bilan!$C$11+-100 | C11: =IFERROR((Bilan!$C$9*$B11+Bilan!$C$12*Bilan!$C$13)-((Bilan!$C$8*C$9+Bilan!$C$18)*(1+Bilan!$C$19/100+Bilan!$C$20/100+Bilan!$C$25/100)+Bilan!$C$21+(Bilan!$C$9*$B11+Bilan!$C$12*Bilan!$C$13)*(Bilan!$C$22+Bilan!$C$23+Bilan!$C$24)/100)-(Bilan!$C$9*$B11+Bilan!$C$12*Bilan!$C$13)*Bilan!$F$20/100,0) | D11: =IFERROR((Bilan!$C$9*$B11+Bilan!$C$12*Bilan!$C$13)-((Bilan!$C$8*D$9+Bilan!$C$18)*(1+Bilan!$C$19/100+Bilan!$C$20/100+Bilan!$C$25/100)+Bilan!$C$21+(Bilan!$C$9*$B11+Bilan!$C$12*Bilan!$C$13)*(Bilan!$C$22+Bilan!$C$23+Bilan!$C$24)/100)-(Bilan!$C$9*$B11+Bilan!$C$12*Bilan!$C$13)*Bilan!$F$20/100,0) | E11: =IFERROR((Bilan!$C$9*$B11+Bilan!$C$12*Bilan!$C$13)-((Bilan!$C$8*E$9+Bilan!$C$18)*(1+Bilan!$C$19/100+Bilan!$C$20/100+Bilan!$C$25/100)+Bilan!$C$21+(Bilan!$C$9*$B11+Bilan!$C$12*Bilan!$C$13)*(Bilan!$C$22+Bilan!$C$23+Bilan!$C$24)/100)-(Bilan!$C$9*$B11+Bilan!$C$12*Bilan!$C$13)*Bilan!$F$20/100,0) | F11: =IFERROR((Bilan!$C$9*$B11+Bilan!$C$12*Bilan!$C$13)-((Bilan!$C$8*F$9+Bilan!$C$18)*(1+Bilan!$C$19/100+Bilan!$C$20/100+Bilan!$C$25/100)+Bilan!$C$21+(Bilan!$C$9*$B11+Bilan!$C$12*Bilan!$C$13)*(Bilan!$C$22+Bilan!$C$23+Bilan!$C$24)/100)-(Bilan!$C$9*$B11+Bilan!$C$12*Bilan!$C$13)*Bilan!$F$20/100,0) | G11: =IFERROR((Bilan!$C$9*$B11+Bilan!$C$12*Bilan!$C$13)-((Bilan!$C$8*G$9+Bilan!$C$18)*(1+Bilan!$C$19/100+Bilan!$C$20/100+Bilan!$C$25/100)+Bilan!$C$21+(Bilan!$C$9*$B11+Bilan!$C$12*Bilan!$C$13)*(Bilan!$C$22+Bilan!$C$23+Bilan!$C$24)/100)-(Bilan!$C$9*$B11+Bilan!$C$12*Bilan!$C$13)*Bilan!$F$20/100,0)
B12: =Bilan!$C$11+0 | C12: =IFERROR((Bilan!$C$9*$B12+Bilan!$C$12*Bilan!$C$13)-((Bilan!$C$8*C$9+Bilan!$C$18)*(1+Bilan!$C$19/100+Bilan!$C$20/100+Bilan!$C$25/100)+Bilan!$C$21+(Bilan!$C$9*$B12+Bilan!$C$12*Bilan!$C$13)*(Bilan!$C$22+Bilan!$C$23+Bilan!$C$24)/100)-(Bilan!$C$9*$B12+Bilan!$C$12*Bilan!$C$13)*Bilan!$F$20/100,0) | D12: =IFERROR((Bilan!$C$9*$B12+Bilan!$C$12*Bilan!$C$13)-((Bilan!$C$8*D$9+Bilan!$C$18)*(1+Bilan!$C$19/100+Bilan!$C$20/100+Bilan!$C$25/100)+Bilan!$C$21+(Bilan!$C$9*$B12+Bilan!$C$12*Bilan!$C$13)*(Bilan!$C$22+Bilan!$C$23+Bilan!$C$24)/100)-(Bilan!$C$9*$B12+Bilan!$C$12*Bilan!$C$13)*Bilan!$F$20/100,0) | E12: =IFERROR((Bilan!$C$9*$B12+Bilan!$C$12*Bilan!$C$13)-((Bilan!$C$8*E$9+Bilan!$C$18)*(1+Bilan!$C$19/100+Bilan!$C$20/100+Bilan!$C$25/100)+Bilan!$C$21+(Bilan!$C$9*$B12+Bilan!$C$12*Bilan!$C$13)*(Bilan!$C$22+Bilan!$C$23+Bilan!$C$24)/100)-(Bilan!$C$9*$B12+Bilan!$C$12*Bilan!$C$13)*Bilan!$F$20/100,0) | F12: =IFERROR((Bilan!$C$9*$B12+Bilan!$C$12*Bilan!$C$13)-((Bilan!$C$8*F$9+Bilan!$C$18)*(1+Bilan!$C$19/100+Bilan!$C$20/100+Bilan!$C$25/100)+Bilan!$C$21+(Bilan!$C$9*$B12+Bilan!$C$12*Bilan!$C$13)*(Bilan!$C$22+Bilan!$C$23+Bilan!$C$24)/100)-(Bilan!$C$9*$B12+Bilan!$C$12*Bilan!$C$13)*Bilan!$F$20/100,0) | G12: =IFERROR((Bilan!$C$9*$B12+Bilan!$C$12*Bilan!$C$13)-((Bilan!$C$8*G$9+Bilan!$C$18)*(1+Bilan!$C$19/100+Bilan!$C$20/100+Bilan!$C$25/100)+Bilan!$C$21+(Bilan!$C$9*$B12+Bilan!$C$12*Bilan!$C$13)*(Bilan!$C$22+Bilan!$C$23+Bilan!$C$24)/100)-(Bilan!$C$9*$B12+Bilan!$C$12*Bilan!$C$13)*Bilan!$F$20/100,0)
B13: =Bilan!$C$11+100 | C13: =IFERROR((Bilan!$C$9*$B13+Bilan!$C$12*Bilan!$C$13)-((Bilan!$C$8*C$9+Bilan!$C$18)*(1+Bilan!$C$19/100+Bilan!$C$20/100+Bilan!$C$25/100)+Bilan!$C$21+(Bilan!$C$9*$B13+Bilan!$C$12*Bilan!$C$13)*(Bilan!$C$22+Bilan!$C$23+Bilan!$C$24)/100)-(Bilan!$C$9*$B13+Bilan!$C$12*Bilan!$C$13)*Bilan!$F$20/100,0) | D13: =IFERROR((Bilan!$C$9*$B13+Bilan!$C$12*Bilan!$C$13)-((Bilan!$C$8*D$9+Bilan!$C$18)*(1+Bilan!$C$19/100+Bilan!$C$20/100+Bilan!$C$25/100)+Bilan!$C$21+(Bilan!$C$9*$B13+Bilan!$C$12*Bilan!$C$13)*(Bilan!$C$22+Bilan!$C$23+Bilan!$C$24)/100)-(Bilan!$C$9*$B13+Bilan!$C$12*Bilan!$C$13)*Bilan!$F$20/100,0) | E13: =IFERROR((Bilan!$C$9*$B13+Bilan!$C$12*Bilan!$C$13)-((Bilan!$C$8*E$9+Bilan!$C$18)*(1+Bilan!$C$19/100+Bilan!$C$20/100+Bilan!$C$25/100)+Bilan!$C$21+(Bilan!$C$9*$B13+Bilan!$C$12*Bilan!$C$13)*(Bilan!$C$22+Bilan!$C$23+Bilan!$C$24)/100)-(Bilan!$C$9*$B13+Bilan!$C$12*Bilan!$C$13)*Bilan!$F$20/100,0) | F13: =IFERROR((Bilan!$C$9*$B13+Bilan!$C$12*Bilan!$C$13)-((Bilan!$C$8*F$9+Bilan!$C$18)*(1+Bilan!$C$19/100+Bilan!$C$20/100+Bilan!$C$25/100)+Bilan!$C$21+(Bilan!$C$9*$B13+Bilan!$C$12*Bilan!$C$13)*(Bilan!$C$22+Bilan!$C$23+Bilan!$C$24)/100)-(Bilan!$C$9*$B13+Bilan!$C$12*Bilan!$C$13)*Bilan!$F$20/100,0) | G13: =IFERROR((Bilan!$C$9*$B13+Bilan!$C$12*Bilan!$C$13)-((Bilan!$C$8*G$9+Bilan!$C$18)*(1+Bilan!$C$19/100+Bilan!$C$20/100+Bilan!$C$25/100)+Bilan!$C$21+(Bilan!$C$9*$B13+Bilan!$C$12*Bilan!$C$13)*(Bilan!$C$22+Bilan!$C$23+Bilan!$C$24)/100)-(Bilan!$C$9*$B13+Bilan!$C$12*Bilan!$C$13)*Bilan!$F$20/100,0)
B14: =Bilan!$C$11+200 | C14: =IFERROR((Bilan!$C$9*$B14+Bilan!$C$12*Bilan!$C$13)-((Bilan!$C$8*C$9+Bilan!$C$18)*(1+Bilan!$C$19/100+Bilan!$C$20/100+Bilan!$C$25/100)+Bilan!$C$21+(Bilan!$C$9*$B14+Bilan!$C$12*Bilan!$C$13)*(Bilan!$C$22+Bilan!$C$23+Bilan!$C$24)/100)-(Bilan!$C$9*$B14+Bilan!$C$12*Bilan!$C$13)*Bilan!$F$20/100,0) | D14: =IFERROR((Bilan!$C$9*$B14+Bilan!$C$12*Bilan!$C$13)-((Bilan!$C$8*D$9+Bilan!$C$18)*(1+Bilan!$C$19/100+Bilan!$C$20/100+Bilan!$C$25/100)+Bilan!$C$21+(Bilan!$C$9*$B14+Bilan!$C$12*Bilan!$C$13)*(Bilan!$C$22+Bilan!$C$23+Bilan!$C$24)/100)-(Bilan!$C$9*$B14+Bilan!$C$12*Bilan!$C$13)*Bilan!$F$20/100,0) | E14: =IFERROR((Bilan!$C$9*$B14+Bilan!$C$12*Bilan!$C$13)-((Bilan!$C$8*E$9+Bilan!$C$18)*(1+Bilan!$C$19/100+Bilan!$C$20/100+Bilan!$C$25/100)+Bilan!$C$21+(Bilan!$C$9*$B14+Bilan!$C$12*Bilan!$C$13)*(Bilan!$C$22+Bilan!$C$23+Bilan!$C$24)/100)-(Bilan!$C$9*$B14+Bilan!$C$12*Bilan!$C$13)*Bilan!$F$20/100,0) | F14: =IFERROR((Bilan!$C$9*$B14+Bilan!$C$12*Bilan!$C$13)-((Bilan!$C$8*F$9+Bilan!$C$18)*(1+Bilan!$C$19/100+Bilan!$C$20/100+Bilan!$C$25/100)+Bilan!$C$21+(Bilan!$C$9*$B14+Bilan!$C$12*Bilan!$C$13)*(Bilan!$C$22+Bilan!$C$23+Bilan!$C$24)/100)-(Bilan!$C$9*$B14+Bilan!$C$12*Bilan!$C$13)*Bilan!$F$20/100,0) | G14: =IFERROR((Bilan!$C$9*$B14+Bilan!$C$12*Bilan!$C$13)-((Bilan!$C$8*G$9+Bilan!$C$18)*(1+Bilan!$C$19/100+Bilan!$C$20/100+Bilan!$C$25/100)+Bilan!$C$21+(Bilan!$C$9*$B14+Bilan!$C$12*Bilan!$C$13)*(Bilan!$C$22+Bilan!$C$23+Bilan!$C$24)/100)-(Bilan!$C$9*$B14+Bilan!$C$12*Bilan!$C$13)*Bilan!$F$20/100,0)
B16: CorpusImmo, millésime 2026. Modèle d'aide à la décision : ne constitue ni un conseil en investissement, ni un conseil fiscal. Vérifiez les paramètres avant tout engagement.

Sheet Méthode
B1: CorpusImmo · www.corpus.immo · Estimer, comparer, décider. Sur les ventes réelles.
B2: Méthode et limites
B3: La logique du bilan promoteur, en clair.
B5: Le sens du calcul | C5: Chiffre d'affaires − coûts hors foncier − marge cible = charge foncière admissible. On ne cherche pas la marge d'un prix de terrain donné : on cherche le prix de terrain qui produit la marge exigée. C'est ainsi qu'un promoteur formule une offre.
B6: Charge foncière | C6: Elle inclut le prix du terrain ET les frais d'acquisition (droits, commission, honoraires de montage). Un vendeur qui compare une offre à sa valeur « nette vendeur » doit donc retrancher ces frais.
B7: Coûts hors foncier | C7: Travaux et VRD, majorés des honoraires techniques, assurances et aléas ; puis les frais assis sur le chiffre d'affaires : commercialisation, frais financiers, structure. Les trois derniers sont proportionnels au CA, pas aux travaux : c'est la convention du métier.
B8: Marge cible | C8: 6 à 10 % du chiffre d'affaires TTC en logement libre. En dessous de 6 %, ni la banque ni le comité d'engagement ne suivent, car la marge ne couvre plus le risque de dérive des travaux.
B9: Contre-épreuve | C9: Le bloc du bas fait le calcul dans l'autre sens à partir du prix réellement demandé. C'est l'outil de négociation : il chiffre exactement de combien le vendeur doit bouger.
B11: CE QUE CE MODÈLE NE FAIT PAS
B12: · Il ne modélise pas la TVA sur marge ni la TVA à taux réduit, trop dépendantes du montage et du régime.
B13: · Il ignore le phasage et l'échéancier d'appels de fonds, donc le besoin en fonds propres réel.
B14: · Il ne traite ni la vente en bloc à un bailleur social, ni la VEFA inversée, qui changent le CA et le risque.
B15: · Il suppose la commercialisation intégrale : aucun stock résiduel, aucune décote de fin de programme.
B16: · Il ne vérifie ni la faisabilité réglementaire, ni les servitudes, ni la dépollution, trois tueurs d'opération.
B18: CorpusImmo, millésime 2026. Modèle d'aide à la décision : ne constitue ni un conseil en investissement, ni un conseil fiscal. Vérifiez les paramètres avant tout engagement.
