Workbook

Sheet Mode d'emploi
B1: CorpusImmo · www.corpus.immo · Estimer, comparer, décider. Sur les ventes réelles.
B2: Mode d'emploi
B3: À quoi sert ce classeur, dans quel ordre le remplir, et comment lire ce qu'il répond.
B6: À QUOI SERT CE CLASSEUR
B7: Vous regardez un appartement ou une maison à louer. Ce classeur répond à la question que tout investisseur se pose avant de signer : une fois payés les charges, l'impôt et le crédit, combien ce bien me rapporte, ou combien il me coûte, chaque mois ?
B8: Il calcule le coût complet de l'achat, le loyer réellement encaissé, la mensualité du prêt, l'impôt de la première année selon cinq régimes fiscaux (location nue au micro-foncier ou au réel, meublé au micro-BIC ou au LMNP réel avec amortissement, meublé de tourisme non classé), puis trois rendements et le cash-flow mensuel après impôt.
B9: Tout tient sur un seul onglet de saisie. Le classeur est livré avec un exemple déjà saisi : pour votre dossier, remplacez toutes les cellules violettes, y compris celles qui ne vous concernent pas (mettez 0 : mobilier en location nue, comptable sans expert-comptable, travaux déductibles sans travaux). Le reste se calcule.
B10: Vous êtes | C10: Ce que le classeur vous donne
B11: Investisseur particulier | C11: Le cash-flow mensuel réel après impôt et l'effort d'épargne à prévoir, avant de faire une offre.
B12: Conseiller en gestion de patrimoine | C12: La comparaison des cinq régimes fiscaux sur le même bien, en changeant une seule cellule.
B13: Agent immobilier, chasseur | C13: Le rendement net-net à présenter à un acquéreur investisseur, à côté du rendement brut de l'annonce.
B14: Courtier, banquier | C14: La mensualité totale assurance comprise et la part du loyer qu'elle absorbe.
B15: Expert-comptable, fiscaliste | C15: La base imposable de l'année 1 avec le détail : intérêts, assurance, travaux déductibles, déficit imputé, amortissement reporté.
B17: LE PRINCIPE, EN UNE LIGNE
B18: Loyer encaissé − charges − impôt − mensualités du prêt = ce qui reste (ou ce qu'il faut sortir) chaque mois
B20: LES ONGLETS, DANS L'ORDRE OÙ ON LES REMPLIT
B21: Onglet | C21: Ce que vous y faites | D21: Ce que vous y lisez
B22: Mode d'emploi | C22: Rien à saisir. Vous lisez ce guide. | D22: La marche à suivre et l'exemple guidé.
B23: Calculateur | C23: Vous remplissez les cinq blocs de saisie, de haut en bas : le bien, les revenus, les charges, le financement, la fiscalité. | D23: Les résultats de l'année 1 en bas de l'onglet : rendements, cash-flow, effort d'épargne, et quatre contrôles OK / À CORRIGER.
B24: Paramètres | C24: Rien, sauf à la mise à jour annuelle des barèmes (prélèvements sociaux, abattements, plafonds), des repères de marché et de la date de vérification. | D24: Chaque valeur avec sa source, sa fréquence de mise à jour, et la date de dernière vérification.
B25: Méthode | C25: Rien à saisir. | D25: Les conventions de calcul, ce que le modèle ne fait pas, les sources.
B27: LE CODE COULEUR, ET COMMENT DÉVERROUILLER UNE CELLULE
B28: Cellule | C28: Ce que c'est | D28: Ce que vous faites
B29: Fond violet clair | C29: Saisie utilisateur | D29: Vous la remplissez. Jamais de formule dedans.
B30: Fond blanc | C30: Calcul | D30: Vous la lisez. Elle est verrouillée.
B31: Fond violet pâle, gras | C31: Résultat de bloc, chiffre clé | D31: Vous la lisez. C'est un chiffre à retenir.
B32: Bandeau violet | C32: Titre de section | D32: Repère de navigation.
B33: Texte gris, à droite | C33: Commentaire d'aide, ordre de grandeur | D33: Une phrase par ligne pour savoir quoi saisir. Les ordres de grandeur y sont lus dans Paramètres.
B34: Cellule violette qui affiche un % | C34: Taux | D34: Tapez le nombre tel qu'il se lit (7 pour 7 %), puis vérifiez l'affichage.
B35: Vert OK / rouge À CORRIGER | C35: Contrôle de cohérence | D35: Rouge : corrigez la saisie indiquée dans le commentaire.
B36: Les onglets sont protégés sans mot de passe pour éviter d'écraser une formule par erreur. En usage normal, vous n'en avez jamais besoin : toutes les cellules violettes sont déjà libres. Pour modifier une cellule blanche ou un texte de source : onglet Révision, puis « Ôter la protection de la feuille ». Aucun mot de passe n'est demandé.
B38: LA MARCHE À SUIVRE, ÉTAPE PAR ÉTAPE
B39: Étape | C39: Où (onglet et plage) | D39: Ce que vous faites | E39: Pourquoi
B40: 0. L'exemple livré | C40: Calculateur, toutes les cellules violettes | D40: Le classeur arrive rempli d'un exemple (appartement de 72 m² loué meublé). Gardez-le pour vous repérer, ou effacez toutes les cellules violettes avant de saisir votre dossier. Vérifiez surtout les saisies secondaires qui n'ont pas de raison d'être dans votre cas : mobilier (C11), comptabilité (C26), travaux déductibles (C49), part du terrain (C50). | E40: Une valeur de l'exemple oubliée est l'erreur la plus probable d'un premier usage. Le contrôle C60 signale les incohérences (travaux déductibles supérieurs aux travaux), pas les oublis plausibles.
B41: 1. Le bien | C41: Calculateur!C7:C12 | D41: Prix net vendeur, honoraires d'agence, frais de notaire (repère dans Paramètres : environ 8,0 % du prix net vendeur dans l'ancien, 2,5 % dans le neuf ; prenez le chiffre du simulateur de votre notaire si vous l'avez), travaux, mobilier (0 en location nue), surface habitable. | E41: Le coût total de l'opération est le dénominateur de tous les rendements. Un rendement calculé sur le seul prix d'achat est flatteur de 10 à 15 %.
B42: 2. Les revenus | C42: Calculateur!C17:C18 | D42: Loyer mensuel hors charges et vacance locative en semaines par an (0 à 52). | E42: Le classeur raisonne sur le loyer réellement encaissé, pas sur le loyer théorique.
B43: 3. Les charges | C43: Calculateur!C23:C28 | D43: Taxe foncière hors TEOM, assurance PNO, copropriété non récupérable, comptabilité (0 sans expert-comptable, le cas courant en location nue), provision d'entretien, gestion locative en pourcentage du loyer. | E43: Ce sont les charges qui restent au bailleur. La provision compte dans le cash-flow, pas dans l'impôt.
B44: 4. Le financement | C44: Calculateur!C33:C36 | D44: Apport : le montant emprunté se déduit en C37 (coût total moins apport) ; si vous partez du prêt proposé par la banque, saisissez en apport la différence entre C13 et ce prêt. Taux nominal du prêt (tapez 3,4 pour 3,40 %). Durée en années entières. Taux d'assurance : celui du contrat de la banque, calculé sur le capital emprunté ; en délégation, tapez le taux annoncé, le classeur sera un peu prudent. Vérifiez que C43 et C44 affichent OK. | E44: La mensualité totale et les intérêts de la première année alimentent le cash-flow et la base imposable au réel.
B45: 5. La fiscalité | C45: Calculateur!C47:C50 | D45: Régime dans la liste. TMI dans la liste : la tranche marginale d'imposition, c'est le taux de la tranche la plus haute de votre foyer (0, 11, 30, 41 ou 45 %) ; elle figure sur l'avis d'impôt, ligne « taux marginal d'imposition » ; en cas de doute, 30 % pour un salarié cadre seul, 11 % pour un couple avec deux revenus moyens. Travaux déductibles au réel foncier : la part d'entretien, de réparation et d'amélioration des travaux ; sans travaux, tapez 0 en C49, le fichier est livré avec 20 000 €, et C49 ne doit jamais dépasser C10. Part du terrain : sans effet hors LMNP réel, laissez la valeur. Vérifiez que C51 affiche OK. | E45: Le régime et la TMI font varier l'impôt de zéro à plusieurs milliers d'euros sur le même bien. Les plafonds des régimes micro sont contrôlés.
B46: 6. Les résultats | C46: Calculateur!C60:C68 | D46: Rien à saisir. Vérifiez d'abord que C60 affiche OK, puis lisez les rendements et le cash-flow. | E46: Tant qu'un contrôle est rouge, les résultats fiscaux restent vides : le classeur préfère ne rien afficher plutôt qu'un chiffre faux.
B47: 7. Les barèmes et repères | C47: Paramètres!C8:C17, C21:C34, C38:C42 et C46:C50 | D47: Une fois par an, comparez chaque valeur violette à sa source (colonne D) et mettez à jour la date en C52 : les mentions « Vérifié le » de Paramètres et de Méthode suivent automatiquement. Si une source change (nouveau texte de loi, nouvelle publication), modifiez son texte en colonne D de Paramètres (cellule verrouillée : Révision, Ôter la protection) ; Méthode le recopie. | E47: Un barème périmé fausse l'impôt sans prévenir. Toutes les formules pointent ici, commentaires d'aide compris.
B49: EXEMPLE GUIDÉ
B50: Le fichier est livré avec un appartement ancien de 72 m² acheté 90 000 € net vendeur, 9 200 € d'honoraires d'agence, 7 500 € de frais de notaire, 20 000 € de travaux et 3 000 € de mobilier : coût total 129 700 € (C13), soit 1 801 € par m². Loué meublé 950 € hors charges avec 3 semaines de vacance par an, il encaisse 10 742 € par an (C19).
B51: Les charges annuelles atteignent 2 580 € (C29) : taxe foncière 900 €, PNO 180 €, copropriété 600 €, comptable 400 €, provision d'entretien 500 €, pas de gestion déléguée. Le revenu net de charges ressort à 8 162 € (C30).
B52: Financement : 5 000 € d'apport, 124 700 € empruntés sur 22 ans à 3,40 % plus 0,34 % d'assurance. Mensualité totale 706,80 € (C40), dont 671,47 € de crédit et 35,33 € d'assurance. Intérêts de la première année : 4 180 € (C41). La mensualité absorbe 74,4 % du loyer (C68).
B53: Fiscalité : régime « Meublé, LMNP réel (amortissement) », TMI 30 %. L'amortissement annuel ressort à 4 785 € (C52) : bâti hors terrain (15 %) sur 30 ans, travaux sur 15 ans, mobilier sur 7 ans. Loyer encaissé moins charges déductibles, intérêts, assurance et amortissement : −726 € (C53), un résultat négatif. La base imposable est donc de 0 € (C54) et l'impôt de l'année 1 est nul (C57). Les 726 € d'amortissement non utilisés sont mis en réserve pour les années suivantes (C56).
B54: Résultats : rendement brut 8,28 % (C61), là où une annonce afficherait 12,67 % (C62) ; net de charges 6,29 % (C63) ; net-net 6,29 % (C64), identique au net de charges puisque l'impôt est nul. Cash-flow mensuel −26,61 € (C66) : l'effort d'épargne est de 26,61 € par mois (C67).
B55: Comment le lire : le bien se finance presque seul la première année grâce à l'amortissement. Changez le régime en C47 pour « Location nue, réel foncier » avec le mobilier à 0 : les 20 000 € de travaux créent un déficit foncier, l'impôt de l'année 1 devient −3 210 € (une économie d'impôt) et le cash-flow de l'année 1 monte à 257,90 € par mois, mais ce n'est vrai qu'une année. Passez en « Meublé, LMNP micro-BIC » : l'impôt monte à 2 610 € et le cash-flow tombe à −244,14 € par mois.
B57: LES CHIFFRES À REGARDER, ET CE QU'ILS VALENT
B58: Indicateur | C58: Où | D58: Repère métier | E58: Ce qu'il dit vraiment
B59: Rendement brut | C59: Calculateur!C61 | D59: Ancien en ville moyenne : 6 à 9 %. Grandes métropoles : 3 à 5 %. | E59: Compare, ne décide pas. Calculé après vacance sur le coût total, il est plus sévère que celui des annonces (ligne suivante).
B60: Rendement net de charges | C60: Calculateur!C63 | D60: En dessous de 5 % dans l'ancien, le cash-flow est presque toujours négatif à crédit 100 %. | E60: Ce que le bien rapporte avant impôt et avant crédit.
B61: Rendement net-net | C61: Calculateur!C64 | D61: Un écart de plus de 1,5 point avec le net de charges signale une fiscalité lourde : testez un autre régime. | E61: Le seul qui dépend de votre situation fiscale. C'est celui qui décide.
B62: Impôt de l'année 1 | C62: Calculateur!C57 | D62: 0 € en LMNP réel est fréquent les premières années. Négatif au réel foncier avec travaux. | E62: Impôt sur le revenu à la TMI plus prélèvements sociaux (17,2 % en nu, 18,6 % en meublé).
B63: Cash-flow mensuel après impôt | C63: Calculateur!C66 | D63: Entre −100 € et +100 € par mois, le bien se finance seul. Au-delà de −300 €, c'est un placement d'épargne, pas un revenu. | E63: Ce qui reste (ou manque) chaque mois une fois tout payé, la première année.
B64: Part du loyer absorbée par la mensualité | C64: Calculateur!C68 | D64: Au-delà de 70 % (Paramètres), la banque retiendra que le loyer ne couvre pas le crédit : elle compte les loyers à cette quotité. | E64: Le premier ratio qu'un banquier regarde. Le taux d'effort complet du foyer se calcule dans la matrice Capacité d'emprunt.
B66: LES DONNÉES À METTRE À JOUR, OÙ ET POURQUOI
B67: Deux familles de données. Les barèmes et repères (barèmes fiscaux, plafonds, durées d'amortissement, taux de crédit et ordres de grandeur de référence) changent avec la loi ou le marché, à date fixe, et se rafraîchissent depuis une source indiquée : ils vivent tous dans Paramètres. Les données de projet (prix, loyer, charges, financement, régime) sont propres à chaque dossier. L'architecture du classeur ne change pas quand les données changent : seules les cellules violettes bougent.
B68: Paramètre | C68: Onglet et cellule | D68: Ce qu'il pilote | E68: Source à consulter, fréquence
B69: Prélèvements sociaux, revenus fonciers | C69: Paramètres!C8 | D69: Impôt des régimes micro-foncier et réel foncier | E69: Loi de financement de la sécurité sociale, chaque décembre
B70: Prélèvements sociaux, BIC meublé | C70: Paramètres!C9 | D70: Impôt des trois régimes meublés | E70: LFSS, chaque décembre (18,6 % depuis les revenus 2025)
B71: Abattements et plafonds micro | C71: Paramètres!C10:C15 | D71: Base imposable des régimes micro et contrôle « Régime autorisé » | E71: CGI art. 32 et 50-0, loi de finances ; plafond micro-BIC revalorisé tous les trois ans
B72: Plafond du déficit foncier | C72: Paramètres!C16 | D72: Économie d'impôt de l'année 1 au réel foncier | E72: CGI art. 156, I-3° ; BOFiP BOI-RFPI-BASE-30-20 : chaque loi de finances. 10 700 € par défaut. Le plafond majoré à 21 400 € ne vaut que pour des travaux de rénovation énergétique payés au plus tard le 31 décembre 2025 : il ne s'applique plus à une dépense de 2026. Si vous le passez à 21 400 € pour un dossier qui remplit encore les conditions, remettez 10 700 € ensuite.
B73: Durée maximale HCSF | C73: Paramètres!C17 | D73: Commentaire de la durée du prêt | E73: Décisions du HCSF
B74: Durées d'amortissement | C74: Paramètres!C21:C23 | D74: Amortissement annuel du LMNP réel | E74: Usage des experts-comptables, stable ; à caler avec le vôtre
B75: Repères de marché (frais de notaire, PNO, comptable, gestion, taux de crédit, assurance, part du terrain, quotité des loyers) | C75: Paramètres!C24:C34 | D75: Les commentaires gris du Calculateur (C9, C24, C26, C28, C34, C35, C36, C50, C68, colonne D) les lisent par formule | E75: Observatoire Crédit Logement (mensuel), baromètres d'assurance et de PNO (annuel), barème des notaires et DMTO (à chaque changement) : à rafraîchir à chaque millésime
B76: Bornes de saisie et plancher de plausibilité des taux | C76: Paramètres!C38:C42 | D76: Validations de saisie, contrôle des taux C44 et contrôle global C60 | E76: Convention du classeur : stable. Relevez le plancher si des taux inférieurs à 0,10 % redeviennent courants
B77: Barème des TMI | C77: Paramètres!C46:C50 | D77: Liste déroulante de la TMI | E77: CGI art. 197, chaque loi de finances
B78: Date de dernière vérification | C78: Paramètres!C52 | D78: Toutes les mentions « Vérifié le » de Paramètres et de Méthode, et le millésime du titre de Paramètres | E78: À chaque vérification : une seule cellule à changer
B79: Textes des sources | C79: Paramètres, colonne D | D79: Méthode, section Sources, les recopie | E79: Quand un texte de loi ou une publication change ; cellule verrouillée : Révision, Ôter la protection
... B81: Prix, loyer, charges, financement, régime, TMI | C81: Calculateur!C7:C12, Calculateur!C17:C28, Calculateur!C33:C36, Calculateur!C47:C50 | D81: Tout le reste | E81: Données de projet, propres à chaque dossier
B83: TROIS FAÇONS DE S'EN SERVIR
B84: Votre situation | C84: Ce que vous faites
B85: Vous hésitez entre louer nu ou meublé | C85: Saisissez le bien une fois. Notez le cash-flow (C66) avec « Location nue, réel foncier » et le mobilier à 0, puis avec « Meublé, LMNP réel (amortissement) » et le mobilier réel. L'écart mensuel est ce que vous coûte le choix de la location nue. Pensez à mettre le comptable en C26 pour le LMNP réel.
B86: Vous voulez savoir jusqu'où monter sur le prix | C86: Augmentez C7 par pas de 5 000 € jusqu'à ce que le cash-flow mensuel passe sous le niveau que vous acceptez. Ajustez C9 en proportion (repère de Paramètres : environ 8,0 % du prix net vendeur dans l'ancien, 2,5 % dans le neuf).
B87: Vous préparez le rendez-vous banque | C87: Renseignez le financement proposé (Calculateur!C33:C36). Lisez la mensualité totale (C40) et la part du loyer absorbée (C68). Au-delà de la quotité retenue par les banques (Paramètres), prévoyez un apport ou une durée plus longue, et passez par la matrice Capacité d'emprunt pour le taux d'effort du foyer.
B89: LES ERREURS QUI FAUSSENT TOUT
B90: Le piège | C90: Le dégât
B91: Saisir un taux en fraction (0,034) dans une cellule qui affiche déjà le pourcentage | C91: La cellule affiche 0,03 % : la mensualité tombe à 474,12 € au lieu de 671,47 € (C38), soit presque le seul remboursement du capital. Le contrôle « Taux vraisemblable » (C44) passe au rouge sous le plancher de plausibilité de Paramètres (0,10 %), sauf à 0 % exactement. Tapez 3,4 et vérifiez que la cellule affiche 3,40 %.
B92: Confondre vacance en semaines et vacance en pourcentage (C18) | C92: Saisir 8 pour « 8 % » retire 8 semaines, soit 15 % du loyer : rendements sous-estimés d'un point. Un mois de vacance = 4,33 semaines.
B93: Oublier les frais de notaire ou les saisir hors barème (C9) | C93: Un oubli de 7 500 € sur 130 000 € gonfle tous les rendements de 0,5 point. À 11 % du prix, ils les écrasent d'autant.
B94: Saisir la taxe foncière TEOM comprise (C23) | C94: La TEOM est récupérable sur le locataire : 100 à 200 € de charges en trop, et une déduction fiscale indue au réel.
B95: Laisser le mobilier à 3 000 € en location nue, ou à 0 en meublé (C11) | C95: En nu, 3 000 € de coût total en trop. En LMNP réel, un amortissement du mobilier oublié, soit plusieurs centaines d'euros de base imposable en plus.
B96: Laisser 20 000 € de travaux déductibles en C49 après avoir mis les travaux à 0 en C10 | C96: Au réel foncier, un déficit fictif de 20 000 € : l'impôt devient négatif et le cash-flow gagne environ 300 € par mois. Le contrôle C60 passe au rouge (C49 ne peut pas dépasser C10) et les résultats fiscaux restent vides jusqu'à la correction.
B97: Prendre le résultat de l'année 1 pour une année de croisière | C97: Au réel foncier avec travaux, l'année 1 est la meilleure (déficit imputé) ; ensuite l'impôt revient. En LMNP réel, l'amortissement tient plusieurs années puis l'impôt apparaît. Le classeur le dit dans Méthode.
B99: Ce que le classeur ne fait pas, et sur quelles sources reposent ses chiffres : voir l'onglet Méthode.
B101: CorpusImmo, millésime 2026. Modèle d'aide à la décision : ne constitue ni un conseil en investissement, ni un conseil fiscal, ni une expertise au sens de la charte de l'expertise en évaluation immobilière. Vérifiez les paramètres avant tout engagement.

Sheet Calculateur
B1: CorpusImmo · www.corpus.immo · Estimer, comparer, décider. Sur les ventes réelles.
B2: Calculateur de rentabilité locative
B3: Rendement brut, net de charges et net-net après impôt, avec le cash-flow réel de la première année.
B5: Cellules violettes : à remplir. Cellules blanches : calculées automatiquement.
B6: LE BIEN
B7: Prix net vendeur | C7: 90000 | D7: Prix hors honoraires d'agence et hors frais de notaire.
B8: Frais d'agence | C8: 9200 | D8: Honoraires à la charge de l'acquéreur. 0 s'ils sont à la charge du vendeur ou sans agence.
B9: Frais de notaire | C9: 7500 | D9: ="Ordre de grandeur (Paramètres) : "&ROUND(Paramètres!$C$24*100,1)&" %"&" du prix net vendeur dans l'ancien, "&ROUND(Paramètres!$C$25*100,1)&" %"&" dans le neuf. Prenez le chiffre de votre notaire si vous l'avez." -> Ordre de grandeur (Paramètres) : 8 % du prix net vendeur dans l'ancien, 2,5 % dans le neuf. Prenez le chiffre de votre notaire si vous l'avez.
B10: Travaux | C10: 20000 | D10: Montant total des travaux, déductibles ou non. La part déductible au réel foncier se précise en C49.
B11: Mobilier et équipement | C11: 3000 | D11: Uniquement en location meublée. 0 en location nue.
B12: Surface habitable | C12: 72 | D12: Surface habitable au sens de la loi Boutin, pas la surface Carrez.
B13: Coût total de l'opération | C13: =SUM($C$7:$C$11) -> 129700 | D13: Dénominateur de tous les rendements du classeur.
B14: Prix de revient au m² | C14: =IF($C$12>0,$C$13/$C$12,"") -> 1801.3889 | D14: Coût total rapporté à la surface habitable.
B16: REVENUS LOCATIFS
B17: Loyer mensuel hors charges | C17: 950 | D17: Le loyer du bail, hors charges et hors provision sur charges.
B18: Vacance locative (semaines par an) | C18: 3 | D18: Entre 0 et 52. Un mois de vacance = 4,33 semaines.
B19: Loyer annuel encaissé | C19: =$C$17*12*(1-$C$18/52) -> 10742.308 | D19: Loyer × 12, diminué de la vacance.
B20: Loyer mensuel au m² | C20: =IF($C$12>0,$C$17/$C$12,"") -> 13.194444 | D20: À comparer aux loyers de marché du quartier.
B22: CHARGES ANNUELLES
B23: Taxe foncière hors TEOM | C23: 900 | D23: Sans la taxe d'enlèvement des ordures ménagères, récupérable sur le locataire.
B24: Assurance propriétaire non occupant (PNO) | C24: 180 | D24: ="Ordre de grandeur (Paramètres) : "&Paramètres!$C$26&" €"&" par an pour un appartement." -> Ordre de grandeur (Paramètres) : 120 € par an pour un appartement.
B25: Charges de copropriété non récupérables | C25: 600 | D25: La part qui reste au bailleur : syndic, assurance de l'immeuble, gros entretien.
B26: Comptabilité | C26: 400 | D26: ="Expert-comptable, surtout en LMNP réel : repère (Paramètres) "&Paramètres!$C$27&" €"&" par an. 0 sans expert-comptable, le cas courant en location nue." -> Expert-comptable, surtout en LMNP réel : repère (Paramètres) 500 € par an. 0 sans expert-comptable, le cas courant en location nue.
B27: Provision entretien et travaux | C27: 500 | D27: Réserve annuelle pour l'entretien courant. Compte dans le cash-flow, pas dans l'impôt.
B28: Gestion locative (% du loyer) | C28: 0 | D28: ="Honoraires en pourcentage du loyer encaissé. Repère en agence (Paramètres) : "&ROUND(Paramètres!$C$28*100,1)&" %"&". 0 en gestion directe." -> Honoraires en pourcentage du loyer encaissé. Repère en agence (Paramètres) : 7 %. 0 en gestion directe.
B29: Total des charges | C29: =SUM($C$23:$C$27)+$C$19*$C$28 -> 2580 | D29: Charges fixes plus gestion locative.
B30: Revenu net de charges | C30: =$C$19-$C$29 -> 8162.3077 | D30: Loyer encaissé moins toutes les charges, avant impôt et avant crédit.
B32: FINANCEMENT
B33: Apport personnel | C33: 5000 | D33: 0 pour un financement à 100 %. Si vous partez du prêt proposé par la banque : apport = coût total (C13) moins ce prêt.
B34: Taux du prêt (hors assurance) | C34: 0.034 | D34: ="Taux nominal annuel. Repère (Paramètres) : "&ROUND(Paramètres!$C$29*100,2)&" %"&" sur 20 ans, "&ROUND(Paramètres!$C$30*100,2)&" %"&" sur 25 ans." -> Taux nominal annuel. Repère (Paramètres) : 3,27 % sur 20 ans, 3,35 % sur 25 ans.
B35: Durée du prêt | C35: 22 | D35: ="Années entières, de 1 à "&Paramètres!$C$39&". Le HCSF limite les prêts à "&Paramètres!$C$17&" ans (Paramètres)." -> Années entières, de 1 à 30. Le HCSF limite les prêts à 25 ans (Paramètres).
B36: Taux d'assurance emprunteur (sur capital initial) | C36: 0.0034 | D36: ="Taux annuel, contrat de la banque sur le capital emprunté. Repère (Paramètres) : "&ROUND(Paramètres!$C$31*100,2)&" %"&" en groupe, "&ROUND(Paramètres!$C$32*100,2)&" %"&" en délégation (tapez le taux annoncé, le classeur sera un peu prudent)." -> Taux annuel, contrat de la banque sur le capital emprunté. Repère (Paramètres) : 0,36 % en groupe, 0,17 % en délégation (tapez le taux annoncé, le classeur sera un peu prudent).
B37: Montant emprunté | C37: =MAX(0,$C$13-$C$33) -> 124700 | D37: Coût total moins apport.
B38: Mensualité (capital + intérêts) | C38: =IF($C$37=0,0,IF($C$35>0,-PMT($C$34/12,$C$35*12,$C$37),"")) -> 671.46611 | D38: Annuité constante, taux nominal divisé par 12.
B39: Assurance mensuelle | C39: =IF($C$38="","",$C$37*$C$36/12) -> 35.331667 | D39: Capital emprunté × taux d'assurance / 12, constante sur toute la durée.
B40: Mensualité totale | C40: =IF($C$38="","",$C$38+$C$39) -> 706.79777 | D40: Ce que la banque prélève chaque mois.
B41: Intérêts de la 1re année | C41: =IF($C$38="","",IF(OR($C$37=0,$C$34=0),0,-CUMIPMT($C$34/12,$C$35*12,$C$37,1,12,0))) -> 4179.7406 | D41: Somme des intérêts des 12 premières échéances. Ils baissent ensuite chaque année.
B42: Assurance emprunteur de la 1re année | C42: =IF($C$39="","",$C$39*12) -> 423.98 | D42: Déductible au réel foncier et au LMNP réel, comme les intérêts.
B43: Financement cohérent | C43: =IF(AND($C$33>=0,$C$33<=$C$13,OR($C$37=0,$C$35>0)),"OK","À CORRIGER") -> OK | D43: À CORRIGER si l'apport est négatif ou dépasse le coût total, ou si la durée manque alors qu'il y a un emprunt.
B44: Taux vraisemblable | C44: =IF(AND(ISNUMBER(Paramètres!$C$42),OR(NOT(ISNUMBER($C$34)),$C$34<=0,$C$34>=Paramètres!$C$42),OR(NOT(ISNUMBER($C$36)),$C$36<=0,$C$36>=Paramètres!$C$42)),"OK","À CORRIGER") -> OK | D44: ="À CORRIGER si le taux du prêt ou le taux d'assurance est strictement positif et inférieur au plancher de plausibilité de Paramètres ("&ROUND(Paramètres!$C$42*100,2)&" %"&") : vous avez sans doute tapé 0,034 au lieu de 3,4. Un prêt à taux zéro se saisit 0 exactement." -> À CORRIGER si le taux du prêt ou le taux d'assurance est strictement positif et inférieur au plancher de plausibilité de Paramètres (0,1 %) : vous avez sans doute tapé 0,034 au lieu de 3,4. Un prêt à taux zéro se saisit 0 exactement.
B46: FISCALITÉ, ANNÉE 1
B47: Régime fiscal | C47: Meublé, LMNP réel (amortissement) | D47: Choisir dans la liste. Les régimes meublés supposent du mobilier en C11.
B48: Tranche marginale d'imposition (TMI) | C48: 0.3 | D48: ="Taux de la tranche la plus haute de votre foyer : "&ROUND(Paramètres!$C$46*100,0)&" %"&", "&ROUND(Paramètres!$C$47*100,0)&" %"&", "&ROUND(Paramètres!$C$48*100,0)&" %"&", "&ROUND(Paramètres!$C$49*100,0)&" %"&", "&ROUND(Paramètres!$C$50*100,0)&" %"&" (avis d'impôt, ligne taux marginal d'imposition)." -> Taux de la tranche la plus haute de votre foyer : 0 %, 11 %, 30 %, 41 %, 45 % (avis d'impôt, ligne taux marginal d'imposition).
B49: Travaux déductibles au réel foncier (année 1) | C49: 20000 | D49: Part d'entretien, de réparation et d'amélioration des travaux de C10. Sans travaux, tapez 0. N'agit qu'au réel foncier.
B50: Part du terrain dans le prix (non amortissable) | C50: 0.15 | D50: ="Sans effet hors LMNP réel : laissez la valeur. Usage (Paramètres) : "&ROUND(Paramètres!$C$33*100,1)&" %"&" pour un appartement, davantage en zone tendue ou pour une maison." -> Sans effet hors LMNP réel : laissez la valeur. Usage (Paramètres) : 15 % pour un appartement, davantage en zone tendue ou pour une maison.
B51: Régime autorisé | C51: =IF(AND(NOT(ISNA(MATCH($C$47,Paramètres!$B$46:$B$50,0))),OR($C$47=Paramètres!$B$47,$C$47=Paramètres!$B$49,AND($C$47=Paramètres!$B$46,$C$17*12<=Paramètres!$C$11),AND($C$47=Paramètres!$B$48,$C$17*12<=Paramètres!$C$13),AND($C$47=Paramètres!$B$50,$C$17*12<=Paramètres!$C$15))),"OK","À CORRIGER") -> OK | D51: À CORRIGER si le régime manque ou si le loyer annuel dépasse le plafond du régime micro choisi.
B52: Amortissement annuel (LMNP réel) | C52: =IF($C$47=Paramètres!$B$49,($C$7+$C$8+$C$9)*(1-$C$50)/Paramètres!$C$21+$C$10/Paramètres!$C$22+$C$11/Paramètres!$C$23,0) -> 4785.0714 | D52: Bâti hors terrain (prix et frais d'acquisition), travaux et mobilier, sur les durées de Paramètres.
B53: Résultat fiscal avant plafonnement | C53: =IF(OR($C$51<>"OK",NOT(AND(ISNUMBER($C$48),NOT(ISNA(MATCH($C$48,Paramètres!$C$46:$C$50,0))))),$C$41=""),"",IF($C$47=Paramètres!$B$46,$C$19*(1-Paramètres!$C$10),IF($C$47=Paramètres!$B$47,$C$19-($C$23+$C$24+$C$25+$C$19*$C$28)-($C$41+$C$42)-$C$49,IF($C$47=Paramètres!$B$48,$C$19*(1-Paramètres!$C$12),IF($C$47=Paramètres!$B$49,$C$19-($C$23+$C$24+$C$25+$C$26+$C$19*$C$28)-($C$41+$C$42)-$C$52,$C$19*(1-Paramètres!$C$14)))))) -> -726.48431 | D53: Négatif : déficit (réel foncier) ou amortissement non imputé (LMNP réel).
B54: Base imposable retenue, année 1 | C54: =IF($C$53="","",MAX(0,$C$53)) -> 0 | D54: Jamais négative.
B55: Déficit imputé sur le revenu global (réel foncier) | C55: =IF($C$53="","",IF($C$47=Paramètres!$B$47,MIN(Paramètres!$C$16,MAX(0,-$C$53-MAX(0,($C$41+$C$42)-$C$19))),0)) -> 0 | D55: Plafonné (Paramètres). La part du déficit qui vient des intérêts n'est jamais imputée sur le revenu global.
B56: Reporté sur les années suivantes | C56: =IF($C$53="","",IF($C$47=Paramètres!$B$47,MAX(0,-$C$53)-$C$55,IF($C$47=Paramètres!$B$49,MAX(0,-$C$53),0))) -> 726.48431 | D56: Réel foncier : déficit reportable 10 ans sur les revenus fonciers. LMNP réel : amortissement reporté sans limite.
B57: Impôt sur le revenu et prélèvements sociaux, année 1 | C57: =IF($C$53="","",$C$54*($C$48+IF(OR($C$47=Paramètres!$B$48,$C$47=Paramètres!$B$49,$C$47=Paramètres!$B$50),Paramètres!$C$9,Paramètres!$C$8))-$C$55*$C$48) -> 0 | D57: Négatif : économie d'impôt sur le revenu global grâce au déficit foncier.
B59: RÉSULTATS, ANNÉE 1
B60: Saisies complètes et cohérentes | C60: =IF(AND(ISNUMBER($C$7),$C$7>0,ISNUMBER($C$12),$C$12>=1,ISNUMBER($C$17),$C$17>0,COUNT($C$7:$C$11)+COUNTBLANK($C$7:$C$11)=5,MIN($C$7:$C$11)>=0,COUNT($C$23:$C$27)+COUNTBLANK($C$23:$C$27)=5,MIN($C$23:$C$27)>=0,IF(ISBLANK($C$18),TRUE,IF(ISNUMBER($C$18),AND($C$18>=0,$C$18<=52),FALSE)),IF(ISBLANK($C$28),TRUE,IF(ISNUMBER($C$28),AND($C$28>=0,$C$28<=1),FALSE)),IF(ISNUMBER($C$34),AND($C$34>=0,$C$34<=Paramètres!$C$38),FALSE),IF(ISNUMBER($C$35),AND($C$35>=1,$C$35<=Paramètres!$C$39,$C$35=INT($C$35)),FALSE),IF(ISNUMBER($C$36),AND($C$36>=0,$C$36<=Paramètres!$C$40),FALSE),IF(ISBLANK($C$49),TRUE,IF(ISNUMBER($C$49),AND($C$49>=0,$C$49<=$C$10),FALSE)),IF(ISBLANK($C$50),TRUE,IF(ISNUMBER($C$50),AND($C$50>=0,$C$50<=Paramètres!$C$41),FALSE)),$C$43="OK",$C$44="OK",$C$51="OK",AND(ISNUMBER($C$48),NOT(ISNA(MATCH($C$48,Paramètres!$C$46:$C$50,0)))),$C$57<>"",COUNT(Paramètres!$C$8:$C$17)=10,COUNT(Paramètres!$C$21:$C$34)=14,COUNT(Paramètres!$C$38:$C$42)=5),"OK","À CORRIGER") -> OK | D60: À CORRIGER : une saisie manque, sort de ses bornes (dont C49 au-delà de C10) ou un contrôle est rouge. Les résultats fiscaux restent vides tant que ce n'est pas corrigé.
B61: Rendement brut (loyer encaissé / coût total) | C61: =IF($C$13>0,$C$19/$C$13,"") -> 0.082824269 | D61: Après vacance, sur le coût total frais et travaux inclus : plus sévère que les annonces.
B62: Rendement brut affiché (loyer théorique / prix net vendeur) | C62: =IF($C$7>0,$C$17*12/$C$7,"") -> 0.12666667 | D62: Le chiffre des annonces, pour comparer. Ne sert pas à décider.
B63: Rendement net de charges | C63: =IF($C$13>0,$C$30/$C$13,"") -> 0.06293221 | D63: Revenu net de charges rapporté au coût total.
B64: Rendement net-net après impôt, année 1 | C64: =IF(OR($C$57="",$C$13=0),"",($C$30-$C$57)/$C$13) -> 0.06293221 | D64: Le seul qui dépend de votre régime et de votre TMI.
B65: Cash-flow annuel après impôt, année 1 | C65: =IF(OR($C$57="",$C$40=""),"",$C$30-$C$57-$C$40*12) -> -319.26559 | D65: Revenu net de charges, moins impôt, moins douze mensualités totales.
B66: Cash-flow mensuel après impôt, année 1 | C66: =IF($C$65="","",$C$65/12) -> -26.605466 | D66: Négatif : ce que le bien vous coûte chaque mois.
B67: Effort d'épargne mensuel | C67: =IF($C$66="","",MAX(0,-$C$66)) -> 26.605466 | D67: Ce qu'il faut sortir de sa poche chaque mois. 0 si le cash-flow est positif.
B68: Part du loyer absorbée par la mensualité | C68: =IF(OR($C$40="",$C$17=0),"",$C$40/$C$17) -> 0.74399766 | D68: ="Au-delà de "&ROUND(Paramètres!$C$34*100,0)&" %"&" (part des loyers retenue par les banques, Paramètres), le bien ne se finance pas seul : premier regard d'un banquier." -> Au-delà de 70 % (part des loyers retenue par les banques, Paramètres), le bien ne se finance pas seul : premier regard d'un banquier.
B70: CorpusImmo, millésime 2026. Modèle d'aide à la décision : ne constitue ni un conseil en investissement, ni un conseil fiscal, ni une expertise au sens de la charte de l'expertise en évaluation immobilière. Vérifiez les paramètres avant tout engagement.

Sheet Paramètres
B1: CorpusImmo · www.corpus.immo · Estimer, comparer, décider. Sur les ventes réelles.
B2: Paramètres
B3: Les seules valeurs à mettre à jour quand la réglementation ou le marché changent. Le Calculateur y renvoie pour chaque barème et chaque repère.
B5: Cellules violettes : à remplir. Cellules blanches : calculées automatiquement.
B6: =" BARÈMES RÉGLEMENTAIRES, MILLÉSIME "&YEAR($C$52) -> BARÈMES RÉGLEMENTAIRES, MILLÉSIME 2026
B7: Paramètre | C7: Valeur | D7: Source (organisme, texte, date) | E7: Mise à jour | F7: Commentaire
B8: Prélèvements sociaux, revenus fonciers (location nue) | C8: 0.172 | D8: ="CSS art. L136-6 (assiette des revenus du patrimoine) et L136-8 (taux : CSG 9,2 %), CRDS 0,5 %, CGI art. 235 ter (solidarité 7,5 %). Inchangé par la LFSS 2026. Vérifié le "&TEXT(DAY($C$52),"00")&"/"&TEXT(MONTH($C$52),"00")&"/"&YEAR($C$52)&"." -> CSS art. L136-6 (assiette des revenus du patrimoine) et L136-8 (taux : CSG 9,2 %), CRDS 0,5 %, CGI art. 235 ter (solidarité 7,5 %). Inchangé par la LFSS 2026. Vérifié le 05/09/2026. | E8: Chaque LFSS (décembre) | F8: S'applique aux régimes micro-foncier et réel foncier.
B9: Prélèvements sociaux, BIC de location meublée (LMNP) | C9: 0.186 | D9: ="LFSS 2026, loi n° 2025-1403 du 30/12/2025, art. 12, modifiant CSS art. L136-8 : CSG portée de 9,2 % à 10,6 % dès les revenus 2025. Vérifié le "&TEXT(DAY($C$52),"00")&"/"&TEXT(MONTH($C$52),"00")&"/"&YEAR($C$52)&"." -> LFSS 2026, loi n° 2025-1403 du 30/12/2025, art. 12, modifiant CSS art. L136-8 : CSG portée de 9,2 % à 10,6 % dès les revenus 2025. Vérifié le 05/09/2026. | E9: Chaque LFSS (décembre) | F9: S'applique aux trois régimes meublés de la liste. La hausse de CSG de la LFSS 2026 vise les revenus du patrimoine et les produits de placement ; les revenus fonciers, les plus-values immobilières, l'assurance vie et les plans d'épargne logement en sont exclus et restent à 17,2 %, ce qui explique l'écart de 1,4 point avec la location nue.
B10: Abattement micro-foncier | C10: 0.3 | D10: ="CGI art. 32. Vérifié le "&TEXT(DAY($C$52),"00")&"/"&TEXT(MONTH($C$52),"00")&"/"&YEAR($C$52)&"." -> CGI art. 32. Vérifié le 05/09/2026. | E10: Chaque loi de finances | F10: Abattement forfaitaire sur les loyers bruts, aucune autre charge déductible.
B11: Plafond de revenus bruts fonciers du micro-foncier | C11: 15000 | D11: ="CGI art. 32, I. Vérifié le "&TEXT(DAY($C$52),"00")&"/"&TEXT(MONTH($C$52),"00")&"/"&YEAR($C$52)&"." -> CGI art. 32, I. Vérifié le 05/09/2026. | E11: Chaque loi de finances | F11: Revenus bruts fonciers annuels du foyer, tous biens nus confondus. Le classeur compare le loyer mensuel × 12.
B12: Abattement micro-BIC, meublé longue durée ou tourisme classé | C12: 0.5 | D12: ="CGI art. 50-0 modifié par la loi n° 2024-1039 du 19/11/2024 (dite Le Meur), revenus 2025 et suivants. Vérifié le "&TEXT(DAY($C$52),"00")&"/"&TEXT(MONTH($C$52),"00")&"/"&YEAR($C$52)&"." -> CGI art. 50-0 modifié par la loi n° 2024-1039 du 19/11/2024 (dite Le Meur), revenus 2025 et suivants. Vérifié le 05/09/2026. | E12: Chaque loi de finances | F12: Meublé de tourisme classé : 50 % aussi, plafond identique.
B13: Plafond de recettes du micro-BIC, meublé longue durée ou classé | C13: 83600 | D13: ="CGI art. 50-0, revalorisation triennale 2026-2028 : 83 600 € pour les recettes 2026 (77 700 € pour 2025). jedeclaremonmeuble.com, cpim.fr. Vérifié le "&TEXT(DAY($C$52),"00")&"/"&TEXT(MONTH($C$52),"00")&"/"&YEAR($C$52)&"." -> CGI art. 50-0, revalorisation triennale 2026-2028 : 83 600 € pour les recettes 2026 (77 700 € pour 2025). jedeclaremonmeuble.com, cpim.fr. Vérifié le 05/09/2026. | E13: Tous les 3 ans (prochaine : recettes 2029) | F13: Recettes charges comprises. Le classeur compare le loyer hors charges × 12, légèrement favorable.
B14: Abattement micro-BIC, meublé de tourisme non classé | C14: 0.3 | D14: ="CGI art. 50-0, loi n° 2024-1039 du 19/11/2024, revenus 2025 et suivants. Vérifié le "&TEXT(DAY($C$52),"00")&"/"&TEXT(MONTH($C$52),"00")&"/"&YEAR($C$52)&"." -> CGI art. 50-0, loi n° 2024-1039 du 19/11/2024, revenus 2025 et suivants. Vérifié le 05/09/2026. | E14: Chaque loi de finances
B15: Plafond de recettes du micro-BIC, meublé de tourisme non classé | C15: 15000 | D15: ="CGI art. 50-0, loi n° 2024-1039 du 19/11/2024. Vérifié le "&TEXT(DAY($C$52),"00")&"/"&TEXT(MONTH($C$52),"00")&"/"&YEAR($C$52)&"." -> CGI art. 50-0, loi n° 2024-1039 du 19/11/2024. Vérifié le 05/09/2026. | E15: Chaque loi de finances
B16: Plafond d'imputation du déficit foncier sur le revenu global | C16: 10700 | D16: ="CGI art. 156, I-3°. Rehaussement à 21 400 € institué par la loi n° 2022-1499 du 01/12/2022 de finances rectificative pour 2022, art. 12 ; décret n° 2023-297 du 21/04/2023 ; CGI annexe III art. 41 DO ; BOFiP BOI-RFPI-BASE-30-20. Vérifié le "&TEXT(DAY($C$52),"00")&"/"&TEXT(MONTH($C$52),"00")&"/"&YEAR($C$52)&"." -> CGI art. 156, I-3°. Rehaussement à 21 400 € institué par la loi n° 2022-1499 du 01/12/2022 de finances rectificative pour 2022, art. 12 ; décret n° 2023-297 du 21/04/2023 ; CGI annexe III art. 41 DO ; BOFiP BOI-RFPI-BASE-30-20. Vérifié le 05/09/2026. | E16: Chaque loi de finances | F16: 10 700 € par défaut, et c'est le seul plafond que le classeur applique. Le rehaussement à 21 400 € est temporaire : il couvre les travaux de rénovation énergétique dont le devis a été accepté à compter du 05/11/2022 et qui ont été payés entre le 01/01/2023 et le 31/12/2025, à condition que le logement passe d'une classe E, F ou G à une classe A, B, C ou D, justifiée par deux diagnostics au plus tard le 31/12/2027. Pour les revenus 2026, une dépense payée dans l'année n'y ouvre donc plus droit : ne passez cette cellule à 21 400 € que pour un dossier dont les travaux étaient déjà payés fin 2025. Une prorogation de la période de paiement est annoncée par la presse fiscale, elle n'est confirmée ni par le code ni par la doctrine à ce jour : le classeur retient la règle la plus stricte. C'est une donnée de dossier, pas un barème : remettez 10 700 € ensuite.
B17: Durée maximale d'un prêt immobilier (HCSF) | C17: 25 | D17: ="HCSF, décision D-HCSF-2021-7 du 29/09/2021, contraignante depuis le 01/01/2022, confirmée par la décision D-HCSF-2023-2 du 29/06/2023 : 25 ans (27 ans avec différé), taux d'effort 35 %. economie.gouv.fr/hcsf. Vérifié le "&TEXT(DAY($C$52),"00")&"/"&TEXT(MONTH($C$52),"00")&"/"&YEAR($C$52)&"." -> HCSF, décision D-HCSF-2021-7 du 29/09/2021, contraignante depuis le 01/01/2022, confirmée par la décision D-HCSF-2023-2 du 29/06/2023 : 25 ans (27 ans avec différé), taux d'effort 35 %. economie.gouv.fr/hcsf. Vérifié le 05/09/2026. | E17: À chaque décision du HCSF | F17: Lu par le commentaire de la durée du prêt. La saisie reste possible jusqu'à la borne de saisie, pour les cas dérogatoires.
B19: REPÈRES DE MARCHÉ (LUS PAR LES COMMENTAIRES DU CALCULATEUR)
B20: Paramètre | C20: Valeur | D20: Source (organisme, texte, date) | E20: Mise à jour | F20: Commentaire
B21: Durée d'amortissement du bâti, LMNP réel | C21: 30 | D21: ="Usage des experts-comptables LMNP : 25 à 40 ans en linéaire simplifié (ou par composants, BOFiP BOI-BIC-AMT-10-40-10). jedeclaremonmeuble.com, calcunet.fr. Vérifié le "&TEXT(DAY($C$52),"00")&"/"&TEXT(MONTH($C$52),"00")&"/"&YEAR($C$52)&"." -> Usage des experts-comptables LMNP : 25 à 40 ans en linéaire simplifié (ou par composants, BOFiP BOI-BIC-AMT-10-40-10). jedeclaremonmeuble.com, calcunet.fr. Vérifié le 05/09/2026. | E21: Stable | F21: Base : prix, honoraires d'agence et frais de notaire, hors quote-part de terrain (saisie dans le Calculateur).
B22: Durée d'amortissement des travaux, LMNP réel | C22: 15 | D22: ="Usage : 10 à 20 ans selon la nature (aménagements 10 à 12 ans, gros œuvre 25 à 30 ans). calcunet.fr. Vérifié le "&TEXT(DAY($C$52),"00")&"/"&TEXT(MONTH($C$52),"00")&"/"&YEAR($C$52)&"." -> Usage : 10 à 20 ans selon la nature (aménagements 10 à 12 ans, gros œuvre 25 à 30 ans). calcunet.fr. Vérifié le 05/09/2026. | E22: Stable | F22: Simplification : une seule durée pour l'ensemble des travaux.
B23: Durée d'amortissement du mobilier, LMNP réel | C23: 7 | D23: ="Usage : 5 à 10 ans. jedeclaremonmeuble.com. Vérifié le "&TEXT(DAY($C$52),"00")&"/"&TEXT(MONTH($C$52),"00")&"/"&YEAR($C$52)&"." -> Usage : 5 à 10 ans. jedeclaremonmeuble.com. Vérifié le 05/09/2026. | E23: Stable | F23: Le petit matériel de moins de 600 € TTC peut passer en charge l'année d'achat (non modélisé).
B24: Frais de notaire dans l'ancien, ordre de grandeur (% du prix net vendeur) | C24: 0.08 | D24: ="DMTO 6,32 % dans la grande majorité des départements (LF 2025 art. 116, droit majoré du 01/04/2025 au 31/03/2028), émoluments (barème prorogé au 29/02/2028), CSI 0,10 % : 7,5 à 8,5 % pour 90 000 €. taximmo.fr, pretto.fr. Vérifié le "&TEXT(DAY($C$52),"00")&"/"&TEXT(MONTH($C$52),"00")&"/"&YEAR($C$52)&"." -> DMTO 6,32 % dans la grande majorité des départements (LF 2025 art. 116, droit majoré du 01/04/2025 au 31/03/2028), émoluments (barème prorogé au 29/02/2028), CSI 0,10 % : 7,5 à 8,5 % pour 90 000 €. taximmo.fr, pretto.fr. Vérifié le 05/09/2026. | E24: À chaque vote départemental des DMTO et chaque arrêté sur les émoluments | F24: Lu par le commentaire de la ligne Frais de notaire. La part fixe pèse davantage sur les petits prix.
B25: Frais de notaire dans le neuf, ordre de grandeur (% du prix) | C25: 0.025 | D25: ="Vente en TVA : taxe de publicité foncière 0,715 %, émoluments, CSI : 2 à 3 % du prix. pretto.fr. Vérifié le "&TEXT(DAY($C$52),"00")&"/"&TEXT(MONTH($C$52),"00")&"/"&YEAR($C$52)&"." -> Vente en TVA : taxe de publicité foncière 0,715 %, émoluments, CSI : 2 à 3 % du prix. pretto.fr. Vérifié le 05/09/2026. | E25: À chaque arrêté sur les émoluments
B26: Assurance propriétaire non occupant, ordre de grandeur annuel (appartement) | C26: 120 | D26: ="Comparateurs 2026 : 100 à 150 € par an pour un appartement, davantage en grande ville. selectra.info, lesfurets.com. Vérifié le "&TEXT(DAY($C$52),"00")&"/"&TEXT(MONTH($C$52),"00")&"/"&YEAR($C$52)&"." -> Comparateurs 2026 : 100 à 150 € par an pour un appartement, davantage en grande ville. selectra.info, lesfurets.com. Vérifié le 05/09/2026. | E26: Annuelle | F26: Lu par le commentaire de la ligne PNO.
B27: Expert-comptable LMNP réel, honoraires annuels, ordre de grandeur | C27: 500 | D27: ="Tarifs 2026 : 300 à 600 € TTC en cabinet en ligne, 600 à 900 € en cabinet traditionnel, pour un lot. jedeclaremonmeuble.com, indy.fr. Vérifié le "&TEXT(DAY($C$52),"00")&"/"&TEXT(MONTH($C$52),"00")&"/"&YEAR($C$52)&"." -> Tarifs 2026 : 300 à 600 € TTC en cabinet en ligne, 600 à 900 € en cabinet traditionnel, pour un lot. jedeclaremonmeuble.com, indy.fr. Vérifié le 05/09/2026. | E27: Annuelle | F27: Lu par le commentaire de la ligne Comptabilité. Déductible au LMNP réel seulement.
B28: Gestion locative en agence, honoraires usuels (% du loyer) | C28: 0.07 | D28: ="Marché 2026 : 6 à 9 % TTC du loyer charges comprises en gestion complète, 4 à 6 % en agence en ligne. manda.fr, nousgerons.com. Vérifié le "&TEXT(DAY($C$52),"00")&"/"&TEXT(MONTH($C$52),"00")&"/"&YEAR($C$52)&"." -> Marché 2026 : 6 à 9 % TTC du loyer charges comprises en gestion complète, 4 à 6 % en agence en ligne. manda.fr, nousgerons.com. Vérifié le 05/09/2026. | E28: Annuelle | F28: Lu par le commentaire de la ligne Gestion locative.
B29: Taux de crédit immobilier moyen sur 20 ans | C29: 0.0327 | D29: ="Observatoire Crédit Logement / CSA, analyse du marché du mois d'août 2026 : 3,27 % sur 20 ans, taux moyen toutes durées 3,31 %, en hausse de 3 centièmes de point en juillet comme en août. lobservatoire.creditlogement.fr. Vérifié le "&TEXT(DAY($C$52),"00")&"/"&TEXT(MONTH($C$52),"00")&"/"&YEAR($C$52)&"." -> Observatoire Crédit Logement / CSA, analyse du marché du mois d'août 2026 : 3,27 % sur 20 ans, taux moyen toutes durées 3,31 %, en hausse de 3 centièmes de point en juillet comme en août. lobservatoire.creditlogement.fr. Vérifié le 05/09/2026. | E29: Mensuelle | F29: Lu par le commentaire de la ligne Taux du prêt. Donnée de projet : saisissez le taux de votre offre.
B30: Taux de crédit immobilier moyen sur 25 ans | C30: 0.0335 | D30: ="Observatoire Crédit Logement / CSA, analyse du marché du mois d'août 2026 : 3,35 % sur 25 ans, 3,14 % sur 15 ans, en hausse de 15 centièmes de point depuis décembre 2025. lobservatoire.creditlogement.fr. Vérifié le "&TEXT(DAY($C$52),"00")&"/"&TEXT(MONTH($C$52),"00")&"/"&YEAR($C$52)&"." -> Observatoire Crédit Logement / CSA, analyse du marché du mois d'août 2026 : 3,35 % sur 25 ans, 3,14 % sur 15 ans, en hausse de 15 centièmes de point depuis décembre 2025. lobservatoire.creditlogement.fr. Vérifié le 05/09/2026. | E30: Mensuelle
B31: Assurance emprunteur, contrat groupe, taux annuel sur capital initial | C31: 0.0036 | D31: ="Baromètres 2026, emprunteur de 35 ans non fumeur. pretclair.fr, covelia.fr. Vérifié le "&TEXT(DAY($C$52),"00")&"/"&TEXT(MONTH($C$52),"00")&"/"&YEAR($C$52)&"." -> Baromètres 2026, emprunteur de 35 ans non fumeur. pretclair.fr, covelia.fr. Vérifié le 05/09/2026. | E31: Annuelle | F31: Lu par le commentaire de la ligne Taux d'assurance.
B32: Assurance emprunteur, délégation, taux annuel sur capital initial | C32: 0.0017 | D32: ="Baromètres 2026, emprunteur de 35 ans non fumeur, équivalent sur capital initial. pretclair.fr, covelia.fr. Vérifié le "&TEXT(DAY($C$52),"00")&"/"&TEXT(MONTH($C$52),"00")&"/"&YEAR($C$52)&"." -> Baromètres 2026, emprunteur de 35 ans non fumeur, équivalent sur capital initial. pretclair.fr, covelia.fr. Vérifié le 05/09/2026. | E32: Annuelle | F32: Une délégation cotise en réalité sur le capital restant dû : le classeur est prudent.
B33: Part du terrain dans le prix, usage pour un appartement | C33: 0.15 | D33: ="Terrain non amortissable (BOFiP BOI-BIC-AMT-10-20). Usage comptable : 10 à 20 % pour un appartement, 20 à 30 % en zone tendue ou pour une maison. jedeclaremonmeuble.com, calcunet.fr. Vérifié le "&TEXT(DAY($C$52),"00")&"/"&TEXT(MONTH($C$52),"00")&"/"&YEAR($C$52)&"." -> Terrain non amortissable (BOFiP BOI-BIC-AMT-10-20). Usage comptable : 10 à 20 % pour un appartement, 20 à 30 % en zone tendue ou pour une maison. jedeclaremonmeuble.com, calcunet.fr. Vérifié le 05/09/2026. | E33: Stable | F33: Lu par le commentaire de la ligne Part du terrain.
B34: Quotité des loyers retenue par les banques (taux d'effort) | C34: 0.7 | D34: ="Pratique bancaire dans le calcul du taux d'effort HCSF : loyers comptés à 70 % pour couvrir vacance et charges. cpim.fr. Vérifié le "&TEXT(DAY($C$52),"00")&"/"&TEXT(MONTH($C$52),"00")&"/"&YEAR($C$52)&"." -> Pratique bancaire dans le calcul du taux d'effort HCSF : loyers comptés à 70 % pour couvrir vacance et charges. cpim.fr. Vérifié le 05/09/2026. | E34: Annuelle | F34: Lu par le commentaire de la ligne Part du loyer absorbée par la mensualité.
B36: BORNES DE SAISIE (VALIDATIONS ET CONTRÔLE GLOBAL)
B37: Paramètre | C37: Valeur | D37: Source (organisme, texte, date) | E37: Mise à jour | F37: Commentaire
B38: Borne de saisie : taux du prêt maximal | C38: 0.2 | D38: ="Borne technique du classeur, pas un barème : refuse une saisie aberrante. Vérifié le "&TEXT(DAY($C$52),"00")&"/"&TEXT(MONTH($C$52),"00")&"/"&YEAR($C$52)&"." -> Borne technique du classeur, pas un barème : refuse une saisie aberrante. Vérifié le 05/09/2026. | E38: Sans objet | F38: Au-delà, la validation refuse la saisie et le contrôle global passe au rouge.
B39: Borne de saisie : durée du prêt maximale | C39: 30 | D39: ="Borne technique du classeur, au-dessus du plafond HCSF pour les cas dérogatoires. Vérifié le "&TEXT(DAY($C$52),"00")&"/"&TEXT(MONTH($C$52),"00")&"/"&YEAR($C$52)&"." -> Borne technique du classeur, au-dessus du plafond HCSF pour les cas dérogatoires. Vérifié le 05/09/2026. | E39: Sans objet | F39: Années entières de 1 à cette borne.
B40: Borne de saisie : taux d'assurance maximal | C40: 0.05 | D40: ="Borne technique du classeur, pas un barème. Vérifié le "&TEXT(DAY($C$52),"00")&"/"&TEXT(MONTH($C$52),"00")&"/"&YEAR($C$52)&"." -> Borne technique du classeur, pas un barème. Vérifié le 05/09/2026. | E40: Sans objet
B41: Borne de saisie : part du terrain maximale | C41: 0.5 | D41: ="Borne technique du classeur, pas un barème. Vérifié le "&TEXT(DAY($C$52),"00")&"/"&TEXT(MONTH($C$52),"00")&"/"&YEAR($C$52)&"." -> Borne technique du classeur, pas un barème. Vérifié le 05/09/2026. | E41: Sans objet
B42: Plancher de plausibilité d'un taux saisi | C42: 0.001 | D42: ="Convention CorpusImmo, commune aux matrices qui saisissent des taux. Vérifié le "&TEXT(DAY($C$52),"00")&"/"&TEXT(MONTH($C$52),"00")&"/"&YEAR($C$52)&"." -> Convention CorpusImmo, commune aux matrices qui saisissent des taux. Vérifié le 05/09/2026. | E42: Stable | F42: Un taux entre 0 et 0,10 % signale presque toujours une saisie en fraction (0,0325 tapé pour 3,25 %). Le contrôle « Taux vraisemblable » passe au rouge dans ce cas, sauf à 0 % exactement (prêt à taux zéro, ou pas d'assurance).
B44: LISTES DÉROULANTES DU CALCULATEUR
B45: Régime fiscal (liste de C47) | C45: TMI (liste de C48) | D45: Source (organisme, texte, date) | E45: Mise à jour | F45: Commentaire
B46: Location nue, micro-foncier | C46: 0 | D46: ="Régimes : libellés fixes, testés par les formules du Calculateur. TMI : CGI art. 197, barème de la LF 2026 (loi n° 2026-103 du 19/02/2026) : 0, 11, 30, 41, 45 %. service-public.gouv.fr. Vérifié le "&TEXT(DAY($C$52),"00")&"/"&TEXT(MONTH($C$52),"00")&"/"&YEAR($C$52)&"." -> Régimes : libellés fixes, testés par les formules du Calculateur. TMI : CGI art. 197, barème de la LF 2026 (loi n° 2026-103 du 19/02/2026) : 0, 11, 30, 41, 45 %. service-public.gouv.fr. Vérifié le 05/09/2026. | E46: TMI : chaque loi de finances | F46: CGI art. 32. Loyers bruts du foyer inférieurs ou égaux au plafond.
B47: Location nue, réel foncier | C47: 0.11 | F47: CGI art. 31 et 156. Charges réelles, intérêts, travaux, déficit foncier.
B48: Meublé, LMNP micro-BIC | C48: 0.3 | F48: CGI art. 50-0. Abattement forfaitaire sur les recettes.
B49: Meublé, LMNP réel (amortissement) | C49: 0.41 | F49: CGI art. 39 C. Charges réelles et amortissement, sans création de déficit.
B50: Meublé de tourisme non classé, micro-BIC | C50: 0.45 | F50: CGI art. 50-0, loi Le Meur. Abattement réduit et plafond bas.
B52: Dernière vérification des paramètres | C52: 46270 | D52: Aucun de ces taux n'est recopié dans une formule : toutes pointent ici. Les mentions de vérification de cet onglet et de Méthode lisent cette date.
B54: Ces valeurs sont volontairement isolées ici. Un modèle qui embarque un barème au cœur de ses formules devient faux dès que la loi bouge,
B55: sans que personne ne s'en aperçoive. Vérifiez-les avant tout usage engageant, et notez la date de votre dernière vérification ci-dessus.
B58: CorpusImmo, millésime 2026. Modèle d'aide à la décision : ne constitue ni un conseil en investissement, ni un conseil fiscal, ni une expertise au sens de la charte de l'expertise en évaluation immobilière. Vérifiez les paramètres avant tout engagement.

Sheet Méthode
B1: CorpusImmo · www.corpus.immo · Estimer, comparer, décider. Sur les ventes réelles.
B2: Méthode de calcul
B3: Ce que le modèle fait, ce qu'il ne fait pas, et sur quelles sources reposent ses chiffres.
B5: CONVENTIONS RETENUES, ET CE QU'ELLES COÛTENT
B6: Coût total de l'opération | C6: Prix net vendeur + frais d'agence + frais de notaire + travaux + mobilier. C'est le dénominateur de tous les rendements : un rendement calculé sur le seul prix d'achat est systématiquement flatteur de 10 à 15 %.
B7: Loyer annuel encaissé | C7: Loyer mensuel hors charges × 12, diminué de la vacance exprimée en semaines. On raisonne sur le loyer réellement perçu, pas sur le loyer théorique. Un mois de vacance vaut 4,33 semaines ; la saisie est bornée de 0 à 52.
B8: Rendement brut | C8: Loyer annuel encaissé ÷ coût total. C'est le chiffre que tout le monde affiche. Il ignore les charges, l'impôt et le financement : il sert à comparer, pas à décider. Le classeur affiche aussi le rendement brut des annonces (loyer théorique sur prix net vendeur), plus flatteur d'environ 4 points sur l'exemple, pour parler la même langue que le marché.
B9: Rendement net de charges | C9: (Loyer annuel encaissé − charges) ÷ coût total. Les charges incluent la taxe foncière hors TEOM, l'assurance PNO, la copropriété non récupérable, la comptabilité, une provision d'entretien et la gestion locative. C'est un rendement de trésorerie : la provision y compte, même si elle n'est pas déductible.
B10: Rendement net-net | C10: (Loyer net de charges − impôt) ÷ coût total. C'est le seul qui décide, parce qu'il dépend de votre situation fiscale personnelle. C'est le chiffre mis en avant par ce modèle.
B11: Base imposable, année 1 | C11: Micro-foncier et micro-BIC : loyer annuel encaissé diminué de l'abattement forfaitaire (le micro-BIC retient en principe les loyers charges comprises ; le classeur prend le loyer hors charges, légèrement favorable). Réel foncier (CGI art. 31) : loyer encaissé, moins la taxe foncière hors TEOM, la PNO, la copropriété non récupérable, la gestion, les intérêts et l'assurance emprunteur de la première année, et les travaux déductibles saisis. La provision d'entretien et la comptabilité ne sont pas déduites : seules les dépenses payées le sont. LMNP réel (CGI art. 39 C) : loyer encaissé, moins les mêmes charges plus la comptabilité, moins intérêts et assurance, moins l'amortissement. Les intérêts sont ceux des douze premières échéances (CUMIPMT) ; ils diminuent ensuite chaque année, ce qui alourdit l'impôt à mesure que le prêt s'amortit.
B12: Déficit foncier (réel foncier) | C12: Quand la base est négative, le déficit qui vient des charges autres que les intérêts s'impute sur le revenu global dans la limite du plafond de Paramètres (10 700 €) : l'impôt de l'année 1 devient négatif, à hauteur du déficit imputé multiplié par la TMI, sans effet sur les prélèvements sociaux. Le surplus, et la part du déficit qui vient des intérêts et de l'assurance, se reportent sur les revenus fonciers des dix années suivantes (CGI art. 156, I-3°). L'imputation sur le revenu global engage à louer le bien jusqu'au 31 décembre de la troisième année suivante. Le plafond majoré à 21 400 € pour rénovation énergétique, institué par la loi n° 2022-1499 du 1er décembre 2022 de finances rectificative pour 2022 (art. 12), est temporaire et ne couvre que les dépenses payées entre le 1er janvier 2023 et le 31 décembre 2025, pour un logement passant d'une classe E, F ou G à une classe A, B, C ou D justifiée au plus tard le 31 décembre 2027. Il n'est donc pas ouvert à une dépense payée en 2026 : le classeur applique 10 700 € et laisse la cellule de Paramètres modifiable pour un dossier qui remplit encore les conditions.
B13: Amortissement (LMNP réel) | C13: Le bâti (prix, honoraires d'agence et frais de notaire, hors quote-part de terrain saisie dans le Calculateur), les travaux et le mobilier s'amortissent en linéaire sur les durées de Paramètres. Simplification : linéaire simplifié plutôt que par composants, frais d'acquisition incorporés au bâti plutôt que passés en charge la première année. L'amortissement ne peut pas créer de déficit (CGI art. 39 C, II) : la part non imputée est reportée sans limite de durée, ce qui se lit sur la ligne « Reporté sur les années suivantes ». Depuis la LF 2025 (art. 84), les amortissements déduits sont réintégrés dans la plus-value à la revente : le classeur ne modélise pas la revente.
B14: Plafonds des régimes micro | C14: Le classeur compare le loyer hors charges × 12 aux plafonds de Paramètres (15 000 € en micro-foncier, 83 600 € en micro-BIC longue durée ou classé, 15 000 € en meublé de tourisme non classé). Les plafonds s'apprécient en réalité sur l'ensemble des revenus du foyer de même nature : si vous avez d'autres biens, vérifiez à la main.
B15: Prélèvements sociaux | C15: 17,2 % sur les revenus fonciers (location nue). 18,6 % sur les BIC de location meublée depuis les revenus 2025 (LFSS 2026, CSG portée à 10,6 %). Le classeur choisit le taux selon le régime.
B16: Assurance emprunteur | C16: Calculée sur le capital initial, constante sur toute la durée : c'est la convention des contrats groupe bancaires. Une délégation d'assurance cotise sur le capital restant dû et coûte 30 à 40 % de moins sur 25 ans à taux égal : le classeur est alors prudent.
B17: Cash-flow mensuel | C17: (Revenu net de charges − impôt) ÷ 12 − mensualité totale. Négatif, il devient un effort d'épargne : la somme à sortir chaque mois pour détenir le bien.
... B19: Taux et dates | C19: Tous les taux sont des fractions affichées en pourcentage : tapez 3,4 dans une cellule de taux, elle affiche 3,40 % et contient 0,034. Aucune formule ne divise par 100. Les durées sont en années entières, les intérêts en mensuel (taux nominal divisé par 12). Les mentions de vérification de Paramètres et de cet onglet lisent la date de dernière vérification de Paramètres.
B21: CE QUE CE MODÈLE NE FAIT PAS
B22: • Il raisonne sur la première année. Les intérêts d'emprunt baissent ensuite, l'impôt monte, l'amortissement reporté se consomme.
B23: • Il ne modélise ni la revalorisation des loyers, ni celle du bien, ni la plus-value à la revente (ni la réintégration des amortissements LMNP dans cette plus-value).
B24: • Il ne calcule pas la CSG déductible du revenu global l'année suivante (6,8 points, réel foncier et LMNP réel), ni la CFE due en meublé, ni le forfait de 20 € par local de frais de gestion, ni les charges refacturées au locataire.
B25: • Il ne calcule pas les frais de notaire (saisis tels quels), ni les frais de garantie et de dossier du prêt, ni le TAEG.
B26: • Il ne calcule pas le taux d'effort au sens du HCSF : c'est l'objet de la matrice Capacité d'emprunt et bilan patrimonial.
B27: • Il ne remplace ni un expert-comptable, ni un conseil fiscal.
B29: SOURCES (LUES DANS PARAMÈTRES, COLONNE D)
B30: Prélèvements sociaux, revenus fonciers (location nue) | C30: =Paramètres!$D$8 -> CSS art. L136-6 (assiette des revenus du patrimoine) et L136-8 (taux : CSG 9,2 %), CRDS 0,5 %, CGI art. 235 ter (solidarité 7,5 %). Inchangé par la LFSS 2026. Vérifié le 05/09/2026.
B31: Prélèvements sociaux, BIC de location meublée (LMNP) | C31: =Paramètres!$D$9 -> LFSS 2026, loi n° 2025-1403 du 30/12/2025, art. 12, modifiant CSS art. L136-8 : CSG portée de 9,2 % à 10,6 % dès les revenus 2025. Vérifié le 05/09/2026.
B32: Abattement micro-foncier | C32: =Paramètres!$D$10 -> CGI art. 32. Vérifié le 05/09/2026.
B33: Plafond de revenus bruts fonciers du micro-foncier | C33: =Paramètres!$D$11 -> CGI art. 32, I. Vérifié le 05/09/2026.
B34: Abattement micro-BIC, meublé longue durée ou tourisme classé | C34: =Paramètres!$D$12 -> CGI art. 50-0 modifié par la loi n° 2024-1039 du 19/11/2024 (dite Le Meur), revenus 2025 et suivants. Vérifié le 05/09/2026.
B35: Plafond de recettes du micro-BIC, meublé longue durée ou classé | C35: =Paramètres!$D$13 -> CGI art. 50-0, revalorisation triennale 2026-2028 : 83 600 € pour les recettes 2026 (77 700 € pour 2025). jedeclaremonmeuble.com, cpim.fr. Vérifié le 05/09/2026.
B36: Abattement micro-BIC, meublé de tourisme non classé | C36: =Paramètres!$D$14 -> CGI art. 50-0, loi n° 2024-1039 du 19/11/2024, revenus 2025 et suivants. Vérifié le 05/09/2026.
B37: Plafond de recettes du micro-BIC, meublé de tourisme non classé | C37: =Paramètres!$D$15 -> CGI art. 50-0, loi n° 2024-1039 du 19/11/2024. Vérifié le 05/09/2026.
B38: Plafond d'imputation du déficit foncier sur le revenu global | C38: =Paramètres!$D$16 -> CGI art. 156, I-3°. Rehaussement à 21 400 € institué par la loi n° 2022-1499 du 01/12/2022 de finances rectificative pour 2022, art. 12 ; décret n° 2023-297 du 21/04/2023 ; CGI annexe III art. 41 DO ; BOFiP BOI-RFPI-BASE-30-20. Vérifié le 05/09/2026.
B39: Durée maximale d'un prêt immobilier (HCSF) | C39: =Paramètres!$D$17 -> HCSF, décision D-HCSF-2021-7 du 29/09/2021, contraignante depuis le 01/01/2022, confirmée par la décision D-HCSF-2023-2 du 29/06/2023 : 25 ans (27 ans avec différé), taux d'effort 35 %. economie.gouv.fr/hcsf. Vérifié le 05/09/2026.
B40: Durée d'amortissement du bâti, LMNP réel | C40: =Paramètres!$D$21 -> Usage des experts-comptables LMNP : 25 à 40 ans en linéaire simplifié (ou par composants, BOFiP BOI-BIC-AMT-10-40-10). jedeclaremonmeuble.com, calcunet.fr. Vérifié le 05/09/2026.
B41: Durée d'amortissement des travaux, LMNP réel | C41: =Paramètres!$D$22 -> Usage : 10 à 20 ans selon la nature (aménagements 10 à 12 ans, gros œuvre 25 à 30 ans). calcunet.fr. Vérifié le 05/09/2026.
B42: Durée d'amortissement du mobilier, LMNP réel | C42: =Paramètres!$D$23 -> Usage : 5 à 10 ans. jedeclaremonmeuble.com. Vérifié le 05/09/2026.
B43: Frais de notaire dans l'ancien, ordre de grandeur (% du prix net vendeur) | C43: =Paramètres!$D$24 -> DMTO 6,32 % dans la grande majorité des départements (LF 2025 art. 116, droit majoré du 01/04/2025 au 31/03/2028), émoluments (barème prorogé au 29/02/2028), CSI 0,10 % : 7,5 à 8,5 % pour 90 000 €. taximmo.fr, pretto.fr. Vérifié le 05/09/2026.
B44: Frais de notaire dans le neuf, ordre de grandeur (% du prix) | C44: =Paramètres!$D$25 -> Vente en TVA : taxe de publicité foncière 0,715 %, émoluments, CSI : 2 à 3 % du prix. pretto.fr. Vérifié le 05/09/2026.
B45: Assurance propriétaire non occupant, ordre de grandeur annuel (appartement) | C45: =Paramètres!$D$26 -> Comparateurs 2026 : 100 à 150 € par an pour un appartement, davantage en grande ville. selectra.info, lesfurets.com. Vérifié le 05/09/2026.
B46: Expert-comptable LMNP réel, honoraires annuels, ordre de grandeur | C46: =Paramètres!$D$27 -> Tarifs 2026 : 300 à 600 € TTC en cabinet en ligne, 600 à 900 € en cabinet traditionnel, pour un lot. jedeclaremonmeuble.com, indy.fr. Vérifié le 05/09/2026.
B47: Gestion locative en agence, honoraires usuels (% du loyer) | C47: =Paramètres!$D$28 -> Marché 2026 : 6 à 9 % TTC du loyer charges comprises en gestion complète, 4 à 6 % en agence en ligne. manda.fr, nousgerons.com. Vérifié le 05/09/2026.
B48: Taux de crédit immobilier moyen sur 20 ans | C48: =Paramètres!$D$29 -> Observatoire Crédit Logement / CSA, analyse du marché du mois d'août 2026 : 3,27 % sur 20 ans, taux moyen toutes durées 3,31 %, en hausse de 3 centièmes de point en juillet comme en août. lobservatoire.creditlogement.fr. Vérifié le 05/09/2026.
B49: Taux de crédit immobilier moyen sur 25 ans | C49: =Paramètres!$D$30 -> Observatoire Crédit Logement / CSA, analyse du marché du mois d'août 2026 : 3,35 % sur 25 ans, 3,14 % sur 15 ans, en hausse de 15 centièmes de point depuis décembre 2025. lobservatoire.creditlogement.fr. Vérifié le 05/09/2026.
B50: Assurance emprunteur, contrat groupe, taux annuel sur capital initial | C50: =Paramètres!$D$31 -> Baromètres 2026, emprunteur de 35 ans non fumeur. pretclair.fr, covelia.fr. Vérifié le 05/09/2026.
B51: Assurance emprunteur, délégation, taux annuel sur capital initial | C51: =Paramètres!$D$32 -> Baromètres 2026, emprunteur de 35 ans non fumeur, équivalent sur capital initial. pretclair.fr, covelia.fr. Vérifié le 05/09/2026.
B52: Part du terrain dans le prix, usage pour un appartement | C52: =Paramètres!$D$33 -> Terrain non amortissable (BOFiP BOI-BIC-AMT-10-20). Usage comptable : 10 à 20 % pour un appartement, 20 à 30 % en zone tendue ou pour une maison. jedeclaremonmeuble.com, calcunet.fr. Vérifié le 05/09/2026.
B53: Quotité des loyers retenue par les banques (taux d'effort) | C53: =Paramètres!$D$34 -> Pratique bancaire dans le calcul du taux d'effort HCSF : loyers comptés à 70 % pour couvrir vacance et charges. cpim.fr. Vérifié le 05/09/2026.
B54: Barème de l'impôt sur le revenu (TMI) | C54: =Paramètres!$D$46 -> Régimes : libellés fixes, testés par les formules du Calculateur. TMI : CGI art. 197, barème de la LF 2026 (loi n° 2026-103 du 19/02/2026) : 0, 11, 30, 41, 45 %. service-public.gouv.fr. Vérifié le 05/09/2026.
B55: Charges déductibles au réel foncier | C55: CGI art. 31, I-1° ; BOFiP BOI-RFPI-DECLA-20 ; règle d'imputation du déficit : CGI art. 156, I-3° et BOFiP BOI-RFPI-BASE-30-20.
B56: Amortissement LMNP et non-création de déficit | C56: CGI art. 39 C, II ; BOFiP BOI-BIC-AMT-10-40-10 (composants) ; LF 2025 art. 84 (réintégration des amortissements dans la plus-value, cessions depuis le 15/02/2025).
B58: CorpusImmo, millésime 2026. Modèle d'aide à la décision : ne constitue ni un conseil en investissement, ni un conseil fiscal, ni une expertise au sens de la charte de l'expertise en évaluation immobilière. Vérifiez les paramètres avant tout engagement.
