Workbook

Sheet Mode d'emploi
B1: CorpusImmo · www.corpus.immo · Estimer, comparer, décider. Sur les ventes réelles.
B2: Mode d'emploi
B3: À quoi sert ce classeur, dans quel ordre le remplir, et comment lire ce qu'il répond.
B6: À QUOI SERT CE CLASSEUR
B7: Vous regardez un appartement ou une maison à rénover. Ce classeur répond à la question qui précède toute offre d'achat : combien vont coûter les travaux, en fourchette crédible, avant d'avoir un seul devis ?
B8: Il part de cinq données du bien (surface, niveaux, hauteur sous plafond, façades exposées, part rénovée), en déduit la géométrie, chiffre vingt-huit postes en quantité × prix unitaire, le prix étant pris dans une fourchette de marché selon un curseur, ajoute aléas et honoraires, calcule la TVA ligne à ligne à trois taux, et qualifie le chantier au regard de la règle de l'immeuble rendu neuf. Il rend trois budgets : bas de fourchette, retenu, haut de fourchette.
B9: Vous remplissez les cellules violettes de haut en bas ; à mesure que les devis arrivent, vous forcez les quantités et les prix, et la fourchette se referme. Deux mots reviennent partout : le gros œuvre, ce qui tient le bâtiment (fondations, murs porteurs, planchers porteurs, charpente), et le second œuvre, tout ce qui vient ensuite (cloisons, fenêtres, plomberie, électricité, chauffage, finitions).
B10: Vous êtes | C10: Ce que le classeur vous donne
B11: Marchand de biens | C11: Le budget travaux TTC en fourchette pour bâtir l'offre, et l'alerte sur la bascule de tout le chantier à 20 % de TVA (immeuble rendu neuf).
B12: Investisseur locatif | C12: Un ordre de grandeur au m² à comparer aux repères du marché, et la liste des postes à faire deviser.
B13: Maître d'œuvre, architecte | C13: Un cadrage par lot à confronter aux devis d'entreprises, avec le contrôle des parts par famille.
B14: Agent immobilier, chasseur | C14: Une réponse chiffrée en cinq minutes à « combien de travaux ? », avec ses hypothèses écrites.
B15: Banquier, courtier | C15: Un budget travaux justifié ligne à ligne, aléas et honoraires compris, pour le plan de financement.
B17: LE PRINCIPE, EN UNE LIGNE
B18: Quantité déduite du bien × prix pris dans la fourchette selon le curseur = lot ; lots + aléas + honoraires + TVA par ligne = budget TTC
B20: LES ONGLETS, DANS L'ORDRE OÙ ON LES REMPLIT
B21: Onglet | C21: Ce que vous y faites | D21: Ce que vous y lisez
B22: Mode d'emploi | C22: Rien à saisir. Vous lisez ce guide. | D22: La marche à suivre et l'exemple guidé.
B23: Chiffrage | C23: Vous décrivez le bien, réglez le curseur, les aléas et les honoraires, forcez des quantités et des prix dans le tableau, puis répondez aux douze questions du bloc TVA. | D23: Le tableau des lots, le récapitulatif en trois colonnes (bas, retenu, haut), les coûts au m², le niveau de rénovation, le contrôle par famille et sept contrôles vert / rouge.
B24: Référentiel | C24: Vous confrontez les fourchettes de prix, les taux de TVA et les ratios à vos chantiers, et les corrigez. Vous nommez les postes libres. | D24: Chaque valeur avec sa source datée : barèmes de TVA, seuils de l'immeuble neuf, coefficients de géométrie, bandes par famille, fourchettes 2026.
B25: Méthode | C25: Rien à saisir. | D25: Les conventions de calcul, la règle de TVA complète, ce que le modèle ne fait pas, les sources.
B27: LE CODE COULEUR, ET COMMENT DÉVERROUILLER UNE CELLULE
B28: Cellule | C28: Ce que c'est | D28: Ce que vous faites
B29: Fond violet clair | C29: Saisie utilisateur | D29: Vous la remplissez, ou vous l'effacez avec la touche Suppr, même feuille protégée. Jamais de formule dedans. Dans le tableau, une cellule violette vide laisse l'automatisme.
B30: Fond blanc | C30: Calcul | D30: Vous la lisez. Elle est verrouillée.
B31: Fond violet pâle, gras | C31: Résultat de bloc, chiffre clé | D31: Vous la lisez. C'est un chiffre à retenir.
B32: Bandeau violet | C32: Titre de section, en-tête de tableau | D32: Repère de navigation.
B33: Texte gris, à droite | C33: Commentaire d'aide, ordre de grandeur | D33: Une phrase par ligne pour savoir quoi saisir.
B34: Vert / rouge | C34: Contrôle de cohérence | D34: Rouge, la cellule affiche « À CORRIGER » : corrigez la saisie indiquée par le commentaire à droite. Le récapitulatif reste vide tant qu'un contrôle bloquant est rouge.
B35: Les onglets sont protégés sans mot de passe pour éviter d'écraser une formule par erreur. Pour modifier une cellule blanche : onglet Révision, puis « Ôter la protection de la feuille ». Aucun mot de passe n'est demandé. En pratique, tout ce qu'un professionnel doit régler est violet, dans le Chiffrage ou dans le Référentiel.
B37: LA MARCHE À SUIVRE, ÉTAPE PAR ÉTAPE
B38: Étape | C38: Où (onglet et plage) | D38: Ce que vous faites | E38: Pourquoi
B39: 0. L'exemple livré | C39: Chiffrage!D7:D16, F29:F59 et J29:J59, D62:D77 | D39: Le classeur est livré rempli d'un exemple (appartement de 90 m², détaillé plus bas). Gardez-le pour vous repérer, ou effacez toutes les cellules violettes du Chiffrage avant de saisir votre dossier : sélectionnez-les et appuyez sur Suppr, la protection de la feuille ne s'y oppose pas. Vérifiez surtout les saisies secondaires qui n'ont pas de raison d'être chez vous : les 8 quantités forcées de la colonne F (dont les 6 zéros qui désactivent couverture, charpente, combles, chaudière, ravalement et VRD, la voirie et les réseaux du terrain), les douze réponses du bloc TVA, le taux forcé D77 (à laisser vide) et le curseur D14. | E39: Une saisie résiduelle de l'exemple est l'erreur la plus probable d'un premier usage : sur une maison, les trois zéros hérités de l'appartement (couverture, charpente, combles) font disparaître 15 030 € de travaux sans un mot.
B40: 1. Vos prix | C40: Référentiel!E70:G100, puis C109 | D40: Premier chiffrage, sans chantier derrière vous : ne touchez à rien, les fourchettes livrées sont sourcées ligne à ligne et datées 2026, elles suffisent à cadrer. Ensuite, à chaque devis reçu, corrigez la ligne concernée, ainsi que son taux de TVA si le devis en applique un autre, et mettez la date de vérification à jour. Nommez les postes libres (lignes 98 à 100) si votre chantier a du désamiantage, du plomb ou un ascenseur. | E40: Ce sont vos prix et vos ratios qui comptent dès que vous en avez. Tout le classeur pointe ici : rien n'est écrit en dur ailleurs.
B41: 2. Le bien | C41: Chiffrage!D7:D11 | D41: Surface habitable (à défaut, la surface Carrez de l'annonce en est très proche pour un appartement), nombre de niveaux, hauteur sous plafond mesurée sur place, façades exposées (4 pour une maison, 2 pour un appartement traversant, 1 sinon), part du logement rénovée. | E41: La surface pilote presque toutes les quantités ; les façades distinguent une maison d'un appartement ; la part rénovée réduit dépose, réseaux, sols et peinture.
B42: 3. Le chiffrage | C42: Chiffrage!D14:D16 | D42: Curseur de fourchette (repères du Référentiel : province 40 % à 60 %, Île-de-France 60 % à 80 %), provision pour aléas (10 % à 15 % dans l'ancien), honoraires de maîtrise d'œuvre (8 % à 12 % en exécution). | E42: Le curseur représente la tension du marché et le type d'entreprise. Les aléas et les honoraires s'ajoutent aux lots avant TVA.
B43: 4. Le tableau des lots | C43: Chiffrage!F29:F59 et J29:J59 | D43: Deux colonnes violettes seulement, F (quantité forcée) et J (prix forcé) : les autres sont calculées. Quantité forcée : 0 pour désactiver un poste (couverture, charpente, combles, chaudière, ravalement et VRD sont livrés à 0 pour un appartement), une valeur comptée sur plan sinon, vide pour l'automatisme. Prix forcés à mesure que les devis arrivent, en priorité sur pompe à chaleur, cuisine, salle de bains, ventilation. | E43: Une valeur forcée l'emporte toujours sur le calcul sans le détruire. Un prix forcé vaut dans les trois colonnes du récapitulatif : c'est un devis.
B44: 5. La TVA du chantier | C44: Chiffrage!D62:D73 et D77 | D44: Douze réponses dans des listes déroulantes : nature du local, ancienneté, extension, trois critères de gros œuvre, six éléments de second œuvre. Lisez D76 : vert « Taux par ligne », ou rouge « TOUT À 20 % ». Laissez D77 vide sauf pour imposer un taux unique. | E44: C'est la règle de l'immeuble rendu neuf (CGI art. 257) : dès qu'un critère est rempli, l'opération entière perd les taux réduits. Le classeur l'applique et l'affiche.
B45: 6. Les sept contrôles | C45: Chiffrage!D24:D25, D80:D83, H110 ; Référentiel!C7 | D45: Vérifiez que tout est vert. Un rouge désigne la saisie à corriger dans son commentaire. Les contrôles rejouent aussi les bornes des listes et des validations : une valeur collée ou héritée de l'exemple n'y échappe pas. | E45: Tant qu'un contrôle bloquant est rouge, le récapitulatif ou la TVA restent vides : le classeur préfère ne rien afficher plutôt qu'un chiffre faux.
B46: 7. Les résultats | C46: Chiffrage!D87:F99 et E100 | D46: Rien à saisir. Lisez les trois colonnes : bas de fourchette, retenu, haut de fourchette. Puis le contrôle par famille en dessous. | E46: Le sous-total des lots se compare à un devis d'entreprise générale ; le TTC est le budget à financer ; les parts par famille disent si un lot manque.
B48: EXEMPLE GUIDÉ
B49: Le fichier est livré avec un appartement traversant de 90 m² sur un niveau, hauteur sous plafond 2,50 m, deux façades exposées, rénové à 100 %. Le classeur en déduit une emprise de 90 m² (D19), un périmètre de 39,8 m (D20) et 50 m² de murs de façade (D21). Curseur à 50 %, aléas 12 %, honoraires 10 %.
B50: Dans le tableau, 8 quantités sont forcées : 1 ouverture de mur porteur, 20 m² de reprise de maçonnerie, et 0 sur la couverture, la charpente, les combles, la chaudière fossile, le ravalement et les VRD (un appartement n'a pas de toit à lui, et il est chauffé par une pompe à chaleur). Tout le reste est automatique : 7 fenêtres, 6 radiateurs, 6 blocs-portes, 1 salle de bains, 2 WC. La peinture, par exemple, ressort à 90 m² au sol × 82 € = 7 380 € HT (L50) ; la pompe à chaleur à 8 750 € HT au milieu de sa fourchette (L44), un prix à forcer dès le premier devis.
B51: Le bloc TVA dit : habitation, achevée depuis plus de deux ans, sans extension, gros œuvre intact, et cinq éléments de second œuvre refaits sur six (huisseries, cloisons, plomberie, électricité, chauffage ; les planchers non porteurs sont conservés). D74 affiche 5, D75 affiche Non, D76 affiche « Taux par ligne » en vert : les taux par ligne s'appliquent. D79 compte 5 éléments refaits par le chiffrage lui-même, cohérent avec les réponses (D83 : OK).
B52: Récapitulatif, colonne retenue : sous-total des lots 99 905 € (E87), aléas 11 989 €, honoraires 9 991 €, total HT 121 884 € (E90). TVA : 1 474 € à 5,5 % (fenêtres, porte, isolation, pompe à chaleur, VMC), 8 510 € à 10 %, 1 998 € à 20 % (les honoraires), soit 11 982 €. Total TTC 133 866 € (E95), 1 487 € par m² (E99) : niveau « Rénovation » (E100). Lots seuls : 1 110 € par m² HT (E97).
B53: Fourchette : 72 166 € TTC au bas de fourchette (D95) et 195 565 € au haut (F95), soit 802 € à 2 173 € par m². C'est la fourchette d'un chantier sans aucun devis : elle se referme à mesure que vous forcez des prix.
B54: Contrôle par famille : la famille Technique pèse 35,9 % du sous-total (E106) pour une bande de 25 à 35 % : « Élevé : à justifier ». C'est normal, une pompe à chaleur déplace le centre de gravité du budget ; le contrôle fait son travail, il ne signale pas un défaut. H110 affiche « Tout est classé ».
B55: Deux variantes à essayer. Passez D68 à Oui : les six éléments sont refaits, D75 passe à Oui, D76 vire au rouge « TOUT À 20 % », toutes les lignes passent à 20 % et le TTC monte à 146 261 € (+ 12 395 €). Remettez Non. Puis remplacez la pompe à chaleur par une chaudière gaz : 0 en F44, cellule F45 vidée : la ligne chaudière est à 20 % de TVA et le TTC devient 130 529 €.
B57: LES CHIFFRES À REGARDER, ET CE QU'ILS VALENT
B58: Indicateur | C58: Où | D58: Repère métier | E58: Ce qu'il dit vraiment
B59: Sous-total des lots HT | C59: Chiffrage!E87 | D59: Le chiffre à comparer à un devis d'entreprise générale. | E59: Hors aléas, hors honoraires, hors TVA. Les colonnes bas et haut donnent la marge d'incertitude tant que les devis manquent.
B60: Total TTC | C60: Chiffrage!E95 | D60: Le budget à financer. | E60: Lots, aléas, honoraires et TVA. La colonne haute est celle à présenter au banquier prudent.
B61: Coût au m² TTC | C61: Chiffrage!E99 et E100 | D61: 250 à 750 €/m² rafraîchir, 750 à 1 500 rénover, 1 500 et plus rénovation lourde ou restructuration (Hellowatt, Illico 2026). | E61: Aléas et honoraires compris. Très en dessous de la fourchette basse : un lot manque, regardez le contrôle par famille.
B62: Taux réduits admis | C62: Chiffrage!D76 | D62: Vert : taux par ligne. Rouge : tout le chantier à 20 %. | E62: La règle de l'immeuble rendu neuf. Rouge sur une rénovation lourde n'est pas rare : c'est le moment de reconsidérer le programme (garder un élément de second œuvre) ou le prix d'achat.
B63: Dont TVA à 5,5 % | C63: Chiffrage!E91 | D63: Le montant à défendre. | E63: Par les critères techniques des équipements (arrêté du 24/12/2024) et la mention certifiée sur le devis.
B64: Part de la famille Technique | C64: Chiffrage!E106 | D64: 25 à 35 % en rénovation lourde ; une pompe à chaleur pousse au-dessus. | E64: Une famille sous sa bande signale presque toujours un poste oublié ; au-dessus, un choix à justifier.
B66: LES DONNÉES À METTRE À JOUR, OÙ ET POURQUOI
B67: Deux familles de données. Les barèmes et les repères (taux de TVA, seuils de l'immeuble neuf, fourchettes de prix, bandes par famille, repères au m²) changent avec la loi ou le marché, à date fixe, et se rafraîchissent depuis une source indiquée dans le Référentiel. Les données de projet (surface, niveaux, façades, curseur, quantités et prix forcés, réponses du bloc TVA) sont propres à chaque dossier. L'architecture du classeur ne change pas quand les données changent : seules les cellules violettes bougent.
B68: Une seule date commande tout, Référentiel!C109 : chaque mention « Vérifié le » du Référentiel et de Méthode la lit, vous n'avez donc qu'une cellule à corriger. En revanche, les chiffres cités en toutes lettres dans ce guide et dans Méthode (repères au m², fourchettes de curseur, d'aléas et d'honoraires, montants de l'exemple) sont du texte, millésime 2026 : relisez-les à chaque mise à jour du Référentiel, ils ne se recalculent pas.
B69: Paramètre | C69: Onglet et cellule | D69: Ce qu'il pilote | E69: Source à consulter, fréquence
B70: Taux de TVA (20, 10, 5,5 %) | C70: Référentiel!C10:C12 | D70: Liste des taux par ligne et du taux forcé, TVA du récapitulatif | E70: CGI art. 278, 279-0 bis, 278-0 bis A ; chaque loi de finances
B71: Seuils de l'immeuble neuf et de l'extension | C71: Référentiel!C13:C14 | D71: Indication des éléments refaits, règle de bascule | E71: CGI art. 257 et annexe II art. 245 A ; stable
B72: Coefficients de géométrie | C72: Référentiel!C19:C21 | D72: Périmètre, murs de façade, surface de toit | E72: Convention CorpusImmo ; à adapter par dossier (plan en L, toit plat)
B73: Repères au m² TTC | C73: Référentiel!C22:C23 | D73: Niveau de rénovation affiché | E73: Hellowatt, Illico Travaux ; annuelle
B74: Repères de saisie (curseur par zone, aléas, honoraires) | C74: Référentiel!C27:D32 | D74: Les ordres de grandeur affichés dans les commentaires du Chiffrage | E74: Observatoire ARTEP, maitre-doeuvre.fr, Ootravaux ; annuelle
B75: Bandes usuelles par famille | C75: Référentiel!C36:D41 | D75: Verdicts du contrôle par famille | E75: Convention CorpusImmo ; à caler sur vos chantiers
B76: Fourchettes, TVA et ratios par prestation | C76: Référentiel!E70:I100 | D76: Tout le tableau des lots | E76: Grilles 2026 citées ligne à ligne ; chaque janvier, puis date en Référentiel!C109
B77: Ancienneté minimale du logement | C77: Référentiel!C15 | D77: La question d'ancienneté du bloc TVA, et la règle des deux ans | E77: CGI art. 279-0 bis, 1 ; stable
B78: Date de dernière vérification du Référentiel | C78: Référentiel!C109 | D78: Toutes les mentions « Vérifié le », et l'alerte au-delà d'un an | E78: La vôtre, le jour où vous relisez les prix ; chaque janvier
B79: Le bien, le curseur, les forçages, le bloc TVA | C79: Chiffrage!D7:D16, F29:F59 et J29:J59, D62:D77 | D79: Tout le reste | E79: Données de projet, propres à chaque dossier
B81: TROIS FAÇONS DE S'EN SERVIR
B82: Votre situation | C82: Ce que vous faites
B83: Vous préparez une offre sur un bien à rénover, sans aucun devis | C83: Saisissez le bien et le curseur de votre zone, forcez 0 sur les postes absents, répondez au bloc TVA. Retenez la colonne haute du TTC (F95) pour l'offre, la colonne retenue pour le prévisionnel. Vérifiez D76 avant d'annoncer 5,5 % ou 10 % à qui que ce soit.
B84: Les devis arrivent | C84: Forcez le prix de chaque poste devisé dans la colonne J (hors taxes, le taux de la ligne fait le reste) et sa quantité si elle diffère. Rapprochez la somme des devis de la ligne « Somme des TTC de ligne » (E96) : les devis ne contiennent ni aléas ni honoraires.
B85: Vous arbitrez le programme de travaux pour rester aux taux réduits | C85: Jouez sur les six réponses du second œuvre (D68:D73). À cinq Oui, un seul élément de plus fait basculer tout le chantier à 20 % : comparez le TTC des deux programmes, l'écart est le coût fiscal du sixième élément.
B87: LES ERREURS QUI FAUSSENT TOUT
B88: Le piège | C88: Le dégât
B89: Saisir une surface de murs en quantité forcée sur la ligne peinture (F50) | C89: Le prix est au m² au sol, ratio murs + plafonds de 3 inclus : le poste triple, soit plus de 14 000 € HT en trop sur l'exemple.
B90: Mettre 4 façades exposées pour un appartement (D10) | C90: Les murs de façade doublent par rapport à un traversant : isolation, doublage et ravalement suivent.
B91: Taper 10 au lieu de 10 % dans le taux forcé (D77) | C91: La liste le refuse ; un taux collé en texte est arrêté par les contrôles D81 et D82, et la TVA reste vide. Sans ces garde-fous, un 10 vaudrait 1 000 % de TVA.
B92: Laisser le bloc TVA sur des réponses par défaut (D62:D73) | C92: Répondre Non partout sur une rénovation qui refait tout affiche 5,5 % et 10 % sur un chantier qui est en réalité à 20 % : 12 395 € d'écart sur l'exemple. Le contrôle « À VÉRIFIER » le signale quand le chiffrage contredit les réponses.
B93: Laisser la surface vide ou à 0 (D7) | C93: Les postes comptés à l'unité (porte, tableau électrique, chauffage, ventilation, cuisine) resteraient à 1 et fabriqueraient un budget fantôme. Ici le récapitulatif reste vide et D24 passe au rouge : le classeur refuse de chiffrer.
B94: Renommer un lot dans le Référentiel après déprotection | C94: Le contrôle par famille perd ses lignes : H110 affiche « LOT HORS FAMILLE ».
B95: Oublier que les fourchettes sont hors Paris intra-muros et hors contraintes de site | C95: Étage sans ascenseur, accès difficile, copropriété, immeuble suivi par un architecte des Bâtiments de France : seul le curseur peut les absorber, montez-le.
B97: Ce que le classeur ne fait pas, et sur quelles sources reposent ses chiffres : voir l'onglet Méthode.
B99: CorpusImmo, millésime 2026. Modèle d'aide à la décision : ne constitue ni un conseil en investissement, ni un conseil fiscal, ni une expertise au sens de la charte de l'expertise en évaluation immobilière. Vérifiez les paramètres avant tout engagement.

Sheet Chiffrage
B1: CorpusImmo · www.corpus.immo · Estimer, comparer, décider. Sur les ventes réelles.
B2: Chiffrage de travaux par lot
B3: Cinq entrées, vingt-huit postes chiffrés en fourchette, chaque quantité et chaque prix restent forçables, et la TVA du chantier est qualifiée.
B5: Cellules violettes : à remplir. Cellules blanches : calculées automatiquement.
B6: LE BIEN
B7: Surface habitable | D7: 90 | E7: Le pivot : elle pilote la plupart des quantités. Bornes de saisie : 9 à 5 000 m².
B8: Nombre de niveaux | D8: 1 | E8: Sert à déduire l'emprise au sol : toiture, combles, charpente. Entier de 1 à 6.
B9: Hauteur sous plafond | D9: 2.5 | E9: Sert aux murs et aux cloisons. Mesurez-la sur place. Bornes de saisie : 2 à 5 m.
B10: Façades exposées | D10: 2 | E10: 4 pour une maison, 2 pour un appartement traversant, 1 sinon (mitoyen ou en cœur d'îlot).
B11: Part du logement rénovée | D11: 1 | E11: 100 % = rénovation complète. Pilote dépose, électricité, plomberie, sols, peinture, cloisons.
B13: LE CHIFFRAGE
B14: Positionnement dans la fourchette | D14: 0.5 | E14: ="0 % = bas de fourchette, 100 % = haut. Repères (Référentiel) : province "&ROUND(Référentiel!$C$27*100,1)&" %"&" à "&ROUND(Référentiel!$D$27*100,1)&" %"&", Île-de-France "&ROUND(Référentiel!$C$28*100,1)&" %"&" à "&ROUND(Référentiel!$D$28*100,1)&" %"&", Paris "&ROUND(Référentiel!$C$29*100,1)&" %"&" à "&ROUND(Référentiel!$D$29*100,1)&" %"&"." -> 0 % = bas de fourchette, 100 % = haut. Repères (Référentiel) : province 40 % à 60 %, Île-de-France 60 % à 80 %, Paris 70 % à 100 %.
B15: Provision pour aléas | D15: 0.12 | E15: ="Rénovation dans l'ancien : "&ROUND(Référentiel!$C$30*100,1)&" %"&" à "&ROUND(Référentiel!$D$30*100,1)&" %"&" (Référentiel). En dessous, vous pariez." -> Rénovation dans l'ancien : 10 % à 15 % (Référentiel). En dessous, vous pariez.
B16: Honoraires de maîtrise d'œuvre | D16: 0.1 | E16: ="Maîtrise d'œuvre d'exécution "&ROUND(Référentiel!$C$31*100,1)&" %"&" à "&ROUND(Référentiel!$D$31*100,1)&" %"&", architecte en mission complète "&ROUND(Référentiel!$C$32*100,1)&" %"&" à "&ROUND(Référentiel!$D$32*100,1)&" %"&" (Référentiel). TVA à "&ROUND(Référentiel!$C$10*100,1)&" %"&"." -> Maîtrise d'œuvre d'exécution 8 % à 12 %, architecte en mission complète 12 % à 18 % (Référentiel). TVA à 20 %.
B18: CE QUE LA GÉOMÉTRIE EN DÉDUIT
B19: Emprise au sol | D19: =IF(AND(ISNUMBER($D$7),$D$7>0,ISNUMBER($D$8),$D$8>0),$D$7/$D$8,"") -> 90 | E19: Surface habitable / nombre de niveaux.
B20: Périmètre estimé | D20: =IF($D$19="","",Référentiel!$C$19*SQRT($D$19)) -> 39.844699 | E20: Coefficient du Référentiel × racine de l'emprise. Le périmètre n'est pas proportionnel à la surface.
B21: Murs de façade | D21: =IF($D$20="","",$D$20*$D$9*$D$8*$D$10/Référentiel!$C$20) -> 49.805873 | E21: Périmètre × HSP × niveaux × façades exposées / nombre de façades (Référentiel). Pilote isolation, doublage, ravalement.
B22: Surface traitée | D22: =IF($D$19="","",$D$7*$D$11) -> 90 | E22: Surface habitable × part rénovée.
B23: Surface de toit | D23: =IF($D$19="","",$D$19*Référentiel!$C$21) -> 108 | E23: Emprise × coefficient de pente (Référentiel).
B24: Saisies du bien et du chiffrage complètes et dans leurs bornes | D24: =IF(AND(ISNUMBER($D$7),$D$7>=9,$D$7<=5000,ISNUMBER($D$8),$D$8>=1,$D$8<=6,$D$8=INT($D$8),ISNUMBER($D$9),$D$9>=2,$D$9<=5,ISNUMBER($D$10),$D$10>=0,$D$10<=4,$D$10=INT($D$10),ISNUMBER($D$11),$D$11>=0,$D$11<=1,ISNUMBER($D$14),$D$14>=0,$D$14<=1,ISNUMBER($D$15),$D$15>=0,$D$15<=0.5,ISNUMBER($D$16),$D$16>=0,$D$16<=0.5,COUNTIF($F$29:$F$59,"<0")=0,SUMPRODUCT(--ISTEXT($F$29:$F$59))=0,COUNTIF($J$29:$J$59,"<0")=0,SUMPRODUCT(--ISTEXT($J$29:$J$59))=0),"OK","À CORRIGER") -> OK | E24: À CORRIGER : une saisie manque, sort de ses bornes, ou un forçage du tableau est négatif ou en texte. Le récapitulatif reste vide tant que c'est rouge.
B25: Référentiel cohérent | D25: =IF(Référentiel!$C$7="OK","OK","À CORRIGER") -> OK | E25: À CORRIGER : une valeur du Référentiel manque ou sort de ses bornes (prix, ratio, taux hors liste, bas supérieur au haut). Le récapitulatif reste vide.
B27: LES LOTS : QUANTITÉ × PRIX UNITAIRE, PRIX PRIS DANS LA FOURCHETTE SELON LE CURSEUR
B28: Lot | C28: Prestation | D28: Unité | E28: Qté auto | F28: Qté forcée | G28: Qté retenue | H28: PU bas | I28: PU haut | J28: PU forcé | K28: PU retenu | L28: Total HT | M28: TVA | N28: Total TTC
B29: =Référentiel!$C$70 -> Dépose et démolition | C29: =Référentiel!$B$70 -> Dépose de cloisons, sols et sanitaires | D29: =Référentiel!$D$70 -> m² au sol | E29: =IF($D$19="","",ROUND($D$22*Référentiel!$I$70,0)) -> 90 | G29: =IF(F29="",E29,F29) -> 90 | H29: =Référentiel!$E$70 -> 25 | I29: =Référentiel!$F$70 -> 60 | K29: =IF(J29="",H29+(I29-H29)*$D$14,J29) -> 42.5 | L29: =IF(OR(G29="",NOT(ISNUMBER(G29)),NOT(ISNUMBER(K29))),"",G29*K29) -> 3825 | M29: =IF($D$78="",Référentiel!$G$70,$D$78) -> 0.1 | N29: =IF(OR(L29="",NOT(ISNUMBER(M29))),"",L29*(1+M29)) -> 4207.5
B30: =Référentiel!$C$71 -> Dépose et démolition | C30: =Référentiel!$B$71 -> Évacuation en benne | D30: =Référentiel!$D$71 -> forfait | E30: =IF($D$19="","",ROUNDUP($D$7*Référentiel!$I$71,0)) -> 1 | G30: =IF(F30="",E30,F30) -> 1 | H30: =Référentiel!$E$71 -> 400 | I30: =Référentiel!$F$71 -> 1200 | K30: =IF(J30="",H30+(I30-H30)*$D$14,J30) -> 800 | L30: =IF(OR(G30="",NOT(ISNUMBER(G30)),NOT(ISNUMBER(K30))),"",G30*K30) -> 800 | M30: =IF($D$78="",Référentiel!$G$71,$D$78) -> 0.1 | N30: =IF(OR(L30="",NOT(ISNUMBER(M30))),"",L30*(1+M30)) -> 880
B31: =Référentiel!$C$72 -> Gros œuvre | C31: =Référentiel!$B$72 -> Ouverture dans un mur porteur avec IPN | D31: =Référentiel!$D$72 -> unité | E31: =IF($D$19="","",ROUND($D$7*Référentiel!$I$72,0)) -> 0 | F31: 1 | G31: =IF(F31="",E31,F31) -> 1 | H31: =Référentiel!$E$72 -> 1800 | I31: =Référentiel!$F$72 -> 4500 | K31: =IF(J31="",H31+(I31-H31)*$D$14,J31) -> 3150 | L31: =IF(OR(G31="",NOT(ISNUMBER(G31)),NOT(ISNUMBER(K31))),"",G31*K31) -> 3150 | M31: =IF($D$78="",Référentiel!$G$72,$D$78) -> 0.1 | N31: =IF(OR(L31="",NOT(ISNUMBER(M31))),"",L31*(1+M31)) -> 3465
B32: =Référentiel!$C$73 -> Gros œuvre | C32: =Référentiel!$B$73 -> Reprise de maçonnerie et rebouchage | D32: =Référentiel!$D$73 -> m² | E32: =IF($D$19="","",ROUND($D$7*Référentiel!$I$73,0)) -> 0 | F32: 20 | G32: =IF(F32="",E32,F32) -> 20 | H32: =Référentiel!$E$73 -> 45 | I32: =Référentiel!$F$73 -> 110 | K32: =IF(J32="",H32+(I32-H32)*$D$14,J32) -> 77.5 | L32: =IF(OR(G32="",NOT(ISNUMBER(G32)),NOT(ISNUMBER(K32))),"",G32*K32) -> 1550 | M32: =IF($D$78="",Référentiel!$G$73,$D$78) -> 0.1 | N32: =IF(OR(L32="",NOT(ISNUMBER(M32))),"",L32*(1+M32)) -> 1705
B33: =Référentiel!$C$74 -> Charpente et toiture | C33: =Référentiel!$B$74 -> Réfection de couverture en tuiles | D33: =Référentiel!$D$74 -> m² de toit | E33: =IF($D$19="","",ROUND($D$23*Référentiel!$I$74,0)) -> 108 | F33: 0 | G33: =IF(F33="",E33,F33) -> 0 | H33: =Référentiel!$E$74 -> 90 | I33: =Référentiel!$F$74 -> 190 | K33: =IF(J33="",H33+(I33-H33)*$D$14,J33) -> 140 | L33: =IF(OR(G33="",NOT(ISNUMBER(G33)),NOT(ISNUMBER(K33))),"",G33*K33) -> 0 | M33: =IF($D$78="",Référentiel!$G$74,$D$78) -> 0.1 | N33: =IF(OR(L33="",NOT(ISNUMBER(M33))),"",L33*(1+M33)) -> 0
B34: =Référentiel!$C$75 -> Charpente et toiture | C34: =Référentiel!$B$75 -> Traitement de charpente | D34: =Référentiel!$D$75 -> m² au sol | E34: =IF($D$19="","",ROUND($D$19*Référentiel!$I$75,0)) -> 90 | F34: 0 | G34: =IF(F34="",E34,F34) -> 0 | H34: =Référentiel!$E$75 -> 25 | I34: =Référentiel!$F$75 -> 55 | K34: =IF(J34="",H34+(I34-H34)*$D$14,J34) -> 40 | L34: =IF(OR(G34="",NOT(ISNUMBER(G34)),NOT(ISNUMBER(K34))),"",G34*K34) -> 0 | M34: =IF($D$78="",Référentiel!$G$75,$D$78) -> 0.1 | N34: =IF(OR(L34="",NOT(ISNUMBER(M34))),"",L34*(1+M34)) -> 0
B35: =Référentiel!$C$76 -> Menuiseries extérieures | C35: =Référentiel!$B$76 -> Fenêtre PVC double vitrage posée | D35: =Référentiel!$D$76 -> unité | E35: =IF($D$19="","",ROUND($D$7*Référentiel!$I$76,0)) -> 7 | G35: =IF(F35="",E35,F35) -> 7 | H35: =Référentiel!$E$76 -> 550 | I35: =Référentiel!$F$76 -> 1400 | K35: =IF(J35="",H35+(I35-H35)*$D$14,J35) -> 975 | L35: =IF(OR(G35="",NOT(ISNUMBER(G35)),NOT(ISNUMBER(K35))),"",G35*K35) -> 6825 | M35: =IF($D$78="",Référentiel!$G$76,$D$78) -> 0.055 | N35: =IF(OR(L35="",NOT(ISNUMBER(M35))),"",L35*(1+M35)) -> 7200.375
B36: =Référentiel!$C$77 -> Menuiseries extérieures | C36: =Référentiel!$B$77 -> Porte d'entrée | D36: =Référentiel!$D$77 -> unité | E36: =ROUND(Référentiel!$I$77,0) -> 1 | G36: =IF(F36="",E36,F36) -> 1 | H36: =Référentiel!$E$77 -> 900 | I36: =Référentiel!$F$77 -> 2600 | K36: =IF(J36="",H36+(I36-H36)*$D$14,J36) -> 1750 | L36: =IF(OR(G36="",NOT(ISNUMBER(G36)),NOT(ISNUMBER(K36))),"",G36*K36) -> 1750 | M36: =IF($D$78="",Référentiel!$G$77,$D$78) -> 0.055 | N36: =IF(OR(L36="",NOT(ISNUMBER(M36))),"",L36*(1+M36)) -> 1846.25
B37: =Référentiel!$C$78 -> Isolation | C37: =Référentiel!$B$78 -> Isolation des murs par l'intérieur | D37: =Référentiel!$D$78 -> m² de mur | E37: =IF($D$19="","",ROUND($D$21*Référentiel!$I$78,0)) -> 50 | G37: =IF(F37="",E37,F37) -> 50 | H37: =Référentiel!$E$78 -> 45 | I37: =Référentiel!$F$78 -> 95 | K37: =IF(J37="",H37+(I37-H37)*$D$14,J37) -> 70 | L37: =IF(OR(G37="",NOT(ISNUMBER(G37)),NOT(ISNUMBER(K37))),"",G37*K37) -> 3500 | M37: =IF($D$78="",Référentiel!$G$78,$D$78) -> 0.055 | N37: =IF(OR(L37="",NOT(ISNUMBER(M37))),"",L37*(1+M37)) -> 3692.5
B38: =Référentiel!$C$79 -> Isolation | C38: =Référentiel!$B$79 -> Isolation des combles perdus | D38: =Référentiel!$D$79 -> m² au sol | E38: =IF($D$19="","",ROUND($D$19*Référentiel!$I$79,0)) -> 90 | F38: 0 | G38: =IF(F38="",E38,F38) -> 0 | H38: =Référentiel!$E$79 -> 25 | I38: =Référentiel!$F$79 -> 60 | K38: =IF(J38="",H38+(I38-H38)*$D$14,J38) -> 42.5 | L38: =IF(OR(G38="",NOT(ISNUMBER(G38)),NOT(ISNUMBER(K38))),"",G38*K38) -> 0 | M38: =IF($D$78="",Référentiel!$G$79,$D$78) -> 0.055 | N38: =IF(OR(L38="",NOT(ISNUMBER(M38))),"",L38*(1+M38)) -> 0
B39: =Référentiel!$C$80 -> Cloisons et plâtrerie | C39: =Référentiel!$B$80 -> Cloison placo sur ossature | D39: =Référentiel!$D$80 -> m² | E39: =IF($D$19="","",ROUND($D$22*$D$9*Référentiel!$I$80,0)) -> 45 | G39: =IF(F39="",E39,F39) -> 45 | H39: =Référentiel!$E$80 -> 45 | I39: =Référentiel!$F$80 -> 95 | K39: =IF(J39="",H39+(I39-H39)*$D$14,J39) -> 70 | L39: =IF(OR(G39="",NOT(ISNUMBER(G39)),NOT(ISNUMBER(K39))),"",G39*K39) -> 3150 | M39: =IF($D$78="",Référentiel!$G$80,$D$78) -> 0.1 | N39: =IF(OR(L39="",NOT(ISNUMBER(M39))),"",L39*(1+M39)) -> 3465
B40: =Référentiel!$C$81 -> Cloisons et plâtrerie | C40: =Référentiel!$B$81 -> Doublage et enduit de finition | D40: =Référentiel!$D$81 -> m² | E40: =IF($D$19="","",ROUND($D$21*Référentiel!$I$81,0)) -> 50 | G40: =IF(F40="",E40,F40) -> 50 | H40: =Référentiel!$E$81 -> 30 | I40: =Référentiel!$F$81 -> 65 | K40: =IF(J40="",H40+(I40-H40)*$D$14,J40) -> 47.5 | L40: =IF(OR(G40="",NOT(ISNUMBER(G40)),NOT(ISNUMBER(K40))),"",G40*K40) -> 2375 | M40: =IF($D$78="",Référentiel!$G$81,$D$78) -> 0.1 | N40: =IF(OR(L40="",NOT(ISNUMBER(M40))),"",L40*(1+M40)) -> 2612.5
B41: =Référentiel!$C$82 -> Électricité | C41: =Référentiel!$B$82 -> Électricité complète, NF C 15-100 | D41: =Référentiel!$D$82 -> m² au sol | E41: =IF($D$19="","",ROUND($D$22*Référentiel!$I$82,0)) -> 90 | G41: =IF(F41="",E41,F41) -> 90 | H41: =Référentiel!$E$82 -> 90 | I41: =Référentiel!$F$82 -> 165 | K41: =IF(J41="",H41+(I41-H41)*$D$14,J41) -> 127.5 | L41: =IF(OR(G41="",NOT(ISNUMBER(G41)),NOT(ISNUMBER(K41))),"",G41*K41) -> 11475 | M41: =IF($D$78="",Référentiel!$G$82,$D$78) -> 0.1 | N41: =IF(OR(L41="",NOT(ISNUMBER(M41))),"",L41*(1+M41)) -> 12622.5
B42: =Référentiel!$C$83 -> Électricité | C42: =Référentiel!$B$83 -> Tableau électrique neuf | D42: =Référentiel!$D$83 -> unité | E42: =ROUND(Référentiel!$I$83,0) -> 1 | G42: =IF(F42="",E42,F42) -> 1 | H42: =Référentiel!$E$83 -> 900 | I42: =Référentiel!$F$83 -> 2200 | K42: =IF(J42="",H42+(I42-H42)*$D$14,J42) -> 1550 | L42: =IF(OR(G42="",NOT(ISNUMBER(G42)),NOT(ISNUMBER(K42))),"",G42*K42) -> 1550 | M42: =IF($D$78="",Référentiel!$G$83,$D$78) -> 0.1 | N42: =IF(OR(L42="",NOT(ISNUMBER(M42))),"",L42*(1+M42)) -> 1705
B43: =Référentiel!$C$84 -> Plomberie et chauffage | C43: =Référentiel!$B$84 -> Réseau plomberie complet | D43: =Référentiel!$D$84 -> m² au sol | E43: =IF($D$19="","",ROUND($D$22*Référentiel!$I$84,0)) -> 90 | G43: =IF(F43="",E43,F43) -> 90 | H43: =Référentiel!$E$84 -> 55 | I43: =Référentiel!$F$84 -> 120 | K43: =IF(J43="",H43+(I43-H43)*$D$14,J43) -> 87.5 | L43: =IF(OR(G43="",NOT(ISNUMBER(G43)),NOT(ISNUMBER(K43))),"",G43*K43) -> 7875 | M43: =IF($D$78="",Référentiel!$G$84,$D$78) -> 0.1 | N43: =IF(OR(L43="",NOT(ISNUMBER(M43))),"",L43*(1+M43)) -> 8662.5
B44: =Référentiel!$C$85 -> Plomberie et chauffage | C44: =Référentiel!$B$85 -> Pompe à chaleur air/eau ou air/air | D44: =Référentiel!$D$85 -> unité | E44: =ROUND(Référentiel!$I$85,0) -> 1 | G44: =IF(F44="",E44,F44) -> 1 | H44: =Référentiel!$E$85 -> 3500 | I44: =Référentiel!$F$85 -> 14000 | K44: =IF(J44="",H44+(I44-H44)*$D$14,J44) -> 8750 | L44: =IF(OR(G44="",NOT(ISNUMBER(G44)),NOT(ISNUMBER(K44))),"",G44*K44) -> 8750 | M44: =IF($D$78="",Référentiel!$G$85,$D$78) -> 0.055 | N44: =IF(OR(L44="",NOT(ISNUMBER(M44))),"",L44*(1+M44)) -> 9231.25
B45: =Référentiel!$C$86 -> Plomberie et chauffage | C45: =Référentiel!$B$86 -> Chaudière gaz ou fioul posée | D45: =Référentiel!$D$86 -> unité | E45: =ROUND(Référentiel!$I$86,0) -> 1 | F45: 0 | G45: =IF(F45="",E45,F45) -> 0 | H45: =Référentiel!$E$86 -> 4000 | I45: =Référentiel!$F$86 -> 7000 | K45: =IF(J45="",H45+(I45-H45)*$D$14,J45) -> 5500 | L45: =IF(OR(G45="",NOT(ISNUMBER(G45)),NOT(ISNUMBER(K45))),"",G45*K45) -> 0 | M45: =IF($D$78="",Référentiel!$G$86,$D$78) -> 0.2 | N45: =IF(OR(L45="",NOT(ISNUMBER(M45))),"",L45*(1+M45)) -> 0
B46: =Référentiel!$C$87 -> Plomberie et chauffage | C46: =Référentiel!$B$87 -> Radiateurs posés | D46: =Référentiel!$D$87 -> unité | E46: =IF($D$19="","",ROUND($D$7*Référentiel!$I$87,0)) -> 6 | G46: =IF(F46="",E46,F46) -> 6 | H46: =Référentiel!$E$87 -> 250 | I46: =Référentiel!$F$87 -> 800 | K46: =IF(J46="",H46+(I46-H46)*$D$14,J46) -> 525 | L46: =IF(OR(G46="",NOT(ISNUMBER(G46)),NOT(ISNUMBER(K46))),"",G46*K46) -> 3150 | M46: =IF($D$78="",Référentiel!$G$87,$D$78) -> 0.1 | N46: =IF(OR(L46="",NOT(ISNUMBER(M46))),"",L46*(1+M46)) -> 3465
B47: =Référentiel!$C$88 -> Ventilation | C47: =Référentiel!$B$88 -> VMC hygroréglable ou double flux | D47: =Référentiel!$D$88 -> logement | E47: =ROUND(Référentiel!$I$88,0) -> 1 | G47: =IF(F47="",E47,F47) -> 1 | H47: =Référentiel!$E$88 -> 700 | I47: =Référentiel!$F$88 -> 5500 | K47: =IF(J47="",H47+(I47-H47)*$D$14,J47) -> 3100 | L47: =IF(OR(G47="",NOT(ISNUMBER(G47)),NOT(ISNUMBER(K47))),"",G47*K47) -> 3100 | M47: =IF($D$78="",Référentiel!$G$88,$D$78) -> 0.055 | N47: =IF(OR(L47="",NOT(ISNUMBER(M47))),"",L47*(1+M47)) -> 3270.5
B48: =Référentiel!$C$89 -> Revêtements de sol | C48: =Référentiel!$B$89 -> Parquet stratifié ou contrecollé posé | D48: =Référentiel!$D$89 -> m² | E48: =IF($D$19="","",ROUND($D$22*Référentiel!$I$89,0)) -> 63 | G48: =IF(F48="",E48,F48) -> 63 | H48: =Référentiel!$E$89 -> 35 | I48: =Référentiel!$F$89 -> 110 | K48: =IF(J48="",H48+(I48-H48)*$D$14,J48) -> 72.5 | L48: =IF(OR(G48="",NOT(ISNUMBER(G48)),NOT(ISNUMBER(K48))),"",G48*K48) -> 4567.5 | M48: =IF($D$78="",Référentiel!$G$89,$D$78) -> 0.1 | N48: =IF(OR(L48="",NOT(ISNUMBER(M48))),"",L48*(1+M48)) -> 5024.25
B49: =Référentiel!$C$90 -> Revêtements de sol | C49: =Référentiel!$B$90 -> Carrelage posé | D49: =Référentiel!$D$90 -> m² | E49: =IF($D$19="","",ROUND($D$22*Référentiel!$I$90,0)) -> 27 | G49: =IF(F49="",E49,F49) -> 27 | H49: =Référentiel!$E$90 -> 55 | I49: =Référentiel!$F$90 -> 140 | K49: =IF(J49="",H49+(I49-H49)*$D$14,J49) -> 97.5 | L49: =IF(OR(G49="",NOT(ISNUMBER(G49)),NOT(ISNUMBER(K49))),"",G49*K49) -> 2632.5 | M49: =IF($D$78="",Référentiel!$G$90,$D$78) -> 0.1 | N49: =IF(OR(L49="",NOT(ISNUMBER(M49))),"",L49*(1+M49)) -> 2895.75
B50: =Référentiel!$C$91 -> Peinture et finitions | C50: =Référentiel!$B$91 -> Peinture murs et plafonds | D50: =Référentiel!$D$91 -> m² au sol | E50: =IF($D$19="","",ROUND($D$22*Référentiel!$I$91,0)) -> 90 | G50: =IF(F50="",E50,F50) -> 90 | H50: =Référentiel!$E$91 -> 52 | I50: =Référentiel!$F$91 -> 112 | K50: =IF(J50="",H50+(I50-H50)*$D$14,J50) -> 82 | L50: =IF(OR(G50="",NOT(ISNUMBER(G50)),NOT(ISNUMBER(K50))),"",G50*K50) -> 7380 | M50: =IF($D$78="",Référentiel!$G$91,$D$78) -> 0.1 | N50: =IF(OR(L50="",NOT(ISNUMBER(M50))),"",L50*(1+M50)) -> 8118
B51: =Référentiel!$C$92 -> Menuiseries intérieures | C51: =Référentiel!$B$92 -> Bloc-porte posé | D51: =Référentiel!$D$92 -> unité | E51: =IF($D$19="","",ROUND($D$7*Référentiel!$I$92,0)) -> 6 | G51: =IF(F51="",E51,F51) -> 6 | H51: =Référentiel!$E$92 -> 250 | I51: =Référentiel!$F$92 -> 650 | K51: =IF(J51="",H51+(I51-H51)*$D$14,J51) -> 450 | L51: =IF(OR(G51="",NOT(ISNUMBER(G51)),NOT(ISNUMBER(K51))),"",G51*K51) -> 2700 | M51: =IF($D$78="",Référentiel!$G$92,$D$78) -> 0.1 | N51: =IF(OR(L51="",NOT(ISNUMBER(M51))),"",L51*(1+M51)) -> 2970
B52: =Référentiel!$C$93 -> Cuisine | C52: =Référentiel!$B$93 -> Cuisine équipée posée | D52: =Référentiel!$D$93 -> unité | E52: =ROUND(Référentiel!$I$93,0) -> 1 | G52: =IF(F52="",E52,F52) -> 1 | H52: =Référentiel!$E$93 -> 3500 | I52: =Référentiel!$F$93 -> 15000 | K52: =IF(J52="",H52+(I52-H52)*$D$14,J52) -> 9250 | L52: =IF(OR(G52="",NOT(ISNUMBER(G52)),NOT(ISNUMBER(K52))),"",G52*K52) -> 9250 | M52: =IF($D$78="",Référentiel!$G$93,$D$78) -> 0.1 | N52: =IF(OR(L52="",NOT(ISNUMBER(M52))),"",L52*(1+M52)) -> 10175
B53: =Référentiel!$C$94 -> Salle de bains | C53: =Référentiel!$B$94 -> Salle de bains complète | D53: =Référentiel!$D$94 -> unité | E53: =IF($D$19="","",MAX(1,ROUND($D$7*Référentiel!$I$94,0))) -> 1 | G53: =IF(F53="",E53,F53) -> 1 | H53: =Référentiel!$E$94 -> 4000 | I53: =Référentiel!$F$94 -> 14000 | K53: =IF(J53="",H53+(I53-H53)*$D$14,J53) -> 9000 | L53: =IF(OR(G53="",NOT(ISNUMBER(G53)),NOT(ISNUMBER(K53))),"",G53*K53) -> 9000 | M53: =IF($D$78="",Référentiel!$G$94,$D$78) -> 0.1 | N53: =IF(OR(L53="",NOT(ISNUMBER(M53))),"",L53*(1+M53)) -> 9900
B54: =Référentiel!$C$95 -> Salle de bains | C54: =Référentiel!$B$95 -> WC suspendu posé | D54: =Référentiel!$D$95 -> unité | E54: =IF($D$19="","",MAX(1,ROUND($D$7*Référentiel!$I$95,0))) -> 2 | G54: =IF(F54="",E54,F54) -> 2 | H54: =Référentiel!$E$95 -> 450 | I54: =Référentiel!$F$95 -> 1100 | K54: =IF(J54="",H54+(I54-H54)*$D$14,J54) -> 775 | L54: =IF(OR(G54="",NOT(ISNUMBER(G54)),NOT(ISNUMBER(K54))),"",G54*K54) -> 1550 | M54: =IF($D$78="",Référentiel!$G$95,$D$78) -> 0.1 | N54: =IF(OR(L54="",NOT(ISNUMBER(M54))),"",L54*(1+M54)) -> 1705
B55: =Référentiel!$C$96 -> Extérieurs | C55: =Référentiel!$B$96 -> Ravalement de façade | D55: =Référentiel!$D$96 -> m² de façade | E55: =IF($D$19="","",ROUND($D$21*Référentiel!$I$96,0)) -> 50 | F55: 0 | G55: =IF(F55="",E55,F55) -> 0 | H55: =Référentiel!$E$96 -> 50 | I55: =Référentiel!$F$96 -> 130 | K55: =IF(J55="",H55+(I55-H55)*$D$14,J55) -> 90 | L55: =IF(OR(G55="",NOT(ISNUMBER(G55)),NOT(ISNUMBER(K55))),"",G55*K55) -> 0 | M55: =IF($D$78="",Référentiel!$G$96,$D$78) -> 0.1 | N55: =IF(OR(L55="",NOT(ISNUMBER(M55))),"",L55*(1+M55)) -> 0
B56: =Référentiel!$C$97 -> Extérieurs | C56: =Référentiel!$B$97 -> Reprise de VRD et abords | D56: =Référentiel!$D$97 -> m² | E56: =IF($D$19="","",ROUND($D$7*Référentiel!$I$97,0)) -> 0 | F56: 0 | G56: =IF(F56="",E56,F56) -> 0 | H56: =Référentiel!$E$97 -> 40 | I56: =Référentiel!$F$97 -> 120 | K56: =IF(J56="",H56+(I56-H56)*$D$14,J56) -> 80 | L56: =IF(OR(G56="",NOT(ISNUMBER(G56)),NOT(ISNUMBER(K56))),"",G56*K56) -> 0 | M56: =IF($D$78="",Référentiel!$G$97,$D$78) -> 0.1 | N56: =IF(OR(L56="",NOT(ISNUMBER(M56))),"",L56*(1+M56)) -> 0
B57: =Référentiel!$C$98 -> Autre | C57: =Référentiel!$B$98 -> Poste libre 1 (à compléter) | D57: =Référentiel!$D$98 -> unité | E57: =IF($D$19="","",ROUND($D$7*Référentiel!$I$98,0)) -> 0 | G57: =IF(F57="",E57,F57) -> 0 | H57: =Référentiel!$E$98 -> 0 | I57: =Référentiel!$F$98 -> 0 | K57: =IF(J57="",H57+(I57-H57)*$D$14,J57) -> 0 | L57: =IF(OR(G57="",NOT(ISNUMBER(G57)),NOT(ISNUMBER(K57))),"",G57*K57) -> 0 | M57: =IF($D$78="",Référentiel!$G$98,$D$78) -> 0.1 | N57: =IF(OR(L57="",NOT(ISNUMBER(M57))),"",L57*(1+M57)) -> 0
B58: =Référentiel!$C$99 -> Autre | C58: =Référentiel!$B$99 -> Poste libre 2 (à compléter) | D58: =Référentiel!$D$99 -> unité | E58: =IF($D$19="","",ROUND($D$7*Référentiel!$I$99,0)) -> 0 | G58: =IF(F58="",E58,F58) -> 0 | H58: =Référentiel!$E$99 -> 0 | I58: =Référentiel!$F$99 -> 0 | K58: =IF(J58="",H58+(I58-H58)*$D$14,J58) -> 0 | L58: =IF(OR(G58="",NOT(ISNUMBER(G58)),NOT(ISNUMBER(K58))),"",G58*K58) -> 0 | M58: =IF($D$78="",Référentiel!$G$99,$D$78) -> 0.1 | N58: =IF(OR(L58="",NOT(ISNUMBER(M58))),"",L58*(1+M58)) -> 0
B59: =Référentiel!$C$100 -> Autre | C59: =Référentiel!$B$100 -> Poste libre 3 (à compléter) | D59: =Référentiel!$D$100 -> unité | E59: =IF($D$19="","",ROUND($D$7*Référentiel!$I$100,0)) -> 0 | G59: =IF(F59="",E59,F59) -> 0 | H59: =Référentiel!$E$100 -> 0 | I59: =Référentiel!$F$100 -> 0 | K59: =IF(J59="",H59+(I59-H59)*$D$14,J59) -> 0 | L59: =IF(OR(G59="",NOT(ISNUMBER(G59)),NOT(ISNUMBER(K59))),"",G59*K59) -> 0 | M59: =IF($D$78="",Référentiel!$G$100,$D$78) -> 0.1 | N59: =IF(OR(L59="",NOT(ISNUMBER(M59))),"",L59*(1+M59)) -> 0
B61: LA TVA DU CHANTIER : QUALIFICATION
B62: Nature du local | D62: Habitation | E62: Habitation : taux réduits possibles. Local autre (bureau, commerce, entrepôt, local professionnel) : 20 % sur tout le chantier.
B63: ="Logement achevé depuis plus de "&Référentiel!$C$15&" ans au début des travaux ?" -> Logement achevé depuis plus de 2 ans au début des travaux ? | D63: Oui | E63: Non : 20 % sur tout le chantier (CGI art. 279-0 bis).
B64: Extension de surface de plancher de plus de 10 % ? | D64: Non | E64: Oui : 20 % sur tout (surélévation, addition, aménagement de combles créant de la surface).
B65: Gros œuvre : majorité des fondations refaite ? | D65: Non | E65: Immeuble rendu neuf (CGI art. 257 I-2-2°, ann. II art. 245 A) : 20 % sur tout.
B66: Gros œuvre : majorité de la structure (hors fondations) refaite ? | D66: Non | E66: Éléments qui déterminent la résistance et la rigidité de l'ouvrage : murs porteurs, planchers porteurs, charpente.
B67: Gros œuvre : majorité des façades refaite (hors ravalement) ? | D67: Non | E67: Un ravalement ne compte pas ; une reconstruction de façade, oui.
B68: Second œuvre : planchers non porteurs refaits à au moins deux tiers ? | D68: Non | E68: Chapes, planchers légers, faux planchers. Ce tableau ne les chiffre pas : répondez d'après votre projet.
B69: Second œuvre : huisseries extérieures refaites à au moins deux tiers ? | D69: Oui | E69: Fenêtres, portes-fenêtres, porte d'entrée.
B70: Second œuvre : cloisons intérieures refaites à au moins deux tiers ? | D70: Oui | E70: Cloisons de distribution.
B71: Second œuvre : plomberie et sanitaires refaits à au moins deux tiers ? | D71: Oui | E71: Réseau, appareils sanitaires.
B72: Second œuvre : électricité refaite à au moins deux tiers ? | D72: Oui | E72: Réseau et tableau.
B73: Second œuvre : chauffage refait à au moins deux tiers ? | D73: Oui | E73: Générateur et émetteurs (pour un local d'habitation).
B74: Éléments de second œuvre déclarés refaits (sur 6) | D74: =COUNTIF($D$68:$D$73,Référentiel!$B$64) -> 5 | E74: Les six ensemble rendent l'immeuble neuf. À cinq, un seul élément de plus fait basculer tout le chantier à 20 %.
B75: Immeuble rendu à l'état neuf ? | D75: =IF(OR($D$65=Référentiel!$B$64,$D$66=Référentiel!$B$64,$D$67=Référentiel!$B$64,$D$74=ROWS($D$68:$D$73)),Référentiel!$B$64,Référentiel!$B$65) -> Non | E75: Oui dès qu'un critère de gros œuvre est rempli, ou que les six éléments de second œuvre le sont.
B76: Taux réduits (5,5 % et 10 %) admis sur ce chantier | D76: =IF(NOT(OR($D$62=Référentiel!$C$65,$D$63=Référentiel!$B$65,$D$64=Référentiel!$B$64,$D$75=Référentiel!$B$64)),"Taux par ligne","TOUT À 20 %") -> Taux par ligne | E76: Rouge : l'opération entière est au taux normal, les taux par ligne sont ignorés.
B77: Taux de TVA forcé (facultatif) | E77: Vide : chaque ligne garde son taux du Référentiel. Sinon, choisissez 5,5 %, 10 % ou 20 % dans la liste.
B78: Taux appliqué à toutes les lignes | D78: =IF(OR($D$62=Référentiel!$C$65,$D$63=Référentiel!$B$65,$D$64=Référentiel!$B$64,$D$75=Référentiel!$B$64),Référentiel!$C$10,IF($D$77="","",$D$77)) | E78: Vide : taux par ligne. 20 % si l'opération bascule. Sinon le taux forcé.
B79: Éléments de second œuvre que ce chiffrage refait (sur 5, indication) | D79: =IF($D$22="","",IF($D$11>=Référentiel!$C$13,(SUM(L35,L36)>0)*1+(SUM(L39)>0)*1+(SUM(L43,L53,L54)>0)*1+(SUM(L41,L42)>0)*1+(SUM(L44,L45,L46)>0)*1,0)) -> 5 | E79: Compté sur les lignes actives quand la part rénovée atteint les deux tiers : huisseries, cloisons, plomberie, électricité, chauffage.
B80: Bloc TVA entièrement renseigné | D80: =IF(AND(COUNTIF($D$63:$D$73,Référentiel!$B$64)+COUNTIF($D$63:$D$73,Référentiel!$B$65)=ROWS($D$63:$D$73),OR($D$62=Référentiel!$C$64,$D$62=Référentiel!$C$65)),"OK","À CORRIGER") -> OK | E80: À CORRIGER : une des douze réponses manque. La TVA et le TTC restent vides tant que c'est rouge.
B81: Taux forcé valide | D81: =IF(OR($D$77="",AND(ISNUMBER($D$77),ISNUMBER(MATCH($D$77,Référentiel!$C$10:$C$12,0)))),"OK","À CORRIGER") -> OK | E81: À CORRIGER : le taux forcé n'est pas 5,5 %, 10 % ou 20 % (par exemple 10 tapé au lieu de 10 %, ou un taux collé en texte).
B82: Taux de chaque ligne dans la liste des trois taux | D82: =IF(AND(COUNT($M$29:$M$59)=ROWS($M$29:$M$59),COUNTIF($M$29:$M$59,Référentiel!$C$10)+COUNTIF($M$29:$M$59,Référentiel!$C$11)+COUNTIF($M$29:$M$59,Référentiel!$C$12)=ROWS($M$29:$M$59)),"OK","À CORRIGER") -> OK | E82: À CORRIGER : un taux hors liste dans le Référentiel (colonne TVA), ou un taux collé en texte dans le taux forcé. Vérifiez le Référentiel.
B83: Réponses du bloc TVA cohérentes avec le chiffrage | D83: =IF(IF($D$79="",TRUE,$D$74>=$D$79),"OK","À VÉRIFIER") -> OK | E83: À VÉRIFIER : le chiffrage refait plus d'éléments de second œuvre que vous n'en déclarez. Relisez vos réponses.
B85: RÉCAPITULATIF : BAS DE FOURCHETTE, CHIFFRAGE RETENU, HAUT DE FOURCHETTE
B86: Montant | D86: Bas de fourchette (curseur 0 %) | E86: Retenu (curseur saisi) | F86: Haut de fourchette (curseur 100 %) | G86: Ce qu'il faut lire
B87: Sous-total des lots HT | D87: =IF(OR($D$24<>"OK",$D$25<>"OK"),"",SUMPRODUCT($G$29:$G$59,$H$29:$H$59,--($J$29:$J$59=""))+SUMPRODUCT($G$29:$G$59,$J$29:$J$59)) -> 53795 | E87: =IF(OR($D$24<>"OK",$D$25<>"OK"),"",SUM($L$29:$L$59)) -> 99905 | F87: =IF(OR($D$24<>"OK",$D$25<>"OK"),"",SUMPRODUCT($G$29:$G$59,$I$29:$I$59,--($J$29:$J$59=""))+SUMPRODUCT($G$29:$G$59,$J$29:$J$59)) -> 146015 | G87: Le chiffre à comparer à un devis d'entreprise générale (hors aléas, hors honoraires).
B88: Provision pour aléas | D88: =IF($D$87="","",$D$87*$D$15) -> 6455.4 | E88: =IF($E$87="","",$E$87*$D$15) -> 11988.6 | F88: =IF($F$87="","",$F$87*$D$15) -> 17521.8 | G88: Appliquée aux lots, avant honoraires et avant TVA.
B89: Honoraires de maîtrise d'œuvre | D89: =IF($D$87="","",$D$87*$D$16) -> 5379.5 | E89: =IF($E$87="","",$E$87*$D$16) -> 9990.5 | F89: =IF($F$87="","",$F$87*$D$16) -> 14601.5 | G89: Pourcentage des lots HT. Toujours à 20 % de TVA.
B90: Total HT | D90: =IF($D$87="","",$D$87+$D$88+$D$89) -> 65629.9 | E90: =IF($E$87="","",$E$87+$E$88+$E$89) -> 121884.1 | F90: =IF($F$87="","",$F$87+$F$88+$F$89) -> 178138.3 | G90: Lots, aléas et honoraires.
B91: dont TVA à 5,5 % | D91: =IF(OR($D$24<>"OK",$D$25<>"OK",$D$80<>"OK",$D$81<>"OK",$D$82<>"OK"),"",(SUMPRODUCT($G$29:$G$59,$H$29:$H$59,--($J$29:$J$59=""),--($M$29:$M$59=Référentiel!$C$12))+SUMPRODUCT($G$29:$G$59,$J$29:$J$59,--($M$29:$M$59=Référentiel!$C$12)))*(1+$D$15)*Référentiel!$C$12) -> 689.92 | E91: =IF(OR($D$24<>"OK",$D$25<>"OK",$D$80<>"OK",$D$81<>"OK",$D$82<>"OK"),"",SUMIF($M$29:$M$59,Référentiel!$C$12,$L$29:$L$59)*(1+$D$15)*Référentiel!$C$12) -> 1473.78 | F91: =IF(OR($D$24<>"OK",$D$25<>"OK",$D$80<>"OK",$D$81<>"OK",$D$82<>"OK"),"",(SUMPRODUCT($G$29:$G$59,$I$29:$I$59,--($J$29:$J$59=""),--($M$29:$M$59=Référentiel!$C$12))+SUMPRODUCT($G$29:$G$59,$J$29:$J$59,--($M$29:$M$59=Référentiel!$C$12)))*(1+$D$15)*Référentiel!$C$12) -> 2257.64 | G91: Le montant à défendre par les critères techniques et la mention sur le devis.
B92: dont TVA à 10 % | D92: =IF(OR($D$24<>"OK",$D$25<>"OK",$D$80<>"OK",$D$81<>"OK",$D$82<>"OK"),"",(SUMPRODUCT($G$29:$G$59,$H$29:$H$59,--($J$29:$J$59=""),--($M$29:$M$59=Référentiel!$C$11))+SUMPRODUCT($G$29:$G$59,$J$29:$J$59,--($M$29:$M$59=Référentiel!$C$11)))*(1+$D$15)*Référentiel!$C$11) -> 4770.64 | E92: =IF(OR($D$24<>"OK",$D$25<>"OK",$D$80<>"OK",$D$81<>"OK",$D$82<>"OK"),"",SUMIF($M$29:$M$59,Référentiel!$C$11,$L$29:$L$59)*(1+$D$15)*Référentiel!$C$11) -> 8509.76 | F92: =IF(OR($D$24<>"OK",$D$25<>"OK",$D$80<>"OK",$D$81<>"OK",$D$82<>"OK"),"",(SUMPRODUCT($G$29:$G$59,$I$29:$I$59,--($J$29:$J$59=""),--($M$29:$M$59=Référentiel!$C$11))+SUMPRODUCT($G$29:$G$59,$J$29:$J$59,--($M$29:$M$59=Référentiel!$C$11)))*(1+$D$15)*Référentiel!$C$11) -> 12248.88
B93: dont TVA à 20 % | D93: =IF(OR($D$24<>"OK",$D$25<>"OK",$D$80<>"OK",$D$81<>"OK",$D$82<>"OK"),"",(SUMPRODUCT($G$29:$G$59,$H$29:$H$59,--($J$29:$J$59=""),--($M$29:$M$59=Référentiel!$C$10))+SUMPRODUCT($G$29:$G$59,$J$29:$J$59,--($M$29:$M$59=Référentiel!$C$10)))*(1+$D$15)*Référentiel!$C$10+$D$89*Référentiel!$C$10) -> 1075.9 | E93: =IF(OR($D$24<>"OK",$D$25<>"OK",$D$80<>"OK",$D$81<>"OK",$D$82<>"OK"),"",SUMIF($M$29:$M$59,Référentiel!$C$10,$L$29:$L$59)*(1+$D$15)*Référentiel!$C$10+$E$89*Référentiel!$C$10) -> 1998.1 | F93: =IF(OR($D$24<>"OK",$D$25<>"OK",$D$80<>"OK",$D$81<>"OK",$D$82<>"OK"),"",(SUMPRODUCT($G$29:$G$59,$I$29:$I$59,--($J$29:$J$59=""),--($M$29:$M$59=Référentiel!$C$10))+SUMPRODUCT($G$29:$G$59,$J$29:$J$59,--($M$29:$M$59=Référentiel!$C$10)))*(1+$D$15)*Référentiel!$C$10+$F$89*Référentiel!$C$10) -> 2920.3 | G93: Honoraires compris.
B94: Total TVA | D94: =IF($D$91="","",$D$91+$D$92+$D$93) -> 6536.46 | E94: =IF($E$91="","",$E$91+$E$92+$E$93) -> 11981.64 | F94: =IF($F$91="","",$F$91+$F$92+$F$93) -> 17426.82 | G94: Somme des trois taux. Vide tant qu'un contrôle du bloc TVA est rouge.
B95: TOTAL TOUTES TAXES COMPRISES | D95: =IF($D$94="","",$D$90+$D$94) -> 72166.36 | E95: =IF($E$94="","",$E$90+$E$94) -> 133865.74 | F95: =IF($F$94="","",$F$90+$F$94) -> 195565.12 | G95: Le budget à financer.
B96: Somme des TTC de ligne, hors aléas et honoraires | E96: =IF($E$95="","",SUM($N$29:$N$59)) -> 108818.88 | G96: À rapprocher de la somme des devis d'entreprises, qui sont TTC et ne contiennent ni aléas ni honoraires.
B97: Lots seuls HT au m² habitable | D97: =IF($D$87="","",$D$87/$D$7) -> 597.72222 | E97: =IF($E$87="","",$E$87/$D$7) -> 1110.0556 | F97: =IF($F$87="","",$F$87/$D$7) -> 1622.3889 | G97: Le chiffre que l'on compare à un devis d'entreprise générale.
B98: Coût au m² HT, aléas et honoraires compris | D98: =IF($D$90="","",$D$90/$D$7) -> 729.22111 | E98: =IF($E$90="","",$E$90/$D$7) -> 1354.2678 | F98: =IF($F$90="","",$F$90/$D$7) -> 1979.3144 | G98: Pour comparer entre professionnels.
B99: Coût au m² TTC, aléas et honoraires compris | D99: =IF($D$95="","",$D$95/$D$7) -> 801.84844 | E99: =IF($E$95="","",$E$95/$D$7) -> 1487.3971 | F99: =IF($F$95="","",$F$95/$D$7) -> 2172.9458 | G99: Pour parler à un particulier. Seuils de lecture dans le Référentiel (lignes 22 et 23).
B100: Niveau de rénovation (lecture du coût TTC au m²) | E100: =IF($E$99="","",IF($E$99<Référentiel!$C$22,"Rafraîchissement",IF($E$99<Référentiel!$C$23,"Rénovation","Rénovation lourde ou restructuration"))) -> Rénovation | G100: Rafraîchissement sous le premier seuil, rénovation jusqu'au second, rénovation lourde ou restructuration au-delà.
B102: CONTRÔLE DE COHÉRENCE : PART DE CHAQUE FAMILLE DE LOTS
B103: Famille de lots | C103: Ce qu'elle regroupe | D103: Montant HT | E103: Part | F103: Bande basse | G103: Bande haute | H103: Verdict
B104: =Référentiel!$B$36 -> Dépose et gros œuvre | C104: =Référentiel!$K$36 -> Dépose et démolition, gros œuvre | D104: =IF($E$87="","",SUMPRODUCT(SUMIF($B$29:$B$59,Référentiel!$B$45:$B$46,$L$29:$L$59))) -> 9325 | E104: =IF(D104="","",IF($E$87>0,D104/$E$87,0)) -> 0.093338672 | F104: =Référentiel!$C$36 -> 0.05 | G104: =Référentiel!$D$36 -> 0.12 | H104: =IF(D104="","",IF(D104=0,"Non traité",IF(E104<F104,"Bas : poste oublié ?",IF(E104>G104,"Élevé : à justifier","Dans la norme")))) -> Dans la norme
B105: =Référentiel!$B$37 -> Enveloppe | C105: =Référentiel!$K$37 -> Toiture, menuiseries extérieures, isolation, extérieurs | D105: =IF($E$87="","",SUMPRODUCT(SUMIF($B$29:$B$59,Référentiel!$B$47:$B$50,$L$29:$L$59))) -> 12075 | E105: =IF(D105="","",IF($E$87>0,D105/$E$87,0)) -> 0.12086482 | F105: =Référentiel!$C$37 -> 0.1 | G105: =Référentiel!$D$37 -> 0.3 | H105: =IF(D105="","",IF(D105=0,"Non traité",IF(E105<F105,"Bas : poste oublié ?",IF(E105>G105,"Élevé : à justifier","Dans la norme")))) -> Dans la norme
B106: =Référentiel!$B$38 -> Technique | C106: =Référentiel!$K$38 -> Électricité, plomberie, chauffage, ventilation | D106: =IF($E$87="","",SUMPRODUCT(SUMIF($B$29:$B$59,Référentiel!$B$51:$B$53,$L$29:$L$59))) -> 35900 | E106: =IF(D106="","",IF($E$87>0,D106/$E$87,0)) -> 0.35934137 | F106: =Référentiel!$C$38 -> 0.25 | G106: =Référentiel!$D$38 -> 0.35 | H106: =IF(D106="","",IF(D106=0,"Non traité",IF(E106<F106,"Bas : poste oublié ?",IF(E106>G106,"Élevé : à justifier","Dans la norme")))) -> Élevé : à justifier
B107: =Référentiel!$B$39 -> Cloisons et finitions | C107: =Référentiel!$K$39 -> Plâtrerie, sols, peinture, menuiseries intérieures | D107: =IF($E$87="","",SUMPRODUCT(SUMIF($B$29:$B$59,Référentiel!$B$54:$B$57,$L$29:$L$59))) -> 22805 | E107: =IF(D107="","",IF($E$87>0,D107/$E$87,0)) -> 0.22826685 | F107: =Référentiel!$C$39 -> 0.15 | G107: =Référentiel!$D$39 -> 0.28 | H107: =IF(D107="","",IF(D107=0,"Non traité",IF(E107<F107,"Bas : poste oublié ?",IF(E107>G107,"Élevé : à justifier","Dans la norme")))) -> Dans la norme
...

Sheet Référentiel
B1: CorpusImmo · www.corpus.immo · Estimer, comparer, décider. Sur les ventes réelles.
B2: Référentiel
B3: Un prix, un taux de TVA et un ratio par prestation ; les barèmes et les conventions du classeur. Rien n'est écrit en dur ailleurs.
B5: Cellules violettes : à remplir. Cellules blanches : calculées automatiquement.
B6: Fourchettes indicatives 2026, France hors Paris intra-muros. Fournitures et pose, hors taxes. Les cellules violettes sont vos prix : confrontez-les à vos trois derniers chantiers.
B7: Référentiel cohérent (bornes des barèmes, des prix, des ratios et des taux) | C7: =IF(AND(COUNT(C10:C15)=ROWS(C10:C15),COUNTIF(C10:C14,"<0")=0,COUNTIF(C10:C14,">1")=0,C15>=0,C15<=50,C15=INT(C15),COUNT(C19:C23)=ROWS(C19:C23),C19>=3.5,C19<=8,C20>=1,C20<=8,C20=INT(C20),C21>=1,C21<=2,C22>=0,C23>=C22,COUNT(C27:D32)=ROWS(C27:D32)*COLUMNS(C27:D32),COUNTIF(C27:D32,"<0")=0,COUNTIF(C27:D32,">1")=0,SUMPRODUCT(--(C27:C32>D27:D32))=0,COUNT(C36:D41)=ROWS(C36:D41)*COLUMNS(C36:D41),COUNTIF(C36:D41,"<0")=0,COUNTIF(C36:D41,">1")=0,SUMPRODUCT(--(C36:C41>D36:D41))=0,COUNT(E70:F100)=ROWS(E70:F100)*COLUMNS(E70:F100),COUNTIF(E70:F100,"<0")=0,SUMPRODUCT(--(E70:E100>F70:F100))=0,COUNT(I70:I100)=ROWS(I70:I100),COUNTIF(I70:I100,"<0")=0,COUNTIF(G70:G100,C10)+COUNTIF(G70:G100,C11)+COUNTIF(G70:G100,C12)=ROWS(G70:G100)),"OK","À CORRIGER") -> OK | D7: Rouge : une cellule violette de cet onglet manque ou sort de ses bornes. Le Chiffrage le reprend et suspend son récapitulatif.
B8: BARÈMES RÉGLEMENTAIRES : TVA DES TRAVAUX ET IMMEUBLE RENDU NEUF (DROIT 2026)
B9: Paramètre | C9: Valeur | D9: Mise à jour | J9: Source (organisme, texte, date) | K9: Commentaire
B10: TVA, taux normal | C10: 0.2 | D10: Chaque loi de finances | J10: ="CGI art. 278 ; Service-public Entreprendre F23568, mis à jour le 21/02/2026. "&"Vérifié le "&TEXT(DAY(Référentiel!$C$109),"00")&"/"&TEXT(MONTH(Référentiel!$C$109),"00")&"/"&YEAR(Référentiel!$C$109) -> CGI art. 278 ; Service-public Entreprendre F23568, mis à jour le 21/02/2026. Vérifié le 05/09/2026 | K10: Local de moins de 2 ans, local non affecté à l'habitation, immeuble rendu neuf, extension de plus de 10 %, honoraires (prestation intellectuelle), chaudière fossile.
B11: TVA, taux intermédiaire (amélioration d'un logement de plus de 2 ans) | C11: 0.1 | D11: Chaque loi de finances | J11: ="CGI art. 279-0 bis ; BOI-TVA-LIQ-30-20-90-10 du 22/10/2025. "&"Vérifié le "&TEXT(DAY(Référentiel!$C$109),"00")&"/"&TEXT(MONTH(Référentiel!$C$109),"00")&"/"&YEAR(Référentiel!$C$109) -> CGI art. 279-0 bis ; BOI-TVA-LIQ-30-20-90-10 du 22/10/2025. Vérifié le 05/09/2026 | K11: Travaux d'amélioration, de transformation, d'aménagement et d'entretien. Taux par défaut du Référentiel.
B12: TVA, taux réduit (rénovation énergétique éligible) | C12: 0.055 | D12: Loi de finances et arrêtés | J12: ="CGI art. 278-0 bis A ; arrêté du 24/12/2024 (liste des équipements) ; BOFiP ACTU-2025-00165 du 22/10/2025 ; FFB, liste du 25/08/2026. "&"Vérifié le "&TEXT(DAY(Référentiel!$C$109),"00")&"/"&TEXT(MONTH(Référentiel!$C$109),"00")&"/"&YEAR(Référentiel!$C$109) -> CGI art. 278-0 bis A ; arrêté du 24/12/2024 (liste des équipements) ; BOFiP ACTU-2025-00165 du 22/10/2025 ; FFB, liste du 25/08/2026. Vérifié le 05/09/2026 | K12: Isolation, fenêtres et portes extérieures, pompes à chaleur (air/air depuis le 18/07/2026), VMC double flux ou hygroréglable. Chaudières fossiles exclues depuis le 01/03/2025.
B13: Immeuble rendu neuf : proportion de chaque élément de second œuvre | C13: 0.66666667 | D13: Stable | J13: ="CGI art. 257, I-2-2° ; CGI annexe II art. 245 A ; BOI-TVA-IMM-10-10-10-20 § 140 et suivants. "&"Vérifié le "&TEXT(DAY(Référentiel!$C$109),"00")&"/"&TEXT(MONTH(Référentiel!$C$109),"00")&"/"&YEAR(Référentiel!$C$109) -> CGI art. 257, I-2-2° ; CGI annexe II art. 245 A ; BOI-TVA-IMM-10-10-10-20 § 140 et suivants. Vérifié le 05/09/2026 | K13: Les six éléments (planchers non porteurs, huisseries extérieures, cloisons, plomberie et sanitaires, électricité, chauffage) refaits chacun à au moins cette proportion rendent l'immeuble neuf : 20 % sur tout.
B14: Extension de surface de plancher qui exclut les taux réduits | C14: 0.1 | D14: Stable | J14: ="CGI art. 279-0 bis, 2 bis ; BOI-TVA-LIQ-30-20-90-10 du 22/10/2025. "&"Vérifié le "&TEXT(DAY(Référentiel!$C$109),"00")&"/"&TEXT(MONTH(Référentiel!$C$109),"00")&"/"&YEAR(Référentiel!$C$109) -> CGI art. 279-0 bis, 2 bis ; BOI-TVA-LIQ-30-20-90-10 du 22/10/2025. Vérifié le 05/09/2026 | K14: Au-delà de cette augmentation de surface, l'ensemble des travaux est au taux normal.
B15: Ancienneté minimale du logement pour les taux réduits | C15: 2 | D15: Stable | J15: ="CGI art. 279-0 bis, 1 ; BOI-TVA-LIQ-30-20-90-10 § 10 : appréciée au début des travaux. "&"Vérifié le "&TEXT(DAY(Référentiel!$C$109),"00")&"/"&TEXT(MONTH(Référentiel!$C$109),"00")&"/"&YEAR(Référentiel!$C$109) -> CGI art. 279-0 bis, 1 ; BOI-TVA-LIQ-30-20-90-10 § 10 : appréciée au début des travaux. Vérifié le 05/09/2026 | K15: Achevé depuis plus de deux ans au début des travaux. Sinon 20 % sur tout le chantier.
B17: REPÈRES DE MARCHÉ ET CONVENTIONS DE CHIFFRAGE
B18: Paramètre | C18: Valeur | D18: Mise à jour | J18: Source (organisme, texte, date) | K18: Commentaire
B19: Coefficient de périmètre (périmètre = coefficient × racine de l'emprise) | C19: 4.2 | D19: Par dossier | J19: ="Géométrie : 4,0 pour un carré, 4,08 pour un rectangle 1,5:1, 4,24 pour un rectangle 2:1. "&"Vérifié le "&TEXT(DAY(Référentiel!$C$109),"00")&"/"&TEXT(MONTH(Référentiel!$C$109),"00")&"/"&YEAR(Référentiel!$C$109) -> Géométrie : 4,0 pour un carré, 4,08 pour un rectangle 1,5:1, 4,24 pour un rectangle 2:1. Vérifié le 05/09/2026 | K19: Convention CorpusImmo pour un plan allongé. Plan en L ou très étroit : montez à 4,5 ou forcez les murs.
B20: Nombre de façades d'un bâtiment (diviseur des façades exposées) | C20: 4 | D20: Jamais | J20: ="Géométrie. "&"Vérifié le "&TEXT(DAY(Référentiel!$C$109),"00")&"/"&TEXT(MONTH(Référentiel!$C$109),"00")&"/"&YEAR(Référentiel!$C$109) -> Géométrie. Vérifié le 05/09/2026 | K20: Murs de façade = périmètre × hauteur × niveaux × façades exposées / ce nombre.
B21: Coefficient de toiture (surface de toit = emprise × coefficient) | C21: 1.2 | D21: Par dossier | J21: ="Trigonométrie : 1/cos 30° = 1,155 ; 1/cos 35° = 1,221 ; 1,41 à 45°. "&"Vérifié le "&TEXT(DAY(Référentiel!$C$109),"00")&"/"&TEXT(MONTH(Référentiel!$C$109),"00")&"/"&YEAR(Référentiel!$C$109) -> Trigonométrie : 1/cos 30° = 1,155 ; 1/cos 35° = 1,221 ; 1,41 à 45°. Vérifié le 05/09/2026 | K21: 1,20 pour une pente de 30 à 35°. Toit plat : 1,00.
B22: Coût TTC au m² : au-dessus, on ne rafraîchit plus, on rénove | C22: 750 | D22: Annuelle | J22: ="Hellowatt 2026 : léger 250 à 750, moyen 750 à 1 500, lourd 2 000 à 4 000 €/m² TTC ; Illico Travaux 2026 : complet 1 000 à 1 800, lourd 1 500 et plus. "&"Vérifié le "&TEXT(DAY(Référentiel!$C$109),"00")&"/"&TEXT(MONTH(Référentiel!$C$109),"00")&"/"&YEAR(Référentiel!$C$109) -> Hellowatt 2026 : léger 250 à 750, moyen 750 à 1 500, lourd 2 000 à 4 000 €/m² TTC ; Illico Travaux 2026 : complet 1 000 à 1 800, lourd 1 500 et plus. Vérifié le 05/09/2026 | K22: Aléas et honoraires compris, comme le chiffrage.
B23: Coût TTC au m² : au-dessus, rénovation lourde ou restructuration | C23: 1500 | D23: Annuelle | J23: ="Mêmes sources. Le 1 500 €/m² est un plancher de rénovation lourde, pas un centre. "&"Vérifié le "&TEXT(DAY(Référentiel!$C$109),"00")&"/"&TEXT(MONTH(Référentiel!$C$109),"00")&"/"&YEAR(Référentiel!$C$109) -> Mêmes sources. Le 1 500 €/m² est un plancher de rénovation lourde, pas un centre. Vérifié le 05/09/2026 | K23: Au-delà, un maître d'œuvre s'impose.
B25: REPÈRES DE SAISIE DU CHIFFRAGE (BAS / HAUT) : CURSEUR PAR ZONE, ALÉAS, HONORAIRES
B26: Repère | C26: Bas | D26: Haut | J26: Source (organisme, texte, date) | K26: Commentaire
B27: Curseur de fourchette usuel, province | C27: 0.4 | D27: 0.6 | J27: ="Observatoire ARTEP (monimmeuble.com), Erema Bat 2026, AZ Bâtiments 2026 : Île-de-France + 15 à 30 % sur la province, Paris intra-muros + 20 à 35 %, soit un curseur plus haut, pas une autre grille. "&"Vérifié le "&TEXT(DAY(Référentiel!$C$109),"00")&"/"&TEXT(MONTH(Référentiel!$C$109),"00")&"/"&YEAR(Référentiel!$C$109) -> Observatoire ARTEP (monimmeuble.com), Erema Bat 2026, AZ Bâtiments 2026 : Île-de-France + 15 à 30 % sur la province, Paris intra-muros + 20 à 35 %, soit un curseur plus haut, pas une autre grille. Vérifié le 05/09/2026 | K27: Tension du marché et type d'entreprise : artisans en direct en bas, entreprise générale en haut.
B28: Curseur de fourchette usuel, Île-de-France | C28: 0.6 | D28: 0.8 | J28: ="Observatoire ARTEP (monimmeuble.com), Erema Bat 2026, AZ Bâtiments 2026 : Île-de-France + 15 à 30 % sur la province, Paris intra-muros + 20 à 35 %, soit un curseur plus haut, pas une autre grille. "&"Vérifié le "&TEXT(DAY(Référentiel!$C$109),"00")&"/"&TEXT(MONTH(Référentiel!$C$109),"00")&"/"&YEAR(Référentiel!$C$109) -> Observatoire ARTEP (monimmeuble.com), Erema Bat 2026, AZ Bâtiments 2026 : Île-de-France + 15 à 30 % sur la province, Paris intra-muros + 20 à 35 %, soit un curseur plus haut, pas une autre grille. Vérifié le 05/09/2026
B29: Curseur de fourchette usuel, Paris intra-muros | C29: 0.7 | D29: 1 | J29: ="Observatoire ARTEP (monimmeuble.com), Erema Bat 2026, AZ Bâtiments 2026 : Île-de-France + 15 à 30 % sur la province, Paris intra-muros + 20 à 35 %, soit un curseur plus haut, pas une autre grille. "&"Vérifié le "&TEXT(DAY(Référentiel!$C$109),"00")&"/"&TEXT(MONTH(Référentiel!$C$109),"00")&"/"&YEAR(Référentiel!$C$109) -> Observatoire ARTEP (monimmeuble.com), Erema Bat 2026, AZ Bâtiments 2026 : Île-de-France + 15 à 30 % sur la province, Paris intra-muros + 20 à 35 %, soit un curseur plus haut, pas une autre grille. Vérifié le 05/09/2026 | K29: Les fourchettes du Référentiel sont hors Paris intra-muros : c'est le curseur qui absorbe le surcoût.
B30: Provision pour aléas, rénovation dans l'ancien | C30: 0.1 | D30: 0.15 | J30: ="maitre-doeuvre.fr, architecte-batiments.fr, 2026 : 5 à 10 % en rénovation standard, 10 à 15 % dans l'ancien, 15 à 20 % avec inconnues structurelles. "&"Vérifié le "&TEXT(DAY(Référentiel!$C$109),"00")&"/"&TEXT(MONTH(Référentiel!$C$109),"00")&"/"&YEAR(Référentiel!$C$109) -> maitre-doeuvre.fr, architecte-batiments.fr, 2026 : 5 à 10 % en rénovation standard, 10 à 15 % dans l'ancien, 15 à 20 % avec inconnues structurelles. Vérifié le 05/09/2026 | K30: En dessous, vous pariez. Jusqu'à 20 % avec inconnues structurelles.
B31: Honoraires de maîtrise d'œuvre d'exécution | C31: 0.08 | D31: 0.12 | J31: ="Ootravaux, tarifs architecte 2026 ; Meta Architecte, barème 2026 : maîtrise d'œuvre 6 à 12 %, architecte 8 à 15 %, mission complète en rénovation 12 à 18 %. "&"Vérifié le "&TEXT(DAY(Référentiel!$C$109),"00")&"/"&TEXT(MONTH(Référentiel!$C$109),"00")&"/"&YEAR(Référentiel!$C$109) -> Ootravaux, tarifs architecte 2026 ; Meta Architecte, barème 2026 : maîtrise d'œuvre 6 à 12 %, architecte 8 à 15 %, mission complète en rénovation 12 à 18 %. Vérifié le 05/09/2026 | K31: Pourcentage des travaux HT, TVA 20 %.
B32: Honoraires d'architecte en mission complète, rénovation | C32: 0.12 | D32: 0.18 | J32: ="Ootravaux, tarifs architecte 2026 ; Meta Architecte, barème 2026 : maîtrise d'œuvre 6 à 12 %, architecte 8 à 15 %, mission complète en rénovation 12 à 18 %. "&"Vérifié le "&TEXT(DAY(Référentiel!$C$109),"00")&"/"&TEXT(MONTH(Référentiel!$C$109),"00")&"/"&YEAR(Référentiel!$C$109) -> Ootravaux, tarifs architecte 2026 ; Meta Architecte, barème 2026 : maîtrise d'œuvre 6 à 12 %, architecte 8 à 15 %, mission complète en rénovation 12 à 18 %. Vérifié le 05/09/2026
B34: FAMILLES DE LOTS ET BANDES USUELLES (PART DU SOUS-TOTAL HT)
B35: Famille | C35: Part basse | D35: Part haute | J35: Source | K35: Ce qu'elle regroupe
B36: Dépose et gros œuvre | C36: 0.05 | D36: 0.12 | J36: ="Convention CorpusImmo, non sourcée : à caler sur vos propres chantiers. Elle décrit une rénovation lourde de logement ancien. "&"Vérifié le "&TEXT(DAY(Référentiel!$C$109),"00")&"/"&TEXT(MONTH(Référentiel!$C$109),"00")&"/"&YEAR(Référentiel!$C$109) -> Convention CorpusImmo, non sourcée : à caler sur vos propres chantiers. Elle décrit une rénovation lourde de logement ancien. Vérifié le 05/09/2026 | K36: Dépose et démolition, gros œuvre
B37: Enveloppe | C37: 0.1 | D37: 0.3 | J37: Idem. | K37: Toiture, menuiseries extérieures, isolation, extérieurs
B38: Technique | C38: 0.25 | D38: 0.35 | J38: Idem. | K38: Électricité, plomberie, chauffage, ventilation
B39: Cloisons et finitions | C39: 0.15 | D39: 0.28 | J39: Idem. | K39: Plâtrerie, sols, peinture, menuiseries intérieures
B40: Cuisine et salle de bains | C40: 0.12 | D40: 0.25 | J40: Idem. | K40: Cuisine équipée, salle de bains, WC
B41: Postes libres | C41: 0 | D41: 0.15 | J41: Idem. | K41: Lignes ajoutées : désamiantage, plomb, ascenseur, escalier, diagnostics
B43: LOTS ET FAMILLES : LIBELLÉS FIXES, TESTÉS PAR LES FORMULES DU CHIFFRAGE
B44: Lot | C44: Famille | K44: Commentaire
B45: Dépose et démolition | C45: Dépose et gros œuvre | K45: Renommer un lot ici sans le renommer dans le tableau des fourchettes fait sortir ses lignes du contrôle par famille (le Chiffrage le signale).
B46: Gros œuvre | C46: Dépose et gros œuvre
B47: Charpente et toiture | C47: Enveloppe
B48: Menuiseries extérieures | C48: Enveloppe
B49: Isolation | C49: Enveloppe
B50: Extérieurs | C50: Enveloppe
B51: Électricité | C51: Technique
B52: Plomberie et chauffage | C52: Technique
B53: Ventilation | C53: Technique
B54: Cloisons et plâtrerie | C54: Cloisons et finitions
B55: Revêtements de sol | C55: Cloisons et finitions
B56: Peinture et finitions | C56: Cloisons et finitions
B57: Menuiseries intérieures | C57: Cloisons et finitions
... B60: Autre | C60: Postes libres
B62: LISTES DÉROULANTES DU BLOC TVA DU CHIFFRAGE
B63: Réponse (oui / non) | C63: Nature du local
B64: Oui | C64: Habitation
B65: Non | C65: Local autre
B66: Libellés fixes, testés par les formules du Chiffrage.
B68: FOURCHETTES DE PRIX PAR PRESTATION, MILLÉSIME 2026
B69: Prestation | C69: Lot | D69: Unité | E69: Bas de fourchette | F69: Haut de fourchette | G69: TVA | H69: Base du ratio | I69: Ratio | J69: Source et date de la fourchette | K69: Ce que dit le ratio
B70: Dépose de cloisons, sols et sanitaires | C70: Dépose et démolition | D70: m² au sol | E70: 25 | F70: 60 | G70: 0.1 | H70: Surface traitée | I70: 1 | J70: ="Hellowatt 2026 : dépose des sols seule 10 à 25 €/m². "&"Vérifié le "&TEXT(DAY(Référentiel!$C$109),"00")&"/"&TEXT(MONTH(Référentiel!$C$109),"00")&"/"&YEAR(Référentiel!$C$109) -> Hellowatt 2026 : dépose des sols seule 10 à 25 €/m². Vérifié le 05/09/2026 | K70: Toute la surface rénovée est déposée en rénovation lourde.
B71: Évacuation en benne | C71: Dépose et démolition | D71: forfait | E71: 400 | F71: 1200 | G71: 0.1 | H71: Surface habitable, arrondi au supérieur | I71: 0.0083 | J71: ="Grilles Hellowatt et Illico Travaux, 2026. "&"Vérifié le "&TEXT(DAY(Référentiel!$C$109),"00")&"/"&TEXT(MONTH(Référentiel!$C$109),"00")&"/"&YEAR(Référentiel!$C$109) -> Grilles Hellowatt et Illico Travaux, 2026. Vérifié le 05/09/2026 | K71: Une rotation par tranche de 120 m² entamée.
B72: Ouverture dans un mur porteur avec IPN | C72: Gros œuvre | D72: unité | E72: 1800 | F72: 4500 | G72: 0.1 | H72: Sans lien avec la surface | I72: 0 | J72: ="Grilles Hellowatt et Illico Travaux, 2026. "&"Vérifié le "&TEXT(DAY(Référentiel!$C$109),"00")&"/"&TEXT(MONTH(Référentiel!$C$109),"00")&"/"&YEAR(Référentiel!$C$109) -> Grilles Hellowatt et Illico Travaux, 2026. Vérifié le 05/09/2026 | K72: À compter sur plan. Quantité forcée dans le scénario livré.
B73: Reprise de maçonnerie et rebouchage | C73: Gros œuvre | D73: m² | E73: 45 | F73: 110 | G73: 0.1 | H73: Sans lien avec la surface | I73: 0 | J73: ="Grilles Hellowatt et Illico Travaux, 2026. "&"Vérifié le "&TEXT(DAY(Référentiel!$C$109),"00")&"/"&TEXT(MONTH(Référentiel!$C$109),"00")&"/"&YEAR(Référentiel!$C$109) -> Grilles Hellowatt et Illico Travaux, 2026. Vérifié le 05/09/2026 | K73: Dépend des ouvertures reprises, pas de la surface. Quantité forcée dans le scénario livré.
B74: Réfection de couverture en tuiles | C74: Charpente et toiture | D74: m² de toit | E74: 90 | F74: 190 | G74: 0.1 | H74: Surface de toit | I74: 1 | J74: ="Illico Travaux 2026 et Hellowatt 2026 : toiture complète (charpente et couverture) 180 à 260 €/m² ; couverture seule non contredite. "&"Vérifié le "&TEXT(DAY(Référentiel!$C$109),"00")&"/"&TEXT(MONTH(Référentiel!$C$109),"00")&"/"&YEAR(Référentiel!$C$109) -> Illico Travaux 2026 et Hellowatt 2026 : toiture complète (charpente et couverture) 180 à 260 €/m² ; couverture seule non contredite. Vérifié le 05/09/2026 | K74: Désactivée par défaut (appartement) : effacez le 0 en quantité forcée pour l'activer.
B75: Traitement de charpente | C75: Charpente et toiture | D75: m² au sol | E75: 25 | F75: 55 | G75: 0.1 | H75: Emprise au sol | I75: 1 | J75: ="Grilles Hellowatt et Illico Travaux, 2026. "&"Vérifié le "&TEXT(DAY(Référentiel!$C$109),"00")&"/"&TEXT(MONTH(Référentiel!$C$109),"00")&"/"&YEAR(Référentiel!$C$109) -> Grilles Hellowatt et Illico Travaux, 2026. Vérifié le 05/09/2026 | K75: Désactivé par défaut. Effacez le 0 pour l'activer.
B76: Fenêtre PVC double vitrage posée | C76: Menuiseries extérieures | D76: unité | E76: 550 | F76: 1400 | G76: 0.055 | H76: Surface habitable | I76: 0.0769 | J76: ="Hellowatt 2026 : 800 à 1 400 € l'unité posée ; Illico Travaux 2026 : 200 à 600 € en fourniture. TVA 5,5 % : arrêté du 24/12/2024. "&"Vérifié le "&TEXT(DAY(Référentiel!$C$109),"00")&"/"&TEXT(MONTH(Référentiel!$C$109),"00")&"/"&YEAR(Référentiel!$C$109) -> Hellowatt 2026 : 800 à 1 400 € l'unité posée ; Illico Travaux 2026 : 200 à 600 € en fourniture. TVA 5,5 % : arrêté du 24/12/2024. Vérifié le 05/09/2026 | K76: Une menuiserie pour 13 m² habitables. À recompter sur plan.
B77: Porte d'entrée | C77: Menuiseries extérieures | D77: unité | E77: 900 | F77: 2600 | G77: 0.055 | H77: Logement | I77: 1 | J77: ="Grilles Hellowatt et Illico Travaux, 2026. TVA 5,5 % (porte donnant sur l'extérieur) : arrêté du 24/12/2024. "&"Vérifié le "&TEXT(DAY(Référentiel!$C$109),"00")&"/"&TEXT(MONTH(Référentiel!$C$109),"00")&"/"&YEAR(Référentiel!$C$109) -> Grilles Hellowatt et Illico Travaux, 2026. TVA 5,5 % (porte donnant sur l'extérieur) : arrêté du 24/12/2024. Vérifié le 05/09/2026 | K77: Une par logement ; deux sur une maison avec accès de service.
B78: Isolation des murs par l'intérieur | C78: Isolation | D78: m² de mur | E78: 45 | F78: 95 | G78: 0.055 | H78: Murs de façade | I78: 1 | J78: ="Educ Spe 2026 (synthèse) : 30 à 120 €/m² selon la technique. "&"Vérifié le "&TEXT(DAY(Référentiel!$C$109),"00")&"/"&TEXT(MONTH(Référentiel!$C$109),"00")&"/"&YEAR(Référentiel!$C$109) -> Educ Spe 2026 (synthèse) : 30 à 120 €/m² selon la technique. Vérifié le 05/09/2026 | K78: Périmètre × hauteur sous plafond × niveaux × façades exposées / 4.
B79: Isolation des combles perdus | C79: Isolation | D79: m² au sol | E79: 25 | F79: 60 | G79: 0.055 | H79: Emprise au sol | I79: 1 | J79: ="Hellowatt 2026 : 19 à 22 €/m² en soufflage. Bas de fourchette prudent. "&"Vérifié le "&TEXT(DAY(Référentiel!$C$109),"00")&"/"&TEXT(MONTH(Référentiel!$C$109),"00")&"/"&YEAR(Référentiel!$C$109) -> Hellowatt 2026 : 19 à 22 €/m² en soufflage. Bas de fourchette prudent. Vérifié le 05/09/2026 | K79: Désactivée par défaut. Effacez le 0 pour l'activer.
B80: Cloison placo sur ossature | C80: Cloisons et plâtrerie | D80: m² | E80: 45 | F80: 95 | G80: 0.1 | H80: Surface traitée × hauteur sous plafond | I80: 0.2 | J80: ="Grilles Hellowatt et Illico Travaux, 2026. "&"Vérifié le "&TEXT(DAY(Référentiel!$C$109),"00")&"/"&TEXT(MONTH(Référentiel!$C$109),"00")&"/"&YEAR(Référentiel!$C$109) -> Grilles Hellowatt et Illico Travaux, 2026. Vérifié le 05/09/2026 | K80: 0,20 ml/m² = redistribution légère. 0,40 = redistribution lourde.
B81: Doublage et enduit de finition | C81: Cloisons et plâtrerie | D81: m² | E81: 30 | F81: 65 | G81: 0.1 | H81: Murs de façade | I81: 1 | J81: ="Grilles Hellowatt et Illico Travaux, 2026. "&"Vérifié le "&TEXT(DAY(Référentiel!$C$109),"00")&"/"&TEXT(MONTH(Référentiel!$C$109),"00")&"/"&YEAR(Référentiel!$C$109) -> Grilles Hellowatt et Illico Travaux, 2026. Vérifié le 05/09/2026 | K81: Suit l'isolation intérieure. Travail induit : peut suivre son 5,5 % (vérifiez, puis changez le taux ici).
B82: Électricité complète, NF C 15-100 | C82: Électricité | D82: m² au sol | E82: 90 | F82: 165 | G82: 0.1 | H82: Surface traitée | I82: 1 | J82: ="Hellowatt 2026 : 50 à 200 €/m², 8 000 à 15 000 € pour 100 m² ; Illico Travaux 2026 : 50 à 100 €/m². "&"Vérifié le "&TEXT(DAY(Référentiel!$C$109),"00")&"/"&TEXT(MONTH(Référentiel!$C$109),"00")&"/"&YEAR(Référentiel!$C$109) -> Hellowatt 2026 : 50 à 200 €/m², 8 000 à 15 000 € pour 100 m² ; Illico Travaux 2026 : 50 à 100 €/m². Vérifié le 05/09/2026 | K82: Refaite à neuf sur toute la surface rénovée.
B83: Tableau électrique neuf | C83: Électricité | D83: unité | E83: 900 | F83: 2200 | G83: 0.1 | H83: Logement | I83: 1 | J83: ="Grilles Hellowatt et Illico Travaux, 2026. "&"Vérifié le "&TEXT(DAY(Référentiel!$C$109),"00")&"/"&TEXT(MONTH(Référentiel!$C$109),"00")&"/"&YEAR(Référentiel!$C$109) -> Grilles Hellowatt et Illico Travaux, 2026. Vérifié le 05/09/2026 | K83: Un par logement.
B84: Réseau plomberie complet | C84: Plomberie et chauffage | D84: m² au sol | E84: 55 | F84: 120 | G84: 0.1 | H84: Surface traitée | I84: 1 | J84: ="Hellowatt 2026 : 70 à 150 €/m², 5 000 à 15 000 € pour 100 m². "&"Vérifié le "&TEXT(DAY(Référentiel!$C$109),"00")&"/"&TEXT(MONTH(Référentiel!$C$109),"00")&"/"&YEAR(Référentiel!$C$109) -> Hellowatt 2026 : 70 à 150 €/m², 5 000 à 15 000 € pour 100 m². Vérifié le 05/09/2026 | K84: Refait à neuf sur toute la surface rénovée.
B85: Pompe à chaleur air/eau ou air/air | C85: Plomberie et chauffage | D85: unité | E85: 3500 | F85: 14000 | G85: 0.055 | H85: Logement | I85: 1 | J85: ="Hellowatt 2026 : PAC hybride 4 500 à 12 000 € (air/air en bas de fourchette, air/eau en haut). TVA 5,5 % : arrêté du 24/12/2024 ; PAC air/air ajoutées par l'arrêté du 13/07/2026 (JO du 17/07/2026), Ef"&"fy 2026. "&"Vérifié le "&TEXT(DAY(Référentiel!$C$109),"00")&"/"&TEXT(MONTH(Référentiel!$C$109),"00")&"/"&YEAR(Référentiel!$C$109) -> Hellowatt 2026 : PAC hybride 4 500 à 12 000 € (air/air en bas de fourchette, air/eau en haut). TVA 5,5 % : arrêté du 24/12/2024 ; PAC air/air ajoutées par l'arrêté du 13/07/2026 (JO du 17/07/2026), Effy 2026. Vérifié le 05/09/2026 | K85: Fourchette de 1 à 4 : choix d'équipement, pas de marché. Forcez le prix.
B86: Chaudière gaz ou fioul posée | C86: Plomberie et chauffage | D86: unité | E86: 4000 | F86: 7000 | G86: 0.2 | H86: Logement | I86: 1 | J86: ="Hellowatt 2026 : chaudière gaz 4 000 à 7 000 €. TVA 20 % depuis le 01/03/2025 : LF 2025 art. 32 ; BOFiP ACTU-2025-00165 du 22/10/2025 ; Service-public F23568 (21/02/2026) ; Quelle Énergie 2026. "&"Vérifié le "&TEXT(DAY(Référentiel!$C$109),"00")&"/"&TEXT(MONTH(Référentiel!$C$109),"00")&"/"&YEAR(Référentiel!$C$109) -> Hellowatt 2026 : chaudière gaz 4 000 à 7 000 €. TVA 20 % depuis le 01/03/2025 : LF 2025 art. 32 ; BOFiP ACTU-2025-00165 du 22/10/2025 ; Service-public F23568 (21/02/2026) ; Quelle Énergie 2026. Vérifié le 05/09/2026 | K86: Désactivée par défaut : l'exemple est équipé d'une pompe à chaleur. Effacez le 0 pour l'activer.
B87: Radiateurs posés | C87: Plomberie et chauffage | D87: unité | E87: 250 | F87: 800 | G87: 0.1 | H87: Surface habitable | I87: 0.0625 | J87: ="Grilles Hellowatt et Illico Travaux, 2026. "&"Vérifié le "&TEXT(DAY(Référentiel!$C$109),"00")&"/"&TEXT(MONTH(Référentiel!$C$109),"00")&"/"&YEAR(Référentiel!$C$109) -> Grilles Hellowatt et Illico Travaux, 2026. Vérifié le 05/09/2026 | K87: Un émetteur pour 16 m².
B88: VMC hygroréglable ou double flux | C88: Ventilation | D88: logement | E88: 700 | F88: 5500 | G88: 0.055 | H88: Logement | I88: 1 | J88: ="Grilles Hellowatt et Illico Travaux, 2026. TVA 5,5 % réservée à la double flux et à la simple flux hygroréglable : arrêté du 24/12/2024, FFB (25/08/2026), CAPEB. "&"Vérifié le "&TEXT(DAY(Référentiel!$C$109),"00")&"/"&TEXT(MONTH(Référentiel!$C$109),"00")&"/"&YEAR(Référentiel!$C$109) -> Grilles Hellowatt et Illico Travaux, 2026. TVA 5,5 % réservée à la double flux et à la simple flux hygroréglable : arrêté du 24/12/2024, FFB (25/08/2026), CAPEB. Vérifié le 05/09/2026 | K88: Hygro B en bas de fourchette, double flux en haut. Forcez le prix. Simple flux autoréglable : 10 %.
B89: Parquet stratifié ou contrecollé posé | C89: Revêtements de sol | D89: m² | E89: 35 | F89: 110 | G89: 0.1 | H89: Surface traitée | I89: 0.7 | J89: ="Hellowatt 2026 : sols posés 50 à 250 €/m² ; Illico Travaux 2026 : 20 à 100 €/m². "&"Vérifié le "&TEXT(DAY(Référentiel!$C$109),"00")&"/"&TEXT(MONTH(Référentiel!$C$109),"00")&"/"&YEAR(Référentiel!$C$109) -> Hellowatt 2026 : sols posés 50 à 250 €/m² ; Illico Travaux 2026 : 20 à 100 €/m². Vérifié le 05/09/2026 | K89: 70 % de la surface traitée. Parquet + carrelage doivent faire 100 %.
B90: Carrelage posé | C90: Revêtements de sol | D90: m² | E90: 55 | F90: 140 | G90: 0.1 | H90: Surface traitée | I90: 0.3 | J90: ="Mêmes sources que le parquet. "&"Vérifié le "&TEXT(DAY(Référentiel!$C$109),"00")&"/"&TEXT(MONTH(Référentiel!$C$109),"00")&"/"&YEAR(Référentiel!$C$109) -> Mêmes sources que le parquet. Vérifié le 05/09/2026 | K90: 30 % de la surface traitée : pièces humides et cuisine.
B91: Peinture murs et plafonds | C91: Peinture et finitions | D91: m² au sol | E91: 52 | F91: 112 | G91: 0.1 | H91: Surface traitée | I91: 1 | J91: ="Monsieur Peinture, grille 2026 : 17,50 €/m² peint en rafraîchissement, 27,50 à 37,50 avec enduit ; Travaux.com 2026 : murs 20 à 35, plafonds 30 à 45 ; Hellowatt 2026 : enduit et peinture 50 à 100 €/m²"&". Avec le ratio 3 (murs et plafonds / sol) : 52 à 112 €/m² au sol. "&"Vérifié le "&TEXT(DAY(Référentiel!$C$109),"00")&"/"&TEXT(MONTH(Référentiel!$C$109),"00")&"/"&YEAR(Référentiel!$C$109) -> Monsieur Peinture, grille 2026 : 17,50 €/m² peint en rafraîchissement, 27,50 à 37,50 avec enduit ; Travaux.com 2026 : murs 20 à 35, plafonds 30 à 45 ; Hellowatt 2026 : enduit et peinture 50 à 100 €/m². Avec le ratio 3 (murs et plafonds / sol) : 52 à 112 €/m² au sol. Vérifié le 05/09/2026 | K91: PRIX AU M² AU SOL : il intègre un ratio murs + plafonds de 3. Ne saisissez jamais une surface de murs ici.
B92: Bloc-porte posé | C92: Menuiseries intérieures | D92: unité | E92: 250 | F92: 650 | G92: 0.1 | H92: Surface habitable | I92: 0.0625 | J92: ="Grilles Hellowatt et Illico Travaux, 2026. "&"Vérifié le "&TEXT(DAY(Référentiel!$C$109),"00")&"/"&TEXT(MONTH(Référentiel!$C$109),"00")&"/"&YEAR(Référentiel!$C$109) -> Grilles Hellowatt et Illico Travaux, 2026. Vérifié le 05/09/2026 | K92: Un pour 16 m², ou nombre de pièces + 1.
B93: Cuisine équipée posée | C93: Cuisine | D93: unité | E93: 3500 | F93: 15000 | G93: 0.1 | H93: Logement | I93: 1 | J93: ="Illico Travaux 2026 : 1 500 à 15 000 €. "&"Vérifié le "&TEXT(DAY(Référentiel!$C$109),"00")&"/"&TEXT(MONTH(Référentiel!$C$109),"00")&"/"&YEAR(Référentiel!$C$109) -> Illico Travaux 2026 : 1 500 à 15 000 €. Vérifié le 05/09/2026 | K93: TVA 10 % sur la pose, 20 % sur l'électroménager : arbitrez selon votre devis.
B94: Salle de bains complète | C94: Salle de bains | D94: unité | E94: 4000 | F94: 14000 | G94: 0.1 | H94: Surface habitable, au moins 1 | I94: 0.0143 | J94: ="Illico Travaux 2026 : 3 000 à 15 000 €. "&"Vérifié le "&TEXT(DAY(Référentiel!$C$109),"00")&"/"&TEXT(MONTH(Référentiel!$C$109),"00")&"/"&YEAR(Référentiel!$C$109) -> Illico Travaux 2026 : 3 000 à 15 000 €. Vérifié le 05/09/2026 | K94: Une pour 70 m², au moins une.
B95: WC suspendu posé | C95: Salle de bains | D95: unité | E95: 450 | F95: 1100 | G95: 0.1 | H95: Surface habitable, au moins 1 | I95: 0.0167 | J95: ="Grilles Hellowatt et Illico Travaux, 2026. "&"Vérifié le "&TEXT(DAY(Référentiel!$C$109),"00")&"/"&TEXT(MONTH(Référentiel!$C$109),"00")&"/"&YEAR(Référentiel!$C$109) -> Grilles Hellowatt et Illico Travaux, 2026. Vérifié le 05/09/2026 | K95: Un pour 60 m², au moins un.
B96: Ravalement de façade | C96: Extérieurs | D96: m² de façade | E96: 50 | F96: 130 | G96: 0.1 | H96: Murs de façade | I96: 1 | J96: ="Illico Travaux 2026 : 20 à 120 €/m². "&"Vérifié le "&TEXT(DAY(Référentiel!$C$109),"00")&"/"&TEXT(MONTH(Référentiel!$C$109),"00")&"/"&YEAR(Référentiel!$C$109) -> Illico Travaux 2026 : 20 à 120 €/m². Vérifié le 05/09/2026 | K96: Désactivé par défaut. Effacez le 0 pour l'activer.
B97: Reprise de VRD et abords | C97: Extérieurs | D97: m² | E97: 40 | F97: 120 | G97: 0.1 | H97: Sans lien avec la surface | I97: 0 | J97: ="Grilles Hellowatt et Illico Travaux, 2026. "&"Vérifié le "&TEXT(DAY(Référentiel!$C$109),"00")&"/"&TEXT(MONTH(Référentiel!$C$109),"00")&"/"&YEAR(Référentiel!$C$109) -> Grilles Hellowatt et Illico Travaux, 2026. Vérifié le 05/09/2026 | K97: À relever sur plan de masse.
B98: Poste libre 1 (à compléter) | C98: Autre | D98: unité | E98: 0 | F98: 0 | G98: 0.1 | H98: Sans lien avec la surface | I98: 0 | J98: ="À renseigner par l'utilisateur, avec son devis. "&"Vérifié le "&TEXT(DAY(Référentiel!$C$109),"00")&"/"&TEXT(MONTH(Référentiel!$C$109),"00")&"/"&YEAR(Référentiel!$C$109) -> À renseigner par l'utilisateur, avec son devis. Vérifié le 05/09/2026 | K98: Ligne libre : désamiantage, plomb, ascenseur, escalier, diagnostics, dommages-ouvrage. Le Chiffrage la reprend.
B99: Poste libre 2 (à compléter) | C99: Autre | D99: unité | E99: 0 | F99: 0 | G99: 0.1 | H99: Sans lien avec la surface | I99: 0 | J99: ="À renseigner par l'utilisateur, avec son devis. "&"Vérifié le "&TEXT(DAY(Référentiel!$C$109),"00")&"/"&TEXT(MONTH(Référentiel!$C$109),"00")&"/"&YEAR(Référentiel!$C$109) -> À renseigner par l'utilisateur, avec son devis. Vérifié le 05/09/2026 | K99: Ligne libre.
B100: Poste libre 3 (à compléter) | C100: Autre | D100: unité | E100: 0 | F100: 0 | G100: 0.1 | H100: Sans lien avec la surface | I100: 0 | J100: ="À renseigner par l'utilisateur, avec son devis. "&"Vérifié le "&TEXT(DAY(Référentiel!$C$109),"00")&"/"&TEXT(MONTH(Référentiel!$C$109),"00")&"/"&YEAR(Référentiel!$C$109) -> À renseigner par l'utilisateur, avec son devis. Vérifié le 05/09/2026 | K100: Ligne libre.
B103: Deux colonnes gouvernent tout le chiffrage. La fourchette de prix dit combien coûte une prestation ; le ratio dit combien il y en a.
B104: Les ratios géométriques (emprise, périmètre, murs, toit) sont exacts et n'ont pas à être discutés. Les ratios de comptage (une fenêtre pour 13 m², un radiateur pour 16 m²,
B105: un bloc-porte pour 16 m², une salle de bains pour 70 m²) sont des conventions de chiffrage : ils cadrent un budget avant de compter sur plan, ils ne remplacent pas le comptage.
B106: Les fourchettes sont larges parce que le marché l'est : un artisan en direct en zone détendue et une entreprise générale en zone tendue varient du simple au triple sur la même prestation.
B107: Confrontez ces deux colonnes à vos trois derniers chantiers et corrigez-les : ce sont VOS prix et VOS ratios qui comptent. Tout le reste du classeur suivra.
B109: Dernière vérification du référentiel | C109: 46270 | D109: =IF(TODAY()-C109>365,"Référentiel vieux de plus d'un an : reprenez les prix et les taux.","À refaire chaque janvier. Toutes les mentions « Vérifié le » de ce classeur lisent cette cellule.") -> À refaire chaque janvier. Toutes les mentions « Vérifié le » de ce classeur lisent cette cellule.
B110: Aucun de ces taux n'est recopié dans une formule : toutes pointent ici.
B111: CorpusImmo, millésime 2026. Modèle d'aide à la décision : ne constitue ni un conseil en investissement, ni un conseil fiscal, ni une expertise au sens de la charte de l'expertise en évaluation immobilière. Vérifiez les paramètres avant tout engagement.

Sheet Méthode
B1: CorpusImmo · www.corpus.immo · Estimer, comparer, décider. Sur les ventes réelles.
B2: Méthode et limites
B3: Comment lire ce chiffrage, ce qu'il ne dit pas, et sur quelles sources reposent ses chiffres.
B5: CONVENTIONS RETENUES, ET CE QU'ELLES COÛTENT
B6: Les cinq entrées | C6: Surface habitable, nombre de niveaux, hauteur sous plafond, façades exposées, part rénovée. Elles suffisent à remplir les vingt-huit postes. Tout le reste est déduit ou forçable. Un bloc de douze réponses oui / non qualifie ensuite la TVA du chantier.
B7: Quantité auto | C7: Base × ratio, arrondie à l'unité pour que le chiffre affiché soit exactement celui qui est multiplié. La base et le ratio sont lisibles ligne à ligne dans le Référentiel.
B8: Quantité et prix forcés | C8: Une valeur saisie dans une colonne violette l'emporte toujours sur le calcul, sans le détruire : effacez-la et l'automatisme revient. C'est la colonne à remplir à mesure que les devis arrivent. Saisir 0 en quantité forcée désactive le poste.
B9: Géométrie | C9: Emprise = surface / niveaux. Périmètre = coefficient × racine de l'emprise (4,2 dans le Référentiel : 4,0 pour un carré, 4,24 pour un rectangle 2:1) : il n'est pas proportionnel à la surface, un coefficient linéaire se trompe de 30 % dès 160 m². Murs de façade = périmètre × hauteur × niveaux × façades exposées / 4 : c'est le paramètre façades qui distingue un appartement d'une maison. Toit = emprise × coefficient de pente (1,20 pour 30 à 35°). Les trois coefficients (périmètre, nombre de façades, pente) sont des cellules du Référentiel : ce ne sont plus des constantes écrites dans les formules, vous pouvez les changer.
B10: Prix retenu | C10: Prix bas + (prix haut − prix bas) × curseur. Le curseur unique représente la tension du marché et le type d'entreprise : 0 à 30 % artisans en direct en zone détendue, 40 à 60 % cas courant, 70 à 100 % entreprise générale, zone tendue, délais courts ou copropriété contraignante. Le curseur est borné de 0 à 100 % par validation. Il absorbe aussi la zone : Île-de-France + 15 à 30 % sur la province, Paris intra-muros + 20 à 35 % (Observatoire ARTEP, Erema Bat 2026), soit un curseur de 60 à 80 %, pas une autre grille.
B11: Fourchette basse et haute | C11: Le récapitulatif affiche trois colonnes : le bas de fourchette (tous les prix au curseur 0 %), le chiffrage retenu (curseur saisi) et le haut (curseur 100 %), avec les mêmes quantités et les mêmes forçages. Un prix forcé vaut dans les trois colonnes : c'est un devis, il n'a plus de fourchette. La fourchette est donc celle des postes encore non devisés.
B12: Quand forcer un prix | C12: Quatre postes ont une fourchette de 1 à 4 parce qu'ils recouvrent un choix d'équipement et non une tension de marché : pompe à chaleur ou chaudière, cuisine, salle de bains, VMC. Ils pèsent environ un tiers du budget. Le curseur ne sait pas arbitrer à votre place : forcez leur prix.
B13: Provision pour aléas | C13: Appliquée aux lots, avant honoraires et avant TVA. Ce n'est pas une marge de confort : en rénovation ancienne, la découverte à l'ouverture des murs est la première cause de dérapage. En dessous de 10 %, vous pariez.
B14: Honoraires | C14: Pourcentage des travaux hors taxes. Les fourchettes usuelles sont dans le Référentiel, bloc Repères de saisie : maîtrise d'œuvre d'exécution, et architecte en mission complète. Le commentaire de la cellule des honoraires les affiche. Ils restent à 20 % de TVA : une prestation intellectuelle ne bénéficie pas du taux réduit, même quand les travaux qu'elle pilote en bénéficient.
B15: TVA par ligne | C15: Chaque prestation porte son taux dans le Référentiel, choisi dans une liste de trois : 5,5 % sur la rénovation énergétique éligible selon l'arrêté du 24 décembre 2024 (isolation, fenêtres et portes extérieures, pompes à chaleur, y compris air/air depuis le 18 juillet 2026, VMC double flux ou hygroréglable), 10 % sur l'amélioration d'un logement achevé depuis plus de deux ans, 20 % sinon. Une chaudière gaz ou fioul est à 20 % depuis le 1er mars 2025, même à très haute performance. Une VMC simple flux autoréglable est à 10 %. Les travaux induits par une opération énergétique peuvent suivre son taux (le doublage et la peinture qui suivent une isolation) : le classeur ne l'applique pas seul, changez le taux de la ligne dans le Référentiel après vérification. Le taux forcé du Chiffrage, choisi dans la même liste, remplace tous les taux de ligne.
B16: Immeuble rendu à l'état neuf | C16: Le bloc de qualification du Chiffrage applique la règle de bascule au taux normal : local autre que d'habitation, logement de moins de deux ans au début des travaux, augmentation de la surface de plancher de plus de 10 %, ou immeuble rendu neuf. Un immeuble est rendu neuf (CGI art. 257, I-2-2° et annexe II art. 245 A) quand les travaux refont la majorité des fondations, ou la majorité des éléments hors fondations qui déterminent la résistance et la rigidité de l'ouvrage, ou la majorité de la consistance des façades hors ravalement, ou les six éléments de second œuvre chacun à au moins deux tiers : planchers non porteurs, huisseries extérieures, cloisons intérieures, installations sanitaires et plomberie, installations électriques, chauffage. Dès qu'un critère est rempli, la cellule « Taux réduits admis » passe au rouge, le taux appliqué à toutes les lignes devient 20 % et le récapitulatif suit. Le classeur compte aussi, à titre indicatif, les éléments de second œuvre que le chiffrage lui-même refait (part rénovée d'au moins deux tiers, lignes actives) et signale « À VÉRIFIER » si vous en déclarez moins. C'est le premier risque fiscal d'une rénovation lourde de marchand de biens : il touche aussi le régime de TVA de la revente, que ce classeur ne traite pas.
B17: Mention sur le devis | C17: L'attestation écrite du client pour les taux réduits est supprimée depuis février 2025 (LF 2025, art. 41). Le client certifie directement sur le devis ou la facture que les conditions sont remplies (nature du local, ancienneté, travaux n'aboutissant pas à un immeuble neuf), et conserve le document jusqu'au 31 décembre de la cinquième année. Le prestataire est déchargé si la mention est inexacte du fait du client.
... B21: Taux et formats | C21: Tous les taux sont des fractions affichées en pourcentage : tapez 12 dans la cellule des aléas, elle affiche 12,0 % et contient 0,12. Aucune formule ne divise par 100. Les quantités sont arrondies à l'unité, les montants sont en euros hors taxes puis toutes taxes comprises, la date de vérification du Référentiel est une vraie date.
B23: CE QUE CE MODÈLE NE FAIT PAS
B24: • Il ne remplace pas un devis. Il sert à décider s'il vaut la peine d'en demander trois.
B25: • Les ratios de comptage cadrent, ils ne comptent pas : au-delà de l'avant-projet, relevez sur plan.
B26: • Il suppose un logement de forme compacte. Sur un plan très développé ou très étroit, forcez les surfaces de murs.
B27: • Il ignore les contraintes de site : étage sans ascenseur, accès difficile, copropriété, ABF.
B28: • Il ne chiffre ni le désamiantage, ni le plomb, ni les fondations, ni les diagnostics et études (amiante, plomb, structure, DPE projeté), ni l'assurance dommages-ouvrage, obligatoire dès qu'il y a gros œuvre. Trois lignes libres sont prévues pour eux, à renseigner dans le Référentiel.
B29: • Il n'intègre aucune aide (MaPrimeRénov', CEE, éco-PTZ) : leurs barèmes changent trop vite pour être figés ici.
B30: • Il ne gère ni le phasage, ni les délais, ni le coût de portage.
B31: • Il n'applique pas de lui-même le taux des travaux induits (doublage, peinture après isolation) : c'est à vous de changer le taux de la ligne.
B32: • Il ne pré-positionne pas le curseur selon la zone (province, métropole, Île-de-France, Paris) : le commentaire du curseur donne les repères.
B33: • L'éligibilité au taux réduit relève de la mention certifiée par le client sur le devis ou la facture (attestation supprimée depuis février 2025), pas de ce tableau : le bloc TVA aide à qualifier, il ne certifie rien.
B34: • Il ne traite pas la TVA de la revente (TVA sur marge, régime du marchand de biens, immeuble neuf à la revente) ni les droits d'enregistrement.
B36: SOURCES
B37: TVA, taux normal | C37: ="CGI art. 278 ; Service-public Entreprendre F23568, mis à jour le 21/02/2026. "&"Vérifié le "&TEXT(DAY(Référentiel!$C$109),"00")&"/"&TEXT(MONTH(Référentiel!$C$109),"00")&"/"&YEAR(Référentiel!$C$109) -> CGI art. 278 ; Service-public Entreprendre F23568, mis à jour le 21/02/2026. Vérifié le 05/09/2026
B38: TVA, taux intermédiaire (amélioration d'un logement de plus de 2 ans) | C38: ="CGI art. 279-0 bis ; BOI-TVA-LIQ-30-20-90-10 du 22/10/2025. "&"Vérifié le "&TEXT(DAY(Référentiel!$C$109),"00")&"/"&TEXT(MONTH(Référentiel!$C$109),"00")&"/"&YEAR(Référentiel!$C$109) -> CGI art. 279-0 bis ; BOI-TVA-LIQ-30-20-90-10 du 22/10/2025. Vérifié le 05/09/2026
B39: TVA, taux réduit (rénovation énergétique éligible) | C39: ="CGI art. 278-0 bis A ; arrêté du 24/12/2024 (liste des équipements) ; BOFiP ACTU-2025-00165 du 22/10/2025 ; FFB, liste du 25/08/2026. "&"Vérifié le "&TEXT(DAY(Référentiel!$C$109),"00")&"/"&TEXT(MONTH(Référentiel!$C$109),"00")&"/"&YEAR(Référentiel!$C$109) -> CGI art. 278-0 bis A ; arrêté du 24/12/2024 (liste des équipements) ; BOFiP ACTU-2025-00165 du 22/10/2025 ; FFB, liste du 25/08/2026. Vérifié le 05/09/2026
B40: Immeuble rendu neuf : proportion de chaque élément de second œuvre | C40: ="CGI art. 257, I-2-2° ; CGI annexe II art. 245 A ; BOI-TVA-IMM-10-10-10-20 § 140 et suivants. "&"Vérifié le "&TEXT(DAY(Référentiel!$C$109),"00")&"/"&TEXT(MONTH(Référentiel!$C$109),"00")&"/"&YEAR(Référentiel!$C$109) -> CGI art. 257, I-2-2° ; CGI annexe II art. 245 A ; BOI-TVA-IMM-10-10-10-20 § 140 et suivants. Vérifié le 05/09/2026
B41: Extension de surface de plancher qui exclut les taux réduits | C41: ="CGI art. 279-0 bis, 2 bis ; BOI-TVA-LIQ-30-20-90-10 du 22/10/2025. "&"Vérifié le "&TEXT(DAY(Référentiel!$C$109),"00")&"/"&TEXT(MONTH(Référentiel!$C$109),"00")&"/"&YEAR(Référentiel!$C$109) -> CGI art. 279-0 bis, 2 bis ; BOI-TVA-LIQ-30-20-90-10 du 22/10/2025. Vérifié le 05/09/2026
B42: Ancienneté minimale du logement pour les taux réduits | C42: ="CGI art. 279-0 bis, 1 ; BOI-TVA-LIQ-30-20-90-10 § 10 : appréciée au début des travaux. "&"Vérifié le "&TEXT(DAY(Référentiel!$C$109),"00")&"/"&TEXT(MONTH(Référentiel!$C$109),"00")&"/"&YEAR(Référentiel!$C$109) -> CGI art. 279-0 bis, 1 ; BOI-TVA-LIQ-30-20-90-10 § 10 : appréciée au début des travaux. Vérifié le 05/09/2026
B43: Coefficient de périmètre (périmètre = coefficient × racine de l'emprise) | C43: ="Géométrie : 4,0 pour un carré, 4,08 pour un rectangle 1,5:1, 4,24 pour un rectangle 2:1. "&"Vérifié le "&TEXT(DAY(Référentiel!$C$109),"00")&"/"&TEXT(MONTH(Référentiel!$C$109),"00")&"/"&YEAR(Référentiel!$C$109) -> Géométrie : 4,0 pour un carré, 4,08 pour un rectangle 1,5:1, 4,24 pour un rectangle 2:1. Vérifié le 05/09/2026
B44: Nombre de façades d'un bâtiment (diviseur des façades exposées) | C44: ="Géométrie. "&"Vérifié le "&TEXT(DAY(Référentiel!$C$109),"00")&"/"&TEXT(MONTH(Référentiel!$C$109),"00")&"/"&YEAR(Référentiel!$C$109) -> Géométrie. Vérifié le 05/09/2026
B45: Coefficient de toiture (surface de toit = emprise × coefficient) | C45: ="Trigonométrie : 1/cos 30° = 1,155 ; 1/cos 35° = 1,221 ; 1,41 à 45°. "&"Vérifié le "&TEXT(DAY(Référentiel!$C$109),"00")&"/"&TEXT(MONTH(Référentiel!$C$109),"00")&"/"&YEAR(Référentiel!$C$109) -> Trigonométrie : 1/cos 30° = 1,155 ; 1/cos 35° = 1,221 ; 1,41 à 45°. Vérifié le 05/09/2026
B46: Coût TTC au m² : au-dessus, on ne rafraîchit plus, on rénove | C46: ="Hellowatt 2026 : léger 250 à 750, moyen 750 à 1 500, lourd 2 000 à 4 000 €/m² TTC ; Illico Travaux 2026 : complet 1 000 à 1 800, lourd 1 500 et plus. "&"Vérifié le "&TEXT(DAY(Référentiel!$C$109),"00")&"/"&TEXT(MONTH(Référentiel!$C$109),"00")&"/"&YEAR(Référentiel!$C$109) -> Hellowatt 2026 : léger 250 à 750, moyen 750 à 1 500, lourd 2 000 à 4 000 €/m² TTC ; Illico Travaux 2026 : complet 1 000 à 1 800, lourd 1 500 et plus. Vérifié le 05/09/2026
B47: Coût TTC au m² : au-dessus, rénovation lourde ou restructuration | C47: ="Mêmes sources. Le 1 500 €/m² est un plancher de rénovation lourde, pas un centre. "&"Vérifié le "&TEXT(DAY(Référentiel!$C$109),"00")&"/"&TEXT(MONTH(Référentiel!$C$109),"00")&"/"&YEAR(Référentiel!$C$109) -> Mêmes sources. Le 1 500 €/m² est un plancher de rénovation lourde, pas un centre. Vérifié le 05/09/2026
B48: Attestation remplacée par la mention sur devis | C48: ="LF 2025 (loi n° 2025-127 du 14/02/2025), art. 41 ; BOFiP ACTU-2025-00165 du 22/10/2025 ; Service-public Entreprendre F23568, mis à jour le 21/02/2026. "&"Vérifié le "&TEXT(DAY(Référentiel!$C$109),"00")&"/"&TEXT(MONTH(Référentiel!$C$109),"00")&"/"&YEAR(Référentiel!$C$109) -> LF 2025 (loi n° 2025-127 du 14/02/2025), art. 41 ; BOFiP ACTU-2025-00165 du 22/10/2025 ; Service-public Entreprendre F23568, mis à jour le 21/02/2026. Vérifié le 05/09/2026
B49: Chaudières fossiles au taux normal | C49: ="LF 2025, art. 32 (depuis le 01/03/2025) ; BOFiP ACTU-2025-00165 ; Quelle Énergie, TVA chaudière gaz 2026 ; Service-public F23568. "&"Vérifié le "&TEXT(DAY(Référentiel!$C$109),"00")&"/"&TEXT(MONTH(Référentiel!$C$109),"00")&"/"&YEAR(Référentiel!$C$109) -> LF 2025, art. 32 (depuis le 01/03/2025) ; BOFiP ACTU-2025-00165 ; Quelle Énergie, TVA chaudière gaz 2026 ; Service-public F23568. Vérifié le 05/09/2026
B50: Liste des équipements éligibles au 5,5 % | C50: ="Arrêté du 24/12/2024 (JO) ; arrêté du 13/07/2026 (JO du 17/07/2026) pour les PAC air/air ; FFB, dossier TVA rénovation énergétique du 25/08/2026 ; CAPEB, TVA au taux de 5,5 % ; Effy, TVA pompe à chale"&"ur 2026. "&"Vérifié le "&TEXT(DAY(Référentiel!$C$109),"00")&"/"&TEXT(MONTH(Référentiel!$C$109),"00")&"/"&YEAR(Référentiel!$C$109) -> Arrêté du 24/12/2024 (JO) ; arrêté du 13/07/2026 (JO du 17/07/2026) pour les PAC air/air ; FFB, dossier TVA rénovation énergétique du 25/08/2026 ; CAPEB, TVA au taux de 5,5 % ; Effy, TVA pompe à chaleur 2026. Vérifié le 05/09/2026
B51: Immeuble rendu neuf | C51: ="CGI art. 257, I-2-2° ; CGI annexe II art. 245 A ; BOI-TVA-IMM-10-10-10-20 § 140 et suivants ; CMS Francis Lefebvre, « Travaux immobiliers, TVA et production d'un immeuble neuf » ; Fintae, second œuvre"&" et marchand de biens. "&"Vérifié le "&TEXT(DAY(Référentiel!$C$109),"00")&"/"&TEXT(MONTH(Référentiel!$C$109),"00")&"/"&YEAR(Référentiel!$C$109) -> CGI art. 257, I-2-2° ; CGI annexe II art. 245 A ; BOI-TVA-IMM-10-10-10-20 § 140 et suivants ; CMS Francis Lefebvre, « Travaux immobiliers, TVA et production d'un immeuble neuf » ; Fintae, second œuvre et marchand de biens. Vérifié le 05/09/2026
B52: Bandes usuelles par famille | C52: ="Convention CorpusImmo, non sourcée : à caler sur vos propres chantiers. Elle décrit une rénovation lourde de logement ancien. "&"Vérifié le "&TEXT(DAY(Référentiel!$C$109),"00")&"/"&TEXT(MONTH(Référentiel!$C$109),"00")&"/"&YEAR(Référentiel!$C$109) -> Convention CorpusImmo, non sourcée : à caler sur vos propres chantiers. Elle décrit une rénovation lourde de logement ancien. Vérifié le 05/09/2026
B53: Fourchettes de prix | C53: ="Hellowatt, prix de la rénovation au m² 2026 ; Illico Travaux, guide des prix 2026 ; Educ Spe, prix rénovation 2026 ; Monsieur Peinture, grille 2026 ; Travaux.com, prix de pose de la peinture 2026. Dét"&"ail ligne à ligne dans le Référentiel. "&"Vérifié le "&TEXT(DAY(Référentiel!$C$109),"00")&"/"&TEXT(MONTH(Référentiel!$C$109),"00")&"/"&YEAR(Référentiel!$C$109) -> Hellowatt, prix de la rénovation au m² 2026 ; Illico Travaux, guide des prix 2026 ; Educ Spe, prix rénovation 2026 ; Monsieur Peinture, grille 2026 ; Travaux.com, prix de pose de la peinture 2026. Détail ligne à ligne dans le Référentiel. Vérifié le 05/09/2026
B54: Aléas et honoraires | C54: ="maitre-doeuvre.fr, imprévus de chantier ; architecte-batiments.fr ; Ootravaux, tarifs architecte 2026 ; Meta Architecte, barème 2026. "&"Vérifié le "&TEXT(DAY(Référentiel!$C$109),"00")&"/"&TEXT(MONTH(Référentiel!$C$109),"00")&"/"&YEAR(Référentiel!$C$109) -> maitre-doeuvre.fr, imprévus de chantier ; architecte-batiments.fr ; Ootravaux, tarifs architecte 2026 ; Meta Architecte, barème 2026. Vérifié le 05/09/2026
B55: Surcoût Île-de-France et Paris | C55: ="Observatoire ARTEP (monimmeuble.com) ; Erema Bat, rénovation d'appartement à Paris 2026 ; AZ Bâtiments 2026. "&"Vérifié le "&TEXT(DAY(Référentiel!$C$109),"00")&"/"&TEXT(MONTH(Référentiel!$C$109),"00")&"/"&YEAR(Référentiel!$C$109) -> Observatoire ARTEP (monimmeuble.com) ; Erema Bat, rénovation d'appartement à Paris 2026 ; AZ Bâtiments 2026. Vérifié le 05/09/2026
B57: CorpusImmo, millésime 2026. Modèle d'aide à la décision : ne constitue ni un conseil en investissement, ni un conseil fiscal, ni une expertise au sens de la charte de l'expertise en évaluation immobilière. Vérifiez les paramètres avant tout engagement.
