Workbook

Sheet Mode d'emploi
B1: CorpusImmo · www.corpus.immo · Estimer, comparer, décider. Sur les ventes réelles.
B2: Mode d'emploi
B3: À quoi sert ce classeur, dans quel ordre le remplir, et comment lire ce qu'il répond.
B6: À QUOI SERT CE CLASSEUR
B7: Un vendeur vous demande ce qu'il touchera. Entre le prix de l'annonce et le virement du notaire, il y a les honoraires d'agence, le solde du prêt et son indemnité, les diagnostics et les frais de mainlevée, et surtout l'impôt de plus-value. Ce classeur fait la soustraction complète, avec le vrai barème fiscal, et vous donne le net en poche.
B8: Il calcule l'impôt de plus-value avec la méthode et les barèmes que le notaire appliquera : durée de détention comptée de date à date, abattements par paliers légaux, deux barèmes différents pour l'impôt sur le revenu et pour les prélèvements sociaux, taxe supplémentaire sur les plus-values élevées, et les exonérations les plus courantes. Chaque barème vit dans l'onglet Paramètres, avec sa source et sa date. Le calcul du notaire reste le seul qui fasse foi : c'est lui qui vérifiera les conditions de fond des exonérations et les pièces de l'acte.
B9: Un second onglet, indépendant du premier, vous aide à décider si le mandat vaut la peine d'être pris : huit critères notés pendant le rendez-vous, un critère de prix éliminatoire, un score et un verdict.
B10: Vous êtes | C10: Ce que le classeur vous donne
B11: Agent immobilier | C11: L'ordre de grandeur du net en poche à annoncer au vendeur, avec la réserve du notaire, et une grille pour décider si le mandat vaut vos six prochains mois.
B12: Vendeur particulier | C12: Ce qui reste réellement après honoraires, remboursement du prêt, frais et impôt, avant de fixer votre prix.
B13: Notaire, clerc | C13: Le détail du calcul de plus-value : prix d'acquisition majoré, durée de date à date, abattements par paliers, surtaxe, exonération retenue.
B14: Conseiller en gestion de patrimoine | C14: L'effet de la durée de détention sur l'impôt, pour arbitrer entre vendre maintenant et attendre une date anniversaire.
B15: Ce que vous pouvez dire au vendeur : arrondissez au millier et annoncez une fourchette. « D'après mon calcul, vous devriez toucher de l'ordre de 206 000 €, à confirmer par votre notaire, qui refera le calcul de plus-value sur pièces. » Ce que vous ne devez pas dire : un chiffre au centime, ni « vous toucherez ». Trois choses peuvent encore bouger après vous : une exonération que le notaire refusera parce qu'une condition de fond manque, un décompte de banque différent de celui que vous avez saisi, et la date d'acte réelle, qui décale la durée de détention.
B16: Cinq mots à poser avant de commencer. Plus-value brute : ce que le bien a pris entre l'achat et la vente, une fois les frais et les travaux ajoutés au prix d'achat. Abattement : une réduction de cette plus-value, qui grandit avec la durée de détention. Paliers : l'abattement ne grandit pas jour par jour mais par marches d'une année entière, ce qui fait que quinze jours de patience valent parfois plusieurs centaines d'euros. Impôt sur le revenu et prélèvements sociaux : deux impôts distincts sur la même plus-value, à 19 % et 17,2 % (millésime 2026), avec deux abattements de cadence différente. Les prélèvements sociaux finissent presque toujours plus lourds que l'impôt sur le revenu, et durent 8 ans de plus. Surtaxe : une taxe en plus, de 2 % à 6 %, qui ne tombe qu'au-delà de 50 000 € de plus-value imposable à l'impôt sur le revenu (millésime 2026), et jamais sur un terrain à bâtir.
B18: LE PRINCIPE, EN UNE LIGNE
B19: Prix affiché − honoraires d'agence = prix net vendeur, puis prix net vendeur − solde du prêt et indemnité − frais de vente − impôt de plus-value = ce que le vendeur touche
B21: LES ONGLETS, DANS L'ORDRE OÙ ON LES REMPLIT
B22: Onglet | C22: Ce que vous y faites | D22: Ce que vous y lisez
B23: Mode d'emploi | C23: Rien à saisir. Vous lisez ce guide. | D23: La marche à suivre et l'exemple guidé.
B24: Net vendeur | C24: Vous remplissez les quatre blocs violets, de haut en bas : la vente, le prêt et les frais, le bien et son acquisition, les exonérations. | D24: Quatre contrôles de bloc (Net vendeur!C12, Net vendeur!C21, Net vendeur!C34, Net vendeur!C42) et le contrôle général (Net vendeur!C65), puis la plus-value, l'impôt et le net en poche (Net vendeur!C62).
B25: Qualifier le mandat | C25: Vous notez huit critères de 0 à 5 pendant le rendez-vous, et vous saisissez l'écart entre le prix espéré et votre estimation. | D25: Le score (Qualifier le mandat!C23) et le verdict (Qualifier le mandat!C24), avec les deux seuils de décision juste en dessous.
B26: Paramètres | C26: Rien, sauf à la mise à jour annuelle des barèmes et des repères. | D26: Chaque valeur avec sa source datée, la table des abattements par durée, le barème de la surtaxe, la liste des exonérations testées, les listes déroulantes.
B27: Méthode | C27: Rien à saisir. | D27: Les conventions de calcul, ce que le modèle ne fait pas, les points tranchés dans le sens prudent, les sources.
B29: LE CODE COULEUR, ET COMMENT DÉVERROUILLER UNE CELLULE
B30: Cellule | C30: Ce que c'est | D30: Ce que vous faites
B31: Fond violet clair | C31: Saisie utilisateur | D31: Vous la remplissez. Jamais de formule dedans.
B32: Fond blanc | C32: Calcul | D32: Vous la lisez. Elle est verrouillée.
B33: Fond violet très pâle, gras | C33: Résultat de bloc ou chiffre clé | D33: Le chiffre à retenir.
B34: Texte gris à droite | C34: Aide de saisie | D34: Une phrase par ligne, avec l'ordre de grandeur attendu.
B35: Pastille verte ou rouge | C35: Contrôle de cohérence | D35: Rouge : corrigez avant de lire le moindre chiffre.
B36: Feuille protégée | C36: Protection sans mot de passe | D36: Onglet Révision, puis Ôter la protection de la feuille. Aucun mot de passe n'est demandé. Reprotégez ensuite, la protection évite d'écraser une formule.
B38: LA MARCHE À SUIVRE, ÉTAPE PAR ÉTAPE
B39: Étape | C39: Où | D39: Ce que vous faites | E39: Pourquoi
B40: Étape 0 : que faire de l'exemple | C40: Net vendeur et Qualifier le mandat | D40: Le classeur est livré rempli d'un cas complet. Gardez-le le temps de vous repérer, puis effacez les cellules violettes de chiffres et de dates de l'onglet Net vendeur, ainsi que les notes de Qualifier le mandat!C8:C15 et l'écart de prix de Qualifier le mandat!C18, avant de saisir votre dossier. Ne touchez ni aux poids de Qualifier le mandat!D8:D15, qui sont votre grille et pas votre dossier, ni aux cellules violettes de l'onglet Paramètres, qui sont vos barèmes. N'effacez jamais les cellules d'option, celles qui se choisissent dans une liste : une option vide fait passer le contrôle au rouge et vide tout le calcul. Remplacez-les, ne les videz pas. | E40: Une saisie oubliée de l'exemple est l'erreur la plus probable d'un premier usage. Regardez surtout les travaux, les frais réels et l'indemnité de remboursement anticipé, qui n'ont aucune raison d'exister dans votre dossier. Les plages indiquées ci-dessous sautent les cellules calculées : suivez-les telles quelles plutôt que de sélectionner une colonne entière, la feuille est protégée et refusera d'effacer une formule.
B41: 1. La vente | C41: Net vendeur!C7:C9 | D41: Prix affiché dans l'annonce, taux d'honoraires toutes taxes comprises, et qui les paie, exactement comme dans le mandat. | E41: La charge des honoraires change la base du taux, donc le prix net vendeur, donc la plus-value. C'est le premier poste où l'on se trompe.
B42: 2. Le prêt et les frais | C42: Net vendeur!C15, C16, puis C18:C20 | D42: Capital restant dû, taux du prêt, indemnité réclamée par la banque, diagnostics, mainlevée et état daté. Laissez vide ce qui n'existe pas. La cellule entre les deux, Net vendeur!C17, est calculée : c'est le plafond légal, vous ne la remplissez pas. | E42: Le classeur calcule le plafond légal de l'indemnité (Net vendeur!C17) et passe au rouge si la banque vous en réclame davantage.
B43: 3. Le bien et son acquisition | C43: Net vendeur!C24:C28, puis C30:C33 | D43: Nature du bien, mode d'acquisition, prix payé ou valeur retenue pour les droits, les deux dates d'acte, puis vos deux options : frais au forfait ou au réel, travaux au forfait, au réel ou aucun. La cellule Net vendeur!C29, entre les dates et les options, est calculée : c'est la durée de détention que le classeur déduit de vos deux dates. | E43: Ce sont les dates qui fixent l'abattement, et les options qui fixent le prix d'acquisition majoré. Un bien reçu par succession ou par donation n'a pas droit au forfait de frais.
B44: 4. Les cas particuliers et les exonérations | C44: Net vendeur!C37, puis C39:C41 | D44: Déclarez d'abord si le cas sort du périmètre du modèle, puis répondez aux trois questions d'exonération. Répondez Non si vous n'êtes pas certain des conditions. Le cas particulier se choisit en Net vendeur!C37. Quatre situations sortent du modèle et l'arrêtent net : « Démembrement de propriété », c'est-à-dire une vente en nue-propriété ou d'un usufruit seul, y compris après une succession où le conjoint garde l'usufruit ; « Bien détenu par une société », SCI familiale comprise ; « Bien situé à l'étranger » ; « Cession de parts de société », quand on vous propose de vendre les parts de la société plutôt que le bien. Dans ces quatre cas, le classeur affiche un avertissement en Net vendeur!C38 et refuse de chiffrer : la fiscalité y est différente, et le calcul se fait avec le notaire. Cette cellule Net vendeur!C38 est calculée, vous ne la remplissez pas. Les trois questions sont la résidence principale, la première cession d'un logement autre que la résidence principale, et la vente à un organisme de logement social. Trois autres exonérations se déclenchent toutes seules, sans question : le prix sous le seuil des petites cessions, 22 ans de détention pour l'impôt sur le revenu, 30 ans pour les prélèvements sociaux. Leurs conditions sont détaillées plus bas, dans la section « Les exonérations, et ce qu'elles exigent vraiment ». | E44: Le vendeur ne vous dira pas spontanément que le bien est dans une SCI ou qu'il ne vend que la nue-propriété. Posez la question au rendez-vous : c'est la première chose qui fait sortir le dossier du modèle. Une exonération à tort, elle, produit un net en poche trop élevé de tout l'impôt : 10 525 € sur l'exemple livré (millésime 2026). Le classeur ne vérifie aucune condition de fond, il applique votre réponse. Le notaire, lui, la vérifiera, et c'est vous qui aurez annoncé le chiffre au vendeur.
B45: 5. Lisez le résultat | C45: Net vendeur!C48:C64 | D45: Vérifiez d'abord que le contrôle général Net vendeur!C65 est vert, puis lisez l'exonération retenue (Net vendeur!C51), l'impôt total (Net vendeur!C59) et le net en poche (Net vendeur!C62). | E45: Tant qu'un contrôle est rouge, ces cellules restent vides. C'est voulu : un impôt calculé sur une saisie fausse ne se voit pas. Une exception : si vous avez déclaré un cas hors périmètre en Net vendeur!C37, le rouge n'est pas une erreur à corriger, c'est le modèle qui refuse de chiffrer. Le message de Net vendeur!C38 vous le dit en toutes lettres. Ne repassez pas sur « Aucun » pour faire revenir les chiffres : ils seraient faux.
B46: 6. Qualifiez le mandat | C46: Qualifier le mandat!C8:C15 et D8:D15, puis Qualifier le mandat!C18 | D46: Notez les huit critères de 0 à 5 en colonne C pendant le rendez-vous. La colonne D porte le poids de chaque critère, de 0 à 5 : elle est livrée réglée et ne se retouche qu'une fois, pas à chaque mandat. Saisissez enfin l'écart entre le prix espéré du vendeur et votre estimation. | E46: Les poids se règlent une fois pour toutes, pas à chaque mandat. L'écart de prix, lui, se ressaisit à chaque fois : au-delà du seuil de Paramètres!C85, le verdict devient éliminatoire. La note maximale et le poids maximal se règlent en Paramètres!C83 et Paramètres!C84.
B48: EXEMPLE GUIDÉ : LE CAS LIVRÉ DANS LE CLASSEUR
B49: Un appartement acheté 268 000 € le 20/09/2013, affiché 385 000 € honoraires inclus, avec 4,50 % d'honoraires à la charge de l'acquéreur, vendu le 04/09/2026. Il reste 148 000 € de prêt, la banque réclame 2 200 € d'indemnité, les diagnostics coûtent 750 € et la mainlevée 700 €.
B50: Les honoraires ressortent à 16 578,95 € : le prix affiché divisé par un plus le taux, pas le prix multiplié par le taux. Le prix net vendeur est donc de 368 421,05 €, et c'est lui qui sert de base à la plus-value.
B51: Entre le 20/09/2013 et le 04/09/2026, il s'est écoulé 12 années révolues, et non 13 : la vente a lieu seize jours avant la date anniversaire, et la treizième année n'est pas acquise. Vendre le 20/09/2026 au lieu du 04/09/2026 ferait tomber l'impôt de 10 525 € à 9 954 €, soit 571 € de moins pour seize jours de patience.
B52: Le prix d'acquisition majoré vaut 328 300 € : 268 000 € de prix, plus 20 100 € de frais au forfait, plus 40 200 € de travaux au forfait, acquis parce que le bien est bâti et détenu depuis plus de cinq ans. La plus-value brute est de 40 121 €.
B53: À 12 ans, l'abattement est de 42,00 % pour l'impôt sur le revenu et de 11,55 % seulement pour les prélèvements sociaux : deux barèmes, deux cadences. La plus-value imposable est donc de 23 270 € d'un côté et de 35 487 € de l'autre, ce qui donne 4 421,34 € d'impôt sur le revenu et 6 103,78 € de prélèvements sociaux. La surtaxe est nulle : la plus-value imposable à l'impôt sur le revenu reste sous le premier seuil du barème (50 000 €). Retenez les deux dates qui comptent : à 22 ans de détention il n'y a plus d'impôt sur le revenu, mais les prélèvements sociaux restent dus ; ils ne disparaissent qu'à 30 ans.
B54: Impôt total : 10 525,12 €. Net en poche : 206 245,94 €, parce que le vendeur rend aussi 148 000 € à sa banque : ce n'est pas un coût de la vente, c'est sa dette qui s'éteint. Rapportés à ce qu'il faut mesurer, les deux vrais coûts sont l'agence, qui lui laisse 95,69 % du prix affiché, et l'impôt, qui lui laisse 97,14 % de son net vendeur. Ce que vous annoncez en rendez-vous sur ce dossier : « de l'ordre de 206 000 €, à confirmer par votre notaire ». Pas 206 245,94 €. Le classeur affiche les centimes parce qu'il calcule sans arrondi intermédiaire, pas parce que le chiffre est certain à ce niveau.
B55: Sur l'onglet de qualification, le même dossier obtient 57 points sur 90, soit un score de 63,33 %, avec un écart de prix de 8 %. Le verdict tombe : « Prenez-le, mais négociez le prix avant de signer ». Chiffres du millésime 2026.
B57: LES EXONÉRATIONS, ET CE QU'ELLES EXIGENT VRAIMENT
B58: Le classeur teste six situations, dans l'ordre de ce tableau. Trois se déclenchent par une réponse Oui à l'étape 4, trois se calculent toutes seules. Le motif retenu s'affiche toujours en toutes lettres en Net vendeur!C51 : un impôt nul sans motif écrit est une erreur de saisie, jamais un résultat.
B59: Le classeur ne vérifie aucune condition de fond. Il signale qu'une exonération paraît applicable au vu de ce que vous lui avez répondu. C'est le notaire qui la confirmera, sur pièces : ne l'annoncez jamais comme acquise.
B60: Exonération | C60: Ce qui la déclenche | D60: Son effet | E60: La condition qui se rate
B61: Résidence principale | C61: Votre réponse Oui en Net vendeur!C39. | D61: Exonération totale : l'impôt de plus-value tombe à zéro. | E61: Le logement doit être l'habitation habituelle du vendeur au jour de la vente, ou venir d'être libéré pour être vendu. Une maison vide depuis deux ans n'y a plus droit. C'est la case sur laquelle on répond Oui par habitude, et c'est tout l'impôt qui disparaît à tort.
B62: Vente à un organisme de logement social | C62: Votre réponse Oui en Net vendeur!C41. | D62: Exonération totale. | E62: L'acquéreur doit être un bailleur social, un organisme de foncier solidaire, ou une collectivité qui rétrocède à un bailleur social. Le dispositif court jusqu'au 31/12/2027.
B63: Première cession d'un logement autre que la résidence principale | C63: Votre réponse Oui en Net vendeur!C40. | D63: Exonération totale. | E63: Trois conditions ensemble, pas une seule : ne pas avoir été propriétaire de sa résidence principale au cours des quatre années précédentes, remployer le prix dans l'achat ou la construction de sa résidence principale dans les vingt-quatre mois, et n'avoir jamais utilisé cette exonération. Le nom trompe : ce n'est pas « la première fois que je vends un bien locatif ».
B64: Petites cessions | C64: Automatique, sans question : le classeur compare le prix affiché au seuil de Paramètres!C13, soit 15 000 € (millésime 2026). | D64: Exonération totale. | E64: Le seuil s'apprécie bien par bien et par vendeur. Le classeur le compare au prix affiché, ce qui est l'hypothèse la moins favorable au vendeur.
B65: 30 ans de détention | C65: Automatique : les deux abattements de la table de Paramètres atteignent 100 %. | D65: Exonération totale. | E65: 30 ans révolus de date à date, pas 30 années civiles. La durée se lit en Net vendeur!C29.
B66: 22 ans de détention | C66: Automatique. | D66: Exonération partielle : plus d'impôt sur le revenu, mais les prélèvements sociaux restent dus jusqu'à 30 ans. | E66: C'est le décalage qui surprend tous les vendeurs : à 25 ans de détention, il n'y a plus d'impôt sur le revenu du tout, et il reste encore 45 % de la plus-value soumise aux prélèvements sociaux (millésime 2026).
B68: LES CHIFFRES À REGARDER, ET CE QU'ILS VALENT
B69: Indicateur | C69: Où | D69: Repère métier | E69: Ce qu'il dit vraiment
B70: Prix net vendeur | C70: Net vendeur!C11 | D70: 368 421 € sur l'exemple (2026) | E70: La base de la plus-value, et le chiffre que le vendeur compare à son estimation. Ce n'est pas ce qu'il touchera.
B71: Durée de détention | C71: Net vendeur!C29 | D71: 12 années révolues (2026) | E71: Comptée de date à date, en années entières. Chaque année franchie au-delà de 5 ans ajoute 6 points d'abattement à l'impôt sur le revenu, jusqu'à l'exonération à 22 ans, la dernière année n'en valant que 4 points. Aux prélèvements sociaux, la même année ne vaut que 1,65 point, et ils ne s'effacent qu'à 30 ans (barème 2026). C'est ce décalage de 8 ans qui surprend tous les vendeurs.
B72: Plus-value brute | C72: Net vendeur!C48 | D72: 40 121 € sur l'exemple (2026) | E72: Une plus-value brute élevée n'est pas un impôt élevé : tout dépend de la durée. Une moins-value vaut zéro, elle ne s'impute nulle part.
B73: Exonération applicable | C73: Net vendeur!C51 | D73: Toujours écrite, même quand il n'y en a pas | E73: Un impôt nul doit avoir un motif affiché. 7 textes sont possibles : les 6 exonérations de la section ci-dessus, ou « Aucune exonération : la plus-value est imposable ». Un impôt nul sans motif, c'est une erreur de saisie.
B74: Impôt total de plus-value | C74: Net vendeur!C59 | D74: 10 525 € sur l'exemple (2026) | E74: L'ordre de grandeur de ce que le notaire retiendra sur le prix le jour de la signature, surtaxe comprise. Le montant définitif est celui que le notaire calculera sur pièces : annoncez-le arrondi au millier, jamais au centime.
B75: Net en poche | C75: Net vendeur!C62 | D75: 206 246 € sur l'exemple (2026) | E75: Le virement attendu. Il ne comprend ni la régularisation du prorata de taxe foncière, qui joue en votre faveur, ni les frais de déménagement.
B76: Score du mandat | C76: Qualifier le mandat!C23 | D76: Solide au-dessus de 75 %, à refuser sous 40 % (repères 2026) | E76: Une aide à la décision commerciale, pas une évaluation du bien.
B77: Une lecture à ne pas confondre : Net vendeur!C63 mesure le coût de l'agence, et rien d'autre ; Net vendeur!C64, juste en dessous, mesure le coût fiscal. Le remboursement du prêt n'est ni l'un ni l'autre : c'est une dette qui s'éteint, et il n'entre dans aucun des deux ratios.
B79: LES DONNÉES À METTRE À JOUR, OÙ ET POURQUOI
B80: Les barèmes fiscaux changent chaque année ou presque, les données de dossier changent à chaque vente. Les deux ne vivent pas au même endroit, et c'est ce qui permet de ne jamais toucher aux formules.
B81: Paramètre | C81: Onglet et cellule | D81: Ce qu'il pilote | E81: Source à consulter, et à quelle fréquence
B82: Barèmes fiscaux (taux, forfaits, seuils) | C82: Paramètres!C8:C15 | D82: Tout le calcul de l'impôt de plus-value (Paramètres!C8:C13), et le plafond légal de l'indemnité de remboursement anticipé (Paramètres!C14:C15, code de la consommation). | E82: BOFiP et Legifrance. Colonne Source de l'onglet Paramètres. Fréquence : chaque janvier, après la loi de finances.
B83: Abattements par durée de détention | C83: Paramètres!B19:D49 | D83: Les deux abattements lus par les formules, année par année. | E83: CGI art. 150 VC et BOI-RFPI-PVI-20-20. Aucune formule ne recalcule un palier. Fréquence : chaque janvier.
B84: Barème de la surtaxe | C84: Paramètres!B53:E62 | D84: La taxe sur les plus-values élevées, tranche par tranche. | E84: CGI art. 1609 nonies G et BOI-RFPI-TPVIE-20. Fréquence : chaque janvier.
B85: Repères de marché et garde-fous des contrôles | C85: Paramètres!C76:C87 | D85: Les ordres de grandeur affichés en aide de saisie, honoraires, diagnostics et mainlevée (Paramètres!C76:C81), et les garde-fous des contrôles : plancher de plausibilité d'un taux, note et poids maximaux de la grille, écart de prix éliminatoire, bornes de dates admises (Paramètres!C82:C87). | E85: Barèmes d'agences et devis de diagnostiqueurs. Fréquence : une fois par an.
B86: Seuils et verdicts du mandat | C86: Paramètres!C85, puis Paramètres!B91:C95 | D86: L'écart de prix éliminatoire, puis les cinq verdicts de la grille de qualification et leurs seuils. | E86: Vos douze derniers mandats. Ce ne sont pas des normes, ce sont vos repères. Fréquence : une fois par an.
B87: Données de dossier | C87: Net vendeur!C7:C9, C15:C16, C18:C20, C24:C28, C30:C33, C37, C39:C41 | D87: Le dossier lui-même : prix, taux, dates, montants, options. Les cellules sautées sont des calculs. | E87: Le mandat, l'acte d'acquisition, le décompte de la banque, les factures. Fréquence : à chaque dossier.
B88: Date de dernière vérification | C88: Paramètres!C105 | D88: Toutes les mentions « Vérifié le » et « Consulté le » de l'onglet Paramètres. | E88: À changer le jour où vous relisez les barèmes. Fréquence : à chaque relecture des barèmes.
B89: L'architecture ne change jamais quand les données changent : seules les cellules violettes de Paramètres bougent, les formules pointent dessus. Les chiffres cités dans ce guide et dans l'onglet Méthode sont du millésime 2026 : relisez-les à chaque mise à jour de Paramètres, en particulier l'exemple guidé et le tableau des repères ci-dessus.
B91: TROIS FAÇONS DE S'EN SERVIR
B92: Votre situation | C92: Ce que vous faites
B93: Un vendeur veut savoir ce qu'il touchera avant de fixer son prix | C93: Remplissez les quatre blocs, lisez le net en poche (Net vendeur!C62) et l'impôt (Net vendeur!C59). Montrez-lui la ligne d'exonération et les deux abattements : c'est là qu'il comprend pourquoi son voisin a payé moins.
B94: Le vendeur hésite entre vendre maintenant et attendre | C94: Changez la seule date de vente (Net vendeur!C28) et regardez l'impôt. Sur l'exemple livré, seize jours de patience font gagner 571 € (repère 2026), parce qu'ils font franchir une date anniversaire.
B95: Vous décidez de prendre ou non un mandat | C95: Notez les huit critères pendant le rendez-vous et saisissez l'écart de prix. Au-delà du seuil de Paramètres!C85, soit 15 % d'écart (repère 2026), le verdict devient éliminatoire quel que soit le reste : c'est le seul critère qui l'emporte sur le score.
B97: LES ERREURS QUI FAUSSENT TOUT
B98: L'erreur | C98: Ce qu'elle coûte (chiffres de l'exemple livré, millésime 2026)
B99: Taper 0,045 au lieu de 4,5 dans le taux d'honoraires (Net vendeur!C8) | C99: La cellule est déjà au format pourcentage : 0,045 y vaut 0,05 %, et les honoraires tomberaient de 16 578,95 € à moins de deux cents euros. Le contrôle de la vente passe au rouge grâce au plancher de plausibilité de Paramètres (Paramètres!C82), et plus rien ne s'affiche tant que le taux n'est pas corrigé.
B100: Se tromper sur la charge des honoraires (Net vendeur!C9) | C100: La base du taux change. Sur l'exemple, passer de la charge acquéreur à la charge vendeur fait passer les honoraires de 16 578,95 € à 17 325,00 € et le net en poche de 206 246 € à 205 696 €. Recopiez le mandat, ne devinez pas.
B101: Saisir des années au lieu de vraies dates (Net vendeur!C27 et Net vendeur!C28) | C101: La validation n'accepte qu'une date, et si une année est collée par-dessus, le contrôle du bloc passe au rouge : 2013 est un vrai numéro de série Excel, qui désigne un jour de 1905 et donnerait 121 ans de détention. Une année entière d'abattement se joue sur quelques jours : 571 € sur l'exemple.
B102: Laisser les travaux de l'exemple (Net vendeur!C33) ou les frais réels (Net vendeur!C31) | C102: Ils ne servent que si l'option correspondante est choisie, mais ils la faussent complètement quand elle l'est. Sur l'exemple, passer du forfait aux travaux réels ferait monter l'impôt de 10 525,12 € à 14 774,93 €, parce que les 24 000 € de factures sont inférieurs au forfait de 40 200 €.
B103: Répondre Oui à la résidence principale par habitude (Net vendeur!C39) | C103: L'impôt tombe à zéro et le net en poche gagne 10 525 € : 216 771 € au lieu de 206 246 €. Le logement doit être l'habitation habituelle au jour de la vente, ou libéré depuis un délai normal de vente. Le notaire, lui, vérifiera.
B104: Demander le forfait travaux sur un bien détenu depuis moins de cinq ans (Net vendeur!C32) | C104: Le contrôle du bloc passe au rouge au lieu de retenir zéro en silence. Choisissez « Aucun travaux » ou les travaux réels : c'est la condition de durée qui manque, pas la saisie.
B105: Oublier l'indemnité de remboursement anticipé ou en accepter une trop élevée (Net vendeur!C18) | C105: Le plafond légal est calculé juste au-dessus (Net vendeur!C17) : sur l'exemple, il vaut 2 368,00 € pour une indemnité réclamée de 2 200 €. Au-delà du plafond, le contrôle passe au rouge et l'indemnité se conteste.
B107: Ce que le classeur ne fait pas, les points tranchés dans le sens prudent et les sources de ses chiffres : voir l'onglet Méthode.
B109: CorpusImmo, millésime 2026. Modèle d'aide à la décision : ne constitue ni un conseil en investissement, ni un conseil fiscal, ni une expertise au sens de la charte de l'expertise en évaluation immobilière. Vérifiez les paramètres avant tout engagement.

Sheet Net vendeur
B1: CorpusImmo · www.corpus.immo · Estimer, comparer, décider. Sur les ventes réelles.
B2: Ce que le vendeur touche vraiment
B3: Du prix affiché au virement du notaire : honoraires, solde de prêt, impôt de plus-value et net en poche.
B5: Cellules violettes : à remplir. Cellules blanches : calculées automatiquement.
B6: LA VENTE
B7: Prix affiché dans l'annonce | C7: 385000 | D7: Le prix que voit l'acquéreur. Honoraires inclus quand ils sont à sa charge, honoraires exclus quand ils sont à la charge du vendeur.
B8: Taux d'honoraires d'agence TTC | C8: 0.045 | D8: ="Barème libre. Repère : "&ROUND(Paramètres!$C$76*100,1)&" %"&" à "&ROUND(Paramètres!$C$77*100,1)&" %"&" du prix (Paramètres, repères). Tapez 4,5 pour 4,5 % : la cellule est déjà au format pourcentage." -> Barème libre. Repère : 3 % à 7 % du prix (Paramètres, repères). Tapez 4,5 pour 4,5 % : la cellule est déjà au format pourcentage.
B9: Honoraires à la charge de | C9: Acquéreur | D9: Exactement comme dans le mandat. À la charge de l'acquéreur, le taux porte sur le prix hors honoraires. À la charge du vendeur, il porte sur le prix de vente.
B10: Honoraires d'agence TTC | C10: =IF('Net vendeur'!$C$12<>"OK","",IF('Net vendeur'!$C$9=Paramètres!$B$99,'Net vendeur'!$C$7-'Net vendeur'!$C$7/(1+'Net vendeur'!$C$8),'Net vendeur'!$C$7*'Net vendeur'!$C$8)) -> 16578.947 | D10: Charge acquéreur : prix affiché moins prix affiché divisé par un plus le taux. Charge vendeur : prix affiché multiplié par le taux.
B11: Prix net vendeur | C11: =IF('Net vendeur'!$C$12<>"OK","",'Net vendeur'!$C$7-'Net vendeur'!$C$10) -> 368421.05 | D11: La base de la plus-value, et le chiffre que le vendeur compare à son estimation.
B12: La vente : saisies cohérentes | C12: =IF(AND(AND(ISNUMBER('Net vendeur'!$C$7),'Net vendeur'!$C$7>=0),'Net vendeur'!$C$7>0,AND(ISNUMBER('Net vendeur'!$C$8),'Net vendeur'!$C$8>=0,'Net vendeur'!$C$8<=0.15),NOT(ISNA(MATCH('Net vendeur'!$C$9,Paramètres!$B$99:$B$100,0))),ISNUMBER(Paramètres!$C$82),AND(ISNUMBER(Paramètres!$C$82),OR(NOT(ISNUMBER('Net vendeur'!$C$8)),'Net vendeur'!$C$8<=0,'Net vendeur'!$C$8>=Paramètres!$C$82))),"OK","À CORRIGER") -> OK | D12: Rouge si le prix manque, est négatif ou nul, si le taux d'honoraires sort de la plage admise ou trahit une saisie en fraction, ou si la charge n'est pas une valeur de la liste.
B14: LE PRÊT EN COURS ET LES FRAIS DE LA VENTE
B15: Capital restant dû du prêt | C15: 148000 | D15: Montant que la banque vous réclamera le jour de la vente. Laissez vide ou 0 s'il n'y a plus de prêt.
B16: Taux nominal du prêt en cours | C16: 0.032 | D16: Sert au plafond légal de l'indemnité ci-dessous. Vide si vous ne le connaissez pas : seul le plafond en pourcentage du capital sera contrôlé.
B17: Plafond légal de l'indemnité de remboursement anticipé | C17: =IF(OR(NOT(OR('Net vendeur'!$C$15="",AND(ISNUMBER('Net vendeur'!$C$15),'Net vendeur'!$C$15>=0))),NOT(ISNUMBER(Paramètres!$C$14)),NOT(ISNUMBER(Paramètres!$C$15))),"",IF(AND(ISNUMBER('Net vendeur'!$C$16),'Net vendeur'!$C$16>0),MIN('Net vendeur'!$C$15*Paramètres!$C$14,'Net vendeur'!$C$15*'Net vendeur'!$C$16*Paramètres!$C$15/12),'Net vendeur'!$C$15*Paramètres!$C$14)) -> 2368 | D17: Le plus faible des deux plafonds du code de la consommation : un semestre d'intérêts au taux du prêt, et une part du capital restant dû (Paramètres).
B18: Indemnité de remboursement anticipé réclamée | C18: 2200 | D18: Le montant écrit sur le décompte de la banque. Aucune indemnité n'est due en cas de changement de lieu de travail, de décès ou de cessation forcée d'activité.
B19: Dossier de diagnostic technique | C19: 750 | D19: ="Repère : "&IF(Paramètres!$C$78>=1000,INT(Paramètres!$C$78/1000)&" "&TEXT(MOD(Paramètres!$C$78,1000),"000"),TEXT(Paramètres!$C$78,"0"))&" €"&" à "&IF(Paramètres!$C$79>=1000,INT(Paramètres!$C$79/1000)&" "&TEXT(MOD(Paramètres!$C$79,1000),"000"),TEXT(Paramètres!$C$79,"0"))&" €"&" selon le bien et son âge (Paramètres, repères)." -> Repère : 300 € à 800 € selon le bien et son âge (Paramètres, repères).
B20: Mainlevée, état daté et autres frais de vente | C20: 700 | D20: ="Repère : "&IF(Paramètres!$C$80>=1000,INT(Paramètres!$C$80/1000)&" "&TEXT(MOD(Paramètres!$C$80,1000),"000"),TEXT(Paramètres!$C$80,"0"))&" €"&" à "&IF(Paramètres!$C$81>=1000,INT(Paramètres!$C$81/1000)&" "&TEXT(MOD(Paramètres!$C$81,1000),"000"),TEXT(Paramètres!$C$81,"0"))&" €"&" (Paramètres, repères). Mainlevée d'hypothèque ou de privilège, état daté de copropriété." -> Repère : 400 € à 1 200 € (Paramètres, repères). Mainlevée d'hypothèque ou de privilège, état daté de copropriété.
B21: Le prêt et les frais : saisies cohérentes | C21: =IF(AND(OR('Net vendeur'!$C$15="",AND(ISNUMBER('Net vendeur'!$C$15),'Net vendeur'!$C$15>=0)),OR('Net vendeur'!$C$16="",AND(ISNUMBER('Net vendeur'!$C$16),'Net vendeur'!$C$16>=0,'Net vendeur'!$C$16<=0.2)),OR('Net vendeur'!$C$18="",AND(ISNUMBER('Net vendeur'!$C$18),'Net vendeur'!$C$18>=0)),OR('Net vendeur'!$C$19="",AND(ISNUMBER('Net vendeur'!$C$19),'Net vendeur'!$C$19>=0)),OR('Net vendeur'!$C$20="",AND(ISNUMBER('Net vendeur'!$C$20),'Net vendeur'!$C$20>=0)),AND(ISNUMBER(Paramètres!$C$82),OR(NOT(ISNUMBER('Net vendeur'!$C$16)),'Net vendeur'!$C$16<=0,'Net vendeur'!$C$16>=Paramètres!$C$82)),ISNUMBER('Net vendeur'!$C$17),'Net vendeur'!$C$18<='Net vendeur'!$C$17),"OK","À CORRIGER") -> OK | D21: Rouge si une saisie est négative, si le taux du prêt sort de la plage admise ou trahit une saisie en fraction, ou si l'indemnité réclamée dépasse le plafond légal calculé au-dessus.
B23: LE BIEN ET SON ACQUISITION D'ORIGINE
B24: Nature du bien vendu | C24: Logement ou immeuble bâti | D24: Un terrain à bâtir n'ouvre droit ni au forfait travaux, ni à la surtaxe sur les plus-values élevées.
B25: Comment le bien a été acquis | C25: Achat (à titre onéreux) | D25: Achat : le forfait de frais d'acquisition est possible. Succession ou donation : seuls les frais réels comptent, et la durée part de la date du décès ou de l'acte de donation.
B26: Prix d'acquisition, ou valeur retenue pour les droits | C26: 268000 | D26: Achat : le prix payé, hors frais. Succession ou donation : la valeur qui a servi de base aux droits de mutation à titre gratuit.
B27: Date d'acquisition | C27: 41537 | D27: Date de l'acte d'achat, du décès pour une succession, de l'acte pour une donation. Une vraie date, pas une année.
B28: Date de la vente | C28: 46269 | D28: Date prévue de l'acte authentique. C'est elle qui fixe la durée de détention, jour pour jour.
B29: Durée de détention, de date à date | C29: =IF('Net vendeur'!$C$34<>"OK","",YEAR('Net vendeur'!$C$28)-YEAR('Net vendeur'!$C$27)-IF(OR(MONTH('Net vendeur'!$C$28)<MONTH('Net vendeur'!$C$27),AND(MONTH('Net vendeur'!$C$28)=MONTH('Net vendeur'!$C$27),DAY('Net vendeur'!$C$28)<DAY('Net vendeur'!$C$27))),1,0)) -> 12 | D29: Années révolues, comptées par périodes de douze mois depuis la date d'acquisition. Une vente la veille de la date anniversaire perd une année entière d'abattement.
B30: Frais d'acquisition retenus | C30: Forfait de 7,5 % | D30: Le forfait est réservé aux achats. Choisissez les frais réels pour une succession ou une donation, ou si vos frais justifiés sont plus élevés que le forfait.
B31: Frais d'acquisition réels justifiés | C31: 19400 | D31: Droits d'enregistrement, émoluments du notaire, honoraires payés à l'acquisition. Pour un bien reçu : droits de mutation à titre gratuit et frais d'acte.
B32: Travaux retenus | C32: Forfait de 15 % | D32: Le forfait suppose un immeuble bâti détenu depuis plus de cinq ans. Les travaux réels ne comptent que sur factures d'entreprise, jamais les matériaux achetés soi-même.
B33: Travaux réels justifiés | C33: 24000 | D33: Construction, reconstruction, agrandissement, amélioration. L'entretien et les réparations locatives sont exclus.
B34: Le bien et son acquisition : saisies cohérentes | C34: =IF(AND(AND(ISNUMBER('Net vendeur'!$C$26),'Net vendeur'!$C$26>=0),'Net vendeur'!$C$26>0,ISNUMBER('Net vendeur'!$C$27),ISNUMBER('Net vendeur'!$C$28),ISNUMBER(Paramètres!$C$86),ISNUMBER(Paramètres!$C$87),'Net vendeur'!$C$27>=Paramètres!$C$86,'Net vendeur'!$C$27<=Paramètres!$C$87,'Net vendeur'!$C$28>=Paramètres!$C$86,'Net vendeur'!$C$28<=Paramètres!$C$87,'Net vendeur'!$C$28>='Net vendeur'!$C$27,NOT(ISNA(MATCH('Net vendeur'!$C$24,Paramètres!$G$99:$G$100,0))),NOT(ISNA(MATCH('Net vendeur'!$C$25,Paramètres!$D$99:$D$101,0))),NOT(ISNA(MATCH('Net vendeur'!$C$30,Paramètres!$E$99:$E$100,0))),NOT(ISNA(MATCH('Net vendeur'!$C$32,Paramètres!$F$99:$F$101,0))),OR('Net vendeur'!$C$31="",AND(ISNUMBER('Net vendeur'!$C$31),'Net vendeur'!$C$31>=0)),OR('Net vendeur'!$C$33="",AND(ISNUMBER('Net vendeur'!$C$33),'Net vendeur'!$C$33>=0)),OR('Net vendeur'!$C$30<>Paramètres!$E$99,'Net vendeur'!$C$25=Paramètres!$D$99),OR('Net vendeur'!$C$32<>Paramètres!$F$99,IF(AND(ISNUMBER('Net vendeur'!$C$27),ISNUMBER('Net vendeur'!$C$28),ISNUMBER(Paramètres!$C$12)),AND('Net vendeur'!$C$24=Paramètres!$G$99,INT('Net vendeur'!$C$28)>EDATE(INT('Net vendeur'!$C$27),Paramètres!$C$12*12)),FALSE))),"OK","À CORRIGER") -> OK | D34: Rouge si une date manque, sort des bornes de plausibilité de Paramètres ou n'est pas une vraie date, si la vente précède l'achat, si le prix d'acquisition manque, si une option n'est pas une valeur de sa liste, si le forfait de frais est demandé sur un bien reçu, ou si le forfait travaux est demandé alors que ses conditions ne sont pas réunies.
B36: LES EXONÉRATIONS ET LES CAS HORS PÉRIMÈTRE
B37: Cas particulier de la cession | C37: Aucun | D37: Choisissez « Aucun » pour une vente ordinaire en pleine propriété par un particulier résident. Les autres cas sortent du périmètre du modèle.
B38: Avertissement | C38: =IF(OR(ISNA(MATCH('Net vendeur'!$C$37,Paramètres!$H$99:$H$103,0)),'Net vendeur'!$C$37=Paramètres!$H$99),"","Cas hors du périmètre de ce modèle : "&'Net vendeur'!$C$37&". Aucun impôt n'est affiché. Voir l'onglet Méthode.")
B39: Le bien est-il votre résidence principale ? | C39: Non | D39: Oui seulement si le logement est votre habitation habituelle au jour de la vente, ou vient d'être libéré pour la vendre.
B40: Première cession d'un logement autre que la résidence principale ? | C40: Non | D40: Oui seulement si vous n'avez pas été propriétaire de votre résidence principale depuis quatre ans, que vous remployez le prix dans les vingt-quatre mois, et que vous n'avez jamais utilisé cette exonération.
B41: Vente à un organisme de logement social ? | C41: Non | D41: Bailleur social, organisme de foncier solidaire, collectivité qui rétrocède à un bailleur social.
B42: Les exonérations : saisies cohérentes | C42: =IF(AND(NOT(ISNA(MATCH('Net vendeur'!$C$37,Paramètres!$H$99:$H$103,0))),NOT(ISNA(MATCH('Net vendeur'!$C$39,Paramètres!$C$99:$C$100,0))),NOT(ISNA(MATCH('Net vendeur'!$C$40,Paramètres!$C$99:$C$100,0))),NOT(ISNA(MATCH('Net vendeur'!$C$41,Paramètres!$C$99:$C$100,0))),'Net vendeur'!$C$37=Paramètres!$H$99,NOT(AND('Net vendeur'!$C$39=Paramètres!$C$99,'Net vendeur'!$C$40=Paramètres!$C$99))),"OK","À CORRIGER") -> OK | D42: Rouge si une réponse n'est pas une valeur de la liste, si le cas sort du périmètre du modèle, ou si la résidence principale et la première cession sont déclarées ensemble, ce qui est contradictoire.
B44: LA PLUS-VALUE IMPOSABLE
B45: Frais d'acquisition retenus | C45: =IF('Net vendeur'!$C$65<>"OK","",IF('Net vendeur'!$C$30=Paramètres!$E$99,'Net vendeur'!$C$26*Paramètres!$C$10,'Net vendeur'!$C$31)) -> 20100 | D45: Forfait sur le prix d'acquisition, ou frais réels justifiés, selon votre choix.
B46: Travaux retenus | C46: =IF('Net vendeur'!$C$65<>"OK","",IF('Net vendeur'!$C$32=Paramètres!$F$99,IF(IF(AND(ISNUMBER('Net vendeur'!$C$27),ISNUMBER('Net vendeur'!$C$28),ISNUMBER(Paramètres!$C$12)),AND('Net vendeur'!$C$24=Paramètres!$G$99,INT('Net vendeur'!$C$28)>EDATE(INT('Net vendeur'!$C$27),Paramètres!$C$12*12)),FALSE),'Net vendeur'!$C$26*Paramètres!$C$11,0),IF('Net vendeur'!$C$32=Paramètres!$F$100,'Net vendeur'!$C$33,0))) -> 40200 | D46: Forfait sur le prix d'acquisition si les conditions de durée et de nature sont réunies, travaux réels justifiés, ou zéro.
B47: Prix d'acquisition majoré | C47: =IF('Net vendeur'!$C$65<>"OK","",'Net vendeur'!$C$26+'Net vendeur'!$C$45+'Net vendeur'!$C$46) -> 328300 | D47: Prix d'acquisition, plus les frais retenus, plus les travaux retenus. C'est ce que l'on retranche du prix net vendeur.
B48: Plus-value brute | C48: =IF('Net vendeur'!$C$65<>"OK","",MAX(0,'Net vendeur'!$C$11-'Net vendeur'!$C$47)) -> 40121.053 | D48: Prix net vendeur moins prix d'acquisition majoré. Une moins-value vaut zéro : elle n'est pas imputable.
B49: Abattement pour durée, impôt sur le revenu | C49: =IF('Net vendeur'!$C$65<>"OK","",INDEX(Paramètres!$C$19:$C$49,MATCH(MIN('Net vendeur'!$C$29,MAX(Paramètres!$B$19:$B$49)),Paramètres!$B$19:$B$49,0))) -> 0.42 | D49: Lu dans la table de Paramètres, par paliers légaux. Nul jusqu'à cinq ans révolus, total à vingt-deux ans.
B50: Abattement pour durée, prélèvements sociaux | C50: =IF('Net vendeur'!$C$65<>"OK","",INDEX(Paramètres!$D$19:$D$49,MATCH(MIN('Net vendeur'!$C$29,MAX(Paramètres!$B$19:$B$49)),Paramètres!$B$19:$B$49,0))) -> 0.1155 | D50: Autre cadence, autre durée : total à trente ans seulement. Ce décalage de huit ans surprend tous les vendeurs.
B51: Exonération applicable | C51: =IF('Net vendeur'!$C$65<>"OK","",IF('Net vendeur'!$C$39=Paramètres!$C$99,Paramètres!$B$66,IF('Net vendeur'!$C$41=Paramètres!$C$99,Paramètres!$B$67,IF('Net vendeur'!$C$40=Paramètres!$C$99,Paramètres!$B$68,IF('Net vendeur'!$C$7<=Paramètres!$C$13,Paramètres!$B$69,IF(AND('Net vendeur'!$C$49>=1,'Net vendeur'!$C$50>=1),Paramètres!$B$70,IF('Net vendeur'!$C$49>=1,Paramètres!$B$71,Paramètres!$B$72))))))) -> Aucune exonération : la plus-value est imposable
B52: Plus-value imposable à l'impôt sur le revenu | C52: =IF('Net vendeur'!$C$65<>"OK","",IF(OR('Net vendeur'!$C$51=Paramètres!$B$66,'Net vendeur'!$C$51=Paramètres!$B$67,'Net vendeur'!$C$51=Paramètres!$B$68,'Net vendeur'!$C$51=Paramètres!$B$69),0,'Net vendeur'!$C$48*(1-'Net vendeur'!$C$49))) -> 23270.211 | D52: Plus-value brute moins l'abattement d'impôt sur le revenu. Zéro en cas d'exonération totale.
B53: Plus-value imposable aux prélèvements sociaux | C53: =IF('Net vendeur'!$C$65<>"OK","",IF(OR('Net vendeur'!$C$51=Paramètres!$B$66,'Net vendeur'!$C$51=Paramètres!$B$67,'Net vendeur'!$C$51=Paramètres!$B$68,'Net vendeur'!$C$51=Paramètres!$B$69),0,'Net vendeur'!$C$48*(1-'Net vendeur'!$C$50))) -> 35487.071 | D53: Plus-value brute moins l'abattement de prélèvements sociaux. Presque toujours plus élevée que la précédente.
B55: L'IMPÔT DE PLUS-VALUE
B56: Impôt sur le revenu | C56: =IF('Net vendeur'!$C$65<>"OK","",'Net vendeur'!$C$52*Paramètres!$C$8) -> 4421.34 | D56: Taux proportionnel de Paramètres, appliqué à la plus-value imposable à l'impôt sur le revenu.
B57: Prélèvements sociaux | C57: =IF('Net vendeur'!$C$65<>"OK","",'Net vendeur'!$C$53*Paramètres!$C$9) -> 6103.7762 | D57: Taux de Paramètres, appliqué à l'autre base. Ils sont presque toujours plus lourds que l'impôt sur le revenu.
B58: Surtaxe sur les plus-values élevées | C58: =IF('Net vendeur'!$C$65<>"OK","",IF('Net vendeur'!$C$24=Paramètres!$G$100,0,IF('Net vendeur'!$C$52<=INDEX(Paramètres!$B$53:$B$62,1),0,INDEX(Paramètres!$C$53:$C$62,MATCH('Net vendeur'!$C$52,Paramètres!$B$53:$B$62,1))*'Net vendeur'!$C$52-INDEX(Paramètres!$D$53:$D$62,MATCH('Net vendeur'!$C$52,Paramètres!$B$53:$B$62,1))*MAX(0,INDEX(Paramètres!$E$53:$E$62,MATCH('Net vendeur'!$C$52,Paramètres!$B$53:$B$62,1))-'Net vendeur'!$C$52)))) -> 0 | D58: Barème par tranches de Paramètres, assis sur la plus-value imposable à l'impôt sur le revenu. Nulle pour un terrain à bâtir.
B59: Impôt total de plus-value | C59: =IF('Net vendeur'!$C$65<>"OK","",'Net vendeur'!$C$56+'Net vendeur'!$C$57+'Net vendeur'!$C$58) -> 10525.116 | D59: Ce que le notaire retiendra sur le prix le jour de la signature.
B61: CE QUE LE VENDEUR ENCAISSE
B62: Net en poche pour le vendeur | C62: =IF('Net vendeur'!$C$65<>"OK","",'Net vendeur'!$C$11-'Net vendeur'!$C$15-'Net vendeur'!$C$18-'Net vendeur'!$C$19-'Net vendeur'!$C$20-'Net vendeur'!$C$59) -> 206245.94 | D62: Prix net vendeur, moins le solde du prêt et l'indemnité, moins les diagnostics et les autres frais, moins l'impôt.
B63: Part du prix affiché qui revient au vendeur | C63: =IF('Net vendeur'!$C$65<>"OK","",'Net vendeur'!$C$11/'Net vendeur'!$C$7) -> 0.9569378 | D63: Le coût de l'intermédiation, et rien d'autre. Cent pour cent en vente sans agence.
B64: Part du net vendeur conservée après impôt | C64: =IF(OR('Net vendeur'!$C$65<>"OK",'Net vendeur'!$C$11<=0),"",('Net vendeur'!$C$11-'Net vendeur'!$C$59)/'Net vendeur'!$C$11) -> 0.97143183 | D64: Le coût fiscal de la vente. Le remboursement du prêt n'entre pas dans ce ratio : ce n'est pas un coût de la vente, c'est votre dette.
B65: Saisies et paramètres complets | C65: =IF(AND('Net vendeur'!$C$12="OK",'Net vendeur'!$C$21="OK",'Net vendeur'!$C$34="OK",'Net vendeur'!$C$42="OK",COUNT(Paramètres!$C$8:$C$15)=8,COUNT(Paramètres!$B$19:$B$49)=31,COUNT(Paramètres!$C$19:$C$49)=31,COUNT(Paramètres!$D$19:$D$49)=31,COUNT(Paramètres!$B$53:$B$62)=10,COUNT(Paramètres!$C$53:$C$62)=10,COUNT(Paramètres!$D$53:$D$62)=10,COUNT(Paramètres!$E$53:$E$62)=10,ISNUMBER(Paramètres!$C$82)),"OK","À CORRIGER") -> OK | D65: Rouge dès qu'un contrôle est rouge ou qu'un barème manque dans Paramètres. Tant qu'il l'est, le classeur n'affiche aucun chiffre de plus-value : un impôt calculé sur une saisie fausse est pire que pas d'impôt du tout.
B67: CorpusImmo, millésime 2026. Modèle d'aide à la décision : ne constitue ni un conseil en investissement, ni un conseil fiscal, ni une expertise au sens de la charte de l'expertise en évaluation immobilière. Vérifiez les paramètres avant tout engagement.

Sheet Qualifier le mandat
B1: CorpusImmo · www.corpus.immo · Estimer, comparer, décider. Sur les ventes réelles.
B2: Ce mandat vaut-il vos six prochains mois ?
B3: Huit critères notés pendant le rendez-vous, un critère de prix éliminatoire, un score, un verdict.
B5: Cellules violettes : à remplir. Cellules blanches : calculées automatiquement.
B6: LES HUIT CRITÈRES DU MANDAT
B7: Critère | C7: Note (0 à 5) | D7: Poids (0 à 5) | E7: Pondéré | F7: Ce que le critère mesure
B8: Le vendeur est-il vraiment décidé à vendre ? | C8: 4 | D8: 3 | E8: =IF(AND(ISNUMBER(C8),ISNUMBER(D8)),C8*D8,"") -> 12 | F8: Un vendeur qui teste le marché consomme votre temps sans le payer.
B9: Son prix espéré est-il compatible avec le marché ? | C9: 2 | D9: 3 | E9: =IF(AND(ISNUMBER(C9),ISNUMBER(D9)),C9*D9,"") -> 6 | F9: Le premier motif d'échec d'un mandat. Notez 0 dès que l'écart dépasse le seuil éliminatoire ci-dessous.
B10: L'échéance est-elle datée et contrainte ? | C10: 4 | D10: 2 | E10: =IF(AND(ISNUMBER(C10),ISNUMBER(D10)),C10*D10,"") -> 8 | F10: Mutation, succession, divorce, achat déjà signé : une date fait vendre.
B11: Le bien est-il présentable en l'état ? | C11: 3 | D11: 2 | E11: =IF(AND(ISNUMBER(C11),ISNUMBER(D11)),C11*D11,"") -> 6 | F11: Photos, encombrement, travaux visibles.
B12: Le titre et les diagnostics sont-ils prêts ? | C12: 3 | D12: 1 | E12: =IF(AND(ISNUMBER(C12),ISNUMBER(D12)),C12*D12,"") -> 3 | F12: Titre de propriété, dossier de diagnostic technique, procès-verbaux d'assemblée générale, surface loi Carrez.
B13: Le mandat est-il exclusif ? | C13: 2 | D13: 3 | E13: =IF(AND(ISNUMBER(C13),ISNUMBER(D13)),C13*D13,"") -> 6 | F13: Un mandat simple partagé à cinq vaut le cinquième de votre effort.
B14: Les signatures nécessaires sont-elles réunies ? | C14: 4 | D14: 2 | E14: =IF(AND(ISNUMBER(C14),ISNUMBER(D14)),C14*D14,"") -> 8 | F14: Notez haut si tous les propriétaires sont d'accord. Notez bas en cas d'indivision ou de copropriété conflictuelle, où plusieurs signatures peuvent bloquer la vente.
B15: Le bien correspond-il à votre fichier acquéreurs ? | C15: 4 | D15: 2 | E15: =IF(AND(ISNUMBER(C15),ISNUMBER(D15)),C15*D15,"") -> 8 | F15: Un bien hors de votre zone ou de votre gamme se vend deux fois plus lentement.
B17: LE PRIX DEMANDÉ : LE CRITÈRE ÉLIMINATOIRE
B18: Écart entre le prix espéré et votre estimation | C18: 0.08 | F18: ="Au-delà de "&ROUND(Paramètres!$C$85*100,0)&" %"&" (Paramètres, repères), le verdict devient éliminatoire quel que soit le score. Tapez 8 pour 8 %." -> Au-delà de 15 % (Paramètres, repères), le verdict devient éliminatoire quel que soit le score. Tapez 8 pour 8 %.
B20: LE SCORE ET LE VERDICT
B21: Total pondéré | C21: =IF($C$27<>"OK","",SUM($E$8:$E$15)) -> 57 | F21: Somme des notes multipliées par leurs poids.
B22: Maximum atteignable | C22: =IF($C$27<>"OK","",SUM($D$8:$D$15)*Paramètres!$C$83) -> 90 | F22: Somme des poids multipliée par la note maximale de Paramètres.
B23: Score du mandat | C23: =IF(OR($C$27<>"OK",$C$22<=0),"",$C$21/$C$22) -> 0.63333333 | F23: Vert au-dessus du seuil de mandat solide, rouge sous le seuil de refus, sans couleur entre les deux.
B24: Verdict | C24: =IF($C$27<>"OK","",IF($C$23="","",IF($C$18>Paramètres!$C$85,Paramètres!$B$95,INDEX(Paramètres!$B$91:$B$94,MATCH($C$23,Paramètres!$C$91:$C$94,1))))) -> Prenez-le, mais négociez le prix avant de signer | F24: Texte lu dans la table des verdicts de Paramètres. L'écart de prix l'emporte sur le score.
B25: Seuil de mandat à refuser | C25: =Paramètres!$C$92 -> 0.4 | F25: Repère commercial, modifiable dans Paramètres.
B26: Seuil de mandat solide | C26: =Paramètres!$C$94 -> 0.75 | F26: Recalez ces deux seuils sur vos douze derniers mandats.
B27: La grille : saisies cohérentes | C27: =IF(IF(AND(COUNT($C$8:$C$15)=8,COUNT($D$8:$D$15)=8,ISNUMBER(Paramètres!$C$83),ISNUMBER(Paramètres!$C$84),ISNUMBER(Paramètres!$C$85),ISNUMBER(Paramètres!$C$82)),AND(MIN($C$8:$C$15)>=0,MAX($C$8:$C$15)<=Paramètres!$C$83,SUMPRODUCT(--($C$8:$C$15<>INT($C$8:$C$15)))=0,MIN($D$8:$D$15)>=0,MAX($D$8:$D$15)<=Paramètres!$C$84,SUMPRODUCT(--($D$8:$D$15<>INT($D$8:$D$15)))=0,SUM($D$8:$D$15)>0,OR($C$18="",AND(ISNUMBER($C$18),$C$18>=0,$C$18<=1)),AND(ISNUMBER(Paramètres!$C$82),OR(NOT(ISNUMBER($C$18)),$C$18<=0,$C$18>=Paramètres!$C$82))),FALSE),"OK","À CORRIGER") -> OK | F27: Rouge si un critère n'est pas noté, si une note ou un poids sort de 0 à 5 ou n'est pas entier, si tous les poids sont à zéro, ou si l'écart de prix sort de la plage admise.
B29: POURQUOI CES POIDS, ET COMMENT LES RECALER
B30: Les poids comptent autant que les notes. Trois critères pèsent trois fois plus que le titre et les diagnostics : la décision réelle du vendeur, la
B31: compatibilité du prix avec le marché, et l'exclusivité. Ce sont les trois seuls qui déterminent si le bien se vendra ; le reste ne fait que moduler le délai.
B32: Le prix est le seul critère éliminatoire : au-delà du seuil de Paramètres, un mandat ne se vend pas au prix demandé, quel que soit le reste du dossier.
B33: Reprenez vos douze derniers mandats, notez-les après coup, et recalez les poids et les deux seuils : votre grille vaudra mieux que celle-ci.
B35: CorpusImmo, millésime 2026. Modèle d'aide à la décision : ne constitue ni un conseil en investissement, ni un conseil fiscal, ni une expertise au sens de la charte de l'expertise en évaluation immobilière. Vérifiez les paramètres avant tout engagement.

Sheet Paramètres
B1: CorpusImmo · www.corpus.immo · Estimer, comparer, décider. Sur les ventes réelles.
B2: Paramètres
B3: Les seules valeurs à mettre à jour quand la loi ou le marché changent. Toutes les formules du classeur pointent ici.
B5: Cellules violettes : à remplir. Cellules blanches : calculées automatiquement.
B6: BARÈMES RÉGLEMENTAIRES, MILLÉSIME 2026
B7: Paramètre | C7: Valeur | D7: Source (organisme, texte, date) | E7: Mise à jour | F7: Commentaire
B8: Impôt sur le revenu sur la plus-value immobilière des particuliers | C8: 0.19 | D8: ="CGI art. 200 B et 150 VF, taux proportionnel de 19 %. Legifrance, version en vigueur au 01/01/2026. Vérifié le "&TEXT(DAY(Paramètres!$C$105),"00")&"/"&TEXT(MONTH(Paramètres!$C$105),"00")&"/"&YEAR(Paramètres!$C$105)&"." -> CGI art. 200 B et 150 VF, taux proportionnel de 19 %. Legifrance, version en vigueur au 01/01/2026. Vérifié le 05/09/2026. | E8: Chaque loi de finances (décembre) | F8: Résidents et non-résidents. Le notaire le prélève sur le prix le jour de la signature.
B9: Prélèvements sociaux sur la plus-value immobilière | C9: 0.172 | D9: ="CSS art. L136-7 et L136-8, CGI art. 235 ter. La hausse de CSG de la loi de financement pour 2026 ne vise pas les plus-values immobilières, maintenues à 17,2 %. service-public.gouv.fr, fiche F10864 du 15/04/2026. Vérifié le "&TEXT(DAY(Paramètres!$C$105),"00")&"/"&TEXT(MONTH(Paramètres!$C$105),"00")&"/"&YEAR(Paramètres!$C$105)&"." -> CSS art. L136-7 et L136-8, CGI art. 235 ter. La hausse de CSG de la loi de financement pour 2026 ne vise pas les plus-values immobilières, maintenues à 17,2 %. service-public.gouv.fr, fiche F10864 du 15/04/2026. Vérifié le 05/09/2026. | E9: Chaque loi de financement de la sécurité sociale (décembre) | F9: Ne pas recopier ici les 18,6 % des revenus de location meublée : la plus-value immobilière des particuliers reste à 17,2 %.
B10: Forfait de frais d'acquisition (acquisitions à titre onéreux) | C10: 0.075 | D10: ="CGI art. 150 VB, II-3° ; BOFiP BOI-RFPI-PVI-20-10-20-20 du 20/12/2013, § 30 : forfait de 7,5 % du prix, sur option, réservé aux acquisitions à titre onéreux. Vérifié le "&TEXT(DAY(Paramètres!$C$105),"00")&"/"&TEXT(MONTH(Paramètres!$C$105),"00")&"/"&YEAR(Paramètres!$C$105)&"." -> CGI art. 150 VB, II-3° ; BOFiP BOI-RFPI-PVI-20-10-20-20 du 20/12/2013, § 30 : forfait de 7,5 % du prix, sur option, réservé aux acquisitions à titre onéreux. Vérifié le 05/09/2026. | E10: Stable, à revérifier à chaque loi de finances | F10: Un bien reçu par succession ou par donation n'y a pas droit : seuls les frais réels justifiés majorent la valeur retenue.
B11: Forfait travaux (immeuble bâti détenu depuis plus de cinq ans) | C11: 0.15 | D11: ="CGI art. 150 VB, II-4° ; BOFiP BOI-RFPI-PVI-20-10-20-20, § 360 et § 380 : 15 % du prix d'acquisition, sans justificatif, pour un immeuble bâti détenu depuis plus de cinq ans. Vérifié le "&TEXT(DAY(Paramètres!$C$105),"00")&"/"&TEXT(MONTH(Paramètres!$C$105),"00")&"/"&YEAR(Paramètres!$C$105)&"." -> CGI art. 150 VB, II-4° ; BOFiP BOI-RFPI-PVI-20-10-20-20, § 360 et § 380 : 15 % du prix d'acquisition, sans justificatif, pour un immeuble bâti détenu depuis plus de cinq ans. Vérifié le 05/09/2026. | E11: Stable, à revérifier à chaque loi de finances | F11: Alternative aux travaux réels sur factures d'entreprise. Le classeur applique celui que vous choisissez, jamais les deux.
B12: Détention minimale exigée pour le forfait travaux | C12: 5 | D12: ="BOFiP BOI-RFPI-PVI-20-10-20-20, § 360 : plus de cinq ans après l'acquisition, apprécié de date à date. Vérifié le "&TEXT(DAY(Paramètres!$C$105),"00")&"/"&TEXT(MONTH(Paramètres!$C$105),"00")&"/"&YEAR(Paramètres!$C$105)&"." -> BOFiP BOI-RFPI-PVI-20-10-20-20, § 360 : plus de cinq ans après l'acquisition, apprécié de date à date. Vérifié le 05/09/2026. | E12: Stable | F12: Strictement plus : à cinq ans jour pour jour le forfait n'est pas acquis, il l'est le lendemain.
B13: Seuil d'exonération des petites cessions | C13: 15000 | D13: ="CGI art. 150 U, II-6° ; BOFiP BOI-RFPI-PVI-10-40 : prix de cession inférieur ou égal à 15 000 €, apprécié bien par bien et par vendeur. Vérifié le "&TEXT(DAY(Paramètres!$C$105),"00")&"/"&TEXT(MONTH(Paramètres!$C$105),"00")&"/"&YEAR(Paramètres!$C$105)&"." -> CGI art. 150 U, II-6° ; BOFiP BOI-RFPI-PVI-10-40 : prix de cession inférieur ou égal à 15 000 €, apprécié bien par bien et par vendeur. Vérifié le 05/09/2026. | E13: Chaque loi de finances (décembre) | F13: Le classeur compare le prix affiché à ce seuil, ce qui est l'hypothèse la moins favorable au vendeur.
B14: Plafond légal de l'indemnité de remboursement anticipé, part du capital | C14: 0.03 | D14: ="Code de la consommation art. L313-47 et R313-25, version en vigueur au 01/07/2016 : 3 % du capital restant dû avant le remboursement. Vérifié le "&TEXT(DAY(Paramètres!$C$105),"00")&"/"&TEXT(MONTH(Paramètres!$C$105),"00")&"/"&YEAR(Paramètres!$C$105)&"." -> Code de la consommation art. L313-47 et R313-25, version en vigueur au 01/07/2016 : 3 % du capital restant dû avant le remboursement. Vérifié le 05/09/2026. | E14: Stable | F14: Plafond absolu : l'indemnité réclamée ne peut jamais le dépasser.
B15: Plafond légal de l'indemnité, nombre de mois d'intérêts | C15: 6 | D15: ="Code de la consommation art. R313-25 : un semestre d'intérêts sur le capital remboursé, au taux moyen du prêt. Le plus faible des deux plafonds s'applique. Vérifié le "&TEXT(DAY(Paramètres!$C$105),"00")&"/"&TEXT(MONTH(Paramètres!$C$105),"00")&"/"&YEAR(Paramètres!$C$105)&"." -> Code de la consommation art. R313-25 : un semestre d'intérêts sur le capital remboursé, au taux moyen du prêt. Le plus faible des deux plafonds s'applique. Vérifié le 05/09/2026. | E15: Stable | F15: Aucune indemnité n'est due en cas de vente liée à un changement de lieu de travail, à un décès ou à une cessation forcée d'activité (art. L313-48).
B17: ABATTEMENTS POUR DURÉE DE DÉTENTION, BARÈME PAR PALIERS LÉGAUX (CGI ART. 150 VC)
B18: Années de détention révolues | C18: Abattement impôt sur le revenu | D18: Abattement prélèvements sociaux | E18: Source (organisme, texte, date) | F18: Commentaire
B19: 0 | C19: 0 | D19: 0 | E19: CGI art. 150 VC, I (Legifrance, version en vigueur depuis le 01/01/2014) et CSS art. L136-7, VI ; BOFiP BOI-RFPI-PVI-20-20 du 18/07/2023, § 60 et § 70. Impôt sur le revenu : 6 % par année de détention de la sixième à la vingt et unième, 4 % la vingt-deuxième. Prélèvements sociaux : 1,65 % par année de la sixième à la vingt et unième, 1,60 % la vingt-deuxième, 9 % de la vingt-troisième à la trentième. | F19: Deux cadences et deux durées : exonération d'impôt sur le revenu à vingt-deux ans, de prélèvements sociaux à trente ans seulement. Le classeur lit cette table, il ne recalcule aucun palier. Une durée supérieure à trente ans lit la dernière ligne.
B20: 1 | C20: 0 | D20: 0
B21: 2 | C21: 0 | D21: 0
B22: 3 | C22: 0 | D22: 0
B23: 4 | C23: 0 | D23: 0
B24: 5 | C24: 0 | D24: 0
B25: 6 | C25: 0.06 | D25: 0.0165
B26: 7 | C26: 0.12 | D26: 0.033
B27: 8 | C27: 0.18 | D27: 0.0495
B28: 9 | C28: 0.24 | D28: 0.066
B29: 10 | C29: 0.3 | D29: 0.0825
B30: 11 | C30: 0.36 | D30: 0.099
B31: 12 | C31: 0.42 | D31: 0.1155
... B49: 30 | C49: 1 | D49: 1
B51: TAXE SUR LES PLUS-VALUES IMMOBILIÈRES ÉLEVÉES, BARÈME PAR TRANCHES (CGI ART. 1609 NONIES G)
B52: Plus-value imposable supérieure à | C52: Taux | D52: Coefficient de lissage | E52: Borne de lissage | F52: Source et commentaire
B53: 50000 | C53: 0.02 | D53: 0.05 | E53: 60000 | F53: CGI art. 1609 nonies G, version en vigueur depuis le 01/01/2024 (Legifrance) ; BOFiP BOI-RFPI-TPVIE-20. Barème par tranches, avec un terme de lissage sur les cinq tranches d'entrée. Assiette : la plus-value imposable à l'impôt sur le revenu, après abattement pour durée de détention. Les terrains à bâtir sont hors du champ.
B54: 60000 | C54: 0.02 | D54: 0 | E54: 0 | F54: Taxe = taux multiplié par la plus-value, moins le coefficient multiplié par l'écart à la borne. Un coefficient nul désigne une tranche sans lissage.
B55: 100000 | C55: 0.03 | D55: 0.1 | E55: 110000
B56: 110000 | C56: 0.03 | D56: 0 | E56: 0
B57: 150000 | C57: 0.04 | D57: 0.15 | E57: 160000
B58: 160000 | C58: 0.04 | D58: 0 | E58: 0
B59: 200000 | C59: 0.05 | D59: 0.2 | E59: 210000
B60: 210000 | C60: 0.05 | D60: 0 | E60: 0
B61: 250000 | C61: 0.06 | D61: 0.25 | E61: 260000
B62: 260000 | C62: 0.06 | D62: 0 | E62: 0
B64: EXONÉRATIONS TESTÉES PAR LE CLASSEUR, DANS L'ORDRE OÙ ELLES SONT EXAMINÉES
B65: Texte affiché dans l'onglet Net vendeur | C65: Ordre | D65: Article du code général des impôts | E65: Effet | F65: Condition testée par le classeur
B66: Exonération totale : résidence principale au jour de la vente | C66: 1 | D66: CGI art. 150 U, II-1° | E66: Exonération totale | F66: Réponse Oui à la question « Résidence principale ». Le logement doit être votre habitation habituelle au jour de la vente, ou avoir été libéré depuis un délai normal de vente. Les dépendances immédiates et nécessaires suivent le même sort.
B67: Exonération totale : cession à un organisme de logement social | C67: 2 | D67: CGI art. 150 U, II-7° et 8° | E67: Exonération totale | F67: Réponse Oui à la question correspondante. Dispositif prorogé jusqu'au 31/12/2027 (service-public.gouv.fr, fiche F10864).
B68: Exonération totale : première cession d'un logement autre que la résidence principale | C68: 3 | D68: CGI art. 150 U, II-1° bis | E68: Exonération totale | F68: Réponse Oui. Trois conditions cumulatives : ne pas avoir été propriétaire de sa résidence principale au cours des quatre années précédentes, remployer le prix dans l'achat ou la construction de sa résidence principale dans les vingt-quatre mois, et n'avoir jamais utilisé cette exonération.
B69: Exonération totale : prix de cession sous le seuil des petites cessions | C69: 4 | D69: CGI art. 150 U, II-6° | E69: Exonération totale | F69: Prix affiché inférieur ou égal au seuil des petites cessions du bloc des barèmes. Le seuil s'apprécie bien par bien et par vendeur.
B70: Exonération totale : plus de trente ans de détention | C70: 5 | D70: CGI art. 150 VC et CSS art. L136-7 | E70: Exonération totale | F70: Abattement de 100 % à l'impôt sur le revenu et de 100 % aux prélèvements sociaux dans la table ci-dessus.
B71: Exonération d'impôt sur le revenu seulement : plus de vingt-deux ans de détention | C71: 6 | D71: CGI art. 150 VC | E71: Exonération partielle | F71: Abattement de 100 % à l'impôt sur le revenu, mais inférieur à 100 % aux prélèvements sociaux : ces derniers restent dus, et la surtaxe ne s'applique plus, son assiette étant nulle.
B72: Aucune exonération : la plus-value est imposable | C72: 7 | E72: Aucune | F72: Aucune des conditions ci-dessus n'est remplie.
B74: REPÈRES DE MARCHÉ ET DE DÉCISION COMMERCIALE (POINTS DE DÉPART, À RECALER)
B75: Paramètre | C75: Valeur | D75: Source (organisme, texte, date) | E75: Mise à jour | F75: Commentaire
B76: Honoraires d'agence TTC, bas de fourchette | C76: 0.03 | D76: ="Barèmes librement fixés depuis la loi Hoguet ; fourchettes observées sur les barèmes affichés en agence en 2026, biens de plus de 300 000 €. Consulté le "&TEXT(DAY(Paramètres!$C$105),"00")&"/"&TEXT(MONTH(Paramètres!$C$105),"00")&"/"&YEAR(Paramètres!$C$105)&"." -> Barèmes librement fixés depuis la loi Hoguet ; fourchettes observées sur les barèmes affichés en agence en 2026, biens de plus de 300 000 €. Consulté le 05/09/2026. | E76: Annuelle | F76: Les gros montants se négocient : le taux baisse quand le prix monte.
B77: Honoraires d'agence TTC, haut de fourchette | C77: 0.07 | D77: Mêmes sources : petits montants, secteurs ruraux, mandats simples. | E77: Annuelle | F77: Le barème doit être affiché en vitrine et sur le site, et le mandat indique qui paie.
B78: Dossier de diagnostic technique, bas de fourchette | C78: 300 | D78: ="Code de la construction et de l'habitation art. L271-4 pour le contenu du dossier ; fourchettes de prix 2026 relevées chez les réseaux de diagnostiqueurs. Consulté le "&TEXT(DAY(Paramètres!$C$105),"00")&"/"&TEXT(MONTH(Paramètres!$C$105),"00")&"/"&YEAR(Paramètres!$C$105)&"." -> Code de la construction et de l'habitation art. L271-4 pour le contenu du dossier ; fourchettes de prix 2026 relevées chez les réseaux de diagnostiqueurs. Consulté le 05/09/2026. | E78: Annuelle | F78: Studio ou T2 récent en copropriété.
B79: Dossier de diagnostic technique, haut de fourchette | C79: 800 | D79: Mêmes sources. | E79: Annuelle | F79: Maison ancienne : amiante avant juillet 1997, plomb avant 1949, électricité et gaz de plus de quinze ans, termites, assainissement, audit énergétique pour les classes E, F et G.
B80: Mainlevée d'hypothèque et état daté, bas de fourchette | C80: 400 | D80: ="Tarif réglementé des notaires pour la mainlevée ; plafond réglementaire de l'état daté en copropriété (décret n° 2020-153 du 21/02/2020). Consulté le "&TEXT(DAY(Paramètres!$C$105),"00")&"/"&TEXT(MONTH(Paramètres!$C$105),"00")&"/"&YEAR(Paramètres!$C$105)&"." -> Tarif réglementé des notaires pour la mainlevée ; plafond réglementaire de l'état daté en copropriété (décret n° 2020-153 du 21/02/2020). Consulté le 05/09/2026. | E80: Annuelle | F80: Petit capital restant dû, pas de copropriété.
B81: Mainlevée d'hypothèque et état daté, haut de fourchette | C81: 1200 | D81: Mêmes sources. | E81: Annuelle | F81: Capital élevé, copropriété, ou privilège de prêteur de deniers à radier.
B82: Plancher de plausibilité d'un taux saisi | C82: 0.001 | D82: Convention CorpusImmo, commune aux matrices qui saisissent des taux. | E82: Stable | F82: Un taux compris entre 0 et 0,10 % signale presque toujours une saisie en fraction : 0,045 tapé pour 4,5 %. Le contrôle de l'onglet passe alors au rouge.
B83: Note maximale de la grille de qualification | C83: 5 | D83: Choix de l'auteur : échelle de 0 à 5, une note par critère. | E83: Aucune | F83: Sert au maximum atteignable de la grille. Une note supérieure est refusée à la saisie et signalée par le contrôle.
B84: Poids maximal d'un critère de la grille | C84: 5 | D84: Choix de l'auteur : les poids livrés vont de 1 à 3. | E84: Aucune | F84: Recalez les poids sur vos douze derniers mandats, une fois pour toutes.
B85: Écart de prix éliminatoire (prix espéré contre estimation) | C85: 0.15 | D85: Repère commercial CorpusImmo, millésime 2026 : au-delà de cet écart, le mandat ne se vend pas au prix demandé, quel que soit le reste. | E85: À recaler sur vos mandats | F85: Au-delà, le verdict devient éliminatoire quel que soit le score.
B86: Date d'acte la plus ancienne admise | C86: 18264 | D86: Convention CorpusImmo : borne de plausibilité des deux dates d'acte, reprise à l'identique dans la validation de saisie et dans le contrôle. | E86: Stable | F86: Une année tapée à la place d'une date (2013) est un vrai numéro de série Excel, qui désigne un jour de 1905 : cette borne l'attrape. Un acte antérieur donne de toute façon une exonération totale par la durée.
B87: Date d'acte la plus lointaine admise | C87: 73415 | D87: Même convention. | E87: Stable | F87: Attrape une date de vente saisie de travers, par exemple un millésime à quatre chiffres tapé dans le mauvais ordre.
B89: VERDICTS DE LA GRILLE DE QUALIFICATION DU MANDAT
B90: Verdict affiché | C90: Score minimal | D90: Commentaire
B91: Passez votre chemin : ce mandat coûtera plus qu'il ne rapporte | C91: 0 | D91: En dessous du seuil suivant. Le temps passé ne sera pas payé.
B92: Mandat à risque : exigez l'exclusivité et une baisse de prix datée | C92: 0.4 | D92: Prenable si vous obtenez les deux contreparties, écrites dans le mandat.
B93: Prenez-le, mais négociez le prix avant de signer | C93: 0.55 | D93: Le dossier tient, le prix est le point faible.
B94: Prenez-le, et en exclusivité | C94: 0.75 | D94: Vendeur décidé, prix tenable, dossier prêt.
B95: Éliminatoire : reprenez le prix avant de parler de mandat | D95: S'affiche quel que soit le score dès que l'écart de prix dépasse le repère éliminatoire ci-dessus.
B97: LISTES DÉROULANTES DE L'ONGLET NET VENDEUR
B98: Honoraires à la charge de | C98: Oui / Non | D98: Mode d'acquisition | E98: Frais d'acquisition retenus | F98: Travaux retenus | G98: Nature du bien | H98: Cas particulier de la cession
B99: Acquéreur | C99: Oui | D99: Achat (à titre onéreux) | E99: Forfait de 7,5 % | F99: Forfait de 15 % | G99: Logement ou immeuble bâti | H99: Aucun
B100: Vendeur | C100: Non | D100: Succession | E100: Frais réels justifiés | F100: Travaux réels justifiés | G100: Terrain à bâtir | H100: Démembrement de propriété
D101: Donation | F101: Aucun travaux | H101: Bien détenu par une société
H102: Bien situé à l'étranger
H103: Cession de parts de société
B105: Dernière vérification des paramètres | C105: 46270 | D105: Aucun de ces taux n'est recopié dans une formule : toutes pointent ici.
B107: Les libellés des listes ci-dessus sont fixes : les formules comparent leur texte. Les modifier casse le classeur ; les valeurs violettes, elles, se mettent à jour librement.
B108: Vérifiez les barèmes chaque janvier, après la loi de finances et la loi de financement de la sécurité sociale, puis mettez à jour la date ci-dessus : toutes les mentions « Vérifié le » et « Consulté le » de cet onglet la lisent.
B110: CorpusImmo, millésime 2026. Modèle d'aide à la décision : ne constitue ni un conseil en investissement, ni un conseil fiscal, ni une expertise au sens de la charte de l'expertise en évaluation immobilière. Vérifiez les paramètres avant tout engagement.

Sheet Méthode
B1: CorpusImmo · www.corpus.immo · Estimer, comparer, décider. Sur les ventes réelles.
B2: Méthode de calcul
B3: Le net vendeur poste par poste, les conventions retenues et ce qu'elles coûtent, ce que le modèle ne fait pas, les sources.
B5: CONVENTIONS RETENUES, ET CE QU'ELLES COÛTENT
B6: Honoraires et prix net vendeur | C6: Honoraires à la charge de l'acquéreur : le prix affiché contient les honoraires, et le prix net vendeur s'obtient en divisant par un plus le taux, pas en soustrayant le taux du prix, erreur qui décale le calcul de plusieurs centaines d'euros. Honoraires à la charge du vendeur : la règle d'affichage veut que le prix annoncé ne les contienne pas, et le taux porte alors sur le prix de vente. Le classeur change donc de base selon la charge choisie, et les deux formules sont écrites en clair dans la colonne d'aide. Conséquence pour l'acheteur, qui n'est pas calculée ici : des honoraires à la charge du vendeur entrent dans l'assiette des droits de mutation, des honoraires à la charge de l'acquéreur en sont exclus si le mandat et l'acte le stipulent.
B7: Base de la plus-value | C7: La plus-value se calcule sur le prix net vendeur, jamais sur le prix affiché. Quand les honoraires sont à la charge de l'acquéreur, ils ne font pas partie du prix de cession ; quand ils sont à la charge du vendeur, ils s'en retranchent comme frais de cession sur justification (CGI art. 150 VA). Le résultat est le même dans les deux cas, et c'est celui que retient le classeur.
B8: Durée de détention, de date à date | C8: La durée est comptée par périodes de douze mois depuis la date d'acquisition jusqu'à la date de vente, et non en années civiles. Le classeur soustrait les millésimes puis retire une année tant que la date anniversaire n'est pas atteinte. Une vente la veille de l'anniversaire perd une année entière d'abattement : sur l'exemple livré, cela vaut 571 € d'impôt. Convention sur le 29 février : l'anniversaire est ramené au 28 février dans une année non bissextile, ce qui est l'usage des tableurs et sans effet en pratique. Pour une succession, la durée part de la date du décès ; pour une donation, de la date de l'acte.
B9: Abattements pour durée de détention | C9: Deux barèmes différents, lus dans la table de Paramètres : 6 % par année de la sixième à la vingt et unième puis 4 % la vingt-deuxième pour l'impôt sur le revenu ; 1,65 % par année de la sixième à la vingt et unième, 1,60 % la vingt-deuxième, puis 9 % par année de la vingt-troisième à la trentième pour les prélèvements sociaux. Aucune formule du classeur ne recalcule un palier : elles lisent toutes la table. Le décalage de huit ans entre les deux exonérations surprend tous les vendeurs et mérite d'être expliqué en rendez-vous.
B10: Prix d'acquisition majoré | C10: Prix d'acquisition, plus les frais d'acquisition retenus, plus les travaux retenus. Les frais sont au forfait de 7,5 % du prix, réservé aux acquisitions à titre onéreux, ou au réel justifié : le classeur applique votre choix, il ne prend pas automatiquement le plus favorable, parce que le forfait et le réel ne se justifient pas de la même façon devant l'administration. Les travaux sont au forfait de 15 % du prix, réservé aux immeubles bâtis détenus depuis plus de cinq ans et apprécié de date à date, ou au réel sur factures d'entreprise, ou nuls. Un même euro de travaux ne peut pas servir deux fois : ceux déjà déduits d'un revenu foncier sont exclus du réel.
B11: Impôt et surtaxe | C11: 19 % d'impôt sur le revenu sur la plus-value après abattement d'impôt sur le revenu, 17,2 % de prélèvements sociaux sur la plus-value après abattement de prélèvements sociaux : deux bases différentes, deux taux différents. S'y ajoute la taxe sur les plus-values immobilières élevées dès que la plus-value imposable à l'impôt sur le revenu dépasse le premier seuil du barème de Paramètres : de 2 % à 6 %, avec un terme de lissage sur les tranches d'entrée, et un ressaut à l'euro près au franchissement du seuil. Les terrains à bâtir en sont exclus. Le classeur applique le barème par tranches, il ne l'approxime pas.
B12: Exonérations | C12: Cinq exonérations totales sont testées, dans l'ordre de la table de Paramètres : résidence principale, cession à un organisme de logement social, première cession d'un logement autre que la résidence principale, prix de cession sous le seuil des petites cessions, détention de plus de trente ans. Une sixième situation, la détention de plus de vingt-deux ans, exonère de l'impôt sur le revenu mais pas des prélèvements sociaux. L'exonération retenue est toujours écrite en toutes lettres dans l'onglet Net vendeur : un impôt nul sans explication est le pire des résultats. Le seuil des petites cessions est comparé au prix affiché, ce qui est l'hypothèse la moins favorable au vendeur quand les honoraires sont à sa charge.
B13: Indemnité de remboursement anticipé | C13: Le classeur calcule le plafond légal du code de la consommation, le plus faible entre un semestre d'intérêts au taux du prêt sur le capital remboursé et une part du capital restant dû, et compare l'indemnité réclamée à ce plafond. Le taux du prêt est facultatif : sans lui, seul le plafond en pourcentage du capital est vérifié, ce qui est moins strict. Le remboursement anticipé est en outre sans indemnité en cas de vente liée à un changement de lieu d'activité professionnelle, à un décès ou à une cessation forcée d'activité.
B14: Ce que mesurent les deux ratios | C14: Le premier rapporte le prix net vendeur au prix affiché : c'est le coût de l'intermédiation, et rien d'autre. Le second rapporte le net après impôt au prix net vendeur : c'est le coût fiscal. Le remboursement du prêt n'entre dans aucun des deux, parce que rendre à la banque un capital emprunté n'est pas un coût de la vente, c'est l'extinction d'une dette. Rapporter le net en poche au prix affiché n'aurait aucun sens : le vendeur croirait perdre la moitié de son prix, alors que l'essentiel de l'écart est le remboursement de son propre emprunt.
B15: Taux, dates et arrondis | C15: Tous les taux sont des fractions affichées en pourcentage : tapez 4,5 dans une cellule de taux, elle affiche 4,50 % et contient 0,045. Ne convertissez jamais vous-même : 0,045 tapé dans cette cellule vaut 0,05 %, et les contrôles des deux onglets passent au rouge grâce au plancher de plausibilité de Paramètres (Paramètres!C82). Aucune formule ne divise par cent. Les dates sont de vraies dates Excel. Les montants sont affichés à l'euro ou au centime selon les lignes, mais calculés sans arrondi intermédiaire : le total peut différer d'un centime de la somme des lignes affichées.
B16: Quand le classeur n'affiche rien | C16: Les contrôles de chaque bloc (Net vendeur!C12, Net vendeur!C21, Net vendeur!C34, Net vendeur!C42) alimentent le contrôle général Net vendeur!C65. Tant que l'un d'eux est rouge, tout le calcul de plus-value, l'impôt et le net en poche restent vides. C'est volontaire : un impôt calculé sur une saisie fausse ou sur une durée par défaut est plus dangereux qu'une cellule vide, parce que personne ne le vérifie.
B17: Millésime des chiffres cités | C17: Les barèmes cités dans cet onglet et dans le Mode d'emploi sont ceux du millésime 2026 et vivent tous dans Paramètres. Ils sont recopiés ici en toutes lettres pour que le texte se lise sans formule : à chaque mise à jour d'une valeur de Paramètres, relisez les lignes qui la citent, ici comme dans le Mode d'emploi. La date de la dernière vérification est en Paramètres!C105.
B19: CE QUE CE MODÈLE NE FAIT PAS
B20: • Il ne remplace pas le calcul du notaire, qui est le seul à faire foi. Il sert à annoncer un ordre de grandeur en rendez-vous et à ne pas signer un mandat sur un net vendeur faux.
B21: • Il ne traite ni le démembrement de propriété, ni les biens détenus par une société, ni les biens situés à l'étranger, ni les cessions de parts de sociétés immobilières. Ces quatre cas se déclarent dans l'onglet Net vendeur et déclenchent un avertissement au lieu d'un chiffre.
B22: • Il ne calcule pas le cas du non-résident, dont les prélèvements sociaux peuvent être limités au prélèvement de solidarité de 7,5 % s'il relève d'un régime de sécurité sociale de l'Union européenne, de l'Espace économique européen ou de Suisse.
B23: • Il ne réintègre pas les amortissements déduits en location meublée non professionnelle, qui viennent en diminution du prix d'acquisition pour les cessions depuis le 15 février 2025 (loi n° 2025-127, CGI art. 150 VB). Un bien loué meublé au réel demande donc un calcul complémentaire.
B24: • Il ne modélise ni l'abattement exceptionnel en zones tendues (CGI art. 150 VE), ni les exonérations liées à l'expropriation, au remembrement, aux retraités et invalides de condition modeste, ni la cession d'un droit de surélévation.
B25: • Il ne vérifie pas les conditions de fond des exonérations : il applique la réponse que vous lui donnez. Une réponse Oui à la légère produit un net en poche trop élevé de tout l'impôt.
B26: • Il ne calcule ni la taxe sur les terrains devenus constructibles, ni les frais de cession autres que ceux que vous saisissez, ni la régularisation du prorata de taxe foncière, qui joue en faveur du vendeur.
B27: • La grille de qualification est un outil de décision commerciale, pas une évaluation du bien. Ses poids et ses seuils sont des repères à recaler sur vos propres mandats.
B29: POINTS TRANCHÉS DANS LE SENS PRUDENT
B30: Seuil des petites cessions | C30: Le seuil de 15 000 € porte sur le prix de cession. Le classeur le compare au prix affiché, plus élevé que le prix net vendeur quand les honoraires sont à la charge de l'acquéreur : l'exonération s'applique donc un peu moins souvent que la lettre du texte ne le permettrait, et l'impôt annoncé n'est jamais sous-estimé.
B31: Forfait travaux à cinq ans jour pour jour | C31: La condition est « plus de cinq ans ». À cinq ans jour pour jour, le classeur refuse le forfait ; il l'accorde le lendemain. C'est l'hypothèse la plus lourde à la date pivot.
B32: Prélèvements sociaux à 17,2 % | C32: La loi de financement de la sécurité sociale pour 2026 a porté la contribution sociale généralisée à 10,6 % sur certains revenus du patrimoine, mais les plus-values immobilières des particuliers restent à 17,2 %, ce que confirment la fiche officielle de service-public.gouv.fr et les commentaires publiés. Si un texte venait à les aligner, la ligne de Paramètres est la seule à changer.
B33: Surtaxe maintenue | C33: Une suppression de la taxe sur les plus-values élevées a été discutée lors des débats budgétaires pour 2026 sans être retenue dans le texte promulgué : l'article 1609 nonies G est toujours en vigueur dans sa version du 1er janvier 2024. Le classeur l'applique. En cas de suppression, mettez les taux du barème de Paramètres à zéro.
B34: Frais d'acquisition, forfait ou réel | C34: Le classeur applique l'option que vous choisissez et ne retient pas d'office la plus favorable : comparez vous-même le forfait au montant réel justifié, la ligne des frais retenus vous donne le résultat de chaque choix.
B36: SOURCES
B37: Impôt sur le revenu sur la plus-value immobilière des particuliers | C37: ="CGI art. 200 B et 150 VF, taux proportionnel de 19 %. Legifrance, version en vigueur au 01/01/2026. Vérifié le "&TEXT(DAY(Paramètres!$C$105),"00")&"/"&TEXT(MONTH(Paramètres!$C$105),"00")&"/"&YEAR(Paramètres!$C$105)&"." -> CGI art. 200 B et 150 VF, taux proportionnel de 19 %. Legifrance, version en vigueur au 01/01/2026. Vérifié le 05/09/2026.
B38: Prélèvements sociaux sur la plus-value immobilière | C38: ="CSS art. L136-7 et L136-8, CGI art. 235 ter. La hausse de CSG de la loi de financement pour 2026 ne vise pas les plus-values immobilières, maintenues à 17,2 %. service-public.gouv.fr, fiche F10864 du 15/04/2026. Vérifié le "&TEXT(DAY(Paramètres!$C$105),"00")&"/"&TEXT(MONTH(Paramètres!$C$105),"00")&"/"&YEAR(Paramètres!$C$105)&"." -> CSS art. L136-7 et L136-8, CGI art. 235 ter. La hausse de CSG de la loi de financement pour 2026 ne vise pas les plus-values immobilières, maintenues à 17,2 %. service-public.gouv.fr, fiche F10864 du 15/04/2026. Vérifié le 05/09/2026.
B39: Forfait de frais d'acquisition (acquisitions à titre onéreux) | C39: ="CGI art. 150 VB, II-3° ; BOFiP BOI-RFPI-PVI-20-10-20-20 du 20/12/2013, § 30 : forfait de 7,5 % du prix, sur option, réservé aux acquisitions à titre onéreux. Vérifié le "&TEXT(DAY(Paramètres!$C$105),"00")&"/"&TEXT(MONTH(Paramètres!$C$105),"00")&"/"&YEAR(Paramètres!$C$105)&"." -> CGI art. 150 VB, II-3° ; BOFiP BOI-RFPI-PVI-20-10-20-20 du 20/12/2013, § 30 : forfait de 7,5 % du prix, sur option, réservé aux acquisitions à titre onéreux. Vérifié le 05/09/2026.
B40: Forfait travaux (immeuble bâti détenu depuis plus de cinq ans) | C40: ="CGI art. 150 VB, II-4° ; BOFiP BOI-RFPI-PVI-20-10-20-20, § 360 et § 380 : 15 % du prix d'acquisition, sans justificatif, pour un immeuble bâti détenu depuis plus de cinq ans. Vérifié le "&TEXT(DAY(Paramètres!$C$105),"00")&"/"&TEXT(MONTH(Paramètres!$C$105),"00")&"/"&YEAR(Paramètres!$C$105)&"." -> CGI art. 150 VB, II-4° ; BOFiP BOI-RFPI-PVI-20-10-20-20, § 360 et § 380 : 15 % du prix d'acquisition, sans justificatif, pour un immeuble bâti détenu depuis plus de cinq ans. Vérifié le 05/09/2026.
B41: Détention minimale exigée pour le forfait travaux | C41: ="BOFiP BOI-RFPI-PVI-20-10-20-20, § 360 : plus de cinq ans après l'acquisition, apprécié de date à date. Vérifié le "&TEXT(DAY(Paramètres!$C$105),"00")&"/"&TEXT(MONTH(Paramètres!$C$105),"00")&"/"&YEAR(Paramètres!$C$105)&"." -> BOFiP BOI-RFPI-PVI-20-10-20-20, § 360 : plus de cinq ans après l'acquisition, apprécié de date à date. Vérifié le 05/09/2026.
B42: Seuil d'exonération des petites cessions | C42: ="CGI art. 150 U, II-6° ; BOFiP BOI-RFPI-PVI-10-40 : prix de cession inférieur ou égal à 15 000 €, apprécié bien par bien et par vendeur. Vérifié le "&TEXT(DAY(Paramètres!$C$105),"00")&"/"&TEXT(MONTH(Paramètres!$C$105),"00")&"/"&YEAR(Paramètres!$C$105)&"." -> CGI art. 150 U, II-6° ; BOFiP BOI-RFPI-PVI-10-40 : prix de cession inférieur ou égal à 15 000 €, apprécié bien par bien et par vendeur. Vérifié le 05/09/2026.
B43: Plafond légal de l'indemnité de remboursement anticipé, part du capital | C43: ="Code de la consommation art. L313-47 et R313-25, version en vigueur au 01/07/2016 : 3 % du capital restant dû avant le remboursement. Vérifié le "&TEXT(DAY(Paramètres!$C$105),"00")&"/"&TEXT(MONTH(Paramètres!$C$105),"00")&"/"&YEAR(Paramètres!$C$105)&"." -> Code de la consommation art. L313-47 et R313-25, version en vigueur au 01/07/2016 : 3 % du capital restant dû avant le remboursement. Vérifié le 05/09/2026.
B44: Plafond légal de l'indemnité, nombre de mois d'intérêts | C44: ="Code de la consommation art. R313-25 : un semestre d'intérêts sur le capital remboursé, au taux moyen du prêt. Le plus faible des deux plafonds s'applique. Vérifié le "&TEXT(DAY(Paramètres!$C$105),"00")&"/"&TEXT(MONTH(Paramètres!$C$105),"00")&"/"&YEAR(Paramètres!$C$105)&"." -> Code de la consommation art. R313-25 : un semestre d'intérêts sur le capital remboursé, au taux moyen du prêt. Le plus faible des deux plafonds s'applique. Vérifié le 05/09/2026.
B45: Abattements pour durée de détention | C45: CGI art. 150 VC, I (Legifrance, version en vigueur depuis le 01/01/2014) et CSS art. L136-7, VI ; BOFiP BOI-RFPI-PVI-20-20 du 18/07/2023, § 60 et § 70. Impôt sur le revenu : 6 % par année de détention de la sixième à la vingt et unième, 4 % la vingt-deuxième. Prélèvements sociaux : 1,65 % par année de la sixième à la vingt et unième, 1,60 % la vingt-deuxième, 9 % de la vingt-troisième à la trentième.
B46: Taxe sur les plus-values élevées | C46: CGI art. 1609 nonies G, version en vigueur depuis le 01/01/2024 (Legifrance) ; BOFiP BOI-RFPI-TPVIE-20. Barème par tranches, avec un terme de lissage sur les cinq tranches d'entrée. Assiette : la plus-value imposable à l'impôt sur le revenu, après abattement pour durée de détention. Les terrains à bâtir sont hors du champ.
B47: Exonérations de plus-value | C47: CGI art. 150 U, II ; BOFiP BOI-RFPI-PVI-10-40 ; service-public.gouv.fr, fiche F10864, mise à jour du 15/04/2026 (résidence principale, première cession, seuil de 15 000 €, organisme de logement social prorogé jusqu'au 31/12/2027, durées de 22 et 30 ans).
B48: Prix d'acquisition à titre gratuit | C48: CGI art. 150 VB, I ; BOFiP BOI-RFPI-PVI-20-10-20-10 : la valeur retenue est celle qui a servi de base aux droits de mutation à titre gratuit, majorée des seuls frais réels justifiés.
B49: Honoraires d'agence et affichage | C49: Loi n° 70-9 du 2 janvier 1970 dite Hoguet ; arrêté du 10 janvier 2017 (JO du 18/01/2017) : barème libre, affiché toutes taxes comprises, en pourcentage de la valeur du bien hors honoraires, avec indication de qui les paie.
B50: Droits de mutation et charge des honoraires | C50: BOFiP BOI-ENR-DMTOI-10-10-20-20 : des honoraires à la charge de l'acquéreur sont exclus de l'assiette des droits de mutation si le mandat et l'acte le stipulent.
B51: Indemnité de remboursement anticipé | C51: Code de la consommation art. L313-47, L313-48 et R313-25, version en vigueur au 01/07/2016 : plafond et cas d'exonération.
B52: Dossier de diagnostic technique | C52: Code de la construction et de l'habitation art. L271-4 : contenu du dossier annexé à la promesse ou à l'acte.
B54: CorpusImmo, millésime 2026. Modèle d'aide à la décision : ne constitue ni un conseil en investissement, ni un conseil fiscal, ni une expertise au sens de la charte de l'expertise en évaluation immobilière. Vérifiez les paramètres avant tout engagement.
