Workbook

Sheet Mode d'emploi
B1: CorpusImmo · corpus.immo · Estimer, comparer, décider. Sur les ventes réelles.
B2: Mode d'emploi
B3: À quoi sert ce classeur, dans quel ordre le remplir, et comment lire ce qu'il répond.
B6: À QUOI SERT CE CLASSEUR
B7: Vous allez louer un appartement ou une maison, et vous hésitez : location nue au micro-foncier ou au réel, meublé au micro-BIC ou au LMNP réel (loueur en meublé non professionnel) avec amortissement, ou société civile à l'impôt sur les sociétés ? Ce classeur prend le même bien, le même loyer et le même prêt, et calcule pour chacun des cinq régimes l'impôt de chaque année, ce qui vous reste en poche après crédit et impôt, ce que vous laissez en réserve (déficits, amortissements différés), puis l'impôt et le net de la revente à la fin de la durée de détention.
B8: Il répond sur toute la durée de détention, revente comprise, et non sur la seule première année. Amortir, c'est déduire chaque année une part du prix du bâti, des travaux et du mobilier, sans rien décaisser : cela efface l'impôt pendant la détention, mais la revente en reprend une partie. Au LMNP réel, les amortissements déduits sont réintégrés dans la plus-value depuis 2025, c'est-à-dire retirés du prix d'achat que l'on retranche du prix de vente. À la SCI à l'impôt sur les sociétés, la plus-value se calcule sur la valeur nette comptable, le prix diminué de tous les amortissements déjà déduits, et sortir l'argent de la société coûte encore le prélèvement forfaitaire unique (PFU, ou flat tax). C'est là que ces deux régimes montrent leur vrai coût.
B9: Tout se saisit dans un seul onglet, Hypothèses. Le Comparateur donne la synthèse en un écran ; le Pluriannuel montre le détail année par année.
B10: Vous êtes | C10: Ce que le classeur vous donne
B11: Investisseur particulier | C11: Le régime qui laisse le plus d'argent en poche sur votre horizon, l'écart avec le suivant, et le taux de rendement interne (TRI) après impôt de chacun.
B12: Conseiller en gestion de patrimoine | C12: Une comparaison à cinq colonnes, année 1 et cumul, avec la revente, pour arbitrer nu, meublé et société devant le client.
B13: Notaire | C13: Le net de revente de chaque régime, avec la plus-value des particuliers (amortissements réintégrés en LMNP) et la plus-value professionnelle à l'IS.
B14: Expert-comptable, fiscaliste | C14: Le détail des reports d'une année sur l'autre (déficit foncier hors intérêts, amortissements différés au titre de l'article 39 C, déficit BIC, déficit IS), la distribution des dividendes et le compte courant d'associé de la SCI, la base réintégrée. Ligne par ligne dans le Pluriannuel : reports fonciers lignes 38 à 40, amortissements différés 54 à 56, déficit BIC 57 à 60, réintégration ligne 64, déficit IS 70 à 72, compte courant et dividendes 81 à 89.
B15: Agent immobilier, chasseur | C15: Un argument chiffré pour un acquéreur investisseur : ce que le bien rapporte après impôt selon la façon de le louer.
B17: LE PRINCIPE, EN UNE LIGNE
B18: Loyers − charges − mensualités du prêt − impôt de chaque année + net de revente = ce que le régime vous laisse, sur toute la durée
B20: LES ONGLETS, DANS L'ORDRE OÙ ON LES REMPLIT
B21: Onglet | C21: Ce que vous y faites | D21: Ce que vous y lisez
B22: Mode d'emploi | C22: Rien à saisir. Vous lisez ce guide. | D22: La marche à suivre et l'exemple guidé.
B23: Hypothèses | C23: Vous remplissez les six blocs de saisie, de haut en bas : le bien, l'exploitation, le financement, le foyer, la détention, les options. | D23: Huit contrôles OK / KO (C13, C23, C33, C38, C46, C58, C61, puis le contrôle général C62) et, tout en bas, le régime le plus favorable (Hypothèses!C63) avec l'écart (Hypothèses!C64).
B24: Comparateur | C24: Rien à saisir. | D24: Cinq colonnes, une par régime, et une colonne Lecture à droite qui explique chaque ligne en français. De haut en bas : éligibilité et année 1 (lignes 8 à 11), cumul sur la détention (14 à 17), revente (20 à 31), bilan, TRI et rang (34 à 38), verdict (41 à 43).
B25: Pluriannuel | C25: Rien à saisir. | D25: Trente années en colonnes (D à AG) : loyer, prêt, amortissements, puis pour chaque régime le résultat, l'impôt, les reports et le flux en poche. La colonne C donne le cumul sur la durée de détention, ou le stock en fin de détention pour les reports : c'est elle que lit le Comparateur. Les années au-delà de la détention sont grisées.
B26: Paramètres | C26: Rien, sauf à la mise à jour annuelle des barèmes et des repères. | D26: Chaque valeur avec sa source datée et sa fréquence de mise à jour, la table des abattements de durée, les listes.
B27: Méthode | C27: Rien à saisir. | D27: Les conventions, ce que le modèle ne fait pas, les points de droit signalés, les sources.
B29: LE CODE COULEUR, ET COMMENT DÉVERROUILLER UNE CELLULE
B30: Cellule | C30: Ce que c'est | D30: Ce que vous faites
B31: Fond bleu ciel, texte bleu nuit | C31: Saisie utilisateur | D31: Vous la remplissez. Jamais de formule dedans.
B32: Fond blanc | C32: Calcul | D32: Vous la lisez. Elle est verrouillée.
B33: Fond presque blanc, texte bleu nuit en gras | C33: Résultat de bloc, chiffre clé | D33: Vous la lisez. C'est un chiffre à retenir.
B34: Bandeau bleu nuit | C34: Titre de section, en-tête de tableau | D34: Repère de navigation.
B35: Texte gris, à droite | C35: Commentaire d'aide, ordre de grandeur | D35: Une phrase par ligne pour savoir quoi saisir. Les ordres de grandeur viennent de Paramètres.
B36: Vert OK / rouge À CORRIGER | C36: Contrôle de cohérence | D36: Rouge : corrigez la saisie indiquée dans le commentaire. Tant qu'un contrôle est rouge, le Comparateur reste entièrement vide, éligibilité et revente comprises : le classeur préfère ne rien afficher plutôt qu'un chiffre faux. Le Pluriannuel, lui, continue d'afficher le détail des années.
B37: Les onglets sont protégés sans mot de passe pour éviter d'écraser une formule par erreur. Les cellules bleues restent modifiables et effaçables sans rien déverrouiller. Pour modifier une cellule blanche : onglet Révision, puis « Ôter la protection de la feuille ». Aucun mot de passe n'est demandé.
B39: LA MARCHE À SUIVRE, ÉTAPE PAR ÉTAPE
B40: Étape | C40: Où (onglet et plage) | D40: Ce que vous faites | E40: Pourquoi
B41: 0. L'exemple livré | C41: Hypothèses!C7, Hypothèses!C9:C11, Hypothèses!C16:C21, Hypothèses!C26:C29, Hypothèses!C36:C37, Hypothèses!C41:C43 (vos données) ; Hypothèses!C8, Hypothèses!C49:C57 (les listes et les options, à ajuster, jamais à effacer) | D41: Le classeur arrive rempli d'un exemple. Gardez-le pour vous repérer, ou effacez vos données de projet avant de saisir votre dossier : les cinq premières plages ci-contre. Vérifiez surtout les saisies secondaires qui n'ont pas de raison d'être chez vous : travaux (Hypothèses!C10), mobilier (Hypothèses!C11), CFE (Hypothèses!C18), honoraires comptables (Hypothèses!C19 et Hypothèses!C20), autres revenus fonciers (Hypothèses!C37), prix de revente forcé (Hypothèses!C43). N'effacez jamais le mode d'acquisition (C8) ni les options C49:C57 : ce sont des listes, elles n'ont pas de valeur vide, et le classeur cesse de calculer dès qu'il en manque une. Ajustez-les une par une, ou gardez les valeurs livrées : achat à titre onéreux, meublé classique, distribution Non, frais immobilisés, rénovation énergétique Non, CSG déductible Non, terrain 15 %, bâti 30 ans, travaux 15 ans, mobilier 7 ans. | E41: Une valeur résiduelle de l'exemple est l'erreur la plus probable d'un premier usage : 8 000 € de mobilier oubliés changent l'amortissement, la CFE et les cinq TRI. Pendant que vous effacez, les contrôles passent au rouge et le Comparateur se vide : c'est normal, tout revient dès que la saisie est complète. Les cellules bleues s'effacent avec la touche Suppr, sans rien déverrouiller.
B42: 1. Le bien | C42: Hypothèses!C7, Hypothèses!C9:C11, plus le mode d'acquisition en Hypothèses!C8 | D42: Prix net vendeur, mode d'acquisition (achat à titre onéreux, succession ou donation), frais d'acquisition (notaire et agence), travaux à l'acquisition, mobilier. Vérifiez que le contrôle du bloc affiche OK. | E42: Le coût total est ce que vous financez ; frais, travaux et mobilier n'ont pas le même sort fiscal selon le régime. Le mode d'acquisition, lui, ne joue qu'à la revente : le forfait de frais de 7,5 % du prix n'est ouvert qu'aux biens achetés à titre onéreux. Sur un bien reçu par succession ou par donation, seuls vos frais réels justifiés entrent dans le prix d'acquisition, et la plus-value imposable est plus élevée.
B43: 2. L'exploitation | C43: Hypothèses!C16:C21 | D43: Loyer annuel encaissé, charges déductibles hors intérêts, cotisation foncière des entreprises (CFE, due par les régimes meublés et par la SCI), honoraires comptables du LMNP réel et de la SCI, indexation annuelle. | E43: Les charges décaissées et les honoraires pèsent différemment : déduits au réel, pas au micro ; la CFE n'existe qu'en meublé. Remettez-la à 0 si vous ne comparez que des locations nues.
B44: 3. Le financement | C44: Hypothèses!C26:C29 | D44: Montant emprunté, taux nominal, durée en années entières, taux d'assurance sur capital initial. L'apport se calcule. Les cellules de taux sont déjà au format pourcentage : tapez 3,25 pour 3,25 %, ne convertissez pas vous-même en fraction. | E44: Les intérêts décroissants alimentent chaque année la base au réel ; l'annuité complète entre dans le flux en poche. Un taux positif inférieur au plancher de plausibilité de Paramètres passe le contrôle « Taux saisis en pourcentage » (Hypothèses!C61) au rouge.
B45: 4. Le foyer | C45: Hypothèses!C36:C37 | D45: Tranche marginale d'imposition (TMI) : le taux auquel un euro de revenu supplémentaire est imposé chez vous. À choisir dans la liste. Autres revenus fonciers nets du foyer (0 sinon). | E45: La TMI fait varier l'impôt de zéro à plusieurs milliers d'euros ; les autres revenus fonciers absorbent d'abord un déficit.
B46: 5. La détention et la revente | C46: Hypothèses!C41:C43 | D46: Durée de détention (1 à 30 ans), revalorisation annuelle du bien, et au besoin un prix de revente forcé. | E46: La revente décide souvent du classement : au LMNP réel les amortissements déjà déduits sont réintégrés dans la plus-value, à la SCI la plus-value se calcule sur la valeur nette comptable (le prix diminué des amortissements), et en direct les abattements pour durée de détention effacent progressivement la plus-value.
B47: 6. Les options | C47: Hypothèses!C49:C57 | D47: Type de meublé, distribution annuelle de la SCI, sort des frais d'acquisition, plafond majoré énergie, CSG déductible, part du terrain, durées d'amortissement. | E47: Chaque option est expliquée dans son commentaire et dans Méthode. Si vous ne savez pas, gardez la valeur livrée : les listes se relisent dans Paramètres (B33:E37), la part du terrain et les trois durées d'amortissement dans les repères de marché (Paramètres!C99:C106).
B48: 7. Lire le verdict | C48: Hypothèses!C62, Comparateur!C43, puis Comparateur!C34:G34 et Comparateur!C41 | D48: Vérifiez que « Saisies complètes et cohérentes » affiche OK, puis que « Classement sans ex aequo » affiche OK dans le Comparateur, et lisez enfin le total net, le TRI et le régime le plus favorable. | E48: Tant qu'un contrôle est rouge, le Comparateur reste vide : le classeur préfère ne rien afficher plutôt qu'un chiffre faux. Un ex aequo signalé en rouge veut dire que deux régimes sont à égalité parfaite et que le verdict désigne le premier par ordre de colonne.
B49: 8. Les barèmes et les repères | C49: Paramètres!C8:C23, C27:D29, B33:B37, C41:D70, B74:E83, C87:C109 | D49: Chaque janvier, après la loi de finances et la loi de financement de la sécurité sociale, comparez chaque barème à sa source et mettez à jour la date en Paramètres!C111 : elle alimente toutes les mentions « Vérifié le » et « Consulté le » du classeur. | E49: Un barème périmé fausse l'impôt sans prévenir. Toutes les formules pointent ici. Les repères de marché (Paramètres!C87:C109) suivent leur propre rythme, indiqué en colonne E : mensuel pour les taux de crédit, annuel pour l'assurance, les honoraires, la CFE, le terrain et les durées. Rafraîchissez les taux de crédit avant tout dossier engageant.
B51: EXEMPLE GUIDÉ
B52: Le fichier est livré avec un T2 ancien acheté 200 000 € net vendeur (le prix du bien seul, hors frais de notaire et hors honoraires d'agence), 16 000 € de frais d'acquisition, 5 000 € de travaux et 8 000 € de mobilier : coût total 229 000 € (Hypothèses!C12). Loué 13 200 € par an avec 3 100 € de charges, 400 € de CFE en meublé, 500 € de comptable au LMNP réel et 1 200 € à l'IS, indexés de 1 % par an. Financé par 200 000 € sur 20 ans à 3,25 % plus 0,34 % d'assurance : apport 29 000 € (Hypothèses!C30), mensualité 1 134,39 € (Hypothèses!C31), intérêts de la première année 6 393 € (Hypothèses!C32). TMI 30 %, pas d'autres revenus fonciers, détention 10 ans avec 1,5 % de revalorisation par an : prix de cession 232 108 € (Hypothèses!C45). Options laissées telles quelles (Hypothèses!C49:C57) : meublé classique, pas de distribution annuelle de la SCI, frais d'acquisition immobilisés avec le bâti, pas de plafond majoré énergie, CSG déductible ignorée, terrain à 15 % du prix, amortissements sur 30 ans pour le bâti, 15 ans pour les travaux et 7 ans pour le mobilier. Ce sont elles qui donnent 61 200 € d'amortissement du bâti sur dix ans (Pluriannuel!C19), et donc le zéro d'impôt du LMNP réel.
B53: Année 1 (Comparateur!C10:G10) : le micro-foncier paie 4 361 € d'impôt ; le réel foncier, grâce aux 5 000 € de travaux déduits, affiche un déficit hors intérêts imputé sur le revenu global et un impôt de -592 €, négatif, c'est-à-dire une économie d'impôt ; le micro-BIC paie 3 208 € (abattement de 50 % et prélèvements sociaux de 18,6 %, barèmes 2026) ; le LMNP réel et la SCI ne paient rien, l'amortissement absorbant tout le résultat. Le flux en poche de l'année 1 (Comparateur!C11:G11) est négatif partout, entre -8 554 € et -3 601 € : l'emprunt couvre 87 % du coût total de l'opération (200 000 € sur 229 000 €, Hypothèses!C26 et Hypothèses!C12), et chaque mensualité rembourse du capital, qui reste dans votre patrimoine.
B54: Sur dix ans (Comparateur!C15:G15), les flux cumulés vont de -82 887 € au micro-foncier à -46 675 € au LMNP réel. Le LMNP réel laisse 35 295 € d'amortissements différés non consommés (Comparateur!C16:G16) et la SCI 42 619 € de déficit reportable : ni l'un ni l'autre n'a payé d'impôt pendant la détention.
B55: À la revente (Comparateur, lignes 20 à 31) : en location nue, le prix d'acquisition majoré des forfaits de frais (7,5 %) et de travaux (15 %), soit 246 000 € (Comparateur!C21:G21), dépasse le prix de cession, aucune plus-value. Au LMNP réel, les 33 908 € d'amortissements déduits sur l'immeuble sont réintégrés (Comparateur!F22, détail en Pluriannuel!C64) : plus-value 20 016 € (Comparateur!F23), impôt 5 821 € après abattements de dix ans (Comparateur!F30). À l'IS, la plus-value sur valeur nette comptable atteint 75 641 € (Comparateur!G23) ; après imputation du déficit reportable, IS et PFU sur le boni de liquidation, l'impôt de sortie est de 13 767 € (Comparateur!G30).
B56: La surtaxe sur les plus-values élevées (Comparateur!C25:G25) est nulle sur ce dossier : la plus-value imposable à l'impôt sur le revenu la plus forte, celle du LMNP réel, ne fait que 14 011 € (Comparateur!F24), loin des 50 000 € au-delà desquels la taxe est due. Pour la voir apparaître, forcez le prix de revente à 400 000 € en Hypothèses!C43 : la plus-value imposable à l'impôt sur le revenu passe à 107 800 € en location nue et la surtaxe à 3 014 €, contre 3 946 € au LMNP réel sur 131 535 € de plus-value imposable. Elle s'ajoute aux 19 % d'impôt sur le revenu et aux 17,2 % de prélèvements sociaux. La colonne « SCI à l'IS » reste vide sur cette ligne : cette taxe ne vise que les plus-values des particuliers, pas celles d'une société à l'impôt sur les sociétés.
B57: Bilan (Comparateur!C34:G34) : le micro-foncier est « Éligible » (le loyer indexé reste sous le plafond du micro-foncier, 15 000 € en 2026 ; il perd faute de charges déductibles : 33 134 €) ; le réel foncier totalise 58 762 €, le micro-BIC 41 019 €, le LMNP réel 63 526 €, la SCI à l'IS 48 256 €. Régime le plus favorable (Comparateur!C41) : « Meublé, LMNP réel », avec 4 763 € d'avance sur le suivant. TRI après impôt (Comparateur!C36:G36) : 5,50 % au LMNP réel contre 4,70 % au réel foncier et 3,17 % à l'IS.
B58: Comment le lire : sur dix ans, l'amortissement du LMNP réel vaut plus que son coût de sortie, et la SCI paie sa comptabilité, sa plus-value sur VNC et le PFU sans avoir eu de bénéfice à distribuer. Passez la détention (Hypothèses!C41) à 25 ans : les abattements de durée effacent l'essentiel de la plus-value des particuliers, la réintégration LMNP pèse davantage, et l'IS se rapproche. Mettez la distribution (Hypothèses!C50) sur Oui : la SCI rembourse d'abord le compte courant, sans impôt.
B60: LES CHIFFRES À REGARDER, ET CE QU'ILS VALENT
B61: Indicateur | C61: Où | D61: Repère métier | E61: Ce qu'il dit vraiment
B62: Total net en poche après revente | C62: Comparateur!C34:G34 | D62: L'écart entre deux régimes se juge en euros sur toute la durée : tant qu'il reste sous le coût cumulé d'une comptabilité ou d'une structure sur la même durée (honoraires annuels en Paramètres!C93:C96), il ne tranche rien. | E62: Le chiffre qui classe. Additionne les flux en poche et le net de revente ; ne dépend pas de l'apport.
B63: TRI après impôt | C63: Comparateur!C36:G36 | D63: Ancien loué à crédit : le TRI après impôt sur dix ans se situe le plus souvent dans la fourchette des repères de marché (Paramètres!C107 et C108, soit 3 % à 7 % en 2026). Au-dessus, vérifiez la revalorisation saisie en Hypothèses!C42. | E63: Rendement annuel de votre apport, revente comprise (taux de rendement interne). Sensible à l'apport et au prix de cession.
B64: Impôt de l'année 1 | C64: Comparateur!C10:G10 | D64: 0 € en LMNP réel et à l'IS est normal les premières années. Négatif au réel foncier avec travaux. | E64: À ne jamais lire seul : l'année 1 est la meilleure du réel foncier et la plus flatteuse du LMNP.
B65: Reports non consommés | C65: Comparateur!C16:G16 | D65: Un stock d'amortissements différés qui grossit chaque année signifie que le LMNP réel n'utilise pas tout son avantage. | E65: Ce que vous emportez dans les années suivantes, ou perdez à la revente.
B66: Impôt total à la revente | C66: Comparateur!C30:G30 | D66: Au LMNP réel, il grossit avec les amortissements déduits ; à l'IS, il est presque toujours le plus lourd. | E66: La contrepartie différée des régimes à amortissement. Le montant réintégré dans la plus-value du LMNP réel se lit juste au-dessus, en Comparateur!F22. Trois lignes le décomposent : la plus-value imposable à l'impôt sur le revenu (Comparateur!C24:G24), la surtaxe sur les plus-values élevées (Comparateur!C25:G25) et, pour la SCI seule, l'IS de cession (Comparateur!G26).
B67: Trésorerie restant en société | C67: Comparateur!G17 | D67: Sans distribution, elle grossit ; ce n'est pas un revenu. | E67: Ce que la SCI garde et qui sera imposé au prélèvement forfaitaire unique (PFU, 31,4 % en 2026) le jour où il sortira vers votre compte personnel.
B69: LES DONNÉES À METTRE À JOUR, OÙ ET POURQUOI
B70: Deux familles de données. Les benchmarks (barèmes fiscaux, plafonds, abattements de durée, repères de marché) changent avec la loi ou le marché, à date fixe, et se rafraîchissent depuis une source indiquée dans Paramètres. Les données de projet (prix, loyer, charges, financement, foyer, durée, options) sont propres à chaque dossier. L'architecture du classeur ne change pas quand les données changent : seules les cellules bleues bougent.
B71: Les chiffres cités dans ce guide sont ceux du millésime 2026 : à chaque mise à jour d'une valeur de Paramètres, relisez les lignes du guide qui la citent, c'est-à-dire l'exemple guidé, le tableau ci-dessous et les erreurs qui faussent tout. Le guide est en texte : il ne se met pas à jour tout seul quand un barème bouge.
B72: Paramètre | C72: Onglet et cellule | D72: Ce qu'il pilote | E72: Source à consulter, fréquence
B73: Prélèvements sociaux 2026 (17,2 % en nu, 18,6 % en meublé) et CSG déductible | C73: Paramètres!C8:C10 | D73: Impôt annuel des quatre régimes à l'IR | E73: LFSS, chaque décembre
B74: Abattement et plafond du micro-foncier, plafonds du déficit foncier (barèmes 2026) | C74: Paramètres!C11:C14 | D74: Base du micro-foncier, éligibilité, économie d'impôt du réel foncier | E74: CGI art. 32 et 156 ; BOFiP BOI-RFPI-BASE-30-20 ; chaque loi de finances. Le plafond majoré à 21 400 € ne vaut que pour des travaux de rénovation énergétique payés au plus tard le 31 décembre 2025 : il ne s'applique plus à une dépense de 2026
B75: IS 2026 (15 % jusqu'à 42 500 €, puis 25 %) et PFU 2026 (31,4 %) | C75: Paramètres!C15:C18 | D75: Impôt de la SCI et de l'associé | E75: CGI art. 219 et 200 A, LF et LFSS
B76: Plus-value des particuliers 2026 (19 %, 17,2 %, forfait frais 7,5 %, forfait travaux 15 % au-delà de cinq ans de détention) | C76: Paramètres!C19:C23 | D76: Impôt de revente en nu et en LMNP | E76: CGI art. 150 VB, 200 B ; loi de finances
B77: Types de meublé 2026 (abattement 50 % ou 30 %, plafond 83 600 € ou 15 000 €) | C77: Paramètres!C27:D29 | D77: Base et éligibilité du micro-BIC | E77: CGI art. 50-0 ; plafond revalorisé tous les trois ans
B78: Abattements pour durée de détention | C78: Paramètres!C41:D70 | D78: Impôt de revente en nu et en LMNP | E78: CGI art. 150 VC, stable depuis 2014
B79: Barème des TMI | C79: Paramètres!B33:B37 | D79: Liste déroulante de la TMI | E79: CGI art. 197, chaque loi de finances
B80: Repères de marché 2026 (taux, assurance, honoraires, CFE, terrain, durées, fourchette de TRI, plancher de plausibilité des taux) | C80: Paramètres!C87:C109 | D80: Les ordres de grandeur affichés dans les commentaires des Hypothèses, et le contrôle des taux saisis | E80: Observatoire Crédit Logement (mensuel), baromètres et tarifs (annuel), colonne E de Paramètres
B81: Barème de la surtaxe sur les plus-values élevées (10 lignes, cinq tranches et leur lissage) | C81: Paramètres!B74:E83 | D81: Impôt de revente en location nue et en LMNP au-delà de 50 000 € de plus-value imposable à l'impôt sur le revenu | E81: CGI art. 1609 nonies G ; BOFiP BOI-RFPI-TPVIE-10 et 20 ; chaque loi de finances
B82: Données de projet | C82: Hypothèses!C7, Hypothèses!C9:C11, Hypothèses!C16:C21, Hypothèses!C26:C29, Hypothèses!C36:C37, Hypothèses!C41:C43, Hypothèses!C8, Hypothèses!C49:C57 | D82: Tout le reste | E82: Propres à chaque dossier
B84: TROIS FAÇONS DE S'EN SERVIR
B85: Votre situation | C85: Ce que vous faites
B86: Vous hésitez entre louer nu ou meublé | C86: Saisissez le bien avec le loyer nu et lisez le total net des colonnes nues (Comparateur!C34:D34). Remplacez le loyer (Hypothèses!C16) par le loyer meublé, saisissez le mobilier, la CFE et le comptable, et lisez les colonnes meublées. La différence est le prix réel du meublé, comptabilité et revente comprises.
B87: Un client vous demande s'il faut créer une SCI à l'IS | C87: Saisissez son dossier, mettez la distribution (Hypothèses!C50) sur Non puis sur Oui, et comparez la colonne SCI aux autres sur sa durée de détention réelle. Regardez la trésorerie bloquée (Comparateur!G17) et l'impôt de revente (Comparateur!C30:G30) : c'est là que l'IS se paie. Si l'écart avec le LMNP réel est inférieur aux honoraires de la société sur la durée, la SCI ne se justifie pas fiscalement.
B88: Vous préparez une revente et voulez chiffrer la note du LMNP | C88: Saisissez la durée déjà courue en Hypothèses!C41, le prix de marché en Hypothèses!C43, puis lisez, dans la colonne « Meublé, LMNP réel » : les amortissements réintégrés dans la plus-value (Comparateur!F22, détail annuel en Pluriannuel!C64), le prix d'acquisition ramené à ce qu'il en reste (Comparateur!F21), la plus-value imposable (Comparateur!F23) et l'impôt de cession (Comparateur!F30). Comparez avec les colonnes nues (Comparateur!C30:D30) : la différence est le coût différé de l'amortissement.
B90: LES ERREURS QUI FAUSSENT TOUT
B91: Le piège | C91: Le dégât
B92: Saisir le prix frais inclus en Hypothèses!C7 et les frais à nouveau en Hypothèses!C9 | C92: Frais comptés deux fois. Sur l'exemple, saisir 216 000 € en C7 en gardant 16 000 € en C9 porte le coût total de 229 000 € à 245 000 € et l'apport de 29 000 € à 45 000 € (Hypothèses!C30), et le prix d'acquisition retenu à la revente de 246 000 € à 264 600 € (Comparateur!C21). Les cinq TRI, qui partent tous du même apport, ne veulent plus rien dire, et l'impôt de sortie est sous-évalué.
B93: Saisir un taux en fraction décimale au lieu du pourcentage (0,0325 au lieu de 3,25 en Hypothèses!C27 ; même piège en C21, C29, C42 et C54) | C93: Les cellules de taux sont au format pourcentage : tapez 3,25 et la cellule affiche 3,25 %. Ne convertissez pas vous-même en fraction. Tapez 0,0325 et la cellule affiche 0,03 % : sur l'exemple, la mensualité tombe de 1 134,39 € à 836,06 € et les intérêts de la première année de 6 393 € à 64 €, et le réel foncier comme le LMNP réel deviennent faussement bénéficiaires. Le contrôle « Taux saisis en pourcentage » (Hypothèses!C61) passe au rouge et le Comparateur se vide. La TMI, elle, se choisit dans une liste ; une valeur hors liste passe le contrôle du foyer (Hypothèses!C38) au rouge, c'est voulu.
B94: Laisser le mobilier de l'exemple (Hypothèses!C11) alors que vous ne comparez que des locations nues | C94: 8 000 € de mobilier gonflent d'autant le coût total et l'apport (Hypothèses!C12 et Hypothèses!C30) : les cinq TRI sont faussés, y compris ceux des colonnes nues, puisqu'ils partent tous du même apport. Le LMNP réel et la SCI amortissent en plus un mobilier qui n'existe pas. Pensez aussi à remettre la CFE (Hypothèses!C18) à 0 : elle se saisit à part et ne dépend pas du mobilier.
B95: Oublier les autres revenus fonciers (Hypothèses!C37) quand on a déjà des biens nus | C95: Le déficit foncier est imputé sur le revenu global, où il ne rapporte que la TMI (30 % dans l'exemple), au lieu d'être absorbé par vos autres loyers, où il rapporte la TMI plus les prélèvements sociaux (47,20 % avec les taux 2026). L'économie d'impôt de l'année 1 du réel foncier est sous-estimée d'environ 17 points du déficit.
B96: Croire que le classeur teste les plafonds des régimes micro au niveau de votre foyer | C96: L'éligibilité (Comparateur!C8:G8) ne teste que le loyer de ce bien, en année 1 et en dernière année indexation comprise, contre Paramètres!C12 pour le micro-foncier et Paramètres!D27:D29 pour le micro-BIC selon le type de meublé. Jamais vos autres loyers. Si vous louez déjà nu, additionnez vos loyers bruts de tête : au-delà du plafond du micro-foncier (15 000 € en 2026), la colonne « Location nue, micro-foncier » ne vous concerne pas, même si le classeur l'affiche « Éligible ». Saisir vos autres revenus fonciers en Hypothèses!C37 ne corrige pas ce test. Au-delà d'un plafond, en revanche, la colonne affiche « Non éligible », son total net ne s'affiche plus et elle sort du classement : c'est voulu, le régime réel devient obligatoire. Sur l'exemple, le micro-foncier arrive dernier, à 30 392 € du régime gagnant (Comparateur!C37) : dans un autre dossier il peut arriver en tête, et l'arbitrage se ferait alors sur un régime qui vous est fermé.
B97: Prendre le résultat de l'année 1 pour un régime de croisière (Comparateur!C10:G10) | C97: Le réel foncier avec travaux et le LMNP réel gagnent toujours l'année 1. Sur l'exemple, le réel foncier rend 592 € d'impôt en année 1, et en paie 20 000 € sur dix ans (Comparateur!D14). Les intérêts baissent, l'amortissement du mobilier s'éteint au terme de la durée saisie (Hypothèses!C57, 7 ans dans l'exemple), et la revente rend l'impôt différé : 5 821 € au LMNP réel, 13 767 € à l'IS.
B98: Laisser « Achat (à titre onéreux) » en Hypothèses!C8 pour un bien reçu par succession ou par donation | C98: Le forfait de frais d'acquisition de 7,5 % du prix est réservé aux biens achetés à titre onéreux. Sur un bien reçu, seuls vos frais réels comptent, et ils sont souvent bien inférieurs au forfait. Sur l'exemple, avec 8 000 € de frais d'acte de succession, laisser « Achat (à titre onéreux) » porte le prix d'acquisition retenu de 238 000 € à 245 000 € (Comparateur!C21) et fait disparaître 2 036 € d'impôt de revente au LMNP réel (Comparateur!F30). L'arbitrage se fait alors sur un impôt de sortie sous-évalué, et le régime qui amortit le plus en sort flatté.
B99: Oublier la surtaxe en comparant deux régimes sur une grosse plus-value (Comparateur!C25:G25) | C99: La surtaxe de 2 à 6 % au-delà de 50 000 € de plus-value imposable à l'impôt sur le revenu ne frappe pas les cinq colonnes de la même façon : elle épargne la SCI à l'impôt sur les sociétés, dont la plus-value est professionnelle, et elle pèse plus lourd au LMNP réel, dont les amortissements réintégrés gonflent la plus-value. Sur l'exemple porté à 400 000 € de prix de revente forcé, elle vaut 3 014 € en location nue et 3 946 € au LMNP réel, et rien à l'IS. Un comparateur qui l'ignore pousse vers le régime à amortissement pour une raison qui n'existe pas.
B100: Confondre le flux en poche de la SCI avec sa trésorerie (Comparateur!G17) | C100: Sans distribution (Hypothèses!C50 sur Non), l'associé ne perçoit rien : la trésorerie de la société n'est pas un revenu, elle sera imposée au prélèvement forfaitaire unique le jour où elle sortira. Sur l'exemple, elle reste à 0 € parce que l'associé remet chaque année de l'argent en compte courant : c'est ce compte courant (82 998 € en Pluriannuel!C88), et non un revenu, qui lui revient à la revente.
B102: Ce que le classeur ne fait pas, les points de droit signalés et les sources de ses chiffres : voir l'onglet Méthode.
B104: CorpusImmo, millésime 2026. Modèle d'aide à la décision : ne constitue ni un conseil en investissement, ni un conseil fiscal, ni une expertise au sens de la charte de l'expertise en évaluation immobilière. Vérifiez les paramètres avant tout engagement.

Sheet Hypothèses
B1: CorpusImmo · corpus.immo · Estimer, comparer, décider. Sur les ventes réelles.
B2: Arbitrage fiscal : nu, LMNP ou SCI à l'IS
B3: Le même bien sous cinq régimes, sur toute la durée de détention, revente comprise. Saisissez ici, lisez le Comparateur.
B5: Cellules bleues : à remplir. Cellules blanches : calculées automatiquement.
B6: LE BIEN
B7: Prix net vendeur | C7: 200000 | D7: Hors frais de notaire et hors honoraires d'agence. Bien reçu : la valeur retenue pour les droits de mutation à titre gratuit.
B8: Comment le bien a été acquis | C8: Achat (à titre onéreux) | D8: Achat : le forfait de frais de 7,5 % du prix est possible à la revente, et le classeur retient le plus élevé du forfait et de vos frais réels. Succession ou donation : le forfait est fermé, seuls les frais réels ci-dessous comptent.
B9: Frais d'acquisition (notaire et agence) | C9: 16000 | D9: ="Notaire dans l'ancien : "&ROUND(Paramètres!$C$91*100,1)&" %"&" à "&ROUND(Paramètres!$C$92*100,1)&" %"&" du prix (Paramètres, repères), plus l'agence si elle est à votre charge." -> Notaire dans l'ancien : 7,5 % à 8,5 % du prix (Paramètres, repères), plus l'agence si elle est à votre charge.
B10: Travaux à l'acquisition | C10: 5000 | D10: Déduits l'année 1 au réel foncier (déficit foncier), amortis au LMNP réel et à l'IS. 0 si aucun.
B11: Mobilier et équipements | C11: 8000 | D11: Justifié par factures. Amorti au LMNP réel et à l'IS. 0 si vous ne comparez que des locations nues.
B12: Coût total de l'opération | C12: =Hypothèses!$C$7+Hypothèses!$C$9+Hypothèses!$C$10+Hypothèses!$C$11 -> 229000 | D12: Ce que vous devez financer : prix, frais, travaux, mobilier.
B13: Le bien : saisies cohérentes | C13: =IF(AND(AND(ISNUMBER(Hypothèses!$C$7),Hypothèses!$C$7>=0),Hypothèses!$C$7>0,OR(Hypothèses!$C$9="",AND(ISNUMBER(Hypothèses!$C$9),Hypothèses!$C$9>=0)),OR(Hypothèses!$C$10="",AND(ISNUMBER(Hypothèses!$C$10),Hypothèses!$C$10>=0)),OR(Hypothèses!$C$11="",AND(ISNUMBER(Hypothèses!$C$11),Hypothèses!$C$11>=0)),NOT(ISNA(MATCH(Hypothèses!$C$8,Paramètres!$E$33:$E$35,0)))),"OK","À CORRIGER") -> OK | D13: KO si le prix manque, si une saisie est négative ou n'est pas un nombre, ou si le mode d'acquisition n'est pas une valeur de sa liste.
B15: L'EXPLOITATION
B16: Loyer annuel encaissé, année 1 | C16: 13200 | D16: Hors charges récupérables, net de vacance. Le même loyer sert aux cinq régimes (voir Méthode).
B17: Charges annuelles déductibles hors intérêts, année 1 | C17: 3100 | D17: Taxe foncière hors TEOM, PNO, copropriété non récupérable, gestion, entretien courant.
B18: CFE annuelle (régimes meublés) | C18: 400 | D18: ="Base minimum 2026 : "&IF(Paramètres!$C$97>=1000,INT(Paramètres!$C$97/1000)&" "&TEXT(MOD(Paramètres!$C$97,1000),"000"),TEXT(Paramètres!$C$97,"0"))&" €"&" à "&IF(Paramètres!$C$98>=1000,INT(Paramètres!$C$98/1000)&" "&TEXT(MOD(Paramètres!$C$98,1000),"000"),TEXT(Paramètres!$C$98,"0"))&" €"&" selon la commune (Paramètres, repères). Exonérée l'année de création." -> Base minimum 2026 : 247 € à 1 179 € selon la commune (Paramètres, repères). Exonérée l'année de création.
B19: Honoraires comptables annuels, LMNP réel | C19: 500 | D19: ="Ordre de grandeur : "&IF(Paramètres!$C$93>=1000,INT(Paramètres!$C$93/1000)&" "&TEXT(MOD(Paramètres!$C$93,1000),"000"),TEXT(Paramètres!$C$93,"0"))&" €"&" à "&IF(Paramètres!$C$94>=1000,INT(Paramètres!$C$94/1000)&" "&TEXT(MOD(Paramètres!$C$94,1000),"000"),TEXT(Paramètres!$C$94,"0"))&" €"&" TTC par an (Paramètres, repères). Déduits au LMNP réel seulement." -> Ordre de grandeur : 300 € à 900 € TTC par an (Paramètres, repères). Déduits au LMNP réel seulement.
B20: Honoraires comptables annuels, SCI à l'IS | C20: 1200 | D20: ="Ordre de grandeur : "&IF(Paramètres!$C$95>=1000,INT(Paramètres!$C$95/1000)&" "&TEXT(MOD(Paramètres!$C$95,1000),"000"),TEXT(Paramètres!$C$95,"0"))&" €"&" à "&IF(Paramètres!$C$96>=1000,INT(Paramètres!$C$96/1000)&" "&TEXT(MOD(Paramètres!$C$96,1000),"000"),TEXT(Paramètres!$C$96,"0"))&" €"&" HT par an (Paramètres, repères). Déduits à l'IS seulement." -> Ordre de grandeur : 1 200 € à 2 500 € HT par an (Paramètres, repères). Déduits à l'IS seulement.
B21: Indexation annuelle des loyers et des charges | C21: 0.01 | D21: Appliquée à partir de l'année 2 au loyer, aux charges, à la CFE et aux honoraires. 0 pour raisonner en euros constants.
B22: Loyer moins charges, année 1 (avant intérêts et impôt) | C22: =Hypothèses!$C$16-Hypothèses!$C$17 -> 10100 | D22: Le résultat d'exploitation avant financement, commun aux cinq régimes.
B23: L'exploitation : saisies cohérentes | C23: =IF(AND(AND(ISNUMBER(Hypothèses!$C$16),Hypothèses!$C$16>=0),Hypothèses!$C$16>0,OR(Hypothèses!$C$17="",AND(ISNUMBER(Hypothèses!$C$17),Hypothèses!$C$17>=0)),OR(Hypothèses!$C$18="",AND(ISNUMBER(Hypothèses!$C$18),Hypothèses!$C$18>=0)),OR(Hypothèses!$C$19="",AND(ISNUMBER(Hypothèses!$C$19),Hypothèses!$C$19>=0)),OR(Hypothèses!$C$20="",AND(ISNUMBER(Hypothèses!$C$20),Hypothèses!$C$20>=0)),OR(Hypothèses!$C$21="",AND(ISNUMBER(Hypothèses!$C$21),Hypothèses!$C$21>=-0.05,Hypothèses!$C$21<=0.1))),"OK","À CORRIGER") -> OK | D23: KO si le loyer manque, si une charge est négative ou si l'indexation sort de la plage admise (de moins 5 % à 10 %).
B25: LE FINANCEMENT
B26: Montant emprunté | C26: 200000 | D26: 0 pour un achat comptant. Au plus le coût total. L'apport est la différence.
B27: Taux du prêt (hors assurance) | C27: 0.0325 | D27: ="Taux nominal annuel. Repère : "&ROUND(Paramètres!$C$87*100,2)&" %"&" à "&ROUND(Paramètres!$C$88*100,2)&" %"&" de 20 à 25 ans (Paramètres, repères). Tapez 3,25 pour 3,25 % : la cellule est déjà au format pourcentage, ne convertissez pas en fraction." -> Taux nominal annuel. Repère : 3,27 % à 3,35 % de 20 à 25 ans (Paramètres, repères). Tapez 3,25 pour 3,25 % : la cellule est déjà au format pourcentage, ne convertissez pas en fraction.
B28: Durée du prêt | C28: 20 | D28: Années entières, de 1 à 30. Vide si aucun emprunt.
B29: Taux d'assurance emprunteur (sur capital initial) | C29: 0.0034 | D29: ="Repère : "&ROUND(Paramètres!$C$90*100,2)&" %"&" à "&ROUND(Paramètres!$C$89*100,2)&" %"&" par an (Paramètres, repères). Déductible comme les intérêts." -> Repère : 0,17 % à 0,36 % par an (Paramètres, repères). Déductible comme les intérêts.
B30: Apport personnel | C30: =Hypothèses!$C$12-Hypothèses!$C$26 -> 29000 | D30: Coût total moins emprunt. À l'IS, il est placé en compte courant d'associé, remboursable sans impôt.
B31: Mensualité du prêt (capital et intérêts) | C31: =IF(AND(Hypothèses!$C$33="OK",Hypothèses!$C$26>0),IF(Hypothèses!$C$27=0,Hypothèses!$C$26/(Hypothèses!$C$28*12),-PMT(Hypothèses!$C$27/12,Hypothèses!$C$28*12,Hypothèses!$C$26)),0) -> 1134.3915 | D31: Annuité constante, taux nominal divisé par 12. Assurance en plus.
B32: Intérêts de la première année | C32: =Pluriannuel!$D$14 -> 6393.0881 | D32: Somme des douze premières échéances. Ils baissent ensuite chaque année (onglet Pluriannuel).
B33: Le financement : saisies cohérentes | C33: =IF(AND(OR(Hypothèses!$C$26="",AND(ISNUMBER(Hypothèses!$C$26),Hypothèses!$C$26>=0,Hypothèses!$C$26<=Hypothèses!$C$12)),OR(Hypothèses!$C$27="",AND(ISNUMBER(Hypothèses!$C$27),Hypothèses!$C$27>=0,Hypothèses!$C$27<=0.2)),OR(Hypothèses!$C$29="",AND(ISNUMBER(Hypothèses!$C$29),Hypothèses!$C$29>=0,Hypothèses!$C$29<=0.05)),OR(Hypothèses!$C$28="",AND(ISNUMBER(Hypothèses!$C$28),Hypothèses!$C$28>=1,Hypothèses!$C$28<=30,Hypothèses!$C$28=INT(Hypothèses!$C$28))),OR(Hypothèses!$C$26=0,ISNUMBER(Hypothèses!$C$28))),"OK","À CORRIGER") -> OK | D33: KO si l'emprunt dépasse le coût total, si la durée manque ou n'est pas entière, ou si un taux sort de la plage admise.
B35: LE FOYER FISCAL
B36: Tranche marginale d'imposition (TMI) | C36: 0.3 | D36: Taux de la tranche la plus haute de votre foyer, après les revenus de ce bien : 0, 11, 30, 41 ou 45 %.
B37: Autres revenus fonciers nets annuels du foyer | C37: 0 | D37: Revenus nets des autres biens loués nus. Ils absorbent d'abord un déficit foncier et les reports. 0 sinon.
B38: Le foyer : saisies cohérentes | C38: =IF(AND(ISNUMBER(Hypothèses!$C$36),NOT(ISNA(MATCH(Hypothèses!$C$36,Paramètres!$B$33:$B$37,0))),OR(Hypothèses!$C$37="",AND(ISNUMBER(Hypothèses!$C$37),Hypothèses!$C$37>=0))),"OK","À CORRIGER") -> OK | D38: KO si la TMI n'est pas une valeur de la liste ou si les autres revenus fonciers sont négatifs.
B40: LA DÉTENTION ET LA REVENTE
B41: Durée de détention | C41: 10 | D41: Années entières, de 1 à 30. La revente a lieu à la fin de cette année. 10 ans par défaut.
B42: Revalorisation annuelle du bien | C42: 0.015 | D42: Hausse de prix annuelle jusqu'à la revente. 0 pour une revente au prix d'achat. De moins 10 % à 20 %.
B43: Prix de revente forcé (facultatif) | D43: Vide : le prix de cession vient de la revalorisation. Un montant saisi la remplace.
B44: Durée retenue pour les calculs | C44: =IF(AND(ISNUMBER(Hypothèses!$C$41),Hypothèses!$C$41>=1,Hypothèses!$C$41<=30,Hypothèses!$C$41=INT(Hypothèses!$C$41)),Hypothèses!$C$41,1) -> 10 | D44: La durée saisie si elle est valide, sinon 1 an et le contrôle passe au rouge.
B45: Prix de cession retenu | C45: =IF(AND(ISNUMBER(Hypothèses!$C$43),Hypothèses!$C$43>0),Hypothèses!$C$43,Hypothèses!$C$7*(1+Hypothèses!$C$42)^Hypothèses!$C$44) -> 232108.17 | D45: Prix net vendeur revalorisé sur la durée, ou prix forcé.
B46: La détention : saisies cohérentes | C46: =IF(AND(AND(ISNUMBER(Hypothèses!$C$41),Hypothèses!$C$41>=1,Hypothèses!$C$41<=30,Hypothèses!$C$41=INT(Hypothèses!$C$41)),OR(Hypothèses!$C$42="",AND(ISNUMBER(Hypothèses!$C$42),Hypothèses!$C$42>=-0.1,Hypothèses!$C$42<=0.2)),OR(Hypothèses!$C$43="",AND(ISNUMBER(Hypothèses!$C$43),Hypothèses!$C$43>=0))),"OK","À CORRIGER") -> OK | D46: KO si la durée n'est pas entière entre 1 et 30, si la revalorisation sort de la plage ou si le prix forcé est négatif.
B48: LES OPTIONS
B49: Type de meublé (régime micro-BIC) | C49: Meublé classique (bail d'habitation, étudiant, mobilité) | D49: Choisir dans la liste. Fixe l'abattement et le plafond du micro-BIC (Paramètres).
B50: SCI à l'IS : distribution annuelle | C50: Non | D50: Oui : chaque année, la trésorerie rembourse d'abord le compte courant, puis distribue les dividendes possibles. Non : tout reste en société jusqu'à la revente.
B51: Frais d'acquisition au LMNP réel et à l'IS | C51: Immobilisés (amortis avec le bâti) | D51: Option comptable irrévocable : immobilisés avec le bâti, ou déduits en charges l'année 1 (déficit reportable).
B52: Travaux de rénovation énergétique (plafond majoré du déficit foncier) | C52: Non | D52: Oui seulement si les travaux font passer le DPE de E, F ou G à A, B, C ou D et ont été payés entre le 01/01/2023 et le 31/12/2025, sur un devis accepté à compter du 05/11/2022. Une dépense payée en 2026 n'ouvre plus droit au plafond majoré : laissez Non.
B53: Tenir compte de la CSG déductible | C53: Non | D53: Oui : économie d'impôt l'année suivante sur 6,8 points de CSG, régimes au barème. Non : ignorée (prudent).
B54: Part du terrain dans le prix (non amortissable) | C54: 0.15 | D54: ="Usage : "&ROUND(Paramètres!$C$99*100,0)&" %"&" à "&ROUND(Paramètres!$C$100*100,0)&" %"&" pour un appartement (Paramètres, repères). À justifier par comparaison. Au plus 50 %." -> Usage : 10 % à 20 % pour un appartement (Paramètres, repères). À justifier par comparaison. Au plus 50 %.
B55: Durée d'amortissement du bâti | C55: 30 | D55: ="Durée moyenne pondérée des composants. Usage : "&Paramètres!$C$101&" à "&Paramètres!$C$102&" ans (Paramètres, repères)." -> Durée moyenne pondérée des composants. Usage : 25 à 40 ans (Paramètres, repères).
B56: Durée d'amortissement des travaux | C56: 15 | D56: ="Usage : "&Paramètres!$C$103&" à "&Paramètres!$C$104&" ans selon la nature (Paramètres, repères)." -> Usage : 10 à 20 ans selon la nature (Paramètres, repères).
B57: Durée d'amortissement du mobilier | C57: 7 | D57: ="Usage : "&Paramètres!$C$105&" à "&Paramètres!$C$106&" ans (Paramètres, repères)." -> Usage : 5 à 10 ans (Paramètres, repères).
B58: Les options : saisies cohérentes | C58: =IF(AND(NOT(ISNA(MATCH(Hypothèses!$C$49,Paramètres!$B$27:$B$29,0))),NOT(ISNA(MATCH(Hypothèses!$C$50,Paramètres!$C$33:$C$34,0))),NOT(ISNA(MATCH(Hypothèses!$C$51,Paramètres!$D$33:$D$34,0))),NOT(ISNA(MATCH(Hypothèses!$C$52,Paramètres!$C$33:$C$34,0))),NOT(ISNA(MATCH(Hypothèses!$C$53,Paramètres!$C$33:$C$34,0))),OR(Hypothèses!$C$54="",AND(ISNUMBER(Hypothèses!$C$54),Hypothèses!$C$54>=0,Hypothèses!$C$54<=0.5)),AND(ISNUMBER(Hypothèses!$C$55),Hypothèses!$C$55>=1,Hypothèses!$C$55<=100,Hypothèses!$C$55=INT(Hypothèses!$C$55)),AND(ISNUMBER(Hypothèses!$C$56),Hypothèses!$C$56>=1,Hypothèses!$C$56<=100,Hypothèses!$C$56=INT(Hypothèses!$C$56)),AND(ISNUMBER(Hypothèses!$C$57),Hypothèses!$C$57>=1,Hypothèses!$C$57<=100,Hypothèses!$C$57=INT(Hypothèses!$C$57))),"OK","À CORRIGER") -> OK | D58: KO si une option n'est pas une valeur de sa liste, si la part du terrain dépasse 50 % ou si une durée d'amortissement manque.
B60: CONTRÔLE GÉNÉRAL ET VERDICT
B61: Taux saisis en pourcentage | C61: =IF(AND(ISNUMBER(Paramètres!$C$109),OR(NOT(ISNUMBER(Hypothèses!$C$21)),Hypothèses!$C$21<=0,Hypothèses!$C$21>=Paramètres!$C$109),OR(NOT(ISNUMBER(Hypothèses!$C$27)),Hypothèses!$C$27<=0,Hypothèses!$C$27>=Paramètres!$C$109),OR(NOT(ISNUMBER(Hypothèses!$C$29)),Hypothèses!$C$29<=0,Hypothèses!$C$29>=Paramètres!$C$109),OR(NOT(ISNUMBER(Hypothèses!$C$42)),Hypothèses!$C$42<=0,Hypothèses!$C$42>=Paramètres!$C$109),OR(NOT(ISNUMBER(Hypothèses!$C$54)),Hypothèses!$C$54<=0,Hypothèses!$C$54>=Paramètres!$C$109)),"OK","À CORRIGER") -> OK | D61: ="KO si l’un des cinq taux (indexation, taux du prêt, assurance, revalorisation, part du terrain) est strictement positif et inférieur au plancher de plausibilité de Paramètres ("&ROUND(Paramètres!$C$109*100,2)&" %"&") : un tel taux trahit une saisie en fraction, comme 0,0325 tapé pour 3,25 %." -> KO si l’un des cinq taux (indexation, taux du prêt, assurance, revalorisation, part du terrain) est strictement positif et inférieur au plancher de plausibilité de Paramètres (0,1 %) : un tel taux trahit une saisie en fraction, comme 0,0325 tapé pour 3,25 %.
B62: Saisies complètes et cohérentes | C62: =IF(AND(Hypothèses!$C$13="OK",Hypothèses!$C$23="OK",Hypothèses!$C$33="OK",Hypothèses!$C$38="OK",Hypothèses!$C$46="OK",Hypothèses!$C$58="OK",Hypothèses!$C$61="OK",COUNT(Paramètres!$C$8:$C$23)=16,COUNT(Paramètres!$C$41:$C$70)=30,COUNT(Paramètres!$D$41:$D$70)=30,COUNT(Paramètres!$C$27:$D$29)=6,COUNT(Paramètres!$B$74:$B$83)=10,COUNT(Paramètres!$C$74:$C$83)=10,COUNT(Paramètres!$D$74:$D$83)=10,COUNT(Paramètres!$E$74:$E$83)=10),"OK","À CORRIGER") -> OK | D62: KO dès qu'un contrôle est rouge ou qu'un paramètre manque. Le Comparateur reste vide tant que ce n'est pas corrigé.
B63: Régime le plus favorable sur la durée de détention | C63: =Comparateur!$C$41 -> Meublé, LMNP réel | D63: Lu dans le Comparateur : total net en poche après impôt et après revente. Jamais à lire seul.
B64: Écart avec le régime suivant | C64: =Comparateur!$C$42 -> 4763.4458 | D64: En euros sur toute la durée. Un écart faible ne justifie pas une structure plus lourde.
B66: CorpusImmo, millésime 2026. Modèle d'aide à la décision : ne constitue ni un conseil en investissement, ni un conseil fiscal, ni une expertise au sens de la charte de l'expertise en évaluation immobilière. Vérifiez les paramètres avant tout engagement.

Sheet Comparateur
B1: CorpusImmo · corpus.immo · Estimer, comparer, décider. Sur les ventes réelles.
B2: Comparateur
B3: Année 1, cumul sur la durée de détention, revente, TRI : le même bien sous cinq régimes, et le plus favorable. Se remplit depuis Hypothèses.
B6: Indicateur | C6: Location nue, micro-foncier | D6: Location nue, réel foncier | E6: Meublé, LMNP micro-BIC | F6: Meublé, LMNP réel | G6: SCI à l'IS | H6: Lecture
B7: ÉLIGIBILITÉ ET PREMIÈRE ANNÉE
B8: Éligibilité au régime | C8: =IF(Hypothèses!$C$62<>"OK","",IF(MAX(Pluriannuel!$D$9,INDEX(Pluriannuel!$D$9:$AG$9,Hypothèses!$C$44))<=Paramètres!$C$12,"Éligible","Non éligible")) -> Éligible | D8: =IF(Hypothèses!$C$62<>"OK","","Éligible") -> Éligible | E8: =IF(Hypothèses!$C$62<>"OK","",IF(MAX(Pluriannuel!$D$9,INDEX(Pluriannuel!$D$9:$AG$9,Hypothèses!$C$44))<=IF(ISNUMBER(MATCH(Hypothèses!$C$49,Paramètres!$B$27:$B$29,0)),INDEX(Paramètres!$D$27:$D$29,MATCH(Hypothèses!$C$49,Paramètres!$B$27:$B$29,0)),0),"Éligible","Non éligible")) -> Éligible | F8: =IF(Hypothèses!$C$62<>"OK","","Éligible") -> Éligible | G8: =IF(Hypothèses!$C$62<>"OK","","Éligible") -> Éligible | H8: Les régimes micro sont fermés au-dessus de leur plafond de recettes (testé en année 1 et en dernière année).
B9: Base imposable, année 1 | C9: =IF(Hypothèses!$C$62<>"OK","",Pluriannuel!$D$25) -> 9240 | D9: =IF(Hypothèses!$C$62<>"OK","",Pluriannuel!$D$41) -> 0 | E9: =IF(Hypothèses!$C$62<>"OK","",Pluriannuel!$D$47) -> 6600 | F9: =IF(Hypothèses!$C$62<>"OK","",Pluriannuel!$D$61) -> 0 | G9: =IF(Hypothèses!$C$62<>"OK","",Pluriannuel!$D$73) -> 0 | H9: IR : base soumise à la TMI et aux prélèvements sociaux. IS : bénéfice imposable de la société.
B10: Impôt, année 1 | C10: =IF(Hypothèses!$C$62<>"OK","",Pluriannuel!$D$26) -> 4361.28 | D10: =IF(Hypothèses!$C$62<>"OK","",Pluriannuel!$D$42) -> -591.92643 | E10: =IF(Hypothèses!$C$62<>"OK","",Pluriannuel!$D$48) -> 3207.6 | F10: =IF(Hypothèses!$C$62<>"OK","",Pluriannuel!$D$62) -> 0 | G10: =IF(Hypothèses!$C$62<>"OK","",Pluriannuel!$D$74) -> 0 | H10: IR plus prélèvements sociaux (négatif : économie d'impôt du déficit foncier). SCI : IS de la société.
B11: Flux net en poche, année 1 | C11: =IF(Hypothèses!$C$62<>"OK","",Pluriannuel!$D$28) -> -8553.9783 | D11: =IF(Hypothèses!$C$62<>"OK","",Pluriannuel!$D$44) -> -3600.7718 | E11: =IF(Hypothèses!$C$62<>"OK","",Pluriannuel!$D$50) -> -7800.2983 | F11: =IF(Hypothèses!$C$62<>"OK","",Pluriannuel!$D$66) -> -5092.6983 | G11: =IF(Hypothèses!$C$62<>"OK","",Pluriannuel!$D$86) -> -5792.6983 | H11: Loyer moins charges, annuité (capital compris) et impôt. SCI : ce que l'associé reçoit ou apporte.
B13: CUMUL SUR LA DURÉE DE DÉTENTION
B14: Impôts cumulés sur la détention | C14: =IF(Hypothèses!$C$62<>"OK","",Pluriannuel!$C$26-Pluriannuel!$C$27) -> 45628.638 | D14: =IF(Hypothèses!$C$62<>"OK","",Pluriannuel!$C$42-Pluriannuel!$C$43) -> 20000.2 | E14: =IF(Hypothèses!$C$62<>"OK","",Pluriannuel!$C$48-Pluriannuel!$C$49) -> 33558.593 | F14: =IF(Hypothèses!$C$62<>"OK","",Pluriannuel!$C$62-Pluriannuel!$C$65) -> 0 | G14: =IF(Hypothèses!$C$62<>"OK","",Pluriannuel!$C$74+Pluriannuel!$C$84) -> 0 | H14: IR et prélèvements sociaux nets de la CSG déductible ; SCI : IS plus PFU sur les dividendes. Hors revente.
B15: Flux nets cumulés sur la détention | C15: =IF(Hypothèses!$C$62<>"OK","",Pluriannuel!$C$28) -> -82887.274 | D15: =IF(Hypothèses!$C$62<>"OK","",Pluriannuel!$C$44) -> -57258.837 | E15: =IF(Hypothèses!$C$62<>"OK","",Pluriannuel!$C$50) -> -75002.114 | F15: =IF(Hypothèses!$C$62<>"OK","",Pluriannuel!$C$66) -> -46674.627 | G15: =IF(Hypothèses!$C$62<>"OK","",Pluriannuel!$C$86) -> -53998.176 | H15: Somme des flux annuels en poche, avant revente. Négatif : effort d'épargne cumulé.
B16: Reports non consommés en fin de détention | C16: =IF(Hypothèses!$C$62<>"OK","",0) -> 0 | D16: =IF(Hypothèses!$C$62<>"OK","",Pluriannuel!$C$40) -> 0 | E16: =IF(Hypothèses!$C$62<>"OK","",0) -> 0 | F16: =IF(Hypothèses!$C$62<>"OK","",Pluriannuel!$C$56+Pluriannuel!$C$60) -> 35295.025 | G16: =IF(Hypothèses!$C$62<>"OK","",Pluriannuel!$C$72) -> 42618.574 | H16: Déficits fonciers, amortissements différés et déficits BIC, déficit IS : ce que le régime laisse en réserve.
B17: Trésorerie restant en société | C17: ="" | D17: ="" | E17: ="" | F17: ="" | G17: =IF(Hypothèses!$C$62<>"OK","",Pluriannuel!$C$87) -> 0 | H17: SCI seulement : l'argent qui n'est pas un revenu tant qu'il n'est pas distribué.
B19: REVENTE À LA FIN DE LA DÉTENTION
B20: Prix de cession | C20: =IF(Hypothèses!$C$62<>"OK","",Hypothèses!$C$45) -> 232108.17 | D20: =IF(Hypothèses!$C$62<>"OK","",Hypothèses!$C$45) -> 232108.17 | E20: =IF(Hypothèses!$C$62<>"OK","",Hypothèses!$C$45) -> 232108.17 | F20: =IF(Hypothèses!$C$62<>"OK","",Hypothèses!$C$45) -> 232108.17 | G20: =IF(Hypothèses!$C$62<>"OK","",Hypothèses!$C$45) -> 232108.17 | H20: Prix revalorisé ou prix forcé (Hypothèses).
B21: Prix d'acquisition retenu ou valeur nette comptable | C21: =IF(Hypothèses!$C$62<>"OK","",Hypothèses!$C$7+IF(Hypothèses!$C$8=Paramètres!$E$33,MAX(Hypothèses!$C$9,Hypothèses!$C$7*Paramètres!$C$21),Hypothèses!$C$9)+IF(Hypothèses!$C$44>Paramètres!$C$23,Hypothèses!$C$7*Paramètres!$C$22,0)) -> 246000 | D21: =IF(Hypothèses!$C$62<>"OK","",Hypothèses!$C$7+IF(Hypothèses!$C$8=Paramètres!$E$33,MAX(Hypothèses!$C$9,Hypothèses!$C$7*Paramètres!$C$21),Hypothèses!$C$9)+IF(Hypothèses!$C$44>Paramètres!$C$23,Hypothèses!$C$7*Paramètres!$C$22,0)) -> 246000 | E21: =IF(Hypothèses!$C$62<>"OK","",Hypothèses!$C$7+IF(Hypothèses!$C$8=Paramètres!$E$33,MAX(Hypothèses!$C$9,Hypothèses!$C$7*Paramètres!$C$21),Hypothèses!$C$9)+IF(Hypothèses!$C$44>Paramètres!$C$23,Hypothèses!$C$7*Paramètres!$C$22,0)) -> 246000 | F21: =IF(Hypothèses!$C$62<>"OK","",Hypothèses!$C$7+IF(Hypothèses!$C$8=Paramètres!$E$33,MAX(Hypothèses!$C$9,Hypothèses!$C$7*Paramètres!$C$21),Hypothèses!$C$9)+IF(Hypothèses!$C$44>Paramètres!$C$23,Hypothèses!$C$7*Paramètres!$C$22,0)-Pluriannuel!$C$64) -> 212092.47 | G21: =IF(Hypothèses!$C$62<>"OK","",Hypothèses!$C$7+IF(Hypothèses!$C$51=Paramètres!$D$33,Hypothèses!$C$9,0)+Hypothèses!$C$10+Hypothèses!$C$11-Pluriannuel!$C$22) -> 156466.67 | H21: Particuliers : prix, frais (réels, ou forfait de 7,5 % si le bien a été acheté à titre onéreux), forfait travaux après cinq ans, moins les amortissements déduits en LMNP réel. SCI : VNC.
B22: dont amortissements réintégrés dans la plus-value | C22: ="" | D22: ="" | E22: ="" | F22: =IF(Hypothèses!$C$62<>"OK","",Pluriannuel!$C$64) -> 33907.527 | G22: ="" | H22: LMNP réel seulement : les amortissements déduits sur l'immeuble (bâti, frais immobilisés, travaux) viennent en moins du prix d'acquisition depuis 2025. Détail année par année dans le Pluriannuel.
B23: Plus-value imposable | C23: =IF(Hypothèses!$C$62<>"OK","",MAX(0,$C$20-$C$21)) -> 0 | D23: =IF(Hypothèses!$C$62<>"OK","",MAX(0,$D$20-$D$21)) -> 0 | E23: =IF(Hypothèses!$C$62<>"OK","",MAX(0,$E$20-$E$21)) -> 0 | F23: =IF(Hypothèses!$C$62<>"OK","",MAX(0,$F$20-$F$21)) -> 20015.692 | G23: =IF(Hypothèses!$C$62<>"OK","",$G$20-$G$21) -> 75641.498 | H23: Particuliers : avant abattements pour durée (une moins-value vaut 0). SCI : plus-value professionnelle sur VNC.
B24: dont plus-value imposable à l'impôt sur le revenu | C24: =IF(Hypothèses!$C$62<>"OK","",$C$23*(1-INDEX(Paramètres!$C$41:$C$70,Hypothèses!$C$44))) -> 0 | D24: =IF(Hypothèses!$C$62<>"OK","",$D$23*(1-INDEX(Paramètres!$C$41:$C$70,Hypothèses!$C$44))) -> 0 | E24: =IF(Hypothèses!$C$62<>"OK","",$E$23*(1-INDEX(Paramètres!$C$41:$C$70,Hypothèses!$C$44))) -> 0 | F24: =IF(Hypothèses!$C$62<>"OK","",$F$23*(1-INDEX(Paramètres!$C$41:$C$70,Hypothèses!$C$44))) -> 14010.984 | G24: ="" | H24: Particuliers : la plus-value après l'abattement pour durée de détention applicable à l'impôt sur le revenu. C'est l'assiette de la surtaxe ci-dessous, et non celle des prélèvements sociaux, qui est plus élevée. Vide à l'IS.
B25: Surtaxe sur les plus-values élevées | C25: =IF(Hypothèses!$C$62<>"OK","",IF($C$24<=INDEX(Paramètres!$B$74:$B$83,1),0,MAX(0,INDEX(Paramètres!$C$74:$C$83,MATCH($C$24,Paramètres!$B$74:$B$83,1))*$C$24-INDEX(Paramètres!$D$74:$D$83,MATCH($C$24,Paramètres!$B$74:$B$83,1))*MAX(0,INDEX(Paramètres!$E$74:$E$83,MATCH($C$24,Paramètres!$B$74:$B$83,1))-$C$24)))) -> 0 | D25: =IF(Hypothèses!$C$62<>"OK","",IF($D$24<=INDEX(Paramètres!$B$74:$B$83,1),0,MAX(0,INDEX(Paramètres!$C$74:$C$83,MATCH($D$24,Paramètres!$B$74:$B$83,1))*$D$24-INDEX(Paramètres!$D$74:$D$83,MATCH($D$24,Paramètres!$B$74:$B$83,1))*MAX(0,INDEX(Paramètres!$E$74:$E$83,MATCH($D$24,Paramètres!$B$74:$B$83,1))-$D$24)))) -> 0 | E25: =IF(Hypothèses!$C$62<>"OK","",IF($E$24<=INDEX(Paramètres!$B$74:$B$83,1),0,MAX(0,INDEX(Paramètres!$C$74:$C$83,MATCH($E$24,Paramètres!$B$74:$B$83,1))*$E$24-INDEX(Paramètres!$D$74:$D$83,MATCH($E$24,Paramètres!$B$74:$B$83,1))*MAX(0,INDEX(Paramètres!$E$74:$E$83,MATCH($E$24,Paramètres!$B$74:$B$83,1))-$E$24)))) -> 0 | F25: =IF(Hypothèses!$C$62<>"OK","",IF($F$24<=INDEX(Paramètres!$B$74:$B$83,1),0,MAX(0,INDEX(Paramètres!$C$74:$C$83,MATCH($F$24,Paramètres!$B$74:$B$83,1))*$F$24-INDEX(Paramètres!$D$74:$D$83,MATCH($F$24,Paramètres!$B$74:$B$83,1))*MAX(0,INDEX(Paramètres!$E$74:$E$83,MATCH($F$24,Paramètres!$B$74:$B$83,1))-$F$24)))) -> 0 | G25: ="" | H25: Taxe par tranches de 2 à 6 % au-delà de 50 000 € de plus-value imposable à l'impôt sur le revenu (CGI art. 1609 nonies G), barème et lissage dans Paramètres. Elle ne vise que les plus-values des particuliers : la SCI à l'IS en est hors du champ, la cellule reste vide.
B26: IS sur la plus-value de cession | C26: ="" | D26: ="" | E26: ="" | F26: ="" | G26: =IF(Hypothèses!$C$62<>"OK","",(MIN(MAX(0,INDEX(Pluriannuel!$D$73:$AG$73,Hypothèses!$C$44)+$G$23-Pluriannuel!$C$72),Paramètres!$C$16)*Paramètres!$C$15+MAX(0,MAX(0,INDEX(Pluriannuel!$D$73:$AG$73,Hypothèses!$C$44)+$G$23-Pluriannuel!$C$72)-Paramètres!$C$16)*Paramètres!$C$17)-(MIN(INDEX(Pluriannuel!$D$73:$AG$73,Hypothèses!$C$44),Paramètres!$C$16)*Paramètres!$C$15+MAX(0,INDEX(Pluriannuel!$D$73:$AG$73,Hypothèses!$C$44)-Paramètres!$C$16)*Paramètres!$C$17)) -> 4953.4386 | H26: SCI : après imputation du déficit reportable, au barème 15 % / 25 % de l'exercice.
B27: Trésorerie de liquidation | C27: ="" | D27: ="" | E27: ="" | F27: ="" | G27: =IF(Hypothèses!$C$62<>"OK","",Pluriannuel!$C$87+$G$20-Pluriannuel!$C$18-$G$26) -> 111067.66 | H27: SCI : trésorerie, plus prix de cession, moins capital restant dû, moins IS.
B28: Remboursement du compte courant d'associé | C28: ="" | D28: ="" | E28: ="" | F28: ="" | G28: =IF(Hypothèses!$C$62<>"OK","",MIN($G$27,Pluriannuel!$C$88)) -> 82998.176 | H28: SCI : restitué sans impôt (négatif : l'associé comble le passif).
B29: Boni de liquidation | C29: ="" | D29: ="" | E29: ="" | F29: ="" | G29: =IF(Hypothèses!$C$62<>"OK","",MAX(0,$G$27-Pluriannuel!$C$88)) -> 28069.486 | H29: SCI : le surplus, imposé au PFU comme un dividende.
B30: Impôt total à la revente | C30: =IF(Hypothèses!$C$62<>"OK","",$C$24*Paramètres!$C$19+$C$23*(1-INDEX(Paramètres!$D$41:$D$70,Hypothèses!$C$44))*Paramètres!$C$20+$C$25) -> 0 | D30: =IF(Hypothèses!$C$62<>"OK","",$D$24*Paramètres!$C$19+$D$23*(1-INDEX(Paramètres!$D$41:$D$70,Hypothèses!$C$44))*Paramètres!$C$20+$D$25) -> 0 | E30: =IF(Hypothèses!$C$62<>"OK","",$E$24*Paramètres!$C$19+$E$23*(1-INDEX(Paramètres!$D$41:$D$70,Hypothèses!$C$44))*Paramètres!$C$20+$E$25) -> 0 | F30: =IF(Hypothèses!$C$62<>"OK","",$F$24*Paramètres!$C$19+$F$23*(1-INDEX(Paramètres!$D$41:$D$70,Hypothèses!$C$44))*Paramètres!$C$20+$F$25) -> 5820.7633 | G30: =IF(Hypothèses!$C$62<>"OK","",$G$26+$G$29*Paramètres!$C$18) -> 13767.257 | H30: Particuliers : 19 % d'IR et 17,2 % de prélèvements sociaux après abattements pour durée, plus la surtaxe ci-dessus. SCI : IS sur la plus-value plus PFU sur le boni.
B31: Net de revente en poche | C31: =IF(Hypothèses!$C$62<>"OK","",$C$20-Pluriannuel!$C$18-$C$30) -> 116021.1 | D31: =IF(Hypothèses!$C$62<>"OK","",$D$20-Pluriannuel!$C$18-$D$30) -> 116021.1 | E31: =IF(Hypothèses!$C$62<>"OK","",$E$20-Pluriannuel!$C$18-$E$30) -> 116021.1 | F31: =IF(Hypothèses!$C$62<>"OK","",$F$20-Pluriannuel!$C$18-$F$30) -> 110200.34 | G31: =IF(Hypothèses!$C$62<>"OK","",$G$28+$G$29*(1-Paramètres!$C$18)) -> 102253.84 | H31: Prix de cession moins capital restant dû moins impôt. SCI : compte courant remboursé plus boni net.
B33: BILAN SUR LA DURÉE DE DÉTENTION
B34: Total net en poche après impôt et après revente | C34: =IF(Hypothèses!$C$62<>"OK","",IF($C$8="Éligible",$C$15+$C$31,"Non éligible")) -> 33133.826 | D34: =IF(Hypothèses!$C$62<>"OK","",IF($D$8="Éligible",$D$15+$D$31,"Non éligible")) -> 58762.264 | E34: =IF(Hypothèses!$C$62<>"OK","",IF($E$8="Éligible",$E$15+$E$31,"Non éligible")) -> 41018.986 | F34: =IF(Hypothèses!$C$62<>"OK","",IF($F$8="Éligible",$F$15+$F$31,"Non éligible")) -> 63525.71 | G34: =IF(Hypothèses!$C$62<>"OK","",IF($G$8="Éligible",$G$15+$G$31,"Non éligible")) -> 48255.667 | H34: Flux nets cumulés plus net de revente. C'est le chiffre qui classe les régimes.
B35: Gain net après remboursement de l'apport | C35: =IF(ISNUMBER($C$34),$C$34-Hypothèses!$C$30,"") -> 4133.826 | D35: =IF(ISNUMBER($D$34),$D$34-Hypothèses!$C$30,"") -> 29762.264 | E35: =IF(ISNUMBER($E$34),$E$34-Hypothèses!$C$30,"") -> 12018.986 | F35: =IF(ISNUMBER($F$34),$F$34-Hypothèses!$C$30,"") -> 34525.71 | G35: =IF(ISNUMBER($G$34),$G$34-Hypothèses!$C$30,"") -> 19255.667 | H35: Total net moins l'apport initial. Négatif : l'opération détruit de la valeur.
B36: TRI après impôt | C36: =IF(ISNUMBER($C$34),IF(AND(MIN(Pluriannuel!$C$92:$AG$92)<0,MAX(Pluriannuel!$C$92:$AG$92)>0),IRR(Pluriannuel!$C$92:$AG$92,IF($C$35<0,-0.2,0.05)),"n.d."),"") -> 0.0060598173 | D36: =IF(ISNUMBER($D$34),IF(AND(MIN(Pluriannuel!$C$93:$AG$93)<0,MAX(Pluriannuel!$C$93:$AG$93)>0),IRR(Pluriannuel!$C$93:$AG$93,IF($D$35<0,-0.2,0.05)),"n.d."),"") -> 0.046979946 | E36: =IF(ISNUMBER($E$34),IF(AND(MIN(Pluriannuel!$C$94:$AG$94)<0,MAX(Pluriannuel!$C$94:$AG$94)>0),IRR(Pluriannuel!$C$94:$AG$94,IF($E$35<0,-0.2,0.05)),"n.d."),"") -> 0.01782064 | F36: =IF(ISNUMBER($F$34),IF(AND(MIN(Pluriannuel!$C$95:$AG$95)<0,MAX(Pluriannuel!$C$95:$AG$95)>0),IRR(Pluriannuel!$C$95:$AG$95,IF($F$35<0,-0.2,0.05)),"n.d."),"") -> 0.055035895 | G36: =IF(ISNUMBER($G$34),IF(AND(MIN(Pluriannuel!$C$96:$AG$96)<0,MAX(Pluriannuel!$C$96:$AG$96)>0),IRR(Pluriannuel!$C$96:$AG$96,IF($G$35<0,-0.2,0.05)),"n.d."),"") -> 0.031670479 | H36: Taux de rendement interne des flux de l'investisseur, apport en année 0, revente en fin de détention.
B37: Écart avec le meilleur régime | C37: =IF(ISNUMBER($C$34),MAX($C$34:$G$34)-$C$34,"") -> 30391.884 | D37: =IF(ISNUMBER($D$34),MAX($C$34:$G$34)-$D$34,"") -> 4763.4458 | E37: =IF(ISNUMBER($E$34),MAX($C$34:$G$34)-$E$34,"") -> 22506.723 | F37: =IF(ISNUMBER($F$34),MAX($C$34:$G$34)-$F$34,"") -> 0 | G37: =IF(ISNUMBER($G$34),MAX($C$34:$G$34)-$G$34,"") -> 15270.043 | H37: En euros sur toute la durée. 0 sur le régime le plus favorable.
B38: Rang | C38: =IF(ISNUMBER($C$34),COUNTIF($C$34:$G$34,">"&$C$34)+1,"") -> 5 | D38: =IF(ISNUMBER($D$34),COUNTIF($C$34:$G$34,">"&$D$34)+1,"") -> 2 | E38: =IF(ISNUMBER($E$34),COUNTIF($C$34:$G$34,">"&$E$34)+1,"") -> 4 | F38: =IF(ISNUMBER($F$34),COUNTIF($C$34:$G$34,">"&$F$34)+1,"") -> 1 | G38: =IF(ISNUMBER($G$34),COUNTIF($C$34:$G$34,">"&$G$34)+1,"") -> 3 | H38: 1 : le plus favorable.
B40: VERDICT
B41: Régime le plus favorable sur la durée | C41: =IF(Hypothèses!$C$62<>"OK","",INDEX($C$6:$G$6,MATCH(MAX($C$34:$G$34),$C$34:$G$34,0))) -> Meublé, LMNP réel | H41: Total net le plus élevé parmi les régimes éligibles.
B42: Écart avec le régime suivant | C42: =IF(Hypothèses!$C$62<>"OK","",IF(COUNT($C$34:$G$34)>=2,MAX($C$34:$G$34)-LARGE($C$34:$G$34,2),0)) -> 4763.4458 | H42: Un écart inférieur au coût d'une comptabilité ou d'une structure ne tranche rien.
B43: Classement sans ex aequo | C43: =IF(AND(Hypothèses!$C$62="OK",COUNTIF($C$34:$G$34,MAX($C$34:$G$34))=1),"OK","À CORRIGER") -> OK | H43: KO si deux régimes arrivent à égalité parfaite : le premier nommé l'emporte par ordre de colonne.
B45: CorpusImmo, millésime 2026. Modèle d'aide à la décision : ne constitue ni un conseil en investissement, ni un conseil fiscal, ni une expertise au sens de la charte de l'expertise en évaluation immobilière. Vérifiez les paramètres avant tout engagement.

Sheet Pluriannuel
B1: CorpusImmo · corpus.immo · Estimer, comparer, décider. Sur les ventes réelles.
B2: Pluriannuel
B3: Année par année, pour chaque régime : résultat fiscal, impôt, reports, flux net en poche. Colonne C : cumul (ou valeur en fin de détention pour les stocks). Les années au-delà de la détention sont grisées.
B6: Année | C6: Cumul sur la détention, ou fin de détention | D6: 1 | E6: 2 | F6: 3 | G6: 4 | H6: 5 | I6: 6 | J6: 7 | K6: 8 | L6: 9 | M6: 10 | N6: 11 | O6: 12 | P6: 13 | Q6: 14 | R6: 15 | S6: 16 | T6: 17 | U6: 18 | V6: 19 | W6: 20 | X6: 21 | Y6: 22 | Z6: 23 | AA6: 24 | AB6: 25 | AC6: 26 | AD6: 27 | AE6: 28 | AF6: 29 | AG6: 30
B8: LE BIEN, LE LOYER ET LE PRÊT
B9: Loyer encaissé | C9: =SUMPRODUCT((D$6:AG$6<=Hypothèses!$C$44)*(D9:AG9)) -> 138101.21 | D9: =Hypothèses!$C$16*(1+Hypothèses!$C$21)^(D$6-1) -> 13200 | E9: =Hypothèses!$C$16*(1+Hypothèses!$C$21)^(E$6-1) -> 13332 | F9: =Hypothèses!$C$16*(1+Hypothèses!$C$21)^(F$6-1) -> 13465.32 | G9: =Hypothèses!$C$16*(1+Hypothèses!$C$21)^(G$6-1) -> 13599.973 | H9: =Hypothèses!$C$16*(1+Hypothèses!$C$21)^(H$6-1) -> 13735.973 | I9: =Hypothèses!$C$16*(1+Hypothèses!$C$21)^(I$6-1) -> 13873.333 | J9: =Hypothèses!$C$16*(1+Hypothèses!$C$21)^(J$6-1) -> 14012.066 | K9: =Hypothèses!$C$16*(1+Hypothèses!$C$21)^(K$6-1) -> 14152.187 | ... AG9: =Hypothèses!$C$16*(1+Hypothèses!$C$21)^(AG$6-1) -> 17615.451
B10: Charges déductibles hors intérêts | C10: =SUMPRODUCT((D$6:AG$6<=Hypothèses!$C$44)*(D10:AG10)) -> 32432.859 | D10: =Hypothèses!$C$17*(1+Hypothèses!$C$21)^(D$6-1) -> 3100 | E10: =Hypothèses!$C$17*(1+Hypothèses!$C$21)^(E$6-1) -> 3131 | F10: =Hypothèses!$C$17*(1+Hypothèses!$C$21)^(F$6-1) -> 3162.31 | G10: =Hypothèses!$C$17*(1+Hypothèses!$C$21)^(G$6-1) -> 3193.9331 | H10: =Hypothèses!$C$17*(1+Hypothèses!$C$21)^(H$6-1) -> 3225.8724 | I10: =Hypothèses!$C$17*(1+Hypothèses!$C$21)^(I$6-1) -> 3258.1312 | J10: =Hypothèses!$C$17*(1+Hypothèses!$C$21)^(J$6-1) -> 3290.7125 | K10: =Hypothèses!$C$17*(1+Hypothèses!$C$21)^(K$6-1) -> 3323.6196 | ... AG10: =Hypothèses!$C$17*(1+Hypothèses!$C$21)^(AG$6-1) -> 4136.962
B11: CFE (régimes meublés) | C11: =SUMPRODUCT((D$6:AG$6<=Hypothèses!$C$44)*(D11:AG11)) -> 4184.885 | D11: =Hypothèses!$C$18*(1+Hypothèses!$C$21)^(D$6-1) -> 400 | E11: =Hypothèses!$C$18*(1+Hypothèses!$C$21)^(E$6-1) -> 404 | F11: =Hypothèses!$C$18*(1+Hypothèses!$C$21)^(F$6-1) -> 408.04 | G11: =Hypothèses!$C$18*(1+Hypothèses!$C$21)^(G$6-1) -> 412.1204 | H11: =Hypothèses!$C$18*(1+Hypothèses!$C$21)^(H$6-1) -> 416.2416 | I11: =Hypothèses!$C$18*(1+Hypothèses!$C$21)^(I$6-1) -> 420.40402 | J11: =Hypothèses!$C$18*(1+Hypothèses!$C$21)^(J$6-1) -> 424.60806 | K11: =Hypothèses!$C$18*(1+Hypothèses!$C$21)^(K$6-1) -> 428.85414 | ... AG11: =Hypothèses!$C$18*(1+Hypothèses!$C$21)^(AG$6-1) -> 533.80155
B12: Honoraires comptables LMNP réel | C12: =SUMPRODUCT((D$6:AG$6<=Hypothèses!$C$44)*(D12:AG12)) -> 5231.1063 | D12: =Hypothèses!$C$19*(1+Hypothèses!$C$21)^(D$6-1) -> 500 | E12: =Hypothèses!$C$19*(1+Hypothèses!$C$21)^(E$6-1) -> 505 | F12: =Hypothèses!$C$19*(1+Hypothèses!$C$21)^(F$6-1) -> 510.05 | G12: =Hypothèses!$C$19*(1+Hypothèses!$C$21)^(G$6-1) -> 515.1505 | H12: =Hypothèses!$C$19*(1+Hypothèses!$C$21)^(H$6-1) -> 520.30201 | I12: =Hypothèses!$C$19*(1+Hypothèses!$C$21)^(I$6-1) -> 525.50503 | J12: =Hypothèses!$C$19*(1+Hypothèses!$C$21)^(J$6-1) -> 530.76008 | K12: =Hypothèses!$C$19*(1+Hypothèses!$C$21)^(K$6-1) -> 536.06768 | ... AG12: =Hypothèses!$C$19*(1+Hypothèses!$C$21)^(AG$6-1) -> 667.25194
B13: Honoraires comptables SCI IS | C13: =SUMPRODUCT((D$6:AG$6<=Hypothèses!$C$44)*(D13:AG13)) -> 12554.655 | D13: =Hypothèses!$C$20*(1+Hypothèses!$C$21)^(D$6-1) -> 1200 | E13: =Hypothèses!$C$20*(1+Hypothèses!$C$21)^(E$6-1) -> 1212 | F13: =Hypothèses!$C$20*(1+Hypothèses!$C$21)^(F$6-1) -> 1224.12 | G13: =Hypothèses!$C$20*(1+Hypothèses!$C$21)^(G$6-1) -> 1236.3612 | H13: =Hypothèses!$C$20*(1+Hypothèses!$C$21)^(H$6-1) -> 1248.7248 | I13: =Hypothèses!$C$20*(1+Hypothèses!$C$21)^(I$6-1) -> 1261.2121 | J13: =Hypothèses!$C$20*(1+Hypothèses!$C$21)^(J$6-1) -> 1273.8242 | K13: =Hypothèses!$C$20*(1+Hypothèses!$C$21)^(K$6-1) -> 1286.5624 | ... AG13: =Hypothèses!$C$20*(1+Hypothèses!$C$21)^(AG$6-1) -> 1601.4047
B14: Intérêts d'emprunt | C14: =SUMPRODUCT((D$6:AG$6<=Hypothèses!$C$44)*(D14:AG14)) -> 52214.047 | D14: =IF(OR(NOT(AND(Hypothèses!$C$26>0,Hypothèses!$C$33="OK",D$6<=Hypothèses!$C$28)),Hypothèses!$C$27=0),0,-CUMIPMT(Hypothèses!$C$27/12,Hypothèses!$C$28*12,Hypothèses!$C$26,12*(D$6-1)+1,12*D$6,0)) -> 6393.0881 | E14: =IF(OR(NOT(AND(Hypothèses!$C$26>0,Hypothèses!$C$33="OK",E$6<=Hypothèses!$C$28)),Hypothèses!$C$27=0),0,-CUMIPMT(Hypothèses!$C$27/12,Hypothèses!$C$28*12,Hypothèses!$C$26,12*(E$6-1)+1,12*E$6,0)) -> 6154.9239 | F14: =IF(OR(NOT(AND(Hypothèses!$C$26>0,Hypothèses!$C$33="OK",F$6<=Hypothèses!$C$28)),Hypothèses!$C$27=0),0,-CUMIPMT(Hypothèses!$C$27/12,Hypothèses!$C$28*12,Hypothèses!$C$26,12*(F$6-1)+1,12*F$6,0)) -> 5908.903 | G14: =IF(OR(NOT(AND(Hypothèses!$C$26>0,Hypothèses!$C$33="OK",G$6<=Hypothèses!$C$28)),Hypothèses!$C$27=0),0,-CUMIPMT(Hypothèses!$C$27/12,Hypothèses!$C$28*12,Hypothèses!$C$26,12*(G$6-1)+1,12*G$6,0)) -> 5654.7663 | H14: =IF(OR(NOT(AND(Hypothèses!$C$26>0,Hypothèses!$C$33="OK",H$6<=Hypothèses!$C$28)),Hypothèses!$C$27=0),0,-CUMIPMT(Hypothèses!$C$27/12,Hypothèses!$C$28*12,Hypothèses!$C$26,12*(H$6-1)+1,12*H$6,0)) -> 5392.2459 | I14: =IF(OR(NOT(AND(Hypothèses!$C$26>0,Hypothèses!$C$33="OK",I$6<=Hypothèses!$C$28)),Hypothèses!$C$27=0),0,-CUMIPMT(Hypothèses!$C$27/12,Hypothèses!$C$28*12,Hypothèses!$C$26,12*(I$6-1)+1,12*I$6,0)) -> 5121.0655 | J14: =IF(OR(NOT(AND(Hypothèses!$C$26>0,Hypothèses!$C$33="OK",J$6<=Hypothèses!$C$28)),Hypothèses!$C$27=0),0,-CUMIPMT(Hypothèses!$C$27/12,Hypothèses!$C$28*12,Hypothèses!$C$26,12*(J$6-1)+1,12*J$6,0)) -> 4840.9391 | K14: =IF(OR(NOT(AND(Hypothèses!$C$26>0,Hypothèses!$C$33="OK",K$6<=Hypothèses!$C$28)),Hypothèses!$C$27=0),0,-CUMIPMT(Hypothèses!$C$27/12,Hypothèses!$C$28*12,Hypothèses!$C$26,12*(K$6-1)+1,12*K$6,0)) -> 4551.5718 | ... AG14: =IF(OR(NOT(AND(Hypothèses!$C$26>0,Hypothèses!$C$33="OK",AG$6<=Hypothèses!$C$28)),Hypothèses!$C$27=0),0,-CUMIPMT(Hypothèses!$C$27/12,Hypothèses!$C$28*12,Hypothèses!$C$26,12*(AG$6-1)+1,12*AG$6,0)) -> 0
B15: Capital remboursé | C15: =SUMPRODUCT((D$6:AG$6<=Hypothèses!$C$44)*(D15:AG15)) -> 83912.935 | D15: =IF(NOT(AND(Hypothèses!$C$26>0,Hypothèses!$C$33="OK",D$6<=Hypothèses!$C$28)),0,IF(Hypothèses!$C$27=0,Hypothèses!$C$26/Hypothèses!$C$28,-CUMPRINC(Hypothèses!$C$27/12,Hypothèses!$C$28*12,Hypothèses!$C$26,12*(D$6-1)+1,12*D$6,0))) -> 7219.6102 | E15: =IF(NOT(AND(Hypothèses!$C$26>0,Hypothèses!$C$33="OK",E$6<=Hypothèses!$C$28)),0,IF(Hypothèses!$C$27=0,Hypothèses!$C$26/Hypothèses!$C$28,-CUMPRINC(Hypothèses!$C$27/12,Hypothèses!$C$28*12,Hypothèses!$C$26,12*(E$6-1)+1,12*E$6,0))) -> 7457.7744 | F15: =IF(NOT(AND(Hypothèses!$C$26>0,Hypothèses!$C$33="OK",F$6<=Hypothèses!$C$28)),0,IF(Hypothèses!$C$27=0,Hypothèses!$C$26/Hypothèses!$C$28,-CUMPRINC(Hypothèses!$C$27/12,Hypothèses!$C$28*12,Hypothèses!$C$26,12*(F$6-1)+1,12*F$6,0))) -> 7703.7953 | G15: =IF(NOT(AND(Hypothèses!$C$26>0,Hypothèses!$C$33="OK",G$6<=Hypothèses!$C$28)),0,IF(Hypothèses!$C$27=0,Hypothèses!$C$26/Hypothèses!$C$28,-CUMPRINC(Hypothèses!$C$27/12,Hypothèses!$C$28*12,Hypothèses!$C$26,12*(G$6-1)+1,12*G$6,0))) -> 7957.932 | H15: =IF(NOT(AND(Hypothèses!$C$26>0,Hypothèses!$C$33="OK",H$6<=Hypothèses!$C$28)),0,IF(Hypothèses!$C$27=0,Hypothèses!$C$26/Hypothèses!$C$28,-CUMPRINC(Hypothèses!$C$27/12,Hypothèses!$C$28*12,Hypothèses!$C$26,12*(H$6-1)+1,12*H$6,0))) -> 8220.4523 | I15: =IF(NOT(AND(Hypothèses!$C$26>0,Hypothèses!$C$33="OK",I$6<=Hypothèses!$C$28)),0,IF(Hypothèses!$C$27=0,Hypothèses!$C$26/Hypothèses!$C$28,-CUMPRINC(Hypothèses!$C$27/12,Hypothèses!$C$28*12,Hypothèses!$C$26,12*(I$6-1)+1,12*I$6,0))) -> 8491.6328 | J15: =IF(NOT(AND(Hypothèses!$C$26>0,Hypothèses!$C$33="OK",J$6<=Hypothèses!$C$28)),0,IF(Hypothèses!$C$27=0,Hypothèses!$C$26/Hypothèses!$C$28,-CUMPRINC(Hypothèses!$C$27/12,Hypothèses!$C$28*12,Hypothèses!$C$26,12*(J$6-1)+1,12*J$6,0))) -> 8771.7592 | K15: =IF(NOT(AND(Hypothèses!$C$26>0,Hypothèses!$C$33="OK",K$6<=Hypothèses!$C$28)),0,IF(Hypothèses!$C$27=0,Hypothèses!$C$26/Hypothèses!$C$28,-CUMPRINC(Hypothèses!$C$27/12,Hypothèses!$C$28*12,Hypothèses!$C$26,12*(K$6-1)+1,12*K$6,0))) -> 9061.1264 | ... AG15: =IF(NOT(AND(Hypothèses!$C$26>0,Hypothèses!$C$33="OK",AG$6<=Hypothèses!$C$28)),0,IF(Hypothèses!$C$27=0,Hypothèses!$C$26/Hypothèses!$C$28,-CUMPRINC(Hypothèses!$C$27/12,Hypothèses!$C$28*12,Hypothèses!$C$26,12*(AG$6-1)+1,12*AG$6,0))) -> 0
B16: Assurance emprunteur | C16: =SUMPRODUCT((D$6:AG$6<=Hypothèses!$C$44)*(D16:AG16)) -> 6800 | D16: =IF(AND(Hypothèses!$C$26>0,Hypothèses!$C$33="OK",D$6<=Hypothèses!$C$28),Hypothèses!$C$26*Hypothèses!$C$29,0) -> 680 | E16: =IF(AND(Hypothèses!$C$26>0,Hypothèses!$C$33="OK",E$6<=Hypothèses!$C$28),Hypothèses!$C$26*Hypothèses!$C$29,0) -> 680 | F16: =IF(AND(Hypothèses!$C$26>0,Hypothèses!$C$33="OK",F$6<=Hypothèses!$C$28),Hypothèses!$C$26*Hypothèses!$C$29,0) -> 680 | G16: =IF(AND(Hypothèses!$C$26>0,Hypothèses!$C$33="OK",G$6<=Hypothèses!$C$28),Hypothèses!$C$26*Hypothèses!$C$29,0) -> 680 | H16: =IF(AND(Hypothèses!$C$26>0,Hypothèses!$C$33="OK",H$6<=Hypothèses!$C$28),Hypothèses!$C$26*Hypothèses!$C$29,0) -> 680 | I16: =IF(AND(Hypothèses!$C$26>0,Hypothèses!$C$33="OK",I$6<=Hypothèses!$C$28),Hypothèses!$C$26*Hypothèses!$C$29,0) -> 680 | J16: =IF(AND(Hypothèses!$C$26>0,Hypothèses!$C$33="OK",J$6<=Hypothèses!$C$28),Hypothèses!$C$26*Hypothèses!$C$29,0) -> 680 | K16: =IF(AND(Hypothèses!$C$26>0,Hypothèses!$C$33="OK",K$6<=Hypothèses!$C$28),Hypothèses!$C$26*Hypothèses!$C$29,0) -> 680 | ... AG16: =IF(AND(Hypothèses!$C$26>0,Hypothèses!$C$33="OK",AG$6<=Hypothèses!$C$28),Hypothèses!$C$26*Hypothèses!$C$29,0) -> 0
B17: Annuité totale (intérêts, capital, assurance) | C17: =SUMPRODUCT((D$6:AG$6<=Hypothèses!$C$44)*(D17:AG17)) -> 142926.98 | D17: =D14+D15+D16 -> 14292.698 | E17: =E14+E15+E16 -> 14292.698 | F17: =F14+F15+F16 -> 14292.698 | G17: =G14+G15+G16 -> 14292.698 | H17: =H14+H15+H16 -> 14292.698 | I17: =I14+I15+I16 -> 14292.698 | J17: =J14+J15+J16 -> 14292.698 | K17: =K14+K15+K16 -> 14292.698 | ... AG17: =AG14+AG15+AG16 -> 0
B18: Capital restant dû en fin d'année | C18: =INDEX(D18:AG18,Hypothèses!$C$44) -> 116087.06 | D18: =IF(AND(Hypothèses!$C$26>0,Hypothèses!$C$33="OK",D$6<=Hypothèses!$C$28),Hypothèses!$C$26-D15,0) -> 192780.39 | E18: =IF(AND(Hypothèses!$C$26>0,Hypothèses!$C$33="OK",E$6<=Hypothèses!$C$28),D18-E15,0) -> 185322.62 | F18: =IF(AND(Hypothèses!$C$26>0,Hypothèses!$C$33="OK",F$6<=Hypothèses!$C$28),E18-F15,0) -> 177618.82 | G18: =IF(AND(Hypothèses!$C$26>0,Hypothèses!$C$33="OK",G$6<=Hypothèses!$C$28),F18-G15,0) -> 169660.89 | H18: =IF(AND(Hypothèses!$C$26>0,Hypothèses!$C$33="OK",H$6<=Hypothèses!$C$28),G18-H15,0) -> 161440.44 | I18: =IF(AND(Hypothèses!$C$26>0,Hypothèses!$C$33="OK",I$6<=Hypothèses!$C$28),H18-I15,0) -> 152948.8 | J18: =IF(AND(Hypothèses!$C$26>0,Hypothèses!$C$33="OK",J$6<=Hypothèses!$C$28),I18-J15,0) -> 144177.04 | K18: =IF(AND(Hypothèses!$C$26>0,Hypothèses!$C$33="OK",K$6<=Hypothèses!$C$28),J18-K15,0) -> 135115.92 | L18: =IF(AND(Hypothèses!$C$26>0,Hypothèses!$C$33="OK",L$6<=Hypothèses!$C$28),K18-L15,0) -> 125755.88 | ... AG18: =IF(AND(Hypothèses!$C$26>0,Hypothèses!$C$33="OK",AG$6<=Hypothèses!$C$28),AF18-AG15,0) -> 0
B19: Amortissement du bâti (hors terrain) | C19: =SUMPRODUCT((D$6:AG$6<=Hypothèses!$C$44)*(D19:AG19)) -> 61200 | D19: =IF(AND(Hypothèses!$C$55>0,D$6<=Hypothèses!$C$55),((Hypothèses!$C$7+IF(Hypothèses!$C$51=Paramètres!$D$33,Hypothèses!$C$9,0))*(1-Hypothèses!$C$54))/Hypothèses!$C$55,0) -> 6120 | E19: =IF(AND(Hypothèses!$C$55>0,E$6<=Hypothèses!$C$55),((Hypothèses!$C$7+IF(Hypothèses!$C$51=Paramètres!$D$33,Hypothèses!$C$9,0))*(1-Hypothèses!$C$54))/Hypothèses!$C$55,0) -> 6120 | F19: =IF(AND(Hypothèses!$C$55>0,F$6<=Hypothèses!$C$55),((Hypothèses!$C$7+IF(Hypothèses!$C$51=Paramètres!$D$33,Hypothèses!$C$9,0))*(1-Hypothèses!$C$54))/Hypothèses!$C$55,0) -> 6120 | G19: =IF(AND(Hypothèses!$C$55>0,G$6<=Hypothèses!$C$55),((Hypothèses!$C$7+IF(Hypothèses!$C$51=Paramètres!$D$33,Hypothèses!$C$9,0))*(1-Hypothèses!$C$54))/Hypothèses!$C$55,0) -> 6120 | H19: =IF(AND(Hypothèses!$C$55>0,H$6<=Hypothèses!$C$55),((Hypothèses!$C$7+IF(Hypothèses!$C$51=Paramètres!$D$33,Hypothèses!$C$9,0))*(1-Hypothèses!$C$54))/Hypothèses!$C$55,0) -> 6120 | I19: =IF(AND(Hypothèses!$C$55>0,I$6<=Hypothèses!$C$55),((Hypothèses!$C$7+IF(Hypothèses!$C$51=Paramètres!$D$33,Hypothèses!$C$9,0))*(1-Hypothèses!$C$54))/Hypothèses!$C$55,0) -> 6120 | J19: =IF(AND(Hypothèses!$C$55>0,J$6<=Hypothèses!$C$55),((Hypothèses!$C$7+IF(Hypothèses!$C$51=Paramètres!$D$33,Hypothèses!$C$9,0))*(1-Hypothèses!$C$54))/Hypothèses!$C$55,0) -> 6120 | K19: =IF(AND(Hypothèses!$C$55>0,K$6<=Hypothèses!$C$55),((Hypothèses!$C$7+IF(Hypothèses!$C$51=Paramètres!$D$33,Hypothèses!$C$9,0))*(1-Hypothèses!$C$54))/Hypothèses!$C$55,0) -> 6120 | ... AG19: =IF(AND(Hypothèses!$C$55>0,AG$6<=Hypothèses!$C$55),((Hypothèses!$C$7+IF(Hypothèses!$C$51=Paramètres!$D$33,Hypothèses!$C$9,0))*(1-Hypothèses!$C$54))/Hypothèses!$C$55,0) -> 6120
B20: Amortissement des travaux | C20: =SUMPRODUCT((D$6:AG$6<=Hypothèses!$C$44)*(D20:AG20)) -> 3333.3333 | D20: =IF(AND(Hypothèses!$C$56>0,D$6<=Hypothèses!$C$56),Hypothèses!$C$10/Hypothèses!$C$56,0) -> 333.33333 | E20: =IF(AND(Hypothèses!$C$56>0,E$6<=Hypothèses!$C$56),Hypothèses!$C$10/Hypothèses!$C$56,0) -> 333.33333 | F20: =IF(AND(Hypothèses!$C$56>0,F$6<=Hypothèses!$C$56),Hypothèses!$C$10/Hypothèses!$C$56,0) -> 333.33333 | G20: =IF(AND(Hypothèses!$C$56>0,G$6<=Hypothèses!$C$56),Hypothèses!$C$10/Hypothèses!$C$56,0) -> 333.33333 | H20: =IF(AND(Hypothèses!$C$56>0,H$6<=Hypothèses!$C$56),Hypothèses!$C$10/Hypothèses!$C$56,0) -> 333.33333 | I20: =IF(AND(Hypothèses!$C$56>0,I$6<=Hypothèses!$C$56),Hypothèses!$C$10/Hypothèses!$C$56,0) -> 333.33333 | J20: =IF(AND(Hypothèses!$C$56>0,J$6<=Hypothèses!$C$56),Hypothèses!$C$10/Hypothèses!$C$56,0) -> 333.33333 | K20: =IF(AND(Hypothèses!$C$56>0,K$6<=Hypothèses!$C$56),Hypothèses!$C$10/Hypothèses!$C$56,0) -> 333.33333 | ... AG20: =IF(AND(Hypothèses!$C$56>0,AG$6<=Hypothèses!$C$56),Hypothèses!$C$10/Hypothèses!$C$56,0) -> 0
B21: Amortissement du mobilier | C21: =SUMPRODUCT((D$6:AG$6<=Hypothèses!$C$44)*(D21:AG21)) -> 8000 | D21: =IF(AND(Hypothèses!$C$57>0,D$6<=Hypothèses!$C$57),Hypothèses!$C$11/Hypothèses!$C$57,0) -> 1142.8571 | E21: =IF(AND(Hypothèses!$C$57>0,E$6<=Hypothèses!$C$57),Hypothèses!$C$11/Hypothèses!$C$57,0) -> 1142.8571 | F21: =IF(AND(Hypothèses!$C$57>0,F$6<=Hypothèses!$C$57),Hypothèses!$C$11/Hypothèses!$C$57,0) -> 1142.8571 | G21: =IF(AND(Hypothèses!$C$57>0,G$6<=Hypothèses!$C$57),Hypothèses!$C$11/Hypothèses!$C$57,0) -> 1142.8571 | H21: =IF(AND(Hypothèses!$C$57>0,H$6<=Hypothèses!$C$57),Hypothèses!$C$11/Hypothèses!$C$57,0) -> 1142.8571 | I21: =IF(AND(Hypothèses!$C$57>0,I$6<=Hypothèses!$C$57),Hypothèses!$C$11/Hypothèses!$C$57,0) -> 1142.8571 | J21: =IF(AND(Hypothèses!$C$57>0,J$6<=Hypothèses!$C$57),Hypothèses!$C$11/Hypothèses!$C$57,0) -> 1142.8571 | K21: =IF(AND(Hypothèses!$C$57>0,K$6<=Hypothèses!$C$57),Hypothèses!$C$11/Hypothèses!$C$57,0) -> 0 | ... AG21: =IF(AND(Hypothèses!$C$57>0,AG$6<=Hypothèses!$C$57),Hypothèses!$C$11/Hypothèses!$C$57,0) -> 0
B22: Amortissement total de l'année | C22: =SUMPRODUCT((D$6:AG$6<=Hypothèses!$C$44)*(D22:AG22)) -> 72533.333 | D22: =D19+D20+D21 -> 7596.1905 | E22: =E19+E20+E21 -> 7596.1905 | F22: =F19+F20+F21 -> 7596.1905 | G22: =G19+G20+G21 -> 7596.1905 | H22: =H19+H20+H21 -> 7596.1905 | I22: =I19+I20+I21 -> 7596.1905 | J22: =J19+J20+J21 -> 7596.1905 | K22: =K19+K20+K21 -> 6453.3333 | ... AG22: =AG19+AG20+AG21 -> 6120
B24: LOCATION NUE, MICRO-FONCIER
B25: Base imposable (loyer moins abattement) | C25: =SUMPRODUCT((D$6:AG$6<=Hypothèses!$C$44)*(D25:AG25)) -> 96670.844 | D25: =D9*(1-Paramètres!$C$11) -> 9240 | E25: =E9*(1-Paramètres!$C$11) -> 9332.4 | F25: =F9*(1-Paramètres!$C$11) -> 9425.724 | G25: =G9*(1-Paramètres!$C$11) -> 9519.9812 | H25: =H9*(1-Paramètres!$C$11) -> 9615.1811 | I25: =I9*(1-Paramètres!$C$11) -> 9711.3329 | J25: =J9*(1-Paramètres!$C$11) -> 9808.4462 | K25: =K9*(1-Paramètres!$C$11) -> 9906.5307 | ... AG25: =AG9*(1-Paramètres!$C$11) -> 12330.816
B26: Impôt sur le revenu et prélèvements sociaux | C26: =SUMPRODUCT((D$6:AG$6<=Hypothèses!$C$44)*(D26:AG26)) -> 45628.638 | D26: =D25*(Hypothèses!$C$36+Paramètres!$C$8) -> 4361.28 | E26: =E25*(Hypothèses!$C$36+Paramètres!$C$8) -> 4404.8928 | F26: =F25*(Hypothèses!$C$36+Paramètres!$C$8) -> 4448.9417 | G26: =G25*(Hypothèses!$C$36+Paramètres!$C$8) -> 4493.4311 | H26: =H25*(Hypothèses!$C$36+Paramètres!$C$8) -> 4538.3655 | I26: =I25*(Hypothèses!$C$36+Paramètres!$C$8) -> 4583.7491 | J26: =J25*(Hypothèses!$C$36+Paramètres!$C$8) -> 4629.5866 | K26: =K25*(Hypothèses!$C$36+Paramètres!$C$8) -> 4675.8825 | ... AG26: =AG25*(Hypothèses!$C$36+Paramètres!$C$8) -> 5820.1451
B27: Économie d'IR sur la CSG déductible (option) | C27: =SUMPRODUCT((D$6:AG$6<=Hypothèses!$C$44)*(D27:AG27)) -> 0 | D27: =0 -> 0 | E27: =IF(Hypothèses!$C$53=Paramètres!$C$33,MAX(0,D25)*Paramètres!$C$10*Hypothèses!$C$36,0) -> 0 | F27: =IF(Hypothèses!$C$53=Paramètres!$C$33,MAX(0,E25)*Paramètres!$C$10*Hypothèses!$C$36,0) -> 0 | G27: =IF(Hypothèses!$C$53=Paramètres!$C$33,MAX(0,F25)*Paramètres!$C$10*Hypothèses!$C$36,0) -> 0 | H27: =IF(Hypothèses!$C$53=Paramètres!$C$33,MAX(0,G25)*Paramètres!$C$10*Hypothèses!$C$36,0) -> 0 | I27: =IF(Hypothèses!$C$53=Paramètres!$C$33,MAX(0,H25)*Paramètres!$C$10*Hypothèses!$C$36,0) -> 0 | J27: =IF(Hypothèses!$C$53=Paramètres!$C$33,MAX(0,I25)*Paramètres!$C$10*Hypothèses!$C$36,0) -> 0 | K27: =IF(Hypothèses!$C$53=Paramètres!$C$33,MAX(0,J25)*Paramètres!$C$10*Hypothèses!$C$36,0) -> 0 | L27: =IF(Hypothèses!$C$53=Paramètres!$C$33,MAX(0,K25)*Paramètres!$C$10*Hypothèses!$C$36,0) -> 0 | ... AG27: =IF(Hypothèses!$C$53=Paramètres!$C$33,MAX(0,AF25)*Paramètres!$C$10*Hypothèses!$C$36,0) -> 0
B28: Flux net en poche (après crédit et impôt) | C28: =SUMPRODUCT((D$6:AG$6<=Hypothèses!$C$44)*(D28:AG28)) -> -82887.274 | D28: =D9-D10-D17-D26+D27 -> -8553.9783 | E28: =E9-E10-E17-E26+E27 -> -8496.5911 | F28: =F9-F10-F17-F26+F27 -> -8438.63 | G28: =G9-G10-G17-G26+G27 -> -8380.0893 | H28: =H9-H10-H17-H26+H27 -> -8320.9632 | I28: =I9-I10-I17-I26+I27 -> -8261.2459 | J28: =J9-J10-J17-J26+J27 -> -8200.9314 | K28: =K9-K10-K17-K26+K27 -> -8140.0137 | ... AG28: =AG9-AG10-AG17-AG26+AG27 -> 7658.3441
B30: LOCATION NUE, RÉEL FONCIER
B31: Résultat foncier du bien (travaux déduits l'année 1) | C31: =SUMPRODUCT((D$6:AG$6<=Hypothèses!$C$44)*(D31:AG31)) -> 41654.299 | D31: =D9-D10-(D14+D16)-IF(D$6=1,Hypothèses!$C$10,0) -> -1973.0881 | E31: =E9-E10-(E14+E16)-IF(E$6=1,Hypothèses!$C$10,0) -> 3366.0761 | F31: =F9-F10-(F14+F16)-IF(F$6=1,Hypothèses!$C$10,0) -> 3714.107 | G31: =G9-G10-(G14+G16)-IF(G$6=1,Hypothèses!$C$10,0) -> 4071.2738 | H31: =H9-H10-(H14+H16)-IF(H$6=1,Hypothèses!$C$10,0) -> 4437.8546 | I31: =I9-I10-(I14+I16)-IF(I$6=1,Hypothèses!$C$10,0) -> 4814.1361 | J31: =J9-J10-(J14+J16)-IF(J$6=1,Hypothèses!$C$10,0) -> 5200.4144 | K31: =K9-K10-(K14+K16)-IF(K$6=1,Hypothèses!$C$10,0) -> 5596.9952 | ... AG31: =AG9-AG10-(AG14+AG16)-IF(AG$6=1,Hypothèses!$C$10,0) -> 13478.489
B32: Déficit issu des intérêts (jamais sur le revenu global) | C32: =SUMPRODUCT((D$6:AG$6<=Hypothèses!$C$44)*(D32:AG32)) -> 0 | D32: =MAX(0,(D14+D16)-D9) -> 0 | E32: =MAX(0,(E14+E16)-E9) -> 0 | F32: =MAX(0,(F14+F16)-F9) -> 0 | G32: =MAX(0,(G14+G16)-G9) -> 0 | H32: =MAX(0,(H14+H16)-H9) -> 0 | I32: =MAX(0,(I14+I16)-I9) -> 0 | J32: =MAX(0,(J14+J16)-J9) -> 0 | K32: =MAX(0,(K14+K16)-K9) -> 0 | ... AG32: =MAX(0,(AG14+AG16)-AG9) -> 0
B33: Déficit issu des autres charges | C33: =SUMPRODUCT((D$6:AG$6<=Hypothèses!$C$44)*(D33:AG33)) -> 1973.0881 | D33: =MAX(0,-D31-D32) -> 1973.0881 | E33: =MAX(0,-E31-E32) -> 0 | F33: =MAX(0,-F31-F32) -> 0 | G33: =MAX(0,-G31-G32) -> 0 | H33: =MAX(0,-H31-H32) -> 0 | I33: =MAX(0,-I31-I32) -> 0 | J33: =MAX(0,-J31-J32) -> 0 | K33: =MAX(0,-K31-K32) -> 0 | ... AG33: =MAX(0,-AG31-AG32) -> 0
B34: Déficit intérêts après les autres revenus fonciers | C34: =SUMPRODUCT((D$6:AG$6<=Hypothèses!$C$44)*(D34:AG34)) -> 0 | D34: =MAX(0,D32-Hypothèses!$C$37) -> 0 | E34: =MAX(0,E32-Hypothèses!$C$37) -> 0 | F34: =MAX(0,F32-Hypothèses!$C$37) -> 0 | G34: =MAX(0,G32-Hypothèses!$C$37) -> 0 | H34: =MAX(0,H32-Hypothèses!$C$37) -> 0 | I34: =MAX(0,I32-Hypothèses!$C$37) -> 0 | J34: =MAX(0,J32-Hypothèses!$C$37) -> 0 | K34: =MAX(0,K32-Hypothèses!$C$37) -> 0 | ... AG34: =MAX(0,AG32-Hypothèses!$C$37) -> 0
B35: Déficit autres charges après les autres revenus fonciers | C35: =SUMPRODUCT((D$6:AG$6<=Hypothèses!$C$44)*(D35:AG35)) -> 1973.0881 | D35: =MAX(0,D33-MAX(0,Hypothèses!$C$37-D32)) -> 1973.0881 | E35: =MAX(0,E33-MAX(0,Hypothèses!$C$37-E32)) -> 0 | F35: =MAX(0,F33-MAX(0,Hypothèses!$C$37-F32)) -> 0 | G35: =MAX(0,G33-MAX(0,Hypothèses!$C$37-G32)) -> 0 | H35: =MAX(0,H33-MAX(0,Hypothèses!$C$37-H32)) -> 0 | I35: =MAX(0,I33-MAX(0,Hypothèses!$C$37-I32)) -> 0 | J35: =MAX(0,J33-MAX(0,Hypothèses!$C$37-J32)) -> 0 | K35: =MAX(0,K33-MAX(0,Hypothèses!$C$37-K32)) -> 0 | ... AG35: =MAX(0,AG33-MAX(0,Hypothèses!$C$37-AG32)) -> 0
B36: Déficit imputé sur le revenu global (plafonné) | C36: =SUMPRODUCT((D$6:AG$6<=Hypothèses!$C$44)*(D36:AG36)) -> 1973.0881 | D36: =MIN(D35,IF(Hypothèses!$C$52=Paramètres!$C$33,Paramètres!$C$14,Paramètres!$C$13)) -> 1973.0881 | E36: =MIN(E35,IF(Hypothèses!$C$52=Paramètres!$C$33,Paramètres!$C$14,Paramètres!$C$13)) -> 0 | F36: =MIN(F35,IF(Hypothèses!$C$52=Paramètres!$C$33,Paramètres!$C$14,Paramètres!$C$13)) -> 0 | G36: =MIN(G35,IF(Hypothèses!$C$52=Paramètres!$C$33,Paramètres!$C$14,Paramètres!$C$13)) -> 0 | H36: =MIN(H35,IF(Hypothèses!$C$52=Paramètres!$C$33,Paramètres!$C$14,Paramètres!$C$13)) -> 0 | I36: =MIN(I35,IF(Hypothèses!$C$52=Paramètres!$C$33,Paramètres!$C$14,Paramètres!$C$13)) -> 0 | J36: =MIN(J35,IF(Hypothèses!$C$52=Paramètres!$C$33,Paramètres!$C$14,Paramètres!$C$13)) -> 0 | K36: =MIN(K35,IF(Hypothèses!$C$52=Paramètres!$C$33,Paramètres!$C$14,Paramètres!$C$13)) -> 0 | ... AG36: =MIN(AG35,IF(Hypothèses!$C$52=Paramètres!$C$33,Paramètres!$C$14,Paramètres!$C$13)) -> 0
B37: Revenu foncier net positif du foyer | C37: =SUMPRODUCT((D$6:AG$6<=Hypothèses!$C$44)*(D37:AG37)) -> 43627.387 | D37: =MAX(0,Hypothèses!$C$37+D31) -> 0 | E37: =MAX(0,Hypothèses!$C$37+E31) -> 3366.0761 | F37: =MAX(0,Hypothèses!$C$37+F31) -> 3714.107 | G37: =MAX(0,Hypothèses!$C$37+G31) -> 4071.2738 | H37: =MAX(0,Hypothèses!$C$37+H31) -> 4437.8546 | I37: =MAX(0,Hypothèses!$C$37+I31) -> 4814.1361 | J37: =MAX(0,Hypothèses!$C$37+J31) -> 5200.4144 | K37: =MAX(0,Hypothèses!$C$37+K31) -> 5596.9952 | ... AG37: =MAX(0,Hypothèses!$C$37+AG31) -> 13478.489
B38: Déficits reportables en début d'année | D38: =0 -> 0 | E38: =D40 -> 0 | F38: =E40 -> 0 | G38: =F40 -> 0 | H38: =G40 -> 0 | I38: =H40 -> 0 | J38: =I40 -> 0 | K38: =J40 -> 0 | L38: =K40 -> 0 | ... AG38: =AF40 -> 0
B39: Report imputé sur les revenus fonciers | C39: =SUMPRODUCT((D$6:AG$6<=Hypothèses!$C$44)*(D39:AG39)) -> 0 | D39: =MIN(D38,D37) -> 0 | E39: =MIN(E38,E37) -> 0 | F39: =MIN(F38,F37) -> 0 | G39: =MIN(G38,G37) -> 0 | H39: =MIN(H38,H37) -> 0 | I39: =MIN(I38,I37) -> 0 | J39: =MIN(J38,J37) -> 0 | K39: =MIN(K38,K37) -> 0 | ... AG39: =MIN(AG38,AG37) -> 0
B40: Déficits reportables en fin d'année (10 ans) | C40: =INDEX(D40:AG40,Hypothèses!$C$44) -> 0 | D40: =D38-D39+D34+D35-D36 -> 0 | E40: =E38-E39+E34+E35-E36 -> 0 | F40: =F38-F39+F34+F35-F36 -> 0 | G40: =G38-G39+G34+G35-G36 -> 0 | H40: =H38-H39+H34+H35-H36 -> 0 | I40: =I38-I39+I34+I35-I36 -> 0 | J40: =J38-J39+J34+J35-J36 -> 0 | K40: =K38-K39+K34+K35-K36 -> 0 | ... AG40: =AG38-AG39+AG34+AG35-AG36 -> 0
B41: Base imposable attribuable au bien | C41: =SUMPRODUCT((D$6:AG$6<=Hypothèses!$C$44)*(D41:AG41)) -> 43627.387 | D41: =D37-D39-Hypothèses!$C$37 -> 0 | E41: =E37-E39-Hypothèses!$C$37 -> 3366.0761 | F41: =F37-F39-Hypothèses!$C$37 -> 3714.107 | G41: =G37-G39-Hypothèses!$C$37 -> 4071.2738 | H41: =H37-H39-Hypothèses!$C$37 -> 4437.8546 | I41: =I37-I39-Hypothèses!$C$37 -> 4814.1361 | J41: =J37-J39-Hypothèses!$C$37 -> 5200.4144 | K41: =K37-K39-Hypothèses!$C$37 -> 5596.9952 | ... AG41: =AG37-AG39-Hypothèses!$C$37 -> 13478.489
B42: Impôt et prélèvements sociaux (négatif : économie) | C42: =SUMPRODUCT((D$6:AG$6<=Hypothèses!$C$44)*(D42:AG42)) -> 20000.2 | D42: =D41*(Hypothèses!$C$36+Paramètres!$C$8)-D36*Hypothèses!$C$36 -> -591.92643 | E42: =E41*(Hypothèses!$C$36+Paramètres!$C$8)-E36*Hypothèses!$C$36 -> 1588.7879 | F42: =F41*(Hypothèses!$C$36+Paramètres!$C$8)-F36*Hypothèses!$C$36 -> 1753.0585 | G42: =G41*(Hypothèses!$C$36+Paramètres!$C$8)-G36*Hypothèses!$C$36 -> 1921.6412 | H42: =H41*(Hypothèses!$C$36+Paramètres!$C$8)-H36*Hypothèses!$C$36 -> 2094.6674 | I42: =I41*(Hypothèses!$C$36+Paramètres!$C$8)-I36*Hypothèses!$C$36 -> 2272.2722 | J42: =J41*(Hypothèses!$C$36+Paramètres!$C$8)-J36*Hypothèses!$C$36 -> 2454.5956 | K42: =K41*(Hypothèses!$C$36+Paramètres!$C$8)-K36*Hypothèses!$C$36 -> 2641.7817 | ... AG42: =AG41*(Hypothèses!$C$36+Paramètres!$C$8)-AG36*Hypothèses!$C$36 -> 6361.8469
B43: Économie d'IR sur la CSG déductible (option) | C43: =SUMPRODUCT((D$6:AG$6<=Hypothèses!$C$44)*(D43:AG43)) -> 0 | D43: =0 -> 0 | E43: =IF(Hypothèses!$C$53=Paramètres!$C$33,MAX(0,D41)*Paramètres!$C$10*Hypothèses!$C$36,0) -> 0 | F43: =IF(Hypothèses!$C$53=Paramètres!$C$33,MAX(0,E41)*Paramètres!$C$10*Hypothèses!$C$36,0) -> 0 | G43: =IF(Hypothèses!$C$53=Paramètres!$C$33,MAX(0,F41)*Paramètres!$C$10*Hypothèses!$C$36,0) -> 0 | H43: =IF(Hypothèses!$C$53=Paramètres!$C$33,MAX(0,G41)*Paramètres!$C$10*Hypothèses!$C$36,0) -> 0 | I43: =IF(Hypothèses!$C$53=Paramètres!$C$33,MAX(0,H41)*Paramètres!$C$10*Hypothèses!$C$36,0) -> 0 | J43: =IF(Hypothèses!$C$53=Paramètres!$C$33,MAX(0,I41)*Paramètres!$C$10*Hypothèses!$C$36,0) -> 0 | K43: =IF(Hypothèses!$C$53=Paramètres!$C$33,MAX(0,J41)*Paramètres!$C$10*Hypothèses!$C$36,0) -> 0 | L43: =IF(Hypothèses!$C$53=Paramètres!$C$33,MAX(0,K41)*Paramètres!$C$10*Hypothèses!$C$36,0) -> 0 | ... AG43: =IF(Hypothèses!$C$53=Paramètres!$C$33,MAX(0,AF41)*Paramètres!$C$10*Hypothèses!$C$36,0) -> 0
B44: Flux net en poche (après crédit et impôt) | C44: =SUMPRODUCT((D$6:AG$6<=Hypothèses!$C$44)*(D44:AG44)) -> -57258.837 | D44: =D9-D10-D17-D42+D43 -> -3600.7718 | E44: =E9-E10-E17-E42+E43 -> -5680.4862 | F44: =F9-F10-F17-F42+F43 -> -5742.7468 | G44: =G9-G10-G17-G42+G43 -> -5808.2994 | H44: =H9-H10-H17-H42+H43 -> -5877.2651 | I44: =I9-I10-I17-I42+I43 -> -5949.769 | J44: =J9-J10-J17-J42+J43 -> -6025.9404 | K44: =K9-K10-K17-K42+K43 -> -6105.913 | ... AG44: =AG9-AG10-AG17-AG42+AG43 -> 7116.6423
B46: MEUBLÉ, LMNP MICRO-BIC
B47: Base imposable (loyer moins abattement du type de meublé) | C47: =SUMPRODUCT((D$6:AG$6<=Hypothèses!$C$44)*(D47:AG47)) -> 69050.603 | D47: =D9*(1-IF(ISNUMBER(MATCH(Hypothèses!$C$49,Paramètres!$B$27:$B$29,0)),INDEX(Paramètres!$C$27:$C$29,MATCH(Hypothèses!$C$49,Paramètres!$B$27:$B$29,0)),0)) -> 6600 | E47: =E9*(1-IF(ISNUMBER(MATCH(Hypothèses!$C$49,Paramètres!$B$27:$B$29,0)),INDEX(Paramètres!$C$27:$C$29,MATCH(Hypothèses!$C$49,Paramètres!$B$27:$B$29,0)),0)) -> 6666 | F47: =F9*(1-IF(ISNUMBER(MATCH(Hypothèses!$C$49,Paramètres!$B$27:$B$29,0)),INDEX(Paramètres!$C$27:$C$29,MATCH(Hypothèses!$C$49,Paramètres!$B$27:$B$29,0)),0)) -> 6732.66 | G47: =G9*(1-IF(ISNUMBER(MATCH(Hypothèses!$C$49,Paramètres!$B$27:$B$29,0)),INDEX(Paramètres!$C$27:$C$29,MATCH(Hypothèses!$C$49,Paramètres!$B$27:$B$29,0)),0)) -> 6799.9866 | H47: =H9*(1-IF(ISNUMBER(MATCH(Hypothèses!$C$49,Paramètres!$B$27:$B$29,0)),INDEX(Paramètres!$C$27:$C$29,MATCH(Hypothèses!$C$49,Paramètres!$B$27:$B$29,0)),0)) -> 6867.9865 | I47: =I9*(1-IF(ISNUMBER(MATCH(Hypothèses!$C$49,Paramètres!$B$27:$B$29,0)),INDEX(Paramètres!$C$27:$C$29,MATCH(Hypothèses!$C$49,Paramètres!$B$27:$B$29,0)),0)) -> 6936.6663 | J47: =J9*(1-IF(ISNUMBER(MATCH(Hypothèses!$C$49,Paramètres!$B$27:$B$29,0)),INDEX(Paramètres!$C$27:$C$29,MATCH(Hypothèses!$C$49,Paramètres!$B$27:$B$29,0)),0)) -> 7006.033 | K47: =K9*(1-IF(ISNUMBER(MATCH(Hypothèses!$C$49,Paramètres!$B$27:$B$29,0)),INDEX(Paramètres!$C$27:$C$29,MATCH(Hypothèses!$C$49,Paramètres!$B$27:$B$29,0)),0)) -> 7076.0933 | ... AG47: =AG9*(1-IF(ISNUMBER(MATCH(Hypothèses!$C$49,Paramètres!$B$27:$B$29,0)),INDEX(Paramètres!$C$27:$C$29,MATCH(Hypothèses!$C$49,Paramètres!$B$27:$B$29,0)),0)) -> 8807.7256
B48: Impôt sur le revenu et prélèvements sociaux | C48: =SUMPRODUCT((D$6:AG$6<=Hypothèses!$C$44)*(D48:AG48)) -> 33558.593 | D48: =D47*(Hypothèses!$C$36+Paramètres!$C$9) -> 3207.6 | E48: =E47*(Hypothèses!$C$36+Paramètres!$C$9) -> 3239.676 | F48: =F47*(Hypothèses!$C$36+Paramètres!$C$9) -> 3272.0728 | G48: =G47*(Hypothèses!$C$36+Paramètres!$C$9) -> 3304.7935 | H48: =H47*(Hypothèses!$C$36+Paramètres!$C$9) -> 3337.8414 | I48: =I47*(Hypothèses!$C$36+Paramètres!$C$9) -> 3371.2198 | J48: =J47*(Hypothèses!$C$36+Paramètres!$C$9) -> 3404.932 | K48: =K47*(Hypothèses!$C$36+Paramètres!$C$9) -> 3438.9814 | ... AG48: =AG47*(Hypothèses!$C$36+Paramètres!$C$9) -> 4280.5546
B49: Économie d'IR sur la CSG déductible (option) | C49: =SUMPRODUCT((D$6:AG$6<=Hypothèses!$C$44)*(D49:AG49)) -> 0 | D49: =0 -> 0 | E49: =IF(Hypothèses!$C$53=Paramètres!$C$33,MAX(0,D47)*Paramètres!$C$10*Hypothèses!$C$36,0) -> 0 | F49: =IF(Hypothèses!$C$53=Paramètres!$C$33,MAX(0,E47)*Paramètres!$C$10*Hypothèses!$C$36,0) -> 0 | G49: =IF(Hypothèses!$C$53=Paramètres!$C$33,MAX(0,F47)*Paramètres!$C$10*Hypothèses!$C$36,0) -> 0 | H49: =IF(Hypothèses!$C$53=Paramètres!$C$33,MAX(0,G47)*Paramètres!$C$10*Hypothèses!$C$36,0) -> 0 | I49: =IF(Hypothèses!$C$53=Paramètres!$C$33,MAX(0,H47)*Paramètres!$C$10*Hypothèses!$C$36,0) -> 0 | J49: =IF(Hypothèses!$C$53=Paramètres!$C$33,MAX(0,I47)*Paramètres!$C$10*Hypothèses!$C$36,0) -> 0 | K49: =IF(Hypothèses!$C$53=Paramètres!$C$33,MAX(0,J47)*Paramètres!$C$10*Hypothèses!$C$36,0) -> 0 | L49: =IF(Hypothèses!$C$53=Paramètres!$C$33,MAX(0,K47)*Paramètres!$C$10*Hypothèses!$C$36,0) -> 0 | ... AG49: =IF(Hypothèses!$C$53=Paramètres!$C$33,MAX(0,AF47)*Paramètres!$C$10*Hypothèses!$C$36,0) -> 0
B50: Flux net en poche (après crédit, CFE et impôt) | C50: =SUMPRODUCT((D$6:AG$6<=Hypothèses!$C$44)*(D50:AG50)) -> -75002.114 | D50: =D9-D10-D11-D17-D48+D49 -> -7800.2983 | E50: =E9-E10-E11-E17-E48+E49 -> -7735.3743 | F50: =F9-F10-F11-F17-F48+F49 -> -7669.801 | G50: =G9-G10-G11-G17-G48+G49 -> -7603.5721 | H50: =H9-H10-H11-H17-H48+H49 -> -7536.6808 | I50: =I9-I10-I11-I17-I48+I49 -> -7469.1206 | J50: =J9-J10-J11-J17-J48+J49 -> -7400.8849 | K50: =K9-K10-K11-K17-K48+K49 -> -7331.9667 | ... AG50: =AG9-AG10-AG11-AG17-AG48+AG49 -> 8664.133
B52: MEUBLÉ, LMNP RÉEL
B53: Résultat avant amortissement | C53: =SUMPRODUCT((D$6:AG$6<=Hypothèses!$C$44)*(D53:AG53)) -> 37238.308 | D53: =D9-D10-D11-D12-(D14+D16)-IF(AND(D$6=1,Hypothèses!$C$51=Paramètres!$D$34),Hypothèses!$C$9,0) -> 2126.9119 | E53: =E9-E10-E11-E12-(E14+E16)-IF(AND(E$6=1,Hypothèses!$C$51=Paramètres!$D$34),Hypothèses!$C$9,0) -> 2457.0761 | F53: =F9-F10-F11-F12-(F14+F16)-IF(AND(F$6=1,Hypothèses!$C$51=Paramètres!$D$34),Hypothèses!$C$9,0) -> 2796.017 | G53: =G9-G10-G11-G12-(G14+G16)-IF(AND(G$6=1,Hypothèses!$C$51=Paramètres!$D$34),Hypothèses!$C$9,0) -> 3144.0029 | H53: =H9-H10-H11-H12-(H14+H16)-IF(AND(H$6=1,Hypothèses!$C$51=Paramètres!$D$34),Hypothèses!$C$9,0) -> 3501.311 | I53: =I9-I10-I11-I12-(I14+I16)-IF(AND(I$6=1,Hypothèses!$C$51=Paramètres!$D$34),Hypothèses!$C$9,0) -> 3868.227 | J53: =J9-J10-J11-J12-(J14+J16)-IF(AND(J$6=1,Hypothèses!$C$51=Paramètres!$D$34),Hypothèses!$C$9,0) -> 4245.0463 | K53: =K9-K10-K11-K12-(K14+K16)-IF(AND(K$6=1,Hypothèses!$C$51=Paramètres!$D$34),Hypothèses!$C$9,0) -> 4632.0734 | ... AG53: =AG9-AG10-AG11-AG12-(AG14+AG16)-IF(AND(AG$6=1,Hypothèses!$C$51=Paramètres!$D$34),Hypothèses!$C$9,0) -> 12277.436
B54: Amortissements différés en début d'année (art. 39 C) | D54: =0 -> 0 | E54: =D56 -> 5469.2786 | F54: =E56 -> 10608.393 | G54: =F56 -> 15408.566 | H54: =G56 -> 19860.754 | I54: =H56 -> 23955.633 | J54: =I56 -> 27683.597 | K54: =J56 -> 31034.741 | L54: =K56 -> 32856.001 | ... AG54: =AF56 -> 0
B55: Amortissement déduit (dans la limite du résultat) | C55: =SUMPRODUCT((D$6:AG$6<=Hypothèses!$C$44)*(D55:AG55)) -> 37238.308 | D55: =MIN(D22+D54,MAX(0,D53)) -> 2126.9119 | E55: =MIN(E22+E54,MAX(0,E53)) -> 2457.0761 | F55: =MIN(F22+F54,MAX(0,F53)) -> 2796.017 | G55: =MIN(G22+G54,MAX(0,G53)) -> 3144.0029 | H55: =MIN(H22+H54,MAX(0,H53)) -> 3501.311 | I55: =MIN(I22+I54,MAX(0,I53)) -> 3868.227 | J55: =MIN(J22+J54,MAX(0,J53)) -> 4245.0463 | K55: =MIN(K22+K54,MAX(0,K53)) -> 4632.0734 | ... AG55: =MIN(AG22+AG54,MAX(0,AG53)) -> 6120
B56: Amortissements différés en fin d'année (sans limite de durée) | C56: =INDEX(D56:AG56,Hypothèses!$C$44) -> 35295.025 | D56: =D54+D22-D55 -> 5469.2786 | E56: =E54+E22-E55 -> 10608.393 | F56: =F54+F22-F55 -> 15408.566 | G56: =G54+G22-G55 -> 19860.754 | H56: =H54+H22-H55 -> 23955.633 | I56: =I54+I22-I55 -> 27683.597 | J56: =J54+J22-J55 -> 31034.741 | K56: =K54+K22-K55 -> 32856.001 | ... AG56: =AG54+AG22-AG55 -> 0
B57: Déficit BIC non professionnel en début d'année | D57: =0 -> 0 | E57: =D60 -> 0 | F57: =E60 -> 0 | G57: =F60 -> 0 | H57: =G60 -> 0 | I57: =H60 -> 0 | J57: =I60 -> 0 | K57: =J60 -> 0 | L57: =K60 -> 0 | ... AG57: =AF60 -> 0
B58: Déficit BIC créé | C58: =SUMPRODUCT((D$6:AG$6<=Hypothèses!$C$44)*(D58:AG58)) -> 0 | D58: =MAX(0,-D53) -> 0 | E58: =MAX(0,-E53) -> 0 | F58: =MAX(0,-F53) -> 0 | G58: =MAX(0,-G53) -> 0 | H58: =MAX(0,-H53) -> 0 | I58: =MAX(0,-I53) -> 0 | J58: =MAX(0,-J53) -> 0 | K58: =MAX(0,-K53) -> 0 | ... AG58: =MAX(0,-AG53) -> 0
B59: Déficit BIC imputé | C59: =SUMPRODUCT((D$6:AG$6<=Hypothèses!$C$44)*(D59:AG59)) -> 0 | D59: =MIN(D57,MAX(0,D53)-D55) -> 0 | E59: =MIN(E57,MAX(0,E53)-E55) -> 0 | F59: =MIN(F57,MAX(0,F53)-F55) -> 0 | G59: =MIN(G57,MAX(0,G53)-G55) -> 0 | H59: =MIN(H57,MAX(0,H53)-H55) -> 0 | I59: =MIN(I57,MAX(0,I53)-I55) -> 0 | J59: =MIN(J57,MAX(0,J53)-J55) -> 0 | K59: =MIN(K57,MAX(0,K53)-K55) -> 0 | ... AG59: =MIN(AG57,MAX(0,AG53)-AG55) -> 0
B60: Déficit BIC reportable en fin d'année (10 ans) | C60: =INDEX(D60:AG60,Hypothèses!$C$44) -> 0 | D60: =D57+D58-D59 -> 0 | E60: =E57+E58-E59 -> 0 | F60: =F57+F58-F59 -> 0 | G60: =G57+G58-G59 -> 0 | H60: =H57+H58-H59 -> 0 | I60: =I57+I58-I59 -> 0 | J60: =J57+J58-J59 -> 0 | K60: =K57+K58-K59 -> 0 | ... AG60: =AG57+AG58-AG59 -> 0
B61: Base imposable | C61: =SUMPRODUCT((D$6:AG$6<=Hypothèses!$C$44)*(D61:AG61)) -> 0 | D61: =MAX(0,D53)-D55-D59 -> 0 | E61: =MAX(0,E53)-E55-E59 -> 0 | F61: =MAX(0,F53)-F55-F59 -> 0 | G61: =MAX(0,G53)-G55-G59 -> 0 | H61: =MAX(0,H53)-H55-H59 -> 0 | I61: =MAX(0,I53)-I55-I59 -> 0 | J61: =MAX(0,J53)-J55-J59 -> 0 | K61: =MAX(0,K53)-K55-K59 -> 0 | ... AG61: =MAX(0,AG53)-AG55-AG59 -> 6157.4357
B62: Impôt sur le revenu et prélèvements sociaux | C62: =SUMPRODUCT((D$6:AG$6<=Hypothèses!$C$44)*(D62:AG62)) -> 0 | D62: =D61*(Hypothèses!$C$36+Paramètres!$C$9) -> 0 | E62: =E61*(Hypothèses!$C$36+Paramètres!$C$9) -> 0 | F62: =F61*(Hypothèses!$C$36+Paramètres!$C$9) -> 0 | G62: =G61*(Hypothèses!$C$36+Paramètres!$C$9) -> 0 | H62: =H61*(Hypothèses!$C$36+Paramètres!$C$9) -> 0 | I62: =I61*(Hypothèses!$C$36+Paramètres!$C$9) -> 0 | J62: =J61*(Hypothèses!$C$36+Paramètres!$C$9) -> 0 | K62: =K61*(Hypothèses!$C$36+Paramètres!$C$9) -> 0 | ... AG62: =AG61*(Hypothèses!$C$36+Paramètres!$C$9) -> 2992.5137
B63: Part de l'immeuble (bâti et travaux) dans l'amortissement déduit | D63: =IF(D22>0,(D19+D20)/D22,IF(((Hypothèses!$C$7+IF(Hypothèses!$C$51=Paramètres!$D$33,Hypothèses!$C$9,0))*(1-Hypothèses!$C$54))+Hypothèses!$C$10+Hypothèses!$C$11>0,(((Hypothèses!$C$7+IF(Hypothèses!$C$51=Paramètres!$D$33,Hypothèses!$C$9,0))*(1-Hypothèses!$C$54))+Hypothèses!$C$10)/(((Hypothèses!$C$7+IF(Hypothèses!$C$51=Paramètres!$D$33,Hypothèses!$C$9,0))*(1-Hypothèses!$C$54))+Hypothèses!$C$10+Hypothèses!$C$11),0)) -> 0.84954865 | E63: =IF(E22>0,(E19+E20)/E22,IF(((Hypothèses!$C$7+IF(Hypothèses!$C$51=Paramètres!$D$33,Hypothèses!$C$9,0))*(1-Hypothèses!$C$54))+Hypothèses!$C$10+Hypothèses!$C$11>0,(((Hypothèses!$C$7+IF(Hypothèses!$C$51=Paramètres!$D$33,Hypothèses!$C$9,0))*(1-Hypothèses!$C$54))+Hypothèses!$C$10)/(((Hypothèses!$C$7+IF(Hypothèses!$C$51=Paramètres!$D$33,Hypothèses!$C$9,0))*(1-Hypothèses!$C$54))+Hypothèses!$C$10+Hypothèses!$C$11),0)) -> 0.84954865 | F63: =IF(F22>0,(F19+F20)/F22,IF(((Hypothèses!$C$7+IF(Hypothèses!$C$51=Paramètres!$D$33,Hypothèses!$C$9,0))*(1-Hypothèses!$C$54))+Hypothèses!$C$10+Hypothèses!$C$11>0,(((Hypothèses!$C$7+IF(Hypothèses!$C$51=Paramètres!$D$33,Hypothèses!$C$9,0))*(1-Hypothèses!$C$54))+Hypothèses!$C$10)/(((Hypothèses!$C$7+IF(Hypothèses!$C$51=Paramètres!$D$33,Hypothèses!$C$9,0))*(1-Hypothèses!$C$54))+Hypothèses!$C$10+Hypothèses!$C$11),0)) -> 0.84954865 | G63: =IF(G22>0,(G19+G20)/G22,IF(((Hypothèses!$C$7+IF(Hypothèses!$C$51=Paramètres!$D$33,Hypothèses!$C$9,0))*(1-Hypothèses!$C$54))+Hypothèses!$C$10+Hypothèses!$C$11>0,(((Hypothèses!$C$7+IF(Hypothèses!$C$51=Paramètres!$D$33,Hypothèses!$C$9,0))*(1-Hypothèses!$C$54))+Hypothèses!$C$10)/(((Hypothèses!$C$7+IF(Hypothèses!$C$51=Paramètres!$D$33,Hypothèses!$C$9,0))*(1-Hypothèses!$C$54))+Hypothèses!$C$10+Hypothèses!$C$11),0)) -> 0.84954865 | H63: =IF(H22>0,(H19+H20)/H22,IF(((Hypothèses!$C$7+IF(Hypothèses!$C$51=Paramètres!$D$33,Hypothèses!$C$9,0))*(1-Hypothèses!$C$54))+Hypothèses!$C$10+Hypothèses!$C$11>0,(((Hypothèses!$C$7+IF(Hypothèses!$C$51=Paramètres!$D$33,Hypothèses!$C$9,0))*(1-Hypothèses!$C$54))+Hypothèses!$C$10)/(((Hypothèses!$C$7+IF(Hypothèses!$C$51=Paramètres!$D$33,Hypothèses!$C$9,0))*(1-Hypothèses!$C$54))+Hypothèses!$C$10+Hypothèses!$C$11),0)) -> 0.84954865 | I63: =IF(I22>0,(I19+I20)/I22,IF(((Hypothèses!$C$7+IF(Hypothèses!$C$51=Paramètres!$D$33,Hypothèses!$C$9,0))*(1-Hypothèses!$C$54))+Hypothèses!$C$10+Hypothèses!$C$11>0,(((Hypothèses!$C$7+IF(Hypothèses!$C$51=Paramètres!$D$33,Hypothèses!$C$9,0))*(1-Hypothèses!$C$54))+Hypothèses!$C$10)/(((Hypothèses!$C$7+IF(Hypothèses!$C$51=Paramètres!$D$33,Hypothèses!$C$9,0))*(1-Hypothèses!$C$54))+Hypothèses!$C$10+Hypothèses!$C$11),0)) -> 0.84954865 | J63: =IF(J22>0,(J19+J20)/J22,IF(((Hypothèses!$C$7+IF(Hypothèses!$C$51=Paramètres!$D$33,Hypothèses!$C$9,0))*(1-Hypothèses!$C$54))+Hypothèses!$C$10+Hypothèses!$C$11>0,(((Hypothèses!$C$7+IF(Hypothèses!$C$51=Paramètres!$D$33,Hypothèses!$C$9,0))*(1-Hypothèses!$C$54))+Hypothèses!$C$10)/(((Hypothèses!$C$7+IF(Hypothèses!$C$51=Paramètres!$D$33,Hypothèses!$C$9,0))*(1-Hypothèses!$C$54))+Hypothèses!$C$10+Hypothèses!$C$11),0)) -> 0.84954865 | K63: =IF(K22>0,(K19+K20)/K22,IF(((Hypothèses!$C$7+IF(Hypothèses!$C$51=Paramètres!$D$33,Hypothèses!$C$9,0))*(1-Hypothèses!$C$54))+Hypothèses!$C$10+Hypothèses!$C$11>0,(((Hypothèses!$C$7+IF(Hypothèses!$C$51=Paramètres!$D$33,Hypothèses!$C$9,0))*(1-Hypothèses!$C$54))+Hypothèses!$C$10)/(((Hypothèses!$C$7+IF(Hypothèses!$C$51=Paramètres!$D$33,Hypothèses!$C$9,0))*(1-Hypothèses!$C$54))+Hypothèses!$C$10+Hypothèses!$C$11),0)) -> 1 | ... AG63: =IF(AG22>0,(AG19+AG20)/AG22,IF(((Hypothèses!$C$7+IF(Hypothèses!$C$51=Paramètres!$D$33,Hypothèses!$C$9,0))*(1-Hypothèses!$C$54))+Hypothèses!$C$10+Hypothèses!$C$11>0,(((Hypothèses!$C$7+IF(Hypothèses!$C$51=Paramètres!$D$33,Hypothèses!$C$9,0))*(1-Hypothèses!$C$54))+Hypothèses!$C$10)/(((Hypothèses!$C$7+IF(Hypothèses!$C$51=Paramètres!$D$33,Hypothèses!$C$9,0))*(1-Hypothèses!$C$54))+Hypothèses!$C$10+Hypothèses!$C$11),0)) -> 1
B64: Amortissement à réintégrer dans la plus-value (art. 150 VB) | C64: =SUMPRODUCT((D$6:AG$6<=Hypothèses!$C$44)*(D64:AG64)) -> 33907.527 | D64: =D55*D63 -> 1806.9151 | E64: =E55*E63 -> 2087.4057 | F64: =F55*F63 -> 2375.3524 | G64: =G55*G63 -> 2670.9834 | H64: =H55*H63 -> 2974.534 | I64: =I55*I63 -> 3286.247 | J64: =J55*J63 -> 3606.3733 | K64: =K55*K63 -> 4632.0734 | ... AG64: =AG55*AG63 -> 6120
B65: Économie d'IR sur la CSG déductible (option) | C65: =SUMPRODUCT((D$6:AG$6<=Hypothèses!$C$44)*(D65:AG65)) -> 0 | D65: =0 -> 0 | E65: =IF(Hypothèses!$C$53=Paramètres!$C$33,MAX(0,D61)*Paramètres!$C$10*Hypothèses!$C$36,0) -> 0 | F65: =IF(Hypothèses!$C$53=Paramètres!$C$33,MAX(0,E61)*Paramètres!$C$10*Hypothèses!$C$36,0) -> 0 | G65: =IF(Hypothèses!$C$53=Paramètres!$C$33,MAX(0,F61)*Paramètres!$C$10*Hypothèses!$C$36,0) -> 0 | H65: =IF(Hypothèses!$C$53=Paramètres!$C$33,MAX(0,G61)*Paramètres!$C$10*Hypothèses!$C$36,0) -> 0 | I65: =IF(Hypothèses!$C$53=Paramètres!$C$33,MAX(0,H61)*Paramètres!$C$10*Hypothèses!$C$36,0) -> 0 | J65: =IF(Hypothèses!$C$53=Paramètres!$C$33,MAX(0,I61)*Paramètres!$C$10*Hypothèses!$C$36,0) -> 0 | K65: =IF(Hypothèses!$C$53=Paramètres!$C$33,MAX(0,J61)*Paramètres!$C$10*Hypothèses!$C$36,0) -> 0 | L65: =IF(Hypothèses!$C$53=Paramètres!$C$33,MAX(0,K61)*Paramètres!$C$10*Hypothèses!$C$36,0) -> 0 | ... AG65: =IF(Hypothèses!$C$53=Paramètres!$C$33,MAX(0,AF61)*Paramètres!$C$10*Hypothèses!$C$36,0) -> 0
B66: Flux net en poche (après crédit, CFE, comptable et impôt) | C66: =SUMPRODUCT((D$6:AG$6<=Hypothèses!$C$44)*(D66:AG66)) -> -46674.627 | D66: =D9-D10-D11-D12-D17-D62+D65 -> -5092.6983 | E66: =E9-E10-E11-E12-E17-E62+E65 -> -5000.6983 | F66: =F9-F10-F11-F12-F17-F62+F65 -> -4907.7783 | G66: =G9-G10-G11-G12-G17-G62+G65 -> -4813.9291 | H66: =H9-H10-H11-H12-H17-H62+H65 -> -4719.1414 | I66: =I9-I10-I11-I12-I17-I62+I65 -> -4623.4058 | J66: =J9-J10-J11-J12-J17-J62+J65 -> -4526.7129 | K66: =K9-K10-K11-K12-K17-K62+K65 -> -4429.053 | ... AG66: =AG9-AG10-AG11-AG12-AG17-AG62+AG65 -> 9284.9219
B68: SCI À L'IS
B69: Résultat fiscal de la société avant report | C69: =SUMPRODUCT((D$6:AG$6<=Hypothèses!$C$44)*(D69:AG69)) -> -42618.574 | D69: =D9-D10-IF(Hypothèses!$C$11>0,D11,0)-D13-(D14+D16)-D22-IF(AND(D$6=1,Hypothèses!$C$51=Paramètres!$D$34),Hypothèses!$C$9,0) -> -6169.2786 | E69: =E9-E10-IF(Hypothèses!$C$11>0,E11,0)-E13-(E14+E16)-E22-IF(AND(E$6=1,Hypothèses!$C$51=Paramètres!$D$34),Hypothèses!$C$9,0) -> -5846.1144 | F69: =F9-F10-IF(Hypothèses!$C$11>0,F11,0)-F13-(F14+F16)-F22-IF(AND(F$6=1,Hypothèses!$C$51=Paramètres!$D$34),Hypothèses!$C$9,0) -> -5514.2435 | G69: =G9-G10-IF(Hypothèses!$C$11>0,G11,0)-G13-(G14+G16)-G22-IF(AND(G$6=1,Hypothèses!$C$51=Paramètres!$D$34),Hypothèses!$C$9,0) -> -5173.3982 | H69: =H9-H10-IF(Hypothèses!$C$11>0,H11,0)-H13-(H14+H16)-H22-IF(AND(H$6=1,Hypothèses!$C$51=Paramètres!$D$34),Hypothèses!$C$9,0) -> -4823.3023 | I69: =I9-I10-IF(Hypothèses!$C$11>0,I11,0)-I13-(I14+I16)-I22-IF(AND(I$6=1,Hypothèses!$C$51=Paramètres!$D$34),Hypothèses!$C$9,0) -> -4463.6705 | J69: =J9-J10-IF(Hypothèses!$C$11>0,J11,0)-J13-(J14+J16)-J22-IF(AND(J$6=1,Hypothèses!$C$51=Paramètres!$D$34),Hypothèses!$C$9,0) -> -4094.2083 | K69: =K9-K10-IF(Hypothèses!$C$11>0,K11,0)-K13-(K14+K16)-K22-IF(AND(K$6=1,Hypothèses!$C$51=Paramètres!$D$34),Hypothèses!$C$9,0) -> -2571.7547 | ... AG69: =AG9-AG10-IF(Hypothèses!$C$11>0,AG11,0)-AG13-(AG14+AG16)-AG22-IF(AND(AG$6=1,Hypothèses!$C$51=Paramètres!$D$34),Hypothèses!$C$9,0) -> 5223.283
B70: Déficit reportable en début d'exercice | D70: =0 -> 0 | E70: =D72 -> 6169.2786 | F70: =E72 -> 12015.393 | G70: =F72 -> 17529.636 | H70: =G72 -> 22703.035 | I70: =H72 -> 27526.337 | J70: =I72 -> 31990.008 | K70: =J72 -> 36084.216 | L70: =K72 -> 38655.971 | ... AG70: =AF72 -> 0
B71: Déficit imputé | C71: =SUMPRODUCT((D$6:AG$6<=Hypothèses!$C$44)*(D71:AG71)) -> 0 | D71: =MIN(D70,MAX(0,D69)) -> 0 | E71: =MIN(E70,MAX(0,E69)) -> 0 | F71: =MIN(F70,MAX(0,F69)) -> 0 | G71: =MIN(G70,MAX(0,G69)) -> 0 | H71: =MIN(H70,MAX(0,H69)) -> 0 | I71: =MIN(I70,MAX(0,I69)) -> 0 | J71: =MIN(J70,MAX(0,J69)) -> 0 | K71: =MIN(K70,MAX(0,K69)) -> 0 | ... AG71: =MIN(AG70,MAX(0,AG69)) -> 0
B72: Déficit reportable en fin d'exercice (sans limite) | C72: =INDEX(D72:AG72,Hypothèses!$C$44) -> 42618.574 | D72: =D70+MAX(0,-D69)-D71 -> 6169.2786 | E72: =E70+MAX(0,-E69)-E71 -> 12015.393 | F72: =F70+MAX(0,-F69)-F71 -> 17529.636 | G72: =G70+MAX(0,-G69)-G71 -> 22703.035 | H72: =H70+MAX(0,-H69)-H71 -> 27526.337 | I72: =I70+MAX(0,-I69)-I71 -> 31990.008 | J72: =J70+MAX(0,-J69)-J71 -> 36084.216 | K72: =K70+MAX(0,-K69)-K71 -> 38655.971 | ... AG72: =AG70+MAX(0,-AG69)-AG71 -> 0
B73: Bénéfice imposable | C73: =SUMPRODUCT((D$6:AG$6<=Hypothèses!$C$44)*(D73:AG73)) -> 0 | D73: =MAX(0,D69)-D71 -> 0 | E73: =MAX(0,E69)-E71 -> 0 | F73: =MAX(0,F69)-F71 -> 0 | G73: =MAX(0,G69)-G71 -> 0 | H73: =MAX(0,H69)-H71 -> 0 | I73: =MAX(0,I69)-I71 -> 0 | J73: =MAX(0,J69)-J71 -> 0 | K73: =MAX(0,K69)-K71 -> 0 | ... AG73: =MAX(0,AG69)-AG71 -> 5223.283
B74: Impôt sur les sociétés | C74: =SUMPRODUCT((D$6:AG$6<=Hypothèses!$C$44)*(D74:AG74)) -> 0 | D74: =(MIN(D73,Paramètres!$C$16)*Paramètres!$C$15+MAX(0,D73-Paramètres!$C$16)*Paramètres!$C$17) -> 0 | E74: =(MIN(E73,Paramètres!$C$16)*Paramètres!$C$15+MAX(0,E73-Paramètres!$C$16)*Paramètres!$C$17) -> 0 | F74: =(MIN(F73,Paramètres!$C$16)*Paramètres!$C$15+MAX(0,F73-Paramètres!$C$16)*Paramètres!$C$17) -> 0 | G74: =(MIN(G73,Paramètres!$C$16)*Paramètres!$C$15+MAX(0,G73-Paramètres!$C$16)*Paramètres!$C$17) -> 0 | H74: =(MIN(H73,Paramètres!$C$16)*Paramètres!$C$15+MAX(0,H73-Paramètres!$C$16)*Paramètres!$C$17) -> 0 | I74: =(MIN(I73,Paramètres!$C$16)*Paramètres!$C$15+MAX(0,I73-Paramètres!$C$16)*Paramètres!$C$17) -> 0 | J74: =(MIN(J73,Paramètres!$C$16)*Paramètres!$C$15+MAX(0,J73-Paramètres!$C$16)*Paramètres!$C$17) -> 0 | K74: =(MIN(K73,Paramètres!$C$16)*Paramètres!$C$15+MAX(0,K73-Paramètres!$C$16)*Paramètres!$C$17) -> 0 | ... AG74: =(MIN(AG73,Paramètres!$C$16)*Paramètres!$C$15+MAX(0,AG73-Paramètres!$C$16)*Paramètres!$C$17) -> 783.49244
B75: Résultat comptable après IS | C75: =SUMPRODUCT((D$6:AG$6<=Hypothèses!$C$44)*(D75:AG75)) -> -42618.574 | D75: =D69-D74 -> -6169.2786 | E75: =E69-E74 -> -5846.1144 | F75: =F69-F74 -> -5514.2435 | G75: =G69-G74 -> -5173.3982 | H75: =H69-H74 -> -4823.3023 | I75: =I69-I74 -> -4463.6705 | J75: =J69-J74 -> -4094.2083 | K75: =K69-K74 -> -2571.7547 | ... AG75: =AG69-AG74 -> 4439.7905
B76: Réserves distribuables en début d'exercice | D76: =0 -> 0 | E76: =D89 -> -6169.2786 | F76: =E89 -> -12015.393 | G76: =F89 -> -17529.636 | H76: =G89 -> -22703.035 | I76: =H89 -> -27526.337 | J76: =I89 -> -31990.008 | K76: =J89 -> -36084.216 | L76: =K89 -> -38655.971 | ... AG76: =AF89 -> 6795.1801
B77: Trésorerie générée (après annuité et IS) | C77: =SUMPRODUCT((D$6:AG$6<=Hypothèses!$C$44)*(D77:AG77)) -> -53998.176 | D77: =D9-D10-IF(Hypothèses!$C$11>0,D11,0)-D13-D17-D74 -> -5792.6983 | E77: =E9-E10-IF(Hypothèses!$C$11>0,E11,0)-E13-E17-E74 -> -5707.6983 | F77: =F9-F10-IF(Hypothèses!$C$11>0,F11,0)-F13-F17-F74 -> -5621.8483 | G77: =G9-G10-IF(Hypothèses!$C$11>0,G11,0)-G13-G17-G74 -> -5535.1398 | H77: =H9-H10-IF(Hypothèses!$C$11>0,H11,0)-H13-H17-H74 -> -5447.5642 | I77: =I9-I10-IF(Hypothèses!$C$11>0,I11,0)-I13-I17-I74 -> -5359.1129 | J77: =J9-J10-IF(Hypothèses!$C$11>0,J11,0)-J13-J17-J74 -> -5269.777 | K77: =K9-K10-IF(Hypothèses!$C$11>0,K11,0)-K13-K17-K74 -> -5179.5478 | ... AG77: =AG9-AG10-IF(Hypothèses!$C$11>0,AG11,0)-AG13-AG17-AG74 -> 10559.791
B78: Trésorerie en début d'exercice | D78: =0 -> 0 | E78: =D87 -> 0 | F78: =E87 -> 0 | G78: =F87 -> 0 | H78: =G87 -> 0 | I78: =H87 -> 0 | J78: =I87 -> 0 | K78: =J87 -> 0 | L78: =K87 -> 0 | ... AG78: =AF87 -> 95967.612
B79: Apport en compte courant par l'associé (trésorerie négative) | C79: =SUMPRODUCT((D$6:AG$6<=Hypothèses!$C$44)*(D79:AG79)) -> 53998.176 | D79: =MAX(0,-(D78+D77)) -> 5792.6983 | E79: =MAX(0,-(E78+E77)) -> 5707.6983 | F79: =MAX(0,-(F78+F77)) -> 5621.8483 | G79: =MAX(0,-(G78+G77)) -> 5535.1398 | H79: =MAX(0,-(H78+H77)) -> 5447.5642 | I79: =MAX(0,-(I78+I77)) -> 5359.1129 | J79: =MAX(0,-(J78+J77)) -> 5269.777 | K79: =MAX(0,-(K78+K77)) -> 5179.5478 | ... AG79: =MAX(0,-(AG78+AG77)) -> 0
B80: Trésorerie disponible | D80: =D78+D77+D79 -> 0 | E80: =E78+E77+E79 -> 0 | F80: =F78+F77+F79 -> 0 | G80: =G78+G77+G79 -> 0 | H80: =H78+H77+H79 -> 0 | I80: =I78+I77+I79 -> 0 | J80: =J78+J77+J79 -> 0 | K80: =K78+K77+K79 -> 0 | ... AG80: =AG78+AG77+AG79 -> 106527.4
B81: Compte courant d'associé en début d'exercice | D81: =Hypothèses!$C$30 -> 29000 | E81: =D88 -> 34792.698 | F81: =E88 -> 40500.397 | G81: =F88 -> 46122.245 | H81: =G88 -> 51657.385 | I81: =H88 -> 57104.949 | J81: =I88 -> 62464.062 | K81: =J88 -> 67733.839 | L81: =K88 -> 72913.386 | ... AG81: =AF88 -> 127692.43
B82: Remboursement du compte courant (sans impôt, si distribution) | C82: =SUMPRODUCT((D$6:AG$6<=Hypothèses!$C$44)*(D82:AG82)) -> 0 | D82: =IF(Hypothèses!$C$50=Paramètres!$C$33,MIN(D80,D81+D79),0) -> 0 | E82: =IF(Hypothèses!$C$50=Paramètres!$C$33,MIN(E80,E81+E79),0) -> 0 | F82: =IF(Hypothèses!$C$50=Paramètres!$C$33,MIN(F80,F81+F79),0) -> 0 | G82: =IF(Hypothèses!$C$50=Paramètres!$C$33,MIN(G80,G81+G79),0) -> 0 | H82: =IF(Hypothèses!$C$50=Paramètres!$C$33,MIN(H80,H81+H79),0) -> 0 | I82: =IF(Hypothèses!$C$50=Paramètres!$C$33,MIN(I80,I81+I79),0) -> 0 | J82: =IF(Hypothèses!$C$50=Paramètres!$C$33,MIN(J80,J81+J79),0) -> 0 | K82: =IF(Hypothèses!$C$50=Paramètres!$C$33,MIN(K80,K81+K79),0) -> 0 | ... AG82: =IF(Hypothèses!$C$50=Paramètres!$C$33,MIN(AG80,AG81+AG79),0) -> 0
B83: Dividende brut (limité au distribuable et à la trésorerie) | C83: =SUMPRODUCT((D$6:AG$6<=Hypothèses!$C$44)*(D83:AG83)) -> 0 | D83: =IF(Hypothèses!$C$50=Paramètres!$C$33,MAX(0,MIN(D80-D82,MAX(0,D76+D75))),0) -> 0 | E83: =IF(Hypothèses!$C$50=Paramètres!$C$33,MAX(0,MIN(E80-E82,MAX(0,E76+E75))),0) -> 0 | F83: =IF(Hypothèses!$C$50=Paramètres!$C$33,MAX(0,MIN(F80-F82,MAX(0,F76+F75))),0) -> 0 | G83: =IF(Hypothèses!$C$50=Paramètres!$C$33,MAX(0,MIN(G80-G82,MAX(0,G76+G75))),0) -> 0 | H83: =IF(Hypothèses!$C$50=Paramètres!$C$33,MAX(0,MIN(H80-H82,MAX(0,H76+H75))),0) -> 0 | I83: =IF(Hypothèses!$C$50=Paramètres!$C$33,MAX(0,MIN(I80-I82,MAX(0,I76+I75))),0) -> 0 | J83: =IF(Hypothèses!$C$50=Paramètres!$C$33,MAX(0,MIN(J80-J82,MAX(0,J76+J75))),0) -> 0 | K83: =IF(Hypothèses!$C$50=Paramètres!$C$33,MAX(0,MIN(K80-K82,MAX(0,K76+K75))),0) -> 0 | ... AG83: =IF(Hypothèses!$C$50=Paramètres!$C$33,MAX(0,MIN(AG80-AG82,MAX(0,AG76+AG75))),0) -> 0
B84: PFU sur le dividende | C84: =SUMPRODUCT((D$6:AG$6<=Hypothèses!$C$44)*(D84:AG84)) -> 0 | D84: =D83*Paramètres!$C$18 -> 0 | E84: =E83*Paramètres!$C$18 -> 0 | F84: =F83*Paramètres!$C$18 -> 0 | G84: =G83*Paramètres!$C$18 -> 0 | H84: =H83*Paramètres!$C$18 -> 0 | I84: =I83*Paramètres!$C$18 -> 0 | J84: =J83*Paramètres!$C$18 -> 0 | K84: =K83*Paramètres!$C$18 -> 0 | ... AG84: =AG83*Paramètres!$C$18 -> 0
B85: Dividende net perçu par l'associé | C85: =SUMPRODUCT((D$6:AG$6<=Hypothèses!$C$44)*(D85:AG85)) -> 0 | D85: =D83-D84 -> 0 | E85: =E83-E84 -> 0 | F85: =F83-F84 -> 0 | G85: =G83-G84 -> 0 | H85: =H83-H84 -> 0 | I85: =I83-I84 -> 0 | J85: =J83-J84 -> 0 | K85: =K83-K84 -> 0 | ... AG85: =AG83-AG84 -> 0
B86: Flux net en poche de l'associé | C86: =SUMPRODUCT((D$6:AG$6<=Hypothèses!$C$44)*(D86:AG86)) -> -53998.176 | D86: =D82+D85-D79 -> -5792.6983 | E86: =E82+E85-E79 -> -5707.6983 | F86: =F82+F85-F79 -> -5621.8483 | G86: =G82+G85-G79 -> -5535.1398 | H86: =H82+H85-H79 -> -5447.5642 | I86: =I82+I85-I79 -> -5359.1129 | J86: =J82+J85-J79 -> -5269.777 | K86: =K82+K85-K79 -> -5179.5478 | ... AG86: =AG82+AG85-AG79 -> 0
B87: Trésorerie en fin d'exercice (bloquée en société) | C87: =INDEX(D87:AG87,Hypothèses!$C$44) -> 0 | D87: =D80-D82-D83 -> 0 | E87: =E80-E82-E83 -> 0 | F87: =F80-F82-F83 -> 0 | G87: =G80-G82-G83 -> 0 | H87: =H80-H82-H83 -> 0 | I87: =I80-I82-I83 -> 0 | J87: =J80-J82-J83 -> 0 | K87: =K80-K82-K83 -> 0 | ... AG87: =AG80-AG82-AG83 -> 106527.4
B88: Compte courant d'associé en fin d'exercice | C88: =INDEX(D88:AG88,Hypothèses!$C$44) -> 82998.176 | D88: =D81+D79-D82 -> 34792.698 | E88: =E81+E79-E82 -> 40500.397 | F88: =F81+F79-F82 -> 46122.245 | G88: =G81+G79-G82 -> 51657.385 | H88: =H81+H79-H82 -> 57104.949 | I88: =I81+I79-I82 -> 62464.062 | J88: =J81+J79-J82 -> 67733.839 | K88: =K81+K79-K82 -> 72913.386 | ... AG88: =AG81+AG79-AG82 -> 127692.43
B89: Réserves distribuables en fin d'exercice | C89: =INDEX(D89:AG89,Hypothèses!$C$44) -> -42618.574 | D89: =D76+D75-D83 -> -6169.2786 | E89: =E76+E75-E83 -> -12015.393 | F89: =F76+F75-F83 -> -17529.636 | G89: =G76+G75-G83 -> -22703.035 | H89: =H76+H75-H83 -> -27526.337 | I89: =I76+I75-I83 -> -31990.008 | J89: =J76+J75-J83 -> -36084.216 | K89: =K76+K75-K83 -> -38655.971 | ... AG89: =AG76+AG75-AG83 -> 11234.971
B91: FLUX POUR LE TRI (COLONNE C : ANNÉE 0, APPORT INITIAL)
B92: Location nue, micro-foncier | C92: =-Hypothèses!$C$30 -> -29000 | D92: =IF(D$6<=Hypothèses!$C$44,D28+IF(D$6=Hypothèses!$C$44,N(Comparateur!$C$31),0),0) -> -8553.9783 | E92: =IF(E$6<=Hypothèses!$C$44,E28+IF(E$6=Hypothèses!$C$44,N(Comparateur!$C$31),0),0) -> -8496.5911 | F92: =IF(F$6<=Hypothèses!$C$44,F28+IF(F$6=Hypothèses!$C$44,N(Comparateur!$C$31),0),0) -> -8438.63 | G92: =IF(G$6<=Hypothèses!$C$44,G28+IF(G$6=Hypothèses!$C$44,N(Comparateur!$C$31),0),0) -> -8380.0893 | H92: =IF(H$6<=Hypothèses!$C$44,H28+IF(H$6=Hypothèses!$C$44,N(Comparateur!$C$31),0),0) -> -8320.9632 | I92: =IF(I$6<=Hypothèses!$C$44,I28+IF(I$6=Hypothèses!$C$44,N(Comparateur!$C$31),0),0) -> -8261.2459 | J92: =IF(J$6<=Hypothèses!$C$44,J28+IF(J$6=Hypothèses!$C$44,N(Comparateur!$C$31),0),0) -> -8200.9314 | K92: =IF(K$6<=Hypothèses!$C$44,K28+IF(K$6=Hypothèses!$C$44,N(Comparateur!$C$31),0),0) -> -8140.0137 | ... AG92: =IF(AG$6<=Hypothèses!$C$44,AG28+IF(AG$6=Hypothèses!$C$44,N(Comparateur!$C$31),0),0) -> 0
B93: Location nue, réel foncier | C93: =-Hypothèses!$C$30 -> -29000 | D93: =IF(D$6<=Hypothèses!$C$44,D44+IF(D$6=Hypothèses!$C$44,N(Comparateur!$D$31),0),0) -> -3600.7718 | E93: =IF(E$6<=Hypothèses!$C$44,E44+IF(E$6=Hypothèses!$C$44,N(Comparateur!$D$31),0),0) -> -5680.4862 | F93: =IF(F$6<=Hypothèses!$C$44,F44+IF(F$6=Hypothèses!$C$44,N(Comparateur!$D$31),0),0) -> -5742.7468 | G93: =IF(G$6<=Hypothèses!$C$44,G44+IF(G$6=Hypothèses!$C$44,N(Comparateur!$D$31),0),0) -> -5808.2994 | H93: =IF(H$6<=Hypothèses!$C$44,H44+IF(H$6=Hypothèses!$C$44,N(Comparateur!$D$31),0),0) -> -5877.2651 | I93: =IF(I$6<=Hypothèses!$C$44,I44+IF(I$6=Hypothèses!$C$44,N(Comparateur!$D$31),0),0) -> -5949.769 | J93: =IF(J$6<=Hypothèses!$C$44,J44+IF(J$6=Hypothèses!$C$44,N(Comparateur!$D$31),0),0) -> -6025.9404 | K93: =IF(K$6<=Hypothèses!$C$44,K44+IF(K$6=Hypothèses!$C$44,N(Comparateur!$D$31),0),0) -> -6105.913 | ... AG93: =IF(AG$6<=Hypothèses!$C$44,AG44+IF(AG$6=Hypothèses!$C$44,N(Comparateur!$D$31),0),0) -> 0
B94: Meublé, LMNP micro-BIC | C94: =-Hypothèses!$C$30 -> -29000 | D94: =IF(D$6<=Hypothèses!$C$44,D50+IF(D$6=Hypothèses!$C$44,N(Comparateur!$E$31),0),0) -> -7800.2983 | E94: =IF(E$6<=Hypothèses!$C$44,E50+IF(E$6=Hypothèses!$C$44,N(Comparateur!$E$31),0),0) -> -7735.3743 | F94: =IF(F$6<=Hypothèses!$C$44,F50+IF(F$6=Hypothèses!$C$44,N(Comparateur!$E$31),0),0) -> -7669.801 | G94: =IF(G$6<=Hypothèses!$C$44,G50+IF(G$6=Hypothèses!$C$44,N(Comparateur!$E$31),0),0) -> -7603.5721 | H94: =IF(H$6<=Hypothèses!$C$44,H50+IF(H$6=Hypothèses!$C$44,N(Comparateur!$E$31),0),0) -> -7536.6808 | I94: =IF(I$6<=Hypothèses!$C$44,I50+IF(I$6=Hypothèses!$C$44,N(Comparateur!$E$31),0),0) -> -7469.1206 | J94: =IF(J$6<=Hypothèses!$C$44,J50+IF(J$6=Hypothèses!$C$44,N(Comparateur!$E$31),0),0) -> -7400.8849 | K94: =IF(K$6<=Hypothèses!$C$44,K50+IF(K$6=Hypothèses!$C$44,N(Comparateur!$E$31),0),0) -> -7331.9667 | ... AG94: =IF(AG$6<=Hypothèses!$C$44,AG50+IF(AG$6=Hypothèses!$C$44,N(Comparateur!$E$31),0),0) -> 0
B95: Meublé, LMNP réel | C95: =-Hypothèses!$C$30 -> -29000 | D95: =IF(D$6<=Hypothèses!$C$44,D66+IF(D$6=Hypothèses!$C$44,N(Comparateur!$F$31),0),0) -> -5092.6983 | E95: =IF(E$6<=Hypothèses!$C$44,E66+IF(E$6=Hypothèses!$C$44,N(Comparateur!$F$31),0),0) -> -5000.6983 | F95: =IF(F$6<=Hypothèses!$C$44,F66+IF(F$6=Hypothèses!$C$44,N(Comparateur!$F$31),0),0) -> -4907.7783 | G95: =IF(G$6<=Hypothèses!$C$44,G66+IF(G$6=Hypothèses!$C$44,N(Comparateur!$F$31),0),0) -> -4813.9291 | H95: =IF(H$6<=Hypothèses!$C$44,H66+IF(H$6=Hypothèses!$C$44,N(Comparateur!$F$31),0),0) -> -4719.1414 | I95: =IF(I$6<=Hypothèses!$C$44,I66+IF(I$6=Hypothèses!$C$44,N(Comparateur!$F$31),0),0) -> -4623.4058 | J95: =IF(J$6<=Hypothèses!$C$44,J66+IF(J$6=Hypothèses!$C$44,N(Comparateur!$F$31),0),0) -> -4526.7129 | K95: =IF(K$6<=Hypothèses!$C$44,K66+IF(K$6=Hypothèses!$C$44,N(Comparateur!$F$31),0),0) -> -4429.053 | ... AG95: =IF(AG$6<=Hypothèses!$C$44,AG66+IF(AG$6=Hypothèses!$C$44,N(Comparateur!$F$31),0),0) -> 0
B96: SCI à l'IS (associé) | C96: =-Hypothèses!$C$30 -> -29000 | D96: =IF(D$6<=Hypothèses!$C$44,D86+IF(D$6=Hypothèses!$C$44,N(Comparateur!$G$31),0),0) -> -5792.6983 | E96: =IF(E$6<=Hypothèses!$C$44,E86+IF(E$6=Hypothèses!$C$44,N(Comparateur!$G$31),0),0) -> -5707.6983 | F96: =IF(F$6<=Hypothèses!$C$44,F86+IF(F$6=Hypothèses!$C$44,N(Comparateur!$G$31),0),0) -> -5621.8483 | G96: =IF(G$6<=Hypothèses!$C$44,G86+IF(G$6=Hypothèses!$C$44,N(Comparateur!$G$31),0),0) -> -5535.1398 | H96: =IF(H$6<=Hypothèses!$C$44,H86+IF(H$6=Hypothèses!$C$44,N(Comparateur!$G$31),0),0) -> -5447.5642 | I96: =IF(I$6<=Hypothèses!$C$44,I86+IF(I$6=Hypothèses!$C$44,N(Comparateur!$G$31),0),0) -> -5359.1129 | J96: =IF(J$6<=Hypothèses!$C$44,J86+IF(J$6=Hypothèses!$C$44,N(Comparateur!$G$31),0),0) -> -5269.777 | K96: =IF(K$6<=Hypothèses!$C$44,K86+IF(K$6=Hypothèses!$C$44,N(Comparateur!$G$31),0),0) -> -5179.5478 | ... AG96: =IF(AG$6<=Hypothèses!$C$44,AG86+IF(AG$6=Hypothèses!$C$44,N(Comparateur!$G$31),0),0) -> 0
B98: CorpusImmo, millésime 2026. Modèle d'aide à la décision : ne constitue ni un conseil en investissement, ni un conseil fiscal, ni une expertise au sens de la charte de l'expertise en évaluation immobilière. Vérifiez les paramètres avant tout engagement.

Sheet Paramètres
B1: CorpusImmo · corpus.immo · Estimer, comparer, décider. Sur les ventes réelles.
B2: Paramètres
B3: Les seules valeurs à mettre à jour quand la loi ou le marché changent. Toutes les formules du classeur pointent ici.
B5: Cellules bleues : à remplir. Cellules blanches : calculées automatiquement.
B6: BARÈMES RÉGLEMENTAIRES, MILLÉSIME 2026
B7: Paramètre | C7: Valeur | D7: Source (organisme, texte, date) | E7: Mise à jour | F7: Commentaire
B8: Prélèvements sociaux, revenus fonciers (location nue) | C8: 0.172 | D8: ="CSS art. L136-6 (assiette des revenus du patrimoine) et L136-8 (taux : CSG 9,2 %), CRDS 0,5 %, CGI art. 235 ter (solidarité 7,5 %). Inchangé par la LFSS 2026. Vérifié le "&TEXT(DAY(Paramètres!$C$111),"00")&"/"&TEXT(MONTH(Paramètres!$C$111),"00")&"/"&YEAR(Paramètres!$C$111)&"." -> CSS art. L136-6 (assiette des revenus du patrimoine) et L136-8 (taux : CSG 9,2 %), CRDS 0,5 %, CGI art. 235 ter (solidarité 7,5 %). Inchangé par la LFSS 2026. Vérifié le 05/09/2026. | E8: Chaque LFSS (décembre) | F8: Micro-foncier et réel foncier.
B9: Prélèvements sociaux, BIC de location meublée non professionnelle | C9: 0.186 | D9: ="LFSS 2026, loi n° 2025-1403 du 30/12/2025, art. 12, modifiant CSS art. L136-8 : CSG portée de 9,2 % à 10,6 % dès les revenus 2025. Vérifié le "&TEXT(DAY(Paramètres!$C$111),"00")&"/"&TEXT(MONTH(Paramètres!$C$111),"00")&"/"&YEAR(Paramètres!$C$111)&"." -> LFSS 2026, loi n° 2025-1403 du 30/12/2025, art. 12, modifiant CSS art. L136-8 : CSG portée de 9,2 % à 10,6 % dès les revenus 2025. Vérifié le 05/09/2026. | E9: Chaque LFSS (décembre) | F9: LMNP micro-BIC et LMNP réel. La hausse de CSG de la LFSS 2026 vise les revenus du patrimoine et les produits de placement ; les revenus fonciers, les plus-values immobilières, l'assurance vie et les plans d'épargne logement en sont exclus et restent à 17,2 % : ne recopiez pas les 17,2 % de la ligne du dessus.
B10: CSG déductible du revenu global de l'année suivante | C10: 0.068 | D10: ="CGI art. 154 quinquies II : 6,8 points de CSG déductibles sur les revenus du patrimoine soumis au barème. Fraction inchangée par la LFSS 2026. Vérifié le "&TEXT(DAY(Paramètres!$C$111),"00")&"/"&TEXT(MONTH(Paramètres!$C$111),"00")&"/"&YEAR(Paramètres!$C$111)&"." -> CGI art. 154 quinquies II : 6,8 points de CSG déductibles sur les revenus du patrimoine soumis au barème. Fraction inchangée par la LFSS 2026. Vérifié le 05/09/2026. | E10: Chaque LFSS | F10: Ne joue que si l'option « CSG déductible » des Hypothèses est sur Oui.
B11: Abattement micro-foncier | C11: 0.3 | D11: ="CGI art. 32. Vérifié le "&TEXT(DAY(Paramètres!$C$111),"00")&"/"&TEXT(MONTH(Paramètres!$C$111),"00")&"/"&YEAR(Paramètres!$C$111)&"." -> CGI art. 32. Vérifié le 05/09/2026. | E11: Chaque loi de finances | F11: Aucune autre charge déductible.
B12: Plafond de revenus bruts fonciers du micro-foncier | C12: 15000 | D12: ="CGI art. 32, I. Vérifié le "&TEXT(DAY(Paramètres!$C$111),"00")&"/"&TEXT(MONTH(Paramètres!$C$111),"00")&"/"&YEAR(Paramètres!$C$111)&"." -> CGI art. 32, I. Vérifié le 05/09/2026. | E12: Chaque loi de finances | F12: Loyers bruts du foyer, tous biens nus confondus. Le classeur teste le loyer du bien en année 1 et en dernière année.
B13: Plafond d'imputation du déficit foncier sur le revenu global | C13: 10700 | D13: ="CGI art. 156, I-3°. Vérifié le "&TEXT(DAY(Paramètres!$C$111),"00")&"/"&TEXT(MONTH(Paramètres!$C$111),"00")&"/"&YEAR(Paramètres!$C$111)&"." -> CGI art. 156, I-3°. Vérifié le 05/09/2026. | E13: Chaque loi de finances | F13: Hors la fraction du déficit issue des intérêts d'emprunt, reportable sur les revenus fonciers seulement.
B14: Plafond majoré, travaux de rénovation énergétique | C14: 21400 | D14: ="CGI art. 156, I-3°. Rehaussement à 21 400 € institué par la loi n° 2022-1499 du 01/12/2022 de finances rectificative pour 2022, art. 12 ; décret n° 2023-297 du 21/04/2023 ; CGI annexe III art. 41 DO ; BOFiP BOI-RFPI-BASE-30-20. Vérifié le "&TEXT(DAY(Paramètres!$C$111),"00")&"/"&TEXT(MONTH(Paramètres!$C$111),"00")&"/"&YEAR(Paramètres!$C$111)&"." -> CGI art. 156, I-3°. Rehaussement à 21 400 € institué par la loi n° 2022-1499 du 01/12/2022 de finances rectificative pour 2022, art. 12 ; décret n° 2023-297 du 21/04/2023 ; CGI annexe III art. 41 DO ; BOFiP BOI-RFPI-BASE-30-20. Vérifié le 05/09/2026. | E14: Chaque loi de finances | F14: Rehaussement temporaire : devis accepté à compter du 05/11/2022, dépenses payées entre le 01/01/2023 et le 31/12/2025, passage d'une classe E, F ou G à une classe A, B, C ou D justifié par deux diagnostics au plus tard le 31/12/2027. Pour les revenus 2026, une dépense payée dans l'année n'y ouvre donc plus droit : ne mettez l'option « rénovation énergétique » des Hypothèses sur Oui que pour un dossier dont les travaux étaient déjà payés fin 2025. Une prorogation de la période de paiement est annoncée par la presse fiscale, elle n'est confirmée ni par le code ni par la doctrine à ce jour : le classeur retient la règle la plus stricte. Appliqué à tout le déficit quand l'option est sur Oui (simplification, voir Méthode).
B15: IS, taux réduit des PME | C15: 0.15 | D15: ="CGI art. 219, I-b : chiffre d'affaires inférieur à 10 M€, capital libéré et détenu à 75 % au moins par des personnes physiques. Vérifié le "&TEXT(DAY(Paramètres!$C$111),"00")&"/"&TEXT(MONTH(Paramètres!$C$111),"00")&"/"&YEAR(Paramètres!$C$111)&"." -> CGI art. 219, I-b : chiffre d'affaires inférieur à 10 M€, capital libéré et détenu à 75 % au moins par des personnes physiques. Vérifié le 05/09/2026. | E15: Chaque loi de finances | F15: Une SCI familiale remplit en général les conditions ; à vérifier.
B16: IS, plafond de bénéfice au taux réduit | C16: 42500 | D16: ="CGI art. 219, I-b, par période de douze mois. L'amendement à 100 000 € du PLF 2026 n'a pas été retenu. Vérifié le "&TEXT(DAY(Paramètres!$C$111),"00")&"/"&TEXT(MONTH(Paramètres!$C$111),"00")&"/"&YEAR(Paramètres!$C$111)&"." -> CGI art. 219, I-b, par période de douze mois. L'amendement à 100 000 € du PLF 2026 n'a pas été retenu. Vérifié le 05/09/2026. | E16: Chaque loi de finances
B17: IS, taux normal | C17: 0.25 | D17: ="CGI art. 219, I. Vérifié le "&TEXT(DAY(Paramètres!$C$111),"00")&"/"&TEXT(MONTH(Paramètres!$C$111),"00")&"/"&YEAR(Paramètres!$C$111)&"." -> CGI art. 219, I. Vérifié le 05/09/2026. | E17: Chaque loi de finances | F17: Sur la fraction du bénéfice au-delà du plafond.
B18: PFU sur les dividendes (12,8 % d'IR + 18,6 % de prélèvements sociaux) | C18: 0.314 | D18: ="CGI art. 200 A et 117 quater ; LFSS 2026, loi n° 2025-1403 du 30/12/2025, art. 12 : 31,4 % sur les dividendes perçus à compter du 01/01/2026. Vérifié le "&TEXT(DAY(Paramètres!$C$111),"00")&"/"&TEXT(MONTH(Paramètres!$C$111),"00")&"/"&YEAR(Paramètres!$C$111)&"." -> CGI art. 200 A et 117 quater ; LFSS 2026, loi n° 2025-1403 du 30/12/2025, art. 12 : 31,4 % sur les dividendes perçus à compter du 01/01/2026. Vérifié le 05/09/2026. | E18: Chaque LF et LFSS | F18: Dividendes annuels et boni de liquidation à la revente. L'option pour le barème n'est pas modélisée.
B19: Impôt sur le revenu sur la plus-value immobilière des particuliers | C19: 0.19 | D19: ="CGI art. 200 B. Vérifié le "&TEXT(DAY(Paramètres!$C$111),"00")&"/"&TEXT(MONTH(Paramètres!$C$111),"00")&"/"&YEAR(Paramètres!$C$111)&"." -> CGI art. 200 B. Vérifié le 05/09/2026. | E19: Chaque loi de finances | F19: Location nue et LMNP.
B20: Prélèvements sociaux sur la plus-value immobilière des particuliers | C20: 0.172 | D20: ="CSS art. L136-7 et L136-8 ; inchangé par la LFSS 2026 (la hausse de CSG vise les revenus, pas les plus-values immobilières). Vérifié le "&TEXT(DAY(Paramètres!$C$111),"00")&"/"&TEXT(MONTH(Paramètres!$C$111),"00")&"/"&YEAR(Paramètres!$C$111)&"." -> CSS art. L136-7 et L136-8 ; inchangé par la LFSS 2026 (la hausse de CSG vise les revenus, pas les plus-values immobilières). Vérifié le 05/09/2026. | E20: Chaque LFSS
B21: Forfait de frais d'acquisition (plus-value des particuliers) | C21: 0.075 | D21: ="CGI art. 150 VB, II-3° ; BOFiP BOI-RFPI-PVI-20-10-20-20 : forfait réservé aux acquisitions à titre onéreux. Vérifié le "&TEXT(DAY(Paramètres!$C$111),"00")&"/"&TEXT(MONTH(Paramètres!$C$111),"00")&"/"&YEAR(Paramètres!$C$111)&"." -> CGI art. 150 VB, II-3° ; BOFiP BOI-RFPI-PVI-20-10-20-20 : forfait réservé aux acquisitions à titre onéreux. Vérifié le 05/09/2026. | E21: Stable | F21: Réservé aux biens achetés à titre onéreux : sur un bien reçu par succession ou par donation, seuls les frais réels comptent. Le mode d'acquisition se saisit dans les Hypothèses. Quand le forfait est ouvert, le classeur retient le plus élevé des frais réels saisis et du forfait.
B22: Forfait travaux (plus-value des particuliers) | C22: 0.15 | D22: ="CGI art. 150 VB, II-4° : 15 % du prix d'acquisition, sans justificatif, pour un immeuble bâti détenu depuis plus de cinq ans. Vérifié le "&TEXT(DAY(Paramètres!$C$111),"00")&"/"&TEXT(MONTH(Paramètres!$C$111),"00")&"/"&YEAR(Paramètres!$C$111)&"." -> CGI art. 150 VB, II-4° : 15 % du prix d'acquisition, sans justificatif, pour un immeuble bâti détenu depuis plus de cinq ans. Vérifié le 05/09/2026. | E22: Stable | F22: Appliqué dès que la durée de détention dépasse la durée ci-dessous ; les travaux réels ne sont pas ajoutés (voir Méthode).
B23: Durée de détention minimale pour le forfait travaux | C23: 5 | D23: ="CGI art. 150 VB, II-4° : « plus de cinq ans ». Vérifié le "&TEXT(DAY(Paramètres!$C$111),"00")&"/"&TEXT(MONTH(Paramètres!$C$111),"00")&"/"&YEAR(Paramètres!$C$111)&"." -> CGI art. 150 VB, II-4° : « plus de cinq ans ». Vérifié le 05/09/2026. | E23: Stable | F23: Strictement plus de cinq années révolues.
B25: RÉGIMES MICRO-BIC SELON LE TYPE DE MEUBLÉ (CGI ART. 50-0, LOI LE MEUR)
B26: Type de meublé (liste des Hypothèses) | C26: Abattement | D26: Plafond de recettes | E26: Source (organisme, texte, date) | F26: Commentaire
B27: Meublé classique (bail d'habitation, étudiant, mobilité) | C27: 0.5 | D27: 83600 | E27: ="CGI art. 50-0 ; plafond revalorisé tous les trois ans : 83 600 € pour les recettes 2026 à 2028 (77 700 € pour 2025). Legifiscal, ARAPL Provence-Var, 18/02/2026. Vérifié le "&TEXT(DAY(Paramètres!$C$111),"00")&"/"&TEXT(MONTH(Paramètres!$C$111),"00")&"/"&YEAR(Paramètres!$C$111)&"." -> CGI art. 50-0 ; plafond revalorisé tous les trois ans : 83 600 € pour les recettes 2026 à 2028 (77 700 € pour 2025). Legifiscal, ARAPL Provence-Var, 18/02/2026. Vérifié le 05/09/2026. | F27: Bail d'habitation meublé, bail étudiant, bail mobilité.
B28: Meublé de tourisme classé | C28: 0.5 | D28: 83600 | E28: ="CGI art. 50-0 modifié par la loi n° 2024-1039 du 19/11/2024 (dite Le Meur), revenus 2025 et suivants ; même plafond que le meublé classique. Vérifié le "&TEXT(DAY(Paramètres!$C$111),"00")&"/"&TEXT(MONTH(Paramètres!$C$111),"00")&"/"&YEAR(Paramètres!$C$111)&"." -> CGI art. 50-0 modifié par la loi n° 2024-1039 du 19/11/2024 (dite Le Meur), revenus 2025 et suivants ; même plafond que le meublé classique. Vérifié le 05/09/2026. | F28: Classement préfectoral en cours de validité.
B29: Meublé de tourisme non classé | C29: 0.3 | D29: 15000 | E29: ="CGI art. 50-0, loi n° 2024-1039 du 19/11/2024 : abattement ramené de 50 à 30 %, plafond à 15 000 €. Vérifié le "&TEXT(DAY(Paramètres!$C$111),"00")&"/"&TEXT(MONTH(Paramètres!$C$111),"00")&"/"&YEAR(Paramètres!$C$111)&"." -> CGI art. 50-0, loi n° 2024-1039 du 19/11/2024 : abattement ramené de 50 à 30 %, plafond à 15 000 €. Vérifié le 05/09/2026. | F29: Courte durée sans classement. Au-delà du plafond, le réel est obligatoire.
B31: LISTES DÉROULANTES DES HYPOTHÈSES
B32: TMI (barème, modifiable) | C32: Oui / Non | D32: Frais d'acquisition (LMNP réel, IS) | E32: Mode d'acquisition (plus-value) | F32: Source et commentaire
B33: 0 | C33: Oui | D33: Immobilisés (amortis avec le bâti) | E33: Achat (à titre onéreux) | F33: TMI : CGI art. 197, barème de la LF 2026 (loi n° 2026-103 du 19/02/2026) : 11 % à partir de 11 600 €, 30 % de 29 579 €, 41 % de 84 577 €, 45 % de 181 917 € par part. Frais d'acquisition : BOFiP BOI-BIC-CHG-20-20-10 (option irrévocable). Mode d'acquisition : CGI art. 150 VB, II-3° et BOFiP BOI-RFPI-PVI-20-10-20-20, qui réservent le forfait de frais de 7,5 % aux acquisitions à titre onéreux. Les libellés Oui / Non, des options et des modes d'acquisition sont fixes : les formules testent leur texte. Ne pas les modifier.
B34: 0.11 | C34: Non | D34: Déduits en charges l'année 1 | E34: Succession
B35: 0.3 | E35: Donation
B36: 0.41
B37: 0.45
B39: ABATTEMENTS POUR DURÉE DE DÉTENTION, PLUS-VALUE IMMOBILIÈRE DES PARTICULIERS
B40: Années de détention révolues | C40: Abattement IR | D40: Abattement prélèvements sociaux | E40: Source (organisme, texte, date) | F40: Commentaire
B41: 1 | C41: 0 | D41: 0 | E41: CGI art. 150 VC, I (IR : 6 % par année de détention au-delà de la cinquième, 4 % la vingt-deuxième) ; CSS art. L136-7, VI (prélèvements sociaux : 1,65 % par année au-delà de la cinquième, 1,60 % la vingt-deuxième, 9 % de la vingt-troisième à la trentième). BOFiP BOI-RFPI-PVI-20-20. | F41: Exonération d'IR après 22 ans, de prélèvements sociaux après 30 ans. L'abattement d'impôt sur le revenu de cette table donne l'assiette de la surtaxe sur les plus-values élevées, dont le barème suit.
B42: 2 | C42: 0 | D42: 0
B43: 3 | C43: 0 | D43: 0
B44: 4 | C44: 0 | D44: 0
B45: 5 | C45: 0 | D45: 0
B46: 6 | C46: 0.06 | D46: 0.0165
B47: 7 | C47: 0.12 | D47: 0.033
B48: 8 | C48: 0.18 | D48: 0.0495
B49: 9 | C49: 0.24 | D49: 0.066
B50: 10 | C50: 0.3 | D50: 0.0825
B51: 11 | C51: 0.36 | D51: 0.099
B52: 12 | C52: 0.42 | D52: 0.1155
B53: 13 | C53: 0.48 | D53: 0.132
... B70: 30 | C70: 1 | D70: 1
B72: TAXE SUR LES PLUS-VALUES IMMOBILIÈRES ÉLEVÉES, BARÈME PAR TRANCHES (CGI ART. 1609 NONIES G)
B73: Plus-value imposable à l'IR supérieure à | C73: Taux | D73: Coefficient de lissage | E73: Borne de lissage | F73: Source et commentaire
B74: 50000 | C74: 0.02 | D74: 0.05 | E74: 60000 | F74: ="CGI art. 1609 nonies G, version en vigueur depuis le 01/01/2024 (LF 2024, loi n° 2023-1322 art. 9), non abrogée ; BOFiP BOI-RFPI-TPVIE-10 et BOI-RFPI-TPVIE-20. Terrains à bâtir hors du champ. Vérifié le "&TEXT(DAY(Paramètres!$C$111),"00")&"/"&TEXT(MONTH(Paramètres!$C$111),"00")&"/"&YEAR(Paramètres!$C$111)&"." -> CGI art. 1609 nonies G, version en vigueur depuis le 01/01/2024 (LF 2024, loi n° 2023-1322 art. 9), non abrogée ; BOFiP BOI-RFPI-TPVIE-10 et BOI-RFPI-TPVIE-20. Terrains à bâtir hors du champ. Vérifié le 05/09/2026.
B75: 60000 | C75: 0.02 | D75: 0 | E75: 0 | F75: Taxe = taux multiplié par la plus-value, moins le coefficient multiplié par l'écart à la borne. Le taux porte sur la totalité de la plus-value, d'où le terme de lissage à l'entrée de chaque tranche ; un coefficient nul désigne une tranche sans lissage. Assiette : la plus-value imposable à l'impôt sur le revenu, c'est-à-dire après l'abattement pour durée de détention de la table ci-dessus (BOI-RFPI-TPVIE-20, I § 10), et non l'assiette des prélèvements sociaux, dont la cadence d'abattement est différente : une plus-value exonérée d'impôt sur le revenu à vingt-deux ans échappe à la taxe alors que les prélèvements sociaux restent dus. Le seuil de 50 000 € s'apprécie après abattement, et par vendeur en indivision ou en couple. La taxe ne frappe que les plus-values des personnes physiques et des sociétés translucides des articles 8 à 8 ter : la SCI à l'impôt sur les sociétés en est hors du champ (BOI-RFPI-TPVIE-10 § 40), sa plus-value étant professionnelle et taxée à l'IS. En cas de suppression du dispositif, mettez à zéro les taux de la colonne C et les coefficients de la colonne D : le terme de lissage se soustrait, un taux annulé seul le laisserait jouer. La taxe calculée ne descend de toute façon jamais en dessous de zéro.
B76: 100000 | C76: 0.03 | D76: 0.1 | E76: 110000
B77: 110000 | C77: 0.03 | D77: 0 | E77: 0
B78: 150000 | C78: 0.04 | D78: 0.15 | E78: 160000
B79: 160000 | C79: 0.04 | D79: 0 | E79: 0
B80: 200000 | C80: 0.05 | D80: 0.2 | E80: 210000
B81: 210000 | C81: 0.05 | D81: 0 | E81: 0
B82: 250000 | C82: 0.06 | D82: 0.25 | E82: 260000
B83: 260000 | C83: 0.06 | D83: 0 | E83: 0
B85: REPÈRES DE MARCHÉ (POINTS DE DÉPART, LUS PAR LES NOTES D'AIDE DES HYPOTHÈSES)
B86: Paramètre | C86: Valeur | D86: Source (organisme, texte, date) | E86: Mise à jour | F86: Commentaire
B87: Taux de crédit immobilier, 20 ans | C87: 0.0327 | D87: Observatoire Crédit Logement / CSA, analyse du marché du mois d'août 2026 (publiée en septembre 2026) : 3,27 % sur 20 ans, taux moyen toutes durées 3,31 %, en hausse de 3 centièmes de point en juillet comme en août. lobservatoire.creditlogement.fr. | E87: Mensuelle | F87: Taux nominal moyen hors assurance.
B88: Taux de crédit immobilier, 25 ans | C88: 0.0335 | D88: Observatoire Crédit Logement / CSA, analyse du marché du mois d'août 2026 (publiée en septembre 2026) : 3,35 % sur 25 ans, 3,14 % sur 15 ans, en hausse de 15 centièmes de point depuis décembre 2025. lobservatoire.creditlogement.fr. | E88: Mensuelle | F88: Le HCSF limite les prêts à 25 ans.
B89: Assurance emprunteur, contrat groupe bancaire | C89: 0.0036 | D89: ="Baromètres 2026 (pretclair.fr, covelia.fr), 35 ans non fumeur, sur capital initial. Consulté le "&TEXT(DAY(Paramètres!$C$111),"00")&"/"&TEXT(MONTH(Paramètres!$C$111),"00")&"/"&YEAR(Paramètres!$C$111)&"." -> Baromètres 2026 (pretclair.fr, covelia.fr), 35 ans non fumeur, sur capital initial. Consulté le 05/09/2026. | E89: Annuelle
B90: Assurance emprunteur, délégation | C90: 0.0017 | D90: Mêmes baromètres 2026. | E90: Annuelle | F90: Sur capital initial, à convertir si le contrat cotise sur le capital restant dû.
B91: Frais d'acquisition dans l'ancien, bas de fourchette (part du prix) | C91: 0.075 | D91: ="DMTO 6,32 % dans la majorité des départements, émoluments du notaire, CSI 0,10 % : barème pretto.fr du 27/08/2026, calcunet.fr. Consulté le "&TEXT(DAY(Paramètres!$C$111),"00")&"/"&TEXT(MONTH(Paramètres!$C$111),"00")&"/"&YEAR(Paramètres!$C$111)&"." -> DMTO 6,32 % dans la majorité des départements, émoluments du notaire, CSI 0,10 % : barème pretto.fr du 27/08/2026, calcunet.fr. Consulté le 05/09/2026. | E91: Annuelle | F91: Notaire seul. Ajouter les honoraires d'agence à la charge de l'acquéreur.
B92: Frais d'acquisition dans l'ancien, haut de fourchette (part du prix) | C92: 0.085 | D92: Mêmes sources. | E92: Annuelle | F92: Neuf : 2 à 3 %.
B93: Honoraires comptables LMNP réel, bas de fourchette (TTC par an) | C93: 300 | D93: ="jedeclaremonmeuble.com et decla.fr, « Prix comptable LMNP 2026 » : 300 à 600 € en cabinet en ligne. Consulté le "&TEXT(DAY(Paramètres!$C$111),"00")&"/"&TEXT(MONTH(Paramètres!$C$111),"00")&"/"&YEAR(Paramètres!$C$111)&"." -> jedeclaremonmeuble.com et decla.fr, « Prix comptable LMNP 2026 » : 300 à 600 € en cabinet en ligne. Consulté le 05/09/2026. | E93: Annuelle | F93: Liasse 2031, 2033, tableau de suivi 39 C, FEC.
B94: Honoraires comptables LMNP réel, haut de fourchette (TTC par an) | C94: 900 | D94: Mêmes sources, complétées par indy.fr : 600 à 900 € et au-delà en cabinet traditionnel. | E94: Annuelle | F94: La réduction d'impôt pour frais de comptabilité (OGA) est supprimée depuis l'exercice 2025.
B95: Honoraires comptables SCI à l'IS, bas de fourchette (HT par an) | C95: 1200 | D95: ="Hayot Expertise, « Prix expert-comptable SCI 2026 », 19/05/2026 : 1 200 à 2 500 € HT par an pour une SCI à l'IS. Consulté le "&TEXT(DAY(Paramètres!$C$111),"00")&"/"&TEXT(MONTH(Paramètres!$C$111),"00")&"/"&YEAR(Paramètres!$C$111)&"." -> Hayot Expertise, « Prix expert-comptable SCI 2026 », 19/05/2026 : 1 200 à 2 500 € HT par an pour une SCI à l'IS. Consulté le 05/09/2026. | E95: Annuelle | F95: Bilan, liasse 2065, approbation des comptes.
B96: Honoraires comptables SCI à l'IS, haut de fourchette (HT par an) | C96: 2500 | D96: Même source. | E96: Annuelle | F96: Selon le nombre de biens et d'associés.
B97: CFE, base minimum 2026, bas de fourchette (recettes de 10 001 à 32 600 €) | C97: 247 | D97: ="CGI art. 1447 et 1647 D ; décret n° 2025-547 du 17/06/2025 ; LMNP.ai, « CFE LMNP 2026 ». Consulté le "&TEXT(DAY(Paramètres!$C$111),"00")&"/"&TEXT(MONTH(Paramètres!$C$111),"00")&"/"&YEAR(Paramètres!$C$111)&"." -> CGI art. 1447 et 1647 D ; décret n° 2025-547 du 17/06/2025 ; LMNP.ai, « CFE LMNP 2026 ». Consulté le 05/09/2026. | E97: Annuelle et par commune | F97: Exonération l'année de création et si les recettes N-2 sont inférieures ou égales à 5 000 €.
B98: CFE, base minimum 2026, haut de fourchette (mêmes recettes) | C98: 1179 | D98: Mêmes sources. | E98: Annuelle et par commune | F98: Le taux communal s'applique à la base minimum : demandez l'avis de l'année précédente en mairie ou au SIE.
B99: Part du terrain dans le prix, bas de fourchette | C99: 0.1 | D99: ="Usage des experts-comptables LMNP ; CE 15/02/2016 n° 380400 (méthode par comparaison en priorité). jedeclaremonmeuble.com. Consulté le "&TEXT(DAY(Paramètres!$C$111),"00")&"/"&TEXT(MONTH(Paramètres!$C$111),"00")&"/"&YEAR(Paramètres!$C$111)&"." -> Usage des experts-comptables LMNP ; CE 15/02/2016 n° 380400 (méthode par comparaison en priorité). jedeclaremonmeuble.com. Consulté le 05/09/2026. | E99: Stable | F99: Appartement en ville moyenne.
B100: Part du terrain dans le prix, haut de fourchette | C100: 0.2 | D100: Mêmes sources. | E100: Stable | F100: Zone tendue, maison : parfois davantage. À justifier par comparaison.
B101: Durée d'amortissement du bâti, bas de fourchette | C101: 25 | D101: ="BOFiP BOI-BIC-AMT-10-40-10 (amortissement par composants) ; usage en linéaire simplifié : jedeclaremonmeuble.com, calcunet.fr. Consulté le "&TEXT(DAY(Paramètres!$C$111),"00")&"/"&TEXT(MONTH(Paramètres!$C$111),"00")&"/"&YEAR(Paramètres!$C$111)&"." -> BOFiP BOI-BIC-AMT-10-40-10 (amortissement par composants) ; usage en linéaire simplifié : jedeclaremonmeuble.com, calcunet.fr. Consulté le 05/09/2026. | E101: Stable | F101: Le classeur retient une durée moyenne pondérée unique (voir Méthode).
B102: Durée d'amortissement du bâti, haut de fourchette | C102: 40 | D102: Mêmes sources. | E102: Stable
B103: Durée d'amortissement des travaux, bas de fourchette | C103: 10 | D103: ="Usage : aménagements 10 à 12 ans, gros œuvre 25 à 30 ans (calcunet.fr). Consulté le "&TEXT(DAY(Paramètres!$C$111),"00")&"/"&TEXT(MONTH(Paramètres!$C$111),"00")&"/"&YEAR(Paramètres!$C$111)&"." -> Usage : aménagements 10 à 12 ans, gros œuvre 25 à 30 ans (calcunet.fr). Consulté le 05/09/2026. | E103: Stable
B104: Durée d'amortissement des travaux, haut de fourchette | C104: 20 | D104: Mêmes sources. | E104: Stable
B105: Durée d'amortissement du mobilier, bas de fourchette | C105: 5 | D105: ="Usage : 5 à 10 ans (jedeclaremonmeuble.com). Consulté le "&TEXT(DAY(Paramètres!$C$111),"00")&"/"&TEXT(MONTH(Paramètres!$C$111),"00")&"/"&YEAR(Paramètres!$C$111)&"." -> Usage : 5 à 10 ans (jedeclaremonmeuble.com). Consulté le 05/09/2026. | E105: Stable
B106: Durée d'amortissement du mobilier, haut de fourchette | C106: 10 | D106: Mêmes sources. | E106: Stable | F106: Le petit matériel de moins de 600 € TTC peut passer en charge (non modélisé).
B107: TRI après impôt sur dix ans, ancien loué à crédit, bas de fourchette | C107: 0.03 | D107: Repère de lecture CorpusImmo, millésime 2026 : fourchette observée sur les simulations d'ancien financé à crédit, après impôt et revente sur dix ans. Elle n'est pas sourcée sur un organisme et se relit à chaque millésime. | E107: Annuelle | F107: En dessous, l'opération repose sur la seule revalorisation du bien. La fourchette est large au regard de la sensibilité aux taux : sur le dossier livré en exemple, 5 centièmes de point de taux de crédit en plus déplacent le TRI de 4 centièmes de point environ. La hausse d'août 2026 ne la remet donc pas en cause, mais une variation de plus d'un demi-point de taux justifierait de la recalculer.
B108: TRI après impôt sur dix ans, ancien loué à crédit, haut de fourchette | C108: 0.07 | D108: Même repère de lecture, même millésime. | E108: Annuelle | F108: Au-dessus de ce repère, vérifiez la revalorisation et le prix de cession saisis.
B109: Plancher de plausibilité d'un taux saisi | C109: 0.001 | D109: Convention CorpusImmo, commune aux matrices qui saisissent des taux. | E109: Stable | F109: Un taux entre 0 et 0,10 % signale presque toujours une saisie en fraction (0,0325 tapé pour 3,25 %). Le contrôle « Taux saisis en pourcentage » des Hypothèses passe au rouge dans ce cas.
B111: Dernière vérification des paramètres | C111: 46270 | D111: Aucun de ces taux n'est recopié dans une formule : toutes pointent ici.
B113: Ces valeurs sont volontairement isolées ici. Un modèle qui embarque un barème au cœur de ses formules devient faux dès que la loi bouge,
B114: sans que personne ne s'en aperçoive. Vérifiez-les chaque janvier après la loi de finances et la LFSS, et mettez à jour la date ci-dessus : toutes les mentions « Vérifié le » et « Consulté le » de cet onglet la lisent.
B116: CorpusImmo, millésime 2026. Modèle d'aide à la décision : ne constitue ni un conseil en investissement, ni un conseil fiscal, ni une expertise au sens de la charte de l'expertise en évaluation immobilière. Vérifiez les paramètres avant tout engagement.

Sheet Méthode
B1: CorpusImmo · corpus.immo · Estimer, comparer, décider. Sur les ventes réelles.
B2: Méthode de calcul
B3: Ce que chaque régime fait à votre imposition, les conventions retenues, ce que le modèle ne fait pas, les sources.
B5: CONVENTIONS RETENUES, ET CE QU'ELLES COÛTENT
B6: Micro-foncier | C6: Abattement forfaitaire de 30 % sur les loyers (taux 2026), sans aucune charge déductible (CGI art. 32). Simple, et pénalisant dès que les charges réelles dépassent l'abattement, ce qui arrive vite avec un emprunt. Réservé aux foyers dont les loyers bruts de location nue ne dépassent pas le plafond de Paramètres (Paramètres!C12, 15 000 € en 2026) : le classeur teste le loyer du bien en année 1 et en dernière année de détention et affiche « Non éligible » au-delà. Ce test ne porte que sur le bien saisi : si vous avez d'autres biens nus, additionnez leurs loyers de tête, le plafond s'apprécie au niveau du foyer.
B7: Réel foncier | C7: Charges, intérêts, assurance emprunteur et travaux déductibles (CGI art. 31), les travaux étant déduits en totalité l'année 1. Si le résultat est négatif, la règle de l'article 156 I 3° s'applique dans cet ordre : les intérêts et frais d'emprunt s'imputent d'abord sur les loyers ; la fraction du déficit qui vient des intérêts ne se reporte que sur les revenus fonciers des dix années suivantes, sans économie immédiate ; le déficit issu des autres charges s'impute sur le revenu global dans la limite du plafond de Paramètres (10 700 € en 2026, ou 21 400 € pour une rénovation énergétique payée entre le 01/01/2023 et le 31/12/2025, option des Hypothèses), le surplus étant reporté sur les revenus fonciers. Les autres revenus fonciers du foyer absorbent d'abord le déficit et les reports. L'économie d'impôt d'un déficit imputé sur le revenu global vaut déficit × TMI (pas de prélèvements sociaux) ; un déficit ou un report imputé sur d'autres revenus fonciers économise la TMI plus les prélèvements sociaux (17,2 % en 2026). L'imputation sur le revenu global engage à louer jusqu'au 31 décembre de la troisième année suivante.
B8: LMNP micro-BIC | C8: Abattement forfaitaire sur les recettes selon le type de meublé choisi dans les Hypothèses (CGI art. 50-0, loi Le Meur) : 50 % pour le meublé classique et le tourisme classé sous 83 600 € de recettes 2026, 30 % pour le tourisme non classé sous 15 000 € (barèmes 2026). Sans comptabilité à tenir. La CFE reste due et n'est pas déductible.
B9: LMNP au réel | C9: Charges, CFE, honoraires comptables, intérêts et assurance, puis amortissement du bâti (prix et frais d'acquisition immobilisés, hors quote-part de terrain), des travaux et du mobilier, chacun en linéaire sur sa durée saisie. L'amortissement ne peut pas créer de déficit (CGI art. 39 C II) : la part non déduite est différée sans limite de durée et reprise dès que le résultat le permet ; le classeur suit ce stock année par année. Si les charges réelles dépassent les loyers, le déficit BIC non professionnel ne s'impute que sur les BIC non professionnels des dix années suivantes (CGI art. 156 I 1° ter). L'amortissement est une charge comptable qui ne sort pas de la trésorerie : d'où un flux en poche très supérieur au résultat fiscal. Contrepartie depuis le 15 février 2025 (loi n° 2025-127 art. 84, CGI art. 150 VB III) : les amortissements déduits sur l'immeuble sont réintégrés dans la plus-value de cession. L'avantage du LMNP réel est un décalage d'impôt, non une exonération.
B10: SCI à l'IS | C10: Même amortissement qu'au LMNP réel, mais sans la limite de l'article 39 C : le résultat de la société peut être déficitaire et le déficit se reporte en avant sans limite de durée (CGI art. 209 I). L'IS est dû au taux réduit de 15 % jusqu'à 42 500 € puis 25 % (art. 219, barème 2026). L'associé n'est imposé qu'à la distribution : dividendes au PFU (31,4 % en 2026), limités au bénéfice distribuable (réserves) et à la trésorerie. L'apport initial est placé en compte courant d'associé, remboursable sans impôt ; quand la trésorerie de la société est négative, l'associé la comble par un apport en compte courant, compté comme un flux négatif. Option « distribution annuelle » : Oui rembourse d'abord le compte courant puis distribue ; Non laisse tout en société jusqu'à la revente. À la revente, la plus-value est professionnelle, calculée sur la valeur nette comptable (donc amputée de tous les amortissements), taxée à l'IS avec le résultat de l'exercice après imputation des déficits ; la trésorerie de liquidation rembourse le compte courant, le surplus (boni) est imposé au PFU. Le taux réduit suppose une société détenue à 75 % au moins par des personnes physiques, au capital libéré.
B11: Plus-value des particuliers (nu et LMNP) | C11: Prix de cession moins prix d'acquisition majoré : frais d'acquisition réels ou forfait de 7,5 % (le plus élevé des deux), forfait travaux de 15 % du prix au-delà de cinq ans de détention (CGI art. 150 VB II, forfaits 2026). Le forfait de 7,5 % n'est ouvert qu'aux biens acquis à titre onéreux : sur un bien reçu par succession ou par donation, seuls les frais réels justifiés sont retenus (droits de mutation à titre gratuit et frais d'acte), ce qui majore la plus-value imposable. Le mode d'acquisition se saisit dans les Hypothèses (Paramètres!C21 pour le taux, BOFiP BOI-RFPI-PVI-20-10-20-20 pour la restriction). Les travaux réels ne sont pas ajoutés (déjà déduits au réel foncier ou amortis au LMNP) ; les frais de cession ne sont pas modélisés. En LMNP réel, le prix d'acquisition est minoré des amortissements effectivement déduits sur l'immeuble (bâti, frais immobilisés, travaux), au prorata de leur part dans l'amortissement de chaque année ; le mobilier et les amortissements différés non encore déduits ne sont pas réintégrés. Une moins-value vaut zéro. Abattements pour durée de détention lus dans la table de Paramètres (exonération d'IR à 22 ans, de prélèvements sociaux à 30 ans), puis 19 % d'IR et 17,2 % de prélèvements sociaux (taux 2026), plus la surtaxe ci-dessous.
B12: Surtaxe sur les plus-values élevées | C12: Le classeur applique la taxe de l'article 1609 nonies G du CGI : de 2 à 6 % par tranches, avec un terme de lissage à l'entrée de chaque tranche, au-delà de 50 000 € de plus-value imposable. Barème complet dans Paramètres (B74:E83), lu par le Comparateur, jamais recopié dans une formule. Trois règles à retenir. D'abord l'assiette : la plus-value imposable à l'impôt sur le revenu, après l'abattement pour durée de détention de l'article 150 VC, et non l'assiette des prélèvements sociaux, dont l'abattement suit une autre cadence ; une plus-value exonérée d'impôt sur le revenu à vingt-deux ans échappe donc à la taxe alors que les prélèvements sociaux restent dus. Ensuite le taux, qui porte sur la totalité de la plus-value et non sur la seule fraction qui dépasse le seuil de tranche : c'est la raison d'être du terme de lissage. Enfin le champ. La taxe frappe les plus-values des personnes physiques et des sociétés translucides des articles 8 à 8 ter : elle s'applique aux quatre régimes imposés à l'impôt sur le revenu de ce classeur, location nue au micro-foncier et au réel, LMNP au micro-BIC et au réel. La SCI à l'impôt sur les sociétés en est hors du champ, sa plus-value étant professionnelle et taxée à l'IS (BOFiP BOI-RFPI-TPVIE-10 § 40) : la ligne « Surtaxe sur les plus-values élevées » du Comparateur reste vide dans sa colonne, elle n'affiche pas zéro. Les terrains à bâtir sont également hors du champ ; ce classeur compare des logements loués, il ne les modélise pas. Le seuil de 50 000 € s'apprécie par vendeur : en indivision ou en couple, chacun regarde sa quote-part, alors que ce classeur raisonne sur un bien entier détenu par un seul contribuable.
B13: Flux net en poche et TRI | C13: Pour chaque régime et chaque année : loyer, moins charges décaissées (CFE et honoraires selon le régime), moins l'annuité complète du prêt (intérêts, capital, assurance), moins l'impôt de l'année (négatif s'il s'agit d'une économie), plus l'économie de CSG déductible si l'option est active. Pour la SCI : ce que l'associé reçoit (remboursement de compte courant, dividende net) ou apporte. Le total net en poche additionne les flux jusqu'à l'année de revente et le net de revente (prix moins capital restant dû moins impôt de cession, ou liquidation de la société). Le TRI actualise l'apport en année 0, les flux annuels et la revente en fin de détention : il n'est pas défini sans apport ni sans flux de signe contraire (« n.d. »).
B14: Le même loyer pour les cinq régimes | C14: Le comparateur raisonne à loyer constant pour isoler l'effet du régime. Un meublé se loue en général plus cher qu'un nu : pour en tenir compte, refaites le calcul avec le loyer meublé et comparez les colonnes meublées de cette seconde passe aux colonnes nues de la première. La CFE s'applique aux régimes meublés et à la SCI si elle exploite le mobilier (mobilier saisi supérieur à zéro).
B15: Indexation, revalorisation, horizon | C15: Loyer, charges, CFE et honoraires sont indexés au même taux à partir de l'année 2. Le prix de cession est le prix net vendeur revalorisé sur la durée de détention, sauf prix forcé. Les intérêts décroissent chaque année selon un prêt à annuité constante mensuelle (taux nominal divisé par douze) ; l'assurance est calculée sur le capital initial. La durée de détention est bornée à 30 ans ; les reports à 10 ans (déficit foncier, déficit BIC) sont suivis en stock sans faire expirer les plus anciens : sur un horizon de dix ans, cela n'a aucun effet ; au-delà, le classeur peut consommer un report que le fisc aurait fait tomber.
B16: TMI et revenu global | C16: Tout le revenu locatif est supposé imposé dans la tranche marginale saisie, et tout déficit imputé sur le revenu global est supposé absorbé par ce revenu à la même TMI. Le classeur ne recalcule pas le barème progressif : choisissez la TMI après les revenus du bien. La CSG déductible (6,8 points en 2026, CGI art. 154 quinquies II) est une option : elle vaut base imposable × 6,8 % × TMI, économisée l'année suivante, pour les régimes au barème seulement ; ignorée par défaut, ce qui est prudent.
B17: Amortissement | C17: Une durée moyenne pondérée unique pour le bâti, à comparer à la fourchette d'usage des repères de marché (Paramètres!C101 et C102), plutôt qu'une ventilation par composants (BOFiP BOI-BIC-AMT-10-40-10) : l'écart sur l'impôt annuel est de l'ordre de la différence entre la durée retenue et la durée moyenne réelle des composants. La quote-part de terrain (fourchette d'usage en Paramètres!C99 et C100) n'a aucun forfait légal : l'administration exige une évaluation, par comparaison en priorité (CE 15/02/2016 n° 380400). Les frais d'acquisition sont soit immobilisés avec le bâti, soit déduits l'année 1 (option comptable irrévocable, BOFiP BOI-BIC-CHG-20-20-10) ; la déduction immédiate crée un déficit BIC ou IS reportable et abaisse la base réintégrée à la revente.
... B19: Millésime des chiffres cités | C19: Les barèmes cités dans cet onglet et dans le Mode d'emploi sont ceux du millésime 2026 et vivent tous dans Paramètres. Ils sont recopiés ici en toutes lettres pour que le texte se lise sans formule : à chaque mise à jour d'une valeur de Paramètres, relisez les lignes qui la citent, ici comme dans le Mode d'emploi (exemple guidé, tableau des données à mettre à jour, erreurs qui faussent tout). La date de la dernière vérification est en Paramètres!C111.
B21: CE QUE CE MODÈLE NE FAIT PAS
B22: • Il ne modélise pas le passage en loueur en meublé professionnel (recettes supérieures à 23 000 € en 2026 et aux autres revenus d'activité du foyer) : déficits imputables sur le revenu global, plus-value professionnelle, cotisations sociales. Au-delà de 23 000 € de recettes meublées, vérifiez votre statut.
B23: • Il ne traite ni la TVA (résidences avec services), ni les cotisations sociales des loueurs en meublé de tourisme au-delà de 23 000 € de recettes, ni la taxe sur les logements vacants, ni les frais de cession (diagnostics, agence vendeur).
B24: • Il ne modélise ni l'exonération de la résidence principale, ni les exonérations particulières (première cession d'un logement autre que la résidence principale, retraités modestes, petites cessions, vente à un organisme de logement social) : la plus-value est toujours calculée comme celle d'un bien locatif imposable. Il n'apprécie pas non plus le seuil de 50 000 € de la surtaxe par quote-part d'indivisaire ou d'époux.
B25: • Il ne fait pas expirer les reports de déficit après dix ans (voir la convention d'horizon), ne recalcule pas le barème progressif de l'impôt sur le revenu, ne modélise pas l'option pour le barème des dividendes ni la contribution exceptionnelle sur les hauts revenus.
B26: • Il compare un seul bien : les plafonds des régimes micro et l'imputation des déficits s'apprécient en réalité au niveau du foyer ; saisissez vos autres revenus fonciers pour le réel foncier et ajoutez vos autres loyers de tête pour les plafonds.
B27: • Il ne modélise pas la constitution ni la dissolution de la SCI (frais de création, honoraires de liquidation, droits d'enregistrement), ni les frais de garantie et de dossier du prêt.
B28: • Il ne remplace ni un expert-comptable, ni un avocat fiscaliste, ni un notaire. Sur un arbitrage IS ou une SCI familiale, consultez.
B30: POINTS DE DROIT SIGNALÉS, TRANCHÉS DANS LE SENS PRUDENT
B31: Réintégration des amortissements LMNP | C31: La loi n° 2025-127 minore le prix d'acquisition « des amortissements admis en déduction ». Les commentaires publiés (GMU Notaires 10/04/2026, lmnp.ai 2026, AUREP) excluent le mobilier et les amortissements différés non déduits ; la place des amortissements de travaux n'est pas tranchée uniformément. Le classeur les réintègre (option la plus lourde) et n'ajoute pas les travaux au prix d'acquisition. Exceptions légales non modélisées : résidences étudiantes, résidences services et établissements médico-sociaux.
B32: Ordre d'imputation des composants | C32: L'administration n'a pas précisé quel composant est réputé déduit en premier quand l'article 39 C limite l'amortissement : le classeur retient le prorata de chaque année.
B33: Plafond majoré 21 400 € | C33: Il ne vise que la part du déficit issue des travaux de rénovation énergétique éligibles. Le classeur, sur option, l'applique à tout le déficit de l'année : à réserver aux dossiers où ces travaux dominent le déficit. Le rehaussement, institué par la loi n° 2022-1499 du 1er décembre 2022 de finances rectificative pour 2022 (art. 12), ne couvre que les dépenses payées entre le 1er janvier 2023 et le 31 décembre 2025, sur un devis accepté à compter du 5 novembre 2022, pour un logement passant d'une classe E, F ou G à une classe A, B, C ou D justifiée au plus tard le 31 décembre 2027. Une prorogation de la période de paiement jusqu'en 2027 est annoncée par la presse fiscale, mais ni le code ni la doctrine ne la portent à ce jour : le classeur retient la règle stricte. Une dépense payée en 2026 n'ouvre donc plus droit au plafond majoré, et l'option des Hypothèses ne se met sur Oui que pour un dossier qui remplit encore les conditions.
B34: Plafond de bénéfice au taux réduit d'IS | C34: 42 500 € par période de douze mois (CGI art. 219 I b) ; l'amendement à 100 000 € discuté au PLF 2026 n'a pas été retenu selon les sources consultées (Compta Online 2026, Legifiscal 03/11/2025). À revérifier à chaque loi de finances.
B35: Surtaxe sur les plus-values élevées maintenue | C35: Une suppression de la taxe de l'article 1609 nonies G a été discutée lors des débats budgétaires pour 2026 sans être retenue dans le texte promulgué : l'article est toujours en vigueur dans sa version du 1er janvier 2024, et Legifrance ne porte aucune version postérieure. Le classeur l'applique, ce qui est l'hypothèse la plus lourde pour le contribuable et la plus prudente pour un arbitrage entre régimes. Si le dispositif était supprimé, mettez à zéro les taux et les coefficients de lissage du barème de Paramètres : rien d'autre n'est à toucher. Le classeur borne par ailleurs la taxe à zéro, pour qu'un barème mal ressaisi ne puisse jamais venir en diminution de l'impôt de sortie.
B37: SOURCES
B38: Prélèvements sociaux, revenus fonciers (location nue) | C38: ="CSS art. L136-6 (assiette des revenus du patrimoine) et L136-8 (taux : CSG 9,2 %), CRDS 0,5 %, CGI art. 235 ter (solidarité 7,5 %). Inchangé par la LFSS 2026. Vérifié le "&TEXT(DAY(Paramètres!$C$111),"00")&"/"&TEXT(MONTH(Paramètres!$C$111),"00")&"/"&YEAR(Paramètres!$C$111)&"." -> CSS art. L136-6 (assiette des revenus du patrimoine) et L136-8 (taux : CSG 9,2 %), CRDS 0,5 %, CGI art. 235 ter (solidarité 7,5 %). Inchangé par la LFSS 2026. Vérifié le 05/09/2026.
B39: Prélèvements sociaux, BIC de location meublée non professionnelle | C39: ="LFSS 2026, loi n° 2025-1403 du 30/12/2025, art. 12, modifiant CSS art. L136-8 : CSG portée de 9,2 % à 10,6 % dès les revenus 2025. Vérifié le "&TEXT(DAY(Paramètres!$C$111),"00")&"/"&TEXT(MONTH(Paramètres!$C$111),"00")&"/"&YEAR(Paramètres!$C$111)&"." -> LFSS 2026, loi n° 2025-1403 du 30/12/2025, art. 12, modifiant CSS art. L136-8 : CSG portée de 9,2 % à 10,6 % dès les revenus 2025. Vérifié le 05/09/2026.
B40: CSG déductible du revenu global de l'année suivante | C40: ="CGI art. 154 quinquies II : 6,8 points de CSG déductibles sur les revenus du patrimoine soumis au barème. Fraction inchangée par la LFSS 2026. Vérifié le "&TEXT(DAY(Paramètres!$C$111),"00")&"/"&TEXT(MONTH(Paramètres!$C$111),"00")&"/"&YEAR(Paramètres!$C$111)&"." -> CGI art. 154 quinquies II : 6,8 points de CSG déductibles sur les revenus du patrimoine soumis au barème. Fraction inchangée par la LFSS 2026. Vérifié le 05/09/2026.
B41: Abattement micro-foncier | C41: ="CGI art. 32. Vérifié le "&TEXT(DAY(Paramètres!$C$111),"00")&"/"&TEXT(MONTH(Paramètres!$C$111),"00")&"/"&YEAR(Paramètres!$C$111)&"." -> CGI art. 32. Vérifié le 05/09/2026.
B42: Plafond de revenus bruts fonciers du micro-foncier | C42: ="CGI art. 32, I. Vérifié le "&TEXT(DAY(Paramètres!$C$111),"00")&"/"&TEXT(MONTH(Paramètres!$C$111),"00")&"/"&YEAR(Paramètres!$C$111)&"." -> CGI art. 32, I. Vérifié le 05/09/2026.
B43: Plafond d'imputation du déficit foncier sur le revenu global | C43: ="CGI art. 156, I-3°. Vérifié le "&TEXT(DAY(Paramètres!$C$111),"00")&"/"&TEXT(MONTH(Paramètres!$C$111),"00")&"/"&YEAR(Paramètres!$C$111)&"." -> CGI art. 156, I-3°. Vérifié le 05/09/2026.
B44: Plafond majoré, travaux de rénovation énergétique | C44: ="CGI art. 156, I-3°. Rehaussement à 21 400 € institué par la loi n° 2022-1499 du 01/12/2022 de finances rectificative pour 2022, art. 12 ; décret n° 2023-297 du 21/04/2023 ; CGI annexe III art. 41 DO ; BOFiP BOI-RFPI-BASE-30-20. Vérifié le "&TEXT(DAY(Paramètres!$C$111),"00")&"/"&TEXT(MONTH(Paramètres!$C$111),"00")&"/"&YEAR(Paramètres!$C$111)&"." -> CGI art. 156, I-3°. Rehaussement à 21 400 € institué par la loi n° 2022-1499 du 01/12/2022 de finances rectificative pour 2022, art. 12 ; décret n° 2023-297 du 21/04/2023 ; CGI annexe III art. 41 DO ; BOFiP BOI-RFPI-BASE-30-20. Vérifié le 05/09/2026.
B45: IS, taux réduit des PME | C45: ="CGI art. 219, I-b : chiffre d'affaires inférieur à 10 M€, capital libéré et détenu à 75 % au moins par des personnes physiques. Vérifié le "&TEXT(DAY(Paramètres!$C$111),"00")&"/"&TEXT(MONTH(Paramètres!$C$111),"00")&"/"&YEAR(Paramètres!$C$111)&"." -> CGI art. 219, I-b : chiffre d'affaires inférieur à 10 M€, capital libéré et détenu à 75 % au moins par des personnes physiques. Vérifié le 05/09/2026.
B46: IS, plafond de bénéfice au taux réduit | C46: ="CGI art. 219, I-b, par période de douze mois. L'amendement à 100 000 € du PLF 2026 n'a pas été retenu. Vérifié le "&TEXT(DAY(Paramètres!$C$111),"00")&"/"&TEXT(MONTH(Paramètres!$C$111),"00")&"/"&YEAR(Paramètres!$C$111)&"." -> CGI art. 219, I-b, par période de douze mois. L'amendement à 100 000 € du PLF 2026 n'a pas été retenu. Vérifié le 05/09/2026.
B47: IS, taux normal | C47: ="CGI art. 219, I. Vérifié le "&TEXT(DAY(Paramètres!$C$111),"00")&"/"&TEXT(MONTH(Paramètres!$C$111),"00")&"/"&YEAR(Paramètres!$C$111)&"." -> CGI art. 219, I. Vérifié le 05/09/2026.
B48: PFU sur les dividendes (12,8 % d'IR + 18,6 % de prélèvements sociaux) | C48: ="CGI art. 200 A et 117 quater ; LFSS 2026, loi n° 2025-1403 du 30/12/2025, art. 12 : 31,4 % sur les dividendes perçus à compter du 01/01/2026. Vérifié le "&TEXT(DAY(Paramètres!$C$111),"00")&"/"&TEXT(MONTH(Paramètres!$C$111),"00")&"/"&YEAR(Paramètres!$C$111)&"." -> CGI art. 200 A et 117 quater ; LFSS 2026, loi n° 2025-1403 du 30/12/2025, art. 12 : 31,4 % sur les dividendes perçus à compter du 01/01/2026. Vérifié le 05/09/2026.
B49: Impôt sur le revenu sur la plus-value immobilière des particuliers | C49: ="CGI art. 200 B. Vérifié le "&TEXT(DAY(Paramètres!$C$111),"00")&"/"&TEXT(MONTH(Paramètres!$C$111),"00")&"/"&YEAR(Paramètres!$C$111)&"." -> CGI art. 200 B. Vérifié le 05/09/2026.
B50: Prélèvements sociaux sur la plus-value immobilière des particuliers | C50: ="CSS art. L136-7 et L136-8 ; inchangé par la LFSS 2026 (la hausse de CSG vise les revenus, pas les plus-values immobilières). Vérifié le "&TEXT(DAY(Paramètres!$C$111),"00")&"/"&TEXT(MONTH(Paramètres!$C$111),"00")&"/"&YEAR(Paramètres!$C$111)&"." -> CSS art. L136-7 et L136-8 ; inchangé par la LFSS 2026 (la hausse de CSG vise les revenus, pas les plus-values immobilières). Vérifié le 05/09/2026.
B51: Forfait de frais d'acquisition (plus-value des particuliers) | C51: ="CGI art. 150 VB, II-3° ; BOFiP BOI-RFPI-PVI-20-10-20-20 : forfait réservé aux acquisitions à titre onéreux. Vérifié le "&TEXT(DAY(Paramètres!$C$111),"00")&"/"&TEXT(MONTH(Paramètres!$C$111),"00")&"/"&YEAR(Paramètres!$C$111)&"." -> CGI art. 150 VB, II-3° ; BOFiP BOI-RFPI-PVI-20-10-20-20 : forfait réservé aux acquisitions à titre onéreux. Vérifié le 05/09/2026.
B52: Forfait travaux (plus-value des particuliers) | C52: ="CGI art. 150 VB, II-4° : 15 % du prix d'acquisition, sans justificatif, pour un immeuble bâti détenu depuis plus de cinq ans. Vérifié le "&TEXT(DAY(Paramètres!$C$111),"00")&"/"&TEXT(MONTH(Paramètres!$C$111),"00")&"/"&YEAR(Paramètres!$C$111)&"." -> CGI art. 150 VB, II-4° : 15 % du prix d'acquisition, sans justificatif, pour un immeuble bâti détenu depuis plus de cinq ans. Vérifié le 05/09/2026.
B53: Durée de détention minimale pour le forfait travaux | C53: ="CGI art. 150 VB, II-4° : « plus de cinq ans ». Vérifié le "&TEXT(DAY(Paramètres!$C$111),"00")&"/"&TEXT(MONTH(Paramètres!$C$111),"00")&"/"&YEAR(Paramètres!$C$111)&"." -> CGI art. 150 VB, II-4° : « plus de cinq ans ». Vérifié le 05/09/2026.
B54: Meublé classique (bail d'habitation, étudiant, mobilité) | C54: ="CGI art. 50-0 ; plafond revalorisé tous les trois ans : 83 600 € pour les recettes 2026 à 2028 (77 700 € pour 2025). Legifiscal, ARAPL Provence-Var, 18/02/2026. Vérifié le "&TEXT(DAY(Paramètres!$C$111),"00")&"/"&TEXT(MONTH(Paramètres!$C$111),"00")&"/"&YEAR(Paramètres!$C$111)&"." -> CGI art. 50-0 ; plafond revalorisé tous les trois ans : 83 600 € pour les recettes 2026 à 2028 (77 700 € pour 2025). Legifiscal, ARAPL Provence-Var, 18/02/2026. Vérifié le 05/09/2026.
B55: Meublé de tourisme classé | C55: ="CGI art. 50-0 modifié par la loi n° 2024-1039 du 19/11/2024 (dite Le Meur), revenus 2025 et suivants ; même plafond que le meublé classique. Vérifié le "&TEXT(DAY(Paramètres!$C$111),"00")&"/"&TEXT(MONTH(Paramètres!$C$111),"00")&"/"&YEAR(Paramètres!$C$111)&"." -> CGI art. 50-0 modifié par la loi n° 2024-1039 du 19/11/2024 (dite Le Meur), revenus 2025 et suivants ; même plafond que le meublé classique. Vérifié le 05/09/2026.
B56: Meublé de tourisme non classé | C56: ="CGI art. 50-0, loi n° 2024-1039 du 19/11/2024 : abattement ramené de 50 à 30 %, plafond à 15 000 €. Vérifié le "&TEXT(DAY(Paramètres!$C$111),"00")&"/"&TEXT(MONTH(Paramètres!$C$111),"00")&"/"&YEAR(Paramètres!$C$111)&"." -> CGI art. 50-0, loi n° 2024-1039 du 19/11/2024 : abattement ramené de 50 à 30 %, plafond à 15 000 €. Vérifié le 05/09/2026.
B57: Barème de l'impôt sur le revenu (TMI) | C57: CGI art. 197, barème de la LF 2026 (loi n° 2026-103 du 19/02/2026) : 11 % à partir de 11 600 €, 30 % de 29 579 €, 41 % de 84 577 €, 45 % de 181 917 € par part.
B58: Abattements pour durée de détention | C58: CGI art. 150 VC, I (IR : 6 % par année de détention au-delà de la cinquième, 4 % la vingt-deuxième) ; CSS art. L136-7, VI (prélèvements sociaux : 1,65 % par année au-delà de la cinquième, 1,60 % la vingt-deuxième, 9 % de la vingt-troisième à la trentième). BOFiP BOI-RFPI-PVI-20-20.
B59: Déficit foncier | C59: CGI art. 156, I-3° ; BOFiP BOI-RFPI-BASE-30-20 (fraction issue des intérêts, et conditions du plafond majoré) ; plafond majoré institué par la loi n° 2022-1499 du 01/12/2022 de finances rectificative pour 2022, art. 12, précisé par le décret n° 2023-297 du 21/04/2023 et codifié au CGI annexe III, art. 41 DO (dépenses payées du 01/01/2023 au 31/12/2025).
B60: Amortissement LMNP et reports | C60: CGI art. 39 C, II ; BOFiP BOI-BIC-AMT-20-40-10-40 (tableau de suivi des amortissements différés) ; CGI art. 156, I-1° ter (déficit BIC non professionnel).
B61: Plus-value et LMNP | C61: Loi n° 2025-127 du 14/02/2025, art. 84 ; CGI art. 150 VB, III ; GMU Notaires, « Vente en LMNP et PVI », 10/04/2026 ; lmnp.ai, « Plus-value LMNP 2026 » ; AUREP.
B62: Forfait de frais d'acquisition et mode d'acquisition | C62: CGI art. 150 VB, II-3° ; BOFiP BOI-RFPI-PVI-20-10-20-20 : le forfait de 7,5 % est réservé aux acquisitions à titre onéreux, un bien reçu par succession ou par donation étant retenu pour ses frais réels.
B63: Surtaxe sur les plus-values élevées | C63: CGI art. 1609 nonies G, version en vigueur depuis le 01/01/2024 (LF 2024, loi n° 2023-1322 du 29/12/2023, art. 9), non abrogée ; BOFiP BOI-RFPI-TPVIE-10 (champ d'application, exclusion des personnes morales à l'IS au § 40, exclusion des terrains à bâtir) et BOI-RFPI-TPVIE-20 (assiette après abattement pour durée de détention, barème, appréciation du seuil de 50 000 €).
B64: SCI à l'IS | C64: CGI art. 206, 209 I, 219 I, 200 A, 117 quater ; Code de commerce art. L232-11 ; Compta Online, « Taux IS 2026 ».
B65: CFE des loueurs en meublé | C65: CGI art. 1447 et 1647 D ; décret n° 2025-547 du 17/06/2025 ; LMNP.ai, Foncia, « CFE location meublée 2026 ».
B66: Honoraires comptables | C66: jedeclaremonmeuble.com et decla.fr, « Prix comptable LMNP 2026 » ; Hayot Expertise, « Prix expert-comptable SCI 2026 », 19/05/2026.
B67: Taux de crédit et assurance | C67: Observatoire Crédit Logement / CSA, analyse du marché du mois d'août 2026, lobservatoire.creditlogement.fr ; baromètres pretclair.fr et covelia.fr 2026.
B69: CorpusImmo, millésime 2026. Modèle d'aide à la décision : ne constitue ni un conseil en investissement, ni un conseil fiscal, ni une expertise au sens de la charte de l'expertise en évaluation immobilière. Vérifiez les paramètres avant tout engagement.
