Workbook

Sheet Mode d'emploi
B1: CorpusImmo · corpus.immo · Estimer, comparer, décider. Sur les ventes réelles.
B2: Mode d'emploi
B3: À quoi sert ce classeur, dans quel ordre le remplir, et comment lire ce qu'il répond.
B6: À QUOI SERT CE CLASSEUR
B7: Vous voulez savoir combien une banque acceptera de vous prêter, quelle mensualité votre foyer peut porter, et donc jusqu'à quel prix vous pouvez acheter, frais compris. Ce classeur applique les deux règles d'un analyste crédit en 2026 : le taux d'effort de 35 % assurance comprise, fixé par le HCSF (Haut Conseil de stabilité financière, norme 2026), et le reste à vivre minimal du foyer, puis remonte du prêt au prix en déduisant les frais de notaire, de garantie et de dossier.
B8: Le second onglet dresse le bilan patrimonial du foyer, ce que la banque regarde après les revenus : ce qu'il possède, ce qu'il doit, ce qu'il peut mobiliser comme apport, et ce que deviendra son patrimoine le jour de l'achat.
B9: Deux onglets de saisie pour le dossier, remplis de haut en bas : les cellules bleues se remplissent, tout le reste se calcule. Un troisième onglet, Paramètres, ne se touche qu'à la mise à jour des barèmes.
B10: Vous êtes | C10: Ce que le classeur vous donne
B11: Acquéreur, primo-accédant | C11: La mensualité tenable, le prix maximal à donner à l'agent immobilier, et le saut de charge par rapport à votre loyer.
B12: Investisseur locatif | C12: La capacité en tenant compte du loyer attendu du bien financé (pondéré) et du loyer que vous continuez à payer.
B13: Courtier, banquier | C13: Les deux ratios (taux d'effort HCSF strict et taux de charges tout compris), le reste à vivre après mensualité, les contrôles apport, durée et endettement.
B14: Conseiller en gestion de patrimoine | C14: Le patrimoine net, l'endettement immobilier (LTV, « loan to value » : encours de crédit rapporté à la valeur des biens), la dette rapportée aux revenus, l'épargne résiduelle après apport et le pro forma après l'opération.
B15: Agent immobilier | C15: Un prix maximal argumenté, frais de notaire 2026 compris (ancien ou neuf, droit départemental majoré ou non).
B17: LE PRINCIPE, EN UNE LIGNE
B18: Revenus retenus × 35 % (HCSF 2026) − charges = mensualité, bornée par le reste à vivre ; mensualité → capital ; capital + apport − frais = prix maximal
B20: LES ONGLETS, DANS L'ORDRE OÙ ON LES REMPLIT
B21: Onglet | C21: Ce que vous y faites | D21: Ce que vous y lisez
B22: Mode d'emploi | C22: Rien à saisir. Vous lisez ce guide. | D22: La marche à suivre et l'exemple guidé.
B23: Capacité d'emprunt | C23: Quatre blocs de saisie : revenus, charges, foyer, projet. | D23: Ce que la banque retient, la mensualité tenable, le capital, le prix maximal, six contrôles OK / À CORRIGER (C35 taux vraisemblable, C50 endettement, C58 durée, C60 taux d'usure, C67 apport, C70 saisies).
B24: Bilan patrimonial | C24: Trois blocs de saisie : immobilier, liquidités et placements, dettes. | D24: Le patrimoine net, la lecture bancaire, l'apport couvert ou non, le pro forma après l'achat.
B25: Paramètres | C25: Rien, sauf à la mise à jour des barèmes (HCSF, droits de mutation, émoluments), des repères de marché (pondérations, reste à vivre, garantie, dossier) et des bornes de saisie. | D25: Chaque valeur avec sa source datée et sa fréquence de mise à jour.
B26: Méthode | C26: Rien à saisir. | D26: Les conventions de calcul, ce que le modèle ne fait pas, les sources.
B28: LE CODE COULEUR, ET COMMENT DÉVERROUILLER UNE CELLULE
B29: Cellule | C29: Ce que c'est | D29: Ce que vous faites
B30: Fond bleu clair | C30: Saisie utilisateur | D30: Vous la remplissez. Jamais de formule dedans.
B31: Fond blanc | C31: Calcul | D31: Vous la lisez. Elle est verrouillée.
B32: Fond presque blanc, texte en gras | C32: Résultat de bloc, chiffre clé | D32: Vous la lisez. C'est un chiffre à retenir. Le gras est le repère, pas la couleur.
B33: Bandeau bleu nuit | C33: Titre de section | D33: Repère de navigation.
B34: Texte gris, à droite | C34: Commentaire d'aide, ordre de grandeur | D34: Une phrase par ligne pour savoir quoi saisir. Dans les onglets, les chiffres cités y sont lus dans Paramètres et se mettent à jour seuls ; ceux de ce guide sont écrits en dur (millésime 2026).
B35: Vert OK / rouge À CORRIGER | C35: Contrôle de cohérence | D35: Rouge : lisez le commentaire de la ligne, corrigez la saisie ou présentez le dossier comme dérogatoire.
B36: Les onglets sont protégés sans mot de passe pour éviter d'écraser une formule par erreur. Pour modifier une cellule blanche : onglet Révision, puis « Ôter la protection de la feuille ». Aucun mot de passe n'est demandé.
B38: LA MARCHE À SUIVRE, ÉTAPE PAR ÉTAPE
B39: Étape | C39: Où (onglet et plage) | D39: Ce que vous faites | E39: Pourquoi
B40: 0. L'exemple livré | C40: Toutes les cellules bleues des onglets Capacité d'emprunt et Bilan patrimonial | D40: Le classeur est livré rempli d'un exemple (section « Exemple guidé »). Gardez-le pour vous repérer, ou remplacez chaque cellule bleue par votre valeur. Mettez 0 dans celles qui ne vous concernent pas, ne laissez jamais une cellule bleue vide et gardez un choix dans chaque liste : le contrôle C70 passe au rouge sinon. Vérifiez surtout les saisies secondaires qui n'ont pas de raison d'être chez vous : loyers encaissés (C10), crédits en cours (C15, C16), loyer payé (C18), loyer du bien financé (C27), les trois choix Oui / Non (C32 à C34), et dans le Bilan patrimonial le bien locatif (C8), son encours (C24), le restant dû du crédit auto (C25) et les quatre postes d'épargne (C13 à C16). | E40: Une saisie résiduelle de l'exemple est l'erreur la plus probable d'un premier usage : les 700 € de loyers ou les 450 € de crédit de l'exemple 2026, s'ils ne sont pas les vôtres, déplacent le prix maximal de plusieurs dizaines de milliers d'euros.
B41: 1. Les revenus | C41: Capacité d'emprunt!C7:C11 | D41: Salaires nets avant impôt, primes lissées, loyers bruts actuels, autres revenus pérennes. | E41: La banque pondère les loyers et parfois les primes : saisissez les montants bruts, le classeur pondère avec Paramètres.
B42: 2. Les charges | C42: Capacité d'emprunt!C15:C18 | D42: Mensualités des crédits qui continueront, pension versée, loyer payé aujourd'hui. | E42: Le loyer actuel disparaît pour une résidence principale et reste pour un investissement : le classeur tranche selon l'objet.
B43: 3. Le foyer | C43: Capacité d'emprunt!C22:C23 | D43: Nombre d'adultes et d'enfants à charge. | E43: Le reste à vivre minimal en dépend : c'est la règle qui refuse un dossier à 33 % avec quatre enfants.
B44: 4. Le projet | C44: Capacité d'emprunt!C26:C34 | D44: Objet (résidence principale ou investissement), loyer attendu du bien financé, apport, taux (tapez 3,3 pour 3,30 %), durée, assurance (taux global du foyer : avec deux emprunteurs couverts à 100 % chacun, additionnez les deux taux), neuf ou en VEFA (vente en l'état futur d'achèvement) ou ancien, différé, droit départemental majoré. Vérifiez que C58 (durée) et C67 (apport) affichent OK. | E44: Ces neuf cellules pilotent le capital et les frais. Le droit majoré (LF 2025, en vigueur jusqu'au 31/03/2028) ne s'applique ni dans les départements restés à 4,50 % (liste à jour sur taximmo.fr ou sur le site des notaires de France, source citée en Paramètres!D13), ni aux primo-accédants pour leur résidence principale.
B45: 5. La lecture | C45: Capacité d'emprunt!C38:C70 | D45: Rien à saisir. Vérifiez que les six contrôles affichent OK : C35 (taux vraisemblable), C50 (endettement dans la norme), C58 (durée), C60 (taux et assurance sous le taux d'usure, ligne C59), C67 (apport), C70 (saisies complètes). Puis lisez la mensualité tenable (C45), le capital (C53) et le prix maximal (C63). | E45: Un contrôle rouge signale une saisie manquante, hors bornes ou un dossier hors norme : le classeur préfère un rouge à un chiffre faux.
B46: 6. Le bilan | C46: Bilan patrimonial!C7:C9, Bilan patrimonial!C13:C18, Bilan patrimonial!C23:C28 | D46: Valeurs de marché des biens, épargne poste par poste avant l'achat (l'apport prévu en fait encore partie : s'il est sur le compte courant, il compte dans C13), capital restant dû de chaque crédit (lu sur le tableau d'amortissement). Vérifiez que Bilan patrimonial!C45 (saisies complètes) puis Bilan patrimonial!C44 (apport couvert par les liquidités) affichent OK. | E46: Le Bilan décrit la situation avant l'achat : le pro forma retire lui-même l'apport. Le même foyer que dans Capacité d'emprunt : le bien loué qui produit les loyers doit figurer ici avec son encours. Si Bilan patrimonial!C44 est rouge, l'épargne saisie ne contient pas l'apport, ou l'apport vient d'ailleurs (donation, PER).
B47: 7. Les barèmes | C47: Paramètres!C8:C19, C28:C39 et C43:C48 | D47: À chaque décision HCSF ou loi de finances, comparez chaque valeur à sa source et mettez à jour la date en Paramètres!C55 : toutes les mentions « vérifié le » du classeur la lisent, et les commentaires gris des onglets se mettent à jour seuls. Ajustez les repères (pondérations, reste à vivre, garantie, dossier) à la banque visée. | E47: Un barème périmé fausse le prix maximal sans prévenir. Toutes les formules pointent ici. En revanche, ce guide et l'onglet Méthode sont du texte fixe au millésime 2026 : après une mise à jour, relisez et corrigez les sections « Exemple guidé », « Les chiffres à regarder » (colonne Repère métier), « Les erreurs qui faussent tout », les lignes Revenus retenus, Mensualité maximale, Capital empruntable, Frais de notaire 2026, Durée et Dérogations HCSF de Méthode, et le pied de page « millésime 2026 » de chaque onglet.
B49: EXEMPLE GUIDÉ
B50: Le fichier est livré avec un exemple calé sur les barèmes 2026 : un couple locataire (850 € de loyer), deux salaires de 2 600 € et 1 900 €, 200 € de primes lissées, un enfant, et un appartement loué 700 € par mois qu'ils remboursent encore (450 € par mois). Ils ont aussi un crédit auto de 280 € par mois. Ils achètent leur résidence principale dans l'ancien, avec 30 000 € d'apport, sur 25 ans à 3,30 % plus 0,30 % d'assurance. Primo-accédants, ils gardent le droit départemental à 4,50 % (« Non » en C34).
B51: Revenus retenus (C39) : 5 190 €, soit les salaires, les primes et 490 € de loyers pondérés à 70 % (C38). Charges retenues (C41) : 730 €, les deux crédits ; le loyer actuel ne compte pas puisqu'il disparaît. Mensualité maximale au taux d'effort (C42) : 1 086,50 €. Reste à vivre minimal (C43) : 1 900 €, ce qui laisserait 2 560,00 € de mensualité (C44). La règle qui limite est donc le taux d'effort (C47) et la mensualité tenable ressort à 1 086,50 € (C45), avec un reste à vivre de 3 373,50 € (C46).
B52: Les deux ratios (C48 et C49) affichent tous deux 35,00 % : sans pension ni loyer conservé, ils coïncident. Le capital empruntable (C53) est de 210 987 € : c'est la mensualité tenable, assurance déduite, ramenée en capital sur 300 mois. La garantie (C54) coûte 2 532 €, le dossier (C55) 2 000 €, et le budget total (C56) atteint 240 987 €.
B53: Frais de notaire : la part proportionnelle (C61) est de 6,87 % (droits 5,81 %, contribution de sécurité immobilière 0,10 %, émoluments marginaux TTC) et la part fixe (C62) de 1 477 €. Le prix d'achat maximal (C63) ressort à 219 875 €, avec 16 579 € de frais de notaire (C64, soit 7,54 % du prix) et 21 111 € de frais au total (C66), couverts par les 30 000 € d'apport : contrôle C67 OK. Le saut de charge (C68) est de 236,50 € par mois par rapport au loyer actuel, et le crédit coûtera 114 963 € d'intérêts et d'assurance sur 25 ans (C69).
B54: Bilan patrimonial (les cellules citées dans ce paragraphe et le suivant sont celles de cet onglet) : l'appartement loué vaut 140 000 € (C8) avec 60 000 € restant dus (C24), et il reste 6 500 € à rembourser sur le crédit auto (C25). L'épargne totalise 63 000 € (C19) : 18 000 € de comptes et livrets, 25 000 € d'assurance-vie, 12 000 € de PEA et 8 000 € de PER ; les 30 000 € d'apport en font encore partie (état avant achat). 55 000 € sont mobilisables (C20, sans le PER). Total actif 203 000 € (C33), total passif 66 500 € (C30), patrimoine net (C34) : 136 500 €. Endettement immobilier (C36) : 42,86 %. Dette totale (C38) : 1,07 année de revenus retenus. Après l'apport de 30 000 €, il reste 25 000 € (C42), soit 23 mois de mensualité (C43).
B55: Pro forma (C48 à C56) : avec le bien acquis à 219 875 € et le nouveau prêt de 210 987 €, le patrimoine net passe à 115 389 € (C53), en baisse de 21 111 € : exactement les frais de l'opération. L'endettement immobilier monte à 75,30 % (C55) et le ratio dettes sur actif à 70,63 % (C56).
B56: Comment le lire : le dossier passe au taux d'effort, avec un reste à vivre confortable et un apport qui couvre largement les frais. Deux essais, indépendants l'un de l'autre (revenez à la saisie d'origine entre les deux). Premier essai : passez C34 à « Oui » (acquéreur non primo-accédant) : le prix maximal recule de 1 044 €, à 218 831 €. Second essai : remettez C34 à « Non », puis passez l'objet (C26) à « Investissement locatif » avec 600 € de loyer attendu en C27 : le loyer actuel de 850 € redevient une charge, le loyer attendu est retenu à 70 %, la mensualité tenable tombe à 383,50 € et le taux d'effort HCSF strict (19,85 %) s'écarte du taux de charges (35,00 %).
B58: LES CHIFFRES À REGARDER, ET CE QU'ILS VALENT
B59: Indicateur | C59: Où | D59: Repère métier | E59: Ce qu'il dit vraiment
B60: Mensualité tenable | C60: Capacité d'emprunt!C45 | D60: À comparer au loyer actuel (saut de charge) : la banque vérifie que l'épargne mensuelle passée couvrait déjà l'écart. | E60: La plus contraignante des deux règles, assurance comprise. Le chiffre du rendez-vous banque.
B61: Reste à vivre après mensualité | C61: Capacité d'emprunt!C46 | D61: 800 € par adulte, 300 € par enfant (repères 2026 de Paramètres) ; davantage en Île-de-France. | E61: La seconde règle, celle qui refuse un dossier à 33 % avec quatre enfants. Toujours calculé après la mensualité retenue.
B62: Taux d'effort HCSF strict et taux de charges | C62: Capacité d'emprunt!C48 et C49 | D62: 35 % (HCSF 2026) ; au-delà, dossier dérogatoire (20 % de la production des banques, 17,5 % utilisés au 1er trimestre 2026). | E62: Le premier est déclaré au régulateur, le second est celui que le modèle plafonne. Ils diffèrent dès qu'il y a une pension ou un loyer conservé.
B63: Capital empruntable | C63: Capacité d'emprunt!C53 | D63: Environ 191 000 € pour 1 000 € de mensualité sur 25 ans à 3,35 % plus 0,36 % d'assurance (repères d'août 2026, chiffre écrit en dur dans ce guide). | E63: Le montant du prêt, pas le prix. Sur l'exemple 2026, oublier l'assurance le gonfle de 5,1 %.
B64: Prix d'achat maximal | C64: Capacité d'emprunt!C63 | D64: Frais de notaire : environ 8,0 % dans l'ancien, 2,5 % dans le neuf (repères 2026). | E64: Le chiffre à donner à l'agent immobilier, hors frais. Vérifiez que l'apport couvre les frais, sinon la banque refusera.
B65: Patrimoine net et LTV | C65: Bilan patrimonial!C34 et C36 | D65: Un patrimoine net positif et une LTV nettement inférieure à 100 % sur l'immobilier existant : la marge de sûreté de la banque. | E65: Ce qui amortit un accident de parcours. Le pro forma montre ce qu'il en reste le jour de l'achat.
B67: LES DONNÉES À METTRE À JOUR, OÙ ET POURQUOI
B68: Deux familles de données. Les benchmarks (règles HCSF, droits de mutation, émoluments, taux de crédit de référence, pondérations et minimums bancaires) changent avec la loi ou le marché, à date fixe, et se rafraîchissent depuis une source indiquée. Les données de projet (revenus, charges, apport, taux, durée, patrimoine) sont propres à chaque dossier. L'architecture du classeur ne change pas quand les données changent : seules les cellules bleues bougent.
B69: Paramètre | C69: Onglet et cellule | D69: Ce qu'il pilote | E69: Source à consulter, fréquence
B70: Taux d'effort et durées HCSF | C70: Paramètres!C8:C10 | D70: Mensualité maximale, contrôle de durée | E70: HCSF (economie.gouv.fr/hcsf), à chaque décision trimestrielle
B71: Seuil de travaux, marge de flexibilité | C71: Paramètres!C11:C12 | D71: Rien : information pour répondre à la question « Différé » et lire les dossiers dérogatoires | E71: HCSF, à chaque décision trimestrielle
B72: Droits de mutation et taxe de publicité foncière | C72: Paramètres!C13:C15 | D72: Frais de notaire, prix maximal | E72: Loi de finances (CGI art. 1594 D et 1594 F quinquies A) ; échéance du droit majoré 31/03/2028. Valeurs composites (droit, taxe communale, frais d'assiette), détail en Paramètres!F13 et F14
B73: Contribution de sécurité immobilière, émoluments, TVA | C73: Paramètres!C16:C19 | D73: Frais de notaire | E73: CGI art. 879 ; Code de commerce art. A444-91, arrêté tarifaire tous les deux ans (prochain : 01/03/2028). C18 se recalcule depuis les tranches, formule en Paramètres!D18
B74: Taux d'usure par tranche de durée | C74: Paramètres!C20:C24 | D74: Le taux d'usure applicable (C59) et le contrôle « Taux et assurance sous le taux d'usure » (C60) | E74: Banque de France, banque-france.fr, rubrique Taux d'usure : avis publié le dernier jour ouvré de mars, juin, septembre et décembre, applicable le 1er du mois suivant. Trimestrielle
B75: Pondérations et reste à vivre | C75: Paramètres!C28:C31 | D75: Revenus retenus, mensualité tenable | E75: Grille de la banque visée, chaque année
B76: Débours, garantie, frais de dossier | C76: Paramètres!C32:C34 | D76: Frais à financer, prix maximal, contrôle d'apport | E76: Notaire, Crédit Logement, banque : chaque année
B77: Repères de taux, d'assurance et de frais de notaire | C77: Paramètres!C35:C39 | D77: Rien : ils alimentent les commentaires d'aide des onglets. Les chiffres du Mode d'emploi, eux, sont écrits en dur : relisez-le après chaque mise à jour (voir l'étape 7) | E77: Observatoire Crédit Logement / CSA (mensuel), baromètres d'assurance et frais-de-notaire.fr (annuel)
B78: Bornes de saisie et plancher de plausibilité des taux | C78: Paramètres!C43:C48 | D78: Validations, contrôle des taux C35 et contrôle « Saisies complètes » | E78: Convention du classeur : stable. Relevez le plancher si des taux inférieurs à 0,10 % redeviennent courants
B79: Date de vérification et listes | C79: Paramètres!C55 ; Paramètres!B52:C53 | D79: La date alimente toutes les mentions « vérifié le » ; les listes sont testées par les formules | E79: La date : à chaque mise à jour. Les listes : ne jamais les modifier
B80: Revenus, charges, foyer, projet, patrimoine | C80: Capacité d'emprunt!C7:C11, Capacité d'emprunt!C15:C18, Capacité d'emprunt!C22:C23, Capacité d'emprunt!C26:C34, toutes les cellules bleues du Bilan patrimonial | D80: Tout le reste | E80: Données de projet, propres à chaque dossier
B82: TROIS FAÇONS DE S'EN SERVIR
B83: Votre situation | C83: Ce que vous faites
B84: Vous préparez un premier achat | C84: Remplissez revenus, charges et foyer, choisissez « Résidence principale » et laissez le loyer actuel en C18 : il disparaît du calcul mais sert au saut de charge (C68). Si le foyer est hébergé ou déjà propriétaire, C68 n'a pas de sens : ne le présentez pas. Lisez le prix maximal (C63) et vérifiez l'apport (C67). Primo-accédant : « Non » en C34.
B85: Vous étudiez un investissement locatif | C85: Choisissez « Investissement locatif », saisissez le loyer attendu en C27 et votre loyer actuel en C18 : il reste une charge. Comparez le taux d'effort HCSF strict (C48) au taux de charges (C49) : c'est l'écart que le courtier devra défendre.
B86: Vous montez un dossier pour la banque | C86: Remplissez les deux onglets. Présentez, dans Capacité d'emprunt, la mensualité tenable (C45), le reste à vivre (C46) et les six contrôles (C35, C50, C58, C60, C67, C70). Puis, dans Bilan patrimonial, le patrimoine net (C34), l'épargne résiduelle (C42) et le patrimoine net pro forma (C53). Ajustez les repères de Paramètres à la grille de la banque visée.
B88: LES ERREURS QUI FAUSSENT TOUT
B89: Le piège | C89: Le dégât
B90: Pondérer soi-même les loyers avant de les saisir (C10) | C90: Ils sont comptés à 49 % au lieu de 70 % : sur l'exemple 2026, 147 € de revenus retenus en moins chaque mois, soit un capital réduit d'environ 10 000 €.
B91: Saisir le net imposable ou le net après prélèvement à la source (C7, C8) | C91: La banque raisonne en net avant impôt : des revenus sous-estimés de 10 % réduisent le capital de plus de 10 %, car les charges, elles, ne bougent pas.
B92: Laisser le loyer actuel à 0 pour un investissement locatif (C18) | C92: Une charge de plusieurs centaines d'euros oubliée : la mensualité tenable est surestimée d'autant, et le dossier sera refusé.
B93: Saisir un taux en fraction (0,033) dans une cellule qui affiche déjà le pourcentage (C29) | C93: Selon le réglage d'Excel, la cellule lit 0,033 % : le capital gonfle de plus de 40 %. Tapez 3,3 et vérifiez que la cellule affiche 3,30 %.
B94: Oublier l'assurance (C31 à 0) | C94: Le capital est surestimé de 5,1 % sur l'exemple 2026, davantage après 45 ans ou en cas de surprime.
B95: Choisir « Oui » au droit majoré pour un primo-accédant, ou « Non » dans un département à 5 % (C34) | C95: Un demi-point de droits : 1 044 € de prix maximal sur l'exemple 2026. L'erreur la plus fréquente depuis avril 2025.
B96: Saisir 0 en restant dû faute de tableau d'amortissement (Bilan patrimonial!C23 à C25) | C96: Le patrimoine net et la dette sur revenus sont surestimés, sans aucun contrôle rouge. Demandez le tableau d'amortissement, ou estimez le restant dû par mensualité × mois restants.
B97: Décrire un foyer différent dans les deux onglets | C97: Des loyers dans Capacité d'emprunt sans bien loué dans le Bilan (ou l'inverse) : le pro forma et la dette sur revenus ne veulent plus rien dire.
B99: Ce que le classeur ne fait pas, et sur quelles sources reposent ses chiffres : voir l'onglet Méthode.
B101: CorpusImmo, millésime 2026. Modèle d'aide à la décision : ne constitue ni un conseil en investissement, ni un conseil fiscal, ni une expertise au sens de la charte de l'expertise en évaluation immobilière. Vérifiez les paramètres avant tout engagement.

Sheet Capacité d'emprunt
B1: CorpusImmo · corpus.immo · Estimer, comparer, décider. Sur les ventes réelles.
B2: Capacité d'emprunt
B3: Jusqu'où la banque peut vous suivre, et ce qu'il vous reste pour vivre.
B5: Cellules bleues : à remplir. Cellules blanches : calculées automatiquement.
B6: REVENUS MENSUELS NETS DU FOYER
B7: Salaire net emprunteur 1 | C7: 2600 | D7: Net avant impôt, hors primes exceptionnelles : la ligne « net à payer avant impôt sur le revenu » de la fiche de paie.
B8: Salaire net emprunteur 2 | C8: 1900 | D8: 0 s'il n'y a qu'un emprunteur. Indépendant : moyenne des derniers bilans.
B9: Primes et variables (moyenne mensuelle) | C9: 200 | D9: ="Moyenne pluriannuelle si elles sont récurrentes. Retenues à "&TEXT(ROUND(Paramètres!$C$29*100,0),"0")&" %"&" (Paramètres, pondération des primes)." -> Moyenne pluriannuelle si elles sont récurrentes. Retenues à 100 % (Paramètres, pondération des primes).
B10: Revenus locatifs actuels (loyers bruts) | C10: 700 | D10: ="Loyers hors charges encaissés aujourd'hui. Retenus à "&TEXT(ROUND(Paramètres!$C$28*100,0),"0")&" %"&" plus bas (Paramètres) : ne les pondérez pas vous-même." -> Loyers hors charges encaissés aujourd'hui. Retenus à 70 % plus bas (Paramètres) : ne les pondérez pas vous-même.
B11: Autres revenus pérennes | C11: 0 | D11: Pensions reçues, rentes, allocations pérennes. Pas les aides temporaires.
B12: Total des revenus du foyer | C12: =SUM($C$7:$C$11) -> 5400 | D12: Ce que le foyer encaisse réellement chaque mois, avant pondération.
B14: CHARGES MENSUELLES ACTUELLES
B15: Crédits immobiliers en cours (mensualités) | C15: 450 | D15: Assurance comprise, pour les prêts qui continueront après l'opération. Exemple : le prêt du bien loué.
B16: Crédit auto, consommation, LOA (mensualités) | C16: 280 | D16: Toutes les mensualités de crédits non immobiliers en cours.
B17: Pension alimentaire versée | C17: 0 | D17: Pension versée. Une pension reçue se saisit dans les autres revenus.
B18: Loyer actuel payé par le foyer | C18: 850 | D18: Loyer payé aujourd'hui. Il disparaît pour une résidence principale, il reste une charge pour un investissement locatif (choix dans Le projet).
B19: Charges de crédits en cours | C19: =SUM($C$15:$C$16) -> 730 | D19: Les seules charges comptées dans le taux d'effort HCSF strict.
B21: LE FOYER
B22: Nombre d'adultes | C22: 2 | D22: Emprunteurs et adultes à charge. Au moins 1.
B23: Nombre d'enfants à charge | C23: 1 | D23: Enfants à charge, garde alternée comprise.
B25: LE PROJET
B26: Objet du financement | C26: Résidence principale | D26: Choisir dans la liste. Résidence principale : le loyer actuel disparaît. Investissement locatif : il reste, et le loyer du bien financé est retenu (pondéré).
B27: Loyer mensuel attendu du bien financé | C27: 0 | D27: ="Hors charges. Retenu à "&TEXT(ROUND(Paramètres!$C$28*100,0),"0")&" %"&" seulement si l'objet est un investissement locatif, ignoré sinon. 0 pour une résidence principale." -> Hors charges. Retenu à 70 % seulement si l'objet est un investissement locatif, ignoré sinon. 0 pour une résidence principale.
B28: Apport personnel | C28: 30000 | D28: Épargne apportée. Doit au moins couvrir les frais de notaire, de garantie et de dossier (contrôle plus bas).
B29: Taux du prêt (hors assurance) | C29: 0.033 | D29: ="Taux nominal annuel. Tapez 3,3 pour 3,30 %. Repère de Paramètres (Observatoire Crédit Logement, vérifié le "&TEXT(DAY(Paramètres!$C$55),"00")&"/"&TEXT(MONTH(Paramètres!$C$55),"00")&"/"&YEAR(Paramètres!$C$55)&") : "&TEXT(INT(ROUND(Paramètres!$C$35*100,2)),"0")&","&TEXT((ROUND(Paramètres!$C$35*100,2)-INT(ROUND(Paramètres!$C$35*100,2)))*100,"00")&" %"&" sur 25 ans." -> Taux nominal annuel. Tapez 3,3 pour 3,30 %. Repère de Paramètres (Observatoire Crédit Logement, vérifié le 05/09/2026) : 3,35 % sur 25 ans.
B30: Durée envisagée | C30: 25 | D30: ="Années entières. "&TEXT(Paramètres!$C$9,"0")&" ans au plus (HCSF), "&TEXT(Paramètres!$C$10,"0")&" avec différé (ligne « Différé »). Au-delà : dossier dérogatoire, contrôle rouge." -> Années entières. 25 ans au plus (HCSF), 27 avec différé (ligne « Différé »). Au-delà : dossier dérogatoire, contrôle rouge.
B31: Taux d'assurance emprunteur (sur capital initial) | C31: 0.003 | D31: ="Taux global du foyer : avec deux emprunteurs couverts à 100 % chacun, additionnez les deux taux. Repères de Paramètres (vérifiés le "&TEXT(DAY(Paramètres!$C$55),"00")&"/"&TEXT(MONTH(Paramètres!$C$55),"00")&"/"&YEAR(Paramètres!$C$55)&") : "&TEXT(INT(ROUND(Paramètres!$C$36*100,2)),"0")&","&TEXT((ROUND(Paramètres!$C$36*100,2)-INT(ROUND(Paramètres!$C$36*100,2)))*100,"00")&" %"&" en contrat groupe, "&TEXT(INT(ROUND(Paramètres!$C$37*100,2)),"0")&","&TEXT((ROUND(Paramètres!$C$37*100,2)-INT(ROUND(Paramètres!$C$37*100,2)))*100,"00")&" %"&" en délégation, par tête." -> Taux global du foyer : avec deux emprunteurs couverts à 100 % chacun, additionnez les deux taux. Repères de Paramètres (vérifiés le 05/09/2026) : 0,36 % en contrat groupe, 0,17 % en délégation, par tête.
B32: Bien neuf ou en VEFA ? | C32: Non | D32: ="Oui : taxe de publicité foncière réduite ("&TEXT(INT(ROUND(Paramètres!$C$15*100,3)),"0")&","&TEXT((ROUND(Paramètres!$C$15*100,3)-INT(ROUND(Paramètres!$C$15*100,3)))*1000,"000")&" %"&") à la place des droits de mutation." -> Oui : taxe de publicité foncière réduite (0,715 %) à la place des droits de mutation.
B33: Différé d'amortissement justifié (VEFA, construction, gros travaux) ? | C33: Non | D33: ="Oui si VEFA, construction, ou travaux d'au moins "&TEXT(ROUND(Paramètres!$C$11*100,0),"0")&" %"&" du coût total : durée HCSF portée à "&TEXT(Paramètres!$C$10,"0")&" ans (différé de 2 ans au plus)." -> Oui si VEFA, construction, ou travaux d'au moins 10 % du coût total : durée HCSF portée à 27 ans (différé de 2 ans au plus).
B34: Droit départemental majoré à 5 % applicable ? | C34: Non | D34: ="Oui dans la grande majorité des départements depuis le 01/04/2025 ("&TEXT(INT(ROUND(Paramètres!$C$13*100,2)),"0")&","&TEXT((ROUND(Paramètres!$C$13*100,2)-INT(ROUND(Paramètres!$C$13*100,2)))*100,"00")&" %"&" de droits). Non si le département est resté au taux de base ("&TEXT(INT(ROUND(Paramètres!$C$14*100,2)),"0")&","&TEXT((ROUND(Paramètres!$C$14*100,2)-INT(ROUND(Paramètres!$C$14*100,2)))*100,"00")&" %"&"), ou pour un primo-accédant achetant sa résidence principale." -> Oui dans la grande majorité des départements depuis le 01/04/2025 (6,32 % de droits). Non si le département est resté au taux de base (5,81 %), ou pour un primo-accédant achetant sa résidence principale.
B35: Taux vraisemblable | C35: =IF(AND(ISNUMBER(Paramètres!$C$48),OR(NOT(ISNUMBER($C$29)),$C$29<=0,$C$29>=Paramètres!$C$48),OR(NOT(ISNUMBER($C$31)),$C$31<=0,$C$31>=Paramètres!$C$48)),"OK","À CORRIGER") -> OK | D35: ="À CORRIGER si le taux du prêt ou le taux d'assurance est strictement positif et inférieur au plancher de plausibilité de Paramètres ("&TEXT(INT(ROUND(Paramètres!$C$48*100,2)),"0")&","&TEXT((ROUND(Paramètres!$C$48*100,2)-INT(ROUND(Paramètres!$C$48*100,2)))*100,"00")&" %"&") : vous avez sans doute tapé 0,033 au lieu de 3,3. Un prêt à taux zéro se saisit 0 exactement." -> À CORRIGER si le taux du prêt ou le taux d'assurance est strictement positif et inférieur au plancher de plausibilité de Paramètres (0,10 %) : vous avez sans doute tapé 0,033 au lieu de 3,3. Un prêt à taux zéro se saisit 0 exactement.
B37: CE QUE LA BANQUE RETIENT
B38: Loyers retenus (pondérés) | C38: =(N($C$10)+IF($C$26=Paramètres!$C$53,N($C$27),0))*Paramètres!$C$28 -> 490 | D38: Loyers actuels, plus loyer du bien financé pour un investissement locatif, multipliés par la pondération de Paramètres.
B39: Revenus retenus par la banque | C39: =SUM($C$7,$C$8,$C$11)+N($C$9)*Paramètres!$C$29+$C$38 -> 5190 | D39: Salaires, primes pondérées, autres revenus et loyers pondérés : le dénominateur de tous les ratios.
B40: Loyer actuel conservé après l'opération | C40: =IF($C$26=Paramètres!$C$52,0,N($C$18)) -> 0 | D40: Le loyer actuel s'il continue (investissement locatif), 0 pour une résidence principale.
B41: Charges retenues | C41: =$C$19+N($C$17)+$C$40 -> 730 | D41: Crédits en cours, pension versée et loyer conservé. Option prudente : tout compte.
B42: Mensualité maximale au taux d'effort | C42: =$C$39*Paramètres!$C$8-$C$41 -> 1086.5 | D42: ="Revenus retenus × taux d'effort HCSF ("&TEXT(ROUND(Paramètres!$C$8*100,0),"0")&" %"&"), moins les charges retenues. Assurance comprise." -> Revenus retenus × taux d'effort HCSF (35 %), moins les charges retenues. Assurance comprise.
B43: Reste à vivre minimal attendu | C43: =N($C$22)*Paramètres!$C$30+N($C$23)*Paramètres!$C$31 -> 1900 | D43: Adultes et enfants multipliés par les minimums de Paramètres. Repère bancaire, pas une règle légale.
B44: Mensualité maximale au reste à vivre | C44: =$C$39-$C$41-$C$43 -> 2560 | D44: Revenus retenus, moins charges retenues, moins reste à vivre minimal.
B45: Mensualité réellement tenable, assurance comprise | C45: =MAX(0,MIN($C$42,$C$44)) -> 1086.5 | D45: La plus contraignante des deux règles. Le chiffre à présenter à la banque.
B46: Reste à vivre du foyer après la mensualité | C46: =$C$39-$C$41-$C$45 -> 3373.5 | D46: Revenus retenus, moins charges retenues, moins la mensualité tenable. Jamais sous le minimum tant qu'une mensualité est possible.
B47: Règle qui limite le dossier | C47: =IF($C$45=0,"Aucune marge",IF($C$42<=$C$44,"Taux d'effort","Reste à vivre")) -> Taux d'effort | D47: Taux d'effort ou reste à vivre. « Aucune marge » : les charges actuelles saturent déjà le dossier.
B48: Taux d'effort HCSF strict | C48: =IF($C$39>0,($C$19+$C$45)/$C$39,"") -> 0.35 | D48: (Crédits en cours + mensualité) / revenus retenus : le ratio déclaré au HCSF, sans loyer ni pension.
B49: Taux de charges tout compris | C49: =IF($C$39>0,($C$41+$C$45)/$C$39,"") -> 0.35 | D49: ="(Charges retenues + mensualité) / revenus retenus : le ratio que le modèle plafonne à "&TEXT(ROUND(Paramètres!$C$8*100,0),"0")&" %"&"." -> (Charges retenues + mensualité) / revenus retenus : le ratio que le modèle plafonne à 35 %.
B50: Endettement dans la norme (taux d'effort et reste à vivre) | C50: =IF(IF($C$39>0,AND($C$45>0,ROUND($C$49,6)<=Paramètres!$C$8,ROUND($C$46,2)>=$C$43),FALSE),"OK","À CORRIGER") -> OK | D50: ="À CORRIGER siles charges actuelles ne laissent aucune mensualité possible. Au-delà de "&TEXT(ROUND(Paramètres!$C$8*100,0),"0")&" %"&" : marge de flexibilité de "&TEXT(ROUND(Paramètres!$C$12*100,0),"0")&" %"&" de la production (Paramètres)." -> À CORRIGER siles charges actuelles ne laissent aucune mensualité possible. Au-delà de 35 % : marge de flexibilité de 20 % de la production (Paramètres).
B52: CAPITAL, FRAIS ET PRIX D'ACHAT
B53: Capital empruntable | C53: =IF(AND(ISNUMBER($C$29),ISNUMBER($C$30),$C$30>0,ISNUMBER($C$31)),PV($C$29/12,$C$30*12,-$C$45)/(1+PV($C$29/12,$C$30*12,-1)*$C$31/12),"") -> 210986.62 | D53: Le montant du prêt, pas le prix du bien. Annuité constante, assurance sur capital initial prise sur la mensualité.
B54: Frais de garantie (caution ou hypothèque) | C54: =IF($C$53="","",$C$53*Paramètres!$C$33) -> 2531.8394 | D54: ="Capital × "&TEXT(INT(ROUND(Paramètres!$C$33*100,2)),"0")&","&TEXT((ROUND(Paramètres!$C$33*100,2)-INT(ROUND(Paramètres!$C$33*100,2)))*100,"00")&" %"&" (Paramètres). À avancer à la signature, même si une caution en restitue une partie à la fin." -> Capital × 1,20 % (Paramètres). À avancer à la signature, même si une caution en restitue une partie à la fin.
B55: Frais de dossier de la banque | C55: =IF($C$53="","",IF($C$53>0,Paramètres!$C$34,0)) -> 2000 | D55: Forfait de Paramètres. 0 s'il n'y a pas de prêt.
B56: Budget total disponible | C56: =IF($C$53="","",$C$53+N($C$28)) -> 240986.62 | D56: Capital plus apport : tout ce qui est disponible, frais compris.
B57: Durée maximale HCSF applicable | C57: =IF($C$33=Paramètres!$B$52,Paramètres!$C$10,Paramètres!$C$9) -> 25 | D57: =TEXT(Paramètres!$C$9,"0")&" ans, ou "&TEXT(Paramètres!$C$10,"0")&" ans avec différé (Paramètres)." -> 25 ans, ou 27 ans avec différé (Paramètres).
B58: Durée conforme HCSF | C58: =IF(AND(ISNUMBER($C$30),$C$30>=1,$C$30<=$C$57),"OK","À CORRIGER") -> OK | D58: À CORRIGER sila durée dépasse le maximum applicable. Un tel dossier ne passe que dans la marge de flexibilité de la banque.
B59: Taux d'usure applicable (selon la durée) | C59: =IF(AND(ISNUMBER($C$30),$C$30>0),IF($C$30<Paramètres!$C$23,Paramètres!$C$20,IF($C$30<Paramètres!$C$24,Paramètres!$C$21,Paramètres!$C$22)),"") -> 0.0529 | D59: ="Tranche choisie automatiquement selon la durée : "&TEXT(INT(ROUND(Paramètres!$C$20*100,2)),"0")&","&TEXT((ROUND(Paramètres!$C$20*100,2)-INT(ROUND(Paramètres!$C$20*100,2)))*100,"00")&" %"&" sous "&TEXT(Paramètres!$C$23,"0")&" ans, "&TEXT(INT(ROUND(Paramètres!$C$21*100,2)),"0")&","&TEXT((ROUND(Paramètres!$C$21*100,2)-INT(ROUND(Paramètres!$C$21*100,2)))*100,"00")&" %"&" de "&TEXT(Paramètres!$C$23,"0")&" à moins de "&TEXT(Paramètres!$C$24,"0")&" ans, "&TEXT(INT(ROUND(Paramètres!$C$22*100,2)),"0")&","&TEXT((ROUND(Paramètres!$C$22*100,2)-INT(ROUND(Paramètres!$C$22*100,2)))*100,"00")&" %"&" à "&TEXT(Paramètres!$C$24,"0")&" ans et plus (Paramètres, Banque de France)." -> Tranche choisie automatiquement selon la durée : 4,07 % sous 10 ans, 4,57 % de 10 à moins de 20 ans, 5,29 % à 20 ans et plus (Paramètres, Banque de France).
B60: Taux et assurance sous le taux d'usure | C60: =IF(AND($C$70="OK",ISNUMBER($C$59)),IF(ROUND(N($C$29)+N($C$31),6)<=$C$59,"OK","À CORRIGER"),"") -> OK | D60: Le plafond légal porte sur le TAEG, que ce classeur ne calcule pas : il compare ici le taux du prêt plus l'assurance, qui est déjà en dessous du TAEG. À CORRIGER veut donc dire que l'offre est certainement illégale ; OK ne garantit pas la conformité, la marge restante doit encore absorber les frais de dossier et de garantie. Le TAEG complet se calcule dans la matrice Tableau d'amortissement.
B61: Frais de notaire, part proportionnelle au prix | C61: =IF($C$32=Paramètres!$B$52,Paramètres!$C$15,IF($C$34=Paramètres!$B$52,Paramètres!$C$13,Paramètres!$C$14))+Paramètres!$C$16+Paramètres!$C$17*(1+Paramètres!$C$19) -> 0.068688 | D61: Droits de mutation (ou taxe de publicité foncière dans le neuf), contribution de sécurité immobilière et taux marginal des émoluments TTC.
B62: Frais de notaire, part fixe | C62: =Paramètres!$C$18*(1+Paramètres!$C$19)+Paramètres!$C$32 -> 1476.7 | D62: Part fixe des émoluments (tranches basses, TTC) et débours.
B63: Prix d'achat maximal (hors frais) | C63: =IF($C$56="","",MAX(0,($C$56-$C$54-$C$55-$C$62)/(1+$C$61))) -> 219875.29 | D63: Le chiffre à donner à l'agent immobilier : budget moins garantie, dossier et frais de notaire.
B64: Frais de notaire estimés | C64: =IF($C$63="","",IF($C$63>0,$C$63*$C$61+$C$62,0)) -> 16579.494 | D64: Sur ce prix : droits, émoluments TTC, contribution de sécurité immobilière, débours.
B65: Frais de notaire rapportés au prix | C65: =IF($C$63="","",IF($C$63>0,$C$64/$C$63,"")) -> 0.07540408 | D65: ="Ordres de grandeur de Paramètres (vérifiés le "&TEXT(DAY(Paramètres!$C$55),"00")&"/"&TEXT(MONTH(Paramètres!$C$55),"00")&"/"&YEAR(Paramètres!$C$55)&") : "&TEXT(INT(ROUND(Paramètres!$C$38*100,1)),"0")&","&TEXT((ROUND(Paramètres!$C$38*100,1)-INT(ROUND(Paramètres!$C$38*100,1)))*10,"0")&" %"&" dans l'ancien, "&TEXT(INT(ROUND(Paramètres!$C$39*100,1)),"0")&","&TEXT((ROUND(Paramètres!$C$39*100,1)-INT(ROUND(Paramètres!$C$39*100,1)))*10,"0")&" %"&" dans le neuf. Plus élevé sur un petit prix." -> Ordres de grandeur de Paramètres (vérifiés le 05/09/2026) : 8,0 % dans l'ancien, 2,5 % dans le neuf. Plus élevé sur un petit prix.
B66: Total des frais à financer | C66: =IF($C$63="","",$C$64+$C$54+$C$55) -> 21111.333 | D66: Notaire, garantie et dossier : ce que l'apport doit couvrir au minimum.
B67: Apport couvre les frais | C67: =IF(IF($C$66<>"",N($C$28)>=ROUND($C$66,2),FALSE),"OK","À CORRIGER") -> OK | D67: À CORRIGER sil'apport est inférieur aux frais : les banques ne financent plus les frais par le prêt, sauf exception.
B68: Saut de charge (mensualité future moins loyer actuel) | C68: =IF($C$26=Paramètres!$C$52,$C$45-N($C$18),"") -> 236.5 | D68: Résidence principale seulement. La banque vérifie que l'épargne mensuelle passée couvrait déjà ce saut.
B69: Coût total du crédit (intérêts et assurance) | C69: =IF($C$53="","",$C$45*12*$C$30-$C$53) -> 114963.38 | D69: Mensualité × 12 × durée, moins le capital. Hors garantie et frais de dossier.
B70: Saisies complètes et dans les bornes | C70: =IF(AND(COUNT($C$7:$C$11)=5,MIN($C$7:$C$11)>=0,COUNT($C$15:$C$18)=4,MIN($C$15:$C$18)>=0,COUNT($C$22:$C$23)=2,$C$22>=1,$C$22<=Paramètres!$C$46,$C$23>=0,$C$23<=Paramètres!$C$47,INT(N($C$22))=N($C$22),INT(N($C$23))=N($C$23),COUNT($C$27:$C$31)=5,MIN($C$27:$C$28)>=0,$C$29>=0,$C$29<=Paramètres!$C$43,$C$30>=1,$C$30<=Paramètres!$C$45,INT(N($C$30))=N($C$30),$C$31>=0,$C$31<=Paramètres!$C$44,NOT(ISNA(MATCH($C$26,Paramètres!$C$52:$C$53,0))),NOT(ISNA(MATCH($C$32,Paramètres!$B$52:$B$53,0))),NOT(ISNA(MATCH($C$33,Paramètres!$B$52:$B$53,0))),NOT(ISNA(MATCH($C$34,Paramètres!$B$52:$B$53,0))),$C$39>0,$C$35="OK",COUNT(Paramètres!$C$8:$C$24)=17,COUNT(Paramètres!$C$28:$C$39)=12,COUNT(Paramètres!$C$43:$C$48)=6),"OK","À CORRIGER") -> OK | D70: À CORRIGER : unesaisie manque, n'est pas un nombre ou sort des bornes de Paramètres, une liste est hors valeurs, un paramètre est vide, ou les revenus sont nuls.
B72: CorpusImmo, millésime 2026. Modèle d'aide à la décision : ne constitue ni un conseil en investissement, ni un conseil fiscal, ni une expertise au sens de la charte de l'expertise en évaluation immobilière. Vérifiez les paramètres avant tout engagement.

Sheet Bilan patrimonial
B1: CorpusImmo · corpus.immo · Estimer, comparer, décider. Sur les ventes réelles.
B2: Bilan patrimonial
B3: Ce que la banque regarde après les revenus : ce que vous possédez déjà, et ce qu'il en restera après l'achat.
B5: Cellules bleues : à remplir. Cellules blanches : calculées automatiquement.
B6: ACTIF IMMOBILIER (VALEUR DE MARCHÉ)
B7: Résidence principale | C7: 0 | D7: Valeur de revente réaliste aujourd'hui (pas le prix payé). 0 si vous êtes locataire.
B8: Biens locatifs | C8: 140000 | D8: Valeur de marché des biens loués. Leurs loyers sont saisis dans Capacité d'emprunt.
B9: Autres biens immobiliers | C9: 0 | D9: Résidence secondaire, terrain, parking, nue-propriété (à sa valeur décotée).
B10: Total immobilier | C10: =SUM($C$7:$C$9) -> 140000 | D10: Valeur brute du patrimoine immobilier.
B12: LIQUIDITÉS ET PLACEMENTS
B13: Comptes courants et livrets | C13: 18000 | D13: Disponibles immédiatement : comptes, Livret A, LDDS, LEP, CEL, PEL.
B14: Assurance-vie | C14: 25000 | D14: Valeur de rachat. Mobilisable sous quelques semaines, avec la fiscalité du rachat.
B15: PEA et comptes-titres | C15: 12000 | D15: Valeur liquidative. Un retrait sur un PEA de moins de cinq ans entraîne sa clôture.
B16: Épargne retraite (PER, PERCO) | C16: 8000 | D16: Bloquée jusqu'à la retraite, sauf déblocage pour l'achat de la résidence principale (PER individuel) : non comptée dans les liquidités mobilisables.
B17: Parts de sociétés et SCPI | C17: 0 | D17: Valeur de retrait ou de marché. Peu liquide : non comptée dans les liquidités mobilisables.
B18: Autres actifs (véhicules, œuvres, métaux) | C18: 0 | D18: À la valeur de revente. Non comptés dans les liquidités mobilisables.
B19: Total liquidités et placements | C19: =SUM($C$13:$C$18) -> 63000 | D19: Actif financier brut.
B20: Liquidités mobilisables pour l'apport | C20: =SUM($C$13:$C$15) -> 55000 | D20: Comptes et livrets, assurance-vie, PEA et comptes-titres. Ce que la banque accepte comme apport disponible.
B22: PASSIF (CAPITAL RESTANT DÛ)
B23: Capital restant dû, résidence principale | C23: 0 | D23: Lire le dernier tableau d'amortissement, pas la mensualité.
B24: Capital restant dû, biens locatifs | C24: 60000 | D24: Encours des prêts des biens loués. Leur mensualité est dans Capacité d'emprunt (crédits immobiliers en cours).
B25: Crédit auto ou consommation (restant dû) | C25: 6500 | D25: Capital restant dû, pas la mensualité.
B26: Découverts et crédits renouvelables | C26: 0 | D26: Encours utilisé à ce jour.
B27: Impôts et charges à régler | C27: 0 | D27: Impôt sur le revenu restant dû, taxe foncière à venir, charges de copropriété impayées.
B28: Autres dettes | C28: 0 | D28: Prêt familial, soulte, dette professionnelle personnelle.
B29: Encours immobilier | C29: =SUM($C$23:$C$24) -> 60000 | D29: Capital restant dû sur l'ensemble des biens immobiliers.
B30: Total passif | C30: =SUM($C$23:$C$28) -> 66500 | D30: Tout ce qui est dû aujourd'hui.
B32: LECTURE BANCAIRE, AVANT L'OPÉRATION
B33: Total actif | C33: =$C$10+$C$19 -> 203000 | D33: Immobilier plus liquidités et placements.
B34: Patrimoine net | C34: =$C$33-$C$30 -> 136500 | D34: Ce qui reste si tout est vendu et toutes les dettes soldées. Ce qui amortit un accident de parcours aux yeux de la banque.
B35: Patrimoine immobilier net | C35: =$C$10-$C$29 -> 80000 | D35: Valeur des biens moins leur encours de crédit.
B36: Endettement immobilier (encours / valeur, LTV) | C36: =IF($C$10>0,$C$29/$C$10,"") -> 0.42857143 | D36: Plus il est proche de 100 %, moins l'immobilier existant offre de marge de sûreté à la banque.
B37: Ratio dettes / actif brut | C37: =IF($C$33>0,$C$30/$C$33,"") -> 0.32758621 | D37: Un ratio de stock (dettes totales rapportées à l'actif total), à ne pas confondre avec le taux d'effort, qui est un ratio de flux.
B38: Dette totale / revenus annuels retenus | C38: =IF('Capacité d''emprunt'!$C$39>0,$C$30/('Capacité d''emprunt'!$C$39*12),"") -> 1.0677585 | D38: En années de revenus retenus (Capacité d'emprunt). Plus il est élevé, plus la stabilité des revenus compte.
B40: APPORT ET ÉPARGNE DE PRÉCAUTION
B41: Apport prévu (lu dans Capacité d'emprunt) | C41: =N('Capacité d''emprunt'!$C$28) -> 30000 | D41: Repris de l'onglet Capacité d'emprunt.
B42: Épargne résiduelle après apport | C42: =$C$20-$C$41 -> 25000 | D42: Liquidités mobilisables moins apport : l'épargne de précaution que la banque veut voir subsister.
B43: Épargne résiduelle en mois de mensualité future | C43: =IF('Capacité d''emprunt'!$C$45>0,$C$42/'Capacité d''emprunt'!$C$45,"") -> 23.009664 | D43: Épargne résiduelle divisée par la mensualité tenable. Vide si aucune mensualité n'est possible.
B44: Apport couvert par les liquidités | C44: =IF($C$41<=$C$20,"OK","À CORRIGER") -> OK | D44: À CORRIGER sil'apport prévu dépasse les liquidités mobilisables : il faudra un rachat, un déblocage de PER ou une donation.
B45: Saisies du bilan complètes et positives | C45: =IF(AND(COUNT($C$7:$C$9)=3,COUNT($C$13:$C$18)=6,COUNT($C$23:$C$28)=6,MIN($C$7:$C$9)>=0,MIN($C$13:$C$18)>=0,MIN($C$23:$C$28)>=0),"OK","À CORRIGER") -> OK | D45: À CORRIGER : unecellule bleue de cet onglet est vide, n'est pas un nombre ou est négative.
B47: PRO FORMA APRÈS L'OPÉRATION (AU PRIX MAXIMAL)
B48: Bien acquis (prix maximal de Capacité d'emprunt) | C48: =IF('Capacité d''emprunt'!$C$53="","",'Capacité d''emprunt'!$C$63) -> 219875.29 | D48: Scénario plafond : le foyer achète au prix maximal calculé.
B49: Frais de l'opération (notaire, garantie, dossier) | C49: =IF('Capacité d''emprunt'!$C$53="","",'Capacité d''emprunt'!$C$66) -> 21111.333 | D49: Payés par l'apport, ils sortent du patrimoine : c'est le coût patrimonial immédiat de l'achat.
B50: Nouveau prêt | C50: =IF('Capacité d''emprunt'!$C$53="","",'Capacité d''emprunt'!$C$53) -> 210986.62 | D50: Capital empruntable.
B51: Total actif pro forma | C51: =IF('Capacité d''emprunt'!$C$53="","",$C$33-$C$41+$C$48) -> 392875.29 | D51: Actif actuel, moins l'apport, plus le bien acquis.
B52: Total passif pro forma | C52: =IF('Capacité d''emprunt'!$C$53="","",$C$30+$C$50) -> 277486.62 | D52: Passif actuel plus le nouveau prêt.
B53: Patrimoine net pro forma | C53: =IF('Capacité d''emprunt'!$C$53="","",$C$51-$C$52) -> 115388.67 | D53: Patrimoine net après l'achat, le jour de la signature.
B54: Variation du patrimoine net | C54: =IF('Capacité d''emprunt'!$C$53="","",$C$53-$C$34) -> -21111.333 | D54: Égale aux frais de l'opération, en négatif : ils sont perdus. Le bien s'apprécie ensuite (ou non).
B55: Endettement immobilier pro forma (LTV) | C55: =IF('Capacité d''emprunt'!$C$53="","",IF($C$10+$C$48>0,($C$29+$C$50)/($C$10+$C$48),"")) -> 0.75300147 | D55: Encours total après l'achat rapporté à la valeur immobilière totale.
B56: Ratio dettes / actif brut pro forma | C56: =IF('Capacité d''emprunt'!$C$53="","",IF($C$51>0,$C$52/$C$51,"")) -> 0.70629696 | D56: Dettes totales après l'achat rapportées à l'actif total.
B58: CorpusImmo, millésime 2026. Modèle d'aide à la décision : ne constitue ni un conseil en investissement, ni un conseil fiscal, ni une expertise au sens de la charte de l'expertise en évaluation immobilière. Vérifiez les paramètres avant tout engagement.

Sheet Paramètres
B1: CorpusImmo · corpus.immo · Estimer, comparer, décider. Sur les ventes réelles.
B2: Paramètres
B3: Les règles de la banque et les barèmes 2026, en clair. Toutes les formules du classeur pointent ici.
B5: Cellules bleues : à remplir. Cellules blanches : calculées automatiquement.
B6: BARÈMES RÉGLEMENTAIRES, MILLÉSIME 2026
B7: Paramètre | C7: Valeur | D7: Source (organisme, texte, date) | E7: Mise à jour | F7: Commentaire
B8: Taux d'effort maximal HCSF (assurance comprise) | C8: 0.35 | D8: ="HCSF, décision D-HCSF-2021-7 du 29/09/2021, confirmée par la décision D-HCSF-2023-2 du 29/06/2023. economie.gouv.fr/hcsf, vérifié le "&TEXT(DAY(Paramètres!$C$55),"00")&"/"&TEXT(MONTH(Paramètres!$C$55),"00")&"/"&YEAR(Paramètres!$C$55)&"." -> HCSF, décision D-HCSF-2021-7 du 29/09/2021, confirmée par la décision D-HCSF-2023-2 du 29/06/2023. economie.gouv.fr/hcsf, vérifié le 05/09/2026. | E8: À chaque décision HCSF (réunion trimestrielle) | F8: Charges d'emprunt assurance comprise rapportées aux revenus nets avant impôt. Norme contraignante depuis le 01/01/2022, avec une marge de flexibilité (ligne plus bas).
B9: Durée maximale HCSF, cas général | C9: 25 | D9: ="HCSF, décision D-HCSF-2021-7 du 29/09/2021. Vérifié le "&TEXT(DAY(Paramètres!$C$55),"00")&"/"&TEXT(MONTH(Paramètres!$C$55),"00")&"/"&YEAR(Paramètres!$C$55)&"." -> HCSF, décision D-HCSF-2021-7 du 29/09/2021. Vérifié le 05/09/2026. | E9: À chaque décision HCSF | F9: Maturité maximale du crédit.
B10: Durée maximale HCSF avec différé (VEFA, construction, travaux) | C10: 27 | D10: ="HCSF, décisions du 29/09/2021 (différé de 2 ans au plus) et du 29/06/2023 (seuil de travaux abaissé de 25 % à 10 % du coût total). Vérifié le "&TEXT(DAY(Paramètres!$C$55),"00")&"/"&TEXT(MONTH(Paramètres!$C$55),"00")&"/"&YEAR(Paramètres!$C$55)&"." -> HCSF, décisions du 29/09/2021 (différé de 2 ans au plus) et du 29/06/2023 (seuil de travaux abaissé de 25 % à 10 % du coût total). Vérifié le 05/09/2026. | E10: À chaque décision HCSF | F10: Durée générale plus 2 ans de différé d'amortissement au plus, quand le bien n'est pas livré ou que les travaux atteignent le seuil de la ligne suivante.
B11: Seuil de travaux ouvrant le différé (part du coût total) | C11: 0.1 | D11: ="HCSF, décision D-HCSF-2023-2 du 29/06/2023 (auparavant 25 %). Vérifié le "&TEXT(DAY(Paramètres!$C$55),"00")&"/"&TEXT(MONTH(Paramètres!$C$55),"00")&"/"&YEAR(Paramètres!$C$55)&"." -> HCSF, décision D-HCSF-2023-2 du 29/06/2023 (auparavant 25 %). Vérifié le 05/09/2026. | E11: À chaque décision HCSF | F11: Information : sert à répondre à la question « Différé » de l'onglet Capacité d'emprunt, pas aux formules.
B12: Marge de flexibilité HCSF (part de la production trimestrielle) | C12: 0.2 | D12: ="HCSF, décision D-HCSF-2023-2 du 29/06/2023 : 20 % de la production, dont au moins 70 % pour la résidence principale et au moins 30 % pour les primo-accédants. Utilisée à 17,5 % au 1er trimestre 2026 (Meilleurtaux, 11/06/2026). Vérifié le "&TEXT(DAY(Paramètres!$C$55),"00")&"/"&TEXT(MONTH(Paramètres!$C$55),"00")&"/"&YEAR(Paramètres!$C$55)&"." -> HCSF, décision D-HCSF-2023-2 du 29/06/2023 : 20 % de la production, dont au moins 70 % pour la résidence principale et au moins 30 % pour les primo-accédants. Utilisée à 17,5 % au 1er trimestre 2026 (Meilleurtaux, 11/06/2026). Vérifié le 05/09/2026. | E12: À chaque décision HCSF | F12: Information : non utilisée par les formules. Un dossier au-delà du taux d'effort ou de la durée ne passe que dans cette marge, à la main de chaque banque.
B13: Droits de mutation, ancien, droit départemental majoré à 5 % | C13: 0.0632 | D13: ="LF 2025 (loi n° 2025-127 du 14/02/2025) art. 116 : droit départemental porté de 4,50 % à 5 % (CGI art. 1594 D) du 01/04/2025 au 31/03/2028 ; taxe communale 1,20 % (art. 1584) ; frais d'assiette 2,37 % du droit départemental (art. 1647 V). taximmo.fr,"&" vérifié le "&TEXT(DAY(Paramètres!$C$55),"00")&"/"&TEXT(MONTH(Paramètres!$C$55),"00")&"/"&YEAR(Paramètres!$C$55)&"." -> LF 2025 (loi n° 2025-127 du 14/02/2025) art. 116 : droit départemental porté de 4,50 % à 5 % (CGI art. 1594 D) du 01/04/2025 au 31/03/2028 ; taxe communale 1,20 % (art. 1584) ; frais d'assiette 2,37 % du droit départemental (art. 1647 V). taximmo.fr, vérifié le 05/09/2026. | E13: À chaque loi de finances ; échéance 31/03/2028 | F13: 5 % × 1,0237 + 1,20 % = 6,32 %. Appliqué par la grande majorité des départements ; le classeur demande si le droit majoré s'applique.
B14: Droits de mutation, ancien, droit départemental à 4,50 % | C14: 0.0581 | D14: ="CGI art. 1594 D (4,50 %), 1584 (1,20 %), 1647 V (2,37 %). Maintenu dans les départements qui n'ont pas voté la hausse et pour les primo-accédants achetant leur résidence principale (LF 2025 art. 116, II). taximmo.fr, vérifié le "&TEXT(DAY(Paramètres!$C$55),"00")&"/"&TEXT(MONTH(Paramètres!$C$55),"00")&"/"&YEAR(Paramètres!$C$55)&"." -> CGI art. 1594 D (4,50 %), 1584 (1,20 %), 1647 V (2,37 %). Maintenu dans les départements qui n'ont pas voté la hausse et pour les primo-accédants achetant leur résidence principale (LF 2025 art. 116, II). taximmo.fr, vérifié le 05/09/2026. | E14: À chaque loi de finances | F14: 4,50 % × 1,0237 + 1,20 % = 5,81 %.
B15: Taxe de publicité foncière, neuf ou VEFA | C15: 0.00715 | D15: ="CGI art. 1594 F quinquies A (taux réduit 0,70 %) et 1647 V (frais d'assiette 2,14 %). Vérifié le "&TEXT(DAY(Paramètres!$C$55),"00")&"/"&TEXT(MONTH(Paramètres!$C$55),"00")&"/"&YEAR(Paramètres!$C$55)&"." -> CGI art. 1594 F quinquies A (taux réduit 0,70 %) et 1647 V (frais d'assiette 2,14 %). Vérifié le 05/09/2026. | E15: À chaque loi de finances | F15: 0,70 % × 1,0214 = 0,715 %. Remplace les droits de mutation pour un logement neuf ou vendu en l'état futur d'achèvement.
B16: Contribution de sécurité immobilière | C16: 0.001 | D16: ="CGI art. 879 : 0,10 % du prix, ancien comme neuf. Vérifié le "&TEXT(DAY(Paramètres!$C$55),"00")&"/"&TEXT(MONTH(Paramètres!$C$55),"00")&"/"&YEAR(Paramètres!$C$55)&"." -> CGI art. 879 : 0,10 % du prix, ancien comme neuf. Vérifié le 05/09/2026. | E16: À chaque loi de finances | F16: Ex-salaire du conservateur des hypothèques.
B17: Émoluments du notaire, taux marginal au-delà de 60 000 € (HT) | C17: 0.00799 | D17: ="Code de commerce art. A444-91, arrêté du 25/02/2026 (en vigueur du 01/03/2026 au 29/02/2028) : 3,870 % jusqu'à 6 500 €, 1,596 % de 6 500 à 17 000 €, 1,064 % de 17 000 à 60 000 €, 0,799 % au-delà. pretto.fr, vérifié le "&TEXT(DAY(Paramètres!$C$55),"00")&"/"&TEXT(MONTH(Paramètres!$C$55),"00")&"/"&YEAR(Paramètres!$C$55)&"." -> Code de commerce art. A444-91, arrêté du 25/02/2026 (en vigueur du 01/03/2026 au 29/02/2028) : 3,870 % jusqu'à 6 500 €, 1,596 % de 6 500 à 17 000 €, 1,064 % de 17 000 à 60 000 €, 0,799 % au-delà. pretto.fr, vérifié le 05/09/2026. | E17: À chaque arrêté tarifaire (tous les deux ans) | F17: Le classeur applique la forme linéaire du barème au-delà de 60 000 € : taux marginal × prix + part fixe (ligne suivante). En dessous de 60 000 €, il surestime légèrement les émoluments (prudent).
B18: Émoluments du notaire, part fixe des tranches inférieures (HT) | C18: 397.25 | D18: Calcul depuis le barème A444-91 : 6 500 × (3,870 − 0,799) % + 10 500 × (1,596 − 0,799) % + 43 000 × (1,064 − 0,799) % = 397,25 €. | E18: À chaque arrêté tarifaire | F18: Ce que les trois premières tranches ajoutent par rapport au taux marginal appliqué dès le premier euro.
B19: TVA sur les émoluments | C19: 0.2 | D19: ="CGI art. 278 : taux normal 20 %. Vérifié le "&TEXT(DAY(Paramètres!$C$55),"00")&"/"&TEXT(MONTH(Paramètres!$C$55),"00")&"/"&YEAR(Paramètres!$C$55)&"." -> CGI art. 278 : taux normal 20 %. Vérifié le 05/09/2026. | E19: À chaque loi de finances | F19: Les émoluments sont exprimés HT dans le barème ; l'acquéreur les paie TTC.
B20: Taux d'usure, prêts à taux fixe de moins de 10 ans | C20: 0.0407 | D20: ="Banque de France, taux d'usure applicables au 3e trimestre 2026, avis publié le 29/06/2026 et applicable depuis le 01/07/2026. banque-france.fr, rubrique Taux d'usure. Vérifié le "&TEXT(DAY(Paramètres!$C$55),"00")&"/"&TEXT(MONTH(Paramètres!$C$55),"00")&"/"&YEAR(Paramètres!$C$55)&"." -> Banque de France, taux d'usure applicables au 3e trimestre 2026, avis publié le 29/06/2026 et applicable depuis le 01/07/2026. banque-france.fr, rubrique Taux d'usure. Vérifié le 05/09/2026. | E20: Trimestrielle (1er janvier, avril, juillet, octobre) | F20: Plafond légal du TAEG. Une offre au-dessus est illégale.
B21: Taux d'usure, prêts à taux fixe de 10 ans à moins de 20 ans | C21: 0.0457 | D21: ="Banque de France, taux d'usure applicables au 3e trimestre 2026, avis publié le 29/06/2026 et applicable depuis le 01/07/2026. banque-france.fr, rubrique Taux d'usure. Vérifié le "&TEXT(DAY(Paramètres!$C$55),"00")&"/"&TEXT(MONTH(Paramètres!$C$55),"00")&"/"&YEAR(Paramètres!$C$55)&"." -> Banque de France, taux d'usure applicables au 3e trimestre 2026, avis publié le 29/06/2026 et applicable depuis le 01/07/2026. banque-france.fr, rubrique Taux d'usure. Vérifié le 05/09/2026. | E21: Trimestrielle
B22: Taux d'usure, prêts à taux fixe de 20 ans et plus | C22: 0.0529 | D22: ="Banque de France, taux d'usure applicables au 3e trimestre 2026, avis publié le 29/06/2026 et applicable depuis le 01/07/2026. banque-france.fr, rubrique Taux d'usure. Vérifié le "&TEXT(DAY(Paramètres!$C$55),"00")&"/"&TEXT(MONTH(Paramètres!$C$55),"00")&"/"&YEAR(Paramètres!$C$55)&"." -> Banque de France, taux d'usure applicables au 3e trimestre 2026, avis publié le 29/06/2026 et applicable depuis le 01/07/2026. banque-france.fr, rubrique Taux d'usure. Vérifié le 05/09/2026. | E22: Trimestrielle | F22: Tranche de la plupart des prêts immobiliers (20 et 25 ans).
B23: Seuil de durée entre les deux premières tranches d'usure | C23: 10 | D23: ="Banque de France, taux d'usure applicables au 3e trimestre 2026, avis publié le 29/06/2026 et applicable depuis le 01/07/2026. banque-france.fr, rubrique Taux d'usure. Vérifié le "&TEXT(DAY(Paramètres!$C$55),"00")&"/"&TEXT(MONTH(Paramètres!$C$55),"00")&"/"&YEAR(Paramètres!$C$55)&"." -> Banque de France, taux d'usure applicables au 3e trimestre 2026, avis publié le 29/06/2026 et applicable depuis le 01/07/2026. banque-france.fr, rubrique Taux d'usure. Vérifié le 05/09/2026. | E23: Stable | F23: Le classeur choisit la tranche d'usure selon la durée du prêt. Le tableau d'amortissement porte le même seuil en mois (120).
B24: Seuil de durée entre les deux dernières tranches d'usure | C24: 20 | D24: ="Banque de France, taux d'usure applicables au 3e trimestre 2026, avis publié le 29/06/2026 et applicable depuis le 01/07/2026. banque-france.fr, rubrique Taux d'usure. Vérifié le "&TEXT(DAY(Paramètres!$C$55),"00")&"/"&TEXT(MONTH(Paramètres!$C$55),"00")&"/"&YEAR(Paramètres!$C$55)&"." -> Banque de France, taux d'usure applicables au 3e trimestre 2026, avis publié le 29/06/2026 et applicable depuis le 01/07/2026. banque-france.fr, rubrique Taux d'usure. Vérifié le 05/09/2026. | E24: Stable | F24: Même seuil que le tableau d'amortissement, exprimé en années (240 mois).
B26: REPÈRES DE MARCHÉ (POINTS DE DÉPART, À AJUSTER SELON LA BANQUE)
B27: Paramètre | C27: Valeur | D27: Source (organisme, texte, date) | E27: Mise à jour | F27: Commentaire
B28: Pondération des revenus locatifs | C28: 0.7 | D28: ="Usage bancaire : 70 % chez la plupart des banques, 80 à 90 % chez quelques-unes sur dossiers de qualité. empruntis.com, quelcredit.com, vérifié le "&TEXT(DAY(Paramètres!$C$55),"00")&"/"&TEXT(MONTH(Paramètres!$C$55),"00")&"/"&YEAR(Paramètres!$C$55)&"." -> Usage bancaire : 70 % chez la plupart des banques, 80 à 90 % chez quelques-unes sur dossiers de qualité. empruntis.com, quelcredit.com, vérifié le 05/09/2026. | E28: Annuelle, selon la banque visée | F28: Couvre la vacance, les impayés et les charges du bailleur. S'applique aux loyers actuels et au loyer du bien financé.
B29: Pondération des primes et variables | C29: 1 | D29: ="Usage bancaire : 100 % si récurrentes sur 2 à 3 ans, 75 % dans certains établissements. prettymo.fr, vérifié le "&TEXT(DAY(Paramètres!$C$55),"00")&"/"&TEXT(MONTH(Paramètres!$C$55),"00")&"/"&YEAR(Paramètres!$C$55)&"." -> Usage bancaire : 100 % si récurrentes sur 2 à 3 ans, 75 % dans certains établissements. prettymo.fr, vérifié le 05/09/2026. | E29: Annuelle, selon la banque visée | F29: Paramètre optionnel. Laissez 100 % si les primes sont déjà lissées sur 3 ans.
B30: Reste à vivre minimal par adulte | C30: 800 | D30: ="Usage bancaire : 700 à 1 000 € par adulte, davantage en Île-de-France ; aucun minimum légal. reassurez-moi.fr (2026), selectra.info, vérifié le "&TEXT(DAY(Paramètres!$C$55),"00")&"/"&TEXT(MONTH(Paramètres!$C$55),"00")&"/"&YEAR(Paramètres!$C$55)&"." -> Usage bancaire : 700 à 1 000 € par adulte, davantage en Île-de-France ; aucun minimum légal. reassurez-moi.fr (2026), selectra.info, vérifié le 05/09/2026. | E30: Annuelle, selon la banque visée | F30: Ordre de grandeur ; varie fortement selon la banque et la zone.
B31: Reste à vivre minimal par enfant à charge | C31: 300 | D31: ="Usage bancaire : 300 à 500 € par enfant. Mêmes sources, vérifié le "&TEXT(DAY(Paramètres!$C$55),"00")&"/"&TEXT(MONTH(Paramètres!$C$55),"00")&"/"&YEAR(Paramètres!$C$55)&"." -> Usage bancaire : 300 à 500 € par enfant. Mêmes sources, vérifié le 05/09/2026. | E31: Annuelle, selon la banque visée | F31: Par enfant à charge.
B32: Débours et frais de formalités du notaire (forfait) | C32: 1000 | D32: ="frais-de-notaire.fr (CSI et débours 1 100 € pour 300 000 €, dont CSI 300 €) et pretto.fr (environ 0,4 % du prix) : 800 à 1 200 € pour un logement. Vérifié le "&TEXT(DAY(Paramètres!$C$55),"00")&"/"&TEXT(MONTH(Paramètres!$C$55),"00")&"/"&YEAR(Paramètres!$C$55)&"." -> frais-de-notaire.fr (CSI et débours 1 100 € pour 300 000 €, dont CSI 300 €) et pretto.fr (environ 0,4 % du prix) : 800 à 1 200 € pour un logement. Vérifié le 05/09/2026. | E32: Annuelle | F32: Documents d'urbanisme, état hypothécaire, cadastre, géomètre : des frais réels, peu liés au prix.
B33: Frais de garantie du prêt (en % du capital emprunté) | C33: 0.012 | D33: ="Convention prudente du classeur : Crédit Logement ne publie pas son barème et les relevés de place vont de 0,85 % + 200 € (optimhome.com, 2026) à 1,5 à 1,75 % du capital (perlib.fr, 2026). Vérifié le "&TEXT(DAY(Paramètres!$C$55),"00")&"/"&TEXT(MONTH(Paramètres!$C$55),"00")&"/"&YEAR(Paramètres!$C$55)&"." -> Convention prudente du classeur : Crédit Logement ne publie pas son barème et les relevés de place vont de 0,85 % + 200 € (optimhome.com, 2026) à 1,5 à 1,75 % du capital (perlib.fr, 2026). Vérifié le 05/09/2026. | E33: Annuelle, sur le simulateur creditlogement.fr | F33: Aucune source primaire ne tranche : le classeur retient la borne haute des relevés, parce que sous-estimer un coût avancé par l'emprunteur flatte le plan de financement. Caution : 65 à 70 % restitués en fin de prêt. Hypothèque ou PPD : 1,5 à 2 %, non restituables. À avancer dans tous les cas.
B34: Frais de dossier de la banque (forfait) | C34: 2000 | D34: ="Meilleurtaux, relevé de 119 banques au 01/03/2026 : moyenne 1 899,68 € pour 200 000 €, 92 établissements entre 0,50 % et 1,40 % du capital, de 0 € à 2 500 € selon les banques. Vérifié le "&TEXT(DAY(Paramètres!$C$55),"00")&"/"&TEXT(MONTH(Paramètres!$C$55),"00")&"/"&YEAR(Paramètres!$C$55)&"." -> Meilleurtaux, relevé de 119 banques au 01/03/2026 : moyenne 1 899,68 € pour 200 000 €, 92 établissements entre 0,50 % et 1,40 % du capital, de 0 € à 2 500 € selon les banques. Vérifié le 05/09/2026. | E34: Annuelle | F34: Négociables. 0 € dans quelques banques en ligne, 2 500 € au plafond le plus élevé du relevé. Valeur prudente, arrondie au-dessus de la moyenne du relevé.
B35: Taux moyen constaté sur 25 ans (repère pour la saisie du taux) | C35: 0.0335 | D35: ="Observatoire Crédit Logement / CSA, analyse du marché du mois d'août 2026 (publiée en septembre 2026) : 3,35 % sur 25 ans, 3,14 % sur 15 ans, en hausse de 15 centièmes de point depuis décembre 2025. lobservatoire.creditlogement.fr. Vérifié le "&TEXT(DAY(Paramètres!$C$55),"00")&"/"&TEXT(MONTH(Paramètres!$C$55),"00")&"/"&YEAR(Paramètres!$C$55)&"." -> Observatoire Crédit Logement / CSA, analyse du marché du mois d'août 2026 (publiée en septembre 2026) : 3,35 % sur 25 ans, 3,14 % sur 15 ans, en hausse de 15 centièmes de point depuis décembre 2025. lobservatoire.creditlogement.fr. Vérifié le 05/09/2026. | E35: Mensuelle | F35: Information : non utilisée par les formules. Le taux du dossier se saisit dans l'onglet Capacité d'emprunt.
B36: Taux d'assurance emprunteur, contrat groupe (repère) | C36: 0.0036 | D36: ="Baromètres 2026 (pretclair.fr, covelia.fr) : environ 0,36 % du capital initial, 35 ans non fumeur. Vérifié le "&TEXT(DAY(Paramètres!$C$55),"00")&"/"&TEXT(MONTH(Paramètres!$C$55),"00")&"/"&YEAR(Paramètres!$C$55)&"." -> Baromètres 2026 (pretclair.fr, covelia.fr) : environ 0,36 % du capital initial, 35 ans non fumeur. Vérifié le 05/09/2026. | E36: Annuelle | F36: Information : repère pour la saisie du taux d'assurance. Davantage après 45 ans ou avec surprime.
B37: Taux d'assurance emprunteur, délégation (repère) | C37: 0.0017 | D37: ="Baromètres 2026 (pretclair.fr, covelia.fr) : environ 0,17 % du capital initial, 35 ans non fumeur. Vérifié le "&TEXT(DAY(Paramètres!$C$55),"00")&"/"&TEXT(MONTH(Paramètres!$C$55),"00")&"/"&YEAR(Paramètres!$C$55)&"." -> Baromètres 2026 (pretclair.fr, covelia.fr) : environ 0,17 % du capital initial, 35 ans non fumeur. Vérifié le 05/09/2026. | E37: Annuelle | F37: Information : repère pour la saisie du taux d'assurance.
B38: Frais de notaire usuels dans l'ancien (ordre de grandeur) | C38: 0.08 | D38: ="frais-de-notaire.fr, achat ancien 2026 : 7,8 % pour 300 000 €, de 7 à 8,5 % selon le prix. Vérifié le "&TEXT(DAY(Paramètres!$C$55),"00")&"/"&TEXT(MONTH(Paramètres!$C$55),"00")&"/"&YEAR(Paramètres!$C$55)&"." -> frais-de-notaire.fr, achat ancien 2026 : 7,8 % pour 300 000 €, de 7 à 8,5 % selon le prix. Vérifié le 05/09/2026. | E38: Annuelle | F38: Information : repère pour lire la ligne « Frais de notaire rapportés au prix ». Le classeur calcule les frais réels.
B39: Frais de notaire usuels dans le neuf (ordre de grandeur) | C39: 0.025 | D39: ="meilleurescpi.com, frais de notaire 2026 : 2 à 3 % dans le neuf. Vérifié le "&TEXT(DAY(Paramètres!$C$55),"00")&"/"&TEXT(MONTH(Paramètres!$C$55),"00")&"/"&YEAR(Paramètres!$C$55)&"." -> meilleurescpi.com, frais de notaire 2026 : 2 à 3 % dans le neuf. Vérifié le 05/09/2026. | E39: Annuelle | F39: Information : repère pour lire la ligne « Frais de notaire rapportés au prix ».
B41: BORNES DE SAISIE (VALIDATIONS ET CONTRÔLE GLOBAL)
B42: Paramètre | C42: Valeur | D42: Source (organisme, texte, date) | E42: Mise à jour | F42: Commentaire
B43: Borne de saisie : taux du prêt maximal | C43: 0.2 | D43: Borne de vraisemblance du classeur, sans valeur réglementaire. | E43: Jamais | F43: Une saisie au-delà est refusée et le contrôle global passe au rouge.
B44: Borne de saisie : taux d'assurance maximal | C44: 0.05 | D44: Borne de vraisemblance du classeur. | E44: Jamais | F44: Idem.
B45: Borne de saisie : durée maximale acceptée | C45: 30 | D45: Borne de vraisemblance du classeur : au-delà du maximum HCSF, la durée reste saisissable (dossier dérogatoire) mais le contrôle de durée est rouge. | E45: Jamais
B46: Borne de saisie : nombre d'adultes maximal | C46: 6 | D46: Borne de vraisemblance du classeur. | E46: Jamais | F46: Au moins 1 adulte.
B47: Borne de saisie : nombre d'enfants maximal | C47: 15 | D47: Borne de vraisemblance du classeur. | E47: Jamais
B48: Plancher de plausibilité d'un taux saisi | C48: 0.001 | D48: Convention CorpusImmo, commune aux matrices qui saisissent des taux. | E48: Stable | F48: Un taux entre 0 et 0,10 % signale presque toujours une saisie en fraction (0,033 tapé pour 3,30 %). Le contrôle « Taux vraisemblable » passe au rouge dans ce cas, sauf à 0 % exactement (prêt à taux zéro, ou pas d'assurance).
B50: LISTES DÉROULANTES DE L'ONGLET CAPACITÉ D'EMPRUNT
B51: Oui / Non (bien neuf, différé, droit majoré) | C51: Objet du financement
B52: Oui | C52: Résidence principale | D52: Libellés fixes, testés par les formules : ne pas les modifier.
B53: Non | C53: Investissement locatif
B55: Dernière vérification des paramètres | C55: 46270 | D55: Aucun de ces taux n'est recopié dans une formule : toutes pointent ici. Les mentions « vérifié le » du classeur lisent cette date.
B57: Le seuil de 35 % n'est pas une loi de plafonnement absolu : c'est une norme du HCSF assortie d'une marge de flexibilité que chaque banque utilise à sa main.
B58: Un dossier à 37 % avec un reste à vivre confortable passe parfois ; un dossier à 33 % avec quatre enfants et un crédit auto peut être refusé. D'où les deux règles côte à côte.
B61: CorpusImmo, millésime 2026. Modèle d'aide à la décision : ne constitue ni un conseil en investissement, ni un conseil fiscal, ni une expertise au sens de la charte de l'expertise en évaluation immobilière. Vérifiez les paramètres avant tout engagement.

Sheet Méthode
B1: CorpusImmo · corpus.immo · Estimer, comparer, décider. Sur les ventes réelles.
B2: Méthode et limites
B3: Comment la banque raisonne, où le modèle s'arrête, et sur quelles sources reposent ses chiffres.
B5: CONVENTIONS RETENUES, ET CE QU'ELLES COÛTENT
B6: Revenus retenus | C6: Salaires nets, primes récurrentes lissées, et loyers PONDÉRÉS. La pondération (70 % par défaut, repère 2026) couvre la vacance, les impayés et les charges du bailleur. Compter les loyers à 100 % au lieu de 70 % majore la part locative des revenus de 43 % ; l'effet sur la capacité dépend du poids des loyers (sur l'exemple 2026 : +210 € de revenus retenus, soit +4 % de capacité). Les primes et variables sont pondérées à part (100 % par défaut, repère 2026). Pour un investissement locatif, le loyer attendu du bien financé est ajouté aux loyers, avec la même pondération : c'est la méthode classique des banques ; la méthode différentielle (loyers nets de charges compensés avec la mensualité) n'est pas modélisée.
B7: Mensualité maximale | C7: Revenus retenus × taux d'effort − charges existantes. Le taux d'effort de 35 % (HCSF, norme 2026) s'entend assurance emprunteur comprise, ce que beaucoup de simulateurs oublient. Les charges retenues comprennent les crédits en cours, la pension versée et, pour un investissement locatif, le loyer actuel qui continue : option prudente, certaines banques renvoient loyer et pension au seul reste à vivre.
B8: Reste à vivre | C8: Deuxième filtre, indépendant du premier. Le modèle retient la plus contraignante des deux règles, parce que c'est ce que fait un analyste crédit. Le reste à vivre affiché est calculé après la mensualité retenue (et non après la mensualité théorique) : il ne peut donc pas passer sous le minimum tant qu'une mensualité est possible. Il est calculé sur les revenus retenus (loyers pondérés) et avant impôt sur le revenu : convention prudente ; une banque qui raisonne après impôt trouvera un reste à vivre plus faible, une banque qui compte les loyers à 100 % un reste à vivre plus élevé.
B9: Deux taux d'endettement | C9: Le taux d'effort HCSF strict rapporte les seules charges d'emprunt (crédits en cours plus la mensualité, assurance comprise) aux revenus retenus : c'est le ratio que la banque déclare au régulateur. Le taux de charges tout compris ajoute la pension versée et le loyer conservé : c'est celui que le modèle plafonne à 35 %. Les deux sont affichés parce qu'un courtier présente les deux.
B10: Capital empruntable | C10: Valeur actuelle (PV) de la mensualité sur la durée, corrigée de l'assurance. L'assurance étant assise sur le capital initial, elle mord sur la mensualité disponible : la corriger après coup surestime le capital d'environ 5 % à 0,30 % d'assurance sur 25 ans (exemple 2026), moins sur une durée courte. Taux mensuel proportionnel (taux annuel divisé par 12), annuité constante. L'assurance est calculée sur le capital initial avec un taux global pour tous les emprunteurs : deux emprunteurs assurés chacun à 100 % doublent ce taux.
B11: Frais de notaire 2026 | C11: Barèmes 2026, tous en Paramètres. Ancien : droits de mutation à 6,32 % du prix (droit départemental porté à 5 % du 1er avril 2025 au 31 mars 2028 dans la grande majorité des départements) ou 5,81 % (départements restés à 4,50 %, et primo-accédants achetant leur résidence principale, exonérés de la hausse), plus contribution de sécurité immobilière 0,10 %, émoluments du notaire TTC selon le barème par tranches (linéarisé au-delà de 60 000 €) et débours forfaitaires. Neuf ou VEFA : taxe de publicité foncière 0,715 % à la place des droits de mutation, le reste inchangé. Hors honoraires d'agence et hors mobilier, qui échappent aux droits.
B12: Prix d'achat maximal | C12: Budget total (capital plus apport), moins les frais de garantie (en % du capital), les frais de dossier et la part fixe des frais de notaire, divisé par (1 + part proportionnelle des frais de notaire). On raisonne à l'envers du budget, car les frais se calculent sur le prix, pas sur le budget. Le contrôle « Apport couvre les frais » signale un dossier où le prêt financerait des frais, ce que les banques refusent en pratique.
B13: Durée | C13: 25 ans au plus (HCSF, norme 2026) ; 27 ans quand un différé d'amortissement de 2 ans au plus est justifié par une VEFA, une construction ou des travaux représentant au moins 10 % du coût total (décision HCSF du 29 juin 2023, seuil auparavant fixé à 25 %). Le classeur accepte une durée jusqu'à la borne de Paramètres (30 ans) mais l'affiche en rouge au-delà du maximum applicable.
B14: Dérogations HCSF | C14: Les banques peuvent déroger au taux d'effort et à la durée pour 20 % de leur production trimestrielle (HCSF, norme 2026), dont au moins 70 % pour l'achat d'une résidence principale et au moins 30 % pour les primo-accédants ; cette marge était utilisée à 17,5 % au premier trimestre 2026. Le classeur signale les dossiers hors norme (contrôles rouges) sans les interdire : leur acceptation relève de chaque banque.
B15: Bilan patrimonial | C15: Le patrimoine net est ce qui reste si tout était vendu et toutes les dettes soldées. Une banque le regarde pour deux raisons : il mesure votre capacité à encaisser un coup dur, et il révèle une éventuelle capacité d'apport complémentaire. Un patrimoine net solide compense parfois un taux d'endettement à la limite. Les liquidités mobilisables retiennent les comptes, livrets, assurance-vie, PEA et comptes-titres, et excluent l'épargne retraite (bloquée, sauf déblocage pour la résidence principale), les parts de sociétés et les autres actifs. Le pro forma se place au jour de la signature, au prix maximal : le patrimoine net baisse exactement des frais de l'opération ; l'endettement immobilier (LTV) et le ratio dettes sur actif sont recalculés avec le nouveau prêt.
B16: Taux d'usure | C16: Le taux d'usure plafonne le TAEG, pas le taux nominal, et la Banque de France le publie par tranche de durée (moins de 10 ans, 10 à moins de 20 ans, 20 ans et plus) le dernier jour ouvré de chaque trimestre. Ce classeur ne calcule pas de TAEG : il compare le taux du prêt augmenté du taux d'assurance au plafond de la tranche. Cette somme est inférieure au TAEG, qui intègre en plus les frais de dossier et de garantie : le contrôle est donc conservateur dans un seul sens. Rouge veut dire que l'offre est certainement illégale ; vert veut dire qu'il reste de la marge, à condition que les frais tiennent dedans. Le TAEG lui-même se calcule dans la matrice Tableau d'amortissement et comparateur de prêts, qui porte les mêmes trois tranches et le même seuil de durée.
B17: Taux et dates | C17: Tous les taux sont des fractions affichées en pourcentage : tapez 3,3 dans une cellule de taux, elle affiche 3,30 % et contient 0,033. Aucune formule ne divise par 100. Les durées sont en années entières.
B19: CE QUE CE MODÈLE NE FAIT PAS
B20: • Il ne remplace pas l'accord d'une banque : chaque établissement a sa grille et ses dérogations.
B21: • Il ne tient pas compte de la stabilité professionnelle, qui pèse autant que le taux d'effort.
B22: • Il ne modélise pas le prêt à taux zéro, ni les prêts employeur ou aidés, ni un prêt relais (dont les intérêts sont exclus du taux d'effort par la décision HCSF du 4 décembre 2023).
B23: • Il ne calcule pas le TAEG, le seul taux que le taux d'usure plafonne légalement. Le contrôle d'usure de cet onglet compare le taux du prêt augmenté de l'assurance, qui reste en dessous du TAEG puisqu'il ignore les frais : il détecte une offre certainement illégale, il ne certifie pas une offre conforme. Le TAEG se calcule dans la matrice Tableau d'amortissement et comparateur de prêts.
B24: • Il ne calcule pas les frais de notaire au barème exact en dessous de 60 000 € (il les surestime légèrement), ni les honoraires d'agence, ni la part de mobilier hors droits.
B25: • Il ne modélise pas la méthode différentielle des banques pour l'investissement locatif, ni la fiscalité des loyers (voir la matrice Calculateur de rentabilité locative).
B26: • Il ne fait pas de sensibilité durée × taux sur le capital empruntable (voir la matrice Tableau d'amortissement et comparateur de prêts).
B27: • Il ne remplace ni un courtier, ni un conseil en gestion de patrimoine.
B29: SOURCES
B30: Taux d'effort maximal HCSF (assurance comprise) | C30: ="HCSF, décision D-HCSF-2021-7 du 29/09/2021, confirmée par la décision D-HCSF-2023-2 du 29/06/2023. economie.gouv.fr/hcsf, vérifié le "&TEXT(DAY(Paramètres!$C$55),"00")&"/"&TEXT(MONTH(Paramètres!$C$55),"00")&"/"&YEAR(Paramètres!$C$55)&"." -> HCSF, décision D-HCSF-2021-7 du 29/09/2021, confirmée par la décision D-HCSF-2023-2 du 29/06/2023. economie.gouv.fr/hcsf, vérifié le 05/09/2026.
B31: Durée maximale HCSF, cas général | C31: ="HCSF, décision D-HCSF-2021-7 du 29/09/2021. Vérifié le "&TEXT(DAY(Paramètres!$C$55),"00")&"/"&TEXT(MONTH(Paramètres!$C$55),"00")&"/"&YEAR(Paramètres!$C$55)&"." -> HCSF, décision D-HCSF-2021-7 du 29/09/2021. Vérifié le 05/09/2026.
B32: Durée maximale HCSF avec différé (VEFA, construction, travaux) | C32: ="HCSF, décisions du 29/09/2021 (différé de 2 ans au plus) et du 29/06/2023 (seuil de travaux abaissé de 25 % à 10 % du coût total). Vérifié le "&TEXT(DAY(Paramètres!$C$55),"00")&"/"&TEXT(MONTH(Paramètres!$C$55),"00")&"/"&YEAR(Paramètres!$C$55)&"." -> HCSF, décisions du 29/09/2021 (différé de 2 ans au plus) et du 29/06/2023 (seuil de travaux abaissé de 25 % à 10 % du coût total). Vérifié le 05/09/2026.
B33: Seuil de travaux ouvrant le différé (part du coût total) | C33: ="HCSF, décision D-HCSF-2023-2 du 29/06/2023 (auparavant 25 %). Vérifié le "&TEXT(DAY(Paramètres!$C$55),"00")&"/"&TEXT(MONTH(Paramètres!$C$55),"00")&"/"&YEAR(Paramètres!$C$55)&"." -> HCSF, décision D-HCSF-2023-2 du 29/06/2023 (auparavant 25 %). Vérifié le 05/09/2026.
B34: Marge de flexibilité HCSF (part de la production trimestrielle) | C34: ="HCSF, décision D-HCSF-2023-2 du 29/06/2023 : 20 % de la production, dont au moins 70 % pour la résidence principale et au moins 30 % pour les primo-accédants. Utilisée à 17,5 % au 1er trimestre 2026 (Meilleurtaux, 11/06/2026). Vérifié le "&TEXT(DAY(Paramètres!$C$55),"00")&"/"&TEXT(MONTH(Paramètres!$C$55),"00")&"/"&YEAR(Paramètres!$C$55)&"." -> HCSF, décision D-HCSF-2023-2 du 29/06/2023 : 20 % de la production, dont au moins 70 % pour la résidence principale et au moins 30 % pour les primo-accédants. Utilisée à 17,5 % au 1er trimestre 2026 (Meilleurtaux, 11/06/2026). Vérifié le 05/09/2026.
B35: Droits de mutation, ancien, droit départemental majoré à 5 % | C35: ="LF 2025 (loi n° 2025-127 du 14/02/2025) art. 116 : droit départemental porté de 4,50 % à 5 % (CGI art. 1594 D) du 01/04/2025 au 31/03/2028 ; taxe communale 1,20 % (art. 1584) ; frais d'assiette 2,37 % du droit départemental (art. 1647 V). taximmo.fr,"&" vérifié le "&TEXT(DAY(Paramètres!$C$55),"00")&"/"&TEXT(MONTH(Paramètres!$C$55),"00")&"/"&YEAR(Paramètres!$C$55)&"." -> LF 2025 (loi n° 2025-127 du 14/02/2025) art. 116 : droit départemental porté de 4,50 % à 5 % (CGI art. 1594 D) du 01/04/2025 au 31/03/2028 ; taxe communale 1,20 % (art. 1584) ; frais d'assiette 2,37 % du droit départemental (art. 1647 V). taximmo.fr, vérifié le 05/09/2026.
B36: Droits de mutation, ancien, droit départemental à 4,50 % | C36: ="CGI art. 1594 D (4,50 %), 1584 (1,20 %), 1647 V (2,37 %). Maintenu dans les départements qui n'ont pas voté la hausse et pour les primo-accédants achetant leur résidence principale (LF 2025 art. 116, II). taximmo.fr, vérifié le "&TEXT(DAY(Paramètres!$C$55),"00")&"/"&TEXT(MONTH(Paramètres!$C$55),"00")&"/"&YEAR(Paramètres!$C$55)&"." -> CGI art. 1594 D (4,50 %), 1584 (1,20 %), 1647 V (2,37 %). Maintenu dans les départements qui n'ont pas voté la hausse et pour les primo-accédants achetant leur résidence principale (LF 2025 art. 116, II). taximmo.fr, vérifié le 05/09/2026.
B37: Taxe de publicité foncière, neuf ou VEFA | C37: ="CGI art. 1594 F quinquies A (taux réduit 0,70 %) et 1647 V (frais d'assiette 2,14 %). Vérifié le "&TEXT(DAY(Paramètres!$C$55),"00")&"/"&TEXT(MONTH(Paramètres!$C$55),"00")&"/"&YEAR(Paramètres!$C$55)&"." -> CGI art. 1594 F quinquies A (taux réduit 0,70 %) et 1647 V (frais d'assiette 2,14 %). Vérifié le 05/09/2026.
B38: Contribution de sécurité immobilière | C38: ="CGI art. 879 : 0,10 % du prix, ancien comme neuf. Vérifié le "&TEXT(DAY(Paramètres!$C$55),"00")&"/"&TEXT(MONTH(Paramètres!$C$55),"00")&"/"&YEAR(Paramètres!$C$55)&"." -> CGI art. 879 : 0,10 % du prix, ancien comme neuf. Vérifié le 05/09/2026.
B39: Émoluments du notaire, taux marginal au-delà de 60 000 € (HT) | C39: ="Code de commerce art. A444-91, arrêté du 25/02/2026 (en vigueur du 01/03/2026 au 29/02/2028) : 3,870 % jusqu'à 6 500 €, 1,596 % de 6 500 à 17 000 €, 1,064 % de 17 000 à 60 000 €, 0,799 % au-delà. pretto.fr, vérifié le "&TEXT(DAY(Paramètres!$C$55),"00")&"/"&TEXT(MONTH(Paramètres!$C$55),"00")&"/"&YEAR(Paramètres!$C$55)&"." -> Code de commerce art. A444-91, arrêté du 25/02/2026 (en vigueur du 01/03/2026 au 29/02/2028) : 3,870 % jusqu'à 6 500 €, 1,596 % de 6 500 à 17 000 €, 1,064 % de 17 000 à 60 000 €, 0,799 % au-delà. pretto.fr, vérifié le 05/09/2026.
B40: Émoluments du notaire, part fixe des tranches inférieures (HT) | C40: Calcul depuis le barème A444-91 : 6 500 × (3,870 − 0,799) % + 10 500 × (1,596 − 0,799) % + 43 000 × (1,064 − 0,799) % = 397,25 €.
B41: TVA sur les émoluments | C41: ="CGI art. 278 : taux normal 20 %. Vérifié le "&TEXT(DAY(Paramètres!$C$55),"00")&"/"&TEXT(MONTH(Paramètres!$C$55),"00")&"/"&YEAR(Paramètres!$C$55)&"." -> CGI art. 278 : taux normal 20 %. Vérifié le 05/09/2026.
B42: Taux d'usure, prêts à taux fixe de moins de 10 ans | C42: ="Banque de France, taux d'usure applicables au 3e trimestre 2026, avis publié le 29/06/2026 et applicable depuis le 01/07/2026. banque-france.fr, rubrique Taux d'usure. Vérifié le "&TEXT(DAY(Paramètres!$C$55),"00")&"/"&TEXT(MONTH(Paramètres!$C$55),"00")&"/"&YEAR(Paramètres!$C$55)&"." -> Banque de France, taux d'usure applicables au 3e trimestre 2026, avis publié le 29/06/2026 et applicable depuis le 01/07/2026. banque-france.fr, rubrique Taux d'usure. Vérifié le 05/09/2026.
B43: Taux d'usure, prêts à taux fixe de 10 ans à moins de 20 ans | C43: ="Banque de France, taux d'usure applicables au 3e trimestre 2026, avis publié le 29/06/2026 et applicable depuis le 01/07/2026. banque-france.fr, rubrique Taux d'usure. Vérifié le "&TEXT(DAY(Paramètres!$C$55),"00")&"/"&TEXT(MONTH(Paramètres!$C$55),"00")&"/"&YEAR(Paramètres!$C$55)&"." -> Banque de France, taux d'usure applicables au 3e trimestre 2026, avis publié le 29/06/2026 et applicable depuis le 01/07/2026. banque-france.fr, rubrique Taux d'usure. Vérifié le 05/09/2026.
B44: Taux d'usure, prêts à taux fixe de 20 ans et plus | C44: ="Banque de France, taux d'usure applicables au 3e trimestre 2026, avis publié le 29/06/2026 et applicable depuis le 01/07/2026. banque-france.fr, rubrique Taux d'usure. Vérifié le "&TEXT(DAY(Paramètres!$C$55),"00")&"/"&TEXT(MONTH(Paramètres!$C$55),"00")&"/"&YEAR(Paramètres!$C$55)&"." -> Banque de France, taux d'usure applicables au 3e trimestre 2026, avis publié le 29/06/2026 et applicable depuis le 01/07/2026. banque-france.fr, rubrique Taux d'usure. Vérifié le 05/09/2026.
B45: Seuil de durée entre les deux premières tranches d'usure | C45: ="Banque de France, taux d'usure applicables au 3e trimestre 2026, avis publié le 29/06/2026 et applicable depuis le 01/07/2026. banque-france.fr, rubrique Taux d'usure. Vérifié le "&TEXT(DAY(Paramètres!$C$55),"00")&"/"&TEXT(MONTH(Paramètres!$C$55),"00")&"/"&YEAR(Paramètres!$C$55)&"." -> Banque de France, taux d'usure applicables au 3e trimestre 2026, avis publié le 29/06/2026 et applicable depuis le 01/07/2026. banque-france.fr, rubrique Taux d'usure. Vérifié le 05/09/2026.
B46: Seuil de durée entre les deux dernières tranches d'usure | C46: ="Banque de France, taux d'usure applicables au 3e trimestre 2026, avis publié le 29/06/2026 et applicable depuis le 01/07/2026. banque-france.fr, rubrique Taux d'usure. Vérifié le "&TEXT(DAY(Paramètres!$C$55),"00")&"/"&TEXT(MONTH(Paramètres!$C$55),"00")&"/"&YEAR(Paramètres!$C$55)&"." -> Banque de France, taux d'usure applicables au 3e trimestre 2026, avis publié le 29/06/2026 et applicable depuis le 01/07/2026. banque-france.fr, rubrique Taux d'usure. Vérifié le 05/09/2026.
B47: Pondération des revenus locatifs | C47: ="Usage bancaire : 70 % chez la plupart des banques, 80 à 90 % chez quelques-unes sur dossiers de qualité. empruntis.com, quelcredit.com, vérifié le "&TEXT(DAY(Paramètres!$C$55),"00")&"/"&TEXT(MONTH(Paramètres!$C$55),"00")&"/"&YEAR(Paramètres!$C$55)&"." -> Usage bancaire : 70 % chez la plupart des banques, 80 à 90 % chez quelques-unes sur dossiers de qualité. empruntis.com, quelcredit.com, vérifié le 05/09/2026.
B48: Pondération des primes et variables | C48: ="Usage bancaire : 100 % si récurrentes sur 2 à 3 ans, 75 % dans certains établissements. prettymo.fr, vérifié le "&TEXT(DAY(Paramètres!$C$55),"00")&"/"&TEXT(MONTH(Paramètres!$C$55),"00")&"/"&YEAR(Paramètres!$C$55)&"." -> Usage bancaire : 100 % si récurrentes sur 2 à 3 ans, 75 % dans certains établissements. prettymo.fr, vérifié le 05/09/2026.
B49: Reste à vivre minimal par adulte | C49: ="Usage bancaire : 700 à 1 000 € par adulte, davantage en Île-de-France ; aucun minimum légal. reassurez-moi.fr (2026), selectra.info, vérifié le "&TEXT(DAY(Paramètres!$C$55),"00")&"/"&TEXT(MONTH(Paramètres!$C$55),"00")&"/"&YEAR(Paramètres!$C$55)&"." -> Usage bancaire : 700 à 1 000 € par adulte, davantage en Île-de-France ; aucun minimum légal. reassurez-moi.fr (2026), selectra.info, vérifié le 05/09/2026.
B50: Reste à vivre minimal par enfant à charge | C50: ="Usage bancaire : 300 à 500 € par enfant. Mêmes sources, vérifié le "&TEXT(DAY(Paramètres!$C$55),"00")&"/"&TEXT(MONTH(Paramètres!$C$55),"00")&"/"&YEAR(Paramètres!$C$55)&"." -> Usage bancaire : 300 à 500 € par enfant. Mêmes sources, vérifié le 05/09/2026.
B51: Débours et frais de formalités du notaire (forfait) | C51: ="frais-de-notaire.fr (CSI et débours 1 100 € pour 300 000 €, dont CSI 300 €) et pretto.fr (environ 0,4 % du prix) : 800 à 1 200 € pour un logement. Vérifié le "&TEXT(DAY(Paramètres!$C$55),"00")&"/"&TEXT(MONTH(Paramètres!$C$55),"00")&"/"&YEAR(Paramètres!$C$55)&"." -> frais-de-notaire.fr (CSI et débours 1 100 € pour 300 000 €, dont CSI 300 €) et pretto.fr (environ 0,4 % du prix) : 800 à 1 200 € pour un logement. Vérifié le 05/09/2026.
B52: Frais de garantie du prêt (en % du capital emprunté) | C52: ="Convention prudente du classeur : Crédit Logement ne publie pas son barème et les relevés de place vont de 0,85 % + 200 € (optimhome.com, 2026) à 1,5 à 1,75 % du capital (perlib.fr, 2026). Vérifié le "&TEXT(DAY(Paramètres!$C$55),"00")&"/"&TEXT(MONTH(Paramètres!$C$55),"00")&"/"&YEAR(Paramètres!$C$55)&"." -> Convention prudente du classeur : Crédit Logement ne publie pas son barème et les relevés de place vont de 0,85 % + 200 € (optimhome.com, 2026) à 1,5 à 1,75 % du capital (perlib.fr, 2026). Vérifié le 05/09/2026.
B53: Frais de dossier de la banque (forfait) | C53: ="Meilleurtaux, relevé de 119 banques au 01/03/2026 : moyenne 1 899,68 € pour 200 000 €, 92 établissements entre 0,50 % et 1,40 % du capital, de 0 € à 2 500 € selon les banques. Vérifié le "&TEXT(DAY(Paramètres!$C$55),"00")&"/"&TEXT(MONTH(Paramètres!$C$55),"00")&"/"&YEAR(Paramètres!$C$55)&"." -> Meilleurtaux, relevé de 119 banques au 01/03/2026 : moyenne 1 899,68 € pour 200 000 €, 92 établissements entre 0,50 % et 1,40 % du capital, de 0 € à 2 500 € selon les banques. Vérifié le 05/09/2026.
B54: Taux moyen constaté sur 25 ans (repère pour la saisie du taux) | C54: ="Observatoire Crédit Logement / CSA, analyse du marché du mois d'août 2026 (publiée en septembre 2026) : 3,35 % sur 25 ans, 3,14 % sur 15 ans, en hausse de 15 centièmes de point depuis décembre 2025. lobservatoire.creditlogement.fr. Vérifié le "&TEXT(DAY(Paramètres!$C$55),"00")&"/"&TEXT(MONTH(Paramètres!$C$55),"00")&"/"&YEAR(Paramètres!$C$55)&"." -> Observatoire Crédit Logement / CSA, analyse du marché du mois d'août 2026 (publiée en septembre 2026) : 3,35 % sur 25 ans, 3,14 % sur 15 ans, en hausse de 15 centièmes de point depuis décembre 2025. lobservatoire.creditlogement.fr. Vérifié le 05/09/2026.
B55: Taux d'assurance emprunteur, contrat groupe (repère) | C55: ="Baromètres 2026 (pretclair.fr, covelia.fr) : environ 0,36 % du capital initial, 35 ans non fumeur. Vérifié le "&TEXT(DAY(Paramètres!$C$55),"00")&"/"&TEXT(MONTH(Paramètres!$C$55),"00")&"/"&YEAR(Paramètres!$C$55)&"." -> Baromètres 2026 (pretclair.fr, covelia.fr) : environ 0,36 % du capital initial, 35 ans non fumeur. Vérifié le 05/09/2026.
B56: Taux d'assurance emprunteur, délégation (repère) | C56: ="Baromètres 2026 (pretclair.fr, covelia.fr) : environ 0,17 % du capital initial, 35 ans non fumeur. Vérifié le "&TEXT(DAY(Paramètres!$C$55),"00")&"/"&TEXT(MONTH(Paramètres!$C$55),"00")&"/"&YEAR(Paramètres!$C$55)&"." -> Baromètres 2026 (pretclair.fr, covelia.fr) : environ 0,17 % du capital initial, 35 ans non fumeur. Vérifié le 05/09/2026.
B57: Frais de notaire usuels dans l'ancien (ordre de grandeur) | C57: ="frais-de-notaire.fr, achat ancien 2026 : 7,8 % pour 300 000 €, de 7 à 8,5 % selon le prix. Vérifié le "&TEXT(DAY(Paramètres!$C$55),"00")&"/"&TEXT(MONTH(Paramètres!$C$55),"00")&"/"&YEAR(Paramètres!$C$55)&"." -> frais-de-notaire.fr, achat ancien 2026 : 7,8 % pour 300 000 €, de 7 à 8,5 % selon le prix. Vérifié le 05/09/2026.
B58: Frais de notaire usuels dans le neuf (ordre de grandeur) | C58: ="meilleurescpi.com, frais de notaire 2026 : 2 à 3 % dans le neuf. Vérifié le "&TEXT(DAY(Paramètres!$C$55),"00")&"/"&TEXT(MONTH(Paramètres!$C$55),"00")&"/"&YEAR(Paramètres!$C$55)&"." -> meilleurescpi.com, frais de notaire 2026 : 2 à 3 % dans le neuf. Vérifié le 05/09/2026.
B59: Prêts relais et taux d'effort | C59: ="HCSF, décision du 04/12/2023 : les intérêts d'un prêt relais sont exclus du calcul du taux d'effort. economie.gouv.fr/hcsf, vérifié le "&TEXT(DAY(Paramètres!$C$55),"00")&"/"&TEXT(MONTH(Paramètres!$C$55),"00")&"/"&YEAR(Paramètres!$C$55)&"." -> HCSF, décision du 04/12/2023 : les intérêts d'un prêt relais sont exclus du calcul du taux d'effort. economie.gouv.fr/hcsf, vérifié le 05/09/2026.
B60: Frais de notaire, ordres de grandeur | C60: ="frais-de-notaire.fr (achat ancien 2026 : 7,8 % pour 300 000 €), plan-immobilier.fr, koliving.fr, vérifié le "&TEXT(DAY(Paramètres!$C$55),"00")&"/"&TEXT(MONTH(Paramètres!$C$55),"00")&"/"&YEAR(Paramètres!$C$55)&"." -> frais-de-notaire.fr (achat ancien 2026 : 7,8 % pour 300 000 €), plan-immobilier.fr, koliving.fr, vérifié le 05/09/2026.
B62: CorpusImmo, millésime 2026. Modèle d'aide à la décision : ne constitue ni un conseil en investissement, ni un conseil fiscal, ni une expertise au sens de la charte de l'expertise en évaluation immobilière. Vérifiez les paramètres avant tout engagement.
