Workbook

Sheet Mode d'emploi
B1: CorpusImmo · corpus.immo · Estimer, comparer, décider. Sur les ventes réelles.
B2: Mode d'emploi
B3: À quoi sert ce classeur, dans quel ordre le remplir, et comment lire ce qu'il répond.
B6: À QUOI SERT CE CLASSEUR
B7: Vous avez un immeuble et ses baux. Ce classeur répond à trois questions : combien il rapporte aujourd'hui, combien de temps ce revenu est sécurisé, et quand il se remet en jeu.
B8: Un rent roll, c'est l'état locatif d'un immeuble : une ligne par lot, avec son locataire, sa surface, son loyer et ses dates. À partir de là, le classeur calcule le WAULT et le WALB, les deux durées résiduelles que publient les foncières, le taux d'occupation physique et le taux d'occupation financier, la réversion, et l'échéancier des sorties année par année.
B9: Un seul onglet à remplir : Rent roll. Vous saisissez les cellules bleues, tout le reste se calcule. La Synthèse et l'Échéancier ne se saisissent pas, ils se lisent.
B10: Vous êtes | C10: Ce que le classeur vous donne
B11: Analyste investissement, acquéreur | C11: Le WALB (Synthèse!C39), la réversion, en euros (Synthèse!C30) et en part du loyer en place (Synthèse!C31), et l'année de pointe de l'échéancier : de quoi savoir si vous achetez un revenu ou un risque de relocation.
B12: Asset manager | C12: Les lots à traiter en priorité : ceux dont la sortie est proche (colonne Q du rent roll) et ceux dont le loyer est au-dessus du marché (colonne L).
B13: Property manager, gestionnaire | C13: Un état locatif tenu, avec un contrôle par ligne qui refuse une saisie incomplète au lieu de la compter à zéro (Rent roll!V11:V50).
B14: Broker, conseil en investissement | C14: Les chiffres du teaser : le loyer facial en place (Synthèse!C24), le taux d'occupation financier, le WAULT et le WALB au loyer facial, l'échéancier. Ceux que l'acquéreur vérifiera. Gardez le loyer économique (Synthèse!C25) pour la discussion de prix : c'est sur lui que se calcule un rendement.
B15: Banquier | C15: Le loyer sécurisé au-delà de la durée du prêt : l'échéancier (Échéancier!B10:I28) dit combien de loyer se remet en jeu chaque année, et sa dernière ligne recoupe le total avec le rent roll.
B16: Expert, évaluateur | C16: Le loyer facial et le loyer économique côte à côte (Synthèse!C24 et Synthèse!C25), et l'écart au marché lot par lot.
B18: LE PRINCIPE, EN UNE LIGNE
B19: Le loyer de chaque bail, pondéré par le temps qui reste avant que le locataire puisse partir, divisé par le loyer total : c'est le WALB, la durée pendant laquelle le revenu est sécurisé. Le reste du classeur dit ce que vaut ce revenu aujourd'hui, ce qu'il vaudrait au marché, et quand il se remet en jeu
B21: LES ONGLETS, DANS L'ORDRE OÙ ON LES REMPLIT
B22: Onglet | C22: Ce que vous y faites | D22: Ce que vous y lisez
B23: Mode d'emploi | C23: Rien à saisir. Vous lisez ce guide. | D23: La marche à suivre et l'exemple guidé.
B24: Rent roll | C24: Vous saisissez la date d'analyse en Rent roll!C7, puis un lot par ligne : nature, locataire, statut, surface, loyer, valeur locative, dates, périodicité de sortie, franchise. | D24: Par ligne : le loyer annuel, la valeur locative annuelle, la réversion, la prochaine sortie calculée, le loyer économique, les deux durées résiduelles, un contrôle et son motif.
B25: Synthèse | C25: Rien à saisir. | D25: Cinq blocs : les contrôles, les surfaces et l'occupation, les loyers et la réversion, les durées résiduelles, la concentration.
B26: Échéancier | C26: Rien à saisir. | D26: Le loyer qui se remet en jeu par année, au terme et à la sortie, avec les baux échus, l'au-delà de l'horizon, le total et son recoupement.
B27: Paramètres | C27: Rien, sauf à la mise à jour des indices et des seuils. | D27: Chaque valeur avec sa source datée et sa fréquence de mise à jour.
B28: Méthode | C28: Rien à saisir. | D28: Les conventions de calcul, ce que le modèle ne fait pas, les sources.
B30: LE CODE COULEUR, ET COMMENT DÉVERROUILLER UNE CELLULE
B31: Cellule | C31: Ce que c'est | D31: Ce que vous faites
B32: Fond bleu ciel, texte bleu nuit | C32: Saisie utilisateur | D32: Vous la remplissez ou l'effacez (touche Suppr), même feuille protégée. Jamais de formule dedans.
B33: Fond blanc | C33: Calcul | D33: Vous la lisez. Elle est verrouillée.
B34: Fond presque blanc, texte bleu nuit en gras | C34: Résultat de bloc, chiffre clé | D34: Vous la lisez. C'est un chiffre à retenir.
B35: Bandeau bleu nuit | C35: Titre de section, en-tête de tableau | D35: Repère de navigation.
B36: Texte gris | C36: Commentaire d'aide, ordre de grandeur | D36: Une phrase par ligne pour savoir quoi saisir.
B37: Vert OK, rouge À CORRIGER | C37: Contrôle de cohérence | D37: Rouge : lisez la colonne W de la ligne concernée, ou la Synthèse, qui nomme la première ligne en cause.
B38: Les onglets sont protégés sans mot de passe pour éviter d'écraser une formule par erreur. Les cellules bleues restent modifiables et effaçables sans rien déverrouiller. N'ôtez la protection que pour toucher une cellule blanche, par l'onglet Révision, « Ôter la protection de la feuille ». Aucun mot de passe n'est demandé.
B40: LA MARCHE À SUIVRE, ÉTAPE PAR ÉTAPE
B41: Étape | C41: Où (onglet et plage) | D41: Ce que vous faites | E41: Pourquoi
B42: 0. L'exemple livré | C42: Rent roll!B11:G50, Rent roll!I11:I50, Rent roll!M11:P50, Rent roll!R11:R50, Rent roll!C7 | D42: Le classeur est livré rempli d'un exemple : un immeuble de 1 755 m² avec sept lots. Gardez-le pour vous repérer, ou effacez les sept lignes de l'exemple avant de saisir votre immeuble. Les colonnes bleues d'une ligne ne sont pas contiguës : sélectionnez Rent roll!B11:G17, Rent roll!I11:I17, Rent roll!M11:P17 et Rent roll!R11:R17, en maintenant la touche Ctrl pour ajouter chaque bloc à la sélection, puis appuyez sur Suppr. Les colonnes H, J, K, L et Q sont des formules verrouillées : si vous les incluez dans la sélection, Excel refuse l'effacement entier et affiche un message de protection. Elles se videront d'elles-mêmes. Videz toujours une ligne de bail en entier : une ligne à demi effacée reste comptée comme renseignée, passe au rouge et bloque le contrôle d'ensemble. La grille accepte 40 baux, lignes 11 à 50 : pour ajouter un lot, servez-vous de la première ligne bleue libre, elles sont déjà prêtes et il n'y a aucune ligne à insérer. Vérifiez surtout les saisies facultatives, qui n'ont pas de raison d'être dans votre cas : la périodicité de sortie (Rent roll!O11:O50, à ne remplir que pour un bail ayant renoncé à ses triennales), la sortie forcée (Rent roll!P11:P50) et la franchise (Rent roll!R11:R50). Pendant que vous effacez, les contrôles passent au rouge et les totaux tombent : c'est normal, tout revient dès que la saisie est complète. | E42: Une saisie résiduelle de l'exemple est l'erreur la plus probable d'un premier usage, et les deux colonnes facultatives ne se trahissent pas de la même façon. Une périodicité de six ans héritée allonge le WALB et gonfle le loyer économique, parce que la franchise s'étale alors sur 72 mois au lieu de 36. Une franchise héritée, elle, ne touche pas au WALB, qui ne dépend que des dates : elle rabote le loyer économique. Trois mois hérités sur un lot à 119 700 € lui retirent 9 975 € par an. Dans les deux cas, aucun contrôle ne s'allume.
B43: 1. La date d'analyse | C43: Rent roll!C7 | D43: Tapez la date à laquelle vous photographiez l'immeuble, en vraie date au format jj/mm/aaaa. Le plus souvent la date d'un arrêté comptable, d'une offre ou d'un rapport d'expertise. | E43: Toutes les durées résiduelles, la prochaine sortie de chaque bail et la première année de l'échéancier en dépendent. C'est la seule cellule qui commande tout le classeur.
B44: 2. Les lots et les locataires | C44: Rent roll!B11:E50 | D44: Une ligne par lot : un libellé (obligatoire, il nomme la ligne dans les contrôles), la nature dans la liste, le nom du locataire, et le statut Loué ou Vacant. Laissez le locataire vide sur un lot vacant. | E44: Le statut remplace le test « la colonne locataire est-elle vide ». Écrire « Vacant » dans la colonne du locataire ne suffit pas : c'est le statut qui décide. Avec le statut Vacant, la ligne passe au rouge ; avec le statut Loué et un loyer saisi, le lot est compté comme loué et rien ne le signale.
B45: 3. Surfaces, loyers et valeur locative | C45: Rent roll!F11:G50 et Rent roll!I11:I50 | D45: La surface locative, le loyer facial hors taxes hors charges au mètre carré et par an, et la valeur locative de marché au mètre carré. Cette colonne s'intitule VLM sur la feuille, pour valeur locative de marché. Renseignez-la sur tous les lots, vacants compris. | E45: Le loyer annuel (Rent roll!H11:H50) et la valeur locative annuelle (Rent roll!J11:J50) se calculent seuls. Sans valeur locative sur tous les lots, le contrôle Synthèse!C10 passe au rouge, et le taux d'occupation financier comme la réversion restent vides : sur un lot vacant, une valeur locative manquante minorerait la vacance, donc flatterait l'immeuble ; sur un lot loué, elle vaudrait zéro et retournerait la réversion. Tant que ce contrôle est rouge, ne lisez ni l'un ni l'autre, et cherchez la ligne que nomme Synthèse!C9.
B46: 4. Les dates du bail | C46: Rent roll!M11:P50 | D46: La prise d'effet et l'échéance, en vraies dates. Laissez la périodicité de sortie vide dans le cas général : le classeur applique la périodicité légale de Paramètres!C8. Mettez 6 ou 9 pour un bail de bureaux, un bail long, un local monovalent ou de stockage ayant renoncé à ses premières triennales. Ne remplissez la sortie forcée que si vous connaissez déjà la date de sortie, par exemple parce qu'un congé a été reçu. | E46: La prochaine sortie (Rent roll!Q11:Q50) est alors calculée, pas devinée : c'est la première fin de période strictement postérieure à la date d'analyse, plafonnée à l'échéance. C'est le cœur du WALB, et la première cause d'erreur dans un rent roll tenu à la main.
B47: 5. Les franchises | C47: Rent roll!R11:R50 | D47: Le nombre de mois de franchise accordés au bail. Laissez vide s'il n'y en a pas. Repère de marché quand le bail n'est pas encore signé : Paramètres!C18. Une franchise, ce sont des mois de loyer offerts au preneur à l'entrée dans les lieux, en contrepartie de son engagement. | E47: Le loyer économique (Rent roll!S11:S50) déduit la franchise, étalée sur la période d'engagement ferme. Le WALB est alors affiché sur les deux bases, Synthèse!C39 au loyer facial et Synthèse!C41 au loyer économique : le premier est ce que dit le bail, le second ce que l'immeuble encaisse. La période d'engagement ferme est la durée pendant laquelle le locataire ne peut pas partir : la première période de sortie du bail, trois ans le plus souvent, six ou neuf s'il a renoncé à ses triennales. C'est sur elle que la franchise est étalée.
B48: 6. Les contrôles | C48: Rent roll!V11:W50, Synthèse!C7:C12 et Échéancier!C28 et F28 | D48: Vérifiez que chaque ligne remplie affiche OK en colonne V. Une ligne rouge porte son motif juste à côté, en colonne W, et elle est exclue de tous les totaux. Parcourez aussi la colonne W des lignes vertes : une valeur locative manquante y écrit son motif sans faire passer la ligne au rouge, parce qu'elle n'empêche de calculer ni les loyers ni les durées, seulement le taux d'occupation financier et la réversion. La Synthèse compte les unes et les autres (Synthèse!C35) et nomme la première (Synthèse!C9). | E48: Une ligne à corriger est exclue de tous les totaux, jamais comptée à zéro. C'est ce qui évite qu'un bail sans date d'échéance pèse son loyer avec une durée nulle et fasse chuter le WAULT sans prévenir.
B49: 7. La lecture | C49: Synthèse!B14:D48 | D49: Rien à saisir. Lisez dans l'ordre : le taux d'occupation financier (Synthèse!C21), le loyer facial en place (Synthèse!C24) et, juste en dessous, le loyer économique (Synthèse!C25), la réversion (Synthèse!C30 et Synthèse!C31), le WAULT et le WALB (Synthèse!C38 et Synthèse!C39), le poids du premier locataire (Synthèse!C47). | E49: C'est l'ordre dans lequel un acquéreur lit un immeuble : combien il encaisse, à quel prix par rapport au marché, pendant combien de temps, et de qui il dépend.
B50: 8. L'échéancier | C50: Échéancier!B10:I28 | D50: Rien à saisir. Cherchez la ligne en alerte : c'est l'année où le plus de loyer se remet en jeu. Vérifiez d'abord les deux contrôles de recoupement, Échéancier!C28 pour la colonne du terme et Échéancier!F28 pour celle de la sortie : tant qu'ils ne sont pas verts, ne lisez ni le tableau ni l'année de pointe. | E50: Le seuil d'alerte est en Paramètres!C16. Les deux contrôles de la ligne 28 garantissent que chaque euro de loyer du rent roll se retrouve dans une période et une seule : sans eux, un échéancier peut être entièrement faux sans qu'aucune cellule n'affiche d'erreur. Si l'un des deux passe au rouge, un loyer n'est tombé dans aucune période : reprenez les dates des lignes retenues, une date d'échéance ou une sortie forcée a échappé aux garde-fous, presque toujours après un collage depuis un autre fichier. Le même contrôle est repris en Synthèse!C11, pour que vous le voyiez sans quitter la Synthèse. La première ligne du tableau isole les baux échus, ceux dont l'échéance est passée : ils restent dans tous les totaux avec leur loyer, mais comptent zéro an dans le WAULT comme dans le WALB, parce qu'en tacite prolongation le congé peut être donné à tout moment. Un WALB écrasé sans cause apparente vient souvent de là : regardez Synthèse!C36 et Synthèse!C37.
B51: 9. Les paramètres | C51: Paramètres!C8:C12, Paramètres!C16:C25 et Paramètres!C38:C40 | D51: Chaque trimestre, mettez à jour les trois indices (Paramètres!C10:C12, source Insee), puis les deux trimestres et la date de vérification (Paramètres!C38, Paramètres!C39 et Paramètres!C40). Les repères de durée résiduelle des foncières (Paramètres!C19 et Paramètres!C20) se rafraîchissent une fois par an, à la publication des résultats annuels. | E51: Les seuils d'alerte et les garde-fous de saisie sont des conventions du classeur : ajustez-les à votre pratique. Toutes les formules pointent ici, et les libellés de source de Paramètres et de Méthode se mettent à jour seuls à partir des trois cellules de millésime.
B53: EXEMPLE GUIDÉ
B54: Le fichier est livré avec un immeuble mixte de 1 755 m² : quatre plateaux de bureaux, trois locaux de commerce en pied d'immeuble, analysé au 30/06/2026. Six lots sont loués, un local de commerce de 95 m² est vacant. Les cinq contrôles de la Synthèse affichent OK, et la ligne « Première ligne à corriger ou à compléter » (Synthèse!C9) reste vide, comme elle doit l'être quand aucune ligne n'est en cause.
B55: Occupation : 1 660 m² loués sur 1 755 m², soit un taux d'occupation physique de 94,59 % (Synthèse!C18). Le taux d'occupation financier au sens de l'EPRA, l'association des foncières cotées européennes dont les recommandations font la référence de place, ressort à 93,62 % (Synthèse!C21) : il est plus bas que le taux physique parce que le local vacant vaut, au marché, 36 100 € par an (Synthèse!C20) sur une valeur locative d'ensemble de 566 100 € (Synthèse!C19). C'est toujours ce taux-là qu'un investisseur regarde : il pèse la vacance en euros, pas en mètres carrés.
B56: Loyers : le loyer facial en place atteint 500 730 € par an (Synthèse!C24), soit 302 € par mètre carré loué (Synthèse!C28). Trois baux ont reçu une franchise, deux signatures : 3 mois sur chacun des deux lots du Locataire Alpha et 6 mois pour le Locataire Delta. Le loyer économique tombe à 476 957 € (Synthèse!C25), soit 23 773 € de moins, 4,75 % du loyer facial (Synthèse!C26 et Synthèse!C27). La valeur locative des surfaces louées étant de 530 000 € (Synthèse!C29), la réversion est positive de 29 270 € (Synthèse!C30), soit 5,85 % du loyer facial (Synthèse!C31) : les loyers en place sont sous le marché, sauf le commerce du RDC Local 1, loué 420 € le mètre carré pour une valeur locative de 400 €, dont la réversion est négative de 4,76 % (Rent roll!L13).
B57: Durées : le WAULT ressort à 4,8 ans (Synthèse!C38), le WALB à 2,2 ans (Synthèse!C39). L'écart de 2,7 ans (Synthèse!C42) est le poids des facultés de sortie : sur le papier les baux courent près de cinq ans, en réalité le revenu n'est ferme que deux ans. Sur base de loyer économique, les deux durées deviennent 4,8 ans et 2,1 ans (Synthèse!C40 et Synthèse!C41). Le WALB de 2,2 ans est sous le repère bas des foncières de bureaux, 3,4 ans (Paramètres!C19, millésime 2026) : cet immeuble se vend comme un risque locatif, pas comme un revenu long.
B58: Ce que le classeur a calculé tout seul : la prochaine sortie de chaque bail. Le Locataire Bêta, entré le 01/01/2021, peut partir au 31/12/2026, dans 0,5 ans, soit six mois, alors que son bail court jusqu'au 31/12/2029. Le Locataire Delta occupe des bureaux et a renoncé à ses premières triennales : sa périodicité est saisie à 6 ans (Rent roll!O15), sa prochaine sortie tombe au 31/03/2030. Sans cette saisie, sa première sortie serait le 31/03/2027 et le WALB de l'immeuble tomberait à 1,5 ans : c'est la différence entre un bail lu et un bail supposé.
B59: Échéancier : 2029 concentre 35,56 % du loyer à la sortie, 178 080 € sur 500 730 €, parce que les deux lots du Locataire Alpha sortent le même jour. La ligne porte l'alerte « Concentration forte », le seuil étant en Paramètres!C16. Le total de l'échéancier, 500 730 € au terme comme à la sortie, est égal au loyer facial en place : les deux contrôles de recoupement, Échéancier!C28 et Échéancier!F28, affichent OK.
B60: Concentration : cinq locataires pour six lots (Synthèse!C45), parce que le Locataire Alpha occupe deux plateaux. Son poids est de 35,56 % du loyer (Synthèse!C47), sous le seuil de Paramètres!C17. Compté lot par lot, son plus gros lot ne pèse que 23,91 % du loyer facial, 119 700 € sur 500 730 € (Rent roll!H11 et Synthèse!C24) : la concentration se mesure par signature, jamais par lot.
B61: Un cas d'école, à essayer : effacez la date d'échéance du premier lot (cellule Rent roll!N11). La ligne passe au rouge avec le motif « Date d'échéance manquante. », le compteur Synthèse!C35 affiche 1, la Synthèse nomme la ligne, et le WAULT devient 4,5 ans sur les cinq baux restants au lieu de 4,8 ans sur six. Le loyer du lot sort du calcul au lieu d'y peser avec une durée nulle, ce qui aurait donné 3,4 ans sans le moindre message.
B62: Un second cas d'école, celui que personne ne cherche : effacez la valeur locative du plus gros lot loué (cellule Rent roll!I11). La ligne reste verte, son loyer et ses durées restent comptés, mais son motif s'affiche en colonne W, Synthèse!C35 passe à 1, Synthèse!C9 la nomme, et le contrôle Synthèse!C10 passe au rouge. Le taux d'occupation financier, la valeur locative des surfaces louées et la réversion se vident : sans ce garde-fou, la réversion resterait affichée et passerait de 5,85 % à moins 19,32 %, c'est-à-dire d'un immeuble sous le marché à un immeuble très au-dessus, parce que ce lot compterait pour une valeur locative nulle.
B64: LES CHIFFRES À REGARDER, ET CE QU'ILS VALENT
B65: Indicateur | C65: Où | D65: Repère métier | E65: Ce qu'il dit vraiment
B66: Loyer facial et loyer économique | C66: Synthèse!C24 et Synthèse!C25 | D66: Leur écart se lit en Synthèse!C26 et Synthèse!C27. Sur l'exemple, 23 773 €, soit 4,75 % (millésime 2026). | E66: Annoncez le facial : c'est le loyer du bail, celui qu'annualisent les foncières et celui que porte un teaser. Calculez un taux de rendement sur l'économique : c'est ce que l'immeuble encaisse. Dès que l'écart dépasse quelques pour cent, citez les deux, sinon votre acquéreur le fera pour vous.
B67: WALB, durée résiduelle ferme | C67: Synthèse!C39 | D67: Situez-le entre les deux repères publiés : Paramètres!C19 pour une foncière de bureaux, Paramètres!C20 pour une foncière diversifiée (repères 2026). Ce sont ces deux cellules qui font foi, elles se rafraîchissent chaque année à la publication des résultats. En dessous du premier, l'immeuble se vend comme un risque locatif. | E67: La durée pendant laquelle le loyer est sécurisé. C'est le chiffre que retient un investisseur, et celui qu'une banque regarde avant d'aligner la durée d'un prêt.
B68: WAULT, durée jusqu'au terme | C68: Synthèse!C38 | D68: Toujours supérieur au WALB. L'écart se lit en Synthèse!C42 ; sur l'exemple livré il vaut 2,7 ans (millésime 2026). | E68: L'horizon maximal, si aucun locataire n'exerçait sa faculté de sortie. Publié seul, il flatte l'immeuble : les foncières publient toujours les deux.
B69: WAULT et WALB sur base de loyer économique | C69: Synthèse!C40 et Synthèse!C41 | D69: Toujours proches des deux premiers, plus courts dès qu'un gros bail porte une franchise. Sur l'exemple, 4,8 ans et 2,1 ans (millésime 2026). | E69: La même durée, vue par celui qui encaisse. Publiez les durées au loyer facial, ce sont celles que publient les foncières et celles auxquelles votre acquéreur comparera. Gardez celles au loyer économique pour vous : quand elles décrochent nettement, ce sont vos plus gros baux qui portent les franchises.
B70: Taux d'occupation financier (EPRA) | C70: Synthèse!C21 | D70: Comparez-le au taux d'occupation physique (Synthèse!C18) : l'écart dit si les surfaces vacantes valent cher ou pas. Sur l'exemple, 93,62 % contre 94,59 % (millésime 2026). | E70: La part de la valeur locative de l'immeuble qui est effectivement louée. Il pèse la vacance en euros, pas en mètres carrés. C'est celui d'un teaser, d'une note d'investissement et d'un reporting de foncière. Gardez le taux physique (Synthèse!C18) pour la gestion et la commercialisation, où l'on raisonne en mètres carrés à relouer : les deux sont justes, ils ne répondent pas à la même question.
B71: Réversion | C71: Synthèse!C30 et Synthèse!C31 ; par lot en Rent roll!L11:L50 | D71: Positive : potentiel de hausse. Négative : baisse programmée du loyer à l'échéance. Sur l'exemple, 5,85 % (millésime 2026). | E71: L'écart entre le loyer en place et le marché. C'est ce que devient le revenu quand les baux se renouvellent, donc ce qui décide de la valeur de sortie.
B72: Année de pointe de l'échéancier | C72: Échéancier!B10:I26, colonnes F et G | D72: Seuil d'alerte en Paramètres!C16. Sur l'exemple, 2029 porte 35,56 % du loyer (millésime 2026). | E72: L'année où le plus de loyer se remet en jeu. Un WALB moyen rassurant peut cacher un mur d'échéances : c'est là qu'on le voit. La ligne des baux échus et celle de l'au-delà de l'horizon peuvent porter le pic, elles aussi.
B73: Poids du premier locataire | C73: Synthèse!C47 | D73: Seuil d'alerte en Paramètres!C17. Sur l'exemple, 35,56 % (millésime 2026). | E73: Le risque de contrepartie, mesuré par signature et non par lot. Au-delà du seuil, l'immeuble est un pari sur une entreprise autant que sur un emplacement.
B75: LES DONNÉES À METTRE À JOUR, OÙ ET POURQUOI
B76: Deux familles de données. Les benchmarks (périodicité légale, préavis, indices Insee, seuils d'alerte, repères de durée résiduelle, garde-fous de saisie) changent avec la réglementation ou le marché, à date fixe, et se rafraîchissent depuis une source indiquée. Les données de projet (date d'analyse, lots, locataires, surfaces, loyers, valeurs locatives, dates, franchises) sont propres à chaque immeuble. L'architecture du classeur ne change pas quand les données changent : seules les cellules bleues bougent.
B77: Les chiffres cités dans ce guide et dans Méthode sont écrits en toutes lettres et datés du millésime 2026 : relisez-les à chaque mise à jour de Paramètres, en particulier les repères de durée résiduelle des foncières et les seuils de la colonne « Repère métier » ci-dessus. Les libellés de source de Paramètres et de Méthode, eux, se reconstruisent seuls à partir des trois cellules de millésime (Paramètres!C38:C40).
B78: Paramètre | C78: Onglet et cellule | D78: Ce qu'il pilote | E78: Source à consulter, fréquence
B79: Périodicité légale des facultés de sortie | C79: Paramètres!C8 | D79: La prochaine sortie calculée de chaque bail dont la colonne O est vide, donc le WALB et l'échéancier | E79: Code de commerce, art. L145-4, Légifrance : à chaque réforme du statut des baux commerciaux
B80: Préavis de congé | C80: Paramètres!C9 | D80: Le message de la ligne des baux échus de l'échéancier | E80: Code de commerce, art. L145-9 : à chaque réforme
B81: Indices ILAT, ILC et IRL | C81: Paramètres!C10:C12 | D81: Rien dans les calculs : ils servent à dater la dernière indexation connue des loyers saisis | E81: Insee, publications trimestrielles : trimestrielle
B82: Trimestres des indices et date de vérification | C82: Paramètres!C38:C40 | D82: Les libellés de source de Paramètres et de Méthode, qui les lisent par formule | E82: Les mêmes publications Insee : trimestrielle
B83: Seuil d'alerte de concentration | C83: Paramètres!C16 | D83: L'alerte de la colonne Alerte de l'échéancier | E83: Convention du classeur : stable, à ajuster à votre pratique
B84: Seuil de dépendance au premier locataire | C84: Paramètres!C17 | D84: Le contrôle Synthèse!C48 | E84: Convention du classeur : stable
B85: Repères de durée résiduelle des foncières | C85: Paramètres!C19:C20 | D85: Rien : ils servent à situer votre WALB, les notes d'aide y renvoient | E85: Communiqués de résultats annuels des foncières cotées, nommés et datés en colonne D de Paramètres : annuelle, à la publication des résultats
B86: Repère de franchise usuelle | C86: Paramètres!C18 | D86: Rien : point de départ quand le bail n'est pas encore signé, la franchise réelle se saisissant bail par bail | E86: Publications de place sur les mesures d'accompagnement, GIE Immostat pour l'Île-de-France : trimestrielle. Le repère vaut hors Île-de-France prime : la source de Paramètres dit ce que mesure chacun des deux chiffres
B87: Garde-fous de saisie | C87: Paramètres!C21:C24 | D87: Les bornes de validation et les contrôles de ligne du rent roll | E87: Conventions du classeur : stable, à relever pour un actif hors normes
B88: Plancher de plausibilité d'un taux saisi | C88: Paramètres!C25 | D88: Le contrôle Synthèse!C12, qui attrape un seuil d'alerte saisi en fraction | E88: Convention CorpusImmo, commune aux matrices qui saisissent des taux : stable
B89: L'immeuble et ses baux | C89: Rent roll!C7, Rent roll!B11:G50, Rent roll!I11:I50, Rent roll!M11:P50, Rent roll!R11:R50 | D89: Tout le reste | E89: Les baux eux-mêmes, l'état locatif du property manager, et un avis de valeur locative pour la colonne de valeur locative de marché
B91: TROIS FAÇONS DE S'EN SERVIR
B92: Votre situation | C92: Ce que vous faites
B93: Vous étudiez une acquisition | C93: Saisissez l'état locatif du vendeur, puis vérifiez trois choses. La colonne Q : le vendeur a-t-il retenu les mêmes dates de sortie que le classeur ? Un écart de trois ans sur un gros bail change le WALB. La colonne L : quels baux sont au-dessus du marché, donc quels loyers baisseront au renouvellement. Et l'échéancier : quelle année concentre le plus de loyer, et si elle tombe pendant votre durée de détention.
B94: Vous préparez un plan d'asset management | C94: Pour voir dans l'ordre les baux à renégocier, triez la grille sur la colonne Q. Le tri demande d'ôter d'abord la protection de la feuille, par l'onglet Révision, sans mot de passe : Excel refuse de trier une plage qui contient des colonnes calculées, et ce sont justement elles qui doivent suivre leur ligne. Sélectionnez toujours la plage entière, Rent roll!B11:X50, colonnes calculées comprises : si vous ne triez que les colonnes bleues, les colonnes blanches restent en place et chaque ligne se retrouve avec les calculs d'une autre. Remettez la protection ensuite. Pour filtrer, rien à ôter : le filtre automatique est en place sur la ligne d'en-tête et la protection l'autorise. Pour chaque bail, la colonne L dit s'il faut défendre le loyer ou aller le chercher. Simulez une renégociation en changeant la périodicité de sortie ou la sortie forcée d'une ligne : le WALB de Synthèse!C39 se met à jour immédiatement.
B95: Vous montez un financement | C95: L'échéancier dit combien de loyer se remet en jeu chaque année. Comparez la durée du prêt au WALB (Synthèse!C39) et regardez la part du loyer qui tombe avant l'échéance du prêt : c'est le loyer que la banque ne considérera pas comme sécurisé. La ligne des baux échus est la plus fragile de toutes, le congé pouvant y être donné à tout moment.
B97: LES ERREURS QUI FAUSSENT TOUT
B98: Le piège | C98: Le dégât
B99: Laisser la prochaine sortie au bail alors qu'il a renoncé à ses triennales, ou l'inverse (Rent roll!O11:O50) | C99: Sur l'exemple, le Locataire Delta a une période ferme de six ans. Saisie à blanc, sa sortie tomberait le 31/03/2027 et le WALB de l'immeuble passerait de 2,2 ans à 1,5 ans. Lisez la clause de renonciation du bail, ne la supposez pas.
B100: Oublier la valeur locative de marché d'un lot, vacant ou loué (Rent roll!I11:I50) | C100: Le taux d'occupation financier, la valeur locative des surfaces louées et la réversion ne s'affichent plus du tout, et le contrôle Synthèse!C10 passe au rouge. C'est voulu : sur un lot vacant, la vacance serait sous-estimée et le taux affiché flatté ; sur un lot loué, le lot compterait pour une valeur locative nulle et la réversion de l'immeuble entier deviendrait fausse. Sur l'exemple, le taux vaut 93,62 % et la réversion 5,85 % : effacer la seule valeur locative du plus gros lot loué ferait afficher moins 19,32 % à un classeur qui ne se garderait pas. Pour lever le blocage : la ligne reste verte, mais elle est comptée par Synthèse!C35, nommée par Synthèse!C9, et son motif « Valeur locative de marché non renseignée. » s'affiche dans la colonne W.
B101: Saisir un loyer annuel dans une colonne au mètre carré (Rent roll!G11:G50 ou Rent roll!I11:I50) | C101: Au-delà du garde-fou de Paramètres!C21, la saisie est refusée et la ligne passe au rouge, avec le motif « Loyer facial au-delà du garde-fou de saisie. » si la valeur a été collée depuis un autre fichier. Le garde-fou attrape les grands lots, pas les petits : un parking ou un local d'archives dont le loyer annuel tient sous le plafond passe sans un mot, avec un loyer multiplié par sa surface. Contrôlez la colonne H, le loyer annuel calculé, sur vos plus petits lots.
B102: Écrire « Vacant » dans la colonne du locataire au lieu de la colonne Statut (Rent roll!D11:D50) | C102: Avec le statut Vacant, la ligne passe au rouge avec le motif « Lot vacant avec un locataire renseigné. ». Avec le statut Loué et sans loyer, elle passe au rouge avec « Loyer facial manquant ou nul. » et sort de tous les totaux. Le seul cas où rien ne s'allume est celui d'un statut resté à Loué avec un loyer saisi : le lot est alors compté comme loué, sa surface entre dans la surface louée et son loyer dans le loyer en place. Le statut est une liste déroulante : servez-vous-en.
B103: Laisser une ligne à demi remplie, un bail sans date d'échéance par exemple (Rent roll!N11:N50) | C103: La ligne est exclue de tous les totaux et le compteur Synthèse!C35 l'annonce. Sur l'exemple, effacer l'échéance du premier lot fait passer le WAULT de 4,8 ans à 4,5 ans sur les baux restants : le classeur préfère calculer sur moins de baux qu'inventer une durée nulle.
B104: Prendre le WAULT pour la durée du revenu (Synthèse!C38) | C104: Sur l'exemple, le WAULT annonce 4,8 ans et le WALB 2,2 ans. Un acquéreur qui paie le WAULT achète 2,7 ans de revenu que le locataire peut lui reprendre.
B105: Confondre loyer facial et loyer économique (Synthèse!C24 et Synthèse!C25) | C105: Sur l'exemple, 23 773 € par an séparent les deux, soit 4,75 %. Un taux de rendement calculé sur le loyer facial d'un immeuble plein de franchises est faux d'autant. Le loyer facial est ce que dit le bail, le loyer économique ce que l'immeuble encaisse.
B107: Ce que le classeur ne fait pas, et sur quelles sources reposent ses chiffres : voir l'onglet Méthode.
B109: CorpusImmo, millésime 2026. Modèle d'aide à la décision : ne constitue ni un conseil en investissement, ni un conseil fiscal, ni une expertise au sens de la charte de l'expertise en évaluation immobilière. Vérifiez les paramètres avant tout engagement.

Sheet Rent roll
B1: CorpusImmo · corpus.immo · Estimer, comparer, décider. Sur les ventes réelles.
B2: Rent roll
B3: L'état locatif lot par lot : loyer facial et loyer économique, valeur locative de marché, prochaine faculté de sortie et durées résiduelles.
B5: Cellules bleues : à remplir. Cellules blanches : calculées automatiquement. | E5: Une ligne par lot. La grille accepte 40 baux, lignes 11 à 50 : ajoutez vos lots à la suite, dans les lignes bleues déjà prêtes, sans jamais insérer de ligne. Aucune cellule n'est fusionnée. Le filtre automatique est posé sur la ligne d'en-tête et la protection l'autorise : filtrez sans rien déverrouiller. Pour trier, ôtez d'abord la protection par l'onglet Révision, puis triez la plage entière, colonnes calculées comprises, et remettez la protection.
B7: Date d'analyse | C7: 46203 | E7: Toutes les durées résiduelles et l'échéancier partent de cette date. Une vraie date, au format jj/mm/aaaa.
B8: État locatif exploitable | C8: =IF(Synthèse!$C$7="OK","OK","À CORRIGER") -> OK | E8: Rouge : la date d'analyse manque, aucun bail n'est retenu, une ligne est à corriger ou à compléter, ou un paramètre est vide. Le motif est dans la colonne W, y compris sur une ligne verte à laquelle il ne manque que sa valeur locative ; la Synthèse les compte et nomme la première.
B10: Lot | C10: Nature | D10: Locataire | E10: Statut | F10: Surface | G10: Loyer facial €/m²/an HT HC | H10: Loyer facial annuel HT HC | I10: VLM €/m²/an | J10: VLM annuelle | K10: Réversion | L10: Réversion % | M10: Prise d'effet | N10: Échéance | O10: Périodicité de sortie (ans) | P10: Sortie forcée (facultatif) | Q10: Prochaine sortie retenue | R10: Franchise (mois) | S10: Loyer économique annuel | T10: Durée au terme | U10: Durée à la sortie | V10: Contrôle | W10: Motif | X10: Loyer du locataire (tous ses lots)
B11: R+1 Plateau A | C11: Bureaux | D11: Locataire Alpha | E11: Loué | F11: 420 | G11: 285 | H11: =IF(AND(ISNUMBER(F11),ISNUMBER(G11)),F11*G11,0) -> 119700 | I11: 300 | J11: =IF(AND(ISNUMBER(F11),ISNUMBER(I11)),F11*I11,0) -> 126000 | K11: =IF(OR(H11<=0,J11<=0),"",J11-H11) -> 6300 | L11: =IF(OR(H11<=0,J11<=0),"",J11/H11-1) -> 0.052631579 | M11: 45108 | N11: 48395 | Q11: =IF(OR(NOT(ISNUMBER($C$7)),NOT(ISNUMBER(M11)),NOT(ISNUMBER(N11))),"",IF(ISNUMBER(P11),P11,IF((IF(OR(O11="",NOT(ISNUMBER(O11))),Paramètres!$C$8,O11))<=0,"",MIN(EDATE(M11,(12*(IF(OR(O11="",NOT(ISNUMBER(O11))),Paramètres!$C$8,O11)))*MAX(1,INT(((YEAR($C$7+1)-YEAR(M11))*12+MONTH($C$7+1)-MONTH(M11)-(DAY($C$7+1)<DAY(M11)))/(12*(IF(OR(O11="",NOT(ISNUMBER(O11))),Paramètres!$C$8,O11))))+1))-1,N11)))) -> 47299 | R11: 3 | S11: =IF(H11=0,0,IF(OR(R11="",R11=0),H11,IF(OR(NOT(ISNUMBER(R11)),(IF(OR(NOT(ISNUMBER(M11)),NOT(ISNUMBER(N11)),N11<=M11),0,MIN(12*(IF(OR(O11="",NOT(ISNUMBER(O11))),Paramètres!$C$8,O11)),(YEAR(N11)-YEAR(M11))*12+MONTH(N11)-MONTH(M11)+1)))<=0),0,MAX(0,H11*(1-R11/(IF(OR(NOT(ISNUMBER(M11)),NOT(ISNUMBER(N11)),N11<=M11),0,MIN(12*(IF(OR(O11="",NOT(ISNUMBER(O11))),Paramètres!$C$8,O11)),(YEAR(N11)-YEAR(M11))*12+MONTH(N11)-MONTH(M11)+1)))))))) -> 109725 | T11: =IF(AND(ISNUMBER(N11),ISNUMBER($C$7)),MAX(0,(N11-$C$7)/365.25),0) -> 6.0013689 | U11: =IF(AND(ISNUMBER(Q11),ISNUMBER($C$7)),MAX(0,(Q11-$C$7)/365.25),0) -> 3.0006845 | V11: =IF(COUNTA(B11,C11,D11,E11,F11,G11,I11,M11,N11,O11,P11,R11)>0,IF(AND(COUNT(Paramètres!$C$8:$C$12)=5,COUNT(Paramètres!$C$16:$C$25)=10,ISNUMBER($C$7),B11<>"",NOT(ISNA(MATCH(C11,Paramètres!$B$29:$B$34,0))),NOT(ISNA(MATCH(E11,Paramètres!$D$29:$D$30,0))),ISNUMBER(F11),F11>0,F11<=Paramètres!$C$22,OR(I11="",AND(ISNUMBER(I11),I11>=0,I11<=Paramètres!$C$21)),IF(E11=Paramètres!$D$29,AND(D11<>"",ISNUMBER(G11),G11>0,G11<=Paramètres!$C$21,ISNUMBER(M11),ISNUMBER(N11),N11>M11,(N(N11)-N(M11))/365.25<=Paramètres!$C$23,OR(O11="",AND(ISNUMBER(O11),O11>=1,O11<=Paramètres!$C$23,O11=INT(N(O11)))),OR(P11="",AND(ISNUMBER(P11),P11>$C$7,P11<=N11)),OR(R11="",AND(ISNUMBER(R11),R11>=0,R11<=Paramètres!$C$24,R11<=(IF(OR(NOT(ISNUMBER(M11)),NOT(ISNUMBER(N11)),N11<=M11),0,MIN(12*(IF(OR(O11="",NOT(ISNUMBER(O11))),Paramètres!$C$8,O11)),(YEAR(N11)-YEAR(M11))*12+MONTH(N11)-MONTH(M11)+1)))))),AND(D11="",OR(G11="",G11=0)))),"OK","À CORRIGER"),"") -> OK | W11: =IF(NOT(COUNTA(B11,C11,D11,E11,F11,G11,I11,M11,N11,O11,P11,R11)>0),"",IF(OR(COUNT(Paramètres!$C$8:$C$12)<>5,COUNT(Paramètres!$C$16:$C$25)<>10),"Un paramètre de l'onglet Paramètres est vide.",IF(NOT(ISNUMBER($C$7)),"Date d'analyse manquante.",IF(B11="","Libellé du lot manquant.",IF(ISNA(MATCH(C11,Paramètres!$B$29:$B$34,0)),"Nature hors liste.",IF(ISNA(MATCH(E11,Paramètres!$D$29:$D$30,0)),"Statut hors liste.",IF(NOT(AND(ISNUMBER(F11),F11>0)),"Surface manquante ou nulle.",IF(F11>Paramètres!$C$22,"Surface au-delà du garde-fou de saisie.",IF(AND(I11<>"",NOT(AND(ISNUMBER(I11),I11>=0,I11<=Paramètres!$C$21))),"Valeur locative de marché hors bornes.",IF(AND(E11=Paramètres!$D$29,D11=""),"Lot déclaré loué sans locataire.",IF(AND(E11=Paramètres!$D$29,NOT(AND(ISNUMBER(G11),G11>0))),"Loyer facial manquant ou nul.",IF(AND(E11=Paramètres!$D$29,G11>Paramètres!$C$21),"Loyer facial au-delà du garde-fou de saisie.",IF(AND(E11=Paramètres!$D$29,NOT(ISNUMBER(M11))),"Date de prise d'effet manquante.",IF(AND(E11=Paramètres!$D$29,NOT(ISNUMBER(N11))),"Date d'échéance manquante.",IF(AND(E11=Paramètres!$D$29,N11<=M11),"Échéance antérieure ou égale à la prise d'effet.",IF(AND(E11=Paramètres!$D$29,(N(N11)-N(M11))/365.25>Paramètres!$C$23),"Durée du bail au-delà du garde-fou de saisie.",IF(AND(E11=Paramètres!$D$29,O11<>"",NOT(AND(ISNUMBER(O11),O11>=1,O11<=Paramètres!$C$23,O11=INT(N(O11))))),"Périodicité de sortie hors bornes.",IF(AND(E11=Paramètres!$D$29,P11<>"",NOT(AND(ISNUMBER(P11),P11>$C$7,P11<=N11))),"Sortie forcée hors de l'intervalle admis.",IF(AND(E11=Paramètres!$D$29,R11<>"",NOT(AND(ISNUMBER(R11),R11>=0,R11<=Paramètres!$C$24,R11<=(IF(OR(NOT(ISNUMBER(M11)),NOT(ISNUMBER(N11)),N11<=M11),0,MIN(12*(IF(OR(O11="",NOT(ISNUMBER(O11))),Paramètres!$C$8,O11)),(YEAR(N11)-YEAR(M11))*12+MONTH(N11)-MONTH(M11)+1)))))),"Franchise hors bornes ou plus longue que la période ferme.",IF(AND(E11=Paramètres!$D$30,D11<>""),"Lot vacant avec un locataire renseigné.",IF(AND(E11=Paramètres!$D$30,G11<>"",G11<>0),"Lot vacant avec un loyer renseigné.",IF(AND(E11=Paramètres!$D$29,ISNUMBER(N11),ISNUMBER($C$7),N11<$C$7),"Bail échu, en tacite prolongation.",IF(I11="","Valeur locative de marché non renseignée.",""))))))))))))))))))))))) | X11: =IF(AND(V11="OK",E11=Paramètres!$D$29),SUMIFS($H$11:$H$50,$D$11:$D$50,D11,$E$11:$E$50,Paramètres!$D$29,$V$11:$V$50,"OK"),0) -> 178080
B12: R+1 Plateau B | C12: Bureaux | D12: Locataire Bêta | E12: Loué | F12: 310 | G12: 275 | H12: =IF(AND(ISNUMBER(F12),ISNUMBER(G12)),F12*G12,0) -> 85250 | I12: 300 | J12: =IF(AND(ISNUMBER(F12),ISNUMBER(I12)),F12*I12,0) -> 93000 | K12: =IF(OR(H12<=0,J12<=0),"",J12-H12) -> 7750 | L12: =IF(OR(H12<=0,J12<=0),"",J12/H12-1) -> 0.090909091 | M12: 44197 | N12: 47483 | Q12: =IF(OR(NOT(ISNUMBER($C$7)),NOT(ISNUMBER(M12)),NOT(ISNUMBER(N12))),"",IF(ISNUMBER(P12),P12,IF((IF(OR(O12="",NOT(ISNUMBER(O12))),Paramètres!$C$8,O12))<=0,"",MIN(EDATE(M12,(12*(IF(OR(O12="",NOT(ISNUMBER(O12))),Paramètres!$C$8,O12)))*MAX(1,INT(((YEAR($C$7+1)-YEAR(M12))*12+MONTH($C$7+1)-MONTH(M12)-(DAY($C$7+1)<DAY(M12)))/(12*(IF(OR(O12="",NOT(ISNUMBER(O12))),Paramètres!$C$8,O12))))+1))-1,N12)))) -> 46387 | S12: =IF(H12=0,0,IF(OR(R12="",R12=0),H12,IF(OR(NOT(ISNUMBER(R12)),(IF(OR(NOT(ISNUMBER(M12)),NOT(ISNUMBER(N12)),N12<=M12),0,MIN(12*(IF(OR(O12="",NOT(ISNUMBER(O12))),Paramètres!$C$8,O12)),(YEAR(N12)-YEAR(M12))*12+MONTH(N12)-MONTH(M12)+1)))<=0),0,MAX(0,H12*(1-R12/(IF(OR(NOT(ISNUMBER(M12)),NOT(ISNUMBER(N12)),N12<=M12),0,MIN(12*(IF(OR(O12="",NOT(ISNUMBER(O12))),Paramètres!$C$8,O12)),(YEAR(N12)-YEAR(M12))*12+MONTH(N12)-MONTH(M12)+1)))))))) -> 85250 | T12: =IF(AND(ISNUMBER(N12),ISNUMBER($C$7)),MAX(0,(N12-$C$7)/365.25),0) -> 3.504449 | U12: =IF(AND(ISNUMBER(Q12),ISNUMBER($C$7)),MAX(0,(Q12-$C$7)/365.25),0) -> 0.50376454 | V12: =IF(COUNTA(B12,C12,D12,E12,F12,G12,I12,M12,N12,O12,P12,R12)>0,IF(AND(COUNT(Paramètres!$C$8:$C$12)=5,COUNT(Paramètres!$C$16:$C$25)=10,ISNUMBER($C$7),B12<>"",NOT(ISNA(MATCH(C12,Paramètres!$B$29:$B$34,0))),NOT(ISNA(MATCH(E12,Paramètres!$D$29:$D$30,0))),ISNUMBER(F12),F12>0,F12<=Paramètres!$C$22,OR(I12="",AND(ISNUMBER(I12),I12>=0,I12<=Paramètres!$C$21)),IF(E12=Paramètres!$D$29,AND(D12<>"",ISNUMBER(G12),G12>0,G12<=Paramètres!$C$21,ISNUMBER(M12),ISNUMBER(N12),N12>M12,(N(N12)-N(M12))/365.25<=Paramètres!$C$23,OR(O12="",AND(ISNUMBER(O12),O12>=1,O12<=Paramètres!$C$23,O12=INT(N(O12)))),OR(P12="",AND(ISNUMBER(P12),P12>$C$7,P12<=N12)),OR(R12="",AND(ISNUMBER(R12),R12>=0,R12<=Paramètres!$C$24,R12<=(IF(OR(NOT(ISNUMBER(M12)),NOT(ISNUMBER(N12)),N12<=M12),0,MIN(12*(IF(OR(O12="",NOT(ISNUMBER(O12))),Paramètres!$C$8,O12)),(YEAR(N12)-YEAR(M12))*12+MONTH(N12)-MONTH(M12)+1)))))),AND(D12="",OR(G12="",G12=0)))),"OK","À CORRIGER"),"") -> OK | W12: =IF(NOT(COUNTA(B12,C12,D12,E12,F12,G12,I12,M12,N12,O12,P12,R12)>0),"",IF(OR(COUNT(Paramètres!$C$8:$C$12)<>5,COUNT(Paramètres!$C$16:$C$25)<>10),"Un paramètre de l'onglet Paramètres est vide.",IF(NOT(ISNUMBER($C$7)),"Date d'analyse manquante.",IF(B12="","Libellé du lot manquant.",IF(ISNA(MATCH(C12,Paramètres!$B$29:$B$34,0)),"Nature hors liste.",IF(ISNA(MATCH(E12,Paramètres!$D$29:$D$30,0)),"Statut hors liste.",IF(NOT(AND(ISNUMBER(F12),F12>0)),"Surface manquante ou nulle.",IF(F12>Paramètres!$C$22,"Surface au-delà du garde-fou de saisie.",IF(AND(I12<>"",NOT(AND(ISNUMBER(I12),I12>=0,I12<=Paramètres!$C$21))),"Valeur locative de marché hors bornes.",IF(AND(E12=Paramètres!$D$29,D12=""),"Lot déclaré loué sans locataire.",IF(AND(E12=Paramètres!$D$29,NOT(AND(ISNUMBER(G12),G12>0))),"Loyer facial manquant ou nul.",IF(AND(E12=Paramètres!$D$29,G12>Paramètres!$C$21),"Loyer facial au-delà du garde-fou de saisie.",IF(AND(E12=Paramètres!$D$29,NOT(ISNUMBER(M12))),"Date de prise d'effet manquante.",IF(AND(E12=Paramètres!$D$29,NOT(ISNUMBER(N12))),"Date d'échéance manquante.",IF(AND(E12=Paramètres!$D$29,N12<=M12),"Échéance antérieure ou égale à la prise d'effet.",IF(AND(E12=Paramètres!$D$29,(N(N12)-N(M12))/365.25>Paramètres!$C$23),"Durée du bail au-delà du garde-fou de saisie.",IF(AND(E12=Paramètres!$D$29,O12<>"",NOT(AND(ISNUMBER(O12),O12>=1,O12<=Paramètres!$C$23,O12=INT(N(O12))))),"Périodicité de sortie hors bornes.",IF(AND(E12=Paramètres!$D$29,P12<>"",NOT(AND(ISNUMBER(P12),P12>$C$7,P12<=N12))),"Sortie forcée hors de l'intervalle admis.",IF(AND(E12=Paramètres!$D$29,R12<>"",NOT(AND(ISNUMBER(R12),R12>=0,R12<=Paramètres!$C$24,R12<=(IF(OR(NOT(ISNUMBER(M12)),NOT(ISNUMBER(N12)),N12<=M12),0,MIN(12*(IF(OR(O12="",NOT(ISNUMBER(O12))),Paramètres!$C$8,O12)),(YEAR(N12)-YEAR(M12))*12+MONTH(N12)-MONTH(M12)+1)))))),"Franchise hors bornes ou plus longue que la période ferme.",IF(AND(E12=Paramètres!$D$30,D12<>""),"Lot vacant avec un locataire renseigné.",IF(AND(E12=Paramètres!$D$30,G12<>"",G12<>0),"Lot vacant avec un loyer renseigné.",IF(AND(E12=Paramètres!$D$29,ISNUMBER(N12),ISNUMBER($C$7),N12<$C$7),"Bail échu, en tacite prolongation.",IF(I12="","Valeur locative de marché non renseignée.",""))))))))))))))))))))))) | X12: =IF(AND(V12="OK",E12=Paramètres!$D$29),SUMIFS($H$11:$H$50,$D$11:$D$50,D12,$E$11:$E$50,Paramètres!$D$29,$V$11:$V$50,"OK"),0) -> 85250
B13: RDC Local 1 | C13: Commerce | D13: Locataire Gamma | E13: Loué | F13: 180 | G13: 420 | H13: =IF(AND(ISNUMBER(F13),ISNUMBER(G13)),F13*G13,0) -> 75600 | I13: 400 | J13: =IF(AND(ISNUMBER(F13),ISNUMBER(I13)),F13*I13,0) -> 72000 | K13: =IF(OR(H13<=0,J13<=0),"",J13-H13) -> -3600 | L13: =IF(OR(H13<=0,J13<=0),"",J13/H13-1) -> -0.047619048 | M13: 44440 | N13: 47726 | Q13: =IF(OR(NOT(ISNUMBER($C$7)),NOT(ISNUMBER(M13)),NOT(ISNUMBER(N13))),"",IF(ISNUMBER(P13),P13,IF((IF(OR(O13="",NOT(ISNUMBER(O13))),Paramètres!$C$8,O13))<=0,"",MIN(EDATE(M13,(12*(IF(OR(O13="",NOT(ISNUMBER(O13))),Paramètres!$C$8,O13)))*MAX(1,INT(((YEAR($C$7+1)-YEAR(M13))*12+MONTH($C$7+1)-MONTH(M13)-(DAY($C$7+1)<DAY(M13)))/(12*(IF(OR(O13="",NOT(ISNUMBER(O13))),Paramètres!$C$8,O13))))+1))-1,N13)))) -> 46630 | S13: =IF(H13=0,0,IF(OR(R13="",R13=0),H13,IF(OR(NOT(ISNUMBER(R13)),(IF(OR(NOT(ISNUMBER(M13)),NOT(ISNUMBER(N13)),N13<=M13),0,MIN(12*(IF(OR(O13="",NOT(ISNUMBER(O13))),Paramètres!$C$8,O13)),(YEAR(N13)-YEAR(M13))*12+MONTH(N13)-MONTH(M13)+1)))<=0),0,MAX(0,H13*(1-R13/(IF(OR(NOT(ISNUMBER(M13)),NOT(ISNUMBER(N13)),N13<=M13),0,MIN(12*(IF(OR(O13="",NOT(ISNUMBER(O13))),Paramètres!$C$8,O13)),(YEAR(N13)-YEAR(M13))*12+MONTH(N13)-MONTH(M13)+1)))))))) -> 75600 | T13: =IF(AND(ISNUMBER(N13),ISNUMBER($C$7)),MAX(0,(N13-$C$7)/365.25),0) -> 4.1697467 | U13: =IF(AND(ISNUMBER(Q13),ISNUMBER($C$7)),MAX(0,(Q13-$C$7)/365.25),0) -> 1.1690623 | V13: =IF(COUNTA(B13,C13,D13,E13,F13,G13,I13,M13,N13,O13,P13,R13)>0,IF(AND(COUNT(Paramètres!$C$8:$C$12)=5,COUNT(Paramètres!$C$16:$C$25)=10,ISNUMBER($C$7),B13<>"",NOT(ISNA(MATCH(C13,Paramètres!$B$29:$B$34,0))),NOT(ISNA(MATCH(E13,Paramètres!$D$29:$D$30,0))),ISNUMBER(F13),F13>0,F13<=Paramètres!$C$22,OR(I13="",AND(ISNUMBER(I13),I13>=0,I13<=Paramètres!$C$21)),IF(E13=Paramètres!$D$29,AND(D13<>"",ISNUMBER(G13),G13>0,G13<=Paramètres!$C$21,ISNUMBER(M13),ISNUMBER(N13),N13>M13,(N(N13)-N(M13))/365.25<=Paramètres!$C$23,OR(O13="",AND(ISNUMBER(O13),O13>=1,O13<=Paramètres!$C$23,O13=INT(N(O13)))),OR(P13="",AND(ISNUMBER(P13),P13>$C$7,P13<=N13)),OR(R13="",AND(ISNUMBER(R13),R13>=0,R13<=Paramètres!$C$24,R13<=(IF(OR(NOT(ISNUMBER(M13)),NOT(ISNUMBER(N13)),N13<=M13),0,MIN(12*(IF(OR(O13="",NOT(ISNUMBER(O13))),Paramètres!$C$8,O13)),(YEAR(N13)-YEAR(M13))*12+MONTH(N13)-MONTH(M13)+1)))))),AND(D13="",OR(G13="",G13=0)))),"OK","À CORRIGER"),"") -> OK | W13: =IF(NOT(COUNTA(B13,C13,D13,E13,F13,G13,I13,M13,N13,O13,P13,R13)>0),"",IF(OR(COUNT(Paramètres!$C$8:$C$12)<>5,COUNT(Paramètres!$C$16:$C$25)<>10),"Un paramètre de l'onglet Paramètres est vide.",IF(NOT(ISNUMBER($C$7)),"Date d'analyse manquante.",IF(B13="","Libellé du lot manquant.",IF(ISNA(MATCH(C13,Paramètres!$B$29:$B$34,0)),"Nature hors liste.",IF(ISNA(MATCH(E13,Paramètres!$D$29:$D$30,0)),"Statut hors liste.",IF(NOT(AND(ISNUMBER(F13),F13>0)),"Surface manquante ou nulle.",IF(F13>Paramètres!$C$22,"Surface au-delà du garde-fou de saisie.",IF(AND(I13<>"",NOT(AND(ISNUMBER(I13),I13>=0,I13<=Paramètres!$C$21))),"Valeur locative de marché hors bornes.",IF(AND(E13=Paramètres!$D$29,D13=""),"Lot déclaré loué sans locataire.",IF(AND(E13=Paramètres!$D$29,NOT(AND(ISNUMBER(G13),G13>0))),"Loyer facial manquant ou nul.",IF(AND(E13=Paramètres!$D$29,G13>Paramètres!$C$21),"Loyer facial au-delà du garde-fou de saisie.",IF(AND(E13=Paramètres!$D$29,NOT(ISNUMBER(M13))),"Date de prise d'effet manquante.",IF(AND(E13=Paramètres!$D$29,NOT(ISNUMBER(N13))),"Date d'échéance manquante.",IF(AND(E13=Paramètres!$D$29,N13<=M13),"Échéance antérieure ou égale à la prise d'effet.",IF(AND(E13=Paramètres!$D$29,(N(N13)-N(M13))/365.25>Paramètres!$C$23),"Durée du bail au-delà du garde-fou de saisie.",IF(AND(E13=Paramètres!$D$29,O13<>"",NOT(AND(ISNUMBER(O13),O13>=1,O13<=Paramètres!$C$23,O13=INT(N(O13))))),"Périodicité de sortie hors bornes.",IF(AND(E13=Paramètres!$D$29,P13<>"",NOT(AND(ISNUMBER(P13),P13>$C$7,P13<=N13))),"Sortie forcée hors de l'intervalle admis.",IF(AND(E13=Paramètres!$D$29,R13<>"",NOT(AND(ISNUMBER(R13),R13>=0,R13<=Paramètres!$C$24,R13<=(IF(OR(NOT(ISNUMBER(M13)),NOT(ISNUMBER(N13)),N13<=M13),0,MIN(12*(IF(OR(O13="",NOT(ISNUMBER(O13))),Paramètres!$C$8,O13)),(YEAR(N13)-YEAR(M13))*12+MONTH(N13)-MONTH(M13)+1)))))),"Franchise hors bornes ou plus longue que la période ferme.",IF(AND(E13=Paramètres!$D$30,D13<>""),"Lot vacant avec un locataire renseigné.",IF(AND(E13=Paramètres!$D$30,G13<>"",G13<>0),"Lot vacant avec un loyer renseigné.",IF(AND(E13=Paramètres!$D$29,ISNUMBER(N13),ISNUMBER($C$7),N13<$C$7),"Bail échu, en tacite prolongation.",IF(I13="","Valeur locative de marché non renseignée.",""))))))))))))))))))))))) | X13: =IF(AND(V13="OK",E13=Paramètres!$D$29),SUMIFS($H$11:$H$50,$D$11:$D$50,D13,$E$11:$E$50,Paramètres!$D$29,$V$11:$V$50,"OK"),0) -> 75600
B14: RDC Local 2 | C14: Commerce | E14: Vacant | F14: 95 | H14: =IF(AND(ISNUMBER(F14),ISNUMBER(G14)),F14*G14,0) -> 0 | I14: 380 | J14: =IF(AND(ISNUMBER(F14),ISNUMBER(I14)),F14*I14,0) -> 36100 | K14: =IF(OR(H14<=0,J14<=0),"",J14-H14) | L14: =IF(OR(H14<=0,J14<=0),"",J14/H14-1) | Q14: =IF(OR(NOT(ISNUMBER($C$7)),NOT(ISNUMBER(M14)),NOT(ISNUMBER(N14))),"",IF(ISNUMBER(P14),P14,IF((IF(OR(O14="",NOT(ISNUMBER(O14))),Paramètres!$C$8,O14))<=0,"",MIN(EDATE(M14,(12*(IF(OR(O14="",NOT(ISNUMBER(O14))),Paramètres!$C$8,O14)))*MAX(1,INT(((YEAR($C$7+1)-YEAR(M14))*12+MONTH($C$7+1)-MONTH(M14)-(DAY($C$7+1)<DAY(M14)))/(12*(IF(OR(O14="",NOT(ISNUMBER(O14))),Paramètres!$C$8,O14))))+1))-1,N14)))) | S14: =IF(H14=0,0,IF(OR(R14="",R14=0),H14,IF(OR(NOT(ISNUMBER(R14)),(IF(OR(NOT(ISNUMBER(M14)),NOT(ISNUMBER(N14)),N14<=M14),0,MIN(12*(IF(OR(O14="",NOT(ISNUMBER(O14))),Paramètres!$C$8,O14)),(YEAR(N14)-YEAR(M14))*12+MONTH(N14)-MONTH(M14)+1)))<=0),0,MAX(0,H14*(1-R14/(IF(OR(NOT(ISNUMBER(M14)),NOT(ISNUMBER(N14)),N14<=M14),0,MIN(12*(IF(OR(O14="",NOT(ISNUMBER(O14))),Paramètres!$C$8,O14)),(YEAR(N14)-YEAR(M14))*12+MONTH(N14)-MONTH(M14)+1)))))))) -> 0 | T14: =IF(AND(ISNUMBER(N14),ISNUMBER($C$7)),MAX(0,(N14-$C$7)/365.25),0) -> 0 | U14: =IF(AND(ISNUMBER(Q14),ISNUMBER($C$7)),MAX(0,(Q14-$C$7)/365.25),0) -> 0 | V14: =IF(COUNTA(B14,C14,D14,E14,F14,G14,I14,M14,N14,O14,P14,R14)>0,IF(AND(COUNT(Paramètres!$C$8:$C$12)=5,COUNT(Paramètres!$C$16:$C$25)=10,ISNUMBER($C$7),B14<>"",NOT(ISNA(MATCH(C14,Paramètres!$B$29:$B$34,0))),NOT(ISNA(MATCH(E14,Paramètres!$D$29:$D$30,0))),ISNUMBER(F14),F14>0,F14<=Paramètres!$C$22,OR(I14="",AND(ISNUMBER(I14),I14>=0,I14<=Paramètres!$C$21)),IF(E14=Paramètres!$D$29,AND(D14<>"",ISNUMBER(G14),G14>0,G14<=Paramètres!$C$21,ISNUMBER(M14),ISNUMBER(N14),N14>M14,(N(N14)-N(M14))/365.25<=Paramètres!$C$23,OR(O14="",AND(ISNUMBER(O14),O14>=1,O14<=Paramètres!$C$23,O14=INT(N(O14)))),OR(P14="",AND(ISNUMBER(P14),P14>$C$7,P14<=N14)),OR(R14="",AND(ISNUMBER(R14),R14>=0,R14<=Paramètres!$C$24,R14<=(IF(OR(NOT(ISNUMBER(M14)),NOT(ISNUMBER(N14)),N14<=M14),0,MIN(12*(IF(OR(O14="",NOT(ISNUMBER(O14))),Paramètres!$C$8,O14)),(YEAR(N14)-YEAR(M14))*12+MONTH(N14)-MONTH(M14)+1)))))),AND(D14="",OR(G14="",G14=0)))),"OK","À CORRIGER"),"") -> OK | W14: =IF(NOT(COUNTA(B14,C14,D14,E14,F14,G14,I14,M14,N14,O14,P14,R14)>0),"",IF(OR(COUNT(Paramètres!$C$8:$C$12)<>5,COUNT(Paramètres!$C$16:$C$25)<>10),"Un paramètre de l'onglet Paramètres est vide.",IF(NOT(ISNUMBER($C$7)),"Date d'analyse manquante.",IF(B14="","Libellé du lot manquant.",IF(ISNA(MATCH(C14,Paramètres!$B$29:$B$34,0)),"Nature hors liste.",IF(ISNA(MATCH(E14,Paramètres!$D$29:$D$30,0)),"Statut hors liste.",IF(NOT(AND(ISNUMBER(F14),F14>0)),"Surface manquante ou nulle.",IF(F14>Paramètres!$C$22,"Surface au-delà du garde-fou de saisie.",IF(AND(I14<>"",NOT(AND(ISNUMBER(I14),I14>=0,I14<=Paramètres!$C$21))),"Valeur locative de marché hors bornes.",IF(AND(E14=Paramètres!$D$29,D14=""),"Lot déclaré loué sans locataire.",IF(AND(E14=Paramètres!$D$29,NOT(AND(ISNUMBER(G14),G14>0))),"Loyer facial manquant ou nul.",IF(AND(E14=Paramètres!$D$29,G14>Paramètres!$C$21),"Loyer facial au-delà du garde-fou de saisie.",IF(AND(E14=Paramètres!$D$29,NOT(ISNUMBER(M14))),"Date de prise d'effet manquante.",IF(AND(E14=Paramètres!$D$29,NOT(ISNUMBER(N14))),"Date d'échéance manquante.",IF(AND(E14=Paramètres!$D$29,N14<=M14),"Échéance antérieure ou égale à la prise d'effet.",IF(AND(E14=Paramètres!$D$29,(N(N14)-N(M14))/365.25>Paramètres!$C$23),"Durée du bail au-delà du garde-fou de saisie.",IF(AND(E14=Paramètres!$D$29,O14<>"",NOT(AND(ISNUMBER(O14),O14>=1,O14<=Paramètres!$C$23,O14=INT(N(O14))))),"Périodicité de sortie hors bornes.",IF(AND(E14=Paramètres!$D$29,P14<>"",NOT(AND(ISNUMBER(P14),P14>$C$7,P14<=N14))),"Sortie forcée hors de l'intervalle admis.",IF(AND(E14=Paramètres!$D$29,R14<>"",NOT(AND(ISNUMBER(R14),R14>=0,R14<=Paramètres!$C$24,R14<=(IF(OR(NOT(ISNUMBER(M14)),NOT(ISNUMBER(N14)),N14<=M14),0,MIN(12*(IF(OR(O14="",NOT(ISNUMBER(O14))),Paramètres!$C$8,O14)),(YEAR(N14)-YEAR(M14))*12+MONTH(N14)-MONTH(M14)+1)))))),"Franchise hors bornes ou plus longue que la période ferme.",IF(AND(E14=Paramètres!$D$30,D14<>""),"Lot vacant avec un locataire renseigné.",IF(AND(E14=Paramètres!$D$30,G14<>"",G14<>0),"Lot vacant avec un loyer renseigné.",IF(AND(E14=Paramètres!$D$29,ISNUMBER(N14),ISNUMBER($C$7),N14<$C$7),"Bail échu, en tacite prolongation.",IF(I14="","Valeur locative de marché non renseignée.",""))))))))))))))))))))))) | X14: =IF(AND(V14="OK",E14=Paramètres!$D$29),SUMIFS($H$11:$H$50,$D$11:$D$50,D14,$E$11:$E$50,Paramètres!$D$29,$V$11:$V$50,"OK"),0) -> 0
B15: R+2 Plateau C | C15: Bureaux | D15: Locataire Delta | E15: Loué | F15: 400 | G15: 268 | H15: =IF(AND(ISNUMBER(F15),ISNUMBER(G15)),F15*G15,0) -> 107200 | I15: 300 | J15: =IF(AND(ISNUMBER(F15),ISNUMBER(I15)),F15*I15,0) -> 120000 | K15: =IF(OR(H15<=0,J15<=0),"",J15-H15) -> 12800 | L15: =IF(OR(H15<=0,J15<=0),"",J15/H15-1) -> 0.11940299 | M15: 45383 | N15: 48669 | O15: 6 | Q15: =IF(OR(NOT(ISNUMBER($C$7)),NOT(ISNUMBER(M15)),NOT(ISNUMBER(N15))),"",IF(ISNUMBER(P15),P15,IF((IF(OR(O15="",NOT(ISNUMBER(O15))),Paramètres!$C$8,O15))<=0,"",MIN(EDATE(M15,(12*(IF(OR(O15="",NOT(ISNUMBER(O15))),Paramètres!$C$8,O15)))*MAX(1,INT(((YEAR($C$7+1)-YEAR(M15))*12+MONTH($C$7+1)-MONTH(M15)-(DAY($C$7+1)<DAY(M15)))/(12*(IF(OR(O15="",NOT(ISNUMBER(O15))),Paramètres!$C$8,O15))))+1))-1,N15)))) -> 47573 | R15: 6 | S15: =IF(H15=0,0,IF(OR(R15="",R15=0),H15,IF(OR(NOT(ISNUMBER(R15)),(IF(OR(NOT(ISNUMBER(M15)),NOT(ISNUMBER(N15)),N15<=M15),0,MIN(12*(IF(OR(O15="",NOT(ISNUMBER(O15))),Paramètres!$C$8,O15)),(YEAR(N15)-YEAR(M15))*12+MONTH(N15)-MONTH(M15)+1)))<=0),0,MAX(0,H15*(1-R15/(IF(OR(NOT(ISNUMBER(M15)),NOT(ISNUMBER(N15)),N15<=M15),0,MIN(12*(IF(OR(O15="",NOT(ISNUMBER(O15))),Paramètres!$C$8,O15)),(YEAR(N15)-YEAR(M15))*12+MONTH(N15)-MONTH(M15)+1)))))))) -> 98266.667 | T15: =IF(AND(ISNUMBER(N15),ISNUMBER($C$7)),MAX(0,(N15-$C$7)/365.25),0) -> 6.75154 | U15: =IF(AND(ISNUMBER(Q15),ISNUMBER($C$7)),MAX(0,(Q15-$C$7)/365.25),0) -> 3.7508556 | V15: =IF(COUNTA(B15,C15,D15,E15,F15,G15,I15,M15,N15,O15,P15,R15)>0,IF(AND(COUNT(Paramètres!$C$8:$C$12)=5,COUNT(Paramètres!$C$16:$C$25)=10,ISNUMBER($C$7),B15<>"",NOT(ISNA(MATCH(C15,Paramètres!$B$29:$B$34,0))),NOT(ISNA(MATCH(E15,Paramètres!$D$29:$D$30,0))),ISNUMBER(F15),F15>0,F15<=Paramètres!$C$22,OR(I15="",AND(ISNUMBER(I15),I15>=0,I15<=Paramètres!$C$21)),IF(E15=Paramètres!$D$29,AND(D15<>"",ISNUMBER(G15),G15>0,G15<=Paramètres!$C$21,ISNUMBER(M15),ISNUMBER(N15),N15>M15,(N(N15)-N(M15))/365.25<=Paramètres!$C$23,OR(O15="",AND(ISNUMBER(O15),O15>=1,O15<=Paramètres!$C$23,O15=INT(N(O15)))),OR(P15="",AND(ISNUMBER(P15),P15>$C$7,P15<=N15)),OR(R15="",AND(ISNUMBER(R15),R15>=0,R15<=Paramètres!$C$24,R15<=(IF(OR(NOT(ISNUMBER(M15)),NOT(ISNUMBER(N15)),N15<=M15),0,MIN(12*(IF(OR(O15="",NOT(ISNUMBER(O15))),Paramètres!$C$8,O15)),(YEAR(N15)-YEAR(M15))*12+MONTH(N15)-MONTH(M15)+1)))))),AND(D15="",OR(G15="",G15=0)))),"OK","À CORRIGER"),"") -> OK | W15: =IF(NOT(COUNTA(B15,C15,D15,E15,F15,G15,I15,M15,N15,O15,P15,R15)>0),"",IF(OR(COUNT(Paramètres!$C$8:$C$12)<>5,COUNT(Paramètres!$C$16:$C$25)<>10),"Un paramètre de l'onglet Paramètres est vide.",IF(NOT(ISNUMBER($C$7)),"Date d'analyse manquante.",IF(B15="","Libellé du lot manquant.",IF(ISNA(MATCH(C15,Paramètres!$B$29:$B$34,0)),"Nature hors liste.",IF(ISNA(MATCH(E15,Paramètres!$D$29:$D$30,0)),"Statut hors liste.",IF(NOT(AND(ISNUMBER(F15),F15>0)),"Surface manquante ou nulle.",IF(F15>Paramètres!$C$22,"Surface au-delà du garde-fou de saisie.",IF(AND(I15<>"",NOT(AND(ISNUMBER(I15),I15>=0,I15<=Paramètres!$C$21))),"Valeur locative de marché hors bornes.",IF(AND(E15=Paramètres!$D$29,D15=""),"Lot déclaré loué sans locataire.",IF(AND(E15=Paramètres!$D$29,NOT(AND(ISNUMBER(G15),G15>0))),"Loyer facial manquant ou nul.",IF(AND(E15=Paramètres!$D$29,G15>Paramètres!$C$21),"Loyer facial au-delà du garde-fou de saisie.",IF(AND(E15=Paramètres!$D$29,NOT(ISNUMBER(M15))),"Date de prise d'effet manquante.",IF(AND(E15=Paramètres!$D$29,NOT(ISNUMBER(N15))),"Date d'échéance manquante.",IF(AND(E15=Paramètres!$D$29,N15<=M15),"Échéance antérieure ou égale à la prise d'effet.",IF(AND(E15=Paramètres!$D$29,(N(N15)-N(M15))/365.25>Paramètres!$C$23),"Durée du bail au-delà du garde-fou de saisie.",IF(AND(E15=Paramètres!$D$29,O15<>"",NOT(AND(ISNUMBER(O15),O15>=1,O15<=Paramètres!$C$23,O15=INT(N(O15))))),"Périodicité de sortie hors bornes.",IF(AND(E15=Paramètres!$D$29,P15<>"",NOT(AND(ISNUMBER(P15),P15>$C$7,P15<=N15))),"Sortie forcée hors de l'intervalle admis.",IF(AND(E15=Paramètres!$D$29,R15<>"",NOT(AND(ISNUMBER(R15),R15>=0,R15<=Paramètres!$C$24,R15<=(IF(OR(NOT(ISNUMBER(M15)),NOT(ISNUMBER(N15)),N15<=M15),0,MIN(12*(IF(OR(O15="",NOT(ISNUMBER(O15))),Paramètres!$C$8,O15)),(YEAR(N15)-YEAR(M15))*12+MONTH(N15)-MONTH(M15)+1)))))),"Franchise hors bornes ou plus longue que la période ferme.",IF(AND(E15=Paramètres!$D$30,D15<>""),"Lot vacant avec un locataire renseigné.",IF(AND(E15=Paramètres!$D$30,G15<>"",G15<>0),"Lot vacant avec un loyer renseigné.",IF(AND(E15=Paramètres!$D$29,ISNUMBER(N15),ISNUMBER($C$7),N15<$C$7),"Bail échu, en tacite prolongation.",IF(I15="","Valeur locative de marché non renseignée.",""))))))))))))))))))))))) | X15: =IF(AND(V15="OK",E15=Paramètres!$D$29),SUMIFS($H$11:$H$50,$D$11:$D$50,D15,$E$11:$E$50,Paramètres!$D$29,$V$11:$V$50,"OK"),0) -> 107200
B16: R+2 Plateau D | C16: Bureaux | D16: Locataire Alpha | E16: Loué | F16: 210 | G16: 278 | H16: =IF(AND(ISNUMBER(F16),ISNUMBER(G16)),F16*G16,0) -> 58380 | I16: 300 | J16: =IF(AND(ISNUMBER(F16),ISNUMBER(I16)),F16*I16,0) -> 63000 | K16: =IF(OR(H16<=0,J16<=0),"",J16-H16) -> 4620 | L16: =IF(OR(H16<=0,J16<=0),"",J16/H16-1) -> 0.079136691 | M16: 45108 | N16: 48395 | Q16: =IF(OR(NOT(ISNUMBER($C$7)),NOT(ISNUMBER(M16)),NOT(ISNUMBER(N16))),"",IF(ISNUMBER(P16),P16,IF((IF(OR(O16="",NOT(ISNUMBER(O16))),Paramètres!$C$8,O16))<=0,"",MIN(EDATE(M16,(12*(IF(OR(O16="",NOT(ISNUMBER(O16))),Paramètres!$C$8,O16)))*MAX(1,INT(((YEAR($C$7+1)-YEAR(M16))*12+MONTH($C$7+1)-MONTH(M16)-(DAY($C$7+1)<DAY(M16)))/(12*(IF(OR(O16="",NOT(ISNUMBER(O16))),Paramètres!$C$8,O16))))+1))-1,N16)))) -> 47299 | R16: 3 | S16: =IF(H16=0,0,IF(OR(R16="",R16=0),H16,IF(OR(NOT(ISNUMBER(R16)),(IF(OR(NOT(ISNUMBER(M16)),NOT(ISNUMBER(N16)),N16<=M16),0,MIN(12*(IF(OR(O16="",NOT(ISNUMBER(O16))),Paramètres!$C$8,O16)),(YEAR(N16)-YEAR(M16))*12+MONTH(N16)-MONTH(M16)+1)))<=0),0,MAX(0,H16*(1-R16/(IF(OR(NOT(ISNUMBER(M16)),NOT(ISNUMBER(N16)),N16<=M16),0,MIN(12*(IF(OR(O16="",NOT(ISNUMBER(O16))),Paramètres!$C$8,O16)),(YEAR(N16)-YEAR(M16))*12+MONTH(N16)-MONTH(M16)+1)))))))) -> 53515 | T16: =IF(AND(ISNUMBER(N16),ISNUMBER($C$7)),MAX(0,(N16-$C$7)/365.25),0) -> 6.0013689 | U16: =IF(AND(ISNUMBER(Q16),ISNUMBER($C$7)),MAX(0,(Q16-$C$7)/365.25),0) -> 3.0006845 | V16: =IF(COUNTA(B16,C16,D16,E16,F16,G16,I16,M16,N16,O16,P16,R16)>0,IF(AND(COUNT(Paramètres!$C$8:$C$12)=5,COUNT(Paramètres!$C$16:$C$25)=10,ISNUMBER($C$7),B16<>"",NOT(ISNA(MATCH(C16,Paramètres!$B$29:$B$34,0))),NOT(ISNA(MATCH(E16,Paramètres!$D$29:$D$30,0))),ISNUMBER(F16),F16>0,F16<=Paramètres!$C$22,OR(I16="",AND(ISNUMBER(I16),I16>=0,I16<=Paramètres!$C$21)),IF(E16=Paramètres!$D$29,AND(D16<>"",ISNUMBER(G16),G16>0,G16<=Paramètres!$C$21,ISNUMBER(M16),ISNUMBER(N16),N16>M16,(N(N16)-N(M16))/365.25<=Paramètres!$C$23,OR(O16="",AND(ISNUMBER(O16),O16>=1,O16<=Paramètres!$C$23,O16=INT(N(O16)))),OR(P16="",AND(ISNUMBER(P16),P16>$C$7,P16<=N16)),OR(R16="",AND(ISNUMBER(R16),R16>=0,R16<=Paramètres!$C$24,R16<=(IF(OR(NOT(ISNUMBER(M16)),NOT(ISNUMBER(N16)),N16<=M16),0,MIN(12*(IF(OR(O16="",NOT(ISNUMBER(O16))),Paramètres!$C$8,O16)),(YEAR(N16)-YEAR(M16))*12+MONTH(N16)-MONTH(M16)+1)))))),AND(D16="",OR(G16="",G16=0)))),"OK","À CORRIGER"),"") -> OK | W16: =IF(NOT(COUNTA(B16,C16,D16,E16,F16,G16,I16,M16,N16,O16,P16,R16)>0),"",IF(OR(COUNT(Paramètres!$C$8:$C$12)<>5,COUNT(Paramètres!$C$16:$C$25)<>10),"Un paramètre de l'onglet Paramètres est vide.",IF(NOT(ISNUMBER($C$7)),"Date d'analyse manquante.",IF(B16="","Libellé du lot manquant.",IF(ISNA(MATCH(C16,Paramètres!$B$29:$B$34,0)),"Nature hors liste.",IF(ISNA(MATCH(E16,Paramètres!$D$29:$D$30,0)),"Statut hors liste.",IF(NOT(AND(ISNUMBER(F16),F16>0)),"Surface manquante ou nulle.",IF(F16>Paramètres!$C$22,"Surface au-delà du garde-fou de saisie.",IF(AND(I16<>"",NOT(AND(ISNUMBER(I16),I16>=0,I16<=Paramètres!$C$21))),"Valeur locative de marché hors bornes.",IF(AND(E16=Paramètres!$D$29,D16=""),"Lot déclaré loué sans locataire.",IF(AND(E16=Paramètres!$D$29,NOT(AND(ISNUMBER(G16),G16>0))),"Loyer facial manquant ou nul.",IF(AND(E16=Paramètres!$D$29,G16>Paramètres!$C$21),"Loyer facial au-delà du garde-fou de saisie.",IF(AND(E16=Paramètres!$D$29,NOT(ISNUMBER(M16))),"Date de prise d'effet manquante.",IF(AND(E16=Paramètres!$D$29,NOT(ISNUMBER(N16))),"Date d'échéance manquante.",IF(AND(E16=Paramètres!$D$29,N16<=M16),"Échéance antérieure ou égale à la prise d'effet.",IF(AND(E16=Paramètres!$D$29,(N(N16)-N(M16))/365.25>Paramètres!$C$23),"Durée du bail au-delà du garde-fou de saisie.",IF(AND(E16=Paramètres!$D$29,O16<>"",NOT(AND(ISNUMBER(O16),O16>=1,O16<=Paramètres!$C$23,O16=INT(N(O16))))),"Périodicité de sortie hors bornes.",IF(AND(E16=Paramètres!$D$29,P16<>"",NOT(AND(ISNUMBER(P16),P16>$C$7,P16<=N16))),"Sortie forcée hors de l'intervalle admis.",IF(AND(E16=Paramètres!$D$29,R16<>"",NOT(AND(ISNUMBER(R16),R16>=0,R16<=Paramètres!$C$24,R16<=(IF(OR(NOT(ISNUMBER(M16)),NOT(ISNUMBER(N16)),N16<=M16),0,MIN(12*(IF(OR(O16="",NOT(ISNUMBER(O16))),Paramètres!$C$8,O16)),(YEAR(N16)-YEAR(M16))*12+MONTH(N16)-MONTH(M16)+1)))))),"Franchise hors bornes ou plus longue que la période ferme.",IF(AND(E16=Paramètres!$D$30,D16<>""),"Lot vacant avec un locataire renseigné.",IF(AND(E16=Paramètres!$D$30,G16<>"",G16<>0),"Lot vacant avec un loyer renseigné.",IF(AND(E16=Paramètres!$D$29,ISNUMBER(N16),ISNUMBER($C$7),N16<$C$7),"Bail échu, en tacite prolongation.",IF(I16="","Valeur locative de marché non renseignée.",""))))))))))))))))))))))) | X16: =IF(AND(V16="OK",E16=Paramètres!$D$29),SUMIFS($H$11:$H$50,$D$11:$D$50,D16,$E$11:$E$50,Paramètres!$D$29,$V$11:$V$50,"OK"),0) -> 178080
B17: RDC Local 3 | C17: Commerce | D17: Locataire Epsilon | E17: Loué | F17: 140 | G17: 390 | H17: =IF(AND(ISNUMBER(F17),ISNUMBER(G17)),F17*G17,0) -> 54600 | I17: 400 | J17: =IF(AND(ISNUMBER(F17),ISNUMBER(I17)),F17*I17,0) -> 56000 | K17: =IF(OR(H17<=0,J17<=0),"",J17-H17) -> 1400 | L17: =IF(OR(H17<=0,J17<=0),"",J17/H17-1) -> 0.025641026 | M17: 43009 | N17: 46295 | Q17: =IF(OR(NOT(ISNUMBER($C$7)),NOT(ISNUMBER(M17)),NOT(ISNUMBER(N17))),"",IF(ISNUMBER(P17),P17,IF((IF(OR(O17="",NOT(ISNUMBER(O17))),Paramètres!$C$8,O17))<=0,"",MIN(EDATE(M17,(12*(IF(OR(O17="",NOT(ISNUMBER(O17))),Paramètres!$C$8,O17)))*MAX(1,INT(((YEAR($C$7+1)-YEAR(M17))*12+MONTH($C$7+1)-MONTH(M17)-(DAY($C$7+1)<DAY(M17)))/(12*(IF(OR(O17="",NOT(ISNUMBER(O17))),Paramètres!$C$8,O17))))+1))-1,N17)))) -> 46295 | S17: =IF(H17=0,0,IF(OR(R17="",R17=0),H17,IF(OR(NOT(ISNUMBER(R17)),(IF(OR(NOT(ISNUMBER(M17)),NOT(ISNUMBER(N17)),N17<=M17),0,MIN(12*(IF(OR(O17="",NOT(ISNUMBER(O17))),Paramètres!$C$8,O17)),(YEAR(N17)-YEAR(M17))*12+MONTH(N17)-MONTH(M17)+1)))<=0),0,MAX(0,H17*(1-R17/(IF(OR(NOT(ISNUMBER(M17)),NOT(ISNUMBER(N17)),N17<=M17),0,MIN(12*(IF(OR(O17="",NOT(ISNUMBER(O17))),Paramètres!$C$8,O17)),(YEAR(N17)-YEAR(M17))*12+MONTH(N17)-MONTH(M17)+1)))))))) -> 54600 | T17: =IF(AND(ISNUMBER(N17),ISNUMBER($C$7)),MAX(0,(N17-$C$7)/365.25),0) -> 0.25188227 | U17: =IF(AND(ISNUMBER(Q17),ISNUMBER($C$7)),MAX(0,(Q17-$C$7)/365.25),0) -> 0.25188227 | V17: =IF(COUNTA(B17,C17,D17,E17,F17,G17,I17,M17,N17,O17,P17,R17)>0,IF(AND(COUNT(Paramètres!$C$8:$C$12)=5,COUNT(Paramètres!$C$16:$C$25)=10,ISNUMBER($C$7),B17<>"",NOT(ISNA(MATCH(C17,Paramètres!$B$29:$B$34,0))),NOT(ISNA(MATCH(E17,Paramètres!$D$29:$D$30,0))),ISNUMBER(F17),F17>0,F17<=Paramètres!$C$22,OR(I17="",AND(ISNUMBER(I17),I17>=0,I17<=Paramètres!$C$21)),IF(E17=Paramètres!$D$29,AND(D17<>"",ISNUMBER(G17),G17>0,G17<=Paramètres!$C$21,ISNUMBER(M17),ISNUMBER(N17),N17>M17,(N(N17)-N(M17))/365.25<=Paramètres!$C$23,OR(O17="",AND(ISNUMBER(O17),O17>=1,O17<=Paramètres!$C$23,O17=INT(N(O17)))),OR(P17="",AND(ISNUMBER(P17),P17>$C$7,P17<=N17)),OR(R17="",AND(ISNUMBER(R17),R17>=0,R17<=Paramètres!$C$24,R17<=(IF(OR(NOT(ISNUMBER(M17)),NOT(ISNUMBER(N17)),N17<=M17),0,MIN(12*(IF(OR(O17="",NOT(ISNUMBER(O17))),Paramètres!$C$8,O17)),(YEAR(N17)-YEAR(M17))*12+MONTH(N17)-MONTH(M17)+1)))))),AND(D17="",OR(G17="",G17=0)))),"OK","À CORRIGER"),"") -> OK | W17: =IF(NOT(COUNTA(B17,C17,D17,E17,F17,G17,I17,M17,N17,O17,P17,R17)>0),"",IF(OR(COUNT(Paramètres!$C$8:$C$12)<>5,COUNT(Paramètres!$C$16:$C$25)<>10),"Un paramètre de l'onglet Paramètres est vide.",IF(NOT(ISNUMBER($C$7)),"Date d'analyse manquante.",IF(B17="","Libellé du lot manquant.",IF(ISNA(MATCH(C17,Paramètres!$B$29:$B$34,0)),"Nature hors liste.",IF(ISNA(MATCH(E17,Paramètres!$D$29:$D$30,0)),"Statut hors liste.",IF(NOT(AND(ISNUMBER(F17),F17>0)),"Surface manquante ou nulle.",IF(F17>Paramètres!$C$22,"Surface au-delà du garde-fou de saisie.",IF(AND(I17<>"",NOT(AND(ISNUMBER(I17),I17>=0,I17<=Paramètres!$C$21))),"Valeur locative de marché hors bornes.",IF(AND(E17=Paramètres!$D$29,D17=""),"Lot déclaré loué sans locataire.",IF(AND(E17=Paramètres!$D$29,NOT(AND(ISNUMBER(G17),G17>0))),"Loyer facial manquant ou nul.",IF(AND(E17=Paramètres!$D$29,G17>Paramètres!$C$21),"Loyer facial au-delà du garde-fou de saisie.",IF(AND(E17=Paramètres!$D$29,NOT(ISNUMBER(M17))),"Date de prise d'effet manquante.",IF(AND(E17=Paramètres!$D$29,NOT(ISNUMBER(N17))),"Date d'échéance manquante.",IF(AND(E17=Paramètres!$D$29,N17<=M17),"Échéance antérieure ou égale à la prise d'effet.",IF(AND(E17=Paramètres!$D$29,(N(N17)-N(M17))/365.25>Paramètres!$C$23),"Durée du bail au-delà du garde-fou de saisie.",IF(AND(E17=Paramètres!$D$29,O17<>"",NOT(AND(ISNUMBER(O17),O17>=1,O17<=Paramètres!$C$23,O17=INT(N(O17))))),"Périodicité de sortie hors bornes.",IF(AND(E17=Paramètres!$D$29,P17<>"",NOT(AND(ISNUMBER(P17),P17>$C$7,P17<=N17))),"Sortie forcée hors de l'intervalle admis.",IF(AND(E17=Paramètres!$D$29,R17<>"",NOT(AND(ISNUMBER(R17),R17>=0,R17<=Paramètres!$C$24,R17<=(IF(OR(NOT(ISNUMBER(M17)),NOT(ISNUMBER(N17)),N17<=M17),0,MIN(12*(IF(OR(O17="",NOT(ISNUMBER(O17))),Paramètres!$C$8,O17)),(YEAR(N17)-YEAR(M17))*12+MONTH(N17)-MONTH(M17)+1)))))),"Franchise hors bornes ou plus longue que la période ferme.",IF(AND(E17=Paramètres!$D$30,D17<>""),"Lot vacant avec un locataire renseigné.",IF(AND(E17=Paramètres!$D$30,G17<>"",G17<>0),"Lot vacant avec un loyer renseigné.",IF(AND(E17=Paramètres!$D$29,ISNUMBER(N17),ISNUMBER($C$7),N17<$C$7),"Bail échu, en tacite prolongation.",IF(I17="","Valeur locative de marché non renseignée.",""))))))))))))))))))))))) | X17: =IF(AND(V17="OK",E17=Paramètres!$D$29),SUMIFS($H$11:$H$50,$D$11:$D$50,D17,$E$11:$E$50,Paramètres!$D$29,$V$11:$V$50,"OK"),0) -> 54600
H18: =IF(AND(ISNUMBER(F18),ISNUMBER(G18)),F18*G18,0) -> 0 | J18: =IF(AND(ISNUMBER(F18),ISNUMBER(I18)),F18*I18,0) -> 0 | K18: =IF(OR(H18<=0,J18<=0),"",J18-H18) | L18: =IF(OR(H18<=0,J18<=0),"",J18/H18-1) | Q18: =IF(OR(NOT(ISNUMBER($C$7)),NOT(ISNUMBER(M18)),NOT(ISNUMBER(N18))),"",IF(ISNUMBER(P18),P18,IF((IF(OR(O18="",NOT(ISNUMBER(O18))),Paramètres!$C$8,O18))<=0,"",MIN(EDATE(M18,(12*(IF(OR(O18="",NOT(ISNUMBER(O18))),Paramètres!$C$8,O18)))*MAX(1,INT(((YEAR($C$7+1)-YEAR(M18))*12+MONTH($C$7+1)-MONTH(M18)-(DAY($C$7+1)<DAY(M18)))/(12*(IF(OR(O18="",NOT(ISNUMBER(O18))),Paramètres!$C$8,O18))))+1))-1,N18)))) | S18: =IF(H18=0,0,IF(OR(R18="",R18=0),H18,IF(OR(NOT(ISNUMBER(R18)),(IF(OR(NOT(ISNUMBER(M18)),NOT(ISNUMBER(N18)),N18<=M18),0,MIN(12*(IF(OR(O18="",NOT(ISNUMBER(O18))),Paramètres!$C$8,O18)),(YEAR(N18)-YEAR(M18))*12+MONTH(N18)-MONTH(M18)+1)))<=0),0,MAX(0,H18*(1-R18/(IF(OR(NOT(ISNUMBER(M18)),NOT(ISNUMBER(N18)),N18<=M18),0,MIN(12*(IF(OR(O18="",NOT(ISNUMBER(O18))),Paramètres!$C$8,O18)),(YEAR(N18)-YEAR(M18))*12+MONTH(N18)-MONTH(M18)+1)))))))) -> 0 | T18: =IF(AND(ISNUMBER(N18),ISNUMBER($C$7)),MAX(0,(N18-$C$7)/365.25),0) -> 0 | U18: =IF(AND(ISNUMBER(Q18),ISNUMBER($C$7)),MAX(0,(Q18-$C$7)/365.25),0) -> 0 | V18: =IF(COUNTA(B18,C18,D18,E18,F18,G18,I18,M18,N18,O18,P18,R18)>0,IF(AND(COUNT(Paramètres!$C$8:$C$12)=5,COUNT(Paramètres!$C$16:$C$25)=10,ISNUMBER($C$7),B18<>"",NOT(ISNA(MATCH(C18,Paramètres!$B$29:$B$34,0))),NOT(ISNA(MATCH(E18,Paramètres!$D$29:$D$30,0))),ISNUMBER(F18),F18>0,F18<=Paramètres!$C$22,OR(I18="",AND(ISNUMBER(I18),I18>=0,I18<=Paramètres!$C$21)),IF(E18=Paramètres!$D$29,AND(D18<>"",ISNUMBER(G18),G18>0,G18<=Paramètres!$C$21,ISNUMBER(M18),ISNUMBER(N18),N18>M18,(N(N18)-N(M18))/365.25<=Paramètres!$C$23,OR(O18="",AND(ISNUMBER(O18),O18>=1,O18<=Paramètres!$C$23,O18=INT(N(O18)))),OR(P18="",AND(ISNUMBER(P18),P18>$C$7,P18<=N18)),OR(R18="",AND(ISNUMBER(R18),R18>=0,R18<=Paramètres!$C$24,R18<=(IF(OR(NOT(ISNUMBER(M18)),NOT(ISNUMBER(N18)),N18<=M18),0,MIN(12*(IF(OR(O18="",NOT(ISNUMBER(O18))),Paramètres!$C$8,O18)),(YEAR(N18)-YEAR(M18))*12+MONTH(N18)-MONTH(M18)+1)))))),AND(D18="",OR(G18="",G18=0)))),"OK","À CORRIGER"),"") | W18: =IF(NOT(COUNTA(B18,C18,D18,E18,F18,G18,I18,M18,N18,O18,P18,R18)>0),"",IF(OR(COUNT(Paramètres!$C$8:$C$12)<>5,COUNT(Paramètres!$C$16:$C$25)<>10),"Un paramètre de l'onglet Paramètres est vide.",IF(NOT(ISNUMBER($C$7)),"Date d'analyse manquante.",IF(B18="","Libellé du lot manquant.",IF(ISNA(MATCH(C18,Paramètres!$B$29:$B$34,0)),"Nature hors liste.",IF(ISNA(MATCH(E18,Paramètres!$D$29:$D$30,0)),"Statut hors liste.",IF(NOT(AND(ISNUMBER(F18),F18>0)),"Surface manquante ou nulle.",IF(F18>Paramètres!$C$22,"Surface au-delà du garde-fou de saisie.",IF(AND(I18<>"",NOT(AND(ISNUMBER(I18),I18>=0,I18<=Paramètres!$C$21))),"Valeur locative de marché hors bornes.",IF(AND(E18=Paramètres!$D$29,D18=""),"Lot déclaré loué sans locataire.",IF(AND(E18=Paramètres!$D$29,NOT(AND(ISNUMBER(G18),G18>0))),"Loyer facial manquant ou nul.",IF(AND(E18=Paramètres!$D$29,G18>Paramètres!$C$21),"Loyer facial au-delà du garde-fou de saisie.",IF(AND(E18=Paramètres!$D$29,NOT(ISNUMBER(M18))),"Date de prise d'effet manquante.",IF(AND(E18=Paramètres!$D$29,NOT(ISNUMBER(N18))),"Date d'échéance manquante.",IF(AND(E18=Paramètres!$D$29,N18<=M18),"Échéance antérieure ou égale à la prise d'effet.",IF(AND(E18=Paramètres!$D$29,(N(N18)-N(M18))/365.25>Paramètres!$C$23),"Durée du bail au-delà du garde-fou de saisie.",IF(AND(E18=Paramètres!$D$29,O18<>"",NOT(AND(ISNUMBER(O18),O18>=1,O18<=Paramètres!$C$23,O18=INT(N(O18))))),"Périodicité de sortie hors bornes.",IF(AND(E18=Paramètres!$D$29,P18<>"",NOT(AND(ISNUMBER(P18),P18>$C$7,P18<=N18))),"Sortie forcée hors de l'intervalle admis.",IF(AND(E18=Paramètres!$D$29,R18<>"",NOT(AND(ISNUMBER(R18),R18>=0,R18<=Paramètres!$C$24,R18<=(IF(OR(NOT(ISNUMBER(M18)),NOT(ISNUMBER(N18)),N18<=M18),0,MIN(12*(IF(OR(O18="",NOT(ISNUMBER(O18))),Paramètres!$C$8,O18)),(YEAR(N18)-YEAR(M18))*12+MONTH(N18)-MONTH(M18)+1)))))),"Franchise hors bornes ou plus longue que la période ferme.",IF(AND(E18=Paramètres!$D$30,D18<>""),"Lot vacant avec un locataire renseigné.",IF(AND(E18=Paramètres!$D$30,G18<>"",G18<>0),"Lot vacant avec un loyer renseigné.",IF(AND(E18=Paramètres!$D$29,ISNUMBER(N18),ISNUMBER($C$7),N18<$C$7),"Bail échu, en tacite prolongation.",IF(I18="","Valeur locative de marché non renseignée.",""))))))))))))))))))))))) | X18: =IF(AND(V18="OK",E18=Paramètres!$D$29),SUMIFS($H$11:$H$50,$D$11:$D$50,D18,$E$11:$E$50,Paramètres!$D$29,$V$11:$V$50,"OK"),0) -> 0
H19: =IF(AND(ISNUMBER(F19),ISNUMBER(G19)),F19*G19,0) -> 0 | J19: =IF(AND(ISNUMBER(F19),ISNUMBER(I19)),F19*I19,0) -> 0 | K19: =IF(OR(H19<=0,J19<=0),"",J19-H19) | L19: =IF(OR(H19<=0,J19<=0),"",J19/H19-1) | Q19: =IF(OR(NOT(ISNUMBER($C$7)),NOT(ISNUMBER(M19)),NOT(ISNUMBER(N19))),"",IF(ISNUMBER(P19),P19,IF((IF(OR(O19="",NOT(ISNUMBER(O19))),Paramètres!$C$8,O19))<=0,"",MIN(EDATE(M19,(12*(IF(OR(O19="",NOT(ISNUMBER(O19))),Paramètres!$C$8,O19)))*MAX(1,INT(((YEAR($C$7+1)-YEAR(M19))*12+MONTH($C$7+1)-MONTH(M19)-(DAY($C$7+1)<DAY(M19)))/(12*(IF(OR(O19="",NOT(ISNUMBER(O19))),Paramètres!$C$8,O19))))+1))-1,N19)))) | S19: =IF(H19=0,0,IF(OR(R19="",R19=0),H19,IF(OR(NOT(ISNUMBER(R19)),(IF(OR(NOT(ISNUMBER(M19)),NOT(ISNUMBER(N19)),N19<=M19),0,MIN(12*(IF(OR(O19="",NOT(ISNUMBER(O19))),Paramètres!$C$8,O19)),(YEAR(N19)-YEAR(M19))*12+MONTH(N19)-MONTH(M19)+1)))<=0),0,MAX(0,H19*(1-R19/(IF(OR(NOT(ISNUMBER(M19)),NOT(ISNUMBER(N19)),N19<=M19),0,MIN(12*(IF(OR(O19="",NOT(ISNUMBER(O19))),Paramètres!$C$8,O19)),(YEAR(N19)-YEAR(M19))*12+MONTH(N19)-MONTH(M19)+1)))))))) -> 0 | T19: =IF(AND(ISNUMBER(N19),ISNUMBER($C$7)),MAX(0,(N19-$C$7)/365.25),0) -> 0 | U19: =IF(AND(ISNUMBER(Q19),ISNUMBER($C$7)),MAX(0,(Q19-$C$7)/365.25),0) -> 0 | V19: =IF(COUNTA(B19,C19,D19,E19,F19,G19,I19,M19,N19,O19,P19,R19)>0,IF(AND(COUNT(Paramètres!$C$8:$C$12)=5,COUNT(Paramètres!$C$16:$C$25)=10,ISNUMBER($C$7),B19<>"",NOT(ISNA(MATCH(C19,Paramètres!$B$29:$B$34,0))),NOT(ISNA(MATCH(E19,Paramètres!$D$29:$D$30,0))),ISNUMBER(F19),F19>0,F19<=Paramètres!$C$22,OR(I19="",AND(ISNUMBER(I19),I19>=0,I19<=Paramètres!$C$21)),IF(E19=Paramètres!$D$29,AND(D19<>"",ISNUMBER(G19),G19>0,G19<=Paramètres!$C$21,ISNUMBER(M19),ISNUMBER(N19),N19>M19,(N(N19)-N(M19))/365.25<=Paramètres!$C$23,OR(O19="",AND(ISNUMBER(O19),O19>=1,O19<=Paramètres!$C$23,O19=INT(N(O19)))),OR(P19="",AND(ISNUMBER(P19),P19>$C$7,P19<=N19)),OR(R19="",AND(ISNUMBER(R19),R19>=0,R19<=Paramètres!$C$24,R19<=(IF(OR(NOT(ISNUMBER(M19)),NOT(ISNUMBER(N19)),N19<=M19),0,MIN(12*(IF(OR(O19="",NOT(ISNUMBER(O19))),Paramètres!$C$8,O19)),(YEAR(N19)-YEAR(M19))*12+MONTH(N19)-MONTH(M19)+1)))))),AND(D19="",OR(G19="",G19=0)))),"OK","À CORRIGER"),"") | W19: =IF(NOT(COUNTA(B19,C19,D19,E19,F19,G19,I19,M19,N19,O19,P19,R19)>0),"",IF(OR(COUNT(Paramètres!$C$8:$C$12)<>5,COUNT(Paramètres!$C$16:$C$25)<>10),"Un paramètre de l'onglet Paramètres est vide.",IF(NOT(ISNUMBER($C$7)),"Date d'analyse manquante.",IF(B19="","Libellé du lot manquant.",IF(ISNA(MATCH(C19,Paramètres!$B$29:$B$34,0)),"Nature hors liste.",IF(ISNA(MATCH(E19,Paramètres!$D$29:$D$30,0)),"Statut hors liste.",IF(NOT(AND(ISNUMBER(F19),F19>0)),"Surface manquante ou nulle.",IF(F19>Paramètres!$C$22,"Surface au-delà du garde-fou de saisie.",IF(AND(I19<>"",NOT(AND(ISNUMBER(I19),I19>=0,I19<=Paramètres!$C$21))),"Valeur locative de marché hors bornes.",IF(AND(E19=Paramètres!$D$29,D19=""),"Lot déclaré loué sans locataire.",IF(AND(E19=Paramètres!$D$29,NOT(AND(ISNUMBER(G19),G19>0))),"Loyer facial manquant ou nul.",IF(AND(E19=Paramètres!$D$29,G19>Paramètres!$C$21),"Loyer facial au-delà du garde-fou de saisie.",IF(AND(E19=Paramètres!$D$29,NOT(ISNUMBER(M19))),"Date de prise d'effet manquante.",IF(AND(E19=Paramètres!$D$29,NOT(ISNUMBER(N19))),"Date d'échéance manquante.",IF(AND(E19=Paramètres!$D$29,N19<=M19),"Échéance antérieure ou égale à la prise d'effet.",IF(AND(E19=Paramètres!$D$29,(N(N19)-N(M19))/365.25>Paramètres!$C$23),"Durée du bail au-delà du garde-fou de saisie.",IF(AND(E19=Paramètres!$D$29,O19<>"",NOT(AND(ISNUMBER(O19),O19>=1,O19<=Paramètres!$C$23,O19=INT(N(O19))))),"Périodicité de sortie hors bornes.",IF(AND(E19=Paramètres!$D$29,P19<>"",NOT(AND(ISNUMBER(P19),P19>$C$7,P19<=N19))),"Sortie forcée hors de l'intervalle admis.",IF(AND(E19=Paramètres!$D$29,R19<>"",NOT(AND(ISNUMBER(R19),R19>=0,R19<=Paramètres!$C$24,R19<=(IF(OR(NOT(ISNUMBER(M19)),NOT(ISNUMBER(N19)),N19<=M19),0,MIN(12*(IF(OR(O19="",NOT(ISNUMBER(O19))),Paramètres!$C$8,O19)),(YEAR(N19)-YEAR(M19))*12+MONTH(N19)-MONTH(M19)+1)))))),"Franchise hors bornes ou plus longue que la période ferme.",IF(AND(E19=Paramètres!$D$30,D19<>""),"Lot vacant avec un locataire renseigné.",IF(AND(E19=Paramètres!$D$30,G19<>"",G19<>0),"Lot vacant avec un loyer renseigné.",IF(AND(E19=Paramètres!$D$29,ISNUMBER(N19),ISNUMBER($C$7),N19<$C$7),"Bail échu, en tacite prolongation.",IF(I19="","Valeur locative de marché non renseignée.",""))))))))))))))))))))))) | X19: =IF(AND(V19="OK",E19=Paramètres!$D$29),SUMIFS($H$11:$H$50,$D$11:$D$50,D19,$E$11:$E$50,Paramètres!$D$29,$V$11:$V$50,"OK"),0) -> 0
H20: =IF(AND(ISNUMBER(F20),ISNUMBER(G20)),F20*G20,0) -> 0 | J20: =IF(AND(ISNUMBER(F20),ISNUMBER(I20)),F20*I20,0) -> 0 | K20: =IF(OR(H20<=0,J20<=0),"",J20-H20) | L20: =IF(OR(H20<=0,J20<=0),"",J20/H20-1) | Q20: =IF(OR(NOT(ISNUMBER($C$7)),NOT(ISNUMBER(M20)),NOT(ISNUMBER(N20))),"",IF(ISNUMBER(P20),P20,IF((IF(OR(O20="",NOT(ISNUMBER(O20))),Paramètres!$C$8,O20))<=0,"",MIN(EDATE(M20,(12*(IF(OR(O20="",NOT(ISNUMBER(O20))),Paramètres!$C$8,O20)))*MAX(1,INT(((YEAR($C$7+1)-YEAR(M20))*12+MONTH($C$7+1)-MONTH(M20)-(DAY($C$7+1)<DAY(M20)))/(12*(IF(OR(O20="",NOT(ISNUMBER(O20))),Paramètres!$C$8,O20))))+1))-1,N20)))) | S20: =IF(H20=0,0,IF(OR(R20="",R20=0),H20,IF(OR(NOT(ISNUMBER(R20)),(IF(OR(NOT(ISNUMBER(M20)),NOT(ISNUMBER(N20)),N20<=M20),0,MIN(12*(IF(OR(O20="",NOT(ISNUMBER(O20))),Paramètres!$C$8,O20)),(YEAR(N20)-YEAR(M20))*12+MONTH(N20)-MONTH(M20)+1)))<=0),0,MAX(0,H20*(1-R20/(IF(OR(NOT(ISNUMBER(M20)),NOT(ISNUMBER(N20)),N20<=M20),0,MIN(12*(IF(OR(O20="",NOT(ISNUMBER(O20))),Paramètres!$C$8,O20)),(YEAR(N20)-YEAR(M20))*12+MONTH(N20)-MONTH(M20)+1)))))))) -> 0 | T20: =IF(AND(ISNUMBER(N20),ISNUMBER($C$7)),MAX(0,(N20-$C$7)/365.25),0) -> 0 | U20: =IF(AND(ISNUMBER(Q20),ISNUMBER($C$7)),MAX(0,(Q20-$C$7)/365.25),0) -> 0 | V20: =IF(COUNTA(B20,C20,D20,E20,F20,G20,I20,M20,N20,O20,P20,R20)>0,IF(AND(COUNT(Paramètres!$C$8:$C$12)=5,COUNT(Paramètres!$C$16:$C$25)=10,ISNUMBER($C$7),B20<>"",NOT(ISNA(MATCH(C20,Paramètres!$B$29:$B$34,0))),NOT(ISNA(MATCH(E20,Paramètres!$D$29:$D$30,0))),ISNUMBER(F20),F20>0,F20<=Paramètres!$C$22,OR(I20="",AND(ISNUMBER(I20),I20>=0,I20<=Paramètres!$C$21)),IF(E20=Paramètres!$D$29,AND(D20<>"",ISNUMBER(G20),G20>0,G20<=Paramètres!$C$21,ISNUMBER(M20),ISNUMBER(N20),N20>M20,(N(N20)-N(M20))/365.25<=Paramètres!$C$23,OR(O20="",AND(ISNUMBER(O20),O20>=1,O20<=Paramètres!$C$23,O20=INT(N(O20)))),OR(P20="",AND(ISNUMBER(P20),P20>$C$7,P20<=N20)),OR(R20="",AND(ISNUMBER(R20),R20>=0,R20<=Paramètres!$C$24,R20<=(IF(OR(NOT(ISNUMBER(M20)),NOT(ISNUMBER(N20)),N20<=M20),0,MIN(12*(IF(OR(O20="",NOT(ISNUMBER(O20))),Paramètres!$C$8,O20)),(YEAR(N20)-YEAR(M20))*12+MONTH(N20)-MONTH(M20)+1)))))),AND(D20="",OR(G20="",G20=0)))),"OK","À CORRIGER"),"") | W20: =IF(NOT(COUNTA(B20,C20,D20,E20,F20,G20,I20,M20,N20,O20,P20,R20)>0),"",IF(OR(COUNT(Paramètres!$C$8:$C$12)<>5,COUNT(Paramètres!$C$16:$C$25)<>10),"Un paramètre de l'onglet Paramètres est vide.",IF(NOT(ISNUMBER($C$7)),"Date d'analyse manquante.",IF(B20="","Libellé du lot manquant.",IF(ISNA(MATCH(C20,Paramètres!$B$29:$B$34,0)),"Nature hors liste.",IF(ISNA(MATCH(E20,Paramètres!$D$29:$D$30,0)),"Statut hors liste.",IF(NOT(AND(ISNUMBER(F20),F20>0)),"Surface manquante ou nulle.",IF(F20>Paramètres!$C$22,"Surface au-delà du garde-fou de saisie.",IF(AND(I20<>"",NOT(AND(ISNUMBER(I20),I20>=0,I20<=Paramètres!$C$21))),"Valeur locative de marché hors bornes.",IF(AND(E20=Paramètres!$D$29,D20=""),"Lot déclaré loué sans locataire.",IF(AND(E20=Paramètres!$D$29,NOT(AND(ISNUMBER(G20),G20>0))),"Loyer facial manquant ou nul.",IF(AND(E20=Paramètres!$D$29,G20>Paramètres!$C$21),"Loyer facial au-delà du garde-fou de saisie.",IF(AND(E20=Paramètres!$D$29,NOT(ISNUMBER(M20))),"Date de prise d'effet manquante.",IF(AND(E20=Paramètres!$D$29,NOT(ISNUMBER(N20))),"Date d'échéance manquante.",IF(AND(E20=Paramètres!$D$29,N20<=M20),"Échéance antérieure ou égale à la prise d'effet.",IF(AND(E20=Paramètres!$D$29,(N(N20)-N(M20))/365.25>Paramètres!$C$23),"Durée du bail au-delà du garde-fou de saisie.",IF(AND(E20=Paramètres!$D$29,O20<>"",NOT(AND(ISNUMBER(O20),O20>=1,O20<=Paramètres!$C$23,O20=INT(N(O20))))),"Périodicité de sortie hors bornes.",IF(AND(E20=Paramètres!$D$29,P20<>"",NOT(AND(ISNUMBER(P20),P20>$C$7,P20<=N20))),"Sortie forcée hors de l'intervalle admis.",IF(AND(E20=Paramètres!$D$29,R20<>"",NOT(AND(ISNUMBER(R20),R20>=0,R20<=Paramètres!$C$24,R20<=(IF(OR(NOT(ISNUMBER(M20)),NOT(ISNUMBER(N20)),N20<=M20),0,MIN(12*(IF(OR(O20="",NOT(ISNUMBER(O20))),Paramètres!$C$8,O20)),(YEAR(N20)-YEAR(M20))*12+MONTH(N20)-MONTH(M20)+1)))))),"Franchise hors bornes ou plus longue que la période ferme.",IF(AND(E20=Paramètres!$D$30,D20<>""),"Lot vacant avec un locataire renseigné.",IF(AND(E20=Paramètres!$D$30,G20<>"",G20<>0),"Lot vacant avec un loyer renseigné.",IF(AND(E20=Paramètres!$D$29,ISNUMBER(N20),ISNUMBER($C$7),N20<$C$7),"Bail échu, en tacite prolongation.",IF(I20="","Valeur locative de marché non renseignée.",""))))))))))))))))))))))) | X20: =IF(AND(V20="OK",E20=Paramètres!$D$29),SUMIFS($H$11:$H$50,$D$11:$D$50,D20,$E$11:$E$50,Paramètres!$D$29,$V$11:$V$50,"OK"),0) -> 0
H21: =IF(AND(ISNUMBER(F21),ISNUMBER(G21)),F21*G21,0) -> 0 | J21: =IF(AND(ISNUMBER(F21),ISNUMBER(I21)),F21*I21,0) -> 0 | K21: =IF(OR(H21<=0,J21<=0),"",J21-H21) | L21: =IF(OR(H21<=0,J21<=0),"",J21/H21-1) | Q21: =IF(OR(NOT(ISNUMBER($C$7)),NOT(ISNUMBER(M21)),NOT(ISNUMBER(N21))),"",IF(ISNUMBER(P21),P21,IF((IF(OR(O21="",NOT(ISNUMBER(O21))),Paramètres!$C$8,O21))<=0,"",MIN(EDATE(M21,(12*(IF(OR(O21="",NOT(ISNUMBER(O21))),Paramètres!$C$8,O21)))*MAX(1,INT(((YEAR($C$7+1)-YEAR(M21))*12+MONTH($C$7+1)-MONTH(M21)-(DAY($C$7+1)<DAY(M21)))/(12*(IF(OR(O21="",NOT(ISNUMBER(O21))),Paramètres!$C$8,O21))))+1))-1,N21)))) | S21: =IF(H21=0,0,IF(OR(R21="",R21=0),H21,IF(OR(NOT(ISNUMBER(R21)),(IF(OR(NOT(ISNUMBER(M21)),NOT(ISNUMBER(N21)),N21<=M21),0,MIN(12*(IF(OR(O21="",NOT(ISNUMBER(O21))),Paramètres!$C$8,O21)),(YEAR(N21)-YEAR(M21))*12+MONTH(N21)-MONTH(M21)+1)))<=0),0,MAX(0,H21*(1-R21/(IF(OR(NOT(ISNUMBER(M21)),NOT(ISNUMBER(N21)),N21<=M21),0,MIN(12*(IF(OR(O21="",NOT(ISNUMBER(O21))),Paramètres!$C$8,O21)),(YEAR(N21)-YEAR(M21))*12+MONTH(N21)-MONTH(M21)+1)))))))) -> 0 | T21: =IF(AND(ISNUMBER(N21),ISNUMBER($C$7)),MAX(0,(N21-$C$7)/365.25),0) -> 0 | U21: =IF(AND(ISNUMBER(Q21),ISNUMBER($C$7)),MAX(0,(Q21-$C$7)/365.25),0) -> 0 | V21: =IF(COUNTA(B21,C21,D21,E21,F21,G21,I21,M21,N21,O21,P21,R21)>0,IF(AND(COUNT(Paramètres!$C$8:$C$12)=5,COUNT(Paramètres!$C$16:$C$25)=10,ISNUMBER($C$7),B21<>"",NOT(ISNA(MATCH(C21,Paramètres!$B$29:$B$34,0))),NOT(ISNA(MATCH(E21,Paramètres!$D$29:$D$30,0))),ISNUMBER(F21),F21>0,F21<=Paramètres!$C$22,OR(I21="",AND(ISNUMBER(I21),I21>=0,I21<=Paramètres!$C$21)),IF(E21=Paramètres!$D$29,AND(D21<>"",ISNUMBER(G21),G21>0,G21<=Paramètres!$C$21,ISNUMBER(M21),ISNUMBER(N21),N21>M21,(N(N21)-N(M21))/365.25<=Paramètres!$C$23,OR(O21="",AND(ISNUMBER(O21),O21>=1,O21<=Paramètres!$C$23,O21=INT(N(O21)))),OR(P21="",AND(ISNUMBER(P21),P21>$C$7,P21<=N21)),OR(R21="",AND(ISNUMBER(R21),R21>=0,R21<=Paramètres!$C$24,R21<=(IF(OR(NOT(ISNUMBER(M21)),NOT(ISNUMBER(N21)),N21<=M21),0,MIN(12*(IF(OR(O21="",NOT(ISNUMBER(O21))),Paramètres!$C$8,O21)),(YEAR(N21)-YEAR(M21))*12+MONTH(N21)-MONTH(M21)+1)))))),AND(D21="",OR(G21="",G21=0)))),"OK","À CORRIGER"),"") | W21: =IF(NOT(COUNTA(B21,C21,D21,E21,F21,G21,I21,M21,N21,O21,P21,R21)>0),"",IF(OR(COUNT(Paramètres!$C$8:$C$12)<>5,COUNT(Paramètres!$C$16:$C$25)<>10),"Un paramètre de l'onglet Paramètres est vide.",IF(NOT(ISNUMBER($C$7)),"Date d'analyse manquante.",IF(B21="","Libellé du lot manquant.",IF(ISNA(MATCH(C21,Paramètres!$B$29:$B$34,0)),"Nature hors liste.",IF(ISNA(MATCH(E21,Paramètres!$D$29:$D$30,0)),"Statut hors liste.",IF(NOT(AND(ISNUMBER(F21),F21>0)),"Surface manquante ou nulle.",IF(F21>Paramètres!$C$22,"Surface au-delà du garde-fou de saisie.",IF(AND(I21<>"",NOT(AND(ISNUMBER(I21),I21>=0,I21<=Paramètres!$C$21))),"Valeur locative de marché hors bornes.",IF(AND(E21=Paramètres!$D$29,D21=""),"Lot déclaré loué sans locataire.",IF(AND(E21=Paramètres!$D$29,NOT(AND(ISNUMBER(G21),G21>0))),"Loyer facial manquant ou nul.",IF(AND(E21=Paramètres!$D$29,G21>Paramètres!$C$21),"Loyer facial au-delà du garde-fou de saisie.",IF(AND(E21=Paramètres!$D$29,NOT(ISNUMBER(M21))),"Date de prise d'effet manquante.",IF(AND(E21=Paramètres!$D$29,NOT(ISNUMBER(N21))),"Date d'échéance manquante.",IF(AND(E21=Paramètres!$D$29,N21<=M21),"Échéance antérieure ou égale à la prise d'effet.",IF(AND(E21=Paramètres!$D$29,(N(N21)-N(M21))/365.25>Paramètres!$C$23),"Durée du bail au-delà du garde-fou de saisie.",IF(AND(E21=Paramètres!$D$29,O21<>"",NOT(AND(ISNUMBER(O21),O21>=1,O21<=Paramètres!$C$23,O21=INT(N(O21))))),"Périodicité de sortie hors bornes.",IF(AND(E21=Paramètres!$D$29,P21<>"",NOT(AND(ISNUMBER(P21),P21>$C$7,P21<=N21))),"Sortie forcée hors de l'intervalle admis.",IF(AND(E21=Paramètres!$D$29,R21<>"",NOT(AND(ISNUMBER(R21),R21>=0,R21<=Paramètres!$C$24,R21<=(IF(OR(NOT(ISNUMBER(M21)),NOT(ISNUMBER(N21)),N21<=M21),0,MIN(12*(IF(OR(O21="",NOT(ISNUMBER(O21))),Paramètres!$C$8,O21)),(YEAR(N21)-YEAR(M21))*12+MONTH(N21)-MONTH(M21)+1)))))),"Franchise hors bornes ou plus longue que la période ferme.",IF(AND(E21=Paramètres!$D$30,D21<>""),"Lot vacant avec un locataire renseigné.",IF(AND(E21=Paramètres!$D$30,G21<>"",G21<>0),"Lot vacant avec un loyer renseigné.",IF(AND(E21=Paramètres!$D$29,ISNUMBER(N21),ISNUMBER($C$7),N21<$C$7),"Bail échu, en tacite prolongation.",IF(I21="","Valeur locative de marché non renseignée.",""))))))))))))))))))))))) | X21: =IF(AND(V21="OK",E21=Paramètres!$D$29),SUMIFS($H$11:$H$50,$D$11:$D$50,D21,$E$11:$E$50,Paramètres!$D$29,$V$11:$V$50,"OK"),0) -> 0
H22: =IF(AND(ISNUMBER(F22),ISNUMBER(G22)),F22*G22,0) -> 0 | J22: =IF(AND(ISNUMBER(F22),ISNUMBER(I22)),F22*I22,0) -> 0 | K22: =IF(OR(H22<=0,J22<=0),"",J22-H22) | L22: =IF(OR(H22<=0,J22<=0),"",J22/H22-1) | Q22: =IF(OR(NOT(ISNUMBER($C$7)),NOT(ISNUMBER(M22)),NOT(ISNUMBER(N22))),"",IF(ISNUMBER(P22),P22,IF((IF(OR(O22="",NOT(ISNUMBER(O22))),Paramètres!$C$8,O22))<=0,"",MIN(EDATE(M22,(12*(IF(OR(O22="",NOT(ISNUMBER(O22))),Paramètres!$C$8,O22)))*MAX(1,INT(((YEAR($C$7+1)-YEAR(M22))*12+MONTH($C$7+1)-MONTH(M22)-(DAY($C$7+1)<DAY(M22)))/(12*(IF(OR(O22="",NOT(ISNUMBER(O22))),Paramètres!$C$8,O22))))+1))-1,N22)))) | S22: =IF(H22=0,0,IF(OR(R22="",R22=0),H22,IF(OR(NOT(ISNUMBER(R22)),(IF(OR(NOT(ISNUMBER(M22)),NOT(ISNUMBER(N22)),N22<=M22),0,MIN(12*(IF(OR(O22="",NOT(ISNUMBER(O22))),Paramètres!$C$8,O22)),(YEAR(N22)-YEAR(M22))*12+MONTH(N22)-MONTH(M22)+1)))<=0),0,MAX(0,H22*(1-R22/(IF(OR(NOT(ISNUMBER(M22)),NOT(ISNUMBER(N22)),N22<=M22),0,MIN(12*(IF(OR(O22="",NOT(ISNUMBER(O22))),Paramètres!$C$8,O22)),(YEAR(N22)-YEAR(M22))*12+MONTH(N22)-MONTH(M22)+1)))))))) -> 0 | T22: =IF(AND(ISNUMBER(N22),ISNUMBER($C$7)),MAX(0,(N22-$C$7)/365.25),0) -> 0 | U22: =IF(AND(ISNUMBER(Q22),ISNUMBER($C$7)),MAX(0,(Q22-$C$7)/365.25),0) -> 0 | V22: =IF(COUNTA(B22,C22,D22,E22,F22,G22,I22,M22,N22,O22,P22,R22)>0,IF(AND(COUNT(Paramètres!$C$8:$C$12)=5,COUNT(Paramètres!$C$16:$C$25)=10,ISNUMBER($C$7),B22<>"",NOT(ISNA(MATCH(C22,Paramètres!$B$29:$B$34,0))),NOT(ISNA(MATCH(E22,Paramètres!$D$29:$D$30,0))),ISNUMBER(F22),F22>0,F22<=Paramètres!$C$22,OR(I22="",AND(ISNUMBER(I22),I22>=0,I22<=Paramètres!$C$21)),IF(E22=Paramètres!$D$29,AND(D22<>"",ISNUMBER(G22),G22>0,G22<=Paramètres!$C$21,ISNUMBER(M22),ISNUMBER(N22),N22>M22,(N(N22)-N(M22))/365.25<=Paramètres!$C$23,OR(O22="",AND(ISNUMBER(O22),O22>=1,O22<=Paramètres!$C$23,O22=INT(N(O22)))),OR(P22="",AND(ISNUMBER(P22),P22>$C$7,P22<=N22)),OR(R22="",AND(ISNUMBER(R22),R22>=0,R22<=Paramètres!$C$24,R22<=(IF(OR(NOT(ISNUMBER(M22)),NOT(ISNUMBER(N22)),N22<=M22),0,MIN(12*(IF(OR(O22="",NOT(ISNUMBER(O22))),Paramètres!$C$8,O22)),(YEAR(N22)-YEAR(M22))*12+MONTH(N22)-MONTH(M22)+1)))))),AND(D22="",OR(G22="",G22=0)))),"OK","À CORRIGER"),"") | W22: =IF(NOT(COUNTA(B22,C22,D22,E22,F22,G22,I22,M22,N22,O22,P22,R22)>0),"",IF(OR(COUNT(Paramètres!$C$8:$C$12)<>5,COUNT(Paramètres!$C$16:$C$25)<>10),"Un paramètre de l'onglet Paramètres est vide.",IF(NOT(ISNUMBER($C$7)),"Date d'analyse manquante.",IF(B22="","Libellé du lot manquant.",IF(ISNA(MATCH(C22,Paramètres!$B$29:$B$34,0)),"Nature hors liste.",IF(ISNA(MATCH(E22,Paramètres!$D$29:$D$30,0)),"Statut hors liste.",IF(NOT(AND(ISNUMBER(F22),F22>0)),"Surface manquante ou nulle.",IF(F22>Paramètres!$C$22,"Surface au-delà du garde-fou de saisie.",IF(AND(I22<>"",NOT(AND(ISNUMBER(I22),I22>=0,I22<=Paramètres!$C$21))),"Valeur locative de marché hors bornes.",IF(AND(E22=Paramètres!$D$29,D22=""),"Lot déclaré loué sans locataire.",IF(AND(E22=Paramètres!$D$29,NOT(AND(ISNUMBER(G22),G22>0))),"Loyer facial manquant ou nul.",IF(AND(E22=Paramètres!$D$29,G22>Paramètres!$C$21),"Loyer facial au-delà du garde-fou de saisie.",IF(AND(E22=Paramètres!$D$29,NOT(ISNUMBER(M22))),"Date de prise d'effet manquante.",IF(AND(E22=Paramètres!$D$29,NOT(ISNUMBER(N22))),"Date d'échéance manquante.",IF(AND(E22=Paramètres!$D$29,N22<=M22),"Échéance antérieure ou égale à la prise d'effet.",IF(AND(E22=Paramètres!$D$29,(N(N22)-N(M22))/365.25>Paramètres!$C$23),"Durée du bail au-delà du garde-fou de saisie.",IF(AND(E22=Paramètres!$D$29,O22<>"",NOT(AND(ISNUMBER(O22),O22>=1,O22<=Paramètres!$C$23,O22=INT(N(O22))))),"Périodicité de sortie hors bornes.",IF(AND(E22=Paramètres!$D$29,P22<>"",NOT(AND(ISNUMBER(P22),P22>$C$7,P22<=N22))),"Sortie forcée hors de l'intervalle admis.",IF(AND(E22=Paramètres!$D$29,R22<>"",NOT(AND(ISNUMBER(R22),R22>=0,R22<=Paramètres!$C$24,R22<=(IF(OR(NOT(ISNUMBER(M22)),NOT(ISNUMBER(N22)),N22<=M22),0,MIN(12*(IF(OR(O22="",NOT(ISNUMBER(O22))),Paramètres!$C$8,O22)),(YEAR(N22)-YEAR(M22))*12+MONTH(N22)-MONTH(M22)+1)))))),"Franchise hors bornes ou plus longue que la période ferme.",IF(AND(E22=Paramètres!$D$30,D22<>""),"Lot vacant avec un locataire renseigné.",IF(AND(E22=Paramètres!$D$30,G22<>"",G22<>0),"Lot vacant avec un loyer renseigné.",IF(AND(E22=Paramètres!$D$29,ISNUMBER(N22),ISNUMBER($C$7),N22<$C$7),"Bail échu, en tacite prolongation.",IF(I22="","Valeur locative de marché non renseignée.",""))))))))))))))))))))))) | X22: =IF(AND(V22="OK",E22=Paramètres!$D$29),SUMIFS($H$11:$H$50,$D$11:$D$50,D22,$E$11:$E$50,Paramètres!$D$29,$V$11:$V$50,"OK"),0) -> 0
H23: =IF(AND(ISNUMBER(F23),ISNUMBER(G23)),F23*G23,0) -> 0 | J23: =IF(AND(ISNUMBER(F23),ISNUMBER(I23)),F23*I23,0) -> 0 | K23: =IF(OR(H23<=0,J23<=0),"",J23-H23) | L23: =IF(OR(H23<=0,J23<=0),"",J23/H23-1) | Q23: =IF(OR(NOT(ISNUMBER($C$7)),NOT(ISNUMBER(M23)),NOT(ISNUMBER(N23))),"",IF(ISNUMBER(P23),P23,IF((IF(OR(O23="",NOT(ISNUMBER(O23))),Paramètres!$C$8,O23))<=0,"",MIN(EDATE(M23,(12*(IF(OR(O23="",NOT(ISNUMBER(O23))),Paramètres!$C$8,O23)))*MAX(1,INT(((YEAR($C$7+1)-YEAR(M23))*12+MONTH($C$7+1)-MONTH(M23)-(DAY($C$7+1)<DAY(M23)))/(12*(IF(OR(O23="",NOT(ISNUMBER(O23))),Paramètres!$C$8,O23))))+1))-1,N23)))) | S23: =IF(H23=0,0,IF(OR(R23="",R23=0),H23,IF(OR(NOT(ISNUMBER(R23)),(IF(OR(NOT(ISNUMBER(M23)),NOT(ISNUMBER(N23)),N23<=M23),0,MIN(12*(IF(OR(O23="",NOT(ISNUMBER(O23))),Paramètres!$C$8,O23)),(YEAR(N23)-YEAR(M23))*12+MONTH(N23)-MONTH(M23)+1)))<=0),0,MAX(0,H23*(1-R23/(IF(OR(NOT(ISNUMBER(M23)),NOT(ISNUMBER(N23)),N23<=M23),0,MIN(12*(IF(OR(O23="",NOT(ISNUMBER(O23))),Paramètres!$C$8,O23)),(YEAR(N23)-YEAR(M23))*12+MONTH(N23)-MONTH(M23)+1)))))))) -> 0 | T23: =IF(AND(ISNUMBER(N23),ISNUMBER($C$7)),MAX(0,(N23-$C$7)/365.25),0) -> 0 | U23: =IF(AND(ISNUMBER(Q23),ISNUMBER($C$7)),MAX(0,(Q23-$C$7)/365.25),0) -> 0 | V23: =IF(COUNTA(B23,C23,D23,E23,F23,G23,I23,M23,N23,O23,P23,R23)>0,IF(AND(COUNT(Paramètres!$C$8:$C$12)=5,COUNT(Paramètres!$C$16:$C$25)=10,ISNUMBER($C$7),B23<>"",NOT(ISNA(MATCH(C23,Paramètres!$B$29:$B$34,0))),NOT(ISNA(MATCH(E23,Paramètres!$D$29:$D$30,0))),ISNUMBER(F23),F23>0,F23<=Paramètres!$C$22,OR(I23="",AND(ISNUMBER(I23),I23>=0,I23<=Paramètres!$C$21)),IF(E23=Paramètres!$D$29,AND(D23<>"",ISNUMBER(G23),G23>0,G23<=Paramètres!$C$21,ISNUMBER(M23),ISNUMBER(N23),N23>M23,(N(N23)-N(M23))/365.25<=Paramètres!$C$23,OR(O23="",AND(ISNUMBER(O23),O23>=1,O23<=Paramètres!$C$23,O23=INT(N(O23)))),OR(P23="",AND(ISNUMBER(P23),P23>$C$7,P23<=N23)),OR(R23="",AND(ISNUMBER(R23),R23>=0,R23<=Paramètres!$C$24,R23<=(IF(OR(NOT(ISNUMBER(M23)),NOT(ISNUMBER(N23)),N23<=M23),0,MIN(12*(IF(OR(O23="",NOT(ISNUMBER(O23))),Paramètres!$C$8,O23)),(YEAR(N23)-YEAR(M23))*12+MONTH(N23)-MONTH(M23)+1)))))),AND(D23="",OR(G23="",G23=0)))),"OK","À CORRIGER"),"") | W23: =IF(NOT(COUNTA(B23,C23,D23,E23,F23,G23,I23,M23,N23,O23,P23,R23)>0),"",IF(OR(COUNT(Paramètres!$C$8:$C$12)<>5,COUNT(Paramètres!$C$16:$C$25)<>10),"Un paramètre de l'onglet Paramètres est vide.",IF(NOT(ISNUMBER($C$7)),"Date d'analyse manquante.",IF(B23="","Libellé du lot manquant.",IF(ISNA(MATCH(C23,Paramètres!$B$29:$B$34,0)),"Nature hors liste.",IF(ISNA(MATCH(E23,Paramètres!$D$29:$D$30,0)),"Statut hors liste.",IF(NOT(AND(ISNUMBER(F23),F23>0)),"Surface manquante ou nulle.",IF(F23>Paramètres!$C$22,"Surface au-delà du garde-fou de saisie.",IF(AND(I23<>"",NOT(AND(ISNUMBER(I23),I23>=0,I23<=Paramètres!$C$21))),"Valeur locative de marché hors bornes.",IF(AND(E23=Paramètres!$D$29,D23=""),"Lot déclaré loué sans locataire.",IF(AND(E23=Paramètres!$D$29,NOT(AND(ISNUMBER(G23),G23>0))),"Loyer facial manquant ou nul.",IF(AND(E23=Paramètres!$D$29,G23>Paramètres!$C$21),"Loyer facial au-delà du garde-fou de saisie.",IF(AND(E23=Paramètres!$D$29,NOT(ISNUMBER(M23))),"Date de prise d'effet manquante.",IF(AND(E23=Paramètres!$D$29,NOT(ISNUMBER(N23))),"Date d'échéance manquante.",IF(AND(E23=Paramètres!$D$29,N23<=M23),"Échéance antérieure ou égale à la prise d'effet.",IF(AND(E23=Paramètres!$D$29,(N(N23)-N(M23))/365.25>Paramètres!$C$23),"Durée du bail au-delà du garde-fou de saisie.",IF(AND(E23=Paramètres!$D$29,O23<>"",NOT(AND(ISNUMBER(O23),O23>=1,O23<=Paramètres!$C$23,O23=INT(N(O23))))),"Périodicité de sortie hors bornes.",IF(AND(E23=Paramètres!$D$29,P23<>"",NOT(AND(ISNUMBER(P23),P23>$C$7,P23<=N23))),"Sortie forcée hors de l'intervalle admis.",IF(AND(E23=Paramètres!$D$29,R23<>"",NOT(AND(ISNUMBER(R23),R23>=0,R23<=Paramètres!$C$24,R23<=(IF(OR(NOT(ISNUMBER(M23)),NOT(ISNUMBER(N23)),N23<=M23),0,MIN(12*(IF(OR(O23="",NOT(ISNUMBER(O23))),Paramètres!$C$8,O23)),(YEAR(N23)-YEAR(M23))*12+MONTH(N23)-MONTH(M23)+1)))))),"Franchise hors bornes ou plus longue que la période ferme.",IF(AND(E23=Paramètres!$D$30,D23<>""),"Lot vacant avec un locataire renseigné.",IF(AND(E23=Paramètres!$D$30,G23<>"",G23<>0),"Lot vacant avec un loyer renseigné.",IF(AND(E23=Paramètres!$D$29,ISNUMBER(N23),ISNUMBER($C$7),N23<$C$7),"Bail échu, en tacite prolongation.",IF(I23="","Valeur locative de marché non renseignée.",""))))))))))))))))))))))) | X23: =IF(AND(V23="OK",E23=Paramètres!$D$29),SUMIFS($H$11:$H$50,$D$11:$D$50,D23,$E$11:$E$50,Paramètres!$D$29,$V$11:$V$50,"OK"),0) -> 0
H24: =IF(AND(ISNUMBER(F24),ISNUMBER(G24)),F24*G24,0) -> 0 | J24: =IF(AND(ISNUMBER(F24),ISNUMBER(I24)),F24*I24,0) -> 0 | K24: =IF(OR(H24<=0,J24<=0),"",J24-H24) | L24: =IF(OR(H24<=0,J24<=0),"",J24/H24-1) | Q24: =IF(OR(NOT(ISNUMBER($C$7)),NOT(ISNUMBER(M24)),NOT(ISNUMBER(N24))),"",IF(ISNUMBER(P24),P24,IF((IF(OR(O24="",NOT(ISNUMBER(O24))),Paramètres!$C$8,O24))<=0,"",MIN(EDATE(M24,(12*(IF(OR(O24="",NOT(ISNUMBER(O24))),Paramètres!$C$8,O24)))*MAX(1,INT(((YEAR($C$7+1)-YEAR(M24))*12+MONTH($C$7+1)-MONTH(M24)-(DAY($C$7+1)<DAY(M24)))/(12*(IF(OR(O24="",NOT(ISNUMBER(O24))),Paramètres!$C$8,O24))))+1))-1,N24)))) | S24: =IF(H24=0,0,IF(OR(R24="",R24=0),H24,IF(OR(NOT(ISNUMBER(R24)),(IF(OR(NOT(ISNUMBER(M24)),NOT(ISNUMBER(N24)),N24<=M24),0,MIN(12*(IF(OR(O24="",NOT(ISNUMBER(O24))),Paramètres!$C$8,O24)),(YEAR(N24)-YEAR(M24))*12+MONTH(N24)-MONTH(M24)+1)))<=0),0,MAX(0,H24*(1-R24/(IF(OR(NOT(ISNUMBER(M24)),NOT(ISNUMBER(N24)),N24<=M24),0,MIN(12*(IF(OR(O24="",NOT(ISNUMBER(O24))),Paramètres!$C$8,O24)),(YEAR(N24)-YEAR(M24))*12+MONTH(N24)-MONTH(M24)+1)))))))) -> 0 | T24: =IF(AND(ISNUMBER(N24),ISNUMBER($C$7)),MAX(0,(N24-$C$7)/365.25),0) -> 0 | U24: =IF(AND(ISNUMBER(Q24),ISNUMBER($C$7)),MAX(0,(Q24-$C$7)/365.25),0) -> 0 | V24: =IF(COUNTA(B24,C24,D24,E24,F24,G24,I24,M24,N24,O24,P24,R24)>0,IF(AND(COUNT(Paramètres!$C$8:$C$12)=5,COUNT(Paramètres!$C$16:$C$25)=10,ISNUMBER($C$7),B24<>"",NOT(ISNA(MATCH(C24,Paramètres!$B$29:$B$34,0))),NOT(ISNA(MATCH(E24,Paramètres!$D$29:$D$30,0))),ISNUMBER(F24),F24>0,F24<=Paramètres!$C$22,OR(I24="",AND(ISNUMBER(I24),I24>=0,I24<=Paramètres!$C$21)),IF(E24=Paramètres!$D$29,AND(D24<>"",ISNUMBER(G24),G24>0,G24<=Paramètres!$C$21,ISNUMBER(M24),ISNUMBER(N24),N24>M24,(N(N24)-N(M24))/365.25<=Paramètres!$C$23,OR(O24="",AND(ISNUMBER(O24),O24>=1,O24<=Paramètres!$C$23,O24=INT(N(O24)))),OR(P24="",AND(ISNUMBER(P24),P24>$C$7,P24<=N24)),OR(R24="",AND(ISNUMBER(R24),R24>=0,R24<=Paramètres!$C$24,R24<=(IF(OR(NOT(ISNUMBER(M24)),NOT(ISNUMBER(N24)),N24<=M24),0,MIN(12*(IF(OR(O24="",NOT(ISNUMBER(O24))),Paramètres!$C$8,O24)),(YEAR(N24)-YEAR(M24))*12+MONTH(N24)-MONTH(M24)+1)))))),AND(D24="",OR(G24="",G24=0)))),"OK","À CORRIGER"),"") | W24: =IF(NOT(COUNTA(B24,C24,D24,E24,F24,G24,I24,M24,N24,O24,P24,R24)>0),"",IF(OR(COUNT(Paramètres!$C$8:$C$12)<>5,COUNT(Paramètres!$C$16:$C$25)<>10),"Un paramètre de l'onglet Paramètres est vide.",IF(NOT(ISNUMBER($C$7)),"Date d'analyse manquante.",IF(B24="","Libellé du lot manquant.",IF(ISNA(MATCH(C24,Paramètres!$B$29:$B$34,0)),"Nature hors liste.",IF(ISNA(MATCH(E24,Paramètres!$D$29:$D$30,0)),"Statut hors liste.",IF(NOT(AND(ISNUMBER(F24),F24>0)),"Surface manquante ou nulle.",IF(F24>Paramètres!$C$22,"Surface au-delà du garde-fou de saisie.",IF(AND(I24<>"",NOT(AND(ISNUMBER(I24),I24>=0,I24<=Paramètres!$C$21))),"Valeur locative de marché hors bornes.",IF(AND(E24=Paramètres!$D$29,D24=""),"Lot déclaré loué sans locataire.",IF(AND(E24=Paramètres!$D$29,NOT(AND(ISNUMBER(G24),G24>0))),"Loyer facial manquant ou nul.",IF(AND(E24=Paramètres!$D$29,G24>Paramètres!$C$21),"Loyer facial au-delà du garde-fou de saisie.",IF(AND(E24=Paramètres!$D$29,NOT(ISNUMBER(M24))),"Date de prise d'effet manquante.",IF(AND(E24=Paramètres!$D$29,NOT(ISNUMBER(N24))),"Date d'échéance manquante.",IF(AND(E24=Paramètres!$D$29,N24<=M24),"Échéance antérieure ou égale à la prise d'effet.",IF(AND(E24=Paramètres!$D$29,(N(N24)-N(M24))/365.25>Paramètres!$C$23),"Durée du bail au-delà du garde-fou de saisie.",IF(AND(E24=Paramètres!$D$29,O24<>"",NOT(AND(ISNUMBER(O24),O24>=1,O24<=Paramètres!$C$23,O24=INT(N(O24))))),"Périodicité de sortie hors bornes.",IF(AND(E24=Paramètres!$D$29,P24<>"",NOT(AND(ISNUMBER(P24),P24>$C$7,P24<=N24))),"Sortie forcée hors de l'intervalle admis.",IF(AND(E24=Paramètres!$D$29,R24<>"",NOT(AND(ISNUMBER(R24),R24>=0,R24<=Paramètres!$C$24,R24<=(IF(OR(NOT(ISNUMBER(M24)),NOT(ISNUMBER(N24)),N24<=M24),0,MIN(12*(IF(OR(O24="",NOT(ISNUMBER(O24))),Paramètres!$C$8,O24)),(YEAR(N24)-YEAR(M24))*12+MONTH(N24)-MONTH(M24)+1)))))),"Franchise hors bornes ou plus longue que la période ferme.",IF(AND(E24=Paramètres!$D$30,D24<>""),"Lot vacant avec un locataire renseigné.",IF(AND(E24=Paramètres!$D$30,G24<>"",G24<>0),"Lot vacant avec un loyer renseigné.",IF(AND(E24=Paramètres!$D$29,ISNUMBER(N24),ISNUMBER($C$7),N24<$C$7),"Bail échu, en tacite prolongation.",IF(I24="","Valeur locative de marché non renseignée.",""))))))))))))))))))))))) | X24: =IF(AND(V24="OK",E24=Paramètres!$D$29),SUMIFS($H$11:$H$50,$D$11:$D$50,D24,$E$11:$E$50,Paramètres!$D$29,$V$11:$V$50,"OK"),0) -> 0
H25: =IF(AND(ISNUMBER(F25),ISNUMBER(G25)),F25*G25,0) -> 0 | J25: =IF(AND(ISNUMBER(F25),ISNUMBER(I25)),F25*I25,0) -> 0 | K25: =IF(OR(H25<=0,J25<=0),"",J25-H25) | L25: =IF(OR(H25<=0,J25<=0),"",J25/H25-1) | Q25: =IF(OR(NOT(ISNUMBER($C$7)),NOT(ISNUMBER(M25)),NOT(ISNUMBER(N25))),"",IF(ISNUMBER(P25),P25,IF((IF(OR(O25="",NOT(ISNUMBER(O25))),Paramètres!$C$8,O25))<=0,"",MIN(EDATE(M25,(12*(IF(OR(O25="",NOT(ISNUMBER(O25))),Paramètres!$C$8,O25)))*MAX(1,INT(((YEAR($C$7+1)-YEAR(M25))*12+MONTH($C$7+1)-MONTH(M25)-(DAY($C$7+1)<DAY(M25)))/(12*(IF(OR(O25="",NOT(ISNUMBER(O25))),Paramètres!$C$8,O25))))+1))-1,N25)))) | S25: =IF(H25=0,0,IF(OR(R25="",R25=0),H25,IF(OR(NOT(ISNUMBER(R25)),(IF(OR(NOT(ISNUMBER(M25)),NOT(ISNUMBER(N25)),N25<=M25),0,MIN(12*(IF(OR(O25="",NOT(ISNUMBER(O25))),Paramètres!$C$8,O25)),(YEAR(N25)-YEAR(M25))*12+MONTH(N25)-MONTH(M25)+1)))<=0),0,MAX(0,H25*(1-R25/(IF(OR(NOT(ISNUMBER(M25)),NOT(ISNUMBER(N25)),N25<=M25),0,MIN(12*(IF(OR(O25="",NOT(ISNUMBER(O25))),Paramètres!$C$8,O25)),(YEAR(N25)-YEAR(M25))*12+MONTH(N25)-MONTH(M25)+1)))))))) -> 0 | T25: =IF(AND(ISNUMBER(N25),ISNUMBER($C$7)),MAX(0,(N25-$C$7)/365.25),0) -> 0 | U25: =IF(AND(ISNUMBER(Q25),ISNUMBER($C$7)),MAX(0,(Q25-$C$7)/365.25),0) -> 0 | V25: =IF(COUNTA(B25,C25,D25,E25,F25,G25,I25,M25,N25,O25,P25,R25)>0,IF(AND(COUNT(Paramètres!$C$8:$C$12)=5,COUNT(Paramètres!$C$16:$C$25)=10,ISNUMBER($C$7),B25<>"",NOT(ISNA(MATCH(C25,Paramètres!$B$29:$B$34,0))),NOT(ISNA(MATCH(E25,Paramètres!$D$29:$D$30,0))),ISNUMBER(F25),F25>0,F25<=Paramètres!$C$22,OR(I25="",AND(ISNUMBER(I25),I25>=0,I25<=Paramètres!$C$21)),IF(E25=Paramètres!$D$29,AND(D25<>"",ISNUMBER(G25),G25>0,G25<=Paramètres!$C$21,ISNUMBER(M25),ISNUMBER(N25),N25>M25,(N(N25)-N(M25))/365.25<=Paramètres!$C$23,OR(O25="",AND(ISNUMBER(O25),O25>=1,O25<=Paramètres!$C$23,O25=INT(N(O25)))),OR(P25="",AND(ISNUMBER(P25),P25>$C$7,P25<=N25)),OR(R25="",AND(ISNUMBER(R25),R25>=0,R25<=Paramètres!$C$24,R25<=(IF(OR(NOT(ISNUMBER(M25)),NOT(ISNUMBER(N25)),N25<=M25),0,MIN(12*(IF(OR(O25="",NOT(ISNUMBER(O25))),Paramètres!$C$8,O25)),(YEAR(N25)-YEAR(M25))*12+MONTH(N25)-MONTH(M25)+1)))))),AND(D25="",OR(G25="",G25=0)))),"OK","À CORRIGER"),"") | W25: =IF(NOT(COUNTA(B25,C25,D25,E25,F25,G25,I25,M25,N25,O25,P25,R25)>0),"",IF(OR(COUNT(Paramètres!$C$8:$C$12)<>5,COUNT(Paramètres!$C$16:$C$25)<>10),"Un paramètre de l'onglet Paramètres est vide.",IF(NOT(ISNUMBER($C$7)),"Date d'analyse manquante.",IF(B25="","Libellé du lot manquant.",IF(ISNA(MATCH(C25,Paramètres!$B$29:$B$34,0)),"Nature hors liste.",IF(ISNA(MATCH(E25,Paramètres!$D$29:$D$30,0)),"Statut hors liste.",IF(NOT(AND(ISNUMBER(F25),F25>0)),"Surface manquante ou nulle.",IF(F25>Paramètres!$C$22,"Surface au-delà du garde-fou de saisie.",IF(AND(I25<>"",NOT(AND(ISNUMBER(I25),I25>=0,I25<=Paramètres!$C$21))),"Valeur locative de marché hors bornes.",IF(AND(E25=Paramètres!$D$29,D25=""),"Lot déclaré loué sans locataire.",IF(AND(E25=Paramètres!$D$29,NOT(AND(ISNUMBER(G25),G25>0))),"Loyer facial manquant ou nul.",IF(AND(E25=Paramètres!$D$29,G25>Paramètres!$C$21),"Loyer facial au-delà du garde-fou de saisie.",IF(AND(E25=Paramètres!$D$29,NOT(ISNUMBER(M25))),"Date de prise d'effet manquante.",IF(AND(E25=Paramètres!$D$29,NOT(ISNUMBER(N25))),"Date d'échéance manquante.",IF(AND(E25=Paramètres!$D$29,N25<=M25),"Échéance antérieure ou égale à la prise d'effet.",IF(AND(E25=Paramètres!$D$29,(N(N25)-N(M25))/365.25>Paramètres!$C$23),"Durée du bail au-delà du garde-fou de saisie.",IF(AND(E25=Paramètres!$D$29,O25<>"",NOT(AND(ISNUMBER(O25),O25>=1,O25<=Paramètres!$C$23,O25=INT(N(O25))))),"Périodicité de sortie hors bornes.",IF(AND(E25=Paramètres!$D$29,P25<>"",NOT(AND(ISNUMBER(P25),P25>$C$7,P25<=N25))),"Sortie forcée hors de l'intervalle admis.",IF(AND(E25=Paramètres!$D$29,R25<>"",NOT(AND(ISNUMBER(R25),R25>=0,R25<=Paramètres!$C$24,R25<=(IF(OR(NOT(ISNUMBER(M25)),NOT(ISNUMBER(N25)),N25<=M25),0,MIN(12*(IF(OR(O25="",NOT(ISNUMBER(O25))),Paramètres!$C$8,O25)),(YEAR(N25)-YEAR(M25))*12+MONTH(N25)-MONTH(M25)+1)))))),"Franchise hors bornes ou plus longue que la période ferme.",IF(AND(E25=Paramètres!$D$30,D25<>""),"Lot vacant avec un locataire renseigné.",IF(AND(E25=Paramètres!$D$30,G25<>"",G25<>0),"Lot vacant avec un loyer renseigné.",IF(AND(E25=Paramètres!$D$29,ISNUMBER(N25),ISNUMBER($C$7),N25<$C$7),"Bail échu, en tacite prolongation.",IF(I25="","Valeur locative de marché non renseignée.",""))))))))))))))))))))))) | X25: =IF(AND(V25="OK",E25=Paramètres!$D$29),SUMIFS($H$11:$H$50,$D$11:$D$50,D25,$E$11:$E$50,Paramètres!$D$29,$V$11:$V$50,"OK"),0) -> 0
H26: =IF(AND(ISNUMBER(F26),ISNUMBER(G26)),F26*G26,0) -> 0 | J26: =IF(AND(ISNUMBER(F26),ISNUMBER(I26)),F26*I26,0) -> 0 | K26: =IF(OR(H26<=0,J26<=0),"",J26-H26) | L26: =IF(OR(H26<=0,J26<=0),"",J26/H26-1) | Q26: =IF(OR(NOT(ISNUMBER($C$7)),NOT(ISNUMBER(M26)),NOT(ISNUMBER(N26))),"",IF(ISNUMBER(P26),P26,IF((IF(OR(O26="",NOT(ISNUMBER(O26))),Paramètres!$C$8,O26))<=0,"",MIN(EDATE(M26,(12*(IF(OR(O26="",NOT(ISNUMBER(O26))),Paramètres!$C$8,O26)))*MAX(1,INT(((YEAR($C$7+1)-YEAR(M26))*12+MONTH($C$7+1)-MONTH(M26)-(DAY($C$7+1)<DAY(M26)))/(12*(IF(OR(O26="",NOT(ISNUMBER(O26))),Paramètres!$C$8,O26))))+1))-1,N26)))) | S26: =IF(H26=0,0,IF(OR(R26="",R26=0),H26,IF(OR(NOT(ISNUMBER(R26)),(IF(OR(NOT(ISNUMBER(M26)),NOT(ISNUMBER(N26)),N26<=M26),0,MIN(12*(IF(OR(O26="",NOT(ISNUMBER(O26))),Paramètres!$C$8,O26)),(YEAR(N26)-YEAR(M26))*12+MONTH(N26)-MONTH(M26)+1)))<=0),0,MAX(0,H26*(1-R26/(IF(OR(NOT(ISNUMBER(M26)),NOT(ISNUMBER(N26)),N26<=M26),0,MIN(12*(IF(OR(O26="",NOT(ISNUMBER(O26))),Paramètres!$C$8,O26)),(YEAR(N26)-YEAR(M26))*12+MONTH(N26)-MONTH(M26)+1)))))))) -> 0 | T26: =IF(AND(ISNUMBER(N26),ISNUMBER($C$7)),MAX(0,(N26-$C$7)/365.25),0) -> 0 | U26: =IF(AND(ISNUMBER(Q26),ISNUMBER($C$7)),MAX(0,(Q26-$C$7)/365.25),0) -> 0 | V26: =IF(COUNTA(B26,C26,D26,E26,F26,G26,I26,M26,N26,O26,P26,R26)>0,IF(AND(COUNT(Paramètres!$C$8:$C$12)=5,COUNT(Paramètres!$C$16:$C$25)=10,ISNUMBER($C$7),B26<>"",NOT(ISNA(MATCH(C26,Paramètres!$B$29:$B$34,0))),NOT(ISNA(MATCH(E26,Paramètres!$D$29:$D$30,0))),ISNUMBER(F26),F26>0,F26<=Paramètres!$C$22,OR(I26="",AND(ISNUMBER(I26),I26>=0,I26<=Paramètres!$C$21)),IF(E26=Paramètres!$D$29,AND(D26<>"",ISNUMBER(G26),G26>0,G26<=Paramètres!$C$21,ISNUMBER(M26),ISNUMBER(N26),N26>M26,(N(N26)-N(M26))/365.25<=Paramètres!$C$23,OR(O26="",AND(ISNUMBER(O26),O26>=1,O26<=Paramètres!$C$23,O26=INT(N(O26)))),OR(P26="",AND(ISNUMBER(P26),P26>$C$7,P26<=N26)),OR(R26="",AND(ISNUMBER(R26),R26>=0,R26<=Paramètres!$C$24,R26<=(IF(OR(NOT(ISNUMBER(M26)),NOT(ISNUMBER(N26)),N26<=M26),0,MIN(12*(IF(OR(O26="",NOT(ISNUMBER(O26))),Paramètres!$C$8,O26)),(YEAR(N26)-YEAR(M26))*12+MONTH(N26)-MONTH(M26)+1)))))),AND(D26="",OR(G26="",G26=0)))),"OK","À CORRIGER"),"") | W26: =IF(NOT(COUNTA(B26,C26,D26,E26,F26,G26,I26,M26,N26,O26,P26,R26)>0),"",IF(OR(COUNT(Paramètres!$C$8:$C$12)<>5,COUNT(Paramètres!$C$16:$C$25)<>10),"Un paramètre de l'onglet Paramètres est vide.",IF(NOT(ISNUMBER($C$7)),"Date d'analyse manquante.",IF(B26="","Libellé du lot manquant.",IF(ISNA(MATCH(C26,Paramètres!$B$29:$B$34,0)),"Nature hors liste.",IF(ISNA(MATCH(E26,Paramètres!$D$29:$D$30,0)),"Statut hors liste.",IF(NOT(AND(ISNUMBER(F26),F26>0)),"Surface manquante ou nulle.",IF(F26>Paramètres!$C$22,"Surface au-delà du garde-fou de saisie.",IF(AND(I26<>"",NOT(AND(ISNUMBER(I26),I26>=0,I26<=Paramètres!$C$21))),"Valeur locative de marché hors bornes.",IF(AND(E26=Paramètres!$D$29,D26=""),"Lot déclaré loué sans locataire.",IF(AND(E26=Paramètres!$D$29,NOT(AND(ISNUMBER(G26),G26>0))),"Loyer facial manquant ou nul.",IF(AND(E26=Paramètres!$D$29,G26>Paramètres!$C$21),"Loyer facial au-delà du garde-fou de saisie.",IF(AND(E26=Paramètres!$D$29,NOT(ISNUMBER(M26))),"Date de prise d'effet manquante.",IF(AND(E26=Paramètres!$D$29,NOT(ISNUMBER(N26))),"Date d'échéance manquante.",IF(AND(E26=Paramètres!$D$29,N26<=M26),"Échéance antérieure ou égale à la prise d'effet.",IF(AND(E26=Paramètres!$D$29,(N(N26)-N(M26))/365.25>Paramètres!$C$23),"Durée du bail au-delà du garde-fou de saisie.",IF(AND(E26=Paramètres!$D$29,O26<>"",NOT(AND(ISNUMBER(O26),O26>=1,O26<=Paramètres!$C$23,O26=INT(N(O26))))),"Périodicité de sortie hors bornes.",IF(AND(E26=Paramètres!$D$29,P26<>"",NOT(AND(ISNUMBER(P26),P26>$C$7,P26<=N26))),"Sortie forcée hors de l'intervalle admis.",IF(AND(E26=Paramètres!$D$29,R26<>"",NOT(AND(ISNUMBER(R26),R26>=0,R26<=Paramètres!$C$24,R26<=(IF(OR(NOT(ISNUMBER(M26)),NOT(ISNUMBER(N26)),N26<=M26),0,MIN(12*(IF(OR(O26="",NOT(ISNUMBER(O26))),Paramètres!$C$8,O26)),(YEAR(N26)-YEAR(M26))*12+MONTH(N26)-MONTH(M26)+1)))))),"Franchise hors bornes ou plus longue que la période ferme.",IF(AND(E26=Paramètres!$D$30,D26<>""),"Lot vacant avec un locataire renseigné.",IF(AND(E26=Paramètres!$D$30,G26<>"",G26<>0),"Lot vacant avec un loyer renseigné.",IF(AND(E26=Paramètres!$D$29,ISNUMBER(N26),ISNUMBER($C$7),N26<$C$7),"Bail échu, en tacite prolongation.",IF(I26="","Valeur locative de marché non renseignée.",""))))))))))))))))))))))) | X26: =IF(AND(V26="OK",E26=Paramètres!$D$29),SUMIFS($H$11:$H$50,$D$11:$D$50,D26,$E$11:$E$50,Paramètres!$D$29,$V$11:$V$50,"OK"),0) -> 0
H27: =IF(AND(ISNUMBER(F27),ISNUMBER(G27)),F27*G27,0) -> 0 | J27: =IF(AND(ISNUMBER(F27),ISNUMBER(I27)),F27*I27,0) -> 0 | K27: =IF(OR(H27<=0,J27<=0),"",J27-H27) | L27: =IF(OR(H27<=0,J27<=0),"",J27/H27-1) | Q27: =IF(OR(NOT(ISNUMBER($C$7)),NOT(ISNUMBER(M27)),NOT(ISNUMBER(N27))),"",IF(ISNUMBER(P27),P27,IF((IF(OR(O27="",NOT(ISNUMBER(O27))),Paramètres!$C$8,O27))<=0,"",MIN(EDATE(M27,(12*(IF(OR(O27="",NOT(ISNUMBER(O27))),Paramètres!$C$8,O27)))*MAX(1,INT(((YEAR($C$7+1)-YEAR(M27))*12+MONTH($C$7+1)-MONTH(M27)-(DAY($C$7+1)<DAY(M27)))/(12*(IF(OR(O27="",NOT(ISNUMBER(O27))),Paramètres!$C$8,O27))))+1))-1,N27)))) | S27: =IF(H27=0,0,IF(OR(R27="",R27=0),H27,IF(OR(NOT(ISNUMBER(R27)),(IF(OR(NOT(ISNUMBER(M27)),NOT(ISNUMBER(N27)),N27<=M27),0,MIN(12*(IF(OR(O27="",NOT(ISNUMBER(O27))),Paramètres!$C$8,O27)),(YEAR(N27)-YEAR(M27))*12+MONTH(N27)-MONTH(M27)+1)))<=0),0,MAX(0,H27*(1-R27/(IF(OR(NOT(ISNUMBER(M27)),NOT(ISNUMBER(N27)),N27<=M27),0,MIN(12*(IF(OR(O27="",NOT(ISNUMBER(O27))),Paramètres!$C$8,O27)),(YEAR(N27)-YEAR(M27))*12+MONTH(N27)-MONTH(M27)+1)))))))) -> 0 | T27: =IF(AND(ISNUMBER(N27),ISNUMBER($C$7)),MAX(0,(N27-$C$7)/365.25),0) -> 0 | U27: =IF(AND(ISNUMBER(Q27),ISNUMBER($C$7)),MAX(0,(Q27-$C$7)/365.25),0) -> 0 | V27: =IF(COUNTA(B27,C27,D27,E27,F27,G27,I27,M27,N27,O27,P27,R27)>0,IF(AND(COUNT(Paramètres!$C$8:$C$12)=5,COUNT(Paramètres!$C$16:$C$25)=10,ISNUMBER($C$7),B27<>"",NOT(ISNA(MATCH(C27,Paramètres!$B$29:$B$34,0))),NOT(ISNA(MATCH(E27,Paramètres!$D$29:$D$30,0))),ISNUMBER(F27),F27>0,F27<=Paramètres!$C$22,OR(I27="",AND(ISNUMBER(I27),I27>=0,I27<=Paramètres!$C$21)),IF(E27=Paramètres!$D$29,AND(D27<>"",ISNUMBER(G27),G27>0,G27<=Paramètres!$C$21,ISNUMBER(M27),ISNUMBER(N27),N27>M27,(N(N27)-N(M27))/365.25<=Paramètres!$C$23,OR(O27="",AND(ISNUMBER(O27),O27>=1,O27<=Paramètres!$C$23,O27=INT(N(O27)))),OR(P27="",AND(ISNUMBER(P27),P27>$C$7,P27<=N27)),OR(R27="",AND(ISNUMBER(R27),R27>=0,R27<=Paramètres!$C$24,R27<=(IF(OR(NOT(ISNUMBER(M27)),NOT(ISNUMBER(N27)),N27<=M27),0,MIN(12*(IF(OR(O27="",NOT(ISNUMBER(O27))),Paramètres!$C$8,O27)),(YEAR(N27)-YEAR(M27))*12+MONTH(N27)-MONTH(M27)+1)))))),AND(D27="",OR(G27="",G27=0)))),"OK","À CORRIGER"),"") | W27: =IF(NOT(COUNTA(B27,C27,D27,E27,F27,G27,I27,M27,N27,O27,P27,R27)>0),"",IF(OR(COUNT(Paramètres!$C$8:$C$12)<>5,COUNT(Paramètres!$C$16:$C$25)<>10),"Un paramètre de l'onglet Paramètres est vide.",IF(NOT(ISNUMBER($C$7)),"Date d'analyse manquante.",IF(B27="","Libellé du lot manquant.",IF(ISNA(MATCH(C27,Paramètres!$B$29:$B$34,0)),"Nature hors liste.",IF(ISNA(MATCH(E27,Paramètres!$D$29:$D$30,0)),"Statut hors liste.",IF(NOT(AND(ISNUMBER(F27),F27>0)),"Surface manquante ou nulle.",IF(F27>Paramètres!$C$22,"Surface au-delà du garde-fou de saisie.",IF(AND(I27<>"",NOT(AND(ISNUMBER(I27),I27>=0,I27<=Paramètres!$C$21))),"Valeur locative de marché hors bornes.",IF(AND(E27=Paramètres!$D$29,D27=""),"Lot déclaré loué sans locataire.",IF(AND(E27=Paramètres!$D$29,NOT(AND(ISNUMBER(G27),G27>0))),"Loyer facial manquant ou nul.",IF(AND(E27=Paramètres!$D$29,G27>Paramètres!$C$21),"Loyer facial au-delà du garde-fou de saisie.",IF(AND(E27=Paramètres!$D$29,NOT(ISNUMBER(M27))),"Date de prise d'effet manquante.",IF(AND(E27=Paramètres!$D$29,NOT(ISNUMBER(N27))),"Date d'échéance manquante.",IF(AND(E27=Paramètres!$D$29,N27<=M27),"Échéance antérieure ou égale à la prise d'effet.",IF(AND(E27=Paramètres!$D$29,(N(N27)-N(M27))/365.25>Paramètres!$C$23),"Durée du bail au-delà du garde-fou de saisie.",IF(AND(E27=Paramètres!$D$29,O27<>"",NOT(AND(ISNUMBER(O27),O27>=1,O27<=Paramètres!$C$23,O27=INT(N(O27))))),"Périodicité de sortie hors bornes.",IF(AND(E27=Paramètres!$D$29,P27<>"",NOT(AND(ISNUMBER(P27),P27>$C$7,P27<=N27))),"Sortie forcée hors de l'intervalle admis.",IF(AND(E27=Paramètres!$D$29,R27<>"",NOT(AND(ISNUMBER(R27),R27>=0,R27<=Paramètres!$C$24,R27<=(IF(OR(NOT(ISNUMBER(M27)),NOT(ISNUMBER(N27)),N27<=M27),0,MIN(12*(IF(OR(O27="",NOT(ISNUMBER(O27))),Paramètres!$C$8,O27)),(YEAR(N27)-YEAR(M27))*12+MONTH(N27)-MONTH(M27)+1)))))),"Franchise hors bornes ou plus longue que la période ferme.",IF(AND(E27=Paramètres!$D$30,D27<>""),"Lot vacant avec un locataire renseigné.",IF(AND(E27=Paramètres!$D$30,G27<>"",G27<>0),"Lot vacant avec un loyer renseigné.",IF(AND(E27=Paramètres!$D$29,ISNUMBER(N27),ISNUMBER($C$7),N27<$C$7),"Bail échu, en tacite prolongation.",IF(I27="","Valeur locative de marché non renseignée.",""))))))))))))))))))))))) | X27: =IF(AND(V27="OK",E27=Paramètres!$D$29),SUMIFS($H$11:$H$50,$D$11:$D$50,D27,$E$11:$E$50,Paramètres!$D$29,$V$11:$V$50,"OK"),0) -> 0
H28: =IF(AND(ISNUMBER(F28),ISNUMBER(G28)),F28*G28,0) -> 0 | J28: =IF(AND(ISNUMBER(F28),ISNUMBER(I28)),F28*I28,0) -> 0 | K28: =IF(OR(H28<=0,J28<=0),"",J28-H28) | L28: =IF(OR(H28<=0,J28<=0),"",J28/H28-1) | Q28: =IF(OR(NOT(ISNUMBER($C$7)),NOT(ISNUMBER(M28)),NOT(ISNUMBER(N28))),"",IF(ISNUMBER(P28),P28,IF((IF(OR(O28="",NOT(ISNUMBER(O28))),Paramètres!$C$8,O28))<=0,"",MIN(EDATE(M28,(12*(IF(OR(O28="",NOT(ISNUMBER(O28))),Paramètres!$C$8,O28)))*MAX(1,INT(((YEAR($C$7+1)-YEAR(M28))*12+MONTH($C$7+1)-MONTH(M28)-(DAY($C$7+1)<DAY(M28)))/(12*(IF(OR(O28="",NOT(ISNUMBER(O28))),Paramètres!$C$8,O28))))+1))-1,N28)))) | S28: =IF(H28=0,0,IF(OR(R28="",R28=0),H28,IF(OR(NOT(ISNUMBER(R28)),(IF(OR(NOT(ISNUMBER(M28)),NOT(ISNUMBER(N28)),N28<=M28),0,MIN(12*(IF(OR(O28="",NOT(ISNUMBER(O28))),Paramètres!$C$8,O28)),(YEAR(N28)-YEAR(M28))*12+MONTH(N28)-MONTH(M28)+1)))<=0),0,MAX(0,H28*(1-R28/(IF(OR(NOT(ISNUMBER(M28)),NOT(ISNUMBER(N28)),N28<=M28),0,MIN(12*(IF(OR(O28="",NOT(ISNUMBER(O28))),Paramètres!$C$8,O28)),(YEAR(N28)-YEAR(M28))*12+MONTH(N28)-MONTH(M28)+1)))))))) -> 0 | T28: =IF(AND(ISNUMBER(N28),ISNUMBER($C$7)),MAX(0,(N28-$C$7)/365.25),0) -> 0 | U28: =IF(AND(ISNUMBER(Q28),ISNUMBER($C$7)),MAX(0,(Q28-$C$7)/365.25),0) -> 0 | V28: =IF(COUNTA(B28,C28,D28,E28,F28,G28,I28,M28,N28,O28,P28,R28)>0,IF(AND(COUNT(Paramètres!$C$8:$C$12)=5,COUNT(Paramètres!$C$16:$C$25)=10,ISNUMBER($C$7),B28<>"",NOT(ISNA(MATCH(C28,Paramètres!$B$29:$B$34,0))),NOT(ISNA(MATCH(E28,Paramètres!$D$29:$D$30,0))),ISNUMBER(F28),F28>0,F28<=Paramètres!$C$22,OR(I28="",AND(ISNUMBER(I28),I28>=0,I28<=Paramètres!$C$21)),IF(E28=Paramètres!$D$29,AND(D28<>"",ISNUMBER(G28),G28>0,G28<=Paramètres!$C$21,ISNUMBER(M28),ISNUMBER(N28),N28>M28,(N(N28)-N(M28))/365.25<=Paramètres!$C$23,OR(O28="",AND(ISNUMBER(O28),O28>=1,O28<=Paramètres!$C$23,O28=INT(N(O28)))),OR(P28="",AND(ISNUMBER(P28),P28>$C$7,P28<=N28)),OR(R28="",AND(ISNUMBER(R28),R28>=0,R28<=Paramètres!$C$24,R28<=(IF(OR(NOT(ISNUMBER(M28)),NOT(ISNUMBER(N28)),N28<=M28),0,MIN(12*(IF(OR(O28="",NOT(ISNUMBER(O28))),Paramètres!$C$8,O28)),(YEAR(N28)-YEAR(M28))*12+MONTH(N28)-MONTH(M28)+1)))))),AND(D28="",OR(G28="",G28=0)))),"OK","À CORRIGER"),"") | W28: =IF(NOT(COUNTA(B28,C28,D28,E28,F28,G28,I28,M28,N28,O28,P28,R28)>0),"",IF(OR(COUNT(Paramètres!$C$8:$C$12)<>5,COUNT(Paramètres!$C$16:$C$25)<>10),"Un paramètre de l'onglet Paramètres est vide.",IF(NOT(ISNUMBER($C$7)),"Date d'analyse manquante.",IF(B28="","Libellé du lot manquant.",IF(ISNA(MATCH(C28,Paramètres!$B$29:$B$34,0)),"Nature hors liste.",IF(ISNA(MATCH(E28,Paramètres!$D$29:$D$30,0)),"Statut hors liste.",IF(NOT(AND(ISNUMBER(F28),F28>0)),"Surface manquante ou nulle.",IF(F28>Paramètres!$C$22,"Surface au-delà du garde-fou de saisie.",IF(AND(I28<>"",NOT(AND(ISNUMBER(I28),I28>=0,I28<=Paramètres!$C$21))),"Valeur locative de marché hors bornes.",IF(AND(E28=Paramètres!$D$29,D28=""),"Lot déclaré loué sans locataire.",IF(AND(E28=Paramètres!$D$29,NOT(AND(ISNUMBER(G28),G28>0))),"Loyer facial manquant ou nul.",IF(AND(E28=Paramètres!$D$29,G28>Paramètres!$C$21),"Loyer facial au-delà du garde-fou de saisie.",IF(AND(E28=Paramètres!$D$29,NOT(ISNUMBER(M28))),"Date de prise d'effet manquante.",IF(AND(E28=Paramètres!$D$29,NOT(ISNUMBER(N28))),"Date d'échéance manquante.",IF(AND(E28=Paramètres!$D$29,N28<=M28),"Échéance antérieure ou égale à la prise d'effet.",IF(AND(E28=Paramètres!$D$29,(N(N28)-N(M28))/365.25>Paramètres!$C$23),"Durée du bail au-delà du garde-fou de saisie.",IF(AND(E28=Paramètres!$D$29,O28<>"",NOT(AND(ISNUMBER(O28),O28>=1,O28<=Paramètres!$C$23,O28=INT(N(O28))))),"Périodicité de sortie hors bornes.",IF(AND(E28=Paramètres!$D$29,P28<>"",NOT(AND(ISNUMBER(P28),P28>$C$7,P28<=N28))),"Sortie forcée hors de l'intervalle admis.",IF(AND(E28=Paramètres!$D$29,R28<>"",NOT(AND(ISNUMBER(R28),R28>=0,R28<=Paramètres!$C$24,R28<=(IF(OR(NOT(ISNUMBER(M28)),NOT(ISNUMBER(N28)),N28<=M28),0,MIN(12*(IF(OR(O28="",NOT(ISNUMBER(O28))),Paramètres!$C$8,O28)),(YEAR(N28)-YEAR(M28))*12+MONTH(N28)-MONTH(M28)+1)))))),"Franchise hors bornes ou plus longue que la période ferme.",IF(AND(E28=Paramètres!$D$30,D28<>""),"Lot vacant avec un locataire renseigné.",IF(AND(E28=Paramètres!$D$30,G28<>"",G28<>0),"Lot vacant avec un loyer renseigné.",IF(AND(E28=Paramètres!$D$29,ISNUMBER(N28),ISNUMBER($C$7),N28<$C$7),"Bail échu, en tacite prolongation.",IF(I28="","Valeur locative de marché non renseignée.",""))))))))))))))))))))))) | X28: =IF(AND(V28="OK",E28=Paramètres!$D$29),SUMIFS($H$11:$H$50,$D$11:$D$50,D28,$E$11:$E$50,Paramètres!$D$29,$V$11:$V$50,"OK"),0) -> 0
H29: =IF(AND(ISNUMBER(F29),ISNUMBER(G29)),F29*G29,0) -> 0 | J29: =IF(AND(ISNUMBER(F29),ISNUMBER(I29)),F29*I29,0) -> 0 | K29: =IF(OR(H29<=0,J29<=0),"",J29-H29) | L29: =IF(OR(H29<=0,J29<=0),"",J29/H29-1) | Q29: =IF(OR(NOT(ISNUMBER($C$7)),NOT(ISNUMBER(M29)),NOT(ISNUMBER(N29))),"",IF(ISNUMBER(P29),P29,IF((IF(OR(O29="",NOT(ISNUMBER(O29))),Paramètres!$C$8,O29))<=0,"",MIN(EDATE(M29,(12*(IF(OR(O29="",NOT(ISNUMBER(O29))),Paramètres!$C$8,O29)))*MAX(1,INT(((YEAR($C$7+1)-YEAR(M29))*12+MONTH($C$7+1)-MONTH(M29)-(DAY($C$7+1)<DAY(M29)))/(12*(IF(OR(O29="",NOT(ISNUMBER(O29))),Paramètres!$C$8,O29))))+1))-1,N29)))) | S29: =IF(H29=0,0,IF(OR(R29="",R29=0),H29,IF(OR(NOT(ISNUMBER(R29)),(IF(OR(NOT(ISNUMBER(M29)),NOT(ISNUMBER(N29)),N29<=M29),0,MIN(12*(IF(OR(O29="",NOT(ISNUMBER(O29))),Paramètres!$C$8,O29)),(YEAR(N29)-YEAR(M29))*12+MONTH(N29)-MONTH(M29)+1)))<=0),0,MAX(0,H29*(1-R29/(IF(OR(NOT(ISNUMBER(M29)),NOT(ISNUMBER(N29)),N29<=M29),0,MIN(12*(IF(OR(O29="",NOT(ISNUMBER(O29))),Paramètres!$C$8,O29)),(YEAR(N29)-YEAR(M29))*12+MONTH(N29)-MONTH(M29)+1)))))))) -> 0 | T29: =IF(AND(ISNUMBER(N29),ISNUMBER($C$7)),MAX(0,(N29-$C$7)/365.25),0) -> 0 | U29: =IF(AND(ISNUMBER(Q29),ISNUMBER($C$7)),MAX(0,(Q29-$C$7)/365.25),0) -> 0 | V29: =IF(COUNTA(B29,C29,D29,E29,F29,G29,I29,M29,N29,O29,P29,R29)>0,IF(AND(COUNT(Paramètres!$C$8:$C$12)=5,COUNT(Paramètres!$C$16:$C$25)=10,ISNUMBER($C$7),B29<>"",NOT(ISNA(MATCH(C29,Paramètres!$B$29:$B$34,0))),NOT(ISNA(MATCH(E29,Paramètres!$D$29:$D$30,0))),ISNUMBER(F29),F29>0,F29<=Paramètres!$C$22,OR(I29="",AND(ISNUMBER(I29),I29>=0,I29<=Paramètres!$C$21)),IF(E29=Paramètres!$D$29,AND(D29<>"",ISNUMBER(G29),G29>0,G29<=Paramètres!$C$21,ISNUMBER(M29),ISNUMBER(N29),N29>M29,(N(N29)-N(M29))/365.25<=Paramètres!$C$23,OR(O29="",AND(ISNUMBER(O29),O29>=1,O29<=Paramètres!$C$23,O29=INT(N(O29)))),OR(P29="",AND(ISNUMBER(P29),P29>$C$7,P29<=N29)),OR(R29="",AND(ISNUMBER(R29),R29>=0,R29<=Paramètres!$C$24,R29<=(IF(OR(NOT(ISNUMBER(M29)),NOT(ISNUMBER(N29)),N29<=M29),0,MIN(12*(IF(OR(O29="",NOT(ISNUMBER(O29))),Paramètres!$C$8,O29)),(YEAR(N29)-YEAR(M29))*12+MONTH(N29)-MONTH(M29)+1)))))),AND(D29="",OR(G29="",G29=0)))),"OK","À CORRIGER"),"") | W29: =IF(NOT(COUNTA(B29,C29,D29,E29,F29,G29,I29,M29,N29,O29,P29,R29)>0),"",IF(OR(COUNT(Paramètres!$C$8:$C$12)<>5,COUNT(Paramètres!$C$16:$C$25)<>10),"Un paramètre de l'onglet Paramètres est vide.",IF(NOT(ISNUMBER($C$7)),"Date d'analyse manquante.",IF(B29="","Libellé du lot manquant.",IF(ISNA(MATCH(C29,Paramètres!$B$29:$B$34,0)),"Nature hors liste.",IF(ISNA(MATCH(E29,Paramètres!$D$29:$D$30,0)),"Statut hors liste.",IF(NOT(AND(ISNUMBER(F29),F29>0)),"Surface manquante ou nulle.",IF(F29>Paramètres!$C$22,"Surface au-delà du garde-fou de saisie.",IF(AND(I29<>"",NOT(AND(ISNUMBER(I29),I29>=0,I29<=Paramètres!$C$21))),"Valeur locative de marché hors bornes.",IF(AND(E29=Paramètres!$D$29,D29=""),"Lot déclaré loué sans locataire.",IF(AND(E29=Paramètres!$D$29,NOT(AND(ISNUMBER(G29),G29>0))),"Loyer facial manquant ou nul.",IF(AND(E29=Paramètres!$D$29,G29>Paramètres!$C$21),"Loyer facial au-delà du garde-fou de saisie.",IF(AND(E29=Paramètres!$D$29,NOT(ISNUMBER(M29))),"Date de prise d'effet manquante.",IF(AND(E29=Paramètres!$D$29,NOT(ISNUMBER(N29))),"Date d'échéance manquante.",IF(AND(E29=Paramètres!$D$29,N29<=M29),"Échéance antérieure ou égale à la prise d'effet.",IF(AND(E29=Paramètres!$D$29,(N(N29)-N(M29))/365.25>Paramètres!$C$23),"Durée du bail au-delà du garde-fou de saisie.",IF(AND(E29=Paramètres!$D$29,O29<>"",NOT(AND(ISNUMBER(O29),O29>=1,O29<=Paramètres!$C$23,O29=INT(N(O29))))),"Périodicité de sortie hors bornes.",IF(AND(E29=Paramètres!$D$29,P29<>"",NOT(AND(ISNUMBER(P29),P29>$C$7,P29<=N29))),"Sortie forcée hors de l'intervalle admis.",IF(AND(E29=Paramètres!$D$29,R29<>"",NOT(AND(ISNUMBER(R29),R29>=0,R29<=Paramètres!$C$24,R29<=(IF(OR(NOT(ISNUMBER(M29)),NOT(ISNUMBER(N29)),N29<=M29),0,MIN(12*(IF(OR(O29="",NOT(ISNUMBER(O29))),Paramètres!$C$8,O29)),(YEAR(N29)-YEAR(M29))*12+MONTH(N29)-MONTH(M29)+1)))))),"Franchise hors bornes ou plus longue que la période ferme.",IF(AND(E29=Paramètres!$D$30,D29<>""),"Lot vacant avec un locataire renseigné.",IF(AND(E29=Paramètres!$D$30,G29<>"",G29<>0),"Lot vacant avec un loyer renseigné.",IF(AND(E29=Paramètres!$D$29,ISNUMBER(N29),ISNUMBER($C$7),N29<$C$7),"Bail échu, en tacite prolongation.",IF(I29="","Valeur locative de marché non renseignée.",""))))))))))))))))))))))) | X29: =IF(AND(V29="OK",E29=Paramètres!$D$29),SUMIFS($H$11:$H$50,$D$11:$D$50,D29,$E$11:$E$50,Paramètres!$D$29,$V$11:$V$50,"OK"),0) -> 0
... H50: =IF(AND(ISNUMBER(F50),ISNUMBER(G50)),F50*G50,0) -> 0 | J50: =IF(AND(ISNUMBER(F50),ISNUMBER(I50)),F50*I50,0) -> 0 | K50: =IF(OR(H50<=0,J50<=0),"",J50-H50) | L50: =IF(OR(H50<=0,J50<=0),"",J50/H50-1) | Q50: =IF(OR(NOT(ISNUMBER($C$7)),NOT(ISNUMBER(M50)),NOT(ISNUMBER(N50))),"",IF(ISNUMBER(P50),P50,IF((IF(OR(O50="",NOT(ISNUMBER(O50))),Paramètres!$C$8,O50))<=0,"",MIN(EDATE(M50,(12*(IF(OR(O50="",NOT(ISNUMBER(O50))),Paramètres!$C$8,O50)))*MAX(1,INT(((YEAR($C$7+1)-YEAR(M50))*12+MONTH($C$7+1)-MONTH(M50)-(DAY($C$7+1)<DAY(M50)))/(12*(IF(OR(O50="",NOT(ISNUMBER(O50))),Paramètres!$C$8,O50))))+1))-1,N50)))) | S50: =IF(H50=0,0,IF(OR(R50="",R50=0),H50,IF(OR(NOT(ISNUMBER(R50)),(IF(OR(NOT(ISNUMBER(M50)),NOT(ISNUMBER(N50)),N50<=M50),0,MIN(12*(IF(OR(O50="",NOT(ISNUMBER(O50))),Paramètres!$C$8,O50)),(YEAR(N50)-YEAR(M50))*12+MONTH(N50)-MONTH(M50)+1)))<=0),0,MAX(0,H50*(1-R50/(IF(OR(NOT(ISNUMBER(M50)),NOT(ISNUMBER(N50)),N50<=M50),0,MIN(12*(IF(OR(O50="",NOT(ISNUMBER(O50))),Paramètres!$C$8,O50)),(YEAR(N50)-YEAR(M50))*12+MONTH(N50)-MONTH(M50)+1)))))))) -> 0 | T50: =IF(AND(ISNUMBER(N50),ISNUMBER($C$7)),MAX(0,(N50-$C$7)/365.25),0) -> 0 | U50: =IF(AND(ISNUMBER(Q50),ISNUMBER($C$7)),MAX(0,(Q50-$C$7)/365.25),0) -> 0 | V50: =IF(COUNTA(B50,C50,D50,E50,F50,G50,I50,M50,N50,O50,P50,R50)>0,IF(AND(COUNT(Paramètres!$C$8:$C$12)=5,COUNT(Paramètres!$C$16:$C$25)=10,ISNUMBER($C$7),B50<>"",NOT(ISNA(MATCH(C50,Paramètres!$B$29:$B$34,0))),NOT(ISNA(MATCH(E50,Paramètres!$D$29:$D$30,0))),ISNUMBER(F50),F50>0,F50<=Paramètres!$C$22,OR(I50="",AND(ISNUMBER(I50),I50>=0,I50<=Paramètres!$C$21)),IF(E50=Paramètres!$D$29,AND(D50<>"",ISNUMBER(G50),G50>0,G50<=Paramètres!$C$21,ISNUMBER(M50),ISNUMBER(N50),N50>M50,(N(N50)-N(M50))/365.25<=Paramètres!$C$23,OR(O50="",AND(ISNUMBER(O50),O50>=1,O50<=Paramètres!$C$23,O50=INT(N(O50)))),OR(P50="",AND(ISNUMBER(P50),P50>$C$7,P50<=N50)),OR(R50="",AND(ISNUMBER(R50),R50>=0,R50<=Paramètres!$C$24,R50<=(IF(OR(NOT(ISNUMBER(M50)),NOT(ISNUMBER(N50)),N50<=M50),0,MIN(12*(IF(OR(O50="",NOT(ISNUMBER(O50))),Paramètres!$C$8,O50)),(YEAR(N50)-YEAR(M50))*12+MONTH(N50)-MONTH(M50)+1)))))),AND(D50="",OR(G50="",G50=0)))),"OK","À CORRIGER"),"") | W50: =IF(NOT(COUNTA(B50,C50,D50,E50,F50,G50,I50,M50,N50,O50,P50,R50)>0),"",IF(OR(COUNT(Paramètres!$C$8:$C$12)<>5,COUNT(Paramètres!$C$16:$C$25)<>10),"Un paramètre de l'onglet Paramètres est vide.",IF(NOT(ISNUMBER($C$7)),"Date d'analyse manquante.",IF(B50="","Libellé du lot manquant.",IF(ISNA(MATCH(C50,Paramètres!$B$29:$B$34,0)),"Nature hors liste.",IF(ISNA(MATCH(E50,Paramètres!$D$29:$D$30,0)),"Statut hors liste.",IF(NOT(AND(ISNUMBER(F50),F50>0)),"Surface manquante ou nulle.",IF(F50>Paramètres!$C$22,"Surface au-delà du garde-fou de saisie.",IF(AND(I50<>"",NOT(AND(ISNUMBER(I50),I50>=0,I50<=Paramètres!$C$21))),"Valeur locative de marché hors bornes.",IF(AND(E50=Paramètres!$D$29,D50=""),"Lot déclaré loué sans locataire.",IF(AND(E50=Paramètres!$D$29,NOT(AND(ISNUMBER(G50),G50>0))),"Loyer facial manquant ou nul.",IF(AND(E50=Paramètres!$D$29,G50>Paramètres!$C$21),"Loyer facial au-delà du garde-fou de saisie.",IF(AND(E50=Paramètres!$D$29,NOT(ISNUMBER(M50))),"Date de prise d'effet manquante.",IF(AND(E50=Paramètres!$D$29,NOT(ISNUMBER(N50))),"Date d'échéance manquante.",IF(AND(E50=Paramètres!$D$29,N50<=M50),"Échéance antérieure ou égale à la prise d'effet.",IF(AND(E50=Paramètres!$D$29,(N(N50)-N(M50))/365.25>Paramètres!$C$23),"Durée du bail au-delà du garde-fou de saisie.",IF(AND(E50=Paramètres!$D$29,O50<>"",NOT(AND(ISNUMBER(O50),O50>=1,O50<=Paramètres!$C$23,O50=INT(N(O50))))),"Périodicité de sortie hors bornes.",IF(AND(E50=Paramètres!$D$29,P50<>"",NOT(AND(ISNUMBER(P50),P50>$C$7,P50<=N50))),"Sortie forcée hors de l'intervalle admis.",IF(AND(E50=Paramètres!$D$29,R50<>"",NOT(AND(ISNUMBER(R50),R50>=0,R50<=Paramètres!$C$24,R50<=(IF(OR(NOT(ISNUMBER(M50)),NOT(ISNUMBER(N50)),N50<=M50),0,MIN(12*(IF(OR(O50="",NOT(ISNUMBER(O50))),Paramètres!$C$8,O50)),(YEAR(N50)-YEAR(M50))*12+MONTH(N50)-MONTH(M50)+1)))))),"Franchise hors bornes ou plus longue que la période ferme.",IF(AND(E50=Paramètres!$D$30,D50<>""),"Lot vacant avec un locataire renseigné.",IF(AND(E50=Paramètres!$D$30,G50<>"",G50<>0),"Lot vacant avec un loyer renseigné.",IF(AND(E50=Paramètres!$D$29,ISNUMBER(N50),ISNUMBER($C$7),N50<$C$7),"Bail échu, en tacite prolongation.",IF(I50="","Valeur locative de marché non renseignée.",""))))))))))))))))))))))) | X50: =IF(AND(V50="OK",E50=Paramètres!$D$29),SUMIFS($H$11:$H$50,$D$11:$D$50,D50,$E$11:$E$50,Paramètres!$D$29,$V$11:$V$50,"OK"),0) -> 0
B52: Ce que vous saisissez, colonne par colonne :
B53: B Lot | D53: Identifiant du lot, libre mais obligatoire : c'est lui qui nomme la ligne dans les contrôles.
B54: C Nature | D54: Liste déroulante alimentée par Paramètres.
B55: D Locataire | D55: Le nom de la signature. Le même nom sur deux lots additionne leurs loyers dans la concentration.
B56: E Statut | D56: Loué ou Vacant. Un lot vacant garde sa surface et sa valeur locative, sans locataire ni loyer.
B57: F Surface | D57: Surface locative du lot.
B58: G Loyer facial €/m²/an HT HC | D58: Loyer facial hors taxes hors charges, par mètre carré et par an, avant toute franchise.
B59: I VLM €/m²/an | D59: Valeur locative de marché estimée, notée VLM en en-tête. À renseigner sur tous les lots, vacants compris : sans elle, ni le taux d'occupation financier ni la réversion ne se calculent, et la ligne est comptée comme à compléter.
B60: M Prise d'effet | D60: Date de prise d'effet du bail, en vraie date.
B61: N Échéance | D61: Dernier jour du bail, en vraie date.
B62: O Périodicité de sortie (ans) | D62: Vide : la périodicité légale de Paramètres. 6 ou 9 pour un bail de bureaux, un bail de plus de neuf ans, un local monovalent ou de stockage ayant renoncé à ses triennales.
B63: P Sortie forcée (facultatif) | D63: À ne remplir que pour imposer une date de sortie connue, postérieure à la date d'analyse et au plus tard à l'échéance.
B64: R Franchise (mois) | D64: Nombre de mois de loyer offerts au preneur à l'entrée dans les lieux, étalés sur la période d'engagement ferme initiale, c'est-à-dire la durée pendant laquelle il ne peut pas partir.
B66: CorpusImmo, millésime 2026. Modèle d'aide à la décision : ne constitue ni un conseil en investissement, ni un conseil fiscal, ni une expertise au sens de la charte de l'expertise en évaluation immobilière. Vérifiez les paramètres avant tout engagement.

Sheet Synthèse
B1: CorpusImmo · corpus.immo · Estimer, comparer, décider. Sur les ventes réelles.
B2: Synthèse
B3: Ce que le rent roll dit de l'immeuble : occupation, loyers, réversion, durées résiduelles et concentration. Rien à saisir ici.
B5: Toutes les valeurs de cet onglet sont calculées à partir de l'onglet Rent roll. Une ligne à corriger en est exclue, jamais comptée à zéro.
B6: CONTRÔLES DE COHÉRENCE
B7: État locatif exploitable | C7: =IF(AND(ISNUMBER('Rent roll'!$C$7),COUNT(Paramètres!$C$8:$C$12)=5,COUNT(Paramètres!$C$16:$C$25)=10,Synthèse!$C$34>0,Synthèse!$C$35=0),"OK","À CORRIGER") -> OK | D7: Rouge tant que la date d'analyse manque, qu'aucun bail n'est retenu, qu'une ligne est à corriger ou à compléter, ou qu'un paramètre est vide.
B8: Aucune ligne à corriger ou à compléter | C8: =IF(Synthèse!$C$35=0,"OK","À CORRIGER") -> OK | D8: Rouge : une ligne du rent roll porte un motif en colonne W. Une ligne à corriger est rouge et exclue de tous les totaux ; une ligne à compléter reste verte et comptée, mais il lui manque sa valeur locative.
B9: Première ligne à corriger ou à compléter | C9: =IF(Synthèse!$C$35=0,"","Ligne "&TEXT(ROW('Rent roll'!$B$11)+MIN(IF(COUNTIF('Rent roll'!$V$11:$V$50,"À CORRIGER")=0,ROWS('Rent roll'!$V$11:$V$50)+1,MATCH("À CORRIGER",'Rent roll'!$V$11:$V$50,0)),IF(COUNTIF('Rent roll'!$W$11:$W$50,"Valeur locative de marché non renseignée.")=0,ROWS('Rent roll'!$V$11:$V$50)+1,MATCH("Valeur locative de marché non renseignée.",'Rent roll'!$W$11:$W$50,0)))-1,"0")&IF(INDEX('Rent roll'!$B$11:$B$50,MIN(IF(COUNTIF('Rent roll'!$V$11:$V$50,"À CORRIGER")=0,ROWS('Rent roll'!$V$11:$V$50)+1,MATCH("À CORRIGER",'Rent roll'!$V$11:$V$50,0)),IF(COUNTIF('Rent roll'!$W$11:$W$50,"Valeur locative de marché non renseignée.")=0,ROWS('Rent roll'!$V$11:$V$50)+1,MATCH("Valeur locative de marché non renseignée.",'Rent roll'!$W$11:$W$50,0))))="",""," : "&INDEX('Rent roll'!$B$11:$B$50,MIN(IF(COUNTIF('Rent roll'!$V$11:$V$50,"À CORRIGER")=0,ROWS('Rent roll'!$V$11:$V$50)+1,MATCH("À CORRIGER",'Rent roll'!$V$11:$V$50,0)),IF(COUNTIF('Rent roll'!$W$11:$W$50,"Valeur locative de marché non renseignée.")=0,ROWS('Rent roll'!$V$11:$V$50)+1,MATCH("Valeur locative de marché non renseignée.",'Rent roll'!$W$11:$W$50,0)))))) | D9: Le numéro de ligne et le libellé du lot en cause. Vide quand tout est en ordre. Son motif se lit en colonne W du rent roll.
B10: Valeur locative renseignée sur tous les lots | C10: =IF(AND(COUNTIF('Rent roll'!$V$11:$V$50,"OK")>0,COUNTIFS('Rent roll'!$V$11:$V$50,"OK",'Rent roll'!$I$11:$I$50,"")=0),"OK","À CORRIGER") -> OK | D10: Rouge : un lot retenu, loué ou vacant, n'a pas de valeur locative de marché. Le taux d'occupation financier et la réversion restent vides plutôt que faux : sur un lot loué, une valeur locative absente vaudrait zéro et retournerait la réversion. La ligne en cause est nommée deux lignes plus haut.
B11: Échéancier recoupé avec le rent roll | C11: =IF(AND(ROUND(Échéancier!$C$27,2)=ROUND(Synthèse!$C$24,2),ROUND(Échéancier!$F$27,2)=ROUND(Synthèse!$C$24,2)),"OK","À CORRIGER") -> OK | D11: Le total de l'échéancier, au terme comme à la sortie, doit être égal au loyer facial en place. Rouge : un loyer n'est tombé dans aucune période, reprenez les dates des lignes retenues. Ni l'échéancier ni l'année de pointe ne veulent rien dire tant qu'il n'est pas vert.
B12: Taux vraisemblable | C12: =IF(AND(ISNUMBER(Paramètres!$C$25),OR(NOT(ISNUMBER(Paramètres!$C$16)),Paramètres!$C$16<=0,Paramètres!$C$16>=Paramètres!$C$25),OR(NOT(ISNUMBER(Paramètres!$C$17)),Paramètres!$C$17<=0,Paramètres!$C$17>=Paramètres!$C$25)),"OK","À CORRIGER") -> OK | D12: Rouge : un seuil d'alerte de Paramètres (Paramètres!C16 ou Paramètres!C17) est strictement positif et inférieur au plancher de plausibilité de Paramètres!C25, ce qui est presque toujours une saisie en fraction. Rouge aussi si le plancher lui-même est vide : le contrôle échoue fermé plutôt que d'afficher un vert silencieux.
B14: SURFACES ET OCCUPATION
B15: Surface totale | C15: =SUMIFS('Rent roll'!$F$11:$F$50,'Rent roll'!$V$11:$V$50,"OK") -> 1755 | D15: Tous les lots retenus, loués et vacants.
B16: Surface louée | C16: =SUMIFS('Rent roll'!$F$11:$F$50,'Rent roll'!$V$11:$V$50,"OK",'Rent roll'!$E$11:$E$50,Paramètres!$D$29) -> 1660 | D16: Lots dont le statut est Loué.
B17: Surface vacante | C17: =SUMIFS('Rent roll'!$F$11:$F$50,'Rent roll'!$V$11:$V$50,"OK",'Rent roll'!$E$11:$E$50,Paramètres!$D$30) -> 95 | D17: Lots dont le statut est Vacant.
B18: Taux d'occupation physique | C18: =IF(Synthèse!$C$15=0,"",Synthèse!$C$16/Synthèse!$C$15) -> 0.94586895 | D18: Surface louée rapportée à la surface totale. La lecture la plus simple, la moins fidèle à la valeur.
B19: Valeur locative de marché, ensemble de l'immeuble | C19: =SUMIFS('Rent roll'!$J$11:$J$50,'Rent roll'!$V$11:$V$50,"OK") -> 566100 | D19: Somme des valeurs locatives annuelles de tous les lots retenus.
B20: Valeur locative de marché des surfaces vacantes | C20: =SUMIFS('Rent roll'!$J$11:$J$50,'Rent roll'!$V$11:$V$50,"OK",'Rent roll'!$E$11:$E$50,Paramètres!$D$30) -> 36100 | D20: Le loyer que rapporteraient les lots vacants s'ils étaient reloués au marché.
B21: Taux d'occupation financier (EPRA) | C21: =IF(OR(Synthèse!$C$10<>"OK",Synthèse!$C$19=0),"",1-Synthèse!$C$20/Synthèse!$C$19) -> 0.93623035 | D21: Un moins la valeur locative des surfaces vacantes rapportée à celle de l'ensemble. C'est le taux que lisent les foncières et les investisseurs.
B23: LOYERS EN PLACE, FRANCHISES ET RÉVERSION
B24: Loyer facial annuel en place | C24: =SUMIFS('Rent roll'!$H$11:$H$50,'Rent roll'!$V$11:$V$50,"OK",'Rent roll'!$E$11:$E$50,Paramètres!$D$29) -> 500730 | D24: Hors taxes hors charges, avant franchise. C'est le loyer du bail.
B25: Loyer économique annuel en place | C25: =SUMIFS('Rent roll'!$S$11:$S$50,'Rent roll'!$V$11:$V$50,"OK",'Rent roll'!$E$11:$E$50,Paramètres!$D$29) -> 476956.67 | D25: Loyer facial net des franchises étalées sur la période d'engagement ferme. C'est ce que l'immeuble encaisse vraiment.
B26: Effet des franchises | C26: =Synthèse!$C$24-Synthèse!$C$25 -> 23773.333 | D26: Écart entre les deux loyers.
B27: Effet des franchises, en part du loyer facial | C27: =IF(Synthèse!$C$24=0,"",Synthèse!$C$26/Synthèse!$C$24) -> 0.04747735 | D27: Repère de marché sur la franchise usuelle : Paramètres!C18.
B28: Loyer facial moyen au mètre carré loué | C28: =IF(Synthèse!$C$16=0,"",Synthèse!$C$24/Synthèse!$C$16) -> 301.64458 | D28: Loyer facial rapporté à la surface louée.
B29: Valeur locative de marché des surfaces louées | C29: =IF(Synthèse!$C$10<>"OK","",SUMIFS('Rent roll'!$J$11:$J$50,'Rent roll'!$V$11:$V$50,"OK",'Rent roll'!$E$11:$E$50,Paramètres!$D$29)) -> 530000 | D29: Base de comparaison du loyer en place. Vide tant qu'un lot retenu n'a pas de valeur locative : la somme porterait alors sur un périmètre plus étroit que le loyer auquel on la compare.
B30: Réversion | C30: =IF(OR(Synthèse!$C$10<>"OK",Synthèse!$C$24=0,Synthèse!$C$29=0),"",Synthèse!$C$29-Synthèse!$C$24) -> 29270 | D30: Valeur locative des surfaces louées moins loyer facial. Positive : le loyer en place est sous le marché. Vide, et jamais approchée, tant que le contrôle de valeur locative est rouge.
B31: Réversion, en part du loyer facial | C31: =IF(OR(Synthèse!$C$10<>"OK",Synthèse!$C$24=0,Synthèse!$C$29=0),"",Synthèse!$C$29/Synthèse!$C$24-1) -> 0.058454656 | D31: Le premier chiffre que regarde un investisseur après le taux de rendement.
B33: DURÉES RÉSIDUELLES
B34: Baux retenus dans les moyennes | C34: =COUNTIFS('Rent roll'!$V$11:$V$50,"OK",'Rent roll'!$E$11:$E$50,Paramètres!$D$29) -> 6 | D34: Lots loués dont la ligne est cohérente. Une ligne à corriger n'est pas comptée à zéro : elle est exclue.
B35: Lignes à corriger ou à compléter | C35: =COUNTIF('Rent roll'!$V$11:$V$50,"À CORRIGER")+COUNTIFS('Rent roll'!$V$11:$V$50,"OK",'Rent roll'!$I$11:$I$50,"") -> 0 | D35: Lignes rouges en colonne V du rent roll, plus lignes vertes auxquelles il manque leur valeur locative. Zéro attendu avant toute lecture.
B36: Baux échus, en tacite prolongation | C36: =COUNTIFS('Rent roll'!$V$11:$V$50,"OK",'Rent roll'!$E$11:$E$50,Paramètres!$D$29,'Rent roll'!$N$11:$N$50,"<"&'Rent roll'!$C$7) -> 0 | D36: Baux dont l'échéance est antérieure à la date d'analyse. Ils comptent zéro an dans les moyennes.
B37: Loyer facial des baux échus | C37: =SUMIFS('Rent roll'!$H$11:$H$50,'Rent roll'!$V$11:$V$50,"OK",'Rent roll'!$E$11:$E$50,Paramètres!$D$29,'Rent roll'!$N$11:$N$50,"<"&'Rent roll'!$C$7) -> 0 | D37: Congé possible à tout moment, avec le préavis de Paramètres!C9.
B38: WAULT, durée résiduelle jusqu'au terme | C38: =IF(Synthèse!$C$24=0,"",SUMPRODUCT(('Rent roll'!$V$11:$V$50="OK")*('Rent roll'!$E$11:$E$50=Paramètres!$D$29)*'Rent roll'!$H$11:$H$50*'Rent roll'!$T$11:$T$50)/Synthèse!$C$24) -> 4.8334008 | D38: Moyenne des durées jusqu'au terme des baux, pondérée par le loyer facial. L'horizon maximal de sécurisation des revenus.
B39: WALB, durée résiduelle ferme | C39: =IF(Synthèse!$C$24=0,"",SUMPRODUCT(('Rent roll'!$V$11:$V$50="OK")*('Rent roll'!$E$11:$E$50=Paramètres!$D$29)*'Rent roll'!$H$11:$H$50*'Rent roll'!$U$11:$U$50)/Synthèse!$C$24) -> 2.1599134 | D39: Jusqu'à la prochaine faculté de sortie du locataire, pondérée par le loyer facial. Repères publiés : Paramètres!C19 et Paramètres!C20.
B40: WAULT sur base de loyer économique | C40: =IF(Synthèse!$C$25=0,"",SUMPRODUCT(('Rent roll'!$V$11:$V$50="OK")*('Rent roll'!$E$11:$E$50=Paramètres!$D$29)*'Rent roll'!$S$11:$S$50*'Rent roll'!$T$11:$T$50)/Synthèse!$C$25) -> 4.7611342 | D40: Même calcul, pondéré par le loyer économique. Il pèse moins les baux qui ont reçu une franchise.
B41: WALB sur base de loyer économique | C41: =IF(Synthèse!$C$25=0,"",SUMPRODUCT(('Rent roll'!$V$11:$V$50="OK")*('Rent roll'!$E$11:$E$50=Paramètres!$D$29)*'Rent roll'!$S$11:$S$50*'Rent roll'!$U$11:$U$50)/Synthèse!$C$25) -> 2.1039555 | D41: La durée ferme telle que la voit celui qui encaisse, franchises déduites.
B42: Écart entre le WAULT et le WALB | C42: =IF(OR(Synthèse!$C$38="",Synthèse!$C$39=""),"",Synthèse!$C$38-Synthèse!$C$39) -> 2.6734874 | D42: Le poids des options de sortie. Plus il est large, plus le WAULT est trompeur.
B44: CONCENTRATION LOCATIVE
B45: Nombre de locataires | C45: =IF(Synthèse!$C$24=0,0,ROUND(SUMPRODUCT(('Rent roll'!$V$11:$V$50="OK")*('Rent roll'!$E$11:$E$50=Paramètres!$D$29)*'Rent roll'!$H$11:$H$50/('Rent roll'!$X$11:$X$50+('Rent roll'!$X$11:$X$50=0))),0)) -> 5 | D45: Signatures distinctes, pas nombre de lots. Un locataire présent sur deux lots compte pour un.
B46: Premier locataire | C46: =IF(Synthèse!$C$24=0,"",INDEX('Rent roll'!$D$11:$D$50,MATCH(MAX('Rent roll'!$X$11:$X$50),'Rent roll'!$X$11:$X$50,0))) -> Locataire Alpha | D46: Celui qui pèse le plus lourd, tous ses lots additionnés.
B47: Poids du premier locataire | C47: =IF(Synthèse!$C$24=0,"",MAX('Rent roll'!$X$11:$X$50)/Synthèse!$C$24) -> 0.35564076 | D47: Part du loyer facial en place portée par cette seule signature.
B48: Dépendance sous le seuil d'alerte | C48: =IF(Synthèse!$C$47<>"",IF(Synthèse!$C$47<=Paramètres!$C$17,"OK","À CORRIGER"),"") -> OK | D48: Seuil en Paramètres!C17. Rouge : l'immeuble se valorise comme un pari sur une signature.
B50: CorpusImmo, millésime 2026. Modèle d'aide à la décision : ne constitue ni un conseil en investissement, ni un conseil fiscal, ni une expertise au sens de la charte de l'expertise en évaluation immobilière. Vérifiez les paramètres avant tout engagement.

Sheet Échéancier
B1: CorpusImmo · corpus.immo · Estimer, comparer, décider. Sur les ventes réelles.
B2: Échéancier des baux
B3: Un WAULT de cinq ans ne vaut rien si tout tombe la même année. Rien à saisir ici.
B5: Le tableau répartit le loyer facial en place par période de sortie : au terme des baux d'un côté, à la prochaine faculté de sortie de l'autre. C'est la lecture que fait un acquéreur, il ne cherche pas la moyenne, il cherche le pic.
B6: Une période qui concentre plus que le seuil d'alerte de Paramètres est un risque de refinancement autant qu'un risque locatif : la banque valorise l'immeuble sur le loyer sécurisé au-delà de cette date.
B7: Le total de chaque colonne de loyer est égal au loyer facial en place du rent roll : c'est le contrôle de la ligne 28. Si un loyer manque à l'appel, il passe au rouge.
B9: Période | C9: Loyer au terme | D9: Part au terme | E9: Baux au terme | F9: Loyer à la sortie | G9: Part à la sortie | H9: Baux à la sortie | I9: Alerte
B10: Baux échus, en tacite prolongation | C10: =IF(NOT(ISNUMBER('Rent roll'!$C$7)),0,SUMIFS('Rent roll'!$H$11:$H$50,'Rent roll'!$E$11:$E$50,Paramètres!$D$29,'Rent roll'!$V$11:$V$50,"OK",'Rent roll'!$N$11:$N$50,"<"&'Rent roll'!$C$7)) -> 0 | D10: =IF(Synthèse!$C$24=0,"",C10/Synthèse!$C$24) -> 0 | E10: =IF(NOT(ISNUMBER('Rent roll'!$C$7)),0,COUNTIFS('Rent roll'!$E$11:$E$50,Paramètres!$D$29,'Rent roll'!$V$11:$V$50,"OK",'Rent roll'!$N$11:$N$50,"<"&'Rent roll'!$C$7)) -> 0 | F10: =IF(NOT(ISNUMBER('Rent roll'!$C$7)),0,SUMIFS('Rent roll'!$H$11:$H$50,'Rent roll'!$E$11:$E$50,Paramètres!$D$29,'Rent roll'!$V$11:$V$50,"OK",'Rent roll'!$Q$11:$Q$50,"<"&'Rent roll'!$C$7)) -> 0 | G10: =IF(Synthèse!$C$24=0,"",F10/Synthèse!$C$24) -> 0 | H10: =IF(NOT(ISNUMBER('Rent roll'!$C$7)),0,COUNTIFS('Rent roll'!$E$11:$E$50,Paramètres!$D$29,'Rent roll'!$V$11:$V$50,"OK",'Rent roll'!$Q$11:$Q$50,"<"&'Rent roll'!$C$7)) -> 0 | I10: =IF(OR(F10=0,NOT(ISNUMBER(Paramètres!$C$9))),"","Congé à tout moment, préavis de "&TEXT(Paramètres!$C$9,"0")&" mois.")
B11: =IF(NOT(ISNUMBER('Rent roll'!$C$7)),"",YEAR('Rent roll'!$C$7)) -> 2026 | C11: =IF($B11="",0,SUMIFS('Rent roll'!$H$11:$H$50,'Rent roll'!$E$11:$E$50,Paramètres!$D$29,'Rent roll'!$V$11:$V$50,"OK",'Rent roll'!$N$11:$N$50,">="&MAX(DATE($B11,1,1),'Rent roll'!$C$7),'Rent roll'!$N$11:$N$50,"<="&DATE($B11,12,31))) -> 54600 | D11: =IF(Synthèse!$C$24=0,"",C11/Synthèse!$C$24) -> 0.1090408 | E11: =IF($B11="",0,COUNTIFS('Rent roll'!$E$11:$E$50,Paramètres!$D$29,'Rent roll'!$V$11:$V$50,"OK",'Rent roll'!$N$11:$N$50,">="&MAX(DATE($B11,1,1),'Rent roll'!$C$7),'Rent roll'!$N$11:$N$50,"<="&DATE($B11,12,31))) -> 1 | F11: =IF($B11="",0,SUMIFS('Rent roll'!$H$11:$H$50,'Rent roll'!$E$11:$E$50,Paramètres!$D$29,'Rent roll'!$V$11:$V$50,"OK",'Rent roll'!$Q$11:$Q$50,">="&MAX(DATE($B11,1,1),'Rent roll'!$C$7),'Rent roll'!$Q$11:$Q$50,"<="&DATE($B11,12,31))) -> 139850 | G11: =IF(Synthèse!$C$24=0,"",F11/Synthèse!$C$24) -> 0.27929223 | H11: =IF($B11="",0,COUNTIFS('Rent roll'!$E$11:$E$50,Paramètres!$D$29,'Rent roll'!$V$11:$V$50,"OK",'Rent roll'!$Q$11:$Q$50,">="&MAX(DATE($B11,1,1),'Rent roll'!$C$7),'Rent roll'!$Q$11:$Q$50,"<="&DATE($B11,12,31))) -> 2 | I11: =IF(OR($B11="",G11="",NOT(ISNUMBER(Paramètres!$C$16))),"",IF(G11>Paramètres!$C$16,"Concentration forte",""))
B12: =IF($B11="","",$B11+1) -> 2027 | C12: =IF($B12="",0,SUMIFS('Rent roll'!$H$11:$H$50,'Rent roll'!$E$11:$E$50,Paramètres!$D$29,'Rent roll'!$V$11:$V$50,"OK",'Rent roll'!$N$11:$N$50,">="&MAX(DATE($B12,1,1),'Rent roll'!$C$7),'Rent roll'!$N$11:$N$50,"<="&DATE($B12,12,31))) -> 0 | D12: =IF(Synthèse!$C$24=0,"",C12/Synthèse!$C$24) -> 0 | E12: =IF($B12="",0,COUNTIFS('Rent roll'!$E$11:$E$50,Paramètres!$D$29,'Rent roll'!$V$11:$V$50,"OK",'Rent roll'!$N$11:$N$50,">="&MAX(DATE($B12,1,1),'Rent roll'!$C$7),'Rent roll'!$N$11:$N$50,"<="&DATE($B12,12,31))) -> 0 | F12: =IF($B12="",0,SUMIFS('Rent roll'!$H$11:$H$50,'Rent roll'!$E$11:$E$50,Paramètres!$D$29,'Rent roll'!$V$11:$V$50,"OK",'Rent roll'!$Q$11:$Q$50,">="&MAX(DATE($B12,1,1),'Rent roll'!$C$7),'Rent roll'!$Q$11:$Q$50,"<="&DATE($B12,12,31))) -> 75600 | G12: =IF(Synthèse!$C$24=0,"",F12/Synthèse!$C$24) -> 0.15097957 | H12: =IF($B12="",0,COUNTIFS('Rent roll'!$E$11:$E$50,Paramètres!$D$29,'Rent roll'!$V$11:$V$50,"OK",'Rent roll'!$Q$11:$Q$50,">="&MAX(DATE($B12,1,1),'Rent roll'!$C$7),'Rent roll'!$Q$11:$Q$50,"<="&DATE($B12,12,31))) -> 1 | I12: =IF(OR($B12="",G12="",NOT(ISNUMBER(Paramètres!$C$16))),"",IF(G12>Paramètres!$C$16,"Concentration forte",""))
B13: =IF($B12="","",$B12+1) -> 2028 | C13: =IF($B13="",0,SUMIFS('Rent roll'!$H$11:$H$50,'Rent roll'!$E$11:$E$50,Paramètres!$D$29,'Rent roll'!$V$11:$V$50,"OK",'Rent roll'!$N$11:$N$50,">="&MAX(DATE($B13,1,1),'Rent roll'!$C$7),'Rent roll'!$N$11:$N$50,"<="&DATE($B13,12,31))) -> 0 | D13: =IF(Synthèse!$C$24=0,"",C13/Synthèse!$C$24) -> 0 | E13: =IF($B13="",0,COUNTIFS('Rent roll'!$E$11:$E$50,Paramètres!$D$29,'Rent roll'!$V$11:$V$50,"OK",'Rent roll'!$N$11:$N$50,">="&MAX(DATE($B13,1,1),'Rent roll'!$C$7),'Rent roll'!$N$11:$N$50,"<="&DATE($B13,12,31))) -> 0 | F13: =IF($B13="",0,SUMIFS('Rent roll'!$H$11:$H$50,'Rent roll'!$E$11:$E$50,Paramètres!$D$29,'Rent roll'!$V$11:$V$50,"OK",'Rent roll'!$Q$11:$Q$50,">="&MAX(DATE($B13,1,1),'Rent roll'!$C$7),'Rent roll'!$Q$11:$Q$50,"<="&DATE($B13,12,31))) -> 0 | G13: =IF(Synthèse!$C$24=0,"",F13/Synthèse!$C$24) -> 0 | H13: =IF($B13="",0,COUNTIFS('Rent roll'!$E$11:$E$50,Paramètres!$D$29,'Rent roll'!$V$11:$V$50,"OK",'Rent roll'!$Q$11:$Q$50,">="&MAX(DATE($B13,1,1),'Rent roll'!$C$7),'Rent roll'!$Q$11:$Q$50,"<="&DATE($B13,12,31))) -> 0 | I13: =IF(OR($B13="",G13="",NOT(ISNUMBER(Paramètres!$C$16))),"",IF(G13>Paramètres!$C$16,"Concentration forte",""))
B14: =IF($B13="","",$B13+1) -> 2029 | C14: =IF($B14="",0,SUMIFS('Rent roll'!$H$11:$H$50,'Rent roll'!$E$11:$E$50,Paramètres!$D$29,'Rent roll'!$V$11:$V$50,"OK",'Rent roll'!$N$11:$N$50,">="&MAX(DATE($B14,1,1),'Rent roll'!$C$7),'Rent roll'!$N$11:$N$50,"<="&DATE($B14,12,31))) -> 85250 | D14: =IF(Synthèse!$C$24=0,"",C14/Synthèse!$C$24) -> 0.17025143 | E14: =IF($B14="",0,COUNTIFS('Rent roll'!$E$11:$E$50,Paramètres!$D$29,'Rent roll'!$V$11:$V$50,"OK",'Rent roll'!$N$11:$N$50,">="&MAX(DATE($B14,1,1),'Rent roll'!$C$7),'Rent roll'!$N$11:$N$50,"<="&DATE($B14,12,31))) -> 1 | F14: =IF($B14="",0,SUMIFS('Rent roll'!$H$11:$H$50,'Rent roll'!$E$11:$E$50,Paramètres!$D$29,'Rent roll'!$V$11:$V$50,"OK",'Rent roll'!$Q$11:$Q$50,">="&MAX(DATE($B14,1,1),'Rent roll'!$C$7),'Rent roll'!$Q$11:$Q$50,"<="&DATE($B14,12,31))) -> 178080 | G14: =IF(Synthèse!$C$24=0,"",F14/Synthèse!$C$24) -> 0.35564076 | H14: =IF($B14="",0,COUNTIFS('Rent roll'!$E$11:$E$50,Paramètres!$D$29,'Rent roll'!$V$11:$V$50,"OK",'Rent roll'!$Q$11:$Q$50,">="&MAX(DATE($B14,1,1),'Rent roll'!$C$7),'Rent roll'!$Q$11:$Q$50,"<="&DATE($B14,12,31))) -> 2 | I14: =IF(OR($B14="",G14="",NOT(ISNUMBER(Paramètres!$C$16))),"",IF(G14>Paramètres!$C$16,"Concentration forte","")) -> Concentration forte
B15: =IF($B14="","",$B14+1) -> 2030 | C15: =IF($B15="",0,SUMIFS('Rent roll'!$H$11:$H$50,'Rent roll'!$E$11:$E$50,Paramètres!$D$29,'Rent roll'!$V$11:$V$50,"OK",'Rent roll'!$N$11:$N$50,">="&MAX(DATE($B15,1,1),'Rent roll'!$C$7),'Rent roll'!$N$11:$N$50,"<="&DATE($B15,12,31))) -> 75600 | D15: =IF(Synthèse!$C$24=0,"",C15/Synthèse!$C$24) -> 0.15097957 | E15: =IF($B15="",0,COUNTIFS('Rent roll'!$E$11:$E$50,Paramètres!$D$29,'Rent roll'!$V$11:$V$50,"OK",'Rent roll'!$N$11:$N$50,">="&MAX(DATE($B15,1,1),'Rent roll'!$C$7),'Rent roll'!$N$11:$N$50,"<="&DATE($B15,12,31))) -> 1 | F15: =IF($B15="",0,SUMIFS('Rent roll'!$H$11:$H$50,'Rent roll'!$E$11:$E$50,Paramètres!$D$29,'Rent roll'!$V$11:$V$50,"OK",'Rent roll'!$Q$11:$Q$50,">="&MAX(DATE($B15,1,1),'Rent roll'!$C$7),'Rent roll'!$Q$11:$Q$50,"<="&DATE($B15,12,31))) -> 107200 | G15: =IF(Synthèse!$C$24=0,"",F15/Synthèse!$C$24) -> 0.21408743 | H15: =IF($B15="",0,COUNTIFS('Rent roll'!$E$11:$E$50,Paramètres!$D$29,'Rent roll'!$V$11:$V$50,"OK",'Rent roll'!$Q$11:$Q$50,">="&MAX(DATE($B15,1,1),'Rent roll'!$C$7),'Rent roll'!$Q$11:$Q$50,"<="&DATE($B15,12,31))) -> 1 | I15: =IF(OR($B15="",G15="",NOT(ISNUMBER(Paramètres!$C$16))),"",IF(G15>Paramètres!$C$16,"Concentration forte",""))
B16: =IF($B15="","",$B15+1) -> 2031 | C16: =IF($B16="",0,SUMIFS('Rent roll'!$H$11:$H$50,'Rent roll'!$E$11:$E$50,Paramètres!$D$29,'Rent roll'!$V$11:$V$50,"OK",'Rent roll'!$N$11:$N$50,">="&MAX(DATE($B16,1,1),'Rent roll'!$C$7),'Rent roll'!$N$11:$N$50,"<="&DATE($B16,12,31))) -> 0 | D16: =IF(Synthèse!$C$24=0,"",C16/Synthèse!$C$24) -> 0 | E16: =IF($B16="",0,COUNTIFS('Rent roll'!$E$11:$E$50,Paramètres!$D$29,'Rent roll'!$V$11:$V$50,"OK",'Rent roll'!$N$11:$N$50,">="&MAX(DATE($B16,1,1),'Rent roll'!$C$7),'Rent roll'!$N$11:$N$50,"<="&DATE($B16,12,31))) -> 0 | F16: =IF($B16="",0,SUMIFS('Rent roll'!$H$11:$H$50,'Rent roll'!$E$11:$E$50,Paramètres!$D$29,'Rent roll'!$V$11:$V$50,"OK",'Rent roll'!$Q$11:$Q$50,">="&MAX(DATE($B16,1,1),'Rent roll'!$C$7),'Rent roll'!$Q$11:$Q$50,"<="&DATE($B16,12,31))) -> 0 | G16: =IF(Synthèse!$C$24=0,"",F16/Synthèse!$C$24) -> 0 | H16: =IF($B16="",0,COUNTIFS('Rent roll'!$E$11:$E$50,Paramètres!$D$29,'Rent roll'!$V$11:$V$50,"OK",'Rent roll'!$Q$11:$Q$50,">="&MAX(DATE($B16,1,1),'Rent roll'!$C$7),'Rent roll'!$Q$11:$Q$50,"<="&DATE($B16,12,31))) -> 0 | I16: =IF(OR($B16="",G16="",NOT(ISNUMBER(Paramètres!$C$16))),"",IF(G16>Paramètres!$C$16,"Concentration forte",""))
B17: =IF($B16="","",$B16+1) -> 2032 | C17: =IF($B17="",0,SUMIFS('Rent roll'!$H$11:$H$50,'Rent roll'!$E$11:$E$50,Paramètres!$D$29,'Rent roll'!$V$11:$V$50,"OK",'Rent roll'!$N$11:$N$50,">="&MAX(DATE($B17,1,1),'Rent roll'!$C$7),'Rent roll'!$N$11:$N$50,"<="&DATE($B17,12,31))) -> 178080 | D17: =IF(Synthèse!$C$24=0,"",C17/Synthèse!$C$24) -> 0.35564076 | E17: =IF($B17="",0,COUNTIFS('Rent roll'!$E$11:$E$50,Paramètres!$D$29,'Rent roll'!$V$11:$V$50,"OK",'Rent roll'!$N$11:$N$50,">="&MAX(DATE($B17,1,1),'Rent roll'!$C$7),'Rent roll'!$N$11:$N$50,"<="&DATE($B17,12,31))) -> 2 | F17: =IF($B17="",0,SUMIFS('Rent roll'!$H$11:$H$50,'Rent roll'!$E$11:$E$50,Paramètres!$D$29,'Rent roll'!$V$11:$V$50,"OK",'Rent roll'!$Q$11:$Q$50,">="&MAX(DATE($B17,1,1),'Rent roll'!$C$7),'Rent roll'!$Q$11:$Q$50,"<="&DATE($B17,12,31))) -> 0 | G17: =IF(Synthèse!$C$24=0,"",F17/Synthèse!$C$24) -> 0 | H17: =IF($B17="",0,COUNTIFS('Rent roll'!$E$11:$E$50,Paramètres!$D$29,'Rent roll'!$V$11:$V$50,"OK",'Rent roll'!$Q$11:$Q$50,">="&MAX(DATE($B17,1,1),'Rent roll'!$C$7),'Rent roll'!$Q$11:$Q$50,"<="&DATE($B17,12,31))) -> 0 | I17: =IF(OR($B17="",G17="",NOT(ISNUMBER(Paramètres!$C$16))),"",IF(G17>Paramètres!$C$16,"Concentration forte",""))
B18: =IF($B17="","",$B17+1) -> 2033 | C18: =IF($B18="",0,SUMIFS('Rent roll'!$H$11:$H$50,'Rent roll'!$E$11:$E$50,Paramètres!$D$29,'Rent roll'!$V$11:$V$50,"OK",'Rent roll'!$N$11:$N$50,">="&MAX(DATE($B18,1,1),'Rent roll'!$C$7),'Rent roll'!$N$11:$N$50,"<="&DATE($B18,12,31))) -> 107200 | D18: =IF(Synthèse!$C$24=0,"",C18/Synthèse!$C$24) -> 0.21408743 | E18: =IF($B18="",0,COUNTIFS('Rent roll'!$E$11:$E$50,Paramètres!$D$29,'Rent roll'!$V$11:$V$50,"OK",'Rent roll'!$N$11:$N$50,">="&MAX(DATE($B18,1,1),'Rent roll'!$C$7),'Rent roll'!$N$11:$N$50,"<="&DATE($B18,12,31))) -> 1 | F18: =IF($B18="",0,SUMIFS('Rent roll'!$H$11:$H$50,'Rent roll'!$E$11:$E$50,Paramètres!$D$29,'Rent roll'!$V$11:$V$50,"OK",'Rent roll'!$Q$11:$Q$50,">="&MAX(DATE($B18,1,1),'Rent roll'!$C$7),'Rent roll'!$Q$11:$Q$50,"<="&DATE($B18,12,31))) -> 0 | G18: =IF(Synthèse!$C$24=0,"",F18/Synthèse!$C$24) -> 0 | H18: =IF($B18="",0,COUNTIFS('Rent roll'!$E$11:$E$50,Paramètres!$D$29,'Rent roll'!$V$11:$V$50,"OK",'Rent roll'!$Q$11:$Q$50,">="&MAX(DATE($B18,1,1),'Rent roll'!$C$7),'Rent roll'!$Q$11:$Q$50,"<="&DATE($B18,12,31))) -> 0 | I18: =IF(OR($B18="",G18="",NOT(ISNUMBER(Paramètres!$C$16))),"",IF(G18>Paramètres!$C$16,"Concentration forte",""))
B19: =IF($B18="","",$B18+1) -> 2034 | C19: =IF($B19="",0,SUMIFS('Rent roll'!$H$11:$H$50,'Rent roll'!$E$11:$E$50,Paramètres!$D$29,'Rent roll'!$V$11:$V$50,"OK",'Rent roll'!$N$11:$N$50,">="&MAX(DATE($B19,1,1),'Rent roll'!$C$7),'Rent roll'!$N$11:$N$50,"<="&DATE($B19,12,31))) -> 0 | D19: =IF(Synthèse!$C$24=0,"",C19/Synthèse!$C$24) -> 0 | E19: =IF($B19="",0,COUNTIFS('Rent roll'!$E$11:$E$50,Paramètres!$D$29,'Rent roll'!$V$11:$V$50,"OK",'Rent roll'!$N$11:$N$50,">="&MAX(DATE($B19,1,1),'Rent roll'!$C$7),'Rent roll'!$N$11:$N$50,"<="&DATE($B19,12,31))) -> 0 | F19: =IF($B19="",0,SUMIFS('Rent roll'!$H$11:$H$50,'Rent roll'!$E$11:$E$50,Paramètres!$D$29,'Rent roll'!$V$11:$V$50,"OK",'Rent roll'!$Q$11:$Q$50,">="&MAX(DATE($B19,1,1),'Rent roll'!$C$7),'Rent roll'!$Q$11:$Q$50,"<="&DATE($B19,12,31))) -> 0 | G19: =IF(Synthèse!$C$24=0,"",F19/Synthèse!$C$24) -> 0 | H19: =IF($B19="",0,COUNTIFS('Rent roll'!$E$11:$E$50,Paramètres!$D$29,'Rent roll'!$V$11:$V$50,"OK",'Rent roll'!$Q$11:$Q$50,">="&MAX(DATE($B19,1,1),'Rent roll'!$C$7),'Rent roll'!$Q$11:$Q$50,"<="&DATE($B19,12,31))) -> 0 | I19: =IF(OR($B19="",G19="",NOT(ISNUMBER(Paramètres!$C$16))),"",IF(G19>Paramètres!$C$16,"Concentration forte",""))
B20: =IF($B19="","",$B19+1) -> 2035 | C20: =IF($B20="",0,SUMIFS('Rent roll'!$H$11:$H$50,'Rent roll'!$E$11:$E$50,Paramètres!$D$29,'Rent roll'!$V$11:$V$50,"OK",'Rent roll'!$N$11:$N$50,">="&MAX(DATE($B20,1,1),'Rent roll'!$C$7),'Rent roll'!$N$11:$N$50,"<="&DATE($B20,12,31))) -> 0 | D20: =IF(Synthèse!$C$24=0,"",C20/Synthèse!$C$24) -> 0 | E20: =IF($B20="",0,COUNTIFS('Rent roll'!$E$11:$E$50,Paramètres!$D$29,'Rent roll'!$V$11:$V$50,"OK",'Rent roll'!$N$11:$N$50,">="&MAX(DATE($B20,1,1),'Rent roll'!$C$7),'Rent roll'!$N$11:$N$50,"<="&DATE($B20,12,31))) -> 0 | F20: =IF($B20="",0,SUMIFS('Rent roll'!$H$11:$H$50,'Rent roll'!$E$11:$E$50,Paramètres!$D$29,'Rent roll'!$V$11:$V$50,"OK",'Rent roll'!$Q$11:$Q$50,">="&MAX(DATE($B20,1,1),'Rent roll'!$C$7),'Rent roll'!$Q$11:$Q$50,"<="&DATE($B20,12,31))) -> 0 | G20: =IF(Synthèse!$C$24=0,"",F20/Synthèse!$C$24) -> 0 | H20: =IF($B20="",0,COUNTIFS('Rent roll'!$E$11:$E$50,Paramètres!$D$29,'Rent roll'!$V$11:$V$50,"OK",'Rent roll'!$Q$11:$Q$50,">="&MAX(DATE($B20,1,1),'Rent roll'!$C$7),'Rent roll'!$Q$11:$Q$50,"<="&DATE($B20,12,31))) -> 0 | I20: =IF(OR($B20="",G20="",NOT(ISNUMBER(Paramètres!$C$16))),"",IF(G20>Paramètres!$C$16,"Concentration forte",""))
B21: =IF($B20="","",$B20+1) -> 2036 | C21: =IF($B21="",0,SUMIFS('Rent roll'!$H$11:$H$50,'Rent roll'!$E$11:$E$50,Paramètres!$D$29,'Rent roll'!$V$11:$V$50,"OK",'Rent roll'!$N$11:$N$50,">="&MAX(DATE($B21,1,1),'Rent roll'!$C$7),'Rent roll'!$N$11:$N$50,"<="&DATE($B21,12,31))) -> 0 | D21: =IF(Synthèse!$C$24=0,"",C21/Synthèse!$C$24) -> 0 | E21: =IF($B21="",0,COUNTIFS('Rent roll'!$E$11:$E$50,Paramètres!$D$29,'Rent roll'!$V$11:$V$50,"OK",'Rent roll'!$N$11:$N$50,">="&MAX(DATE($B21,1,1),'Rent roll'!$C$7),'Rent roll'!$N$11:$N$50,"<="&DATE($B21,12,31))) -> 0 | F21: =IF($B21="",0,SUMIFS('Rent roll'!$H$11:$H$50,'Rent roll'!$E$11:$E$50,Paramètres!$D$29,'Rent roll'!$V$11:$V$50,"OK",'Rent roll'!$Q$11:$Q$50,">="&MAX(DATE($B21,1,1),'Rent roll'!$C$7),'Rent roll'!$Q$11:$Q$50,"<="&DATE($B21,12,31))) -> 0 | G21: =IF(Synthèse!$C$24=0,"",F21/Synthèse!$C$24) -> 0 | H21: =IF($B21="",0,COUNTIFS('Rent roll'!$E$11:$E$50,Paramètres!$D$29,'Rent roll'!$V$11:$V$50,"OK",'Rent roll'!$Q$11:$Q$50,">="&MAX(DATE($B21,1,1),'Rent roll'!$C$7),'Rent roll'!$Q$11:$Q$50,"<="&DATE($B21,12,31))) -> 0 | I21: =IF(OR($B21="",G21="",NOT(ISNUMBER(Paramètres!$C$16))),"",IF(G21>Paramètres!$C$16,"Concentration forte",""))
B22: =IF($B21="","",$B21+1) -> 2037 | C22: =IF($B22="",0,SUMIFS('Rent roll'!$H$11:$H$50,'Rent roll'!$E$11:$E$50,Paramètres!$D$29,'Rent roll'!$V$11:$V$50,"OK",'Rent roll'!$N$11:$N$50,">="&MAX(DATE($B22,1,1),'Rent roll'!$C$7),'Rent roll'!$N$11:$N$50,"<="&DATE($B22,12,31))) -> 0 | D22: =IF(Synthèse!$C$24=0,"",C22/Synthèse!$C$24) -> 0 | E22: =IF($B22="",0,COUNTIFS('Rent roll'!$E$11:$E$50,Paramètres!$D$29,'Rent roll'!$V$11:$V$50,"OK",'Rent roll'!$N$11:$N$50,">="&MAX(DATE($B22,1,1),'Rent roll'!$C$7),'Rent roll'!$N$11:$N$50,"<="&DATE($B22,12,31))) -> 0 | F22: =IF($B22="",0,SUMIFS('Rent roll'!$H$11:$H$50,'Rent roll'!$E$11:$E$50,Paramètres!$D$29,'Rent roll'!$V$11:$V$50,"OK",'Rent roll'!$Q$11:$Q$50,">="&MAX(DATE($B22,1,1),'Rent roll'!$C$7),'Rent roll'!$Q$11:$Q$50,"<="&DATE($B22,12,31))) -> 0 | G22: =IF(Synthèse!$C$24=0,"",F22/Synthèse!$C$24) -> 0 | H22: =IF($B22="",0,COUNTIFS('Rent roll'!$E$11:$E$50,Paramètres!$D$29,'Rent roll'!$V$11:$V$50,"OK",'Rent roll'!$Q$11:$Q$50,">="&MAX(DATE($B22,1,1),'Rent roll'!$C$7),'Rent roll'!$Q$11:$Q$50,"<="&DATE($B22,12,31))) -> 0 | I22: =IF(OR($B22="",G22="",NOT(ISNUMBER(Paramètres!$C$16))),"",IF(G22>Paramètres!$C$16,"Concentration forte",""))
B23: =IF($B22="","",$B22+1) -> 2038 | C23: =IF($B23="",0,SUMIFS('Rent roll'!$H$11:$H$50,'Rent roll'!$E$11:$E$50,Paramètres!$D$29,'Rent roll'!$V$11:$V$50,"OK",'Rent roll'!$N$11:$N$50,">="&MAX(DATE($B23,1,1),'Rent roll'!$C$7),'Rent roll'!$N$11:$N$50,"<="&DATE($B23,12,31))) -> 0 | D23: =IF(Synthèse!$C$24=0,"",C23/Synthèse!$C$24) -> 0 | E23: =IF($B23="",0,COUNTIFS('Rent roll'!$E$11:$E$50,Paramètres!$D$29,'Rent roll'!$V$11:$V$50,"OK",'Rent roll'!$N$11:$N$50,">="&MAX(DATE($B23,1,1),'Rent roll'!$C$7),'Rent roll'!$N$11:$N$50,"<="&DATE($B23,12,31))) -> 0 | F23: =IF($B23="",0,SUMIFS('Rent roll'!$H$11:$H$50,'Rent roll'!$E$11:$E$50,Paramètres!$D$29,'Rent roll'!$V$11:$V$50,"OK",'Rent roll'!$Q$11:$Q$50,">="&MAX(DATE($B23,1,1),'Rent roll'!$C$7),'Rent roll'!$Q$11:$Q$50,"<="&DATE($B23,12,31))) -> 0 | G23: =IF(Synthèse!$C$24=0,"",F23/Synthèse!$C$24) -> 0 | H23: =IF($B23="",0,COUNTIFS('Rent roll'!$E$11:$E$50,Paramètres!$D$29,'Rent roll'!$V$11:$V$50,"OK",'Rent roll'!$Q$11:$Q$50,">="&MAX(DATE($B23,1,1),'Rent roll'!$C$7),'Rent roll'!$Q$11:$Q$50,"<="&DATE($B23,12,31))) -> 0 | I23: =IF(OR($B23="",G23="",NOT(ISNUMBER(Paramètres!$C$16))),"",IF(G23>Paramètres!$C$16,"Concentration forte",""))
... B25: =IF($B24="","",$B24+1) -> 2040 | C25: =IF($B25="",0,SUMIFS('Rent roll'!$H$11:$H$50,'Rent roll'!$E$11:$E$50,Paramètres!$D$29,'Rent roll'!$V$11:$V$50,"OK",'Rent roll'!$N$11:$N$50,">="&MAX(DATE($B25,1,1),'Rent roll'!$C$7),'Rent roll'!$N$11:$N$50,"<="&DATE($B25,12,31))) -> 0 | D25: =IF(Synthèse!$C$24=0,"",C25/Synthèse!$C$24) -> 0 | E25: =IF($B25="",0,COUNTIFS('Rent roll'!$E$11:$E$50,Paramètres!$D$29,'Rent roll'!$V$11:$V$50,"OK",'Rent roll'!$N$11:$N$50,">="&MAX(DATE($B25,1,1),'Rent roll'!$C$7),'Rent roll'!$N$11:$N$50,"<="&DATE($B25,12,31))) -> 0 | F25: =IF($B25="",0,SUMIFS('Rent roll'!$H$11:$H$50,'Rent roll'!$E$11:$E$50,Paramètres!$D$29,'Rent roll'!$V$11:$V$50,"OK",'Rent roll'!$Q$11:$Q$50,">="&MAX(DATE($B25,1,1),'Rent roll'!$C$7),'Rent roll'!$Q$11:$Q$50,"<="&DATE($B25,12,31))) -> 0 | G25: =IF(Synthèse!$C$24=0,"",F25/Synthèse!$C$24) -> 0 | H25: =IF($B25="",0,COUNTIFS('Rent roll'!$E$11:$E$50,Paramètres!$D$29,'Rent roll'!$V$11:$V$50,"OK",'Rent roll'!$Q$11:$Q$50,">="&MAX(DATE($B25,1,1),'Rent roll'!$C$7),'Rent roll'!$Q$11:$Q$50,"<="&DATE($B25,12,31))) -> 0 | I25: =IF(OR($B25="",G25="",NOT(ISNUMBER(Paramètres!$C$16))),"",IF(G25>Paramètres!$C$16,"Concentration forte",""))
B26: =IF($B$25="","","Au-delà de "&TEXT($B$25,"0")) -> Au-delà de 2040 | C26: =IF($B$25="",0,SUMIFS('Rent roll'!$H$11:$H$50,'Rent roll'!$E$11:$E$50,Paramètres!$D$29,'Rent roll'!$V$11:$V$50,"OK",'Rent roll'!$N$11:$N$50,">"&DATE($B$25,12,31))) -> 0 | D26: =IF(Synthèse!$C$24=0,"",C26/Synthèse!$C$24) -> 0 | E26: =IF($B$25="",0,COUNTIFS('Rent roll'!$E$11:$E$50,Paramètres!$D$29,'Rent roll'!$V$11:$V$50,"OK",'Rent roll'!$N$11:$N$50,">"&DATE($B$25,12,31))) -> 0 | F26: =IF($B$25="",0,SUMIFS('Rent roll'!$H$11:$H$50,'Rent roll'!$E$11:$E$50,Paramètres!$D$29,'Rent roll'!$V$11:$V$50,"OK",'Rent roll'!$Q$11:$Q$50,">"&DATE($B$25,12,31))) -> 0 | G26: =IF(Synthèse!$C$24=0,"",F26/Synthèse!$C$24) -> 0 | H26: =IF($B$25="",0,COUNTIFS('Rent roll'!$E$11:$E$50,Paramètres!$D$29,'Rent roll'!$V$11:$V$50,"OK",'Rent roll'!$Q$11:$Q$50,">"&DATE($B$25,12,31))) -> 0 | I26: =IF(OR($B$25="",G26="",NOT(ISNUMBER(Paramètres!$C$16))),"",IF(G26>Paramètres!$C$16,"Concentration forte",""))
B27: Total | C27: =SUM(C10:C26) -> 500730 | D27: =IF(Synthèse!$C$24=0,"",C27/Synthèse!$C$24) -> 1 | E27: =SUM(E10:E26) -> 6 | F27: =SUM(F10:F26) -> 500730 | G27: =IF(Synthèse!$C$24=0,"",F27/Synthèse!$C$24) -> 1 | H27: =SUM(H10:H26) -> 6
B28: Recoupement avec le loyer en place du rent roll | C28: =IF(ROUND(C27,2)=ROUND(Synthèse!$C$24,2),"OK","À CORRIGER") -> OK | F28: =IF(ROUND(F27,2)=ROUND(Synthèse!$C$24,2),"OK","À CORRIGER") -> OK | I28: Les deux totaux doivent égaler le loyer facial en place de la Synthèse.
B30: CorpusImmo, millésime 2026. Modèle d'aide à la décision : ne constitue ni un conseil en investissement, ni un conseil fiscal, ni une expertise au sens de la charte de l'expertise en évaluation immobilière. Vérifiez les paramètres avant tout engagement.

Sheet Paramètres
B1: CorpusImmo · corpus.immo · Estimer, comparer, décider. Sur les ventes réelles.
B2: Paramètres
B3: Les seules valeurs à mettre à jour quand la réglementation ou le marché changent. Le rent roll, la Synthèse et l'Échéancier y renvoient pour chaque barème.
B5: Cellules bleues : à remplir. Cellules blanches : calculées automatiquement.
B6: BARÈMES RÉGLEMENTAIRES ET INDICES
B7: Paramètre | C7: Valeur | D7: Source (organisme, texte, date) | E7: Mise à jour | F7: Commentaire
B8: Périodicité légale des facultés de sortie d'un bail commercial | C8: 3 | D8: ="Code de commerce, art. L145-4 (Légifrance, version en vigueur depuis le 25 novembre 2018) : le preneur peut donner congé à l'expiration de chaque période triennale. Dérogation possible pour les locaux"&" à usage exclusif de bureaux, les baux de plus de neuf ans, les locaux monovalents et les locaux de stockage. Vérifié le "&TEXT(DAY($C$40),"00")&"/"&TEXT(MONTH($C$40),"00")&"/"&YEAR($C$40)&"." -> Code de commerce, art. L145-4 (Légifrance, version en vigueur depuis le 25 novembre 2018) : le preneur peut donner congé à l'expiration de chaque période triennale. Dérogation possible pour les locaux à usage exclusif de bureaux, les baux de plus de neuf ans, les locaux monovalents et les locaux de stockage. Vérifié le 05/09/2026. | E8: À chaque réforme du statut des baux commerciaux | F8: Périodicité retenue par défaut quand la colonne Périodicité de sortie du rent roll est laissée vide.
B9: Préavis de congé d'un bail commercial | C9: 6 | D9: ="Code de commerce, art. L145-9 (Légifrance, version en vigueur depuis le 8 août 2015) : congé donné six mois à l'avance ; en tacite prolongation, congé à tout moment pour le dernier jour du trimestre c"&"ivil. Vérifié le "&TEXT(DAY($C$40),"00")&"/"&TEXT(MONTH($C$40),"00")&"/"&YEAR($C$40)&"." -> Code de commerce, art. L145-9 (Légifrance, version en vigueur depuis le 8 août 2015) : congé donné six mois à l'avance ; en tacite prolongation, congé à tout moment pour le dernier jour du trimestre civil. Vérifié le 05/09/2026. | E9: À chaque réforme du statut des baux commerciaux | F9: Sert au message de l'échéancier sur les baux échus, résiliables à tout moment moyennant ce préavis.
B10: Indice des loyers des activités tertiaires (ILAT) | C10: 137.42 | D10: ="Insee, Informations rapides n° 155 : ILAT du "&$C$38&", base 100 au 1er trimestre 2010, hausse de 0,09 % sur un an. Vérifié le "&TEXT(DAY($C$40),"00")&"/"&TEXT(MONTH($C$40),"00")&"/"&YEAR($C$40)&"." -> Insee, Informations rapides n° 155 : ILAT du 1er trimestre 2026, base 100 au 1er trimestre 2010, hausse de 0,09 % sur un an. Vérifié le 05/09/2026. | E10: Trimestrielle (fin mars, juin, septembre, décembre) | F10: Dernier indice publié. Indexation des baux de bureaux et de professions libérales. Le classeur ne calcule pas l'indexation : voir Méthode.
B11: Indice des loyers commerciaux (ILC) | C11: 135.26 | D11: ="Insee, Informations rapides n° 154 du 24 juin 2026 : ILC du "&$C$38&", base 100 au 1er trimestre 2008, baisse de 0,45 % sur un an. Vérifié le "&TEXT(DAY($C$40),"00")&"/"&TEXT(MONTH($C$40),"00")&"/"&YEAR($C$40)&"." -> Insee, Informations rapides n° 154 du 24 juin 2026 : ILC du 1er trimestre 2026, base 100 au 1er trimestre 2008, baisse de 0,45 % sur un an. Vérifié le 05/09/2026. | E11: Trimestrielle | F11: Dernier indice publié. Indexation des baux de commerce et d'artisanat.
B12: Indice de référence des loyers (IRL) | C12: 148.37 | D12: ="Insee, Informations rapides n° 167 du 10 juillet 2026 : IRL du "&$C$39&", France métropolitaine, base 100 au 4e trimestre 1998, hausse de 1,15 % sur un an. Vérifié le "&TEXT(DAY($C$40),"00")&"/"&TEXT(MONTH($C$40),"00")&"/"&YEAR($C$40)&"." -> Insee, Informations rapides n° 167 du 10 juillet 2026 : IRL du 2e trimestre 2026, France métropolitaine, base 100 au 4e trimestre 1998, hausse de 1,15 % sur un an. Vérifié le 05/09/2026. | E12: Trimestrielle | F12: Dernier indice publié. Baux d'habitation, hors du champ de ce classeur, donné comme repère.
B14: REPÈRES DE MARCHÉ ET GARDE-FOUS DE SAISIE
B15: Paramètre | C15: Valeur | D15: Source (organisme, texte, date) | E15: Mise à jour | F15: Commentaire
B16: Seuil d'alerte de concentration d'une année de sortie | C16: 0.33 | D16: Convention du classeur : il n'existe pas de norme de place. Un tiers du loyer qui tombe sur une seule année de sortie est le repère d'analyse retenu. | E16: Stable | F16: Au-delà, l'échéancier affiche une alerte sur la ligne de l'année concernée.
B17: Seuil de dépendance au premier locataire | C17: 0.4 | D17: Convention du classeur : au-delà de ce seuil, l'immeuble se valorise comme un risque de contrepartie autant que comme un actif immobilier. | E17: Stable | F17: Le poids se mesure par signature, tous les lots d'un même locataire additionnés.
B18: Repère : franchise usuelle par année ferme, hors Île-de-France prime | C18: 1 | D18: ="Repère de place, hors Île-de-France prime et hors grandes surfaces : de l'ordre d'un mois de franchise par année d'engagement ferme, pratique relevée par les conseils en immobilier d'entreprise, sans "&"statistique publiée. Sur les bureaux franciliens de plus de 1 000 m², le GIE Immostat mesure 30,4 % de mesures d'accompagnement au "&$C$38&", franchises, participations aux travaux et loyers progressifs confondus, pour une durée ferme moyenne de 6,1 ans, soit environ trois mois de franchise par année ferme (immostat.com, mesures d'accompa"&"gnement et note méthodologique). Vérifié le "&TEXT(DAY($C$40),"00")&"/"&TEXT(MONTH($C$40),"00")&"/"&YEAR($C$40)&"." -> Repère de place, hors Île-de-France prime et hors grandes surfaces : de l'ordre d'un mois de franchise par année d'engagement ferme, pratique relevée par les conseils en immobilier d'entreprise, sans statistique publiée. Sur les bureaux franciliens de plus de 1 000 m², le GIE Immostat mesure 30,4 % de mesures d'accompagnement au 1er trimestre 2026, franchises, participations aux travaux et loyers progressifs confondus, pour une durée ferme moyenne de 6,1 ans, soit environ trois mois de franchise par année ferme (immostat.com, mesures d'accompagnement et note méthodologique). Vérifié le 05/09/2026. | E18: Trimestrielle, avec les publications de marché (GIE Immostat, mesures d'accompagnement) | F18: Point de départ quand le bail n'est pas encore signé. La franchise réelle se saisit bail par bail en colonne R du rent roll : ce repère ne pilote aucun calcul. Convention prudente : à défaut d'information sur le dossier, retenez la franchise la plus longue, elle minore le loyer économique et le revenu affiché. Voir Méthode.
B19: Repère : durée résiduelle ferme d'une foncière de bureaux | C19: 3.4 | D19: ="Icade, communiqué de presse Résultats annuels 2025 du 17 février 2026, chapitre Foncière, tableau des indicateurs locatifs : durée résiduelle ferme des baux de 3,4 ans au 31 décembre 2025, stable sur "&"un an, pour un taux d'occupation financier de 86,8 %. Le glossaire du même communiqué définit cette durée comme le WALB, pondéré par le loyer annualisé. icade.fr, rubrique Finance. Vérifié sur la sour"&"ce primaire le "&TEXT(DAY($C$40),"00")&"/"&TEXT(MONTH($C$40),"00")&"/"&YEAR($C$40)&"." -> Icade, communiqué de presse Résultats annuels 2025 du 17 février 2026, chapitre Foncière, tableau des indicateurs locatifs : durée résiduelle ferme des baux de 3,4 ans au 31 décembre 2025, stable sur un an, pour un taux d'occupation financier de 86,8 %. Le glossaire du même communiqué définit cette durée comme le WALB, pondéré par le loyer annualisé. icade.fr, rubrique Finance. Vérifié sur la source primaire le 05/09/2026. | E19: Annuelle, à la publication des résultats annuels de la foncière | F19: Ordre de grandeur pour situer le WALB de votre immeuble, bas de fourchette.
B20: Repère : durée résiduelle ferme d'une foncière diversifiée | C20: 6.4 | D20: ="Covivio, communiqué de presse Résultats annuels 2025 du 18 février 2026, faits marquants : durée ferme moyenne des baux de 6,4 ans au 31 décembre 2025, pour un taux d'occupation de 97,1 %. Le détail p"&"ar activité du même communiqué donne 4,9 ans en bureaux et 11,1 ans en hôtellerie. covivio.eu, rubrique Finance. Vérifié sur la source primaire le "&TEXT(DAY($C$40),"00")&"/"&TEXT(MONTH($C$40),"00")&"/"&YEAR($C$40)&"." -> Covivio, communiqué de presse Résultats annuels 2025 du 18 février 2026, faits marquants : durée ferme moyenne des baux de 6,4 ans au 31 décembre 2025, pour un taux d'occupation de 97,1 %. Le détail par activité du même communiqué donne 4,9 ans en bureaux et 11,1 ans en hôtellerie. covivio.eu, rubrique Finance. Vérifié sur la source primaire le 05/09/2026. | E20: Annuelle, à la publication des résultats annuels de la foncière | F20: Haut de fourchette, tiré par les baux longs de l'hôtellerie et du bureau prime.
B21: Loyer et valeur locative maximaux admis à la saisie (garde-fou) | C21: 5000 | D21: Convention du classeur : au-delà de ce plafond, la saisie est refusée et la ligne passe au rouge. C'est presque toujours un loyer annuel saisi dans une colonne au mètre carré. | E21: Stable | F21: À relever pour un actif de commerce de très grand pied d'immeuble parisien.
B22: Surface maximale admise à la saisie pour un lot (garde-fou) | C22: 100000 | D22: Convention du classeur : un lot au-delà de cette surface se saisit en plusieurs lignes. | E22: Stable
B23: Durée maximale d'un bail et d'une périodicité de sortie | C23: 99 | D23: ="Code rural et de la pêche maritime, art. L451-1 : le bail emphytéotique, le plus long des baux, ne peut excéder quatre-vingt-dix-neuf ans. Sert de garde-fou de saisie. Vérifié le "&TEXT(DAY($C$40),"00")&"/"&TEXT(MONTH($C$40),"00")&"/"&YEAR($C$40)&"." -> Code rural et de la pêche maritime, art. L451-1 : le bail emphytéotique, le plus long des baux, ne peut excéder quatre-vingt-dix-neuf ans. Sert de garde-fou de saisie. Vérifié le 05/09/2026. | E23: Stable | F23: Une échéance plus lointaine que cette durée est une erreur de saisie de date.
B24: Franchise maximale admise à la saisie (garde-fou) | C24: 24 | D24: Convention du classeur : au-delà de deux ans, une franchise ne s'étale plus, elle se traite à part comme une mesure d'accompagnement exceptionnelle. | E24: Stable | F24: La franchise doit aussi tenir dans la période d'engagement ferme du bail.
B25: Plancher de plausibilité d'un taux saisi | C25: 0.001 | D25: Convention CorpusImmo, commune aux matrices qui saisissent des taux. | E25: Stable | F25: Un taux entre 0 et 0,10 % signale presque toujours une saisie en fraction (0,0325 tapé pour 3,25 %). Le contrôle « Taux vraisemblable » de la Synthèse passe au rouge dans ce cas, sauf à 0 % exactement. Il porte sur les deux seuils d'alerte ci-dessus, les seuls taux que ce classeur saisit.
B27: LISTES DÉROULANTES DU RENT ROLL
B28: Nature du lot | D28: Statut du lot
B29: Bureaux | D29: Loué | E29: Lot occupé par un locataire, avec un bail et un loyer.
B30: Commerce | D30: Vacant | E30: Lot libre : sa surface et sa valeur locative comptent, son loyer est nul.
B31: Activité | D31: Libellés fixes, testés par les formules du rent roll, de la Synthèse et de l'Échéancier. Ne les renommez pas.
B32: Logistique
B33: Parking
B34: Autre
B35: Libellés libres, à adapter à votre patrimoine. Ils ne servent qu'au classement des lots : aucune formule ne les teste.
B37: MILLÉSIME DES INDICES ET VÉRIFICATION
B38: Trimestre des indices ILAT et ILC | C38: 1er trimestre 2026 | D38: Insee, publications trimestrielles. Écrivez le trimestre tel qu'il doit apparaître, par exemple « 3e trimestre 2026 ». | E38: Trimestrielle | F38: Repris tel quel dans la colonne Source ci-dessus et dans l'onglet Méthode : une seule saisie met tous les libellés à jour.
B39: Trimestre de l'indice IRL | C39: 2e trimestre 2026 | D39: Insee, publication trimestrielle. L'IRL paraît un trimestre plus tôt que l'ILAT et l'ILC. | E39: Trimestrielle | F39: Indice des baux d'habitation, hors du champ de ce classeur.
B40: Dernière vérification des paramètres | C40: 46270 | D40: Aucun de ces taux n'est recopié dans une formule : toutes pointent ici. | E40: À chaque vérification | F40: Cette date s'affiche dans chaque libellé de source, ici et dans Méthode.
B42: Ces valeurs sont volontairement isolées ici. Un rent roll qui embarque un seuil d'alerte ou une périodicité de sortie au cœur de ses formules devient faux le jour où la règle change,
B43: sans que personne ne s'en aperçoive. Vérifiez-les avant tout usage engageant, et notez la date de votre dernière vérification ci-dessus.
B46: CorpusImmo, millésime 2026. Modèle d'aide à la décision : ne constitue ni un conseil en investissement, ni un conseil fiscal, ni une expertise au sens de la charte de l'expertise en évaluation immobilière. Vérifiez les paramètres avant tout engagement.

Sheet Méthode
B1: CorpusImmo · corpus.immo · Estimer, comparer, décider. Sur les ventes réelles.
B2: Méthode et limites
B3: Ce que WAULT, WALB, taux d'occupation financier et réversion mesurent exactement, et ce que ce modèle ne fait pas.
B5: CONVENTIONS RETENUES, ET CE QU'ELLES COÛTENT
B6: WAULT | C6: Weighted Average Unexpired Lease Term : durée moyenne restant à courir jusqu'au TERME des baux, pondérée par le loyer. C'est l'horizon maximal de sécurisation des revenus.
B7: WALB | C7: Même calcul, mais jusqu'à la prochaine FACULTÉ DE SORTIE du locataire. En France, un bail 3/6/9 signé pour neuf ans peut être résilié à la fin de chaque période triennale : le WAULT affiche neuf ans quand le risque réel porte sur trois. C'est le chiffre à publier. Les foncières françaises publient ce chiffre sous le nom de WALB, pour Weighted Average Lease Break, et le présentent toujours en couple avec le WAULT. Le statut des baux commerciaux admet des dérogations à la faculté triennale pour les locaux à usage exclusif de bureaux, les baux de plus de neuf ans, les locaux monovalents et les locaux de stockage : une période ferme de six ou neuf ans y est courante. C'est ce que la colonne Périodicité de sortie du rent roll permet de saisir bail par bail.
B8: Pondération par le loyer | C8: Jamais par la surface. Un entrepôt de 2 000 m² à 45 €/m² pèse moins qu'un plateau de 400 m² à 285 €/m² : c'est le loyer qui paie la dette, pas les mètres carrés. Le classeur ne publie pas de variante pondérée par la surface : elle donne des durées plus longues dès qu'un grand lot bon marché a un bail long, ce qui flatte l'immeuble.
B9: Prochaine faculté de sortie | C9: Calculée, jamais saisie à l'aveugle. Les périodes de sortie courent depuis la prise d'effet par tranches égales à la périodicité retenue, celle de la colonne Périodicité de sortie ou, à défaut, la périodicité légale de Paramètres. La date retenue est la première fin de période strictement postérieure à la date d'analyse, plafonnée à l'échéance du bail. Une sortie déjà connue, par exemple parce qu'un congé a été reçu, se force dans la colonne prévue. Convention prudente : à égalité, c'est la sortie la plus proche qui l'emporte, donc le WALB le plus court.
B10: Dates et durées | C10: Toutes les dates sont de vraies dates Excel, jamais du texte : le classeur ne lit aucune date écrite à la main dans une cellule de texte, et fonctionne à l'identique dans un Excel réglé sur un autre ordre de date. Les durées résiduelles sont exprimées en années de 365,25 jours, comptées de la date d'analyse à la date de sortie incluse. La convention actual sur actual donnerait un écart de l'ordre de cinq dix-millièmes d'année sur un WAULT de cinq ans, sans portée pratique. Une durée résiduelle ne descend jamais sous zéro : un bail échu compte zéro an.
B11: Baux échus, en tacite prolongation | C11: Un bail dont l'échéance est antérieure à la date d'analyse reste dans les agrégats avec son loyer, mais compte zéro an de durée résiduelle, au terme comme à la sortie. Convention prudente : en tacite prolongation, le congé peut être donné à tout moment avec le préavis légal, pour le dernier jour du trimestre civil. La ligne porte la mention correspondante dans la colonne Motif, la Synthèse compte ces baux et leur loyer, et l'échéancier leur consacre sa première ligne.
B12: Loyer facial et loyer économique | C12: Le loyer facial est celui du bail, hors taxes hors charges, avant toute mesure d'accompagnement. Le loyer économique en déduit la franchise, étalée linéairement sur la période d'engagement ferme initiale, c'est-à-dire la périodicité de sortie exprimée en mois, plafonnée à la durée totale du bail quand celui-ci est plus court. Convention prudente : c'est la base la plus courte défendable, donc celle qui minore le loyer économique. Le classeur ne suit pas le calendrier réel des mois francs : il annualise. Une franchise à cheval sur deux exercices ne change donc rien au chiffre affiché. Le WAULT et le WALB sont donnés sur les deux bases, côte à côte, et une franchise plus longue que la période ferme fait passer la ligne au rouge au lieu d'afficher un loyer économique négatif.
B13: Choix du repère de franchise | C13: Convention prudente de CorpusImmo, et non une donnée de marché : quand le périmètre du dossier ne permet pas de choisir entre deux repères de franchise, retenez le plus long. Une franchise plus longue minore le loyer économique, donc le revenu affiché et la valeur qui en découle. Un rent roll optimiste fait rater une acquisition ; un rent roll prudent ne fait rater qu'une négociation. Le repère de Paramètres vaut hors Île-de-France prime et hors grandes surfaces. Sur les bureaux franciliens de plus de 1 000 m², le GIE Immostat publie un indicateur de mesures d'accompagnement qui agrège les franchises, les participations aux travaux et les loyers progressifs, rapportés au revenu qui serait obtenu au loyer facial sur la durée ferme : il est sensiblement au-dessus du repère du classeur, et il ne mesure pas la même grandeur. Ni l'un ni l'autre ne pilote de calcul ici : la franchise réelle se saisit bail par bail en colonne R du rent roll.
B14: Taux d'occupation physique | C14: Surface louée rapportée à la surface totale. Simple à lire, mais insensible au prix : cent mètres carrés de commerce en pied d'immeuble ne valent pas cent mètres carrés d'archives.
B15: Taux d'occupation financier | C15: Retenu au sens des recommandations de l'EPRA, l'European Public Real Estate Association, l'association des foncières cotées européennes dont les recommandations font la référence de place en matière de publication : le taux de vacance est la valeur locative de marché des surfaces vacantes rapportée à celle de l'ensemble du patrimoine, et le taux d'occupation financier en est le complément à cent pour cent. Il exige donc une valeur locative de marché sur chaque lot, vacant compris. Tant qu'un lot retenu n'en a pas, le classeur laisse la cellule vide et allume un contrôle, plutôt que d'afficher un taux d'occupation flatté par une vacance sous-estimée. La variante publiée par certaines foncières rapporte les loyers faciaux annualisés à la somme des loyers faciaux et de la valeur locative des vacants : elle est très proche, et n'est pas calculée ici.
B16: Réversion | C16: Valeur locative de marché des surfaces louées moins loyer facial en place. Positive, elle signale un potentiel de hausse à la relocation ou au renouvellement ; négative, elle annonce une baisse du loyer à l'échéance, que le WAULT ne dit pas. Elle est aussi affichée lot par lot : c'est là qu'on voit lequel des baux porte l'écart. Comme le taux d'occupation financier, elle exige une valeur locative sur chaque lot retenu : tant qu'un lot loué n'en a pas, la valeur locative des surfaces louées et la réversion restent vides, avec un contrôle rouge. Les calculer sur le périmètre partiel reviendrait à compter ce lot pour une valeur locative nulle, donc très au-dessus du marché, et la réversion de l'immeuble entier pourrait passer de positive à négative sans qu'aucune cellule ne l'annonce.
B17: Lignes exclues des agrégats | C17: Une ligne dont une saisie manque ou sort des bornes est exclue de tous les totaux, et son exclusion est visible : contrôle rouge sur la ligne, motif nommé à côté, compteur de lignes à corriger ou à compléter et numéro de la première ligne en cause dans la Synthèse. Elle n'est jamais comptée à zéro. Un bail loué sans date d'échéance, par exemple, ne pèse pas son loyer avec une durée nulle : il sort du calcul jusqu'à correction. Une seule saisie manquante ne fait pas rougir sa ligne ni ne l'exclut : la valeur locative de marché, qui n'empêche de calculer ni les loyers ni les durées. La ligne reste verte, porte son motif dans la colonne prévue, et le compteur de la Synthèse la compte au même titre qu'une ligne rouge.
... B19: Concentration | C19: Deux concentrations tuent la valeur : celle d'un locataire qui pèse trop lourd, et celle d'une année d'échéance qui en concentre trop. L'échéancier traite la seconde ; la ligne « poids du premier locataire » traite la première. Le poids du premier locataire se mesure par signature : tous les lots portés par le même nom sont additionnés avant comparaison. Un locataire présent sur deux plateaux pèse la somme des deux, jamais le plus gros des deux.
B20: Indexation | C20: ="Le classeur ne calcule pas l'indexation des loyers : il photographie l'état locatif à la date d'analyse. Les indices de référence sont donnés dans Paramètres pour situer la dernière indexation connue."&" Depuis la loi du 18 juin 2014, l'indice du coût de la construction est exclu de la révision des baux commerciaux conclus ou renouvelés : l'indice des loyers des activités tertiaires s'applique aux bu"&"reaux et aux professions libérales, l'indice des loyers commerciaux au commerce et à l'artisanat. Valeurs du "&Paramètres!$C$38&" pour les deux premiers et du "&Paramètres!$C$39&" pour l'indice de référence des loyers, vérifiées le "&TEXT(DAY(Paramètres!$C$40),"00")&"/"&TEXT(MONTH(Paramètres!$C$40),"00")&"/"&YEAR(Paramètres!$C$40)&"." -> Le classeur ne calcule pas l'indexation des loyers : il photographie l'état locatif à la date d'analyse. Les indices de référence sont donnés dans Paramètres pour situer la dernière indexation connue. Depuis la loi du 18 juin 2014, l'indice du coût de la construction est exclu de la révision des baux commerciaux conclus ou renouvelés : l'indice des loyers des activités tertiaires s'applique aux bureaux et aux professions libérales, l'indice des loyers commerciaux au commerce et à l'artisanat. Valeurs du 1er trimestre 2026 pour les deux premiers et du 2e trimestre 2026 pour l'indice de référence des loyers, vérifiées le 05/09/2026.
B22: CE QUE CE MODÈLE NE FAIT PAS
B23: • Il ne juge pas la qualité de signature des locataires, qui compte autant que la durée.
B24: • Il ne calcule ni la valeur de l'immeuble, ni son taux de rendement : c'est l'objet des matrices d'avis de valeur et de flux actualisés.
B25: • Il ne modélise ni les paliers de loyer, ni les travaux preneur amortis sur le bail, ni les loyers variables indexés sur le chiffre d'affaires d'un commerce.
B26: • Il ne suit pas le calendrier réel des mois de franchise : il les étale linéairement sur la période d'engagement ferme.
B27: • Il ne calcule pas l'indexation des loyers et ne date pas la dernière indexation de chaque bail.
B28: • Il ne traite pas les baux dérogatoires, les conventions d'occupation précaire ni les baux d'habitation, dont le locataire peut partir à tout moment moyennant préavis : pour ceux-là, forcez la date de sortie dans la colonne prévue.
B29: • Il ne saisit pas un loyer annuel global sans surface : un parking, une antenne ou une enseigne se saisissent avec une surface conventionnelle et le loyer au mètre carré correspondant.
B30: • Il ne remplace ni la lecture des baux, seuls documents opposables, ni la revue juridique des baux.
B32: SOURCES
B33: Périodicité légale des facultés de sortie d'un bail commercial | C33: ="Code de commerce, art. L145-4 (Légifrance, version en vigueur depuis le 25 novembre 2018) : le preneur peut donner congé à l'expiration de chaque période triennale. Dérogation possible pour les locaux"&" à usage exclusif de bureaux, les baux de plus de neuf ans, les locaux monovalents et les locaux de stockage. Vérifié le "&TEXT(DAY(Paramètres!$C$40),"00")&"/"&TEXT(MONTH(Paramètres!$C$40),"00")&"/"&YEAR(Paramètres!$C$40)&"." -> Code de commerce, art. L145-4 (Légifrance, version en vigueur depuis le 25 novembre 2018) : le preneur peut donner congé à l'expiration de chaque période triennale. Dérogation possible pour les locaux à usage exclusif de bureaux, les baux de plus de neuf ans, les locaux monovalents et les locaux de stockage. Vérifié le 05/09/2026.
B34: Préavis de congé d'un bail commercial | C34: ="Code de commerce, art. L145-9 (Légifrance, version en vigueur depuis le 8 août 2015) : congé donné six mois à l'avance ; en tacite prolongation, congé à tout moment pour le dernier jour du trimestre c"&"ivil. Vérifié le "&TEXT(DAY(Paramètres!$C$40),"00")&"/"&TEXT(MONTH(Paramètres!$C$40),"00")&"/"&YEAR(Paramètres!$C$40)&"." -> Code de commerce, art. L145-9 (Légifrance, version en vigueur depuis le 8 août 2015) : congé donné six mois à l'avance ; en tacite prolongation, congé à tout moment pour le dernier jour du trimestre civil. Vérifié le 05/09/2026.
B35: Indice des loyers des activités tertiaires (ILAT) | C35: ="Insee, Informations rapides n° 155 : ILAT du "&Paramètres!$C$38&", base 100 au 1er trimestre 2010, hausse de 0,09 % sur un an. Vérifié le "&TEXT(DAY(Paramètres!$C$40),"00")&"/"&TEXT(MONTH(Paramètres!$C$40),"00")&"/"&YEAR(Paramètres!$C$40)&"." -> Insee, Informations rapides n° 155 : ILAT du 1er trimestre 2026, base 100 au 1er trimestre 2010, hausse de 0,09 % sur un an. Vérifié le 05/09/2026.
B36: Indice des loyers commerciaux (ILC) | C36: ="Insee, Informations rapides n° 154 du 24 juin 2026 : ILC du "&Paramètres!$C$38&", base 100 au 1er trimestre 2008, baisse de 0,45 % sur un an. Vérifié le "&TEXT(DAY(Paramètres!$C$40),"00")&"/"&TEXT(MONTH(Paramètres!$C$40),"00")&"/"&YEAR(Paramètres!$C$40)&"." -> Insee, Informations rapides n° 154 du 24 juin 2026 : ILC du 1er trimestre 2026, base 100 au 1er trimestre 2008, baisse de 0,45 % sur un an. Vérifié le 05/09/2026.
B37: Indice de référence des loyers (IRL) | C37: ="Insee, Informations rapides n° 167 du 10 juillet 2026 : IRL du "&Paramètres!$C$39&", France métropolitaine, base 100 au 4e trimestre 1998, hausse de 1,15 % sur un an. Vérifié le "&TEXT(DAY(Paramètres!$C$40),"00")&"/"&TEXT(MONTH(Paramètres!$C$40),"00")&"/"&YEAR(Paramètres!$C$40)&"." -> Insee, Informations rapides n° 167 du 10 juillet 2026 : IRL du 2e trimestre 2026, France métropolitaine, base 100 au 4e trimestre 1998, hausse de 1,15 % sur un an. Vérifié le 05/09/2026.
B38: Seuil d'alerte de concentration d'une année de sortie | C38: Convention du classeur : il n'existe pas de norme de place. Un tiers du loyer qui tombe sur une seule année de sortie est le repère d'analyse retenu.
B39: Seuil de dépendance au premier locataire | C39: Convention du classeur : au-delà de ce seuil, l'immeuble se valorise comme un risque de contrepartie autant que comme un actif immobilier.
B40: Repère : franchise usuelle par année ferme, hors Île-de-France prime | C40: ="Repère de place, hors Île-de-France prime et hors grandes surfaces : de l'ordre d'un mois de franchise par année d'engagement ferme, pratique relevée par les conseils en immobilier d'entreprise, sans "&"statistique publiée. Sur les bureaux franciliens de plus de 1 000 m², le GIE Immostat mesure 30,4 % de mesures d'accompagnement au "&Paramètres!$C$38&", franchises, participations aux travaux et loyers progressifs confondus, pour une durée ferme moyenne de 6,1 ans, soit environ trois mois de franchise par année ferme (immostat.com, mesures d'accompa"&"gnement et note méthodologique). Vérifié le "&TEXT(DAY(Paramètres!$C$40),"00")&"/"&TEXT(MONTH(Paramètres!$C$40),"00")&"/"&YEAR(Paramètres!$C$40)&"." -> Repère de place, hors Île-de-France prime et hors grandes surfaces : de l'ordre d'un mois de franchise par année d'engagement ferme, pratique relevée par les conseils en immobilier d'entreprise, sans statistique publiée. Sur les bureaux franciliens de plus de 1 000 m², le GIE Immostat mesure 30,4 % de mesures d'accompagnement au 1er trimestre 2026, franchises, participations aux travaux et loyers progressifs confondus, pour une durée ferme moyenne de 6,1 ans, soit environ trois mois de franchise par année ferme (immostat.com, mesures d'accompagnement et note méthodologique). Vérifié le 05/09/2026.
B41: Repère : durée résiduelle ferme d'une foncière de bureaux | C41: ="Icade, communiqué de presse Résultats annuels 2025 du 17 février 2026, chapitre Foncière, tableau des indicateurs locatifs : durée résiduelle ferme des baux de 3,4 ans au 31 décembre 2025, stable sur "&"un an, pour un taux d'occupation financier de 86,8 %. Le glossaire du même communiqué définit cette durée comme le WALB, pondéré par le loyer annualisé. icade.fr, rubrique Finance. Vérifié sur la sour"&"ce primaire le "&TEXT(DAY(Paramètres!$C$40),"00")&"/"&TEXT(MONTH(Paramètres!$C$40),"00")&"/"&YEAR(Paramètres!$C$40)&"." -> Icade, communiqué de presse Résultats annuels 2025 du 17 février 2026, chapitre Foncière, tableau des indicateurs locatifs : durée résiduelle ferme des baux de 3,4 ans au 31 décembre 2025, stable sur un an, pour un taux d'occupation financier de 86,8 %. Le glossaire du même communiqué définit cette durée comme le WALB, pondéré par le loyer annualisé. icade.fr, rubrique Finance. Vérifié sur la source primaire le 05/09/2026.
B42: Repère : durée résiduelle ferme d'une foncière diversifiée | C42: ="Covivio, communiqué de presse Résultats annuels 2025 du 18 février 2026, faits marquants : durée ferme moyenne des baux de 6,4 ans au 31 décembre 2025, pour un taux d'occupation de 97,1 %. Le détail p"&"ar activité du même communiqué donne 4,9 ans en bureaux et 11,1 ans en hôtellerie. covivio.eu, rubrique Finance. Vérifié sur la source primaire le "&TEXT(DAY(Paramètres!$C$40),"00")&"/"&TEXT(MONTH(Paramètres!$C$40),"00")&"/"&YEAR(Paramètres!$C$40)&"." -> Covivio, communiqué de presse Résultats annuels 2025 du 18 février 2026, faits marquants : durée ferme moyenne des baux de 6,4 ans au 31 décembre 2025, pour un taux d'occupation de 97,1 %. Le détail par activité du même communiqué donne 4,9 ans en bureaux et 11,1 ans en hôtellerie. covivio.eu, rubrique Finance. Vérifié sur la source primaire le 05/09/2026.
B43: Loyer et valeur locative maximaux admis à la saisie (garde-fou) | C43: Convention du classeur : au-delà de ce plafond, la saisie est refusée et la ligne passe au rouge. C'est presque toujours un loyer annuel saisi dans une colonne au mètre carré.
B44: Surface maximale admise à la saisie pour un lot (garde-fou) | C44: Convention du classeur : un lot au-delà de cette surface se saisit en plusieurs lignes.
B45: Durée maximale d'un bail et d'une périodicité de sortie | C45: ="Code rural et de la pêche maritime, art. L451-1 : le bail emphytéotique, le plus long des baux, ne peut excéder quatre-vingt-dix-neuf ans. Sert de garde-fou de saisie. Vérifié le "&TEXT(DAY(Paramètres!$C$40),"00")&"/"&TEXT(MONTH(Paramètres!$C$40),"00")&"/"&YEAR(Paramètres!$C$40)&"." -> Code rural et de la pêche maritime, art. L451-1 : le bail emphytéotique, le plus long des baux, ne peut excéder quatre-vingt-dix-neuf ans. Sert de garde-fou de saisie. Vérifié le 05/09/2026.
B46: Franchise maximale admise à la saisie (garde-fou) | C46: Convention du classeur : au-delà de deux ans, une franchise ne s'étale plus, elle se traite à part comme une mesure d'accompagnement exceptionnelle.
B47: Plancher de plausibilité d'un taux saisi | C47: Convention CorpusImmo, commune aux matrices qui saisissent des taux.
B48: Taux d'occupation financier et vacance | C48: ="EPRA, Best Practices Recommendations Guidelines, édition de septembre 2024, section sur le taux de vacance : valeur locative de marché des surfaces vacantes rapportée à la valeur locative de marché de"&" l'ensemble du portefeuille. Vérifié le "&TEXT(DAY(Paramètres!$C$40),"00")&"/"&TEXT(MONTH(Paramètres!$C$40),"00")&"/"&YEAR(Paramètres!$C$40)&"." -> EPRA, Best Practices Recommendations Guidelines, édition de septembre 2024, section sur le taux de vacance : valeur locative de marché des surfaces vacantes rapportée à la valeur locative de marché de l'ensemble du portefeuille. Vérifié le 05/09/2026.
B49: WAULT et WALB | C49: ="Icade, rapport annuel 2025, glossaire : le WALB, Weighted Average Lease Break, retient pour chaque bail la date de prochaine option de sortie exerçable par le locataire, pondérée par le loyer annualis"&"é. Covivio, résultats annuels 2025 : même définition. Vérifié le "&TEXT(DAY(Paramètres!$C$40),"00")&"/"&TEXT(MONTH(Paramètres!$C$40),"00")&"/"&YEAR(Paramètres!$C$40)&"." -> Icade, rapport annuel 2025, glossaire : le WALB, Weighted Average Lease Break, retient pour chaque bail la date de prochaine option de sortie exerçable par le locataire, pondérée par le loyer annualisé. Covivio, résultats annuels 2025 : même définition. Vérifié le 05/09/2026.
B50: Indices d'indexation des baux commerciaux | C50: ="Loi n° 2014-626 du 18 juin 2014 : l'indice du coût de la construction est exclu de la révision et du renouvellement des baux commerciaux conclus ou renouvelés depuis le 1er septembre 2014. Insee pour "&"les valeurs d'indice. Vérifié le "&TEXT(DAY(Paramètres!$C$40),"00")&"/"&TEXT(MONTH(Paramètres!$C$40),"00")&"/"&YEAR(Paramètres!$C$40)&"." -> Loi n° 2014-626 du 18 juin 2014 : l'indice du coût de la construction est exclu de la révision et du renouvellement des baux commerciaux conclus ou renouvelés depuis le 1er septembre 2014. Insee pour les valeurs d'indice. Vérifié le 05/09/2026.
B51: Statut des baux commerciaux | C51: ="Code de commerce, art. L145-4 (facultés de sortie triennales et dérogations) et L145-9 (préavis de congé et tacite prolongation), Légifrance. Vérifié le "&TEXT(DAY(Paramètres!$C$40),"00")&"/"&TEXT(MONTH(Paramètres!$C$40),"00")&"/"&YEAR(Paramètres!$C$40)&"." -> Code de commerce, art. L145-4 (facultés de sortie triennales et dérogations) et L145-9 (préavis de congé et tacite prolongation), Légifrance. Vérifié le 05/09/2026.
B53: CorpusImmo, millésime 2026. Modèle d'aide à la décision : ne constitue ni un conseil en investissement, ni un conseil fiscal, ni une expertise au sens de la charte de l'expertise en évaluation immobilière. Vérifiez les paramètres avant tout engagement.
