Workbook

Sheet Mode d'emploi
B1: CorpusImmo · corpus.immo · Estimer, comparer, décider. Sur les ventes réelles.
B2: Mode d'emploi
B3: À quoi sert ce classeur, dans quel ordre le remplir, et comment lire ce qu'il répond.
B6: À QUOI SERT CE CLASSEUR
B7: Vous avez une offre de prêt immobilier en main, ou trois. Ce classeur répond à deux questions : combien ce crédit me coûte vraiment, mois par mois et au total, et laquelle des offres est la meilleure.
B8: Il calcule la mensualité, l'échéancier complet sur 30 ans au plus (intérêts, capital, assurance, capital restant dû à chaque date), le coût total du crédit, le TAEG réglementaire face au taux d'usure, le taux d'effort au sens du HCSF (Haut Conseil de stabilité financière, l'autorité qui fixe les normes d'octroi des banques) et ce qu'il faudrait payer pour solder le prêt à une date donnée. Le comparateur met trois offres côte à côte et les classe par TAEG et par coût total.
B9: Deux onglets de saisie seulement : Mon prêt pour un prêt, Comparateur pour trois offres. Vous remplissez les cellules bleues, le reste se calcule.
B10: Vous êtes | C10: Ce que le classeur vous donne
B11: Emprunteur, primo-accédant | C11: La mensualité totale assurance comprise, le coût total du crédit, et si le prêt passe dans les normes de la banque (35 % d'effort, 25 ans).
B12: Investisseur | C12: Le capital restant dû à la date de revente envisagée et l'indemnité de remboursement anticipé maximale : ce que la revente doit couvrir.
B13: Courtier | C13: Le TAEG de chaque offre, contrôlé contre le taux d'usure du trimestre, et un classement défendable devant le client.
B14: Banquier, conseiller financement | C14: Un échéancier au centime, la décomposition intérêts, capital, assurance, et l'effet d'une délégation d'assurance sur capital restant dû.
B15: Notaire, expert-comptable | C15: Le capital remboursé à une date, lisible ligne par ligne dans l'Échéancier, et les intérêts d'une année donnée, en additionnant les douze lignes de l'année (Échéancier!E8:E367).
B17: LE PRINCIPE, EN UNE LIGNE
B18: Chaque mois : intérêts = capital restant dû × taux ÷ 12 ; capital remboursé = échéance − intérêts ; le capital restant dû baisse d'autant
B20: LES ONGLETS, DANS L'ORDRE OÙ ON LES REMPLIT
B21: Onglet | C21: Ce que vous y faites | D21: Ce que vous y lisez
B22: Mode d'emploi | C22: Rien à saisir. Vous lisez ce guide. | D22: La marche à suivre et l'exemple guidé.
B23: Mon prêt | C23: Vous saisissez le prêt : montant, taux, durée en mois, différé éventuel, date de première échéance, assurance (assiette et taux), frais. Puis, si vous voulez, vos revenus et un mois de remboursement anticipé. | D23: Mensualité, coût total, TAEG face au taux d'usure, taux d'effort, capital restant dû et indemnité à la date choisie. Deux contrôles de saisie en tête.
B24: Échéancier | C24: Rien à saisir. | D24: Les 360 lignes possibles du prêt : date, échéance, intérêts, capital, assurance, capital restant dû. Totaux en tête de tableau.
B25: Comparateur | C25: Vous saisissez jusqu'à trois offres, mêmes montant et durée. Une colonne laissée vide est ignorée. | D25: Pour chaque offre : mensualité, coût total, TAEG, rang. En bas, le verdict.
B26: Détail des offres | C26: Rien à saisir. | D26: L'échéancier de chacune des trois offres, qui alimente leur TAEG.
B27: Paramètres | C27: Rien, sauf à la mise à jour trimestrielle du taux d'usure et des repères. | D27: Chaque valeur avec sa source datée et sa fréquence de mise à jour.
B28: Méthode | C28: Rien à saisir. | D28: Les conventions de calcul, ce que le modèle ne fait pas, les sources.
B30: LE CODE COULEUR, ET COMMENT DÉVERROUILLER UNE CELLULE
B31: Cellule | C31: Ce que c'est | D31: Ce que vous faites
B32: Fond bleu ciel, texte bleu nuit | C32: Saisie utilisateur | D32: Vous la remplissez ou l'effacez (touche Suppr), même feuille protégée. Jamais de formule dedans.
B33: Fond blanc | C33: Calcul | D33: Vous la lisez. Elle est verrouillée.
B34: Fond presque blanc, texte bleu nuit en gras | C34: Résultat de bloc, chiffre clé | D34: Vous la lisez. C'est un chiffre à retenir.
B35: Bandeau bleu nuit | C35: Titre de section, en-tête de tableau | D35: Repère de navigation.
B36: Texte gris, à droite | C36: Commentaire d'aide, ordre de grandeur | D36: Une phrase par ligne pour savoir quoi saisir.
B37: Vert OK, rouge (À CORRIGER, DÉPASSÉ, HORS NORME, DIFFÉRENTES), gris (sans objet) | C37: Contrôle de cohérence | D37: Rouge : lisez le commentaire de la ligne et corrigez. Un contrôle sans objet reste gris.
B38: Les onglets sont protégés sans mot de passe pour éviter d'écraser une formule par erreur. Les cellules bleues, elles, restent modifiables et effaçables sans rien déverrouiller : n'ôtez la protection que pour toucher une cellule blanche, par l'onglet Révision, « Ôter la protection de la feuille ». Aucun mot de passe n'est demandé.
B40: LA MARCHE À SUIVRE, ÉTAPE PAR ÉTAPE
B41: Étape | C41: Où (onglet et plage) | D41: Ce que vous faites | E41: Pourquoi
B42: 0. L'exemple livré | C42: Mon prêt!C7:C16, Mon prêt!C41, Mon prêt!C47 ; Comparateur!C8:E16 | D42: Le classeur est livré rempli d'un exemple (un prêt de 180 000 € sur 25 ans, trois offres). Gardez-le pour vous repérer, ou effacez toutes les cellules bleues avant de saisir votre dossier : la touche Suppr suffit, la protection de la feuille ne s'y oppose pas. Vérifiez surtout les saisies secondaires qui n'ont pas de raison d'être dans votre cas : le différé (Mon prêt!C10), le versement au FMG, c'est-à-dire au fonds mutuel de garantie d'une caution (Mon prêt!C16), les revenus (Mon prêt!C41), le mois de remboursement anticipé (Mon prêt!C47), et la colonne E du Comparateur si vous n'avez que deux offres. Pendant que vous effacez, Mon prêt!C17 passe au rouge et les résultats se vident : c'est normal, tout revient dès que la saisie est complète. | E42: Une saisie résiduelle de l'exemple est l'erreur la plus probable d'un premier usage : un différé ou un FMG hérités changent la mensualité et le coût net sans que rien ne le signale.
B43: 1. Le prêt | C43: Mon prêt!C7:C16 | D43: Montant, taux nominal (tapez 3,35 pour 3,35 %, 0 pour un prêt à taux zéro), durée en mois entiers (300 = 25 ans), différé en mois (0 si aucun), date de la première échéance, assiette de l'assurance dans la liste, taux d'assurance, frais de dossier, frais de garantie et, pour une caution Crédit Logement, la part versée au FMG. Vérifiez que Mon prêt!C17 et Mon prêt!C18 affichent OK. Frais de garantie : le montant de l'offre. Sans l'offre en main, une caution Crédit Logement se rapproche de Paramètres!C31 du capital ; une hypothèque coûte de l'ordre de Paramètres!C32 du capital (repère 2026). La part versée au FMG ne se lit que sur l'offre cautionnée : dans le doute, laissez Mon prêt!C16 vide, cela ne change ni le TAEG ni le coût total, seulement la restitution (Mon prêt!C30) et le coût net (Mon prêt!C31). | E43: Tout le classeur découle de ces dix cellules. Tant qu'un contrôle est rouge, les résultats restent vides : le classeur préfère ne rien afficher plutôt qu'un chiffre faux.
B44: 2. Ce que ça donne | C44: Mon prêt!C21:C31 | D44: Rien à saisir. Lisez la mensualité totale, le total des intérêts, le coût total du crédit et le coût net de la restitution de garantie. | E44: Annoncez le coût total (Mon prêt!C28) : c'est ce que le client décaisse, et c'est ce que la banque appelle coût total du crédit. Il ne se compare entre offres qu'à durée égale. Le coût net (Mon prêt!C31) est une estimation, à citer en second : la restitution du FMG (Paramètres!C21 du versement) n'est ni garantie, ni comptée dans le TAEG.
B45: 3. TAEG et usure | C45: Mon prêt!C34:C38 | D45: Rien à saisir. Lisez le TAEG assurance comprise et vérifiez que Mon prêt!C38 affiche OK. Pour les offres du Comparateur, le même contrôle se lit sur la ligne 31 (Comparateur!C31:E31). | E45: Le TAEG est le seul taux opposable ; au-dessus du taux d'usure du trimestre, la banque ne peut pas prêter. La tranche d'usure se choisit seule selon la durée.
B46: 4. Repères HCSF | C46: Mon prêt!C41:C44 | D46: Saisissez vos revenus nets mensuels en Mon prêt!C41 (facultatif). Lisez le taux d'effort et les deux contrôles. | E46: 35 % d'effort assurance comprise et 25 ans (27 avec différé) sont les normes fixées par le HCSF (Haut Conseil de stabilité financière), que la banque doit respecter sur au moins 80 % de sa production : elle garde une marge de flexibilité de 20 %, réservée en priorité à la résidence principale (Paramètres!F13).
B47: 5. Remboursement anticipé | C47: Mon prêt!C47:C50 | D47: Saisissez en Mon prêt!C47 le numéro du mois où vous pourriez solder le prêt (84 = après 7 ans). Facultatif. | E47: Un investisseur revend rarement au terme : le capital restant dû et l'indemnité plafonnée disent ce que la revente doit couvrir.
B48: 6. L'échéancier | C48: Échéancier!B8:L367 | D48: Rien à saisir. Cherchez la date qui vous intéresse en colonne C et lisez le capital restant dû en colonne J. Les totaux sont en ligne 6 (Échéancier!D6:H6). La ligne d'un mois vaut le numéro du mois plus 7 : le mois 84 est en ligne 91. | E48: Les premières années remboursent surtout des intérêts : c'est ce qui rend une revente précoce coûteuse, et ce que le tableau rend visible.
B49: 7. Trois offres | C49: Comparateur!C8:E16 | D49: Une offre par colonne. Le montant doit être le même. Les durées peuvent différer, mais le classement par coût total ne s'affichera qu'à durée égale. Laissez une colonne entièrement vide pour n'en comparer que deux. Vérifiez la ligne 17 (Comparateur!C17:E17 : OK ou « non renseignée »). Pas de date, de différé ni de revenus ici : le Comparateur compare des prêts sans différé ; pour un prêt avec différé ou pour le taux d'effort, utilisez Mon prêt. | E49: Le comparateur ignore une colonne vide et signale une colonne incomplète, au lieu de la déclarer gagnante avec un coût nul.
B50: 8. Le verdict | C50: Comparateur!C20:E39 et Comparateur!C42:C47 | D50: Lisez les rangs (ligne 34 par TAEG, ligne 35 par coût total), les écarts, puis la meilleure offre en Comparateur!C44 et la moins chère en Comparateur!C45. Vérifiez Comparateur!C43. Vérifiez aussi la ligne 31 (Comparateur!C31:E31) : chaque offre y est contrôlée contre le taux d'usure de sa durée (ligne 30, Comparateur!C30:E30). Une offre DÉPASSÉ ne peut pas être signée en l'état, même si elle est classée première. | E50: Le TAEG classe à toute durée. Le coût total ne classe qu'à durée égale : si les durées diffèrent, Comparateur!C43 affiche DIFFÉRENTES et Comparateur!C45 ne désigne pas d'offre la moins chère. Les coûts totaux (ligne 25) et les mensualités (ligne 22) de chaque offre restent lisibles : présentez-les au client avec l'écart de durée, ou demandez à la banque une offre à la même durée que l'autre pour comparer à armes égales.
B51: 9. Les barèmes | C51: Paramètres!C8:C17, C21:C32 et C41:C43 | D51: Chaque trimestre, mettez à jour les trois taux d'usure (Paramètres!C8:C10, Banque de France), puis le trimestre et la date de l'avis (Paramètres!C41 et Paramètres!C42) et la date de vérification (Paramètres!C43). Les repères de taux (Paramètres!C25 et Paramètres!C26) bougent chaque mois : rafraîchissez-les avant tout dossier engageant. Les repères d'assurance et de frais (Paramètres!C27:C32), une fois par an. Source : banque-france.fr, rubrique Taux d'usure, avis publié le dernier jour ouvré de mars, juin, septembre et décembre. | E51: Un taux d'usure périmé fausse le contrôle d'usure sans prévenir. Toutes les formules pointent ici, et les libellés de source de Paramètres et de Méthode se mettent à jour seuls à partir du trimestre et des dates saisis : ce sont des cellules bleues, rien à déverrouiller.
B53: EXEMPLE GUIDÉ
B54: Le fichier est livré avec un prêt de 180 000 € sur 300 mois (25 ans) à 3,35 %, sans différé, première échéance le 05/11/2026, assurance à 0,28 % sur capital initial, 1 200 € de frais de dossier et 2 100 € de caution Crédit Logement dont 1 500 € versés au FMG. Les deux contrôles de saisie affichent OK.
B55: Mensualité capital et intérêts : 886,71 € (Mon prêt!C22). Assurance : 42,00 € par mois (Mon prêt!C24). Mensualité totale : 928,71 € (Mon prêt!C25). Sur 25 ans, les intérêts atteignent 86 012 € (Mon prêt!C26) et l'assurance 12 600 € (Mon prêt!C27) : coût total du crédit 101 912 € (Mon prêt!C28), soit 56,62 % du capital (Mon prêt!C29). La restitution attendue du FMG, 1 050 € (Mon prêt!C30), ramène le coût net à 100 862 € (Mon prêt!C31).
B56: TAEG assurance comprise : 4,03 % (Mon prêt!C34), contre 3,58 % hors assurance (Mon prêt!C35) : l'assurance pèse 0,45 point de TAEA, le taux annuel effectif de l'assurance (Mon prêt!C36). Le taux d'usure applicable à un prêt de 20 ans et plus est de 5,29 % (Mon prêt!C37) : le contrôle Mon prêt!C38 affiche OK. Avec 3 400 € de revenus nets, le taux d'effort ressort à 27,3 % (Mon prêt!C42), dans la norme des 35 %, et la durée de 25 ans est dans la norme.
B57: Remboursement anticipé au mois 84 (après 7 ans) : capital restant dû 143 685,14 € (Mon prêt!C48), indemnité maximale 2 406,73 € (Mon prêt!C49), soit six mois d'intérêts, moins que 3 % du capital restant dû ; il faudrait 146 091,87 € pour solder (Mon prêt!C50). Dans l'Échéancier, la ligne 91 donne la même valeur en colonne J (ligne = mois + 7, le numéro du mois se lit en colonne B) ; à la ligne 127 (mois 120, dix ans), il reste 125 322,24 € à rembourser. La première année, vous payez 5 958,56 € d'intérêts pour 4 681,96 € de capital : Échéancier!B8 à B19.
B58: Comparateur : trois offres pour le même prêt de 180 000 € sur 300 mois. Offre A (Banque 1) à 3,25 % avec un contrat groupe à 0,42 % sur capital initial ; offre B (Banque 2) à 3,40 % avec une délégation à 0,18 % sur capital restant dû ; offre C (Banque 3) à 3,55 % avec 0,20 % sur capital initial, sans frais de dossier mais une hypothèque à 2 700 € sans restitution. TAEG (Comparateur!C28:E28) : A 4,17 %, B 3,80 %, C 4,08 %, toutes trois sous le taux d'usure : la ligne 31 (Comparateur!C31:E31) affiche OK pour chacune. Coût total (Comparateur!C25:E25) : A 105 651 €, B 95 079 €, C 103 486 €. Le verdict désigne « Offre B : Banque 2 » par TAEG (Comparateur!C44) et par coût total (Comparateur!C45) ; l'écart entre la meilleure et la pire atteint 10 572 € (Comparateur!C46).
B59: Comment le lire : la banque au taux nominal le plus bas (A) n'est pas la moins chère, parce que son assurance groupe coûte 18 900 € contre 4 630 € pour la délégation dégressive de B. Passez la durée de l'offre C à 240 mois : son coût total tombe à 81 554 €, sous celui de B, mais le contrôle Comparateur!C43 passe à DIFFÉRENTES et Comparateur!C45 cesse de désigner une offre. Seul le TAEG reste comparable : les coûts totaux et les mensualités des deux offres restent lisibles côte à côte, à présenter au client avec l'écart de durée.
B61: LES CHIFFRES À REGARDER, ET CE QU'ILS VALENT
B62: Indicateur | C62: Où | D62: Repère métier | E62: Ce qu'il dit vraiment
B63: Mensualité totale, assurance comprise | C63: Mon prêt!C25 | D63: Au plus 35 % des revenus nets, tous crédits confondus (HCSF, repère 2026). | E63: Ce que la banque prélève chaque mois. C'est elle qui décide si le dossier passe.
B64: TAEG, assurance comprise | C64: Mon prêt!C34 ; Comparateur!C28:E28 (usure en ligne 31) | D64: Un nominal de 3,35 % sur 25 ans avec frais et assurance groupe donne 4,03 % sur l'exemple ; taux d'usure 5,29 % à 20 ans et plus (3e trimestre 2026). | E64: Le seul taux opposable, celui de l'offre de prêt. Il agrège taux, frais et assurance : c'est lui qui classe les offres. Dans le Comparateur, la ligne 31 dit, offre par offre, si le TAEG passe sous le taux d'usure de sa durée (ligne 30).
B65: Coût total du crédit | C65: Mon prêt!C28 ; Comparateur!C25:E25 | D65: Sur 25 ans à 3,35 %, plus de la moitié du capital : l'exemple donne 56,62 %. | E65: Ce que le crédit ajoute au prix du bien, et ce que le client décaisse. Comparable entre offres à durée égale seulement.
B66: TAEA, taux annuel effectif de l'assurance | C66: Mon prêt!C36 | D66: Sur l'exemple, 0,28 % d'assurance sur capital initial pèse 0,45 point de TAEA : sur capital initial, le TAEA dépasse le taux d'assurance affiché. | E66: Le poids de l'assurance dans le TAEG. Il figure aussi sur la fiche standardisée d'information. Plus il est élevé, plus une délégation se négocie.
B67: Capital restant dû à une date | C67: Échéancier!J8:J367 ; Mon prêt!C48 | D67: Après 7 ans sur 25, il reste encore 80 % du capital sur l'exemple. | E67: Ce qu'une revente ou un rachat doit couvrir, avant indemnité.
B68: Taux d'effort | C68: Mon prêt!C42 | D68: 35 % maximum assurance comprise ; 33 % laisse une marge (repère 2026). | E68: Ne compte que ce prêt. Ajoutez vos autres mensualités pour le chiffre de la banque.
B70: LES DONNÉES À METTRE À JOUR, OÙ ET POURQUOI
B71: Deux familles de données. Les benchmarks (taux d'usure, normes HCSF, plafond d'indemnité, part de FMG restituée, repères de taux, d'assurance et de garantie) changent avec la réglementation ou le marché, à date fixe, et se rafraîchissent depuis une source indiquée. Les données de projet (montant, taux, durée, assurance, frais, revenus, offres) sont propres à chaque dossier. L'architecture du classeur ne change pas quand les données changent : seules les cellules bleues bougent.
B72: Tout se met à jour dans des cellules bleues, sans ôter la protection : les libellés de source de Paramètres et de Méthode se reconstruisent seuls à partir du trimestre, de la date de l'avis et de la date de vérification (Paramètres!C41:C43). Les chiffres cités dans ce guide et dans Méthode, eux, sont écrits en toutes lettres et datés du millésime 2026 : relisez-les à chaque mise à jour de Paramètres, en particulier le taux d'usure de l'exemple guidé, les repères de la colonne « Repère métier » ci-dessus et les ordres de grandeur de garantie de l'étape 1.
B73: Paramètre | C73: Onglet et cellule | D73: Ce qu'il pilote | E73: Source à consulter, fréquence
B74: Taux d'usure par tranche de durée | C74: Paramètres!C8:C10 | D74: Contrôle « TAEG inférieur ou égal au taux d'usure », dans Mon prêt et le Comparateur | E74: Banque de France, banque-france.fr, rubrique Taux d'usure, avis publié le dernier jour ouvré de mars, juin, septembre et décembre : trimestriel
B75: Trimestre, date de l'avis, date de vérification | C75: Paramètres!C41:C43 | D75: Les libellés de source de Paramètres et de Méthode, qui les lisent par formule | E75: Les mêmes avis Banque de France : trimestriel
B76: Seuils de durée des tranches d'usure | C76: Paramètres!C11:C12 | D76: Choix de la tranche selon la durée | E76: Banque de France : stable
B77: Normes HCSF (35 %, 25 ans, différé 2 ans) | C77: Paramètres!C13:C15 | D77: Contrôles « Taux d'effort » et « Durée dans la norme » | E77: HCSF, à chaque décision
B78: Plafonds de l'indemnité de remboursement anticipé | C78: Paramètres!C16:C17 | D78: Indemnité maximale de Mon prêt | E78: Code de la consommation, art. R313-25 : stable
B79: Part du FMG restituée | C79: Paramètres!C21 | D79: Restitution estimée et coût net | E79: Crédit Logement, page tarif : trimestriel
B80: Plancher et plafonds de saisie des taux | C80: Paramètres!C22:C24 | D80: Contrôle « Taux vraisemblable » et validation des taux nominal et d'assurance | E80: Convention du classeur : stable. Relevez le plancher si des taux inférieurs à 0,10 % redeviennent courants
B81: Repères de taux | C81: Paramètres!C25:C26 | D81: Rien : ils servent à juger une offre, les notes d'aide y renvoient | E81: Observatoire Crédit Logement / CSA : mensuel, à rafraîchir avant tout dossier engageant
B82: Repères d'assurance, de frais de dossier et de garantie (caution, hypothèque) | C82: Paramètres!C27:C32 | D82: Rien : ils servent à estimer une garantie ou une assurance quand l'offre n'est pas encore en main | E82: Baromètres d'assurance et comparateurs (PrêtClair, Meilleurtaux, Pretto) : annuel
B83: Le prêt et les offres | C83: Mon prêt!C7:C16, Mon prêt!C41, Mon prêt!C47, Comparateur!C8:E16 | D83: Tout le reste | E83: Données de projet, lues sur l'offre de prêt ou la simulation de la banque
B85: TROIS FAÇONS DE S'EN SERVIR
B86: Votre situation | C86: Ce que vous faites
B87: Vous négociez votre assurance | C87: Saisissez le prêt avec le contrat groupe (assiette « Capital initial » en Mon prêt!C12, taux de la banque). Notez le coût total (Mon prêt!C28) et le TAEA (Mon prêt!C36). Passez l'assiette en « Capital restant dû » avec le taux de la délégation : l'écart de coût total est ce que la délégation vous fait gagner sur la durée.
B88: Vous revendez dans sept ans | C88: Saisissez 84 en Mon prêt!C47. Le capital restant dû (Mon prêt!C48) plus l'indemnité maximale (Mon prêt!C49) est ce que le prix de vente net doit couvrir. Pour les intérêts déjà payés à cette date, sélectionnez Échéancier!E8:E91 : la somme s'affiche en bas de la fenêtre Excel, dans la barre d'état.
B89: Vous avez deux offres, pas trois | C89: Remplissez les colonnes C et D du Comparateur et laissez la colonne E entièrement vide : la ligne 17 affiche « non renseignée » pour E, Comparateur!C42 affiche 2, et le verdict compare les deux. Mettez la même durée aux deux, sinon fiez-vous au TAEG seul et présentez au client les deux coûts totaux avec l'écart de durée.
B91: LES ERREURS QUI FAUSSENT TOUT
B92: Le piège | C92: Le dégât
B93: Saisir le taux en décimal, 0,0335 au lieu de 3,35 (Mon prêt!C8) | C93: La cellule affiche 0,03 % : mensualité proche du seul capital, 602,52 € au lieu de 886,71 €, coût total quasi nul. Le contrôle « Taux vraisemblable » (Mon prêt!C18) passe au rouge en dessous du plancher de Paramètres!C22, sauf à 0 % exactement.
B94: Saisir la durée en années dans une cellule en mois (Mon prêt!C9) | C94: 25 au lieu de 300 : un prêt de 25 mois, mensualité de 7 464,21 €. Le libellé et le format « mois » sont là pour ça ; 240 = 20 ans, 300 = 25 ans.
B95: Saisir un taux d'assurance sur capital restant dû avec l'assiette « Capital initial » (Mon prêt!C12) | C95: Le même taux appliqué au capital initial plutôt qu'au capital restant dû gonfle l'assurance de 75 % sur l'exemple et le TAEG de 0,16 point. Choisissez l'assiette qui figure sur le contrat.
B96: Comparer des offres de durées différentes par le coût total (Comparateur!C11:E11) | C96: L'offre la plus courte gagne presque toujours en coût total : ce n'est pas un signal de qualité. Comparateur!C43 passe à DIFFÉRENTES et seul le classement par TAEG reste. Redemandez une offre à la même durée pour comparer à armes égales.
B97: Laisser un montant ou une durée dans une offre incomplète (Comparateur!C9:E11) | C97: L'offre est signalée À CORRIGER et exclue du classement ; le verdict ne compte plus qu'une offre et demande d'en renseigner deux. Videz la colonne entière pour l'ignorer.
B98: Oublier les frais de garantie ou de dossier (Mon prêt!C14, Mon prêt!C15) | C98: 3 300 € oubliés sur 180 000 € abaissent le TAEG de 0,18 point sur l'exemple : une offre peut sembler sous le taux d'usure alors qu'elle le dépasse. Sans l'offre en main, estimez-les depuis Paramètres!C31 et Paramètres!C32.
B99: Prendre le coût total pour ce que le crédit vous coûtera si vous revendez avant le terme | C99: Le coût total suppose d'aller au bout. Après 7 ans sur 25, vous n'avez payé qu'une partie des intérêts mais l'essentiel de ce qui pèse le plus : lisez le capital restant dû et l'indemnité, pas le coût total.
B101: Ce que le classeur ne fait pas, et sur quelles sources reposent ses chiffres : voir l'onglet Méthode.
B103: CorpusImmo, millésime 2026. Modèle d'aide à la décision : ne constitue ni un conseil en investissement, ni un conseil fiscal, ni une expertise au sens de la charte de l'expertise en évaluation immobilière. Vérifiez les paramètres avant tout engagement.

Sheet Mon prêt
B1: CorpusImmo · corpus.immo · Estimer, comparer, décider. Sur les ventes réelles.
B2: Mon prêt
B3: Mensualité, coût total, TAEG face au taux d'usure, repères HCSF et capital restant dû à une date donnée.
B5: Cellules bleues : à remplir. Cellules blanches : calculées automatiquement.
B6: L'EMPRUNT
B7: Montant emprunté | C7: 180000 | D7: Capital débloqué par la banque, hors frais.
B8: Taux nominal annuel (hors assurance) | C8: 0.0335 | D8: Tapez 3,35 pour 3,35 %. Repères de marché sur 20 et 25 ans : Paramètres!C25 et Paramètres!C26. 0 pour un prêt à taux zéro.
B9: Durée totale du prêt (en mois) | C9: 300 | D9: Mois entiers, de 1 à 360 (30 ans). 240 = 20 ans, 300 = 25 ans. Différé compris.
B10: Différé d'amortissement (en mois, 0 ou vide si aucun) | C10: 0 | D10: VEFA, construction, travaux : pendant ces mois vous ne payez que les intérêts et l'assurance. Inférieur à la durée.
B11: Date de la première échéance | C11: 46331 | D11: Vraie date (jj/mm/aaaa). Le déblocage est supposé un mois plus tôt, sans intérêts intercalaires.
B12: Assurance calculée sur | C12: Capital initial | D12: Liste : capital initial (contrat groupe, cotisation constante) ou capital restant dû (délégation, cotisation dégressive).
B13: Taux d'assurance annuel | C13: 0.0028 | D13: Tapez 0,28 pour 0,28 %. Repères 2026 en groupe et en délégation : Paramètres!C27 et Paramètres!C28. 0 si aucune assurance.
B14: Frais de dossier | C14: 1200 | D14: Négociables. Fourchette usuelle : Paramètres!C29 à Paramètres!C30. Vide = 0.
B15: Frais de garantie (caution ou hypothèque) | C15: 2100 | D15: Le montant de l'offre. Sans l'offre : caution Crédit Logement, environ Paramètres!C31 du capital ; hypothèque (émoluments, publicité foncière, formalités), environ Paramètres!C32 du capital. Vide = 0.
B16: Dont versement au fonds mutuel de garantie (FMG), 0 ou vide sinon | C16: 1500 | D16: Fonds mutuel de garantie d'une caution Crédit Logement, lisible sur l'offre cautionnée, en partie restitué en fin de prêt. 0 pour une hypothèque. Sans l'offre, laissez vide : ni le TAEG ni le coût total n'en dépendent, seulement la restitution et le coût net. Au plus les frais de garantie.
B17: Saisie complète et cohérente | C17: =IF(AND(ISNUMBER($C$7),$C$7>0,ISNUMBER($C$8),$C$8>=0,$C$8<=Paramètres!$C$23,ISNUMBER($C$9),$C$9>=1,$C$9<=360,$C$9=INT(N($C$9)),OR($C$10="",AND(ISNUMBER($C$10),$C$10>=0,$C$10<$C$9,$C$10=INT(N($C$10)))),ISNUMBER($C$11),N($C$11)>1,NOT(ISNA(MATCH($C$12,Paramètres!$B$36:$B$37,0))),ISNUMBER($C$13),$C$13>=0,$C$13<=Paramètres!$C$24,OR($C$14="",AND(ISNUMBER($C$14),$C$14>=0)),OR($C$15="",AND(ISNUMBER($C$15),$C$15>=0)),OR($C$16="",AND(ISNUMBER($C$16),$C$16>=0,$C$16<=N($C$15))),OR($C$41="",AND(ISNUMBER($C$41),$C$41>0)),OR($C$47="",AND(ISNUMBER($C$47),$C$47>=1,$C$47<=N($C$9),$C$47=INT(N($C$47)))),COUNT(Paramètres!$C$8:$C$17)=10,COUNT(Paramètres!$C$21:$C$32)=12),"OK","À CORRIGER") -> OK | D17: À CORRIGER : un montant, le taux, la durée, la date ou l'assiette manque, une valeur est négative ou hors bornes, ou un paramètre est vide. Les résultats restent vides tant que c'est rouge.
B18: Taux vraisemblable | C18: =IF(AND(ISNUMBER($C$8),ISNUMBER(Paramètres!$C$22),OR($C$8=0,$C$8>=Paramètres!$C$22)),"OK","À CORRIGER") -> OK | D18: À CORRIGER si le taux est entre 0 et le plancher de Paramètres!C22 : vous avez sans doute tapé 0,0335 au lieu de 3,35. Un prêt à taux zéro se saisit 0 exactement.
B20: CE QUE ÇA DONNE
B21: Durée en années | C21: =IF($C$17<>"OK","",$C$9/12) -> 25 | D21: Durée totale, différé compris.
B22: Mensualité, capital et intérêts (hors différé) | C22: =IF($C$17<>"OK","",ROUND(IF($C$8=0,$C$7/($C$9-N($C$10)),$C$7*($C$8/12)/(1-(1+$C$8/12)^(-($C$9-N($C$10))))),2)) -> 886.71 | D22: Échéance constante, arrondie au centime comme dans l'offre de prêt. La dernière échéance absorbe l'arrondi.
B23: Échéance pendant le différé (intérêts + assurance) | C23: =IF(OR($C$17<>"OK",N($C$10)=0),"",ROUND($C$7*$C$8/12,2)+$C$24) | D23: Vide s'il n'y a pas de différé.
B24: Assurance du premier mois | C24: =IF($C$17<>"OK","",ROUND($C$7*$C$13/12,2)) -> 42 | D24: Sur capital initial : constante. Sur capital restant dû : elle baisse ensuite chaque mois.
B25: Mensualité totale, assurance comprise | C25: =IF($C$17<>"OK","",$C$22+INDEX(Échéancier!$G$8:$G$367,N($C$10)+1)) -> 928.71 | D25: Première échéance d'amortissement. C'est le chiffre à rapporter à vos revenus.
B26: Total des intérêts | C26: =IF($C$17<>"OK","",Échéancier!$E$6) -> 86011.54 | D26: Somme de la colonne Intérêts de l'Échéancier.
B27: Total de l'assurance | C27: =IF($C$17<>"OK","",Échéancier!$G$6) -> 12600 | D27: Somme de la colonne Assurance de l'Échéancier.
B28: Coût total du crédit | C28: =IF($C$17<>"OK","",$C$26+$C$27+$C$14+$C$15) -> 101911.54 | D28: Intérêts + assurance + frais de dossier + frais de garantie. Comparable entre offres à durée égale seulement.
B29: Coût du crédit rapporté au capital | C29: =IF($C$17<>"OK","",$C$28/$C$7) -> 0.56617522 | D29: Pour 100 € empruntés, ce que le crédit coûte en plus.
B30: Garantie restituée en fin de prêt (estimation) | C30: =IF($C$17<>"OK","",$C$16*Paramètres!$C$21) -> 1050 | D30: Versement au FMG × part restituée (Paramètres!C21). Ne réduit pas le TAEG, qui compte la garantie en entier.
B31: Coût total net de la restitution | C31: =IF($C$17<>"OK","",$C$28-$C$30) -> 100861.54 | D31: Ce que le crédit vous aura réellement coûté si vous allez au terme.
B33: TAEG ET TAUX D'USURE
B34: TAEG, assurance comprise | C34: =IF($C$17<>"OK","",(1+IRR(Échéancier!$K$7:$K$367,$C$8/12))^12-1) -> 0.040317933 | D34: Taux annuel effectif global (Code de la consommation, art. R314-3) : le seul taux opposable, celui de l'offre de prêt.
B35: TAEG hors assurance | C35: =IF($C$17<>"OK","",(1+IRR(Échéancier!$L$7:$L$367,$C$8/12))^12-1) -> 0.035796192 | D35: Même calcul sans les cotisations d'assurance : le coût de la banque seule, frais compris.
B36: TAEA, coût de l'assurance en points de taux | C36: =IF($C$17<>"OK","",$C$34-$C$35) -> 0.0045217407 | D36: Taux annuel effectif de l'assurance : différence entre les deux TAEG. Il figure aussi sur la fiche standardisée d'information.
B37: Taux d'usure applicable (selon la durée) | C37: =IF($C$17<>"OK","",IF($C$9<Paramètres!$C$11,Paramètres!$C$8,IF($C$9<Paramètres!$C$12,Paramètres!$C$9,Paramètres!$C$10))) -> 0.0529 | D37: Tranche choisie automatiquement parmi Paramètres!C8:C10 selon les seuils de durée de Paramètres.
B38: TAEG inférieur ou égal au taux d'usure | C38: =IF($C$17="OK",IF($C$34<=$C$37,"OK","DÉPASSÉ"),"") -> OK | D38: DÉPASSÉ : la banque ne peut pas prêter à ces conditions. Baissez l'assurance ou les frais, ou allongez la durée.
B40: REPÈRES HCSF
B41: Revenus nets mensuels du foyer (facultatif) | C41: 3400 | D41: Revenus nets avant impôt, tels que la banque les retient. Vide : le taux d'effort n'est pas calculé.
B42: Taux d'effort, assurance comprise | C42: =IF(OR($C$17<>"OK",$C$41=""),"",$C$25/$C$41) -> 0.27315 | D42: Mensualité totale ÷ revenus. Ne compte que ce prêt : ajoutez vos autres crédits pour le taux d'effort complet.
B43: Taux d'effort dans la norme HCSF | C43: =IF($C$42<>"",IF($C$42<=Paramètres!$C$13,"OK","HORS NORME"),"sans objet") -> OK | D43: Plafond en Paramètres!C13. HORS NORME : la banque doit puiser dans sa marge de flexibilité, réservée en priorité à la résidence principale.
B44: Durée dans la norme HCSF (différé toléré en plus) | C44: =IF($C$17="OK",IF($C$9<=Paramètres!$C$14+MIN(N($C$10),Paramètres!$C$15),"OK","HORS NORME"),"") -> OK | D44: Durée maximale en Paramètres!C14, différé toléré en plus en Paramètres!C15. HORS NORME : le prêt sort du cadre du HCSF.
B46: REMBOURSEMENT ANTICIPÉ, À TITRE D'INFORMATION
B47: Mois du remboursement anticipé envisagé (facultatif) | C47: 84 | D47: Numéro d'échéance, entre 1 et la durée. 84 = après 7 ans. Vide : rien n'est calculé.
B48: Capital restant dû après cette échéance | C48: =IF(OR($C$17<>"OK",$C$47=""),"",INDEX(Échéancier!$J$8:$J$367,$C$47)) -> 143685.14 | D48: Lu dans l'Échéancier. C'est ce qu'il faut rembourser pour solder le prêt, avant indemnité.
B49: Indemnité de remboursement anticipé maximale | C49: =IF($C$48="","",MIN($C$48*$C$8*Paramètres!$C$16/12,$C$48*Paramètres!$C$17)) -> 2406.7261 | D49: Le plus bas des deux plafonds légaux : Paramètres!C16 (en mois d'intérêts) et Paramètres!C17 (en part du capital restant dû). Souvent négociable, parfois exonérée : voir Méthode.
B50: À débourser pour solder le prêt (capital + indemnité maximale) | C50: =IF($C$48="","",$C$48+$C$49) -> 146091.87 | D50: Hors intérêts courus depuis la dernière échéance.
B52: CorpusImmo, millésime 2026. Modèle d'aide à la décision : ne constitue ni un conseil en investissement, ni un conseil fiscal, ni une expertise au sens de la charte de l'expertise en évaluation immobilière. Vérifiez les paramètres avant tout engagement.

Sheet Échéancier
B1: CorpusImmo · corpus.immo · Estimer, comparer, décider. Sur les ventes réelles.
B2: Échéancier mois par mois
B3: Alimenté par Mon prêt. Rien à saisir ici. Les lignes au-delà de la durée restent vides.
C4: Saisie de Mon prêt : | E4: =IF('Mon prêt'!$C$17="OK","OK","À CORRIGER") -> OK | F4: Rouge : corrigez la saisie dans Mon prêt, l'échéancier reste vide.
B5: Mois | C5: Date | D5: Échéance (capital + intérêts) | E5: Intérêts | F5: Capital | G5: Assurance | H5: Total prélevé | I5: Capital remboursé (cumul) | J5: Capital restant dû | K5: Flux (TAEG) | L5: Flux hors assurance
B6: Total | D6: =IF($B$7="","",SUM(D8:D367)) -> 266011.54 | E6: =IF($B$7="","",SUM(E8:E367)) -> 86011.54 | F6: =IF($B$7="","",SUM(F8:F367)) -> 180000 | G6: =IF($B$7="","",SUM(G8:G367)) -> 12600 | H6: =IF($B$7="","",SUM(H8:H367)) -> 278611.54 | J6: Somme des colonnes : recoupement avec Mon prêt.
B7: =IF('Mon prêt'!$C$17<>"OK","",0) -> 0 | C7: =IF($B$7="","",EDATE('Mon prêt'!$C$11,-1)) -> 46300 | I7: =IF($B$7="","",0) -> 0 | J7: =IF($B$7="","",'Mon prêt'!$C$7) -> 180000 | K7: =IF($B$7="","",-('Mon prêt'!$C$7-'Mon prêt'!$C$14-'Mon prêt'!$C$15)) -> -176700 | L7: =IF($B$7="","",-('Mon prêt'!$C$7-'Mon prêt'!$C$14-'Mon prêt'!$C$15)) -> -176700
B8: =IF(B7="","",IF(B7+1>'Mon prêt'!$C$9,"",B7+1)) -> 1 | C8: =IF($B8="","",EDATE('Mon prêt'!$C$11,B8-1)) -> 46331 | D8: =IF($B8="","",IF(B8='Mon prêt'!$C$9,J7+E8,IF(B8<='Mon prêt'!$C$10,E8,'Mon prêt'!$C$22))) -> 886.71 | E8: =IF($B8="","",ROUND(J7*'Mon prêt'!$C$8/12,2)) -> 502.5 | F8: =IF($B8="","",D8-E8) -> 384.21 | G8: =IF($B8="","",ROUND(IF('Mon prêt'!$C$12=Paramètres!$B$36,'Mon prêt'!$C$7,J7)*'Mon prêt'!$C$13/12,2)) -> 42 | H8: =IF($B8="","",D8+G8) -> 928.71 | I8: =IF($B8="","",I7+F8) -> 384.21 | J8: =IF($B8="","",ROUND(J7-F8,2)) -> 179615.79 | K8: =IF($B8="","",H8) -> 928.71 | L8: =IF($B8="","",D8) -> 886.71
B9: =IF(B8="","",IF(B8+1>'Mon prêt'!$C$9,"",B8+1)) -> 2 | C9: =IF($B9="","",EDATE('Mon prêt'!$C$11,B9-1)) -> 46361 | D9: =IF($B9="","",IF(B9='Mon prêt'!$C$9,J8+E9,IF(B9<='Mon prêt'!$C$10,E9,'Mon prêt'!$C$22))) -> 886.71 | E9: =IF($B9="","",ROUND(J8*'Mon prêt'!$C$8/12,2)) -> 501.43 | F9: =IF($B9="","",D9-E9) -> 385.28 | G9: =IF($B9="","",ROUND(IF('Mon prêt'!$C$12=Paramètres!$B$36,'Mon prêt'!$C$7,J8)*'Mon prêt'!$C$13/12,2)) -> 42 | H9: =IF($B9="","",D9+G9) -> 928.71 | I9: =IF($B9="","",I8+F9) -> 769.49 | J9: =IF($B9="","",ROUND(J8-F9,2)) -> 179230.51 | K9: =IF($B9="","",H9) -> 928.71 | L9: =IF($B9="","",D9) -> 886.71
B10: =IF(B9="","",IF(B9+1>'Mon prêt'!$C$9,"",B9+1)) -> 3 | C10: =IF($B10="","",EDATE('Mon prêt'!$C$11,B10-1)) -> 46392 | D10: =IF($B10="","",IF(B10='Mon prêt'!$C$9,J9+E10,IF(B10<='Mon prêt'!$C$10,E10,'Mon prêt'!$C$22))) -> 886.71 | E10: =IF($B10="","",ROUND(J9*'Mon prêt'!$C$8/12,2)) -> 500.35 | F10: =IF($B10="","",D10-E10) -> 386.36 | G10: =IF($B10="","",ROUND(IF('Mon prêt'!$C$12=Paramètres!$B$36,'Mon prêt'!$C$7,J9)*'Mon prêt'!$C$13/12,2)) -> 42 | H10: =IF($B10="","",D10+G10) -> 928.71 | I10: =IF($B10="","",I9+F10) -> 1155.85 | J10: =IF($B10="","",ROUND(J9-F10,2)) -> 178844.15 | K10: =IF($B10="","",H10) -> 928.71 | L10: =IF($B10="","",D10) -> 886.71
B11: =IF(B10="","",IF(B10+1>'Mon prêt'!$C$9,"",B10+1)) -> 4 | C11: =IF($B11="","",EDATE('Mon prêt'!$C$11,B11-1)) -> 46423 | D11: =IF($B11="","",IF(B11='Mon prêt'!$C$9,J10+E11,IF(B11<='Mon prêt'!$C$10,E11,'Mon prêt'!$C$22))) -> 886.71 | E11: =IF($B11="","",ROUND(J10*'Mon prêt'!$C$8/12,2)) -> 499.27 | F11: =IF($B11="","",D11-E11) -> 387.44 | G11: =IF($B11="","",ROUND(IF('Mon prêt'!$C$12=Paramètres!$B$36,'Mon prêt'!$C$7,J10)*'Mon prêt'!$C$13/12,2)) -> 42 | H11: =IF($B11="","",D11+G11) -> 928.71 | I11: =IF($B11="","",I10+F11) -> 1543.29 | J11: =IF($B11="","",ROUND(J10-F11,2)) -> 178456.71 | K11: =IF($B11="","",H11) -> 928.71 | L11: =IF($B11="","",D11) -> 886.71
B12: =IF(B11="","",IF(B11+1>'Mon prêt'!$C$9,"",B11+1)) -> 5 | C12: =IF($B12="","",EDATE('Mon prêt'!$C$11,B12-1)) -> 46451 | D12: =IF($B12="","",IF(B12='Mon prêt'!$C$9,J11+E12,IF(B12<='Mon prêt'!$C$10,E12,'Mon prêt'!$C$22))) -> 886.71 | E12: =IF($B12="","",ROUND(J11*'Mon prêt'!$C$8/12,2)) -> 498.19 | F12: =IF($B12="","",D12-E12) -> 388.52 | G12: =IF($B12="","",ROUND(IF('Mon prêt'!$C$12=Paramètres!$B$36,'Mon prêt'!$C$7,J11)*'Mon prêt'!$C$13/12,2)) -> 42 | H12: =IF($B12="","",D12+G12) -> 928.71 | I12: =IF($B12="","",I11+F12) -> 1931.81 | J12: =IF($B12="","",ROUND(J11-F12,2)) -> 178068.19 | K12: =IF($B12="","",H12) -> 928.71 | L12: =IF($B12="","",D12) -> 886.71
B13: =IF(B12="","",IF(B12+1>'Mon prêt'!$C$9,"",B12+1)) -> 6 | C13: =IF($B13="","",EDATE('Mon prêt'!$C$11,B13-1)) -> 46482 | D13: =IF($B13="","",IF(B13='Mon prêt'!$C$9,J12+E13,IF(B13<='Mon prêt'!$C$10,E13,'Mon prêt'!$C$22))) -> 886.71 | E13: =IF($B13="","",ROUND(J12*'Mon prêt'!$C$8/12,2)) -> 497.11 | F13: =IF($B13="","",D13-E13) -> 389.6 | G13: =IF($B13="","",ROUND(IF('Mon prêt'!$C$12=Paramètres!$B$36,'Mon prêt'!$C$7,J12)*'Mon prêt'!$C$13/12,2)) -> 42 | H13: =IF($B13="","",D13+G13) -> 928.71 | I13: =IF($B13="","",I12+F13) -> 2321.41 | J13: =IF($B13="","",ROUND(J12-F13,2)) -> 177678.59 | K13: =IF($B13="","",H13) -> 928.71 | L13: =IF($B13="","",D13) -> 886.71
B14: =IF(B13="","",IF(B13+1>'Mon prêt'!$C$9,"",B13+1)) -> 7 | C14: =IF($B14="","",EDATE('Mon prêt'!$C$11,B14-1)) -> 46512 | D14: =IF($B14="","",IF(B14='Mon prêt'!$C$9,J13+E14,IF(B14<='Mon prêt'!$C$10,E14,'Mon prêt'!$C$22))) -> 886.71 | E14: =IF($B14="","",ROUND(J13*'Mon prêt'!$C$8/12,2)) -> 496.02 | F14: =IF($B14="","",D14-E14) -> 390.69 | G14: =IF($B14="","",ROUND(IF('Mon prêt'!$C$12=Paramètres!$B$36,'Mon prêt'!$C$7,J13)*'Mon prêt'!$C$13/12,2)) -> 42 | H14: =IF($B14="","",D14+G14) -> 928.71 | I14: =IF($B14="","",I13+F14) -> 2712.1 | J14: =IF($B14="","",ROUND(J13-F14,2)) -> 177287.9 | K14: =IF($B14="","",H14) -> 928.71 | L14: =IF($B14="","",D14) -> 886.71
B15: =IF(B14="","",IF(B14+1>'Mon prêt'!$C$9,"",B14+1)) -> 8 | C15: =IF($B15="","",EDATE('Mon prêt'!$C$11,B15-1)) -> 46543 | D15: =IF($B15="","",IF(B15='Mon prêt'!$C$9,J14+E15,IF(B15<='Mon prêt'!$C$10,E15,'Mon prêt'!$C$22))) -> 886.71 | E15: =IF($B15="","",ROUND(J14*'Mon prêt'!$C$8/12,2)) -> 494.93 | F15: =IF($B15="","",D15-E15) -> 391.78 | G15: =IF($B15="","",ROUND(IF('Mon prêt'!$C$12=Paramètres!$B$36,'Mon prêt'!$C$7,J14)*'Mon prêt'!$C$13/12,2)) -> 42 | H15: =IF($B15="","",D15+G15) -> 928.71 | I15: =IF($B15="","",I14+F15) -> 3103.88 | J15: =IF($B15="","",ROUND(J14-F15,2)) -> 176896.12 | K15: =IF($B15="","",H15) -> 928.71 | L15: =IF($B15="","",D15) -> 886.71
B16: =IF(B15="","",IF(B15+1>'Mon prêt'!$C$9,"",B15+1)) -> 9 | C16: =IF($B16="","",EDATE('Mon prêt'!$C$11,B16-1)) -> 46573 | D16: =IF($B16="","",IF(B16='Mon prêt'!$C$9,J15+E16,IF(B16<='Mon prêt'!$C$10,E16,'Mon prêt'!$C$22))) -> 886.71 | E16: =IF($B16="","",ROUND(J15*'Mon prêt'!$C$8/12,2)) -> 493.84 | F16: =IF($B16="","",D16-E16) -> 392.87 | G16: =IF($B16="","",ROUND(IF('Mon prêt'!$C$12=Paramètres!$B$36,'Mon prêt'!$C$7,J15)*'Mon prêt'!$C$13/12,2)) -> 42 | H16: =IF($B16="","",D16+G16) -> 928.71 | I16: =IF($B16="","",I15+F16) -> 3496.75 | J16: =IF($B16="","",ROUND(J15-F16,2)) -> 176503.25 | K16: =IF($B16="","",H16) -> 928.71 | L16: =IF($B16="","",D16) -> 886.71
B17: =IF(B16="","",IF(B16+1>'Mon prêt'!$C$9,"",B16+1)) -> 10 | C17: =IF($B17="","",EDATE('Mon prêt'!$C$11,B17-1)) -> 46604 | D17: =IF($B17="","",IF(B17='Mon prêt'!$C$9,J16+E17,IF(B17<='Mon prêt'!$C$10,E17,'Mon prêt'!$C$22))) -> 886.71 | E17: =IF($B17="","",ROUND(J16*'Mon prêt'!$C$8/12,2)) -> 492.74 | F17: =IF($B17="","",D17-E17) -> 393.97 | G17: =IF($B17="","",ROUND(IF('Mon prêt'!$C$12=Paramètres!$B$36,'Mon prêt'!$C$7,J16)*'Mon prêt'!$C$13/12,2)) -> 42 | H17: =IF($B17="","",D17+G17) -> 928.71 | I17: =IF($B17="","",I16+F17) -> 3890.72 | J17: =IF($B17="","",ROUND(J16-F17,2)) -> 176109.28 | K17: =IF($B17="","",H17) -> 928.71 | L17: =IF($B17="","",D17) -> 886.71
B18: =IF(B17="","",IF(B17+1>'Mon prêt'!$C$9,"",B17+1)) -> 11 | C18: =IF($B18="","",EDATE('Mon prêt'!$C$11,B18-1)) -> 46635 | D18: =IF($B18="","",IF(B18='Mon prêt'!$C$9,J17+E18,IF(B18<='Mon prêt'!$C$10,E18,'Mon prêt'!$C$22))) -> 886.71 | E18: =IF($B18="","",ROUND(J17*'Mon prêt'!$C$8/12,2)) -> 491.64 | F18: =IF($B18="","",D18-E18) -> 395.07 | G18: =IF($B18="","",ROUND(IF('Mon prêt'!$C$12=Paramètres!$B$36,'Mon prêt'!$C$7,J17)*'Mon prêt'!$C$13/12,2)) -> 42 | H18: =IF($B18="","",D18+G18) -> 928.71 | I18: =IF($B18="","",I17+F18) -> 4285.79 | J18: =IF($B18="","",ROUND(J17-F18,2)) -> 175714.21 | K18: =IF($B18="","",H18) -> 928.71 | L18: =IF($B18="","",D18) -> 886.71
B19: =IF(B18="","",IF(B18+1>'Mon prêt'!$C$9,"",B18+1)) -> 12 | C19: =IF($B19="","",EDATE('Mon prêt'!$C$11,B19-1)) -> 46665 | D19: =IF($B19="","",IF(B19='Mon prêt'!$C$9,J18+E19,IF(B19<='Mon prêt'!$C$10,E19,'Mon prêt'!$C$22))) -> 886.71 | E19: =IF($B19="","",ROUND(J18*'Mon prêt'!$C$8/12,2)) -> 490.54 | F19: =IF($B19="","",D19-E19) -> 396.17 | G19: =IF($B19="","",ROUND(IF('Mon prêt'!$C$12=Paramètres!$B$36,'Mon prêt'!$C$7,J18)*'Mon prêt'!$C$13/12,2)) -> 42 | H19: =IF($B19="","",D19+G19) -> 928.71 | I19: =IF($B19="","",I18+F19) -> 4681.96 | J19: =IF($B19="","",ROUND(J18-F19,2)) -> 175318.04 | K19: =IF($B19="","",H19) -> 928.71 | L19: =IF($B19="","",D19) -> 886.71
... B367: =IF(B366="","",IF(B366+1>'Mon prêt'!$C$9,"",B366+1)) | C367: =IF($B367="","",EDATE('Mon prêt'!$C$11,B367-1)) | D367: =IF($B367="","",IF(B367='Mon prêt'!$C$9,J366+E367,IF(B367<='Mon prêt'!$C$10,E367,'Mon prêt'!$C$22))) | E367: =IF($B367="","",ROUND(J366*'Mon prêt'!$C$8/12,2)) | F367: =IF($B367="","",D367-E367) | G367: =IF($B367="","",ROUND(IF('Mon prêt'!$C$12=Paramètres!$B$36,'Mon prêt'!$C$7,J366)*'Mon prêt'!$C$13/12,2)) | H367: =IF($B367="","",D367+G367) | I367: =IF($B367="","",I366+F367) | J367: =IF($B367="","",ROUND(J366-F367,2)) | K367: =IF($B367="","",H367) | L367: =IF($B367="","",D367)
B369: CorpusImmo, millésime 2026. Modèle d'aide à la décision : ne constitue ni un conseil en investissement, ni un conseil fiscal, ni une expertise au sens de la charte de l'expertise en évaluation immobilière. Vérifiez les paramètres avant tout engagement.

Sheet Comparateur
B1: CorpusImmo · corpus.immo · Estimer, comparer, décider. Sur les ventes réelles.
B2: Comparer trois offres de prêt
B3: Le taux nominal ne suffit pas : le TAEG départage à toute durée, le coût total seulement à durée égale.
B5: Cellules bleues : à remplir. Cellules blanches : calculées automatiquement.
B6: LES OFFRES
C7: Offre A | D7: Offre B | E7: Offre C
B8: Banque ou courtier | C8: Banque 1 | D8: Banque 2 | E8: Banque 3 | F8: Libre. Sert au verdict.
B9: Montant emprunté | C9: 180000 | D9: 180000 | E9: 180000 | F9: Même montant pour les trois offres, sinon la comparaison n'a pas de sens.
B10: Taux nominal annuel (hors assurance) | C10: 0.0325 | D10: 0.034 | E10: 0.0355 | F10: Tapez 3,25 pour 3,25 %.
B11: Durée du prêt (en mois) | C11: 300 | D11: 300 | E11: 300 | F11: Mois entiers, 1 à 360. Le classement par coût total exige des durées identiques.
B12: Assurance calculée sur | C12: Capital initial | D12: Capital restant dû | E12: Capital initial | F12: Liste : capital initial (contrat groupe) ou capital restant dû (délégation).
B13: Taux d'assurance annuel | C13: 0.0042 | D13: 0.0018 | E13: 0.002 | F13: Tapez 0,42 pour 0,42 %.
B14: Frais de dossier | C14: 1500 | D14: 900 | E14: 0 | F14: Vide = 0. Fourchette usuelle : Paramètres!C29 à Paramètres!C30.
B15: Frais de garantie (caution ou hypothèque) | C15: 2100 | D15: 2100 | E15: 2700 | F15: Vide = 0. Ordre de grandeur d'une caution : Paramètres!C31 du capital ; d'une hypothèque : Paramètres!C32 du capital.
B16: Dont versement au FMG (fonds mutuel de garantie d'une caution Crédit Logement) | C16: 1500 | D16: 1500 | E16: 0 | F16: 0 ou vide pour une hypothèque. Au plus les frais de garantie.
B17: Offre renseignée et cohérente | C17: =IF(COUNT(C$9:C$11)>0,IF(AND(ISNUMBER(C$9),C$9>0,ISNUMBER(C$10),C$10>=0,C$10<=Paramètres!$C$23,OR(C$10=0,C$10>=Paramètres!$C$22),ISNUMBER(C$11),C$11>=1,C$11<=360,C$11=INT(N(C$11)),NOT(ISNA(MATCH(C$12,Paramètres!$B$36:$B$37,0))),ISNUMBER(C$13),C$13>=0,C$13<=Paramètres!$C$24,OR(C$14="",AND(ISNUMBER(C$14),C$14>=0)),OR(C$15="",AND(ISNUMBER(C$15),C$15>=0)),OR(C$16="",AND(ISNUMBER(C$16),C$16>=0,C$16<=N(C$15))),COUNT(Paramètres!$C$8:$C$17)=10,COUNT(Paramètres!$C$21:$C$32)=12),"OK","À CORRIGER"),"non renseignée") -> OK | D17: =IF(COUNT(D$9:D$11)>0,IF(AND(ISNUMBER(D$9),D$9>0,ISNUMBER(D$10),D$10>=0,D$10<=Paramètres!$C$23,OR(D$10=0,D$10>=Paramètres!$C$22),ISNUMBER(D$11),D$11>=1,D$11<=360,D$11=INT(N(D$11)),NOT(ISNA(MATCH(D$12,Paramètres!$B$36:$B$37,0))),ISNUMBER(D$13),D$13>=0,D$13<=Paramètres!$C$24,OR(D$14="",AND(ISNUMBER(D$14),D$14>=0)),OR(D$15="",AND(ISNUMBER(D$15),D$15>=0)),OR(D$16="",AND(ISNUMBER(D$16),D$16>=0,D$16<=N(D$15))),COUNT(Paramètres!$C$8:$C$17)=10,COUNT(Paramètres!$C$21:$C$32)=12),"OK","À CORRIGER"),"non renseignée") -> OK | E17: =IF(COUNT(E$9:E$11)>0,IF(AND(ISNUMBER(E$9),E$9>0,ISNUMBER(E$10),E$10>=0,E$10<=Paramètres!$C$23,OR(E$10=0,E$10>=Paramètres!$C$22),ISNUMBER(E$11),E$11>=1,E$11<=360,E$11=INT(N(E$11)),NOT(ISNA(MATCH(E$12,Paramètres!$B$36:$B$37,0))),ISNUMBER(E$13),E$13>=0,E$13<=Paramètres!$C$24,OR(E$14="",AND(ISNUMBER(E$14),E$14>=0)),OR(E$15="",AND(ISNUMBER(E$15),E$15>=0)),OR(E$16="",AND(ISNUMBER(E$16),E$16>=0,E$16<=N(E$15))),COUNT(Paramètres!$C$8:$C$17)=10,COUNT(Paramètres!$C$21:$C$32)=12),"OK","À CORRIGER"),"non renseignée") -> OK | F17: « non renseignée » : la colonne est ignorée (comparer deux offres fonctionne). Rouge : une saisie manque, est hors bornes ou dépasse un plafond de saisie de Paramètres.
B19: CE QUE CHAQUE OFFRE COÛTE VRAIMENT
B20: Mensualité, capital et intérêts | C20: =IF(C$17<>"OK","",ROUND(IF(C$10=0,C$9/C$11,C$9*(C$10/12)/(1-(1+C$10/12)^(-C$11))),2)) -> 877.17 | D20: =IF(D$17<>"OK","",ROUND(IF(D$10=0,D$9/D$11,D$9*(D$10/12)/(1-(1+D$10/12)^(-D$11))),2)) -> 891.5 | E20: =IF(E$17<>"OK","",ROUND(IF(E$10=0,E$9/E$11,E$9*(E$10/12)/(1-(1+E$10/12)^(-E$11))),2)) -> 905.96 | F20: Arrondie au centime.
B21: Assurance du premier mois | C21: =IF(C$17<>"OK","",ROUND(C$9*C$13/12,2)) -> 63 | D21: =IF(D$17<>"OK","",ROUND(D$9*D$13/12,2)) -> 27 | E21: =IF(E$17<>"OK","",ROUND(E$9*E$13/12,2)) -> 30 | F21: Constante sur capital initial, dégressive sur capital restant dû.
B22: Mensualité totale du premier mois | C22: =IF(C$17<>"OK","",C$20+C$21) -> 940.17 | D22: =IF(D$17<>"OK","",D$20+D$21) -> 918.5 | E22: =IF(E$17<>"OK","",E$20+E$21) -> 935.96 | F22: Ce que la mensualité laisse vivre se juge ici.
B23: Total des intérêts | C23: =IF(C$17<>"OK","",SUM('Détail des offres'!$C$8:$C$367)) -> 83150.65 | D23: =IF(D$17<>"OK","",SUM('Détail des offres'!$I$8:$I$367)) -> 87448.89 | E23: =IF(E$17<>"OK","",SUM('Détail des offres'!$O$8:$O$367)) -> 91786.31 | F23: Somme de l'échéancier de l'offre (onglet Détail des offres).
B24: Total de l'assurance | C24: =IF(C$17<>"OK","",SUM('Détail des offres'!$E$8:$E$367)) -> 18900 | D24: =IF(D$17<>"OK","",SUM('Détail des offres'!$K$8:$K$367)) -> 4629.65 | E24: =IF(E$17<>"OK","",SUM('Détail des offres'!$Q$8:$Q$367)) -> 9000
B25: Coût total du crédit | C25: =IF(C$17<>"OK","",C$23+C$24+C$14+C$15) -> 105650.65 | D25: =IF(D$17<>"OK","",D$23+D$24+D$14+D$15) -> 95078.54 | E25: =IF(E$17<>"OK","",E$23+E$24+E$14+E$15) -> 103486.31 | F25: Intérêts + assurance + dossier + garantie.
B26: Garantie restituée en fin de prêt (estimation) | C26: =IF(C$17<>"OK","",C$16*Paramètres!$C$21) -> 1050 | D26: =IF(D$17<>"OK","",D$16*Paramètres!$C$21) -> 1050 | E26: =IF(E$17<>"OK","",E$16*Paramètres!$C$21) -> 0 | F26: Versement au FMG × part restituée (Paramètres!C21).
B27: Coût total net de la restitution | C27: =IF(C$17<>"OK","",C$25-C$26) -> 104600.65 | D27: =IF(D$17<>"OK","",D$25-D$26) -> 94028.54 | E27: =IF(E$17<>"OK","",E$25-E$26) -> 103486.31
B28: TAEG, assurance comprise | C28: =IF(C$17<>"OK","",(1+IRR('Détail des offres'!$G$7:$G$367,C$10/12))^12-1) -> 0.041704835 | D28: =IF(D$17<>"OK","",(1+IRR('Détail des offres'!$M$7:$M$367,D$10/12))^12-1) -> 0.038036721 | E28: =IF(E$17<>"OK","",(1+IRR('Détail des offres'!$S$7:$S$367,E$10/12))^12-1) -> 0.04075235 | F28: Le chiffre qui départage les offres, quelle que soit la durée.
B29: TAEG hors assurance | C29: =IF(C$17<>"OK","",(1+IRR('Détail des offres'!$H$7:$H$367,C$10/12))^12-1) -> 0.034918626 | D29: =IF(D$17<>"OK","",(1+IRR('Détail des offres'!$N$7:$N$367,D$10/12))^12-1) -> 0.036152832 | E29: =IF(E$17<>"OK","",(1+IRR('Détail des offres'!$T$7:$T$367,E$10/12))^12-1) -> 0.037550076 | F29: Le coût de la banque seule, frais compris.
B30: Taux d'usure applicable | C30: =IF(C$17<>"OK","",IF(C$11<Paramètres!$C$11,Paramètres!$C$8,IF(C$11<Paramètres!$C$12,Paramètres!$C$9,Paramètres!$C$10))) -> 0.0529 | D30: =IF(D$17<>"OK","",IF(D$11<Paramètres!$C$11,Paramètres!$C$8,IF(D$11<Paramètres!$C$12,Paramètres!$C$9,Paramètres!$C$10))) -> 0.0529 | E30: =IF(E$17<>"OK","",IF(E$11<Paramètres!$C$11,Paramètres!$C$8,IF(E$11<Paramètres!$C$12,Paramètres!$C$9,Paramètres!$C$10))) -> 0.0529 | F30: Selon la durée de l'offre, parmi Paramètres!C8:C10.
B31: TAEG inférieur ou égal au taux d'usure | C31: =IF(C$17="OK",IF(C$28<=C$30,"OK","DÉPASSÉ"),"") -> OK | D31: =IF(D$17="OK",IF(D$28<=D$30,"OK","DÉPASSÉ"),"") -> OK | E31: =IF(E$17="OK",IF(E$28<=E$30,"OK","DÉPASSÉ"),"") -> OK | F31: DÉPASSÉ : offre illégale en l'état.
B33: CLASSEMENT
B34: Rang par TAEG | C34: =IF(C$28="","",1+SUMPRODUCT(--($C$28:$E$28<C$28))) -> 3 | D34: =IF(D$28="","",1+SUMPRODUCT(--($C$28:$E$28<D$28))) -> 1 | E34: =IF(E$28="","",1+SUMPRODUCT(--($C$28:$E$28<E$28))) -> 2 | F34: 1 = meilleure offre. Deux offres à égalité partagent le même rang.
B35: Rang par coût total | C35: =IF(C$25="","",1+SUMPRODUCT(--($C$25:$E$25<C$25))) -> 3 | D35: =IF(D$25="","",1+SUMPRODUCT(--($C$25:$E$25<D$25))) -> 1 | E35: =IF(E$25="","",1+SUMPRODUCT(--($C$25:$E$25<E$25))) -> 2 | F35: N'a de sens qu'à durées identiques : voir le contrôle du verdict.
B36: Écart de TAEG avec la meilleure offre | C36: =IF(C$28="","",C$28-MIN($C$28:$E$28)) -> 0.003668114 | D36: =IF(D$28="","",D$28-MIN($C$28:$E$28)) -> 0 | E36: =IF(E$28="","",E$28-MIN($C$28:$E$28)) -> 0.0027156289 | F36: En points de taux.
B37: Écart de coût total avec la moins chère | C37: =IF(C$25="","",C$25-MIN($C$25:$E$25)) -> 10572.11 | D37: =IF(D$25="","",D$25-MIN($C$25:$E$25)) -> 0 | E37: =IF(E$25="","",E$25-MIN($C$25:$E$25)) -> 8407.77 | F37: Zéro sur l'offre la moins chère.
B38: Écart de mensualité totale avec la plus basse | C38: =IF(C$22="","",C$22-MIN($C$22:$E$22)) -> 21.67 | D38: =IF(D$22="","",D$22-MIN($C$22:$E$22)) -> 0 | E38: =IF(E$22="","",E$22-MIN($C$22:$E$22)) -> 17.46 | F38: Premier mois.
B39: Durée retenue pour le classement | C39: =IF(C$17<>"OK","",C$11) -> 300 | D39: =IF(D$17<>"OK","",D$11) -> 300 | E39: =IF(E$17<>"OK","",E$11) -> 300 | F39: Vide pour une offre ignorée.
B41: VERDICT
B42: Offres renseignées et cohérentes | C42: =COUNTIF($C$17:$E$17,"OK") -> 3 | F42: Il en faut au moins deux.
B43: Durées identiques | C43: =IF($C$42>=2,IF(COUNTIF($C$39:$E$39,MAX($C$39:$E$39))=$C$42,"OK","DIFFÉRENTES"),"") -> OK | F43: DIFFÉRENTES : le classement par coût total est trompeur (l'offre la plus courte gagne presque toujours). Fiez-vous au TAEG.
B44: Meilleure offre par TAEG | C44: =IF($C$42<2,"Renseignez au moins deux offres",INDEX($C$7:$E$7,MATCH(MIN($C$28:$E$28),$C$28:$E$28,0))&IF(INDEX($C$8:$E$8,MATCH(MIN($C$28:$E$28),$C$28:$E$28,0))="",""," : "&INDEX($C$8:$E$8,MATCH(MIN($C$28:$E$28),$C$28:$E$28,0)))) -> Offre B : Banque 2 | F44: Le verdict de référence : à tout horizon, la plus économique par euro emprunté.
B45: Offre la moins chère en coût total (à durée égale) | C45: =IF($C$42<2,"Renseignez au moins deux offres",IF($C$43<>"OK","Durées différentes : comparez le TAEG",INDEX($C$7:$E$7,MATCH(MIN($C$25:$E$25),$C$25:$E$25,0))&IF(INDEX($C$8:$E$8,MATCH(MIN($C$25:$E$25),$C$25:$E$25,0))="",""," : "&INDEX($C$8:$E$8,MATCH(MIN($C$25:$E$25),$C$25:$E$25,0))))) -> Offre B : Banque 2 | F45: Affiché seulement si les durées sont identiques.
B46: Écart de coût total entre la moins chère et la plus chère | C46: =IF(OR($C$42<2,$C$43<>"OK"),"",MAX($C$25:$E$25)-MIN($C$25:$E$25)) -> 10572.11 | F46: Ce que le choix de la banque vaut en euros, sur toute la durée.
B47: Durée la plus longue des offres retenues | C47: =IF($C$42=0,"",MAX($C$39:$E$39)) -> 300 | F47: Pilote la longueur du détail mois par mois.
B49: CorpusImmo, millésime 2026. Modèle d'aide à la décision : ne constitue ni un conseil en investissement, ni un conseil fiscal, ni une expertise au sens de la charte de l'expertise en évaluation immobilière. Vérifiez les paramètres avant tout engagement.

Sheet Détail des offres
B1: CorpusImmo · corpus.immo · Estimer, comparer, décider. Sur les ventes réelles.
B2: Détail mois par mois des trois offres
B3: Alimenté par le Comparateur. Rien à saisir ici. Ces flux servent au calcul du TAEG de chaque offre.
C5: ="Offre A"&IF(Comparateur!C$8="",""," : "&Comparateur!C$8) -> Offre A : Banque 1 | I5: ="Offre B"&IF(Comparateur!D$8="",""," : "&Comparateur!D$8) -> Offre B : Banque 2 | O5: ="Offre C"&IF(Comparateur!E$8="",""," : "&Comparateur!E$8) -> Offre C : Banque 3
B6: Mois | C6: Intérêts | D6: Capital | E6: Assurance | F6: Capital restant dû | G6: Flux (TAEG) | H6: Flux hors assurance | I6: Intérêts | J6: Capital | K6: Assurance | L6: Capital restant dû | M6: Flux (TAEG) | N6: Flux hors assurance | O6: Intérêts | P6: Capital | Q6: Assurance | R6: Capital restant dû | S6: Flux (TAEG) | T6: Flux hors assurance
B7: =IF(Comparateur!$C$47="","",0) -> 0 | F7: =IF(Comparateur!C$17="OK",Comparateur!C$9,"") -> 180000 | G7: =IF(Comparateur!C$17="OK",-(Comparateur!C$9-Comparateur!C$14-Comparateur!C$15),"") -> -176400 | H7: =IF(Comparateur!C$17="OK",-(Comparateur!C$9-Comparateur!C$14-Comparateur!C$15),"") -> -176400 | L7: =IF(Comparateur!D$17="OK",Comparateur!D$9,"") -> 180000 | M7: =IF(Comparateur!D$17="OK",-(Comparateur!D$9-Comparateur!D$14-Comparateur!D$15),"") -> -177000 | N7: =IF(Comparateur!D$17="OK",-(Comparateur!D$9-Comparateur!D$14-Comparateur!D$15),"") -> -177000 | R7: =IF(Comparateur!E$17="OK",Comparateur!E$9,"") -> 180000 | S7: =IF(Comparateur!E$17="OK",-(Comparateur!E$9-Comparateur!E$14-Comparateur!E$15),"") -> -177300 | T7: =IF(Comparateur!E$17="OK",-(Comparateur!E$9-Comparateur!E$14-Comparateur!E$15),"") -> -177300
B8: =IF(B7="","",IF(B7+1>Comparateur!$C$47,"",B7+1)) -> 1 | C8: =IF(OR($B8="",Comparateur!C$17<>"OK",$B8>Comparateur!C$11),"",ROUND(F7*Comparateur!C$10/12,2)) -> 487.5 | D8: =IF(C8="","",IF($B8=Comparateur!C$11,F7,Comparateur!C$20-C8)) -> 389.67 | E8: =IF(C8="","",ROUND(IF(Comparateur!C$12=Paramètres!$B$36,Comparateur!C$9,F7)*Comparateur!C$13/12,2)) -> 63 | F8: =IF(C8="","",ROUND(F7-D8,2)) -> 179610.33 | G8: =IF(C8="","",C8+D8+E8) -> 940.17 | H8: =IF(C8="","",C8+D8) -> 877.17 | I8: =IF(OR($B8="",Comparateur!D$17<>"OK",$B8>Comparateur!D$11),"",ROUND(L7*Comparateur!D$10/12,2)) -> 510 | J8: =IF(I8="","",IF($B8=Comparateur!D$11,L7,Comparateur!D$20-I8)) -> 381.5 | K8: =IF(I8="","",ROUND(IF(Comparateur!D$12=Paramètres!$B$36,Comparateur!D$9,L7)*Comparateur!D$13/12,2)) -> 27 | L8: =IF(I8="","",ROUND(L7-J8,2)) -> 179618.5 | M8: =IF(I8="","",I8+J8+K8) -> 918.5 | N8: =IF(I8="","",I8+J8) -> 891.5 | O8: =IF(OR($B8="",Comparateur!E$17<>"OK",$B8>Comparateur!E$11),"",ROUND(R7*Comparateur!E$10/12,2)) -> 532.5 | P8: =IF(O8="","",IF($B8=Comparateur!E$11,R7,Comparateur!E$20-O8)) -> 373.46 | Q8: =IF(O8="","",ROUND(IF(Comparateur!E$12=Paramètres!$B$36,Comparateur!E$9,R7)*Comparateur!E$13/12,2)) -> 30 | R8: =IF(O8="","",ROUND(R7-P8,2)) -> 179626.54 | S8: =IF(O8="","",O8+P8+Q8) -> 935.96 | T8: =IF(O8="","",O8+P8) -> 905.96
B9: =IF(B8="","",IF(B8+1>Comparateur!$C$47,"",B8+1)) -> 2 | C9: =IF(OR($B9="",Comparateur!C$17<>"OK",$B9>Comparateur!C$11),"",ROUND(F8*Comparateur!C$10/12,2)) -> 486.44 | D9: =IF(C9="","",IF($B9=Comparateur!C$11,F8,Comparateur!C$20-C9)) -> 390.73 | E9: =IF(C9="","",ROUND(IF(Comparateur!C$12=Paramètres!$B$36,Comparateur!C$9,F8)*Comparateur!C$13/12,2)) -> 63 | F9: =IF(C9="","",ROUND(F8-D9,2)) -> 179219.6 | G9: =IF(C9="","",C9+D9+E9) -> 940.17 | H9: =IF(C9="","",C9+D9) -> 877.17 | I9: =IF(OR($B9="",Comparateur!D$17<>"OK",$B9>Comparateur!D$11),"",ROUND(L8*Comparateur!D$10/12,2)) -> 508.92 | J9: =IF(I9="","",IF($B9=Comparateur!D$11,L8,Comparateur!D$20-I9)) -> 382.58 | K9: =IF(I9="","",ROUND(IF(Comparateur!D$12=Paramètres!$B$36,Comparateur!D$9,L8)*Comparateur!D$13/12,2)) -> 26.94 | L9: =IF(I9="","",ROUND(L8-J9,2)) -> 179235.92 | M9: =IF(I9="","",I9+J9+K9) -> 918.44 | N9: =IF(I9="","",I9+J9) -> 891.5 | O9: =IF(OR($B9="",Comparateur!E$17<>"OK",$B9>Comparateur!E$11),"",ROUND(R8*Comparateur!E$10/12,2)) -> 531.4 | P9: =IF(O9="","",IF($B9=Comparateur!E$11,R8,Comparateur!E$20-O9)) -> 374.56 | Q9: =IF(O9="","",ROUND(IF(Comparateur!E$12=Paramètres!$B$36,Comparateur!E$9,R8)*Comparateur!E$13/12,2)) -> 30 | R9: =IF(O9="","",ROUND(R8-P9,2)) -> 179251.98 | S9: =IF(O9="","",O9+P9+Q9) -> 935.96 | T9: =IF(O9="","",O9+P9) -> 905.96
B10: =IF(B9="","",IF(B9+1>Comparateur!$C$47,"",B9+1)) -> 3 | C10: =IF(OR($B10="",Comparateur!C$17<>"OK",$B10>Comparateur!C$11),"",ROUND(F9*Comparateur!C$10/12,2)) -> 485.39 | D10: =IF(C10="","",IF($B10=Comparateur!C$11,F9,Comparateur!C$20-C10)) -> 391.78 | E10: =IF(C10="","",ROUND(IF(Comparateur!C$12=Paramètres!$B$36,Comparateur!C$9,F9)*Comparateur!C$13/12,2)) -> 63 | F10: =IF(C10="","",ROUND(F9-D10,2)) -> 178827.82 | G10: =IF(C10="","",C10+D10+E10) -> 940.17 | H10: =IF(C10="","",C10+D10) -> 877.17 | I10: =IF(OR($B10="",Comparateur!D$17<>"OK",$B10>Comparateur!D$11),"",ROUND(L9*Comparateur!D$10/12,2)) -> 507.84 | J10: =IF(I10="","",IF($B10=Comparateur!D$11,L9,Comparateur!D$20-I10)) -> 383.66 | K10: =IF(I10="","",ROUND(IF(Comparateur!D$12=Paramètres!$B$36,Comparateur!D$9,L9)*Comparateur!D$13/12,2)) -> 26.89 | L10: =IF(I10="","",ROUND(L9-J10,2)) -> 178852.26 | M10: =IF(I10="","",I10+J10+K10) -> 918.39 | N10: =IF(I10="","",I10+J10) -> 891.5 | O10: =IF(OR($B10="",Comparateur!E$17<>"OK",$B10>Comparateur!E$11),"",ROUND(R9*Comparateur!E$10/12,2)) -> 530.29 | P10: =IF(O10="","",IF($B10=Comparateur!E$11,R9,Comparateur!E$20-O10)) -> 375.67 | Q10: =IF(O10="","",ROUND(IF(Comparateur!E$12=Paramètres!$B$36,Comparateur!E$9,R9)*Comparateur!E$13/12,2)) -> 30 | R10: =IF(O10="","",ROUND(R9-P10,2)) -> 178876.31 | S10: =IF(O10="","",O10+P10+Q10) -> 935.96 | T10: =IF(O10="","",O10+P10) -> 905.96
B11: =IF(B10="","",IF(B10+1>Comparateur!$C$47,"",B10+1)) -> 4 | C11: =IF(OR($B11="",Comparateur!C$17<>"OK",$B11>Comparateur!C$11),"",ROUND(F10*Comparateur!C$10/12,2)) -> 484.33 | D11: =IF(C11="","",IF($B11=Comparateur!C$11,F10,Comparateur!C$20-C11)) -> 392.84 | E11: =IF(C11="","",ROUND(IF(Comparateur!C$12=Paramètres!$B$36,Comparateur!C$9,F10)*Comparateur!C$13/12,2)) -> 63 | F11: =IF(C11="","",ROUND(F10-D11,2)) -> 178434.98 | G11: =IF(C11="","",C11+D11+E11) -> 940.17 | H11: =IF(C11="","",C11+D11) -> 877.17 | I11: =IF(OR($B11="",Comparateur!D$17<>"OK",$B11>Comparateur!D$11),"",ROUND(L10*Comparateur!D$10/12,2)) -> 506.75 | J11: =IF(I11="","",IF($B11=Comparateur!D$11,L10,Comparateur!D$20-I11)) -> 384.75 | K11: =IF(I11="","",ROUND(IF(Comparateur!D$12=Paramètres!$B$36,Comparateur!D$9,L10)*Comparateur!D$13/12,2)) -> 26.83 | L11: =IF(I11="","",ROUND(L10-J11,2)) -> 178467.51 | M11: =IF(I11="","",I11+J11+K11) -> 918.33 | N11: =IF(I11="","",I11+J11) -> 891.5 | O11: =IF(OR($B11="",Comparateur!E$17<>"OK",$B11>Comparateur!E$11),"",ROUND(R10*Comparateur!E$10/12,2)) -> 529.18 | P11: =IF(O11="","",IF($B11=Comparateur!E$11,R10,Comparateur!E$20-O11)) -> 376.78 | Q11: =IF(O11="","",ROUND(IF(Comparateur!E$12=Paramètres!$B$36,Comparateur!E$9,R10)*Comparateur!E$13/12,2)) -> 30 | R11: =IF(O11="","",ROUND(R10-P11,2)) -> 178499.53 | S11: =IF(O11="","",O11+P11+Q11) -> 935.96 | T11: =IF(O11="","",O11+P11) -> 905.96
B12: =IF(B11="","",IF(B11+1>Comparateur!$C$47,"",B11+1)) -> 5 | C12: =IF(OR($B12="",Comparateur!C$17<>"OK",$B12>Comparateur!C$11),"",ROUND(F11*Comparateur!C$10/12,2)) -> 483.26 | D12: =IF(C12="","",IF($B12=Comparateur!C$11,F11,Comparateur!C$20-C12)) -> 393.91 | E12: =IF(C12="","",ROUND(IF(Comparateur!C$12=Paramètres!$B$36,Comparateur!C$9,F11)*Comparateur!C$13/12,2)) -> 63 | F12: =IF(C12="","",ROUND(F11-D12,2)) -> 178041.07 | G12: =IF(C12="","",C12+D12+E12) -> 940.17 | H12: =IF(C12="","",C12+D12) -> 877.17 | I12: =IF(OR($B12="",Comparateur!D$17<>"OK",$B12>Comparateur!D$11),"",ROUND(L11*Comparateur!D$10/12,2)) -> 505.66 | J12: =IF(I12="","",IF($B12=Comparateur!D$11,L11,Comparateur!D$20-I12)) -> 385.84 | K12: =IF(I12="","",ROUND(IF(Comparateur!D$12=Paramètres!$B$36,Comparateur!D$9,L11)*Comparateur!D$13/12,2)) -> 26.77 | L12: =IF(I12="","",ROUND(L11-J12,2)) -> 178081.67 | M12: =IF(I12="","",I12+J12+K12) -> 918.27 | N12: =IF(I12="","",I12+J12) -> 891.5 | O12: =IF(OR($B12="",Comparateur!E$17<>"OK",$B12>Comparateur!E$11),"",ROUND(R11*Comparateur!E$10/12,2)) -> 528.06 | P12: =IF(O12="","",IF($B12=Comparateur!E$11,R11,Comparateur!E$20-O12)) -> 377.9 | Q12: =IF(O12="","",ROUND(IF(Comparateur!E$12=Paramètres!$B$36,Comparateur!E$9,R11)*Comparateur!E$13/12,2)) -> 30 | R12: =IF(O12="","",ROUND(R11-P12,2)) -> 178121.63 | S12: =IF(O12="","",O12+P12+Q12) -> 935.96 | T12: =IF(O12="","",O12+P12) -> 905.96
B13: =IF(B12="","",IF(B12+1>Comparateur!$C$47,"",B12+1)) -> 6 | C13: =IF(OR($B13="",Comparateur!C$17<>"OK",$B13>Comparateur!C$11),"",ROUND(F12*Comparateur!C$10/12,2)) -> 482.19 | D13: =IF(C13="","",IF($B13=Comparateur!C$11,F12,Comparateur!C$20-C13)) -> 394.98 | E13: =IF(C13="","",ROUND(IF(Comparateur!C$12=Paramètres!$B$36,Comparateur!C$9,F12)*Comparateur!C$13/12,2)) -> 63 | F13: =IF(C13="","",ROUND(F12-D13,2)) -> 177646.09 | G13: =IF(C13="","",C13+D13+E13) -> 940.17 | H13: =IF(C13="","",C13+D13) -> 877.17 | I13: =IF(OR($B13="",Comparateur!D$17<>"OK",$B13>Comparateur!D$11),"",ROUND(L12*Comparateur!D$10/12,2)) -> 504.56 | J13: =IF(I13="","",IF($B13=Comparateur!D$11,L12,Comparateur!D$20-I13)) -> 386.94 | K13: =IF(I13="","",ROUND(IF(Comparateur!D$12=Paramètres!$B$36,Comparateur!D$9,L12)*Comparateur!D$13/12,2)) -> 26.71 | L13: =IF(I13="","",ROUND(L12-J13,2)) -> 177694.73 | M13: =IF(I13="","",I13+J13+K13) -> 918.21 | N13: =IF(I13="","",I13+J13) -> 891.5 | O13: =IF(OR($B13="",Comparateur!E$17<>"OK",$B13>Comparateur!E$11),"",ROUND(R12*Comparateur!E$10/12,2)) -> 526.94 | P13: =IF(O13="","",IF($B13=Comparateur!E$11,R12,Comparateur!E$20-O13)) -> 379.02 | Q13: =IF(O13="","",ROUND(IF(Comparateur!E$12=Paramètres!$B$36,Comparateur!E$9,R12)*Comparateur!E$13/12,2)) -> 30 | R13: =IF(O13="","",ROUND(R12-P13,2)) -> 177742.61 | S13: =IF(O13="","",O13+P13+Q13) -> 935.96 | T13: =IF(O13="","",O13+P13) -> 905.96
B14: =IF(B13="","",IF(B13+1>Comparateur!$C$47,"",B13+1)) -> 7 | C14: =IF(OR($B14="",Comparateur!C$17<>"OK",$B14>Comparateur!C$11),"",ROUND(F13*Comparateur!C$10/12,2)) -> 481.12 | D14: =IF(C14="","",IF($B14=Comparateur!C$11,F13,Comparateur!C$20-C14)) -> 396.05 | E14: =IF(C14="","",ROUND(IF(Comparateur!C$12=Paramètres!$B$36,Comparateur!C$9,F13)*Comparateur!C$13/12,2)) -> 63 | F14: =IF(C14="","",ROUND(F13-D14,2)) -> 177250.04 | G14: =IF(C14="","",C14+D14+E14) -> 940.17 | H14: =IF(C14="","",C14+D14) -> 877.17 | I14: =IF(OR($B14="",Comparateur!D$17<>"OK",$B14>Comparateur!D$11),"",ROUND(L13*Comparateur!D$10/12,2)) -> 503.47 | J14: =IF(I14="","",IF($B14=Comparateur!D$11,L13,Comparateur!D$20-I14)) -> 388.03 | K14: =IF(I14="","",ROUND(IF(Comparateur!D$12=Paramètres!$B$36,Comparateur!D$9,L13)*Comparateur!D$13/12,2)) -> 26.65 | L14: =IF(I14="","",ROUND(L13-J14,2)) -> 177306.7 | M14: =IF(I14="","",I14+J14+K14) -> 918.15 | N14: =IF(I14="","",I14+J14) -> 891.5 | O14: =IF(OR($B14="",Comparateur!E$17<>"OK",$B14>Comparateur!E$11),"",ROUND(R13*Comparateur!E$10/12,2)) -> 525.82 | P14: =IF(O14="","",IF($B14=Comparateur!E$11,R13,Comparateur!E$20-O14)) -> 380.14 | Q14: =IF(O14="","",ROUND(IF(Comparateur!E$12=Paramètres!$B$36,Comparateur!E$9,R13)*Comparateur!E$13/12,2)) -> 30 | R14: =IF(O14="","",ROUND(R13-P14,2)) -> 177362.47 | S14: =IF(O14="","",O14+P14+Q14) -> 935.96 | T14: =IF(O14="","",O14+P14) -> 905.96
B15: =IF(B14="","",IF(B14+1>Comparateur!$C$47,"",B14+1)) -> 8 | C15: =IF(OR($B15="",Comparateur!C$17<>"OK",$B15>Comparateur!C$11),"",ROUND(F14*Comparateur!C$10/12,2)) -> 480.05 | D15: =IF(C15="","",IF($B15=Comparateur!C$11,F14,Comparateur!C$20-C15)) -> 397.12 | E15: =IF(C15="","",ROUND(IF(Comparateur!C$12=Paramètres!$B$36,Comparateur!C$9,F14)*Comparateur!C$13/12,2)) -> 63 | F15: =IF(C15="","",ROUND(F14-D15,2)) -> 176852.92 | G15: =IF(C15="","",C15+D15+E15) -> 940.17 | H15: =IF(C15="","",C15+D15) -> 877.17 | I15: =IF(OR($B15="",Comparateur!D$17<>"OK",$B15>Comparateur!D$11),"",ROUND(L14*Comparateur!D$10/12,2)) -> 502.37 | J15: =IF(I15="","",IF($B15=Comparateur!D$11,L14,Comparateur!D$20-I15)) -> 389.13 | K15: =IF(I15="","",ROUND(IF(Comparateur!D$12=Paramètres!$B$36,Comparateur!D$9,L14)*Comparateur!D$13/12,2)) -> 26.6 | L15: =IF(I15="","",ROUND(L14-J15,2)) -> 176917.57 | M15: =IF(I15="","",I15+J15+K15) -> 918.1 | N15: =IF(I15="","",I15+J15) -> 891.5 | O15: =IF(OR($B15="",Comparateur!E$17<>"OK",$B15>Comparateur!E$11),"",ROUND(R14*Comparateur!E$10/12,2)) -> 524.7 | P15: =IF(O15="","",IF($B15=Comparateur!E$11,R14,Comparateur!E$20-O15)) -> 381.26 | Q15: =IF(O15="","",ROUND(IF(Comparateur!E$12=Paramètres!$B$36,Comparateur!E$9,R14)*Comparateur!E$13/12,2)) -> 30 | R15: =IF(O15="","",ROUND(R14-P15,2)) -> 176981.21 | S15: =IF(O15="","",O15+P15+Q15) -> 935.96 | T15: =IF(O15="","",O15+P15) -> 905.96
B16: =IF(B15="","",IF(B15+1>Comparateur!$C$47,"",B15+1)) -> 9 | C16: =IF(OR($B16="",Comparateur!C$17<>"OK",$B16>Comparateur!C$11),"",ROUND(F15*Comparateur!C$10/12,2)) -> 478.98 | D16: =IF(C16="","",IF($B16=Comparateur!C$11,F15,Comparateur!C$20-C16)) -> 398.19 | E16: =IF(C16="","",ROUND(IF(Comparateur!C$12=Paramètres!$B$36,Comparateur!C$9,F15)*Comparateur!C$13/12,2)) -> 63 | F16: =IF(C16="","",ROUND(F15-D16,2)) -> 176454.73 | G16: =IF(C16="","",C16+D16+E16) -> 940.17 | H16: =IF(C16="","",C16+D16) -> 877.17 | I16: =IF(OR($B16="",Comparateur!D$17<>"OK",$B16>Comparateur!D$11),"",ROUND(L15*Comparateur!D$10/12,2)) -> 501.27 | J16: =IF(I16="","",IF($B16=Comparateur!D$11,L15,Comparateur!D$20-I16)) -> 390.23 | K16: =IF(I16="","",ROUND(IF(Comparateur!D$12=Paramètres!$B$36,Comparateur!D$9,L15)*Comparateur!D$13/12,2)) -> 26.54 | L16: =IF(I16="","",ROUND(L15-J16,2)) -> 176527.34 | M16: =IF(I16="","",I16+J16+K16) -> 918.04 | N16: =IF(I16="","",I16+J16) -> 891.5 | O16: =IF(OR($B16="",Comparateur!E$17<>"OK",$B16>Comparateur!E$11),"",ROUND(R15*Comparateur!E$10/12,2)) -> 523.57 | P16: =IF(O16="","",IF($B16=Comparateur!E$11,R15,Comparateur!E$20-O16)) -> 382.39 | Q16: =IF(O16="","",ROUND(IF(Comparateur!E$12=Paramètres!$B$36,Comparateur!E$9,R15)*Comparateur!E$13/12,2)) -> 30 | R16: =IF(O16="","",ROUND(R15-P16,2)) -> 176598.82 | S16: =IF(O16="","",O16+P16+Q16) -> 935.96 | T16: =IF(O16="","",O16+P16) -> 905.96
B17: =IF(B16="","",IF(B16+1>Comparateur!$C$47,"",B16+1)) -> 10 | C17: =IF(OR($B17="",Comparateur!C$17<>"OK",$B17>Comparateur!C$11),"",ROUND(F16*Comparateur!C$10/12,2)) -> 477.9 | D17: =IF(C17="","",IF($B17=Comparateur!C$11,F16,Comparateur!C$20-C17)) -> 399.27 | E17: =IF(C17="","",ROUND(IF(Comparateur!C$12=Paramètres!$B$36,Comparateur!C$9,F16)*Comparateur!C$13/12,2)) -> 63 | F17: =IF(C17="","",ROUND(F16-D17,2)) -> 176055.46 | G17: =IF(C17="","",C17+D17+E17) -> 940.17 | H17: =IF(C17="","",C17+D17) -> 877.17 | I17: =IF(OR($B17="",Comparateur!D$17<>"OK",$B17>Comparateur!D$11),"",ROUND(L16*Comparateur!D$10/12,2)) -> 500.16 | J17: =IF(I17="","",IF($B17=Comparateur!D$11,L16,Comparateur!D$20-I17)) -> 391.34 | K17: =IF(I17="","",ROUND(IF(Comparateur!D$12=Paramètres!$B$36,Comparateur!D$9,L16)*Comparateur!D$13/12,2)) -> 26.48 | L17: =IF(I17="","",ROUND(L16-J17,2)) -> 176136 | M17: =IF(I17="","",I17+J17+K17) -> 917.98 | N17: =IF(I17="","",I17+J17) -> 891.5 | O17: =IF(OR($B17="",Comparateur!E$17<>"OK",$B17>Comparateur!E$11),"",ROUND(R16*Comparateur!E$10/12,2)) -> 522.44 | P17: =IF(O17="","",IF($B17=Comparateur!E$11,R16,Comparateur!E$20-O17)) -> 383.52 | Q17: =IF(O17="","",ROUND(IF(Comparateur!E$12=Paramètres!$B$36,Comparateur!E$9,R16)*Comparateur!E$13/12,2)) -> 30 | R17: =IF(O17="","",ROUND(R16-P17,2)) -> 176215.3 | S17: =IF(O17="","",O17+P17+Q17) -> 935.96 | T17: =IF(O17="","",O17+P17) -> 905.96
B18: =IF(B17="","",IF(B17+1>Comparateur!$C$47,"",B17+1)) -> 11 | C18: =IF(OR($B18="",Comparateur!C$17<>"OK",$B18>Comparateur!C$11),"",ROUND(F17*Comparateur!C$10/12,2)) -> 476.82 | D18: =IF(C18="","",IF($B18=Comparateur!C$11,F17,Comparateur!C$20-C18)) -> 400.35 | E18: =IF(C18="","",ROUND(IF(Comparateur!C$12=Paramètres!$B$36,Comparateur!C$9,F17)*Comparateur!C$13/12,2)) -> 63 | F18: =IF(C18="","",ROUND(F17-D18,2)) -> 175655.11 | G18: =IF(C18="","",C18+D18+E18) -> 940.17 | H18: =IF(C18="","",C18+D18) -> 877.17 | I18: =IF(OR($B18="",Comparateur!D$17<>"OK",$B18>Comparateur!D$11),"",ROUND(L17*Comparateur!D$10/12,2)) -> 499.05 | J18: =IF(I18="","",IF($B18=Comparateur!D$11,L17,Comparateur!D$20-I18)) -> 392.45 | K18: =IF(I18="","",ROUND(IF(Comparateur!D$12=Paramètres!$B$36,Comparateur!D$9,L17)*Comparateur!D$13/12,2)) -> 26.42 | L18: =IF(I18="","",ROUND(L17-J18,2)) -> 175743.55 | M18: =IF(I18="","",I18+J18+K18) -> 917.92 | N18: =IF(I18="","",I18+J18) -> 891.5 | O18: =IF(OR($B18="",Comparateur!E$17<>"OK",$B18>Comparateur!E$11),"",ROUND(R17*Comparateur!E$10/12,2)) -> 521.3 | P18: =IF(O18="","",IF($B18=Comparateur!E$11,R17,Comparateur!E$20-O18)) -> 384.66 | Q18: =IF(O18="","",ROUND(IF(Comparateur!E$12=Paramètres!$B$36,Comparateur!E$9,R17)*Comparateur!E$13/12,2)) -> 30 | R18: =IF(O18="","",ROUND(R17-P18,2)) -> 175830.64 | S18: =IF(O18="","",O18+P18+Q18) -> 935.96 | T18: =IF(O18="","",O18+P18) -> 905.96
B19: =IF(B18="","",IF(B18+1>Comparateur!$C$47,"",B18+1)) -> 12 | C19: =IF(OR($B19="",Comparateur!C$17<>"OK",$B19>Comparateur!C$11),"",ROUND(F18*Comparateur!C$10/12,2)) -> 475.73 | D19: =IF(C19="","",IF($B19=Comparateur!C$11,F18,Comparateur!C$20-C19)) -> 401.44 | E19: =IF(C19="","",ROUND(IF(Comparateur!C$12=Paramètres!$B$36,Comparateur!C$9,F18)*Comparateur!C$13/12,2)) -> 63 | F19: =IF(C19="","",ROUND(F18-D19,2)) -> 175253.67 | G19: =IF(C19="","",C19+D19+E19) -> 940.17 | H19: =IF(C19="","",C19+D19) -> 877.17 | I19: =IF(OR($B19="",Comparateur!D$17<>"OK",$B19>Comparateur!D$11),"",ROUND(L18*Comparateur!D$10/12,2)) -> 497.94 | J19: =IF(I19="","",IF($B19=Comparateur!D$11,L18,Comparateur!D$20-I19)) -> 393.56 | K19: =IF(I19="","",ROUND(IF(Comparateur!D$12=Paramètres!$B$36,Comparateur!D$9,L18)*Comparateur!D$13/12,2)) -> 26.36 | L19: =IF(I19="","",ROUND(L18-J19,2)) -> 175349.99 | M19: =IF(I19="","",I19+J19+K19) -> 917.86 | N19: =IF(I19="","",I19+J19) -> 891.5 | O19: =IF(OR($B19="",Comparateur!E$17<>"OK",$B19>Comparateur!E$11),"",ROUND(R18*Comparateur!E$10/12,2)) -> 520.17 | P19: =IF(O19="","",IF($B19=Comparateur!E$11,R18,Comparateur!E$20-O19)) -> 385.79 | Q19: =IF(O19="","",ROUND(IF(Comparateur!E$12=Paramètres!$B$36,Comparateur!E$9,R18)*Comparateur!E$13/12,2)) -> 30 | R19: =IF(O19="","",ROUND(R18-P19,2)) -> 175444.85 | S19: =IF(O19="","",O19+P19+Q19) -> 935.96 | T19: =IF(O19="","",O19+P19) -> 905.96
... B367: =IF(B366="","",IF(B366+1>Comparateur!$C$47,"",B366+1)) | C367: =IF(OR($B367="",Comparateur!C$17<>"OK",$B367>Comparateur!C$11),"",ROUND(F366*Comparateur!C$10/12,2)) | D367: =IF(C367="","",IF($B367=Comparateur!C$11,F366,Comparateur!C$20-C367)) | E367: =IF(C367="","",ROUND(IF(Comparateur!C$12=Paramètres!$B$36,Comparateur!C$9,F366)*Comparateur!C$13/12,2)) | F367: =IF(C367="","",ROUND(F366-D367,2)) | G367: =IF(C367="","",C367+D367+E367) | H367: =IF(C367="","",C367+D367) | I367: =IF(OR($B367="",Comparateur!D$17<>"OK",$B367>Comparateur!D$11),"",ROUND(L366*Comparateur!D$10/12,2)) | J367: =IF(I367="","",IF($B367=Comparateur!D$11,L366,Comparateur!D$20-I367)) | K367: =IF(I367="","",ROUND(IF(Comparateur!D$12=Paramètres!$B$36,Comparateur!D$9,L366)*Comparateur!D$13/12,2)) | L367: =IF(I367="","",ROUND(L366-J367,2)) | M367: =IF(I367="","",I367+J367+K367) | N367: =IF(I367="","",I367+J367) | O367: =IF(OR($B367="",Comparateur!E$17<>"OK",$B367>Comparateur!E$11),"",ROUND(R366*Comparateur!E$10/12,2)) | P367: =IF(O367="","",IF($B367=Comparateur!E$11,R366,Comparateur!E$20-O367)) | Q367: =IF(O367="","",ROUND(IF(Comparateur!E$12=Paramètres!$B$36,Comparateur!E$9,R366)*Comparateur!E$13/12,2)) | R367: =IF(O367="","",ROUND(R366-P367,2)) | S367: =IF(O367="","",O367+P367+Q367) | T367: =IF(O367="","",O367+P367)
B369: CorpusImmo, millésime 2026. Modèle d'aide à la décision : ne constitue ni un conseil en investissement, ni un conseil fiscal, ni une expertise au sens de la charte de l'expertise en évaluation immobilière. Vérifiez les paramètres avant tout engagement.

Sheet Paramètres
B1: CorpusImmo · corpus.immo · Estimer, comparer, décider. Sur les ventes réelles.
B2: Paramètres
B3: Les seules valeurs à mettre à jour quand la réglementation ou le marché changent. Mon prêt et le Comparateur y renvoient pour chaque barème.
B5: Cellules bleues : à remplir. Cellules blanches : calculées automatiquement.
B6: BARÈMES RÉGLEMENTAIRES
B7: Paramètre | C7: Valeur | D7: Source (organisme, texte, date) | E7: Mise à jour | F7: Commentaire
B8: Taux d'usure, prêts à taux fixe de moins de 10 ans | C8: 0.0407 | D8: ="Banque de France, taux d'usure applicables au "&$C$41&", avis publié le "&TEXT(DAY($C$42),"00")&"/"&TEXT(MONTH($C$42),"00")&"/"&YEAR($C$42)&". Vérifié le "&TEXT(DAY($C$43),"00")&"/"&TEXT(MONTH($C$43),"00")&"/"&YEAR($C$43)&"." -> Banque de France, taux d'usure applicables au 3e trimestre 2026, avis publié le 29/06/2026. Vérifié le 05/09/2026. | E8: Trimestrielle (1er janvier, avril, juillet, octobre) | F8: Plafond légal du TAEG. Une offre au-dessus est illégale.
B9: Taux d'usure, prêts à taux fixe de 10 ans à moins de 20 ans | C9: 0.0457 | D9: ="Banque de France, taux d'usure applicables au "&$C$41&", avis publié le "&TEXT(DAY($C$42),"00")&"/"&TEXT(MONTH($C$42),"00")&"/"&YEAR($C$42)&". Vérifié le "&TEXT(DAY($C$43),"00")&"/"&TEXT(MONTH($C$43),"00")&"/"&YEAR($C$43)&"." -> Banque de France, taux d'usure applicables au 3e trimestre 2026, avis publié le 29/06/2026. Vérifié le 05/09/2026. | E9: Trimestrielle
B10: Taux d'usure, prêts à taux fixe de 20 ans et plus | C10: 0.0529 | D10: ="Banque de France, taux d'usure applicables au "&$C$41&", avis publié le "&TEXT(DAY($C$42),"00")&"/"&TEXT(MONTH($C$42),"00")&"/"&YEAR($C$42)&". Vérifié le "&TEXT(DAY($C$43),"00")&"/"&TEXT(MONTH($C$43),"00")&"/"&YEAR($C$43)&"." -> Banque de France, taux d'usure applicables au 3e trimestre 2026, avis publié le 29/06/2026. Vérifié le 05/09/2026. | E10: Trimestrielle | F10: Tranche de la plupart des prêts immobiliers (20 et 25 ans).
B11: Seuil de durée entre les deux premières tranches d'usure | C11: 120 | D11: ="Banque de France, taux d'usure applicables au "&$C$41&", avis publié le "&TEXT(DAY($C$42),"00")&"/"&TEXT(MONTH($C$42),"00")&"/"&YEAR($C$42)&". Vérifié le "&TEXT(DAY($C$43),"00")&"/"&TEXT(MONTH($C$43),"00")&"/"&YEAR($C$43)&"." -> Banque de France, taux d'usure applicables au 3e trimestre 2026, avis publié le 29/06/2026. Vérifié le 05/09/2026. | E11: Stable | F11: 10 ans. Le classeur choisit la tranche d'usure selon la durée du prêt.
B12: Seuil de durée entre les deux dernières tranches d'usure | C12: 240 | D12: ="Banque de France, taux d'usure applicables au "&$C$41&", avis publié le "&TEXT(DAY($C$42),"00")&"/"&TEXT(MONTH($C$42),"00")&"/"&YEAR($C$42)&". Vérifié le "&TEXT(DAY($C$43),"00")&"/"&TEXT(MONTH($C$43),"00")&"/"&YEAR($C$43)&"." -> Banque de France, taux d'usure applicables au 3e trimestre 2026, avis publié le 29/06/2026. Vérifié le 05/09/2026. | E12: Stable | F12: 20 ans.
B13: Taux d'effort maximal (HCSF), assurance comprise | C13: 0.35 | D13: ="HCSF, décision D-HCSF-2021-7 du 29/09/2021, contraignante depuis le 01/01/2022, confirmée par la décision D-HCSF-2023-2 du 29/06/2023 ; economie.gouv.fr. Vérifié le "&TEXT(DAY($C$43),"00")&"/"&TEXT(MONTH($C$43),"00")&"/"&YEAR($C$43)&"." -> HCSF, décision D-HCSF-2021-7 du 29/09/2021, contraignante depuis le 01/01/2022, confirmée par la décision D-HCSF-2023-2 du 29/06/2023 ; economie.gouv.fr. Vérifié le 05/09/2026. | E13: À chaque décision du HCSF | F13: Norme contraignante avec une marge de flexibilité de 20 % de la production.
B14: Durée maximale d'un prêt (HCSF) | C14: 300 | D14: ="HCSF, décision D-HCSF-2021-7 du 29/09/2021, contraignante depuis le 01/01/2022, confirmée par la décision D-HCSF-2023-2 du 29/06/2023 ; economie.gouv.fr. Vérifié le "&TEXT(DAY($C$43),"00")&"/"&TEXT(MONTH($C$43),"00")&"/"&YEAR($C$43)&"." -> HCSF, décision D-HCSF-2021-7 du 29/09/2021, contraignante depuis le 01/01/2022, confirmée par la décision D-HCSF-2023-2 du 29/06/2023 ; economie.gouv.fr. Vérifié le 05/09/2026. | E14: À chaque décision du HCSF | F14: 25 ans, hors différé.
B15: Différé maximal toléré en plus (HCSF, VEFA, construction, travaux) | C15: 24 | D15: ="HCSF, décision D-HCSF-2021-7 du 29/09/2021, contraignante depuis le 01/01/2022, confirmée par la décision D-HCSF-2023-2 du 29/06/2023 ; economie.gouv.fr. Vérifié le "&TEXT(DAY($C$43),"00")&"/"&TEXT(MONTH($C$43),"00")&"/"&YEAR($C$43)&"." -> HCSF, décision D-HCSF-2021-7 du 29/09/2021, contraignante depuis le 01/01/2022, confirmée par la décision D-HCSF-2023-2 du 29/06/2023 ; economie.gouv.fr. Vérifié le 05/09/2026. | E15: À chaque décision du HCSF | F15: 2 ans : un prêt peut atteindre 27 ans quand le bien n'est pas livré à la signature.
B16: Indemnité de remboursement anticipé : plafond en mois d'intérêts | C16: 6 | D16: ="Code de la consommation, art. L313-47 et R313-25. Vérifié le "&TEXT(DAY($C$43),"00")&"/"&TEXT(MONTH($C$43),"00")&"/"&YEAR($C$43)&"." -> Code de la consommation, art. L313-47 et R313-25. Vérifié le 05/09/2026. | E16: Stable | F16: Six mois d'intérêts sur le capital remboursé, au taux moyen du prêt.
B17: Indemnité de remboursement anticipé : plafond en part du capital restant dû | C17: 0.03 | D17: ="Code de la consommation, art. L313-47 et R313-25. Vérifié le "&TEXT(DAY($C$43),"00")&"/"&TEXT(MONTH($C$43),"00")&"/"&YEAR($C$43)&"." -> Code de la consommation, art. L313-47 et R313-25. Vérifié le 05/09/2026. | E17: Stable | F17: Le plus bas des deux plafonds s'applique. Exonérations : voir Méthode.
B19: REPÈRES DE MARCHÉ ET GARDE-FOUS
B20: Paramètre | C20: Valeur | D20: Source (organisme, texte, date) | E20: Mise à jour | F20: Commentaire
B21: Part du versement au FMG restituée en fin de prêt (caution Crédit Logement) | C21: 0.7 | D21: ="Crédit Logement, page tarif officielle (creditlogement.fr) : restitution « d'environ 70 % », révisée chaque trimestre. Vérifié le "&TEXT(DAY($C$43),"00")&"/"&TEXT(MONTH($C$43),"00")&"/"&YEAR($C$43)&"." -> Crédit Logement, page tarif officielle (creditlogement.fr) : restitution « d'environ 70 % », révisée chaque trimestre. Vérifié le 05/09/2026. | E21: Trimestrielle | F21: 0 % pour une hypothèque, une caution CAMCA ou SACCEF (pas de restitution).
B22: Taux nominal minimal vraisemblable hors prêt à taux zéro (garde-fou de saisie) | C22: 0.001 | D22: Convention CorpusImmo, commune aux matrices qui saisissent des taux : un taux entre 0 et 0,10 % signale presque toujours une saisie en fraction (0,0335 au lieu de 3,35 %). | E22: Stable | F22: Le contrôle « Taux vraisemblable » passe au rouge en dessous, sauf à 0 % exactement (PTZ).
B23: Taux nominal maximal admis à la saisie (garde-fou) | C23: 0.2 | D23: Convention du classeur : au-delà, la saisie est refusée et le contrôle de saisie passe au rouge. Le taux d'usure, bien plus bas, est contrôlé à part. | E23: Stable
B24: Taux d'assurance maximal admis à la saisie (garde-fou) | C24: 0.05 | D24: Convention du classeur : un taux d'assurance annuel au-delà de 5 % du capital n'existe pas ; c'est presque toujours une saisie en euros ou en fraction. | E24: Stable
B25: Repère : taux moyen des prêts sur 20 ans | C25: 0.0327 | D25: ="Observatoire Crédit Logement / CSA, analyse du marché du mois d'août 2026 (publiée en septembre 2026) : 3,27 % sur 20 ans, taux moyen toutes durées 3,31 %, en hausse de 3 centièmes de point en juillet"&" comme en août. lobservatoire.creditlogement.fr. Vérifié le "&TEXT(DAY($C$43),"00")&"/"&TEXT(MONTH($C$43),"00")&"/"&YEAR($C$43)&"." -> Observatoire Crédit Logement / CSA, analyse du marché du mois d'août 2026 (publiée en septembre 2026) : 3,27 % sur 20 ans, taux moyen toutes durées 3,31 %, en hausse de 3 centièmes de point en juillet comme en août. lobservatoire.creditlogement.fr. Vérifié le 05/09/2026. | E25: Mensuelle, à rafraîchir avant tout dossier engageant | F25: Point de départ pour juger une offre ; le taux se saisit dossier par dossier dans Mon prêt et le Comparateur.
B26: Repère : taux moyen des prêts sur 25 ans | C26: 0.0335 | D26: ="Observatoire Crédit Logement / CSA, analyse du marché du mois d'août 2026 (publiée en septembre 2026) : 3,35 % sur 25 ans, 3,14 % sur 15 ans, en hausse de 15 centièmes de point depuis décembre 2025. l"&"observatoire.creditlogement.fr. Vérifié le "&TEXT(DAY($C$43),"00")&"/"&TEXT(MONTH($C$43),"00")&"/"&YEAR($C$43)&"." -> Observatoire Crédit Logement / CSA, analyse du marché du mois d'août 2026 (publiée en septembre 2026) : 3,35 % sur 25 ans, 3,14 % sur 15 ans, en hausse de 15 centièmes de point depuis décembre 2025. lobservatoire.creditlogement.fr. Vérifié le 05/09/2026. | E26: Mensuelle, à rafraîchir avant tout dossier engageant
B27: Repère : taux d'assurance emprunteur, contrat groupe (sur capital initial) | C27: 0.0036 | D27: ="Baromètres 2026 (pretclair.fr, covelia.fr) : 0,30 à 0,42 % selon l'âge et la quotité. Vérifié le "&TEXT(DAY($C$43),"00")&"/"&TEXT(MONTH($C$43),"00")&"/"&YEAR($C$43)&"." -> Baromètres 2026 (pretclair.fr, covelia.fr) : 0,30 à 0,42 % selon l'âge et la quotité. Vérifié le 05/09/2026. | E27: Annuelle
B28: Repère : taux d'assurance emprunteur, délégation (souvent sur capital restant dû) | C28: 0.0017 | D28: ="Baromètres 2026 (pretclair.fr, covelia.fr) : 0,10 à 0,20 %, 35 ans non fumeur. Loi n° 2022-270 du 28 février 2022 (Lemoine) : résiliation à tout moment. Vérifié le "&TEXT(DAY($C$43),"00")&"/"&TEXT(MONTH($C$43),"00")&"/"&YEAR($C$43)&"." -> Baromètres 2026 (pretclair.fr, covelia.fr) : 0,10 à 0,20 %, 35 ans non fumeur. Loi n° 2022-270 du 28 février 2022 (Lemoine) : résiliation à tout moment. Vérifié le 05/09/2026. | E28: Annuelle | F28: Une délégation cotise le plus souvent sur le capital restant dû : choisir l'assiette dans la liste.
B29: Repère : frais de dossier, bas de fourchette | C29: 0 | D29: ="Meilleurtaux, relevé de 119 banques au 01/03/2026 : moyenne 1 899,68 € pour 200 000 € empruntés, 92 établissements entre 0,50 % et 1,40 % du capital, de 0 € à 2 500 € selon les banques. Vérifié le "&TEXT(DAY($C$43),"00")&"/"&TEXT(MONTH($C$43),"00")&"/"&YEAR($C$43)&"." -> Meilleurtaux, relevé de 119 banques au 01/03/2026 : moyenne 1 899,68 € pour 200 000 € empruntés, 92 établissements entre 0,50 % et 1,40 % du capital, de 0 € à 2 500 € selon les banques. Vérifié le 05/09/2026. | E29: Annuelle | F29: Négociables, et offerts par quelques banques en ligne. Moyenne du relevé : 1 899,68 € pour 200 000 €.
B30: Repère : frais de dossier, haut de fourchette | C30: 2500 | D30: ="Meilleurtaux, relevé de 119 banques au 01/03/2026 : moyenne 1 899,68 € pour 200 000 € empruntés, 92 établissements entre 0,50 % et 1,40 % du capital, de 0 € à 2 500 € selon les banques. Vérifié le "&TEXT(DAY($C$43),"00")&"/"&TEXT(MONTH($C$43),"00")&"/"&YEAR($C$43)&"." -> Meilleurtaux, relevé de 119 banques au 01/03/2026 : moyenne 1 899,68 € pour 200 000 € empruntés, 92 établissements entre 0,50 % et 1,40 % du capital, de 0 € à 2 500 € selon les banques. Vérifié le 05/09/2026. | E30: Annuelle | F30: Plafond le plus élevé du relevé. Un dossier au-dessus de la moyenne se négocie.
B31: Repère : frais de caution, en part du capital emprunté | C31: 0.012 | D31: ="Convention prudente du classeur : Crédit Logement ne publie pas son barème et les relevés de place vont de 0,85 % + 200 € (optimhome.com, 2026) à 1,5 à 1,75 % du capital (perlib.fr, 2026). Vérifié le "&TEXT(DAY($C$43),"00")&"/"&TEXT(MONTH($C$43),"00")&"/"&YEAR($C$43)&"." -> Convention prudente du classeur : Crédit Logement ne publie pas son barème et les relevés de place vont de 0,85 % + 200 € (optimhome.com, 2026) à 1,5 à 1,75 % du capital (perlib.fr, 2026). Vérifié le 05/09/2026. | E31: Annuelle, sur le simulateur creditlogement.fr | F31: Aucune source primaire ne tranche : le classeur retient la borne haute des relevés, parce que sous-estimer un coût avancé par l'emprunteur flatte le TAEG. Commission de caution et versement au fonds mutuel de garantie compris. Une hypothèque coûte davantage : voir le repère suivant.
B32: Repère : frais d'hypothèque, en part du capital | C32: 0.015 | D32: ="PrêtClair, « Garantie de prêt immobilier 2026 : caution, hypothèque ou PPD », page du 6 mai 2026 : environ 2 900 € pour 200 000 € empruntés et 4 100 € pour 300 000 €, soit 1,4 à 1,5 % du capital (émol"&"uments du notaire, taxe de publicité foncière, contribution de sécurité immobilière, formalités). Vérifié le "&TEXT(DAY($C$43),"00")&"/"&TEXT(MONTH($C$43),"00")&"/"&YEAR($C$43)&"." -> PrêtClair, « Garantie de prêt immobilier 2026 : caution, hypothèque ou PPD », page du 6 mai 2026 : environ 2 900 € pour 200 000 € empruntés et 4 100 € pour 300 000 €, soit 1,4 à 1,5 % du capital (émoluments du notaire, taxe de publicité foncière, contribution de sécurité immobilière, formalités). Vérifié le 05/09/2026. | E32: Annuelle | F32: Hypothèque conventionnelle. L'hypothèque légale spéciale du prêteur de deniers (ancien PPD), exonérée de taxe de publicité foncière, revient à environ 0,90 % du capital. Aucune restitution en fin de prêt : le FMG reste à 0.
B34: LISTE DÉROULANTE : ASSIETTE DE L'ASSURANCE
B35: Assurance calculée sur (liste de Mon prêt et du Comparateur)
B36: Capital initial | D36: Contrat groupe bancaire : cotisation constante sur toute la durée.
B37: Capital restant dû | D37: Délégation d'assurance : cotisation dégressive, recalculée chaque mois sur le capital restant dû.
B38: Libellés fixes, testés par les formules de l'Échéancier et du Détail des offres. Loi n° 2022-270 du 28 février 2022 (Lemoine) : les délégations cotisent le plus souvent sur le capital restant dû.
B40: MILLÉSIME DES TAUX D'USURE ET VÉRIFICATION
B41: Trimestre d'application des taux d'usure | C41: 3e trimestre 2026 | D41: Banque de France, avis trimestriel. Écrivez le trimestre tel qu'il doit apparaître, par exemple « 1er trimestre 2027 ». | E41: Trimestrielle | F41: Repris tel quel dans la colonne Source ci-dessus et dans l'onglet Méthode : une seule saisie met tous les libellés à jour.
B42: Date de publication de l'avis de la Banque de France | C42: 46202 | D42: banque-france.fr, rubrique Taux d'usure : avis publié le dernier jour ouvré de mars, juin, septembre et décembre. | E42: Trimestrielle | F42: Date de l'avis qui fixe les trois taux d'usure saisis plus haut.
B43: Dernière vérification des paramètres | C43: 46270 | D43: Aucun de ces taux n'est recopié dans une formule : toutes pointent ici. | E43: À chaque vérification | F43: Cette date s'affiche dans chaque libellé de source, ici et dans Méthode.
B45: Ces valeurs sont volontairement isolées ici. Un modèle qui embarque un taux d'usure au cœur de ses formules devient faux au trimestre suivant,
B46: sans que personne ne s'en aperçoive. Vérifiez-les avant tout usage engageant, et notez la date de votre dernière vérification ci-dessus.
B49: CorpusImmo, millésime 2026. Modèle d'aide à la décision : ne constitue ni un conseil en investissement, ni un conseil fiscal, ni une expertise au sens de la charte de l'expertise en évaluation immobilière. Vérifiez les paramètres avant tout engagement.

Sheet Méthode
B1: CorpusImmo · corpus.immo · Estimer, comparer, décider. Sur les ventes réelles.
B2: Méthode de calcul
B3: Ce que le modèle fait, ce qu'il ne fait pas, et sur quelles sources reposent ses chiffres.
B5: CONVENTIONS RETENUES, ET CE QU'ELLES COÛTENT
B6: Mensualité | C6: Échéance constante d'un prêt amortissable : capital × (taux ÷ 12) ÷ (1 − (1 + taux ÷ 12) ^ − nombre d'échéances), soit capital ÷ nombre d'échéances à taux nul. C'est le calcul d'un prêt amortissable à échéances constantes, celui de la quasi-totalité des crédits immobiliers français. Le taux mensuel est proportionnel (taux annuel ÷ 12), convention des banques françaises : 3,35 % nominal équivaut à 3,40 % actuariel. L'échéance est arrondie au centime, comme dans l'offre de prêt ; la dernière échéance solde exactement le capital restant dû et absorbe l'arrondi.
B7: Intérêts et capital du mois | C7: Échéancier itératif : intérêts du mois = capital restant dû du mois précédent × taux ÷ 12, arrondis au centime ; capital = échéance − intérêts ; capital restant dû = précédent − capital. Aucune fonction financière : le tableau reste juste à taux nul (prêt à taux zéro). Les premières années remboursent surtout des intérêts : c'est ce qui rend une revente précoce coûteuse, et ce que le tableau rend visible.
B8: Différé | C8: Différé d'amortissement (VEFA, construction, travaux) : pendant les mois de différé, l'échéance se limite aux intérêts du mois plus l'assurance ; le capital n'est pas entamé. L'amortissement commence ensuite sur la durée restante (durée totale − différé). Le différé total avec capitalisation des intérêts, les déblocages progressifs et les intérêts intercalaires d'une VEFA ne sont pas modélisés.
B9: Dates | C9: Vraies dates Excel. La première échéance tombe à la date saisie, les suivantes le même jour chaque mois (dernier jour du mois si le jour n'existe pas). Le déblocage est supposé un mois avant la première échéance, sans intérêts intercalaires.
B10: Assurance | C10: Deux assiettes au choix, par prêt et par offre. Capital initial : cotisation constante, convention des contrats groupe bancaires. Capital restant dû : cotisation recalculée chaque mois sur le capital restant dû du mois précédent, convention de la plupart des délégations (loi Lemoine du 28 février 2022) ; sur 25 ans à taux égal, elle coûte 30 à 40 % de moins. La cotisation est arrondie au centime.
B11: Coût total du crédit | C11: Intérêts + assurance + frais de dossier + frais de garantie. Il agrège tout ce que la banque facture, mais il ne permet de comparer deux offres qu'à durée égale : une offre plus courte coûte presque toujours moins en intérêts tout en pesant davantage chaque mois. À durées différentes, le classeur refuse de désigner une offre la moins chère et renvoie au TAEG.
B12: Garantie et restitution | C12: Le coût total et le TAEG comptent les frais de garantie en entier. Pour une caution Crédit Logement, une partie du versement au fonds mutuel de garantie (FMG) est restituée en fin de prêt (environ 70 %, Paramètres) : le classeur l'affiche à part, en estimation, et calcule un coût total net de restitution. La restitution n'entre pas dans le TAEG. Le privilège de prêteur de deniers a été remplacé le 1er janvier 2022 par l'hypothèque légale spéciale du prêteur de deniers (ordonnance n° 2021-1192 du 15 septembre 2021), sans changement de coût.
B13: TAEG et TAEA | C13: Taux annuel effectif global selon la méthode d'équivalence de l'annexe à l'article R314-3 du Code de la consommation : le taux mensuel qui égalise le montant net versé (capital − frais de dossier − frais de garantie) et la somme des échéances actualisées (capital, intérêts et assurance obligatoire), annualisé par (1 + taux mensuel) ^ 12 − 1. Résolu par la fonction IRR sur les flux réels de l'Échéancier. Le TAEG hors assurance suit la même méthode sans les cotisations ; le TAEA (taux annuel effectif de l'assurance) est la différence des deux. Ne sont pas comptés : frais de notaire, frais de courtage, frais de tenue de compte, assurances facultatives. Sur l'exemple livré, la conversion proportionnelle du seul nominal (3,35 %) redonne 3,40 % : l'écart avec le TAEG est le poids des frais et de l'assurance.
B14: Taux d'usure | C14: ="Le TAEG ne peut pas dépasser le taux d'usure du trimestre, fixé par la Banque de France par tranche de durée (moins de 10 ans, 10 à moins de 20 ans, 20 ans et plus). Le classeur choisit la tranche sel"&"on la durée du prêt et compare. Les valeurs de Paramètres sont celles du "&Paramètres!$C$41&", avis publié le "&TEXT(DAY(Paramètres!$C$42),"00")&"/"&TEXT(MONTH(Paramètres!$C$42),"00")&"/"&YEAR(Paramètres!$C$42)&" : à rafraîchir chaque trimestre, en corrigeant aussi le trimestre et la date de l'avis dans Paramètres, deux cellules bleues dont dépendent tous les libellés de source." -> Le TAEG ne peut pas dépasser le taux d'usure du trimestre, fixé par la Banque de France par tranche de durée (moins de 10 ans, 10 à moins de 20 ans, 20 ans et plus). Le classeur choisit la tranche selon la durée du prêt et compare. Les valeurs de Paramètres sont celles du 3e trimestre 2026, avis publié le 29/06/2026 : à rafraîchir chaque trimestre, en corrigeant aussi le trimestre et la date de l'avis dans Paramètres, deux cellules bleues dont dépendent tous les libellés de source.
B15: Repères HCSF | C15: Taux d'effort = mensualité totale assurance comprise ÷ revenus nets mensuels, plafonné à 35 % ; durée limitée à 25 ans, 27 ans avec un différé d'au plus 2 ans quand le bien n'est pas livré à la signature. Norme contraignante depuis le 1er janvier 2022, avec une marge de flexibilité de 20 % de la production, dont 70 % pour la résidence principale et 30 % pour les primo-accédants. Le classeur ne compte que ce prêt : ajoutez vos autres crédits à la main.
B16: Remboursement anticipé | C16: Capital restant dû lu dans l'Échéancier après l'échéance choisie. Indemnité plafonnée au plus bas de six mois d'intérêts sur le capital remboursé, au taux moyen du prêt, et de 3 % du capital restant dû (Code de la consommation, art. L313-47 et R313-25). Aucune indemnité n'est due, pour les prêts conclus depuis le 1er juillet 1999, quand la vente suit une mutation professionnelle, une cessation forcée d'activité ou le décès de l'emprunteur ou de son conjoint. Le classeur affiche le plafond légal ; l'offre de prêt peut prévoir moins.
B17: Comparateur | C17: Trois offres côte à côte. Une colonne sans montant, taux ni durée est ignorée : comparer deux offres fonctionne. Chaque offre a son propre échéancier (onglet Détail des offres), son TAEG et son coût total. Classement par TAEG (valable à toute durée) et par coût total (à durée égale seulement, contrôlé). L'offre de rang 1 ressort en vert ; les écarts au meilleur sont affichés en clair. À égalité, deux offres partagent le même rang et la première colonne l'emporte au verdict.
B18: Taux et arrondis | C18: Tous les taux sont des fractions affichées en pourcentage : tapez 3,35 dans une cellule de taux, elle affiche 3,35 % et contient 0,0335. Aucune formule ne divise par 100. Échéances, intérêts et cotisations sont arrondis au centime à chaque ligne ; les totaux sont les sommes des lignes, ce qui peut différer de quelques centimes d'un calcul non arrondi.
B20: CE QUE CE MODÈLE NE FAIT PAS
B21: • Il ne traite ni les prêts à paliers, ni les prêts in fine, ni les taux variables ou révisables, ni la modulation d'échéances.
B22: • Il ne lisse pas un prêt à taux zéro avec un prêt principal : chaque prêt se saisit séparément, le PTZ à 0 % dans Mon prêt.
B23: • Il ne modélise ni les déblocages progressifs d'une VEFA, ni les intérêts intercalaires, ni le différé total avec capitalisation des intérêts.
B24: • Il ne calcule pas les frais de garantie ni les frais de notaire : ils se saisissent tels que l'offre les indique.
B25: • Il ne gère qu'une seule assurance et une seule quotité ; pour deux co-emprunteurs, saisissez le taux cumulé des deux contrats.
B26: • Il ne calcule pas le taux d'effort complet du foyer (autres crédits, revenus locatifs pondérés) : c'est l'objet de la matrice Capacité d'emprunt et bilan patrimonial.
B27: • Il ne remplace ni l'offre de prêt, seul document opposable, ni un conseil en financement.
B29: SOURCES
B30: Taux d'usure, prêts à taux fixe de moins de 10 ans | C30: ="Banque de France, taux d'usure applicables au "&Paramètres!$C$41&", avis publié le "&TEXT(DAY(Paramètres!$C$42),"00")&"/"&TEXT(MONTH(Paramètres!$C$42),"00")&"/"&YEAR(Paramètres!$C$42)&". Vérifié le "&TEXT(DAY(Paramètres!$C$43),"00")&"/"&TEXT(MONTH(Paramètres!$C$43),"00")&"/"&YEAR(Paramètres!$C$43)&"." -> Banque de France, taux d'usure applicables au 3e trimestre 2026, avis publié le 29/06/2026. Vérifié le 05/09/2026.
B31: Taux d'usure, prêts à taux fixe de 10 ans à moins de 20 ans | C31: ="Banque de France, taux d'usure applicables au "&Paramètres!$C$41&", avis publié le "&TEXT(DAY(Paramètres!$C$42),"00")&"/"&TEXT(MONTH(Paramètres!$C$42),"00")&"/"&YEAR(Paramètres!$C$42)&". Vérifié le "&TEXT(DAY(Paramètres!$C$43),"00")&"/"&TEXT(MONTH(Paramètres!$C$43),"00")&"/"&YEAR(Paramètres!$C$43)&"." -> Banque de France, taux d'usure applicables au 3e trimestre 2026, avis publié le 29/06/2026. Vérifié le 05/09/2026.
B32: Taux d'usure, prêts à taux fixe de 20 ans et plus | C32: ="Banque de France, taux d'usure applicables au "&Paramètres!$C$41&", avis publié le "&TEXT(DAY(Paramètres!$C$42),"00")&"/"&TEXT(MONTH(Paramètres!$C$42),"00")&"/"&YEAR(Paramètres!$C$42)&". Vérifié le "&TEXT(DAY(Paramètres!$C$43),"00")&"/"&TEXT(MONTH(Paramètres!$C$43),"00")&"/"&YEAR(Paramètres!$C$43)&"." -> Banque de France, taux d'usure applicables au 3e trimestre 2026, avis publié le 29/06/2026. Vérifié le 05/09/2026.
B33: Seuil de durée entre les deux premières tranches d'usure | C33: ="Banque de France, taux d'usure applicables au "&Paramètres!$C$41&", avis publié le "&TEXT(DAY(Paramètres!$C$42),"00")&"/"&TEXT(MONTH(Paramètres!$C$42),"00")&"/"&YEAR(Paramètres!$C$42)&". Vérifié le "&TEXT(DAY(Paramètres!$C$43),"00")&"/"&TEXT(MONTH(Paramètres!$C$43),"00")&"/"&YEAR(Paramètres!$C$43)&"." -> Banque de France, taux d'usure applicables au 3e trimestre 2026, avis publié le 29/06/2026. Vérifié le 05/09/2026.
B34: Seuil de durée entre les deux dernières tranches d'usure | C34: ="Banque de France, taux d'usure applicables au "&Paramètres!$C$41&", avis publié le "&TEXT(DAY(Paramètres!$C$42),"00")&"/"&TEXT(MONTH(Paramètres!$C$42),"00")&"/"&YEAR(Paramètres!$C$42)&". Vérifié le "&TEXT(DAY(Paramètres!$C$43),"00")&"/"&TEXT(MONTH(Paramètres!$C$43),"00")&"/"&YEAR(Paramètres!$C$43)&"." -> Banque de France, taux d'usure applicables au 3e trimestre 2026, avis publié le 29/06/2026. Vérifié le 05/09/2026.
B35: Taux d'effort maximal (HCSF), assurance comprise | C35: ="HCSF, décision D-HCSF-2021-7 du 29/09/2021, contraignante depuis le 01/01/2022, confirmée par la décision D-HCSF-2023-2 du 29/06/2023 ; economie.gouv.fr. Vérifié le "&TEXT(DAY(Paramètres!$C$43),"00")&"/"&TEXT(MONTH(Paramètres!$C$43),"00")&"/"&YEAR(Paramètres!$C$43)&"." -> HCSF, décision D-HCSF-2021-7 du 29/09/2021, contraignante depuis le 01/01/2022, confirmée par la décision D-HCSF-2023-2 du 29/06/2023 ; economie.gouv.fr. Vérifié le 05/09/2026.
B36: Durée maximale d'un prêt (HCSF) | C36: ="HCSF, décision D-HCSF-2021-7 du 29/09/2021, contraignante depuis le 01/01/2022, confirmée par la décision D-HCSF-2023-2 du 29/06/2023 ; economie.gouv.fr. Vérifié le "&TEXT(DAY(Paramètres!$C$43),"00")&"/"&TEXT(MONTH(Paramètres!$C$43),"00")&"/"&YEAR(Paramètres!$C$43)&"." -> HCSF, décision D-HCSF-2021-7 du 29/09/2021, contraignante depuis le 01/01/2022, confirmée par la décision D-HCSF-2023-2 du 29/06/2023 ; economie.gouv.fr. Vérifié le 05/09/2026.
B37: Différé maximal toléré en plus (HCSF, VEFA, construction, travaux) | C37: ="HCSF, décision D-HCSF-2021-7 du 29/09/2021, contraignante depuis le 01/01/2022, confirmée par la décision D-HCSF-2023-2 du 29/06/2023 ; economie.gouv.fr. Vérifié le "&TEXT(DAY(Paramètres!$C$43),"00")&"/"&TEXT(MONTH(Paramètres!$C$43),"00")&"/"&YEAR(Paramètres!$C$43)&"." -> HCSF, décision D-HCSF-2021-7 du 29/09/2021, contraignante depuis le 01/01/2022, confirmée par la décision D-HCSF-2023-2 du 29/06/2023 ; economie.gouv.fr. Vérifié le 05/09/2026.
B38: Indemnité de remboursement anticipé : plafond en mois d'intérêts | C38: ="Code de la consommation, art. L313-47 et R313-25. Vérifié le "&TEXT(DAY(Paramètres!$C$43),"00")&"/"&TEXT(MONTH(Paramètres!$C$43),"00")&"/"&YEAR(Paramètres!$C$43)&"." -> Code de la consommation, art. L313-47 et R313-25. Vérifié le 05/09/2026.
B39: Indemnité de remboursement anticipé : plafond en part du capital restant dû | C39: ="Code de la consommation, art. L313-47 et R313-25. Vérifié le "&TEXT(DAY(Paramètres!$C$43),"00")&"/"&TEXT(MONTH(Paramètres!$C$43),"00")&"/"&YEAR(Paramètres!$C$43)&"." -> Code de la consommation, art. L313-47 et R313-25. Vérifié le 05/09/2026.
B40: Part du versement au FMG restituée en fin de prêt (caution Crédit Logement) | C40: ="Crédit Logement, page tarif officielle (creditlogement.fr) : restitution « d'environ 70 % », révisée chaque trimestre. Vérifié le "&TEXT(DAY(Paramètres!$C$43),"00")&"/"&TEXT(MONTH(Paramètres!$C$43),"00")&"/"&YEAR(Paramètres!$C$43)&"." -> Crédit Logement, page tarif officielle (creditlogement.fr) : restitution « d'environ 70 % », révisée chaque trimestre. Vérifié le 05/09/2026.
B41: Taux nominal minimal vraisemblable hors prêt à taux zéro (garde-fou de saisie) | C41: Convention CorpusImmo, commune aux matrices qui saisissent des taux : un taux entre 0 et 0,10 % signale presque toujours une saisie en fraction (0,0335 au lieu de 3,35 %).
B42: Taux nominal maximal admis à la saisie (garde-fou) | C42: Convention du classeur : au-delà, la saisie est refusée et le contrôle de saisie passe au rouge. Le taux d'usure, bien plus bas, est contrôlé à part.
B43: Taux d'assurance maximal admis à la saisie (garde-fou) | C43: Convention du classeur : un taux d'assurance annuel au-delà de 5 % du capital n'existe pas ; c'est presque toujours une saisie en euros ou en fraction.
B44: Repère : taux moyen des prêts sur 20 ans | C44: ="Observatoire Crédit Logement / CSA, analyse du marché du mois d'août 2026 (publiée en septembre 2026) : 3,27 % sur 20 ans, taux moyen toutes durées 3,31 %, en hausse de 3 centièmes de point en juillet"&" comme en août. lobservatoire.creditlogement.fr. Vérifié le "&TEXT(DAY(Paramètres!$C$43),"00")&"/"&TEXT(MONTH(Paramètres!$C$43),"00")&"/"&YEAR(Paramètres!$C$43)&"." -> Observatoire Crédit Logement / CSA, analyse du marché du mois d'août 2026 (publiée en septembre 2026) : 3,27 % sur 20 ans, taux moyen toutes durées 3,31 %, en hausse de 3 centièmes de point en juillet comme en août. lobservatoire.creditlogement.fr. Vérifié le 05/09/2026.
B45: Repère : taux moyen des prêts sur 25 ans | C45: ="Observatoire Crédit Logement / CSA, analyse du marché du mois d'août 2026 (publiée en septembre 2026) : 3,35 % sur 25 ans, 3,14 % sur 15 ans, en hausse de 15 centièmes de point depuis décembre 2025. l"&"observatoire.creditlogement.fr. Vérifié le "&TEXT(DAY(Paramètres!$C$43),"00")&"/"&TEXT(MONTH(Paramètres!$C$43),"00")&"/"&YEAR(Paramètres!$C$43)&"." -> Observatoire Crédit Logement / CSA, analyse du marché du mois d'août 2026 (publiée en septembre 2026) : 3,35 % sur 25 ans, 3,14 % sur 15 ans, en hausse de 15 centièmes de point depuis décembre 2025. lobservatoire.creditlogement.fr. Vérifié le 05/09/2026.
B46: Repère : taux d'assurance emprunteur, contrat groupe (sur capital initial) | C46: ="Baromètres 2026 (pretclair.fr, covelia.fr) : 0,30 à 0,42 % selon l'âge et la quotité. Vérifié le "&TEXT(DAY(Paramètres!$C$43),"00")&"/"&TEXT(MONTH(Paramètres!$C$43),"00")&"/"&YEAR(Paramètres!$C$43)&"." -> Baromètres 2026 (pretclair.fr, covelia.fr) : 0,30 à 0,42 % selon l'âge et la quotité. Vérifié le 05/09/2026.
B47: Repère : taux d'assurance emprunteur, délégation (souvent sur capital restant dû) | C47: ="Baromètres 2026 (pretclair.fr, covelia.fr) : 0,10 à 0,20 %, 35 ans non fumeur. Loi n° 2022-270 du 28 février 2022 (Lemoine) : résiliation à tout moment. Vérifié le "&TEXT(DAY(Paramètres!$C$43),"00")&"/"&TEXT(MONTH(Paramètres!$C$43),"00")&"/"&YEAR(Paramètres!$C$43)&"." -> Baromètres 2026 (pretclair.fr, covelia.fr) : 0,10 à 0,20 %, 35 ans non fumeur. Loi n° 2022-270 du 28 février 2022 (Lemoine) : résiliation à tout moment. Vérifié le 05/09/2026.
B48: Repère : frais de dossier, bas de fourchette | C48: ="Meilleurtaux, relevé de 119 banques au 01/03/2026 : moyenne 1 899,68 € pour 200 000 € empruntés, 92 établissements entre 0,50 % et 1,40 % du capital, de 0 € à 2 500 € selon les banques. Vérifié le "&TEXT(DAY(Paramètres!$C$43),"00")&"/"&TEXT(MONTH(Paramètres!$C$43),"00")&"/"&YEAR(Paramètres!$C$43)&"." -> Meilleurtaux, relevé de 119 banques au 01/03/2026 : moyenne 1 899,68 € pour 200 000 € empruntés, 92 établissements entre 0,50 % et 1,40 % du capital, de 0 € à 2 500 € selon les banques. Vérifié le 05/09/2026.
B49: Repère : frais de dossier, haut de fourchette | C49: ="Meilleurtaux, relevé de 119 banques au 01/03/2026 : moyenne 1 899,68 € pour 200 000 € empruntés, 92 établissements entre 0,50 % et 1,40 % du capital, de 0 € à 2 500 € selon les banques. Vérifié le "&TEXT(DAY(Paramètres!$C$43),"00")&"/"&TEXT(MONTH(Paramètres!$C$43),"00")&"/"&YEAR(Paramètres!$C$43)&"." -> Meilleurtaux, relevé de 119 banques au 01/03/2026 : moyenne 1 899,68 € pour 200 000 € empruntés, 92 établissements entre 0,50 % et 1,40 % du capital, de 0 € à 2 500 € selon les banques. Vérifié le 05/09/2026.
B50: Repère : frais de caution, en part du capital emprunté | C50: ="Convention prudente du classeur : Crédit Logement ne publie pas son barème et les relevés de place vont de 0,85 % + 200 € (optimhome.com, 2026) à 1,5 à 1,75 % du capital (perlib.fr, 2026). Vérifié le "&TEXT(DAY(Paramètres!$C$43),"00")&"/"&TEXT(MONTH(Paramètres!$C$43),"00")&"/"&YEAR(Paramètres!$C$43)&"." -> Convention prudente du classeur : Crédit Logement ne publie pas son barème et les relevés de place vont de 0,85 % + 200 € (optimhome.com, 2026) à 1,5 à 1,75 % du capital (perlib.fr, 2026). Vérifié le 05/09/2026.
B51: Repère : frais d'hypothèque, en part du capital | C51: ="PrêtClair, « Garantie de prêt immobilier 2026 : caution, hypothèque ou PPD », page du 6 mai 2026 : environ 2 900 € pour 200 000 € empruntés et 4 100 € pour 300 000 €, soit 1,4 à 1,5 % du capital (émol"&"uments du notaire, taxe de publicité foncière, contribution de sécurité immobilière, formalités). Vérifié le "&TEXT(DAY(Paramètres!$C$43),"00")&"/"&TEXT(MONTH(Paramètres!$C$43),"00")&"/"&YEAR(Paramètres!$C$43)&"." -> PrêtClair, « Garantie de prêt immobilier 2026 : caution, hypothèque ou PPD », page du 6 mai 2026 : environ 2 900 € pour 200 000 € empruntés et 4 100 € pour 300 000 €, soit 1,4 à 1,5 % du capital (émoluments du notaire, taxe de publicité foncière, contribution de sécurité immobilière, formalités). Vérifié le 05/09/2026.
B52: TAEG et TAEA | C52: ="Code de la consommation, art. L314-1 à L314-5 et R314-1 à R314-4, annexe à l'art. R314-3 (méthode d'équivalence), version en vigueur depuis le 20 décembre 2021 ; art. L313-8 (information sur le coût d"&"e l'assurance emprunteur, TAEA sur la fiche standardisée d'information). Vérifié le "&TEXT(DAY(Paramètres!$C$43),"00")&"/"&TEXT(MONTH(Paramètres!$C$43),"00")&"/"&YEAR(Paramètres!$C$43)&"." -> Code de la consommation, art. L314-1 à L314-5 et R314-1 à R314-4, annexe à l'art. R314-3 (méthode d'équivalence), version en vigueur depuis le 20 décembre 2021 ; art. L313-8 (information sur le coût de l'assurance emprunteur, TAEA sur la fiche standardisée d'information). Vérifié le 05/09/2026.
B53: Prêt à taux zéro | C53: ="CCH art. L31-10-1 et suivants ; loi de finances 2025 : PTZ étendu à tout le territoire et aux maisons depuis le 1er avril 2025, prolongé jusqu'au 31 décembre 2027. Guides PTZ 2026. Vérifié le "&TEXT(DAY(Paramètres!$C$43),"00")&"/"&TEXT(MONTH(Paramètres!$C$43),"00")&"/"&YEAR(Paramètres!$C$43)&"." -> CCH art. L31-10-1 et suivants ; loi de finances 2025 : PTZ étendu à tout le territoire et aux maisons depuis le 1er avril 2025, prolongé jusqu'au 31 décembre 2027. Guides PTZ 2026. Vérifié le 05/09/2026.
B54: Hypothèque légale spéciale du prêteur de deniers | C54: ="Ordonnance n° 2021-1192 du 15 septembre 2021, en vigueur le 1er janvier 2022 ; service-public.gouv.fr, fiche F786. Vérifié le "&TEXT(DAY(Paramètres!$C$43),"00")&"/"&TEXT(MONTH(Paramètres!$C$43),"00")&"/"&YEAR(Paramètres!$C$43)&"." -> Ordonnance n° 2021-1192 du 15 septembre 2021, en vigueur le 1er janvier 2022 ; service-public.gouv.fr, fiche F786. Vérifié le 05/09/2026.
B55: Assurance emprunteur | C55: ="Loi n° 2022-270 du 28 février 2022 (Lemoine) : résiliation à tout moment, suppression du questionnaire médical sous conditions. Fourchettes 2026 : Meilleurtaux, PrêtClair. Vérifié le "&TEXT(DAY(Paramètres!$C$43),"00")&"/"&TEXT(MONTH(Paramètres!$C$43),"00")&"/"&YEAR(Paramètres!$C$43)&"." -> Loi n° 2022-270 du 28 février 2022 (Lemoine) : résiliation à tout moment, suppression du questionnaire médical sous conditions. Fourchettes 2026 : Meilleurtaux, PrêtClair. Vérifié le 05/09/2026.
B57: CorpusImmo, millésime 2026. Modèle d'aide à la décision : ne constitue ni un conseil en investissement, ni un conseil fiscal, ni une expertise au sens de la charte de l'expertise en évaluation immobilière. Vérifiez les paramètres avant tout engagement.
